Workbook
Name AEA_Name: #REF!

Sheet Description of Tabs
B1: Click on the Tab name and you will go directly to the tab in the workbook
B3: AEA Payment Summary
B4: Breakdown of the Actual Payment from the State to Each AEA
B5: Includes the share of how much your nonpublic students generate for Media and Ed Services.
B6: SF 659 (section 6) (2025 Legislative Session) authorizes DOM to pay the nonpublic share directly to AEAs.
B8: DetailByDistrict
B9: Includes the Detail by school district for Enrollment data, Cost Per Pupil Amounts, and the Total amounts generated for the program areas
B11: DetailByAEA
B12: Has the same information as the “DetailByDistrict” just summed by AEA.
B14: Special Education Breakdown
B15: Includes the 90% and 10% split and amount district must pay to the AEAs
B16: You can change the AEA number in Column C – “AEA District Chose to Receive Services From” if you have an agreement with a district to provide services to that district. The totals on the tab “Special Education By AEA” will automatically update.
... B28: Has the Nonpublic allocation for Media and Ed services by Nonpublic School

Sheet AEA Payment Summary
C6: AEA | D6: AEA Name | E6: State Aid Portion Sharing Operations | F6: Sharing Operations Property Tax | G6: Total AEA Sharing Operations | H6: AEA Teacher Salary Supplement District Cost | I6: AEA Media Services Nonpublic Portion | J6: AEA Educational Services Nonpublic Portion | K6: Total AEA Payment | L6: AEA Payment State Aid Portion | M6: AEA Payment Property Tax Portion | R6: Check | S6: State Aid Check | T6: Property Tax Check
C7: 01 | D7: Keystone AEA 1 | E7: =SUMIF(Breakdown[AEA],$C7,Breakdown[State Aid Portion Sharing Operations]) -> 22789 | F7: =SUMIF(Breakdown[AEA],$C7,Breakdown[Sharing Operations Property Tax]) -> 7211 | G7: =SUMIF(Breakdown[AEA],$C7,Breakdown[Total AEA Sharing Operations]) -> 30000 | H7: =SUMIF(Breakdown[AEA],$C7,Breakdown[AEA Teacher Salary Supplement District Cost]) -> 1151859 | I7: =SUMIF(Breakdown[AEA],$C7,Breakdown[AEA Media Services Nonpublic Portion]) -> 262085 | J7: =SUMIF(Breakdown[AEA],$C7,Breakdown[AEA Educational Services Nonpublic Portion]) -> 291923 | K7: =SUMIF(Breakdown[AEA],$C7,Breakdown[Total AEA Payment]) -> 1735867 | L7: =SUMIF(Breakdown[AEA],$C7,Breakdown[AEA Payment State Aid Portion]) -> 1174648 | M7: =SUMIF(Breakdown[AEA],$C7,Breakdown[AEA Payment Property Tax Portion]) -> 561219 | R7: =K7-J7-I7-H7-G7 -> 0 | S7: =L7-H7-E7 -> 0 | T7: =M7-J7-I7-F7 -> 0
C8: 05 | D8: Prairie Lakes AEA 8 | E8: =SUMIF(Breakdown[AEA],$C8,Breakdown[State Aid Portion Sharing Operations]) -> 0 | F8: =SUMIF(Breakdown[AEA],$C8,Breakdown[Sharing Operations Property Tax]) -> 0 | G8: =SUMIF(Breakdown[AEA],$C8,Breakdown[Total AEA Sharing Operations]) -> 0 | H8: =SUMIF(Breakdown[AEA],$C8,Breakdown[AEA Teacher Salary Supplement District Cost]) -> 1276124 | I8: =SUMIF(Breakdown[AEA],$C8,Breakdown[AEA Media Services Nonpublic Portion]) -> 150479 | J8: =SUMIF(Breakdown[AEA],$C8,Breakdown[AEA Educational Services Nonpublic Portion]) -> 168486 | K8: =SUMIF(Breakdown[AEA],$C8,Breakdown[Total AEA Payment]) -> 1595089 | L8: =SUMIF(Breakdown[AEA],$C8,Breakdown[AEA Payment State Aid Portion]) -> 1276124 | M8: =SUMIF(Breakdown[AEA],$C8,Breakdown[AEA Payment Property Tax Portion]) -> 318965 | R8: =K8-J8-I8-H8-G8 -> 0 | S8: =L8-H8-E8 -> 0 | T8: =M8-J8-I8-F8 -> 0
C9: 07 | D9: Central Rivers | E9: =SUMIF(Breakdown[AEA],$C9,Breakdown[State Aid Portion Sharing Operations]) -> 23488 | F9: =SUMIF(Breakdown[AEA],$C9,Breakdown[Sharing Operations Property Tax]) -> 6512 | G9: =SUMIF(Breakdown[AEA],$C9,Breakdown[Total AEA Sharing Operations]) -> 30000 | H9: =SUMIF(Breakdown[AEA],$C9,Breakdown[AEA Teacher Salary Supplement District Cost]) -> 3032137 | I9: =SUMIF(Breakdown[AEA],$C9,Breakdown[AEA Media Services Nonpublic Portion]) -> 253193 | J9: =SUMIF(Breakdown[AEA],$C9,Breakdown[AEA Educational Services Nonpublic Portion]) -> 282243 | K9: =SUMIF(Breakdown[AEA],$C9,Breakdown[Total AEA Payment]) -> 3597573 | L9: =SUMIF(Breakdown[AEA],$C9,Breakdown[AEA Payment State Aid Portion]) -> 3055625 | M9: =SUMIF(Breakdown[AEA],$C9,Breakdown[AEA Payment Property Tax Portion]) -> 541948 | R9: =K9-J9-I9-H9-G9 -> 0 | S9: =L9-H9-E9 -> 0 | T9: =M9-J9-I9-F9 -> 0
C10: 09 | D10: Mississippi Bend AEA 9 | E10: =SUMIF(Breakdown[AEA],$C10,Breakdown[State Aid Portion Sharing Operations]) -> 23650 | F10: =SUMIF(Breakdown[AEA],$C10,Breakdown[Sharing Operations Property Tax]) -> 6350 | G10: =SUMIF(Breakdown[AEA],$C10,Breakdown[Total AEA Sharing Operations]) -> 30000 | H10: =SUMIF(Breakdown[AEA],$C10,Breakdown[AEA Teacher Salary Supplement District Cost]) -> 1634071 | I10: =SUMIF(Breakdown[AEA],$C10,Breakdown[AEA Media Services Nonpublic Portion]) -> 245851 | J10: =SUMIF(Breakdown[AEA],$C10,Breakdown[AEA Educational Services Nonpublic Portion]) -> 268841 | K10: =SUMIF(Breakdown[AEA],$C10,Breakdown[Total AEA Payment]) -> 2178763 | L10: =SUMIF(Breakdown[AEA],$C10,Breakdown[AEA Payment State Aid Portion]) -> 1657721 | M10: =SUMIF(Breakdown[AEA],$C10,Breakdown[AEA Payment Property Tax Portion]) -> 521042 | R10: =K10-J10-I10-H10-G10 -> 0 | S10: =L10-H10-E10 -> 0 | T10: =M10-J10-I10-F10 -> 0
C11: 10 | D11: Grant Wood AEA 10 | E11: =SUMIF(Breakdown[AEA],$C11,Breakdown[State Aid Portion Sharing Operations]) -> 23785 | F11: =SUMIF(Breakdown[AEA],$C11,Breakdown[Sharing Operations Property Tax]) -> 6216 | G11: =SUMIF(Breakdown[AEA],$C11,Breakdown[Total AEA Sharing Operations]) -> 30001 | H11: =SUMIF(Breakdown[AEA],$C11,Breakdown[AEA Teacher Salary Supplement District Cost]) -> 2570057 | I11: =SUMIF(Breakdown[AEA],$C11,Breakdown[AEA Media Services Nonpublic Portion]) -> 344008 | J11: =SUMIF(Breakdown[AEA],$C11,Breakdown[AEA Educational Services Nonpublic Portion]) -> 378309 | K11: =SUMIF(Breakdown[AEA],$C11,Breakdown[Total AEA Payment]) -> 3322375 | L11: =SUMIF(Breakdown[AEA],$C11,Breakdown[AEA Payment State Aid Portion]) -> 2593842 | M11: =SUMIF(Breakdown[AEA],$C11,Breakdown[AEA Payment Property Tax Portion]) -> 728533 | R11: =K11-J11-I11-H11-G11 -> 0 | S11: =L11-H11-E11 -> 0 | T11: =M11-J11-I11-F11 -> 0
C12: 11 | D12: Heartland AEA 11 | E12: =SUMIF(Breakdown[AEA],$C12,Breakdown[State Aid Portion Sharing Operations]) -> 0 | F12: =SUMIF(Breakdown[AEA],$C12,Breakdown[Sharing Operations Property Tax]) -> 0 | G12: =SUMIF(Breakdown[AEA],$C12,Breakdown[Total AEA Sharing Operations]) -> 0 | H12: =SUMIF(Breakdown[AEA],$C12,Breakdown[AEA Teacher Salary Supplement District Cost]) -> 4753653 | I12: =SUMIF(Breakdown[AEA],$C12,Breakdown[AEA Media Services Nonpublic Portion]) -> 752248 | J12: =SUMIF(Breakdown[AEA],$C12,Breakdown[AEA Educational Services Nonpublic Portion]) -> 826706 | K12: =SUMIF(Breakdown[AEA],$C12,Breakdown[Total AEA Payment]) -> 6332607 | L12: =SUMIF(Breakdown[AEA],$C12,Breakdown[AEA Payment State Aid Portion]) -> 4753653 | M12: =SUMIF(Breakdown[AEA],$C12,Breakdown[AEA Payment Property Tax Portion]) -> 1578954 | R12: =K12-J12-I12-H12-G12 -> 0 | S12: =L12-H12-E12 -> 0 | T12: =M12-J12-I12-F12 -> 0
C13: 12 | D13: Northwest AEA | E13: =SUMIF(Breakdown[AEA],$C13,Breakdown[State Aid Portion Sharing Operations]) -> 23274 | F13: =SUMIF(Breakdown[AEA],$C13,Breakdown[Sharing Operations Property Tax]) -> 6726 | G13: =SUMIF(Breakdown[AEA],$C13,Breakdown[Total AEA Sharing Operations]) -> 30000 | H13: =SUMIF(Breakdown[AEA],$C13,Breakdown[AEA Teacher Salary Supplement District Cost]) -> 1619590 | I13: =SUMIF(Breakdown[AEA],$C13,Breakdown[AEA Media Services Nonpublic Portion]) -> 377069 | J13: =SUMIF(Breakdown[AEA],$C13,Breakdown[AEA Educational Services Nonpublic Portion]) -> 422065 | K13: =SUMIF(Breakdown[AEA],$C13,Breakdown[Total AEA Payment]) -> 2448724 | L13: =SUMIF(Breakdown[AEA],$C13,Breakdown[AEA Payment State Aid Portion]) -> 1642864 | M13: =SUMIF(Breakdown[AEA],$C13,Breakdown[AEA Payment Property Tax Portion]) -> 805860 | R13: =K13-J13-I13-H13-G13 -> 0 | S13: =L13-H13-E13 -> 0 | T13: =M13-J13-I13-F13 -> 0
C14: 13 | D14: Green Hills AEA 13 | E14: =SUMIF(Breakdown[AEA],$C14,Breakdown[State Aid Portion Sharing Operations]) -> 23715 | F14: =SUMIF(Breakdown[AEA],$C14,Breakdown[Sharing Operations Property Tax]) -> 6285 | G14: =SUMIF(Breakdown[AEA],$C14,Breakdown[Total AEA Sharing Operations]) -> 30000 | H14: =SUMIF(Breakdown[AEA],$C14,Breakdown[AEA Teacher Salary Supplement District Cost]) -> 1519471 | I14: =SUMIF(Breakdown[AEA],$C14,Breakdown[AEA Media Services Nonpublic Portion]) -> 79679 | J14: =SUMIF(Breakdown[AEA],$C14,Breakdown[AEA Educational Services Nonpublic Portion]) -> 88100 | K14: =SUMIF(Breakdown[AEA],$C14,Breakdown[Total AEA Payment]) -> 1717250 | L14: =SUMIF(Breakdown[AEA],$C14,Breakdown[AEA Payment State Aid Portion]) -> 1543186 | M14: =SUMIF(Breakdown[AEA],$C14,Breakdown[AEA Payment Property Tax Portion]) -> 174064 | R14: =K14-J14-I14-H14-G14 -> 0 | S14: =L14-H14-E14 -> 0 | T14: =M14-J14-I14-F14 -> 0
C15: 15 | D15: Great Prairie AEA 15 | E15: =SUMIF(Breakdown[AEA],$C15,Breakdown[State Aid Portion Sharing Operations]) -> 23898 | F15: =SUMIF(Breakdown[AEA],$C15,Breakdown[Sharing Operations Property Tax]) -> 6104 | G15: =SUMIF(Breakdown[AEA],$C15,Breakdown[Total AEA Sharing Operations]) -> 30002 | H15: =SUMIF(Breakdown[AEA],$C15,Breakdown[AEA Teacher Salary Supplement District Cost]) -> 1327569 | I15: =SUMIF(Breakdown[AEA],$C15,Breakdown[AEA Media Services Nonpublic Portion]) -> 95494 | J15: =SUMIF(Breakdown[AEA],$C15,Breakdown[AEA Educational Services Nonpublic Portion]) -> 105003 | K15: =SUMIF(Breakdown[AEA],$C15,Breakdown[Total AEA Payment]) -> 1558068 | L15: =SUMIF(Breakdown[AEA],$C15,Breakdown[AEA Payment State Aid Portion]) -> 1351467 | M15: =SUMIF(Breakdown[AEA],$C15,Breakdown[AEA Payment Property Tax Portion]) -> 206601 | R15: =K15-J15-I15-H15-G15 -> 0 | S15: =L15-H15-E15 -> 0 | T15: =M15-J15-I15-F15 -> 0
E16: =SUM(E7:E15) -> 164599 | F16: =SUM(F7:F15) -> 45404 | G16: =SUM(G7:G15) -> 210003 | H16: =SUM(H7:H15) -> 18884531 | I16: =SUM(I7:I15) -> 2560106 | J16: =SUM(J7:J15) -> 2831676 | K16: =SUM(K7:K15) -> 24486316 | L16: =SUM(L7:L15) -> 19049130 | M16: =SUM(M7:M15) -> 5437186 | R16: =K16-J16-I16-H16-G16 -> 0 | S16: =L16-H16-E16 -> 0 | T16: =M16-J16-I16-F16 -> 0

Sheet DetailByDistrict
A1: AEA | B1: AEA Name | C1: Dist | D1: District | E1: Total Special Ed Weighting in Addition to 1.0 | F1: Budget Enrollment | G1: AEA Weighted Enrollment | H1: AEA Supplementary Weight for Sharing | I1: Resident Accredited Nonpublic Students | J1: Shared-Time Nonpublic Pupils Counted in Line 1.1 | K1: Total Enrollment Served - Media and Ed Services | L1: AEA Special Ed Support Cost Per Pupil | M1: AEA Media Cost Per Pupil | N1: AEA Ed Services Cost Per Pupil | O1: AEA Teacher Salary Supplement District Cost Per Pupil | P1: AEA Special Ed Support District Cost without Adjustment | Q1: AEA Special Ed Support Adjustment | R1: Special Education Total Cost | S1: District/AEA Statewide State Aid Reduction | T1: AEA Media Services Nonpublic Portion | U1: District Media Services | V1: Total Media Services | W1: AEA Educational Services Nonpublic Portion | X1: District Educational Services | Y1: Total Educational Services | Z1: AEA Sharing District Cost | AA1: AEA Teacher Salary Supplement District Cost
A2: 01 | B2: Keystone AEA 1 | C2: 0135 | D2: Allamakee | E2: 170.28 | F2: 1104.7 | G2: 1274.98 | H2: 3.3 | I2: 155 | J2: 1.8 | K2: 1258 | L2: 363.32 | M2: 65.26 | N2: 72.69 | O2: 36.03 | P2: 463226 | Q2: 0 | R2: 463226 | S2: 75370 | T2: 10115 | U2: 71982 | V2: 82097 | W2: 11267 | X2: 80177 | Y2: 91444 | Z2: 1199 | AA2: 45938
A3: 01 | B3: Keystone AEA 1 | C3: 1080 | D3: Central Clayton | E3: 66.67 | F3: 456.1 | G3: 522.77 | H3: 1.35 | I3: 0 | J3: 0 | K3: 456 | L3: 363.32 | M3: 65.26 | N3: 72.69 | O3: 36.03 | P3: 189933 | Q3: 1572 | R3: 191505 | S3: 30904 | T3: 0 | U3: 29759 | V3: 29759 | W3: 0 | X3: 33147 | Y3: 33147 | Z3: 490 | AA3: 18980
A4: 01 | B4: Keystone AEA 1 | C4: 2763 | D4: Clayton Ridge | E4: 79.93 | F4: 638 | G4: 717.93 | H4: 1.86 | I4: 11 | J4: 0 | K4: 649 | L4: 363.32 | M4: 65.26 | N4: 72.69 | O4: 36.03 | P4: 260838 | Q4: 0 | R4: 260838 | S4: 42440 | T4: 718 | U4: 41636 | V4: 42354 | W4: 800 | X4: 46376 | Y4: 47176 | Z4: 676 | AA4: 25867
A5: 01 | B5: Keystone AEA 1 | C5: 1638 | D5: Decorah | E5: 184.18 | F5: 1450.4 | G5: 1634.58 | H5: 4.24 | I5: 170 | J5: 0.8 | K5: 1620 | L5: 363.32 | M5: 65.26 | N5: 72.69 | O5: 36.03 | P5: 593876 | Q5: 10511 | R5: 604387 | S5: 96628 | T5: 11094 | U5: 94627 | V5: 105721 | W5: 12357 | X5: 105401 | Y5: 117758 | Z5: 1540 | AA5: 59900
A6: 01 | B6: Keystone AEA 1 | C6: 1863 | D6: Dubuque | E6: 1892.58 | F6: 9862.9 | G6: 11755.48 | H6: 30.46 | I6: 1933 | J6: 12.5 | K6: 11783 | L6: 363.32 | M6: 65.26 | N6: 72.69 | O6: 36.03 | P6: 4271001 | Q6: 0 | R6: 4271001 | S6: 694923 | T6: 126148 | U6: 642811 | V6: 768959 | W6: 140510 | X6: 715996 | Y6: 856506 | Z6: 11067 | AA6: 423550
A7: 01 | B7: Keystone AEA 1 | C7: 1972 | D7: Eastern Allamakee | E7: 41.27 | F7: 307 | G7: 348.27 | H7: 0.9 | I7: 10 | J7: 0 | K7: 317 | L7: 363.32 | M7: 65.26 | N7: 72.69 | O7: 36.03 | P7: 126533 | Q7: 4789 | R7: 131322 | S7: 20588 | T7: 653 | U7: 20034 | V7: 20687 | W7: 727 | X7: 22316 | Y7: 23043 | Z7: 327 | AA7: 12548
A8: 01 | B8: Keystone AEA 1 | C8: 1989 | D8: Edgewood-Colesburg | E8: 35.81 | F8: 378 | G8: 413.81 | H8: 1.07 | I8: 21 | J8: 0 | K8: 399 | L8: 363.32 | M8: 65.26 | N8: 72.69 | O8: 36.03 | P8: 150345 | Q8: 0 | R8: 150345 | S8: 24462 | T8: 1370 | U8: 24669 | V8: 26039 | W8: 1526 | X8: 27477 | Y8: 29003 | Z8: 389 | AA8: 14910
A9: 01 | B9: Keystone AEA 1 | C9: 3029 | D9: Howard-Winneshiek | E9: 161.42 | F9: 1147 | G9: 1308.42 | H9: 3.39 | I9: 120 | J9: 1.1 | K9: 1266 | L9: 363.32 | M9: 65.26 | N9: 72.69 | O9: 36.03 | P9: 475375 | Q9: 0 | R9: 475375 | S9: 77347 | T9: 7831 | U9: 74788 | V9: 82619 | W9: 8723 | X9: 83303 | Y9: 92026 | Z9: 1232 | AA9: 47142
A10: 01 | B10: Keystone AEA 1 | C10: 4419 | D10: MFL Mar Mac | E10: 100.57 | F10: 794.9 | G10: 895.47 | H10: 2.32 | I10: 6 | J10: 0 | K10: 801 | L10: 363.32 | M10: 65.26 | N10: 72.69 | O10: 36.03 | P10: 325342 | Q10: 570 | R10: 325912 | S10: 52936 | T10: 392 | U10: 51881 | V10: 52273 | W10: 436 | X10: 57789 | Y10: 58225 | Z10: 843 | AA10: 32300
A11: 01 | B11: Keystone AEA 1 | C11: 4043 | D11: Maquoketa Valley | E11: 77.63 | F11: 671.9 | G11: 749.53 | H11: 1.94 | I11: 40 | J11: 0 | K11: 712 | L11: 363.32 | M11: 65.26 | N11: 72.69 | O11: 36.03 | P11: 272319 | Q11: 0 | R11: 272319 | S11: 44308 | T11: 2610 | U11: 43855 | V11: 46465 | W11: 2908 | X11: 48847 | Y11: 51755 | Z11: 705 | AA11: 27006
A12: 01 | B12: Keystone AEA 1 | C12: 4662 | D12: New Hampton | E12: 101.49 | F12: 992.8 | G12: 1094.29 | H12: 2.83 | I12: 71 | J12: 0.6 | K12: 1063 | L12: 363.32 | M12: 65.26 | N12: 72.69 | O12: 36.03 | P12: 397577 | Q12: 0 | R12: 397577 | S12: 64689 | T12: 4633 | U12: 64738 | V12: 69371 | W12: 5161 | X12: 72108 | Y12: 77269 | Z12: 1028 | AA12: 39427
A13: 01 | B13: Keystone AEA 1 | C13: 4774 | D13: North Fayette Valley | E13: 213.57 | F13: 1108.4 | G13: 1321.97 | H13: 3.43 | I13: 2 | J13: 0 | K13: 1110 | L13: 363.32 | M13: 65.26 | N13: 72.69 | O13: 36.03 | P13: 480298 | Q13: 0 | R13: 480298 | S13: 78148 | T13: 131 | U13: 72308 | V13: 72439 | W13: 145 | X13: 80541 | Y13: 80686 | Z13: 1246 | AA13: 47631
... A132: 09 | B132: Mississippi Bend AEA 9 | C132: 7038 | D132: Wilton | E132: 81.58 | F132: 815.4 | G132: 896.98 | H132: 1.52 | I132: 0 | J132: 0 | K132: 815 | L132: 350.08 | M132: 64.8 | N132: 70.86 | O132: 32.33 | P132: 314015 | Q132: 8267 | R132: 322282 | S132: 53024 | T132: 0 | U132: 52812 | V132: 52812 | W132: 0 | X132: 57751 | Y132: 57751 | Z132: 532 | AA132: 29699
A133: 10 | B133: Grant Wood AEA 10 | C133: 0099 | D133: Alburnett | E133: 44.3 | F133: 541.5 | G133: 585.8 | H133: 0.65 | I133: 21 | J133: 0 | K133: 563 | L133: 348.16 | M133: 64.98 | N133: 71.46 | O133: 33.08 | P133: 203952 | Q133: 0 | R133: 203952 | S133: 34629 | T133: 1365 | U133: 35219 | V133: 36584 | W133: 1501 | X133: 38731 | Y133: 40232 | Z133: 226 | AA133: 19378
A134: 10 | B134: Grant Wood AEA 10 | C134: 0234 | D134: Anamosa | E134: 114.19 | F134: 1202.2 | G134: 1316.39 | H134: 1.46 | I134: 68 | J134: 0 | K134: 1270 | L134: 348.16 | M134: 64.98 | N134: 71.46 | O134: 33.08 | P134: 458314 | Q134: 15810 | R134: 474124 | S134: 77818 | T134: 4419 | U134: 78106 | V134: 82525 | W134: 4859 | X134: 85895 | Y134: 90754 | Z134: 508 | AA134: 44979
A135: 10 | B135: Grant Wood AEA 10 | C135: 0576 | D135: Belle Plaine | E135: 58.41 | F135: 466.6 | G135: 525.01 | H135: 0.58 | I135: 7 | J135: 0 | K135: 474 | L135: 348.16 | M135: 64.98 | N135: 71.46 | O135: 33.08 | P135: 182787 | Q135: 0 | R135: 182787 | S135: 31036 | T135: 455 | U135: 30346 | V135: 30801 | W135: 500 | X135: 33372 | Y135: 33872 | Z135: 202 | AA135: 17367
A136: 10 | B136: Grant Wood AEA 10 | C136: 0609 | D136: Benton | E136: 138.17 | F136: 1475.6 | G136: 1613.77 | H136: 1.8 | I136: 140 | J136: 0.3 | K136: 1615 | L136: 348.16 | M136: 64.98 | N136: 71.46 | O136: 33.08 | P136: 561850 | Q136: 443 | R136: 562293 | S136: 95398 | T136: 9097 | U136: 95846 | V136: 104943 | W136: 10004 | X136: 105404 | Y136: 115408 | Z136: 627 | AA136: 53384
A137: 10 | B137: Grant Wood AEA 10 | C137: 1053 | D137: Cedar Rapids | E137: 2496.41 | F137: 16120.7 | G137: 18617.11 | H137: 20.69 | I137: 2073 | J137: 9.2 | K137: 18185 | L137: 348.16 | M137: 64.98 | N137: 71.46 | O137: 33.08 | P137: 6481733 | Q137: 0 | R137: 6481733 | S137: 1100546 | T137: 134704 | U137: 1046957 | V137: 1181661 | W137: 148137 | X137: 1151363 | Y137: 1299500 | Z137: 7203 | AA137: 615854
A138: 10 | B138: Grant Wood AEA 10 | C138: 1062 | D138: Center Point-Urbana | E138: 90.75 | F138: 1131.2 | G138: 1221.95 | H138: 1.36 | I138: 9 | J138: 0 | K138: 1140 | L138: 348.16 | M138: 64.98 | N138: 71.46 | O138: 33.08 | P138: 425434 | Q138: 36359 | R138: 461793 | S138: 72236 | T138: 585 | U138: 73492 | V138: 74077 | W138: 643 | X138: 80821 | Y138: 81464 | Z138: 473 | AA138: 41321
A139: 10 | B139: Grant Wood AEA 10 | C139: 1089 | D139: Central City | E139: 38.55 | F139: 411.3 | G139: 449.85 | H139: 0.5 | I139: 11 | J139: 0 | K139: 422 | L139: 348.16 | M139: 64.98 | N139: 71.46 | O139: 33.08 | P139: 156620 | Q139: 8288 | R139: 164908 | S139: 26593 | T139: 715 | U139: 26707 | V139: 27422 | W139: 786 | X139: 29370 | Y139: 30156 | Z139: 174 | AA139: 14881
A140: 10 | B140: Grant Wood AEA 10 | C140: 1221 | D140: Clear Creek-Amana | E140: 400.49 | F140: 3122.5 | G140: 3522.99 | H140: 3.91 | I140: 71 | J140: 0 | K140: 3194 | L140: 348.16 | M140: 64.98 | N140: 71.46 | O140: 33.08 | P140: 1226564 | Q140: 0 | R140: 1226564 | S140: 208261 | T140: 4614 | U140: 202932 | V140: 207546 | W140: 5074 | X140: 223169 | Y140: 228243 | Z140: 1361 | AA140: 116541
A141: 10 | B141: Grant Wood AEA 10 | C141: 1337 | D141: College Community | E141: 582.63 | F141: 5113.8 | G141: 5696.43 | H141: 6.33 | I141: 168 | J141: 0 | K141: 5282 | L141: 348.16 | M141: 64.98 | N141: 71.46 | O141: 33.08 | P141: 1983269 | Q141: 0 | R141: 1983269 | S141: 336743 | T141: 10917 | U141: 332307 | V141: 343224 | W141: 12005 | X141: 365447 | Y141: 377452 | Z141: 2204 | AA141: 188438
A142: 10 | B142: Grant Wood AEA 10 | C142: 2097 | D142: English Valleys | E142: 49.59 | F142: 443.4 | G142: 492.99 | H142: 0.55 | I142: 7 | J142: 0 | K142: 450 | L142: 348.16 | M142: 64.98 | N142: 71.46 | O142: 33.08 | P142: 171639 | Q142: 3547 | R142: 175186 | S142: 29143 | T142: 455 | U142: 28786 | V142: 29241 | W142: 500 | X142: 31657 | Y142: 32157 | Z142: 191 | AA142: 16308
A143: 10 | B143: Grant Wood AEA 10 | C143: 2766 | D143: HLV | E143: 29.8 | F143: 308 | G143: 337.8 | H143: 0.38 | I143: 5 | J143: 0 | K143: 313 | L143: 348.16 | M143: 64.98 | N143: 71.46 | O143: 33.08 | P143: 117608 | Q143: 3088 | R143: 120696 | S143: 19969 | T143: 325 | U143: 20014 | V143: 20339 | W143: 357 | X143: 22010 | Y143: 22367 | Z143: 132 | AA143: 11359
A144: 10 | B144: Grant Wood AEA 10 | C144: 2977 | D144: Highland | E144: 67.56 | F144: 553.8 | G144: 621.36 | H144: 0.69 | I144: 19 | J144: 0 | K144: 573 | L144: 348.16 | M144: 64.98 | N144: 71.46 | O144: 33.08 | P144: 216333 | Q144: 6569 | R144: 222902 | S144: 36732 | T144: 1235 | U144: 35999 | V144: 37234 | W144: 1358 | X144: 39589 | Y144: 40947 | Z144: 240 | AA144: 21146
... A326: 15 | B326: Great Prairie AEA 15 | C326: 7047 | D326: Winfield-Mt Union | E326: 40.36 | F326: 302.6 | G326: 342.96 | H326: 0.78 | I326: 0 | J326: 0 | K326: 303 | L326: 346.48 | M326: 64.96 | N326: 71.43 | O326: 34.86 | P326: 118829 | Q326: 2392 | R326: 121221 | S326: 20274 | T326: 0 | U326: 19683 | V326: 19683 | W326: 0 | X326: 21643 | Y326: 21643 | Z326: 270 | AA326: 12192

Sheet DetailByAEA
B4: AEA | C4: AEA Name | D4: Total Special Ed Weighting in Addition to 1.0 | E4: Budget Enrollment | F4: AEA Weighted Enrollment | G4: AEA Supplementary Weight for Sharing | H4: Resident Accredited Nonpublic Students | I4: Shared-Time Nonpublic Pupils Counted in Line 1.1 | J4: Total Enrollment Served - Media and Ed Services
B5: 01 | C5: Keystone AEA 1 | D5: =SUMIF(DetailByDistrict[AEA],DetailByAEA!$B5,DetailByDistrict[Total Special Ed Weighting in Addition to 1.0]) -> 4372.45 | E5: =SUMIF(DetailByDistrict[AEA],DetailByAEA!$B5,DetailByDistrict[Budget Enrollment]) -> 27489.7 | F5: =SUMIF(DetailByDistrict[AEA],DetailByAEA!$B5,DetailByDistrict[AEA Weighted Enrollment]) -> 31862.15 | G5: =SUMIF(DetailByDistrict[AEA],DetailByAEA!$B5,DetailByDistrict[AEA Supplementary Weight for Sharing]) -> 82.57 | H5: =SUMIF(DetailByDistrict[AEA],DetailByAEA!$B5,DetailByDistrict[Resident Accredited Nonpublic Students]) -> 4016 | I5: =SUMIF(DetailByDistrict[AEA],DetailByAEA!$B5,DetailByDistrict[Shared-Time Nonpublic Pupils Counted in Line 1.1]) -> 22.5 | J5: =SUMIF(DetailByDistrict[AEA],DetailByAEA!$B5,DetailByDistrict[Total Enrollment Served - Media and Ed Services]) -> 31484
B6: 05 | C6: Prairie Lakes AEA 8 | D6: =SUMIF(DetailByDistrict[AEA],DetailByAEA!$B6,DetailByDistrict[Total Special Ed Weighting in Addition to 1.0]) -> 3767.36 | E6: =SUMIF(DetailByDistrict[AEA],DetailByAEA!$B6,DetailByDistrict[Budget Enrollment]) -> 29544.2 | F6: =SUMIF(DetailByDistrict[AEA],DetailByAEA!$B6,DetailByDistrict[AEA Weighted Enrollment]) -> 33311.56 | G6: =SUMIF(DetailByDistrict[AEA],DetailByAEA!$B6,DetailByDistrict[AEA Supplementary Weight for Sharing]) -> 0 | H6: =SUMIF(DetailByDistrict[AEA],DetailByAEA!$B6,DetailByDistrict[Resident Accredited Nonpublic Students]) -> 2303 | I6: =SUMIF(DetailByDistrict[AEA],DetailByAEA!$B6,DetailByDistrict[Shared-Time Nonpublic Pupils Counted in Line 1.1]) -> 31.2 | J6: =SUMIF(DetailByDistrict[AEA],DetailByAEA!$B6,DetailByDistrict[Total Enrollment Served - Media and Ed Services]) -> 31817
B7: 07 | C7: Central Rivers | D7: =SUMIF(DetailByDistrict[AEA],DetailByAEA!$B7,DetailByDistrict[Total Special Ed Weighting in Addition to 1.0]) -> 9429.69 | E7: =SUMIF(DetailByDistrict[AEA],DetailByAEA!$B7,DetailByDistrict[Budget Enrollment]) -> 60257.5 | F7: =SUMIF(DetailByDistrict[AEA],DetailByAEA!$B7,DetailByDistrict[AEA Weighted Enrollment]) -> 69687.19 | G7: =SUMIF(DetailByDistrict[AEA],DetailByAEA!$B7,DetailByDistrict[AEA Supplementary Weight for Sharing]) -> 85.12 | H7: =SUMIF(DetailByDistrict[AEA],DetailByAEA!$B7,DetailByDistrict[Resident Accredited Nonpublic Students]) -> 3878 | I7: =SUMIF(DetailByDistrict[AEA],DetailByAEA!$B7,DetailByDistrict[Shared-Time Nonpublic Pupils Counted in Line 1.1]) -> 48.5 | J7: =SUMIF(DetailByDistrict[AEA],DetailByAEA!$B7,DetailByDistrict[Total Enrollment Served - Media and Ed Services]) -> 64088
B8: 09 | C8: Mississippi Bend AEA 9 | D8: =SUMIF(DetailByDistrict[AEA],DetailByAEA!$B8,DetailByDistrict[Total Special Ed Weighting in Addition to 1.0]) -> 6726.71 | E8: =SUMIF(DetailByDistrict[AEA],DetailByAEA!$B8,DetailByDistrict[Budget Enrollment]) -> 43736.3 | F8: =SUMIF(DetailByDistrict[AEA],DetailByAEA!$B8,DetailByDistrict[AEA Weighted Enrollment]) -> 50463.01 | G8: =SUMIF(DetailByDistrict[AEA],DetailByAEA!$B8,DetailByDistrict[AEA Supplementary Weight for Sharing]) -> 85.69 | H8: =SUMIF(DetailByDistrict[AEA],DetailByAEA!$B8,DetailByDistrict[Resident Accredited Nonpublic Students]) -> 3794 | I8: =SUMIF(DetailByDistrict[AEA],DetailByAEA!$B8,DetailByDistrict[Shared-Time Nonpublic Pupils Counted in Line 1.1]) -> 7.1 | J8: =SUMIF(DetailByDistrict[AEA],DetailByAEA!$B8,DetailByDistrict[Total Enrollment Served - Media and Ed Services]) -> 47523
B9: 10 | C9: Grant Wood AEA 10 | D9: =SUMIF(DetailByDistrict[AEA],DetailByAEA!$B9,DetailByDistrict[Total Special Ed Weighting in Addition to 1.0]) -> 8534.33 | E9: =SUMIF(DetailByDistrict[AEA],DetailByAEA!$B9,DetailByDistrict[Budget Enrollment]) -> 68981 | F9: =SUMIF(DetailByDistrict[AEA],DetailByAEA!$B9,DetailByDistrict[AEA Weighted Enrollment]) -> 77515.33 | G9: =SUMIF(DetailByDistrict[AEA],DetailByAEA!$B9,DetailByDistrict[AEA Supplementary Weight for Sharing]) -> 86.18 | H9: =SUMIF(DetailByDistrict[AEA],DetailByAEA!$B9,DetailByDistrict[Resident Accredited Nonpublic Students]) -> 5294 | I9: =SUMIF(DetailByDistrict[AEA],DetailByAEA!$B9,DetailByDistrict[Shared-Time Nonpublic Pupils Counted in Line 1.1]) -> 25 | J9: =SUMIF(DetailByDistrict[AEA],DetailByAEA!$B9,DetailByDistrict[Total Enrollment Served - Media and Ed Services]) -> 74252
B10: 11 | C10: Heartland AEA 11 | D10: =SUMIF(DetailByDistrict[AEA],DetailByAEA!$B10,DetailByDistrict[Total Special Ed Weighting in Addition to 1.0]) -> 19560.83 | E10: =SUMIF(DetailByDistrict[AEA],DetailByAEA!$B10,DetailByDistrict[Budget Enrollment]) -> 142402.9 | F10: =SUMIF(DetailByDistrict[AEA],DetailByAEA!$B10,DetailByDistrict[AEA Weighted Enrollment]) -> 161963.73 | G10: =SUMIF(DetailByDistrict[AEA],DetailByAEA!$B10,DetailByDistrict[AEA Supplementary Weight for Sharing]) -> 0 | H10: =SUMIF(DetailByDistrict[AEA],DetailByAEA!$B10,DetailByDistrict[Resident Accredited Nonpublic Students]) -> 11598 | I10: =SUMIF(DetailByDistrict[AEA],DetailByAEA!$B10,DetailByDistrict[Shared-Time Nonpublic Pupils Counted in Line 1.1]) -> 100.2 | J10: =SUMIF(DetailByDistrict[AEA],DetailByAEA!$B10,DetailByDistrict[Total Enrollment Served - Media and Ed Services]) -> 153903
B11: 12 | C11: Northwest AEA | D11: =SUMIF(DetailByDistrict[AEA],DetailByAEA!$B11,DetailByDistrict[Total Special Ed Weighting in Addition to 1.0]) -> 5909.5 | E11: =SUMIF(DetailByDistrict[AEA],DetailByAEA!$B11,DetailByDistrict[Budget Enrollment]) -> 39080.5 | F11: =SUMIF(DetailByDistrict[AEA],DetailByAEA!$B11,DetailByDistrict[AEA Weighted Enrollment]) -> 44990 | G11: =SUMIF(DetailByDistrict[AEA],DetailByAEA!$B11,DetailByDistrict[AEA Supplementary Weight for Sharing]) -> 84.33 | H11: =SUMIF(DetailByDistrict[AEA],DetailByAEA!$B11,DetailByDistrict[Resident Accredited Nonpublic Students]) -> 5777 | I11: =SUMIF(DetailByDistrict[AEA],DetailByAEA!$B11,DetailByDistrict[Shared-Time Nonpublic Pupils Counted in Line 1.1]) -> 45.8 | J11: =SUMIF(DetailByDistrict[AEA],DetailByAEA!$B11,DetailByDistrict[Total Enrollment Served - Media and Ed Services]) -> 44808
B12: 13 | C12: Green Hills AEA 13 | D12: =SUMIF(DetailByDistrict[AEA],DetailByAEA!$B12,DetailByDistrict[Total Special Ed Weighting in Addition to 1.0]) -> 6007.66 | E12: =SUMIF(DetailByDistrict[AEA],DetailByAEA!$B12,DetailByDistrict[Budget Enrollment]) -> 36065.8 | F12: =SUMIF(DetailByDistrict[AEA],DetailByAEA!$B12,DetailByDistrict[AEA Weighted Enrollment]) -> 42073.46 | G12: =SUMIF(DetailByDistrict[AEA],DetailByAEA!$B12,DetailByDistrict[AEA Supplementary Weight for Sharing]) -> 85.93 | H12: =SUMIF(DetailByDistrict[AEA],DetailByAEA!$B12,DetailByDistrict[Resident Accredited Nonpublic Students]) -> 1226 | I12: =SUMIF(DetailByDistrict[AEA],DetailByAEA!$B12,DetailByDistrict[Shared-Time Nonpublic Pupils Counted in Line 1.1]) -> 4 | J12: =SUMIF(DetailByDistrict[AEA],DetailByAEA!$B12,DetailByDistrict[Total Enrollment Served - Media and Ed Services]) -> 37286
B13: 15 | C13: Great Prairie AEA 15 | D13: =SUMIF(DetailByDistrict[AEA],DetailByAEA!$B13,DetailByDistrict[Total Special Ed Weighting in Addition to 1.0]) -> 4803.81 | E13: =SUMIF(DetailByDistrict[AEA],DetailByAEA!$B13,DetailByDistrict[Budget Enrollment]) -> 33107.5 | F13: =SUMIF(DetailByDistrict[AEA],DetailByAEA!$B13,DetailByDistrict[AEA Weighted Enrollment]) -> 37911.31 | G13: =SUMIF(DetailByDistrict[AEA],DetailByAEA!$B13,DetailByDistrict[AEA Supplementary Weight for Sharing]) -> 86.59 | H13: =SUMIF(DetailByDistrict[AEA],DetailByAEA!$B13,DetailByDistrict[Resident Accredited Nonpublic Students]) -> 1470 | I13: =SUMIF(DetailByDistrict[AEA],DetailByAEA!$B13,DetailByDistrict[Shared-Time Nonpublic Pupils Counted in Line 1.1]) -> 9.2 | J13: =SUMIF(DetailByDistrict[AEA],DetailByAEA!$B13,DetailByDistrict[Total Enrollment Served - Media and Ed Services]) -> 34570
D14: =SUM(D5:D13) -> 69112.34 | E14: =SUM(E5:E13) -> 480665.4 | F14: =SUM(F5:F13) -> 549777.74 | G14: =SUM(G5:G13) -> 596.41 | H14: =SUM(H5:H13) -> 39356 | I14: =SUM(I5:I13) -> 293.5 | J14: =SUM(J5:J13) -> 519731
B16: AEA | C16: AEA Name | D16: AEA Special Ed Support Cost Per Pupil | E16: AEA Media Cost Per Pupil | F16: AEA Ed Services Cost Per Pupil | G16: AEA Teacher Salary Supplement District Cost Per Pupil
B17: 01 | C17: Keystone AEA 1 | D17: =_xlfn.MINIFS(DetailByDistrict[AEA Special Ed Support Cost Per Pupil],DetailByDistrict[AEA],$B17) -> 363.32 | E17: =_xlfn.MINIFS(DetailByDistrict[AEA Media Cost Per Pupil],DetailByDistrict[AEA],$B17) -> 65.26 | F17: =_xlfn.MINIFS(DetailByDistrict[AEA Ed Services Cost Per Pupil],DetailByDistrict[AEA],$B17) -> 72.69 | G17: =_xlfn.MINIFS(DetailByDistrict[AEA Teacher Salary Supplement District Cost Per Pupil],DetailByDistrict[AEA],$B17) -> 36.03
B18: 05 | C18: Prairie Lakes AEA 8 | D18: =_xlfn.MINIFS(DetailByDistrict[AEA Special Ed Support Cost Per Pupil],DetailByDistrict[AEA],$B18) -> 359.07 | E18: =_xlfn.MINIFS(DetailByDistrict[AEA Media Cost Per Pupil],DetailByDistrict[AEA],$B18) -> 65.34 | F18: =_xlfn.MINIFS(DetailByDistrict[AEA Ed Services Cost Per Pupil],DetailByDistrict[AEA],$B18) -> 73.16 | G18: =_xlfn.MINIFS(DetailByDistrict[AEA Teacher Salary Supplement District Cost Per Pupil],DetailByDistrict[AEA],$B18) -> 37.99
B19: 07 | C19: Central Rivers | D19: =_xlfn.MINIFS(DetailByDistrict[AEA Special Ed Support Cost Per Pupil],DetailByDistrict[AEA],$B19) -> 352.44 | E19: =_xlfn.MINIFS(DetailByDistrict[AEA Media Cost Per Pupil],DetailByDistrict[AEA],$B19) -> 65.29 | F19: =_xlfn.MINIFS(DetailByDistrict[AEA Ed Services Cost Per Pupil],DetailByDistrict[AEA],$B19) -> 72.78 | G19: =_xlfn.MINIFS(DetailByDistrict[AEA Teacher Salary Supplement District Cost Per Pupil],DetailByDistrict[AEA],$B19) -> 43.26
B20: 09 | C20: Mississippi Bend AEA 9 | D20: =_xlfn.MINIFS(DetailByDistrict[AEA Special Ed Support Cost Per Pupil],DetailByDistrict[AEA],$B20) -> 350.08 | E20: =_xlfn.MINIFS(DetailByDistrict[AEA Media Cost Per Pupil],DetailByDistrict[AEA],$B20) -> 64.8 | F20: =_xlfn.MINIFS(DetailByDistrict[AEA Ed Services Cost Per Pupil],DetailByDistrict[AEA],$B20) -> 70.86 | G20: =_xlfn.MINIFS(DetailByDistrict[AEA Teacher Salary Supplement District Cost Per Pupil],DetailByDistrict[AEA],$B20) -> 32.33
B21: 10 | C21: Grant Wood AEA 10 | D21: =_xlfn.MINIFS(DetailByDistrict[AEA Special Ed Support Cost Per Pupil],DetailByDistrict[AEA],$B21) -> 348.16 | E21: =_xlfn.MINIFS(DetailByDistrict[AEA Media Cost Per Pupil],DetailByDistrict[AEA],$B21) -> 64.98 | F21: =_xlfn.MINIFS(DetailByDistrict[AEA Ed Services Cost Per Pupil],DetailByDistrict[AEA],$B21) -> 71.46 | G21: =_xlfn.MINIFS(DetailByDistrict[AEA Teacher Salary Supplement District Cost Per Pupil],DetailByDistrict[AEA],$B21) -> 33.08
B22: 11 | C22: Heartland AEA 11 | D22: =_xlfn.MINIFS(DetailByDistrict[AEA Special Ed Support Cost Per Pupil],DetailByDistrict[AEA],$B22) -> 341.06 | E22: =_xlfn.MINIFS(DetailByDistrict[AEA Media Cost Per Pupil],DetailByDistrict[AEA],$B22) -> 64.86 | F22: =_xlfn.MINIFS(DetailByDistrict[AEA Ed Services Cost Per Pupil],DetailByDistrict[AEA],$B22) -> 71.28 | G22: =_xlfn.MINIFS(DetailByDistrict[AEA Teacher Salary Supplement District Cost Per Pupil],DetailByDistrict[AEA],$B22) -> 29.31
B23: 12 | C23: Northwest AEA | D23: =_xlfn.MINIFS(DetailByDistrict[AEA Special Ed Support Cost Per Pupil],DetailByDistrict[AEA],$B23) -> 355.7 | E23: =_xlfn.MINIFS(DetailByDistrict[AEA Media Cost Per Pupil],DetailByDistrict[AEA],$B23) -> 65.27 | F23: =_xlfn.MINIFS(DetailByDistrict[AEA Ed Services Cost Per Pupil],DetailByDistrict[AEA],$B23) -> 73.06 | G23: =_xlfn.MINIFS(DetailByDistrict[AEA Teacher Salary Supplement District Cost Per Pupil],DetailByDistrict[AEA],$B23) -> 35.87
B24: 13 | C24: Green Hills AEA 13 | D24: =_xlfn.MINIFS(DetailByDistrict[AEA Special Ed Support Cost Per Pupil],DetailByDistrict[AEA],$B24) -> 349.12 | E24: =_xlfn.MINIFS(DetailByDistrict[AEA Media Cost Per Pupil],DetailByDistrict[AEA],$B24) -> 64.99 | F24: =_xlfn.MINIFS(DetailByDistrict[AEA Ed Services Cost Per Pupil],DetailByDistrict[AEA],$B24) -> 71.86 | G24: =_xlfn.MINIFS(DetailByDistrict[AEA Teacher Salary Supplement District Cost Per Pupil],DetailByDistrict[AEA],$B24) -> 35.85
B25: 15 | C25: Great Prairie AEA 15 | D25: =_xlfn.MINIFS(DetailByDistrict[AEA Special Ed Support Cost Per Pupil],DetailByDistrict[AEA],$B25) -> 346.48 | E25: =_xlfn.MINIFS(DetailByDistrict[AEA Media Cost Per Pupil],DetailByDistrict[AEA],$B25) -> 64.96 | F25: =_xlfn.MINIFS(DetailByDistrict[AEA Ed Services Cost Per Pupil],DetailByDistrict[AEA],$B25) -> 71.43 | G25: =_xlfn.MINIFS(DetailByDistrict[AEA Teacher Salary Supplement District Cost Per Pupil],DetailByDistrict[AEA],$B25) -> 34.86
B27: AEA | C27: AEA Name | D27: AEA Special Ed Support District Cost without Adjustment | E27: AEA Special Ed Support Adjustment | F27: Special Education Total Cost | G27: District/AEA Statewide State Aid Reduction | H27: Total Special Ed Funding Removing Reduction Including Adjustment
B28: 01 | C28: Keystone AEA 1 | D28: =SUMIF(DetailByDistrict[AEA],DetailByAEA!$B28,DetailByDistrict[AEA Special Ed Support District Cost without Adjustment]) -> 11576155 | E28: =SUMIF(DetailByDistrict[AEA],DetailByAEA!$B28,DetailByDistrict[AEA Special Ed Support Adjustment]) -> 47018 | F28: =SUMIF(DetailByDistrict[AEA],DetailByAEA!$B28,DetailByDistrict[Special Education Total Cost]) -> 11623173 | G28: =SUMIF(DetailByDistrict[AEA],DetailByAEA!$B28,DetailByDistrict[District/AEA Statewide State Aid Reduction]) -> 1883523 | H28: =F28-G28 -> 9739650
B29: 05 | C29: Prairie Lakes AEA 8 | D29: =SUMIF(DetailByDistrict[AEA],DetailByAEA!$B29,DetailByDistrict[AEA Special Ed Support District Cost without Adjustment]) -> 11961182 | E29: =SUMIF(DetailByDistrict[AEA],DetailByAEA!$B29,DetailByDistrict[AEA Special Ed Support Adjustment]) -> 167396 | F29: =SUMIF(DetailByDistrict[AEA],DetailByAEA!$B29,DetailByDistrict[Special Education Total Cost]) -> 12128578 | G29: =SUMIF(DetailByDistrict[AEA],DetailByAEA!$B29,DetailByDistrict[District/AEA Statewide State Aid Reduction]) -> 1969206 | H29: =F29-G29 -> 10159372
B30: 07 | C30: Central Rivers | D30: =SUMIF(DetailByDistrict[AEA],DetailByAEA!$B30,DetailByDistrict[AEA Special Ed Support District Cost without Adjustment]) -> 24560553 | E30: =SUMIF(DetailByDistrict[AEA],DetailByAEA!$B30,DetailByDistrict[AEA Special Ed Support Adjustment]) -> 206737 | F30: =SUMIF(DetailByDistrict[AEA],DetailByAEA!$B30,DetailByDistrict[Special Education Total Cost]) -> 24767290 | G30: =SUMIF(DetailByDistrict[AEA],DetailByAEA!$B30,DetailByDistrict[District/AEA Statewide State Aid Reduction]) -> 4119546 | H30: =F30-G30 -> 20647744
B31: 09 | C31: Mississippi Bend AEA 9 | D31: =SUMIF(DetailByDistrict[AEA],DetailByAEA!$B31,DetailByDistrict[AEA Special Ed Support District Cost without Adjustment]) -> 17666093 | E31: =SUMIF(DetailByDistrict[AEA],DetailByAEA!$B31,DetailByDistrict[AEA Special Ed Support Adjustment]) -> 84238 | F31: =SUMIF(DetailByDistrict[AEA],DetailByAEA!$B31,DetailByDistrict[Special Education Total Cost]) -> 17750331 | G31: =SUMIF(DetailByDistrict[AEA],DetailByAEA!$B31,DetailByDistrict[District/AEA Statewide State Aid Reduction]) -> 2983110 | H31: =F31-G31 -> 14767221
B32: 10 | C32: Grant Wood AEA 10 | D32: =SUMIF(DetailByDistrict[AEA],DetailByAEA!$B32,DetailByDistrict[AEA Special Ed Support District Cost without Adjustment]) -> 26987736 | E32: =SUMIF(DetailByDistrict[AEA],DetailByAEA!$B32,DetailByDistrict[AEA Special Ed Support Adjustment]) -> 140219 | F32: =SUMIF(DetailByDistrict[AEA],DetailByAEA!$B32,DetailByDistrict[Special Education Total Cost]) -> 27127955 | G32: =SUMIF(DetailByDistrict[AEA],DetailByAEA!$B32,DetailByDistrict[District/AEA Statewide State Aid Reduction]) -> 4582301 | H32: =F32-G32 -> 22545654
B33: 11 | C33: Heartland AEA 11 | D33: =SUMIF(DetailByDistrict[AEA],DetailByAEA!$B33,DetailByDistrict[AEA Special Ed Support District Cost without Adjustment]) -> 55239348 | E33: =SUMIF(DetailByDistrict[AEA],DetailByAEA!$B33,DetailByDistrict[AEA Special Ed Support Adjustment]) -> 116312 | F33: =SUMIF(DetailByDistrict[AEA],DetailByAEA!$B33,DetailByDistrict[Special Education Total Cost]) -> 55355660 | G33: =SUMIF(DetailByDistrict[AEA],DetailByAEA!$B33,DetailByDistrict[District/AEA Statewide State Aid Reduction]) -> 9574454 | H33: =F33-G33 -> 45781206
B34: 12 | C34: Northwest AEA | D34: =SUMIF(DetailByDistrict[AEA],DetailByAEA!$B34,DetailByDistrict[AEA Special Ed Support District Cost without Adjustment]) -> 16002942 | E34: =SUMIF(DetailByDistrict[AEA],DetailByAEA!$B34,DetailByDistrict[AEA Special Ed Support Adjustment]) -> 106969 | F34: =SUMIF(DetailByDistrict[AEA],DetailByAEA!$B34,DetailByDistrict[Special Education Total Cost]) -> 16109911 | G34: =SUMIF(DetailByDistrict[AEA],DetailByAEA!$B34,DetailByDistrict[District/AEA Statewide State Aid Reduction]) -> 2659575 | H34: =F34-G34 -> 13450336
B35: 13 | C35: Green Hills AEA 13 | D35: =SUMIF(DetailByDistrict[AEA],DetailByAEA!$B35,DetailByDistrict[AEA Special Ed Support District Cost without Adjustment]) -> 14688682 | E35: =SUMIF(DetailByDistrict[AEA],DetailByAEA!$B35,DetailByDistrict[AEA Special Ed Support Adjustment]) -> 172236 | F35: =SUMIF(DetailByDistrict[AEA],DetailByAEA!$B35,DetailByDistrict[Special Education Total Cost]) -> 14860918 | G35: =SUMIF(DetailByDistrict[AEA],DetailByAEA!$B35,DetailByDistrict[District/AEA Statewide State Aid Reduction]) -> 2487165 | H35: =F35-G35 -> 12373753
B36: 15 | C36: Great Prairie AEA 15 | D36: =SUMIF(DetailByDistrict[AEA],DetailByAEA!$B36,DetailByDistrict[AEA Special Ed Support District Cost without Adjustment]) -> 13135510 | E36: =SUMIF(DetailByDistrict[AEA],DetailByAEA!$B36,DetailByDistrict[AEA Special Ed Support Adjustment]) -> 131165 | F36: =SUMIF(DetailByDistrict[AEA],DetailByAEA!$B36,DetailByDistrict[Special Education Total Cost]) -> 13266675 | G36: =SUMIF(DetailByDistrict[AEA],DetailByAEA!$B36,DetailByDistrict[District/AEA Statewide State Aid Reduction]) -> 2241120 | H36: =F36-G36 -> 11025555
D37: =SUM(D28:D36) -> 191818201 | E37: =SUM(E28:E36) -> 1172290 | F37: =SUM(F28:F36) -> 192990491 | G37: =SUM(G28:G36) -> 32500000 | H37: =SUM(H28:H36) -> 160490491
B39: AEA | C39: AEA Name | D39: AEA Media Services Nonpublic Portion | E39: District Media Services | F39: Total Media Services | G39: AEA Educational Services Nonpublic Portion | H39: District Educational Services | I39: Total Educational Services
B40: 01 | C40: Keystone AEA 1 | D40: =SUMIF(DetailByDistrict[AEA],DetailByAEA!$B40,DetailByDistrict[AEA Media Services Nonpublic Portion]) -> 262085 | E40: =SUMIF(DetailByDistrict[AEA],DetailByAEA!$B40,DetailByDistrict[District Media Services]) -> 1792562 | F40: =SUMIF(DetailByDistrict[AEA],DetailByAEA!$B40,DetailByDistrict[Total Media Services]) -> 2054647 | G40: =SUMIF(DetailByDistrict[AEA],DetailByAEA!$B40,DetailByDistrict[AEA Educational Services Nonpublic Portion]) -> 291923 | H40: =SUMIF(DetailByDistrict[AEA],DetailByAEA!$B40,DetailByDistrict[District Educational Services]) -> 1996651 | I40: =SUMIF(DetailByDistrict[AEA],DetailByAEA!$B40,DetailByDistrict[Total Educational Services]) -> 2288574
B41: 05 | C41: Prairie Lakes AEA 8 | D41: =SUMIF(DetailByDistrict[AEA],DetailByAEA!$B41,DetailByDistrict[AEA Media Services Nonpublic Portion]) -> 150479 | E41: =SUMIF(DetailByDistrict[AEA],DetailByAEA!$B41,DetailByDistrict[District Media Services]) -> 1928444 | F41: =SUMIF(DetailByDistrict[AEA],DetailByAEA!$B41,DetailByDistrict[Total Media Services]) -> 2078923 | G41: =SUMIF(DetailByDistrict[AEA],DetailByAEA!$B41,DetailByDistrict[AEA Educational Services Nonpublic Portion]) -> 168486 | H41: =SUMIF(DetailByDistrict[AEA],DetailByAEA!$B41,DetailByDistrict[District Educational Services]) -> 2159246 | I41: =SUMIF(DetailByDistrict[AEA],DetailByAEA!$B41,DetailByDistrict[Total Educational Services]) -> 2327732
B42: 07 | C42: Central Rivers | D42: =SUMIF(DetailByDistrict[AEA],DetailByAEA!$B42,DetailByDistrict[AEA Media Services Nonpublic Portion]) -> 253193 | E42: =SUMIF(DetailByDistrict[AEA],DetailByAEA!$B42,DetailByDistrict[District Media Services]) -> 3931114 | F42: =SUMIF(DetailByDistrict[AEA],DetailByAEA!$B42,DetailByDistrict[Total Media Services]) -> 4184307 | G42: =SUMIF(DetailByDistrict[AEA],DetailByAEA!$B42,DetailByDistrict[AEA Educational Services Nonpublic Portion]) -> 282243 | H42: =SUMIF(DetailByDistrict[AEA],DetailByAEA!$B42,DetailByDistrict[District Educational Services]) -> 4382083 | I42: =SUMIF(DetailByDistrict[AEA],DetailByAEA!$B42,DetailByDistrict[Total Educational Services]) -> 4664326
B43: 09 | C43: Mississippi Bend AEA 9 | D43: =SUMIF(DetailByDistrict[AEA],DetailByAEA!$B43,DetailByDistrict[AEA Media Services Nonpublic Portion]) -> 245851 | E43: =SUMIF(DetailByDistrict[AEA],DetailByAEA!$B43,DetailByDistrict[District Media Services]) -> 2833641 | F43: =SUMIF(DetailByDistrict[AEA],DetailByAEA!$B43,DetailByDistrict[Total Media Services]) -> 3079492 | G43: =SUMIF(DetailByDistrict[AEA],DetailByAEA!$B43,DetailByDistrict[AEA Educational Services Nonpublic Portion]) -> 268841 | H43: =SUMIF(DetailByDistrict[AEA],DetailByAEA!$B43,DetailByDistrict[District Educational Services]) -> 3098639 | I43: =SUMIF(DetailByDistrict[AEA],DetailByAEA!$B43,DetailByDistrict[Total Educational Services]) -> 3367480
B44: 10 | C44: Grant Wood AEA 10 | D44: =SUMIF(DetailByDistrict[AEA],DetailByAEA!$B44,DetailByDistrict[AEA Media Services Nonpublic Portion]) -> 344008 | E44: =SUMIF(DetailByDistrict[AEA],DetailByAEA!$B44,DetailByDistrict[District Media Services]) -> 4480891 | F44: =SUMIF(DetailByDistrict[AEA],DetailByAEA!$B44,DetailByDistrict[Total Media Services]) -> 4824899 | G44: =SUMIF(DetailByDistrict[AEA],DetailByAEA!$B44,DetailByDistrict[AEA Educational Services Nonpublic Portion]) -> 378309 | H44: =SUMIF(DetailByDistrict[AEA],DetailByAEA!$B44,DetailByDistrict[District Educational Services]) -> 4927738 | I44: =SUMIF(DetailByDistrict[AEA],DetailByAEA!$B44,DetailByDistrict[Total Educational Services]) -> 5306047
B45: 11 | C45: Heartland AEA 11 | D45: =SUMIF(DetailByDistrict[AEA],DetailByAEA!$B45,DetailByDistrict[AEA Media Services Nonpublic Portion]) -> 752248 | E45: =SUMIF(DetailByDistrict[AEA],DetailByAEA!$B45,DetailByDistrict[District Media Services]) -> 9229904 | F45: =SUMIF(DetailByDistrict[AEA],DetailByAEA!$B45,DetailByDistrict[Total Media Services]) -> 9982152 | G45: =SUMIF(DetailByDistrict[AEA],DetailByAEA!$B45,DetailByDistrict[AEA Educational Services Nonpublic Portion]) -> 826706 | H45: =SUMIF(DetailByDistrict[AEA],DetailByAEA!$B45,DetailByDistrict[District Educational Services]) -> 10143500 | I45: =SUMIF(DetailByDistrict[AEA],DetailByAEA!$B45,DetailByDistrict[Total Educational Services]) -> 10970206
B46: 12 | C46: Northwest AEA | D46: =SUMIF(DetailByDistrict[AEA],DetailByAEA!$B46,DetailByDistrict[AEA Media Services Nonpublic Portion]) -> 377069 | E46: =SUMIF(DetailByDistrict[AEA],DetailByAEA!$B46,DetailByDistrict[District Media Services]) -> 2547549 | F46: =SUMIF(DetailByDistrict[AEA],DetailByAEA!$B46,DetailByDistrict[Total Media Services]) -> 2924618 | G46: =SUMIF(DetailByDistrict[AEA],DetailByAEA!$B46,DetailByDistrict[AEA Educational Services Nonpublic Portion]) -> 422065 | H46: =SUMIF(DetailByDistrict[AEA],DetailByAEA!$B46,DetailByDistrict[District Educational Services]) -> 2851607 | I46: =SUMIF(DetailByDistrict[AEA],DetailByAEA!$B46,DetailByDistrict[Total Educational Services]) -> 3273672
B47: 13 | C47: Green Hills AEA 13 | D47: =SUMIF(DetailByDistrict[AEA],DetailByAEA!$B47,DetailByDistrict[AEA Media Services Nonpublic Portion]) -> 79679 | E47: =SUMIF(DetailByDistrict[AEA],DetailByAEA!$B47,DetailByDistrict[District Media Services]) -> 2343537 | F47: =SUMIF(DetailByDistrict[AEA],DetailByAEA!$B47,DetailByDistrict[Total Media Services]) -> 2423216 | G47: =SUMIF(DetailByDistrict[AEA],DetailByAEA!$B47,DetailByDistrict[AEA Educational Services Nonpublic Portion]) -> 88100 | H47: =SUMIF(DetailByDistrict[AEA],DetailByAEA!$B47,DetailByDistrict[District Educational Services]) -> 2591273 | I47: =SUMIF(DetailByDistrict[AEA],DetailByAEA!$B47,DetailByDistrict[Total Educational Services]) -> 2679373
B48: 15 | C48: Great Prairie AEA 15 | D48: =SUMIF(DetailByDistrict[AEA],DetailByAEA!$B48,DetailByDistrict[AEA Media Services Nonpublic Portion]) -> 95494 | E48: =SUMIF(DetailByDistrict[AEA],DetailByAEA!$B48,DetailByDistrict[District Media Services]) -> 2150172 | F48: =SUMIF(DetailByDistrict[AEA],DetailByAEA!$B48,DetailByDistrict[Total Media Services]) -> 2245666 | G48: =SUMIF(DetailByDistrict[AEA],DetailByAEA!$B48,DetailByDistrict[AEA Educational Services Nonpublic Portion]) -> 105003 | H48: =SUMIF(DetailByDistrict[AEA],DetailByAEA!$B48,DetailByDistrict[District Educational Services]) -> 2364334 | I48: =SUMIF(DetailByDistrict[AEA],DetailByAEA!$B48,DetailByDistrict[Total Educational Services]) -> 2469337
D49: =SUM(D40:D48) -> 2560106 | E49: =SUM(E40:E48) -> 31237814 | F49: =SUM(F40:F48) -> 33797920 | G49: =SUM(G40:G48) -> 2831676 | H49: =SUM(H40:H48) -> 34515071 | I49: =SUM(I40:I48) -> 37346747
B51: AEA | C51: AEA Name | D51: AEA Sharing District Cost | E51: AEA Teacher Salary Supplement District Cost
B52: 01 | C52: Keystone AEA 1 | D52: =SUMIF(DetailByDistrict[AEA],DetailByAEA!$B52,DetailByDistrict[AEA Sharing District Cost]) -> 30000 | E52: =SUMIF(DetailByDistrict[AEA],DetailByAEA!$B52,DetailByDistrict[AEA Teacher Salary Supplement District Cost]) -> 1151859
B53: 05 | C53: Prairie Lakes AEA 8 | D53: =SUMIF(DetailByDistrict[AEA],DetailByAEA!$B53,DetailByDistrict[AEA Sharing District Cost]) -> 0 | E53: =SUMIF(DetailByDistrict[AEA],DetailByAEA!$B53,DetailByDistrict[AEA Teacher Salary Supplement District Cost]) -> 1276124
B54: 07 | C54: Central Rivers | D54: =SUMIF(DetailByDistrict[AEA],DetailByAEA!$B54,DetailByDistrict[AEA Sharing District Cost]) -> 30000 | E54: =SUMIF(DetailByDistrict[AEA],DetailByAEA!$B54,DetailByDistrict[AEA Teacher Salary Supplement District Cost]) -> 3032137
B55: 09 | C55: Mississippi Bend AEA 9 | D55: =SUMIF(DetailByDistrict[AEA],DetailByAEA!$B55,DetailByDistrict[AEA Sharing District Cost]) -> 30000 | E55: =SUMIF(DetailByDistrict[AEA],DetailByAEA!$B55,DetailByDistrict[AEA Teacher Salary Supplement District Cost]) -> 1634071
B56: 10 | C56: Grant Wood AEA 10 | D56: =SUMIF(DetailByDistrict[AEA],DetailByAEA!$B56,DetailByDistrict[AEA Sharing District Cost]) -> 30001 | E56: =SUMIF(DetailByDistrict[AEA],DetailByAEA!$B56,DetailByDistrict[AEA Teacher Salary Supplement District Cost]) -> 2570057
B57: 11 | C57: Heartland AEA 11 | D57: =SUMIF(DetailByDistrict[AEA],DetailByAEA!$B57,DetailByDistrict[AEA Sharing District Cost]) -> 0 | E57: =SUMIF(DetailByDistrict[AEA],DetailByAEA!$B57,DetailByDistrict[AEA Teacher Salary Supplement District Cost]) -> 4753653
B58: 12 | C58: Northwest AEA | D58: =SUMIF(DetailByDistrict[AEA],DetailByAEA!$B58,DetailByDistrict[AEA Sharing District Cost]) -> 30000 | E58: =SUMIF(DetailByDistrict[AEA],DetailByAEA!$B58,DetailByDistrict[AEA Teacher Salary Supplement District Cost]) -> 1619590
B59: 13 | C59: Green Hills AEA 13 | D59: =SUMIF(DetailByDistrict[AEA],DetailByAEA!$B59,DetailByDistrict[AEA Sharing District Cost]) -> 30000 | E59: =SUMIF(DetailByDistrict[AEA],DetailByAEA!$B59,DetailByDistrict[AEA Teacher Salary Supplement District Cost]) -> 1519471
B60: 15 | C60: Great Prairie AEA 15 | D60: =SUMIF(DetailByDistrict[AEA],DetailByAEA!$B60,DetailByDistrict[AEA Sharing District Cost]) -> 30002 | E60: =SUMIF(DetailByDistrict[AEA],DetailByAEA!$B60,DetailByDistrict[AEA Teacher Salary Supplement District Cost]) -> 1327569
D61: =SUM(D52:D60) -> 210003 | E61: =SUM(E52:E60) -> 18884531

Sheet Special Education Breakdown
I1: Line 4.49 A&L | J1: Calculated | K1: Line 5.16 A&L | L1: Calculated | M1: Line 4.54 A&L | N1: Calculated | O1: Calculated | Q1: Calculated | R1: Line 4.54 A&L | S1: Calculated | T1: Calculated | U1: Calculated | W1: Calculated | X1: Calculated
I2: Column A | J2: Column B | K2: Column C | L2: Column D | M2: Column E | N2: Column F | O2: Column G | Q2: Column H | R2: Column I | S2: Column J | T2: Column K | U2: Column L | W2: Column M | X2: Column N
L3: B-C | N3: A-C+E | O3: A-C+E *10% | S3: H+I | T3: D-G | U3: J+K | W3: G/F | X3: L/F
A4: FiscalYear | B4: AEA To Generate Funds | C4: AEA District Chose to Receive Services From | D4: Dist | E4: DistSub1 | F4: DistSub2 | G4: DistrictNumber | H4: Label | I4: AEA Special Ed Support District Cost Formula Generated | J4: State Aid Portion Special Ed | K4: AEA Statewide State Aid Reduction | L4: State Aid Special Ed Minus Reduction | M4: AEA Special Ed Support Adjustment | N4: Total Special Ed Funding Removing Reduction Including Adjustment | O4: 10% Portion District Can Keep from State Aid portion | Q4: =Breakdown[[#Headers],[Special Education Property Tax Portion]] -> Special Education Property Tax Portion | R4: =Breakdown[[#Headers],[AEA Special Ed Support Adjustment]] -> AEA Special Ed Support Adjustment | S4: Total Property Tax Portion District Pays AEA | T4: State Aid Portion District Sends to AEA | U4: Total Payment from District to AEA | W4: District Percentage ability to Retain | X4: District Percentage to Pay to AEAs
A5: 2026 | B5: 11 | C5: 11 | D5: 0018 | G5: 0018 | H5: Adair-Casey | I5: =INDEX(Breakdown[],MATCH($D5,Breakdown[Dist],0),MATCH(I$4,Breakdown[#Headers],0)) -> 113866 | J5: =INDEX(Breakdown[],MATCH($D5,Breakdown[Dist],0),MATCH(J$4,Breakdown[#Headers],0)) -> 92145 | K5: =INDEX(Breakdown[],MATCH($D5,Breakdown[Dist],0),MATCH(K$4,Breakdown[#Headers],0)) -> 19736 | L5: =INDEX(Breakdown[],MATCH($D5,Breakdown[Dist],0),MATCH(L$4,Breakdown[#Headers],0)) -> 72409 | M5: =INDEX(Breakdown[],MATCH($D5,Breakdown[Dist],0),MATCH(M$4,Breakdown[#Headers],0)) -> 1802 | N5: =I5-K5+M5 -> 95932 | O5: =ROUND(N5*0.1,0) -> 9593 | Q5: =INDEX(Breakdown[],MATCH($D5,Breakdown[Dist],0),MATCH(Q$4,Breakdown[#Headers],0)) -> 21721 | R5: =INDEX(Breakdown[],MATCH($D5,Breakdown[Dist],0),MATCH(R$4,Breakdown[#Headers],0)) -> 1802 | S5: =SUM(Q5:R5) -> 23523 | T5: =L5-O5 -> 62816 | U5: =SUM(S5:T5) -> 86339 | W5: =O5/N5 -> 0.099997915 | X5: =U5/N5 -> 0.90000208
A6: 2026 | B6: 11 | C6: 11 | D6: 0027 | G6: 0027 | H6: Adel-Desoto-Minburn | I6: =INDEX(Breakdown[],MATCH($D6,Breakdown[Dist],0),MATCH(I$4,Breakdown[#Headers],0)) -> 828554 | J6: =INDEX(Breakdown[],MATCH($D6,Breakdown[Dist],0),MATCH(J$4,Breakdown[#Headers],0)) -> 670501 | K6: =INDEX(Breakdown[],MATCH($D6,Breakdown[Dist],0),MATCH(K$4,Breakdown[#Headers],0)) -> 143611 | L6: =INDEX(Breakdown[],MATCH($D6,Breakdown[Dist],0),MATCH(L$4,Breakdown[#Headers],0)) -> 526890 | M6: =INDEX(Breakdown[],MATCH($D6,Breakdown[Dist],0),MATCH(M$4,Breakdown[#Headers],0)) -> 0 | N6: =I6-K6+M6 -> 684943 | O6: =ROUND(N6*0.1,0) -> 68494 | Q6: =INDEX(Breakdown[],MATCH($D6,Breakdown[Dist],0),MATCH(Q$4,Breakdown[#Headers],0)) -> 158053 | R6: =INDEX(Breakdown[],MATCH($D6,Breakdown[Dist],0),MATCH(R$4,Breakdown[#Headers],0)) -> 0 | S6: =SUM(Q6:R6) -> 158053 | T6: =L6-O6 -> 458396 | U6: =SUM(S6:T6) -> 616449 | W6: =O6/N6 -> 0.099999562 | X6: =U6/N6 -> 0.90000044
A7: 2026 | B7: 07 | C7: 07 | D7: 0009 | G7: 0009 | H7: AGWSR | I7: =INDEX(Breakdown[],MATCH($D7,Breakdown[Dist],0),MATCH(I$4,Breakdown[#Headers],0)) -> 281388 | J7: =INDEX(Breakdown[],MATCH($D7,Breakdown[Dist],0),MATCH(J$4,Breakdown[#Headers],0)) -> 220358 | K7: =INDEX(Breakdown[],MATCH($D7,Breakdown[Dist],0),MATCH(K$4,Breakdown[#Headers],0)) -> 47198 | L7: =INDEX(Breakdown[],MATCH($D7,Breakdown[Dist],0),MATCH(L$4,Breakdown[#Headers],0)) -> 173160 | M7: =INDEX(Breakdown[],MATCH($D7,Breakdown[Dist],0),MATCH(M$4,Breakdown[#Headers],0)) -> 4081 | N7: =I7-K7+M7 -> 238271 | O7: =ROUND(N7*0.1,0) -> 23827 | Q7: =INDEX(Breakdown[],MATCH($D7,Breakdown[Dist],0),MATCH(Q$4,Breakdown[#Headers],0)) -> 61030 | R7: =INDEX(Breakdown[],MATCH($D7,Breakdown[Dist],0),MATCH(R$4,Breakdown[#Headers],0)) -> 4081 | S7: =SUM(Q7:R7) -> 65111 | T7: =L7-O7 -> 149333 | U7: =SUM(S7:T7) -> 214444 | W7: =O7/N7 -> 0.09999958 | X7: =U7/N7 -> 0.90000042
A8: 2026 | B8: 13 | C8: 13 | D8: 0441 | G8: 0441 | H8: AHSTW | I8: =INDEX(Breakdown[],MATCH($D8,Breakdown[Dist],0),MATCH(I$4,Breakdown[#Headers],0)) -> 311331 | J8: =INDEX(Breakdown[],MATCH($D8,Breakdown[Dist],0),MATCH(J$4,Breakdown[#Headers],0)) -> 246126 | K8: =INDEX(Breakdown[],MATCH($D8,Breakdown[Dist],0),MATCH(K$4,Breakdown[#Headers],0)) -> 52716 | L8: =INDEX(Breakdown[],MATCH($D8,Breakdown[Dist],0),MATCH(L$4,Breakdown[#Headers],0)) -> 193410 | M8: =INDEX(Breakdown[],MATCH($D8,Breakdown[Dist],0),MATCH(M$4,Breakdown[#Headers],0)) -> 0 | N8: =I8-K8+M8 -> 258615 | O8: =ROUND(N8*0.1,0) -> 25862 | Q8: =INDEX(Breakdown[],MATCH($D8,Breakdown[Dist],0),MATCH(Q$4,Breakdown[#Headers],0)) -> 65205 | R8: =INDEX(Breakdown[],MATCH($D8,Breakdown[Dist],0),MATCH(R$4,Breakdown[#Headers],0)) -> 0 | S8: =SUM(Q8:R8) -> 65205 | T8: =L8-O8 -> 167548 | U8: =SUM(S8:T8) -> 232753 | W8: =O8/N8 -> 0.10000193 | X8: =U8/N8 -> 0.89999807
A9: 2026 | B9: 12 | C9: 12 | D9: 0063 | G9: 0063 | H9: Akron-Westfield | I9: =INDEX(Breakdown[],MATCH($D9,Breakdown[Dist],0),MATCH(I$4,Breakdown[#Headers],0)) -> 214092 | J9: =INDEX(Breakdown[],MATCH($D9,Breakdown[Dist],0),MATCH(J$4,Breakdown[#Headers],0)) -> 166122 | K9: =INDEX(Breakdown[],MATCH($D9,Breakdown[Dist],0),MATCH(K$4,Breakdown[#Headers],0)) -> 35581 | L9: =INDEX(Breakdown[],MATCH($D9,Breakdown[Dist],0),MATCH(L$4,Breakdown[#Headers],0)) -> 130541 | M9: =INDEX(Breakdown[],MATCH($D9,Breakdown[Dist],0),MATCH(M$4,Breakdown[#Headers],0)) -> 1215 | N9: =I9-K9+M9 -> 179726 | O9: =ROUND(N9*0.1,0) -> 17973 | Q9: =INDEX(Breakdown[],MATCH($D9,Breakdown[Dist],0),MATCH(Q$4,Breakdown[#Headers],0)) -> 47970 | R9: =INDEX(Breakdown[],MATCH($D9,Breakdown[Dist],0),MATCH(R$4,Breakdown[#Headers],0)) -> 1215 | S9: =SUM(Q9:R9) -> 49185 | T9: =L9-O9 -> 112568 | U9: =SUM(S9:T9) -> 161753 | W9: =O9/N9 -> 0.10000223 | X9: =U9/N9 -> 0.89999777
A10: 2026 | B10: 05 | C10: 05 | D10: 0072 | G10: 0072 | H10: Albert City-Truesdale | I10: =INDEX(Breakdown[],MATCH($D10,Breakdown[Dist],0),MATCH(I$4,Breakdown[#Headers],0)) -> 82726 | J10: =INDEX(Breakdown[],MATCH($D10,Breakdown[Dist],0),MATCH(J$4,Breakdown[#Headers],0)) -> 63588 | K10: =INDEX(Breakdown[],MATCH($D10,Breakdown[Dist],0),MATCH(K$4,Breakdown[#Headers],0)) -> 13620 | L10: =INDEX(Breakdown[],MATCH($D10,Breakdown[Dist],0),MATCH(L$4,Breakdown[#Headers],0)) -> 49968 | M10: =INDEX(Breakdown[],MATCH($D10,Breakdown[Dist],0),MATCH(M$4,Breakdown[#Headers],0)) -> 0 | N10: =I10-K10+M10 -> 69106 | O10: =ROUND(N10*0.1,0) -> 6911 | Q10: =INDEX(Breakdown[],MATCH($D10,Breakdown[Dist],0),MATCH(Q$4,Breakdown[#Headers],0)) -> 19138 | R10: =INDEX(Breakdown[],MATCH($D10,Breakdown[Dist],0),MATCH(R$4,Breakdown[#Headers],0)) -> 0 | S10: =SUM(Q10:R10) -> 19138 | T10: =L10-O10 -> 43057 | U10: =SUM(S10:T10) -> 62195 | W10: =O10/N10 -> 0.10000579 | X10: =U10/N10 -> 0.89999421
A11: 2026 | B11: 15 | C11: 15 | D11: 0081 | G11: 0081 | H11: Albia | I11: =INDEX(Breakdown[],MATCH($D11,Breakdown[Dist],0),MATCH(I$4,Breakdown[#Headers],0)) -> 419878 | J11: =INDEX(Breakdown[],MATCH($D11,Breakdown[Dist],0),MATCH(J$4,Breakdown[#Headers],0)) -> 334468 | K11: =INDEX(Breakdown[],MATCH($D11,Breakdown[Dist],0),MATCH(K$4,Breakdown[#Headers],0)) -> 71638 | L11: =INDEX(Breakdown[],MATCH($D11,Breakdown[Dist],0),MATCH(L$4,Breakdown[#Headers],0)) -> 262830 | M11: =INDEX(Breakdown[],MATCH($D11,Breakdown[Dist],0),MATCH(M$4,Breakdown[#Headers],0)) -> 0 | N11: =I11-K11+M11 -> 348240 | O11: =ROUND(N11*0.1,0) -> 34824 | Q11: =INDEX(Breakdown[],MATCH($D11,Breakdown[Dist],0),MATCH(Q$4,Breakdown[#Headers],0)) -> 85410 | R11: =INDEX(Breakdown[],MATCH($D11,Breakdown[Dist],0),MATCH(R$4,Breakdown[#Headers],0)) -> 0 | S11: =SUM(Q11:R11) -> 85410 | T11: =L11-O11 -> 228006 | U11: =SUM(S11:T11) -> 313416 | W11: =O11/N11 -> 0.1 | X11: =U11/N11 -> 0.9
A12: 2026 | B12: 10 | C12: 10 | D12: 0099 | G12: 0099 | H12: Alburnett | I12: =INDEX(Breakdown[],MATCH($D12,Breakdown[Dist],0),MATCH(I$4,Breakdown[#Headers],0)) -> 203952 | J12: =INDEX(Breakdown[],MATCH($D12,Breakdown[Dist],0),MATCH(J$4,Breakdown[#Headers],0)) -> 161681 | K12: =INDEX(Breakdown[],MATCH($D12,Breakdown[Dist],0),MATCH(K$4,Breakdown[#Headers],0)) -> 34629 | L12: =INDEX(Breakdown[],MATCH($D12,Breakdown[Dist],0),MATCH(L$4,Breakdown[#Headers],0)) -> 127052 | M12: =INDEX(Breakdown[],MATCH($D12,Breakdown[Dist],0),MATCH(M$4,Breakdown[#Headers],0)) -> 0 | N12: =I12-K12+M12 -> 169323 | O12: =ROUND(N12*0.1,0) -> 16932 | Q12: =INDEX(Breakdown[],MATCH($D12,Breakdown[Dist],0),MATCH(Q$4,Breakdown[#Headers],0)) -> 42271 | R12: =INDEX(Breakdown[],MATCH($D12,Breakdown[Dist],0),MATCH(R$4,Breakdown[#Headers],0)) -> 0 | S12: =SUM(Q12:R12) -> 42271 | T12: =L12-O12 -> 110120 | U12: =SUM(S12:T12) -> 152391 | W12: =O12/N12 -> 0.099998228 | X12: =U12/N12 -> 0.90000177
A13: 2026 | B13: 07 | C13: 07 | D13: 0108 | G13: 0108 | H13: Alden | I13: =INDEX(Breakdown[],MATCH($D13,Breakdown[Dist],0),MATCH(I$4,Breakdown[#Headers],0)) -> 94422 | J13: =INDEX(Breakdown[],MATCH($D13,Breakdown[Dist],0),MATCH(J$4,Breakdown[#Headers],0)) -> 73943 | K13: =INDEX(Breakdown[],MATCH($D13,Breakdown[Dist],0),MATCH(K$4,Breakdown[#Headers],0)) -> 15838 | L13: =INDEX(Breakdown[],MATCH($D13,Breakdown[Dist],0),MATCH(L$4,Breakdown[#Headers],0)) -> 58105 | M13: =INDEX(Breakdown[],MATCH($D13,Breakdown[Dist],0),MATCH(M$4,Breakdown[#Headers],0)) -> 5533 | N13: =I13-K13+M13 -> 84117 | O13: =ROUND(N13*0.1,0) -> 8412 | Q13: =INDEX(Breakdown[],MATCH($D13,Breakdown[Dist],0),MATCH(Q$4,Breakdown[#Headers],0)) -> 20479 | R13: =INDEX(Breakdown[],MATCH($D13,Breakdown[Dist],0),MATCH(R$4,Breakdown[#Headers],0)) -> 5533 | S13: =SUM(Q13:R13) -> 26012 | T13: =L13-O13 -> 49693 | U13: =SUM(S13:T13) -> 75705 | W13: =O13/N13 -> 0.10000357 | X13: =U13/N13 -> 0.89999643
A14: 2026 | B14: 05 | C14: 05 | D14: 0126 | E14: 6417 | F14: 3897 | G14: 0126 | H14: Algona | I14: =INDEX(Breakdown[],MATCH($D14,Breakdown[Dist],0),MATCH(I$4,Breakdown[#Headers],0)) -> 587022 | J14: =INDEX(Breakdown[],MATCH($D14,Breakdown[Dist],0),MATCH(J$4,Breakdown[#Headers],0)) -> 451216 | K14: =INDEX(Breakdown[],MATCH($D14,Breakdown[Dist],0),MATCH(K$4,Breakdown[#Headers],0)) -> 96643 | L14: =INDEX(Breakdown[],MATCH($D14,Breakdown[Dist],0),MATCH(L$4,Breakdown[#Headers],0)) -> 354573 | M14: =INDEX(Breakdown[],MATCH($D14,Breakdown[Dist],0),MATCH(M$4,Breakdown[#Headers],0)) -> 0 | N14: =I14-K14+M14 -> 490379 | O14: =ROUND(N14*0.1,0) -> 49038 | Q14: =INDEX(Breakdown[],MATCH($D14,Breakdown[Dist],0),MATCH(Q$4,Breakdown[#Headers],0)) -> 135806 | R14: =INDEX(Breakdown[],MATCH($D14,Breakdown[Dist],0),MATCH(R$4,Breakdown[#Headers],0)) -> 0 | S14: =SUM(Q14:R14) -> 135806 | T14: =L14-O14 -> 305535 | U14: =SUM(S14:T14) -> 441341 | W14: =O14/N14 -> 0.1000002 | X14: =U14/N14 -> 0.8999998
A15: 2026 | B15: 01 | C15: 01 | D15: 0135 | G15: 0135 | H15: Allamakee | I15: =INDEX(Breakdown[],MATCH($D15,Breakdown[Dist],0),MATCH(I$4,Breakdown[#Headers],0)) -> 463226 | J15: =INDEX(Breakdown[],MATCH($D15,Breakdown[Dist],0),MATCH(J$4,Breakdown[#Headers],0)) -> 351894 | K15: =INDEX(Breakdown[],MATCH($D15,Breakdown[Dist],0),MATCH(K$4,Breakdown[#Headers],0)) -> 75370 | L15: =INDEX(Breakdown[],MATCH($D15,Breakdown[Dist],0),MATCH(L$4,Breakdown[#Headers],0)) -> 276524 | M15: =INDEX(Breakdown[],MATCH($D15,Breakdown[Dist],0),MATCH(M$4,Breakdown[#Headers],0)) -> 0 | N15: =I15-K15+M15 -> 387856 | O15: =ROUND(N15*0.1,0) -> 38786 | Q15: =INDEX(Breakdown[],MATCH($D15,Breakdown[Dist],0),MATCH(Q$4,Breakdown[#Headers],0)) -> 111332 | R15: =INDEX(Breakdown[],MATCH($D15,Breakdown[Dist],0),MATCH(R$4,Breakdown[#Headers],0)) -> 0 | S15: =SUM(Q15:R15) -> 111332 | T15: =L15-O15 -> 237738 | U15: =SUM(S15:T15) -> 349070 | W15: =O15/N15 -> 0.10000103 | X15: =U15/N15 -> 0.89999897
A16: 2026 | B16: 05 | C16: 05 | D16: 0171 | G16: 0171 | H16: Alta-Aurelia | I16: =INDEX(Breakdown[],MATCH($D16,Breakdown[Dist],0),MATCH(I$4,Breakdown[#Headers],0)) -> 334438 | J16: =INDEX(Breakdown[],MATCH($D16,Breakdown[Dist],0),MATCH(J$4,Breakdown[#Headers],0)) -> 257066 | K16: =INDEX(Breakdown[],MATCH($D16,Breakdown[Dist],0),MATCH(K$4,Breakdown[#Headers],0)) -> 55059 | L16: =INDEX(Breakdown[],MATCH($D16,Breakdown[Dist],0),MATCH(L$4,Breakdown[#Headers],0)) -> 202007 | M16: =INDEX(Breakdown[],MATCH($D16,Breakdown[Dist],0),MATCH(M$4,Breakdown[#Headers],0)) -> 0 | N16: =I16-K16+M16 -> 279379 | O16: =ROUND(N16*0.1,0) -> 27938 | Q16: =INDEX(Breakdown[],MATCH($D16,Breakdown[Dist],0),MATCH(Q$4,Breakdown[#Headers],0)) -> 77372 | R16: =INDEX(Breakdown[],MATCH($D16,Breakdown[Dist],0),MATCH(R$4,Breakdown[#Headers],0)) -> 0 | S16: =SUM(Q16:R16) -> 77372 | T16: =L16-O16 -> 174069 | U16: =SUM(S16:T16) -> 251441 | W16: =O16/N16 -> 0.10000036 | X16: =U16/N16 -> 0.89999964
A17: 2026 | B17: 11 | C17: 11 | D17: 0225 | G17: 0225 | H17: Ames | I17: =INDEX(Breakdown[],MATCH($D17,Breakdown[Dist],0),MATCH(I$4,Breakdown[#Headers],0)) -> 1767659 | J17: =INDEX(Breakdown[],MATCH($D17,Breakdown[Dist],0),MATCH(J$4,Breakdown[#Headers],0)) -> 1430464 | K17: =INDEX(Breakdown[],MATCH($D17,Breakdown[Dist],0),MATCH(K$4,Breakdown[#Headers],0)) -> 306383 | L17: =INDEX(Breakdown[],MATCH($D17,Breakdown[Dist],0),MATCH(L$4,Breakdown[#Headers],0)) -> 1124081 | M17: =INDEX(Breakdown[],MATCH($D17,Breakdown[Dist],0),MATCH(M$4,Breakdown[#Headers],0)) -> 0 | N17: =I17-K17+M17 -> 1461276 | O17: =ROUND(N17*0.1,0) -> 146128 | Q17: =INDEX(Breakdown[],MATCH($D17,Breakdown[Dist],0),MATCH(Q$4,Breakdown[#Headers],0)) -> 337195 | R17: =INDEX(Breakdown[],MATCH($D17,Breakdown[Dist],0),MATCH(R$4,Breakdown[#Headers],0)) -> 0 | S17: =SUM(Q17:R17) -> 337195 | T17: =L17-O17 -> 977953 | U17: =SUM(S17:T17) -> 1315148 | W17: =O17/N17 -> 0.10000027 | X17: =U17/N17 -> 0.89999973
A18: 2026 | B18: 10 | C18: 10 | D18: 0234 | G18: 0234 | H18: Anamosa | I18: =INDEX(Breakdown[],MATCH($D18,Breakdown[Dist],0),MATCH(I$4,Breakdown[#Headers],0)) -> 458314 | J18: =INDEX(Breakdown[],MATCH($D18,Breakdown[Dist],0),MATCH(J$4,Breakdown[#Headers],0)) -> 363324 | K18: =INDEX(Breakdown[],MATCH($D18,Breakdown[Dist],0),MATCH(K$4,Breakdown[#Headers],0)) -> 77818 | L18: =INDEX(Breakdown[],MATCH($D18,Breakdown[Dist],0),MATCH(L$4,Breakdown[#Headers],0)) -> 285506 | M18: =INDEX(Breakdown[],MATCH($D18,Breakdown[Dist],0),MATCH(M$4,Breakdown[#Headers],0)) -> 15810 | N18: =I18-K18+M18 -> 396306 | O18: =ROUND(N18*0.1,0) -> 39631 | Q18: =INDEX(Breakdown[],MATCH($D18,Breakdown[Dist],0),MATCH(Q$4,Breakdown[#Headers],0)) -> 94990 | R18: =INDEX(Breakdown[],MATCH($D18,Breakdown[Dist],0),MATCH(R$4,Breakdown[#Headers],0)) -> 15810 | S18: =SUM(Q18:R18) -> 110800 | T18: =L18-O18 -> 245875 | U18: =SUM(S18:T18) -> 356675 | W18: =O18/N18 -> 0.10000101 | X18: =U18/N18 -> 0.89999899
A19: 2026 | B19: 09 | C19: 09 | D19: 0243 | G19: 0243 | H19: Andrew | I19: =INDEX(Breakdown[],MATCH($D19,Breakdown[Dist],0),MATCH(I$4,Breakdown[#Headers],0)) -> 86463 | J19: =INDEX(Breakdown[],MATCH($D19,Breakdown[Dist],0),MATCH(J$4,Breakdown[#Headers],0)) -> 68166 | K19: =INDEX(Breakdown[],MATCH($D19,Breakdown[Dist],0),MATCH(K$4,Breakdown[#Headers],0)) -> 14600 | L19: =INDEX(Breakdown[],MATCH($D19,Breakdown[Dist],0),MATCH(L$4,Breakdown[#Headers],0)) -> 53566 | M19: =INDEX(Breakdown[],MATCH($D19,Breakdown[Dist],0),MATCH(M$4,Breakdown[#Headers],0)) -> 6868 | N19: =I19-K19+M19 -> 78731 | O19: =ROUND(N19*0.1,0) -> 7873 | Q19: =INDEX(Breakdown[],MATCH($D19,Breakdown[Dist],0),MATCH(Q$4,Breakdown[#Headers],0)) -> 18297 | R19: =INDEX(Breakdown[],MATCH($D19,Breakdown[Dist],0),MATCH(R$4,Breakdown[#Headers],0)) -> 6868 | S19: =SUM(Q19:R19) -> 25165 | T19: =L19-O19 -> 45693 | U19: =SUM(S19:T19) -> 70858 | W19: =O19/N19 -> 0.09999873 | X19: =U19/N19 -> 0.90000127
A20: 2026 | B20: 11 | C20: 11 | D20: 0261 | G20: 0261 | H20: Ankeny | I20: =INDEX(Breakdown[],MATCH($D20,Breakdown[Dist],0),MATCH(I$4,Breakdown[#Headers],0)) -> 4834549 | J20: =INDEX(Breakdown[],MATCH($D20,Breakdown[Dist],0),MATCH(J$4,Breakdown[#Headers],0)) -> 3912319 | K20: =INDEX(Breakdown[],MATCH($D20,Breakdown[Dist],0),MATCH(K$4,Breakdown[#Headers],0)) -> 837957 | L20: =INDEX(Breakdown[],MATCH($D20,Breakdown[Dist],0),MATCH(L$4,Breakdown[#Headers],0)) -> 3074362 | M20: =INDEX(Breakdown[],MATCH($D20,Breakdown[Dist],0),MATCH(M$4,Breakdown[#Headers],0)) -> 0 | N20: =I20-K20+M20 -> 3996592 | O20: =ROUND(N20*0.1,0) -> 399659 | Q20: =INDEX(Breakdown[],MATCH($D20,Breakdown[Dist],0),MATCH(Q$4,Breakdown[#Headers],0)) -> 922230 | R20: =INDEX(Breakdown[],MATCH($D20,Breakdown[Dist],0),MATCH(R$4,Breakdown[#Headers],0)) -> 0 | S20: =SUM(Q20:R20) -> 922230 | T20: =L20-O20 -> 2674703 | U20: =SUM(S20:T20) -> 3596933 | W20: =O20/N20 -> 0.09999995 | X20: =U20/N20 -> 0.90000005
A21: 2026 | B21: 07 | C21: 07 | D21: 0279 | G21: 0279 | H21: Aplington-Parkersburg | I21: =INDEX(Breakdown[],MATCH($D21,Breakdown[Dist],0),MATCH(I$4,Breakdown[#Headers],0)) -> 321327 | J21: =INDEX(Breakdown[],MATCH($D21,Breakdown[Dist],0),MATCH(J$4,Breakdown[#Headers],0)) -> 251635 | K21: =INDEX(Breakdown[],MATCH($D21,Breakdown[Dist],0),MATCH(K$4,Breakdown[#Headers],0)) -> 53897 | L21: =INDEX(Breakdown[],MATCH($D21,Breakdown[Dist],0),MATCH(L$4,Breakdown[#Headers],0)) -> 197738 | M21: =INDEX(Breakdown[],MATCH($D21,Breakdown[Dist],0),MATCH(M$4,Breakdown[#Headers],0)) -> 0 | N21: =I21-K21+M21 -> 267430 | O21: =ROUND(N21*0.1,0) -> 26743 | Q21: =INDEX(Breakdown[],MATCH($D21,Breakdown[Dist],0),MATCH(Q$4,Breakdown[#Headers],0)) -> 69692 | R21: =INDEX(Breakdown[],MATCH($D21,Breakdown[Dist],0),MATCH(R$4,Breakdown[#Headers],0)) -> 0 | S21: =SUM(Q21:R21) -> 69692 | T21: =L21-O21 -> 170995 | U21: =SUM(S21:T21) -> 240687 | W21: =O21/N21 -> 0.1 | X21: =U21/N21 -> 0.9
A22: 2026 | B22: 12 | C22: 12 | D22: 0355 | G22: 0355 | H22: Ar-We-Va | I22: =INDEX(Breakdown[],MATCH($D22,Breakdown[Dist],0),MATCH(I$4,Breakdown[#Headers],0)) -> 111829 | J22: =INDEX(Breakdown[],MATCH($D22,Breakdown[Dist],0),MATCH(J$4,Breakdown[#Headers],0)) -> 86772 | K22: =INDEX(Breakdown[],MATCH($D22,Breakdown[Dist],0),MATCH(K$4,Breakdown[#Headers],0)) -> 18585 | L22: =INDEX(Breakdown[],MATCH($D22,Breakdown[Dist],0),MATCH(L$4,Breakdown[#Headers],0)) -> 68187 | M22: =INDEX(Breakdown[],MATCH($D22,Breakdown[Dist],0),MATCH(M$4,Breakdown[#Headers],0)) -> 4886 | N22: =I22-K22+M22 -> 98130 | O22: =ROUND(N22*0.1,0) -> 9813 | Q22: =INDEX(Breakdown[],MATCH($D22,Breakdown[Dist],0),MATCH(Q$4,Breakdown[#Headers],0)) -> 25057 | R22: =INDEX(Breakdown[],MATCH($D22,Breakdown[Dist],0),MATCH(R$4,Breakdown[#Headers],0)) -> 4886 | S22: =SUM(Q22:R22) -> 29943 | T22: =L22-O22 -> 58374 | U22: =SUM(S22:T22) -> 88317 | W22: =O22/N22 -> 0.1 | X22: =U22/N22 -> 0.9
A23: 2026 | B23: 13 | C23: 13 | D23: 0387 | G23: 0387 | H23: Atlantic | I23: =INDEX(Breakdown[],MATCH($D23,Breakdown[Dist],0),MATCH(I$4,Breakdown[#Headers],0)) -> 597557 | J23: =INDEX(Breakdown[],MATCH($D23,Breakdown[Dist],0),MATCH(J$4,Breakdown[#Headers],0)) -> 472404 | K23: =INDEX(Breakdown[],MATCH($D23,Breakdown[Dist],0),MATCH(K$4,Breakdown[#Headers],0)) -> 101182 | L23: =INDEX(Breakdown[],MATCH($D23,Breakdown[Dist],0),MATCH(L$4,Breakdown[#Headers],0)) -> 371222 | M23: =INDEX(Breakdown[],MATCH($D23,Breakdown[Dist],0),MATCH(M$4,Breakdown[#Headers],0)) -> 0 | N23: =I23-K23+M23 -> 496375 | O23: =ROUND(N23*0.1,0) -> 49638 | Q23: =INDEX(Breakdown[],MATCH($D23,Breakdown[Dist],0),MATCH(Q$4,Breakdown[#Headers],0)) -> 125153 | R23: =INDEX(Breakdown[],MATCH($D23,Breakdown[Dist],0),MATCH(R$4,Breakdown[#Headers],0)) -> 0 | S23: =SUM(Q23:R23) -> 125153 | T23: =L23-O23 -> 321584 | U23: =SUM(S23:T23) -> 446737 | W23: =O23/N23 -> 0.10000101 | X23: =U23/N23 -> 0.89999899
A24: 2026 | B24: 11 | C24: 11 | D24: 0414 | G24: 0414 | H24: Audubon | I24: =INDEX(Breakdown[],MATCH($D24,Breakdown[Dist],0),MATCH(I$4,Breakdown[#Headers],0)) -> 189817 | J24: =INDEX(Breakdown[],MATCH($D24,Breakdown[Dist],0),MATCH(J$4,Breakdown[#Headers],0)) -> 153608 | K24: =INDEX(Breakdown[],MATCH($D24,Breakdown[Dist],0),MATCH(K$4,Breakdown[#Headers],0)) -> 32900 | L24: =INDEX(Breakdown[],MATCH($D24,Breakdown[Dist],0),MATCH(L$4,Breakdown[#Headers],0)) -> 120708 | M24: =INDEX(Breakdown[],MATCH($D24,Breakdown[Dist],0),MATCH(M$4,Breakdown[#Headers],0)) -> 3269 | N24: =I24-K24+M24 -> 160186 | O24: =ROUND(N24*0.1,0) -> 16019 | Q24: =INDEX(Breakdown[],MATCH($D24,Breakdown[Dist],0),MATCH(Q$4,Breakdown[#Headers],0)) -> 36209 | R24: =INDEX(Breakdown[],MATCH($D24,Breakdown[Dist],0),MATCH(R$4,Breakdown[#Headers],0)) -> 3269 | S24: =SUM(Q24:R24) -> 39478 | T24: =L24-O24 -> 104689 | U24: =SUM(S24:T24) -> 144167 | W24: =O24/N24 -> 0.1000025 | X24: =U24/N24 -> 0.8999975
A25: 2026 | B25: 11 | C25: 11 | D25: 0472 | G25: 0472 | H25: Ballard | I25: =INDEX(Breakdown[],MATCH($D25,Breakdown[Dist],0),MATCH(I$4,Breakdown[#Headers],0)) -> 662294 | J25: =INDEX(Breakdown[],MATCH($D25,Breakdown[Dist],0),MATCH(J$4,Breakdown[#Headers],0)) -> 535956 | K25: =INDEX(Breakdown[],MATCH($D25,Breakdown[Dist],0),MATCH(K$4,Breakdown[#Headers],0)) -> 114794 | L25: =INDEX(Breakdown[],MATCH($D25,Breakdown[Dist],0),MATCH(L$4,Breakdown[#Headers],0)) -> 421162 | M25: =INDEX(Breakdown[],MATCH($D25,Breakdown[Dist],0),MATCH(M$4,Breakdown[#Headers],0)) -> 0 | N25: =I25-K25+M25 -> 547500 | O25: =ROUND(N25*0.1,0) -> 54750 | Q25: =INDEX(Breakdown[],MATCH($D25,Breakdown[Dist],0),MATCH(Q$4,Breakdown[#Headers],0)) -> 126338 | R25: =INDEX(Breakdown[],MATCH($D25,Breakdown[Dist],0),MATCH(R$4,Breakdown[#Headers],0)) -> 0 | S25: =SUM(Q25:R25) -> 126338 | T25: =L25-O25 -> 366412 | U25: =SUM(S25:T25) -> 492750 | W25: =O25/N25 -> 0.1 | X25: =U25/N25 -> 0.9
A26: 2026 | B26: 11 | C26: 11 | D26: 0513 | G26: 0513 | H26: Baxter | I26: =INDEX(Breakdown[],MATCH($D26,Breakdown[Dist],0),MATCH(I$4,Breakdown[#Headers],0)) -> 129112 | J26: =INDEX(Breakdown[],MATCH($D26,Breakdown[Dist],0),MATCH(J$4,Breakdown[#Headers],0)) -> 104483 | K26: =INDEX(Breakdown[],MATCH($D26,Breakdown[Dist],0),MATCH(K$4,Breakdown[#Headers],0)) -> 22378 | L26: =INDEX(Breakdown[],MATCH($D26,Breakdown[Dist],0),MATCH(L$4,Breakdown[#Headers],0)) -> 82105 | M26: =INDEX(Breakdown[],MATCH($D26,Breakdown[Dist],0),MATCH(M$4,Breakdown[#Headers],0)) -> 360 | N26: =I26-K26+M26 -> 107094 | O26: =ROUND(N26*0.1,0) -> 10709 | Q26: =INDEX(Breakdown[],MATCH($D26,Breakdown[Dist],0),MATCH(Q$4,Breakdown[#Headers],0)) -> 24629 | R26: =INDEX(Breakdown[],MATCH($D26,Breakdown[Dist],0),MATCH(R$4,Breakdown[#Headers],0)) -> 360 | S26: =SUM(Q26:R26) -> 24989 | T26: =L26-O26 -> 71396 | U26: =SUM(S26:T26) -> 96385 | W26: =O26/N26 -> 0.099996265 | X26: =U26/N26 -> 0.90000374
... A63: 2026 | B63: 13 | C63: 13 | D63: 1197 | G63: 1197 | H63: Clarinda | I63: =INDEX(Breakdown[],MATCH($D63,Breakdown[Dist],0),MATCH(I$4,Breakdown[#Headers],0)) -> 375636 | J63: =INDEX(Breakdown[],MATCH($D63,Breakdown[Dist],0),MATCH(J$4,Breakdown[#Headers],0)) -> 296962 | K63: =INDEX(Breakdown[],MATCH($D63,Breakdown[Dist],0),MATCH(K$4,Breakdown[#Headers],0)) -> 63605 | L63: =INDEX(Breakdown[],MATCH($D63,Breakdown[Dist],0),MATCH(L$4,Breakdown[#Headers],0)) -> 233357 | M63: =INDEX(Breakdown[],MATCH($D63,Breakdown[Dist],0),MATCH(M$4,Breakdown[#Headers],0)) -> 0 | N63: =I63-K63+M63 -> 312031 | O63: =ROUND(N63*0.1,0) -> 31203 | Q63: =INDEX(Breakdown[],MATCH($D63,Breakdown[Dist],0),MATCH(Q$4,Breakdown[#Headers],0)) -> 78674 | R63: =INDEX(Breakdown[],MATCH($D63,Breakdown[Dist],0),MATCH(R$4,Breakdown[#Headers],0)) -> 0 | S63: =SUM(Q63:R63) -> 78674 | T63: =L63-O63 -> 202154 | U63: =SUM(S63:T63) -> 280828 | W63: =O63/N63 -> 0.09999968 | X63: =U63/N63 -> 0.90000032
A64: 2026 | B64: 05 | C64: 05 | D64: 1206 | E64: 1854 | G64: 1206 | H64: Clarion-Goldfield-Dows | I64: =INDEX(Breakdown[],MATCH($D64,Breakdown[Dist],0),MATCH(I$4,Breakdown[#Headers],0)) -> 387713 | J64: =INDEX(Breakdown[],MATCH($D64,Breakdown[Dist],0),MATCH(J$4,Breakdown[#Headers],0)) -> 298017 | K64: =INDEX(Breakdown[],MATCH($D64,Breakdown[Dist],0),MATCH(K$4,Breakdown[#Headers],0)) -> 63830 | L64: =INDEX(Breakdown[],MATCH($D64,Breakdown[Dist],0),MATCH(L$4,Breakdown[#Headers],0)) -> 234187 | M64: =INDEX(Breakdown[],MATCH($D64,Breakdown[Dist],0),MATCH(M$4,Breakdown[#Headers],0)) -> 2582 | N64: =I64-K64+M64 -> 326465 | O64: =ROUND(N64*0.1,0) -> 32647 | Q64: =INDEX(Breakdown[],MATCH($D64,Breakdown[Dist],0),MATCH(Q$4,Breakdown[#Headers],0)) -> 89696 | R64: =INDEX(Breakdown[],MATCH($D64,Breakdown[Dist],0),MATCH(R$4,Breakdown[#Headers],0)) -> 2582 | S64: =SUM(Q64:R64) -> 92278 | T64: =L64-O64 -> 201540 | U64: =SUM(S64:T64) -> 293818 | W64: =O64/N64 -> 0.10000153 | X64: =U64/N64 -> 0.89999847
A65: 2026 | B65: 13 | C65: 13 | D65: 1211 | G65: 1211 | H65: Clarke | I65: =INDEX(Breakdown[],MATCH($D65,Breakdown[Dist],0),MATCH(I$4,Breakdown[#Headers],0)) -> 583247 | J65: =INDEX(Breakdown[],MATCH($D65,Breakdown[Dist],0),MATCH(J$4,Breakdown[#Headers],0)) -> 461091 | K65: =INDEX(Breakdown[],MATCH($D65,Breakdown[Dist],0),MATCH(K$4,Breakdown[#Headers],0)) -> 98758 | L65: =INDEX(Breakdown[],MATCH($D65,Breakdown[Dist],0),MATCH(L$4,Breakdown[#Headers],0)) -> 362333 | M65: =INDEX(Breakdown[],MATCH($D65,Breakdown[Dist],0),MATCH(M$4,Breakdown[#Headers],0)) -> 0 | N65: =I65-K65+M65 -> 484489 | O65: =ROUND(N65*0.1,0) -> 48449 | Q65: =INDEX(Breakdown[],MATCH($D65,Breakdown[Dist],0),MATCH(Q$4,Breakdown[#Headers],0)) -> 122156 | R65: =INDEX(Breakdown[],MATCH($D65,Breakdown[Dist],0),MATCH(R$4,Breakdown[#Headers],0)) -> 0 | S65: =SUM(Q65:R65) -> 122156 | T65: =L65-O65 -> 313884 | U65: =SUM(S65:T65) -> 436040 | W65: =O65/N65 -> 0.10000021 | X65: =U65/N65 -> 0.89999979
A66: 2026 | B66: 07 | C66: 07 | D66: 1215 | G66: 1215 | H66: Clarksville | I66: =INDEX(Breakdown[],MATCH($D66,Breakdown[Dist],0),MATCH(I$4,Breakdown[#Headers],0)) -> 116090 | J66: =INDEX(Breakdown[],MATCH($D66,Breakdown[Dist],0),MATCH(J$4,Breakdown[#Headers],0)) -> 90912 | K66: =INDEX(Breakdown[],MATCH($D66,Breakdown[Dist],0),MATCH(K$4,Breakdown[#Headers],0)) -> 19471 | L66: =INDEX(Breakdown[],MATCH($D66,Breakdown[Dist],0),MATCH(L$4,Breakdown[#Headers],0)) -> 71441 | M66: =INDEX(Breakdown[],MATCH($D66,Breakdown[Dist],0),MATCH(M$4,Breakdown[#Headers],0)) -> 1704 | N66: =I66-K66+M66 -> 98323 | O66: =ROUND(N66*0.1,0) -> 9832 | Q66: =INDEX(Breakdown[],MATCH($D66,Breakdown[Dist],0),MATCH(Q$4,Breakdown[#Headers],0)) -> 25178 | R66: =INDEX(Breakdown[],MATCH($D66,Breakdown[Dist],0),MATCH(R$4,Breakdown[#Headers],0)) -> 1704 | S66: =SUM(Q66:R66) -> 26882 | T66: =L66-O66 -> 61609 | U66: =SUM(S66:T66) -> 88491 | W66: =O66/N66 -> 0.099996949 | X66: =U66/N66 -> 0.90000305
A67: 2026 | B67: 05 | C67: 05 | D67: 1218 | G67: 1218 | H67: Clay Central-Everly | I67: =INDEX(Breakdown[],MATCH($D67,Breakdown[Dist],0),MATCH(I$4,Breakdown[#Headers],0)) -> 106023 | J67: =INDEX(Breakdown[],MATCH($D67,Breakdown[Dist],0),MATCH(J$4,Breakdown[#Headers],0)) -> 81495 | K67: =INDEX(Breakdown[],MATCH($D67,Breakdown[Dist],0),MATCH(K$4,Breakdown[#Headers],0)) -> 17455 | L67: =INDEX(Breakdown[],MATCH($D67,Breakdown[Dist],0),MATCH(L$4,Breakdown[#Headers],0)) -> 64040 | M67: =INDEX(Breakdown[],MATCH($D67,Breakdown[Dist],0),MATCH(M$4,Breakdown[#Headers],0)) -> 19010 | N67: =I67-K67+M67 -> 107578 | O67: =ROUND(N67*0.1,0) -> 10758 | Q67: =INDEX(Breakdown[],MATCH($D67,Breakdown[Dist],0),MATCH(Q$4,Breakdown[#Headers],0)) -> 24528 | R67: =INDEX(Breakdown[],MATCH($D67,Breakdown[Dist],0),MATCH(R$4,Breakdown[#Headers],0)) -> 19010 | S67: =SUM(Q67:R67) -> 43538 | T67: =L67-O67 -> 53282 | U67: =SUM(S67:T67) -> 96820 | W67: =O67/N67 -> 0.10000186 | X67: =U67/N67 -> 0.89999814
A68: 2026 | B68: 01 | C68: 01 | D68: 2763 | G68: 2763 | H68: Clayton Ridge | I68: =INDEX(Breakdown[],MATCH($D68,Breakdown[Dist],0),MATCH(I$4,Breakdown[#Headers],0)) -> 260838 | J68: =INDEX(Breakdown[],MATCH($D68,Breakdown[Dist],0),MATCH(J$4,Breakdown[#Headers],0)) -> 198149 | K68: =INDEX(Breakdown[],MATCH($D68,Breakdown[Dist],0),MATCH(K$4,Breakdown[#Headers],0)) -> 42440 | L68: =INDEX(Breakdown[],MATCH($D68,Breakdown[Dist],0),MATCH(L$4,Breakdown[#Headers],0)) -> 155709 | M68: =INDEX(Breakdown[],MATCH($D68,Breakdown[Dist],0),MATCH(M$4,Breakdown[#Headers],0)) -> 0 | N68: =I68-K68+M68 -> 218398 | O68: =ROUND(N68*0.1,0) -> 21840 | Q68: =INDEX(Breakdown[],MATCH($D68,Breakdown[Dist],0),MATCH(Q$4,Breakdown[#Headers],0)) -> 62689 | R68: =INDEX(Breakdown[],MATCH($D68,Breakdown[Dist],0),MATCH(R$4,Breakdown[#Headers],0)) -> 0 | S68: =SUM(Q68:R68) -> 62689 | T68: =L68-O68 -> 133869 | U68: =SUM(S68:T68) -> 196558 | W68: =O68/N68 -> 0.10000092 | X68: =U68/N68 -> 0.89999908
A69: 2026 | B69: 10 | C69: 10 | D69: 1221 | E69: 0216 | G69: 1221 | H69: Clear Creek-Amana | I69: =INDEX(Breakdown[],MATCH($D69,Breakdown[Dist],0),MATCH(I$4,Breakdown[#Headers],0)) -> 1226564 | J69: =INDEX(Breakdown[],MATCH($D69,Breakdown[Dist],0),MATCH(J$4,Breakdown[#Headers],0)) -> 972345 | K69: =INDEX(Breakdown[],MATCH($D69,Breakdown[Dist],0),MATCH(K$4,Breakdown[#Headers],0)) -> 208261 | L69: =INDEX(Breakdown[],MATCH($D69,Breakdown[Dist],0),MATCH(L$4,Breakdown[#Headers],0)) -> 764084 | M69: =INDEX(Breakdown[],MATCH($D69,Breakdown[Dist],0),MATCH(M$4,Breakdown[#Headers],0)) -> 0 | N69: =I69-K69+M69 -> 1018303 | O69: =ROUND(N69*0.1,0) -> 101830 | Q69: =INDEX(Breakdown[],MATCH($D69,Breakdown[Dist],0),MATCH(Q$4,Breakdown[#Headers],0)) -> 254219 | R69: =INDEX(Breakdown[],MATCH($D69,Breakdown[Dist],0),MATCH(R$4,Breakdown[#Headers],0)) -> 0 | S69: =SUM(Q69:R69) -> 254219 | T69: =L69-O69 -> 662254 | U69: =SUM(S69:T69) -> 916473 | W69: =O69/N69 -> 0.099999705 | X69: =U69/N69 -> 0.90000029
A70: 2026 | B70: 07 | C70: 07 | D70: 1233 | G70: 1233 | H70: Clear Lake | I70: =INDEX(Breakdown[],MATCH($D70,Breakdown[Dist],0),MATCH(I$4,Breakdown[#Headers],0)) -> 455395 | J70: =INDEX(Breakdown[],MATCH($D70,Breakdown[Dist],0),MATCH(J$4,Breakdown[#Headers],0)) -> 356625 | K70: =INDEX(Breakdown[],MATCH($D70,Breakdown[Dist],0),MATCH(K$4,Breakdown[#Headers],0)) -> 76383 | L70: =INDEX(Breakdown[],MATCH($D70,Breakdown[Dist],0),MATCH(L$4,Breakdown[#Headers],0)) -> 280242 | M70: =INDEX(Breakdown[],MATCH($D70,Breakdown[Dist],0),MATCH(M$4,Breakdown[#Headers],0)) -> 30 | N70: =I70-K70+M70 -> 379042 | O70: =ROUND(N70*0.1,0) -> 37904 | Q70: =INDEX(Breakdown[],MATCH($D70,Breakdown[Dist],0),MATCH(Q$4,Breakdown[#Headers],0)) -> 98770 | R70: =INDEX(Breakdown[],MATCH($D70,Breakdown[Dist],0),MATCH(R$4,Breakdown[#Headers],0)) -> 30 | S70: =SUM(Q70:R70) -> 98800 | T70: =L70-O70 -> 242338 | U70: =SUM(S70:T70) -> 341138 | W70: =O70/N70 -> 0.099999472 | X70: =U70/N70 -> 0.90000053
A71: 2026 | B71: 09 | C71: 09 | D71: 1278 | G71: 1278 | H71: Clinton | I71: =INDEX(Breakdown[],MATCH($D71,Breakdown[Dist],0),MATCH(I$4,Breakdown[#Headers],0)) -> 1534324 | J71: =INDEX(Breakdown[],MATCH($D71,Breakdown[Dist],0),MATCH(J$4,Breakdown[#Headers],0)) -> 1209647 | K71: =INDEX(Breakdown[],MATCH($D71,Breakdown[Dist],0),MATCH(K$4,Breakdown[#Headers],0)) -> 259087 | L71: =INDEX(Breakdown[],MATCH($D71,Breakdown[Dist],0),MATCH(L$4,Breakdown[#Headers],0)) -> 950560 | M71: =INDEX(Breakdown[],MATCH($D71,Breakdown[Dist],0),MATCH(M$4,Breakdown[#Headers],0)) -> 0 | N71: =I71-K71+M71 -> 1275237 | O71: =ROUND(N71*0.1,0) -> 127524 | Q71: =INDEX(Breakdown[],MATCH($D71,Breakdown[Dist],0),MATCH(Q$4,Breakdown[#Headers],0)) -> 324677 | R71: =INDEX(Breakdown[],MATCH($D71,Breakdown[Dist],0),MATCH(R$4,Breakdown[#Headers],0)) -> 0 | S71: =SUM(Q71:R71) -> 324677 | T71: =L71-O71 -> 823036 | U71: =SUM(S71:T71) -> 1147713 | W71: =O71/N71 -> 0.10000024 | X71: =U71/N71 -> 0.89999976
A72: 2026 | B72: 11 | C72: 11 | D72: 1332 | G72: 1332 | H72: Colfax-Mingo | I72: =INDEX(Breakdown[],MATCH($D72,Breakdown[Dist],0),MATCH(I$4,Breakdown[#Headers],0)) -> 268984 | J72: =INDEX(Breakdown[],MATCH($D72,Breakdown[Dist],0),MATCH(J$4,Breakdown[#Headers],0)) -> 217673 | K72: =INDEX(Breakdown[],MATCH($D72,Breakdown[Dist],0),MATCH(K$4,Breakdown[#Headers],0)) -> 46622 | L72: =INDEX(Breakdown[],MATCH($D72,Breakdown[Dist],0),MATCH(L$4,Breakdown[#Headers],0)) -> 171051 | M72: =INDEX(Breakdown[],MATCH($D72,Breakdown[Dist],0),MATCH(M$4,Breakdown[#Headers],0)) -> 2934 | N72: =I72-K72+M72 -> 225296 | O72: =ROUND(N72*0.1,0) -> 22530 | Q72: =INDEX(Breakdown[],MATCH($D72,Breakdown[Dist],0),MATCH(Q$4,Breakdown[#Headers],0)) -> 51311 | R72: =INDEX(Breakdown[],MATCH($D72,Breakdown[Dist],0),MATCH(R$4,Breakdown[#Headers],0)) -> 2934 | S72: =SUM(Q72:R72) -> 54245 | T72: =L72-O72 -> 148521 | U72: =SUM(S72:T72) -> 202766 | W72: =O72/N72 -> 0.10000178 | X72: =U72/N72 -> 0.89999822
A73: 2026 | B73: 10 | C73: 10 | D73: 1337 | G73: 1337 | H73: College Community | I73: =INDEX(Breakdown[],MATCH($D73,Breakdown[Dist],0),MATCH(I$4,Breakdown[#Headers],0)) -> 1983269 | J73: =INDEX(Breakdown[],MATCH($D73,Breakdown[Dist],0),MATCH(J$4,Breakdown[#Headers],0)) -> 1572215 | K73: =INDEX(Breakdown[],MATCH($D73,Breakdown[Dist],0),MATCH(K$4,Breakdown[#Headers],0)) -> 336743 | L73: =INDEX(Breakdown[],MATCH($D73,Breakdown[Dist],0),MATCH(L$4,Breakdown[#Headers],0)) -> 1235472 | M73: =INDEX(Breakdown[],MATCH($D73,Breakdown[Dist],0),MATCH(M$4,Breakdown[#Headers],0)) -> 0 | N73: =I73-K73+M73 -> 1646526 | O73: =ROUND(N73*0.1,0) -> 164653 | Q73: =INDEX(Breakdown[],MATCH($D73,Breakdown[Dist],0),MATCH(Q$4,Breakdown[#Headers],0)) -> 411054 | R73: =INDEX(Breakdown[],MATCH($D73,Breakdown[Dist],0),MATCH(R$4,Breakdown[#Headers],0)) -> 0 | S73: =SUM(Q73:R73) -> 411054 | T73: =L73-O73 -> 1070819 | U73: =SUM(S73:T73) -> 1481873 | W73: =O73/N73 -> 0.10000024 | X73: =U73/N73 -> 0.89999976
A74: 2026 | B74: 11 | C74: 11 | D74: 1350 | G74: 1350 | H74: Collins-Maxwell | I74: =INDEX(Breakdown[],MATCH($D74,Breakdown[Dist],0),MATCH(I$4,Breakdown[#Headers],0)) -> 162457 | J74: =INDEX(Breakdown[],MATCH($D74,Breakdown[Dist],0),MATCH(J$4,Breakdown[#Headers],0)) -> 131467 | K74: =INDEX(Breakdown[],MATCH($D74,Breakdown[Dist],0),MATCH(K$4,Breakdown[#Headers],0)) -> 28158 | L74: =INDEX(Breakdown[],MATCH($D74,Breakdown[Dist],0),MATCH(L$4,Breakdown[#Headers],0)) -> 103309 | M74: =INDEX(Breakdown[],MATCH($D74,Breakdown[Dist],0),MATCH(M$4,Breakdown[#Headers],0)) -> 9406 | N74: =I74-K74+M74 -> 143705 | O74: =ROUND(N74*0.1,0) -> 14371 | Q74: =INDEX(Breakdown[],MATCH($D74,Breakdown[Dist],0),MATCH(Q$4,Breakdown[#Headers],0)) -> 30990 | R74: =INDEX(Breakdown[],MATCH($D74,Breakdown[Dist],0),MATCH(R$4,Breakdown[#Headers],0)) -> 9406 | S74: =SUM(Q74:R74) -> 40396 | T74: =L74-O74 -> 88938 | U74: =SUM(S74:T74) -> 129334 | W74: =O74/N74 -> 0.10000348 | X74: =U74/N74 -> 0.89999652
A75: 2026 | B75: 11 | C75: 11 | D75: 1359 | G75: 1359 | H75: Colo-Nesco | I75: =INDEX(Breakdown[],MATCH($D75,Breakdown[Dist],0),MATCH(I$4,Breakdown[#Headers],0)) -> 175155 | J75: =INDEX(Breakdown[],MATCH($D75,Breakdown[Dist],0),MATCH(J$4,Breakdown[#Headers],0)) -> 141743 | K75: =INDEX(Breakdown[],MATCH($D75,Breakdown[Dist],0),MATCH(K$4,Breakdown[#Headers],0)) -> 30359 | L75: =INDEX(Breakdown[],MATCH($D75,Breakdown[Dist],0),MATCH(L$4,Breakdown[#Headers],0)) -> 111384 | M75: =INDEX(Breakdown[],MATCH($D75,Breakdown[Dist],0),MATCH(M$4,Breakdown[#Headers],0)) -> 0 | N75: =I75-K75+M75 -> 144796 | O75: =ROUND(N75*0.1,0) -> 14480 | Q75: =INDEX(Breakdown[],MATCH($D75,Breakdown[Dist],0),MATCH(Q$4,Breakdown[#Headers],0)) -> 33412 | R75: =INDEX(Breakdown[],MATCH($D75,Breakdown[Dist],0),MATCH(R$4,Breakdown[#Headers],0)) -> 0 | S75: =SUM(Q75:R75) -> 33412 | T75: =L75-O75 -> 96904 | U75: =SUM(S75:T75) -> 130316 | W75: =O75/N75 -> 0.10000276 | X75: =U75/N75 -> 0.89999724
A76: 2026 | B76: 09 | C76: 09 | D76: 1368 | G76: 1368 | H76: Columbus | I76: =INDEX(Breakdown[],MATCH($D76,Breakdown[Dist],0),MATCH(I$4,Breakdown[#Headers],0)) -> 309058 | J76: =INDEX(Breakdown[],MATCH($D76,Breakdown[Dist],0),MATCH(J$4,Breakdown[#Headers],0)) -> 243658 | K76: =INDEX(Breakdown[],MATCH($D76,Breakdown[Dist],0),MATCH(K$4,Breakdown[#Headers],0)) -> 52187 | L76: =INDEX(Breakdown[],MATCH($D76,Breakdown[Dist],0),MATCH(L$4,Breakdown[#Headers],0)) -> 191471 | M76: =INDEX(Breakdown[],MATCH($D76,Breakdown[Dist],0),MATCH(M$4,Breakdown[#Headers],0)) -> 0 | N76: =I76-K76+M76 -> 256871 | O76: =ROUND(N76*0.1,0) -> 25687 | Q76: =INDEX(Breakdown[],MATCH($D76,Breakdown[Dist],0),MATCH(Q$4,Breakdown[#Headers],0)) -> 65400 | R76: =INDEX(Breakdown[],MATCH($D76,Breakdown[Dist],0),MATCH(R$4,Breakdown[#Headers],0)) -> 0 | S76: =SUM(Q76:R76) -> 65400 | T76: =L76-O76 -> 165784 | U76: =SUM(S76:T76) -> 231184 | W76: =O76/N76 -> 0.099999611 | X76: =U76/N76 -> 0.90000039
A77: 2026 | B77: 11 | C77: 11 | D77: 1413 | G77: 1413 | H77: Coon Rapids-Bayard | I77: =INDEX(Breakdown[],MATCH($D77,Breakdown[Dist],0),MATCH(I$4,Breakdown[#Headers],0)) -> 174350 | J77: =INDEX(Breakdown[],MATCH($D77,Breakdown[Dist],0),MATCH(J$4,Breakdown[#Headers],0)) -> 141091 | K77: =INDEX(Breakdown[],MATCH($D77,Breakdown[Dist],0),MATCH(K$4,Breakdown[#Headers],0)) -> 30220 | L77: =INDEX(Breakdown[],MATCH($D77,Breakdown[Dist],0),MATCH(L$4,Breakdown[#Headers],0)) -> 110871 | M77: =INDEX(Breakdown[],MATCH($D77,Breakdown[Dist],0),MATCH(M$4,Breakdown[#Headers],0)) -> 0 | N77: =I77-K77+M77 -> 144130 | O77: =ROUND(N77*0.1,0) -> 14413 | Q77: =INDEX(Breakdown[],MATCH($D77,Breakdown[Dist],0),MATCH(Q$4,Breakdown[#Headers],0)) -> 33259 | R77: =INDEX(Breakdown[],MATCH($D77,Breakdown[Dist],0),MATCH(R$4,Breakdown[#Headers],0)) -> 0 | S77: =SUM(Q77:R77) -> 33259 | T77: =L77-O77 -> 96458 | U77: =SUM(S77:T77) -> 129717 | W77: =O77/N77 -> 0.1 | X77: =U77/N77 -> 0.9
A78: 2026 | B78: 13 | C78: 13 | D78: 1431 | G78: 1431 | H78: Corning | I78: =INDEX(Breakdown[],MATCH($D78,Breakdown[Dist],0),MATCH(I$4,Breakdown[#Headers],0)) -> 158940 | J78: =INDEX(Breakdown[],MATCH($D78,Breakdown[Dist],0),MATCH(J$4,Breakdown[#Headers],0)) -> 125652 | K78: =INDEX(Breakdown[],MATCH($D78,Breakdown[Dist],0),MATCH(K$4,Breakdown[#Headers],0)) -> 26913 | L78: =INDEX(Breakdown[],MATCH($D78,Breakdown[Dist],0),MATCH(L$4,Breakdown[#Headers],0)) -> 98739 | M78: =INDEX(Breakdown[],MATCH($D78,Breakdown[Dist],0),MATCH(M$4,Breakdown[#Headers],0)) -> 0 | N78: =I78-K78+M78 -> 132027 | O78: =ROUND(N78*0.1,0) -> 13203 | Q78: =INDEX(Breakdown[],MATCH($D78,Breakdown[Dist],0),MATCH(Q$4,Breakdown[#Headers],0)) -> 33288 | R78: =INDEX(Breakdown[],MATCH($D78,Breakdown[Dist],0),MATCH(R$4,Breakdown[#Headers],0)) -> 0 | S78: =SUM(Q78:R78) -> 33288 | T78: =L78-O78 -> 85536 | U78: =SUM(S78:T78) -> 118824 | W78: =O78/N78 -> 0.10000227 | X78: =U78/N78 -> 0.89999773
A79: 2026 | B79: 13 | C79: 13 | D79: 1476 | G79: 1476 | H79: Council Bluffs | I79: =INDEX(Breakdown[],MATCH($D79,Breakdown[Dist],0),MATCH(I$4,Breakdown[#Headers],0)) -> 3701325 | J79: =INDEX(Breakdown[],MATCH($D79,Breakdown[Dist],0),MATCH(J$4,Breakdown[#Headers],0)) -> 2926116 | K79: =INDEX(Breakdown[],MATCH($D79,Breakdown[Dist],0),MATCH(K$4,Breakdown[#Headers],0)) -> 626727 | L79: =INDEX(Breakdown[],MATCH($D79,Breakdown[Dist],0),MATCH(L$4,Breakdown[#Headers],0)) -> 2299389 | M79: =INDEX(Breakdown[],MATCH($D79,Breakdown[Dist],0),MATCH(M$4,Breakdown[#Headers],0)) -> 14980 | N79: =I79-K79+M79 -> 3089578 | O79: =ROUND(N79*0.1,0) -> 308958 | Q79: =INDEX(Breakdown[],MATCH($D79,Breakdown[Dist],0),MATCH(Q$4,Breakdown[#Headers],0)) -> 775209 | R79: =INDEX(Breakdown[],MATCH($D79,Breakdown[Dist],0),MATCH(R$4,Breakdown[#Headers],0)) -> 14980 | S79: =SUM(Q79:R79) -> 790189 | T79: =L79-O79 -> 1990431 | U79: =SUM(S79:T79) -> 2780620 | W79: =O79/N79 -> 0.10000006 | X79: =U79/N79 -> 0.89999994
A80: 2026 | B80: 13 | C80: 13 | D80: 1503 | G80: 1503 | H80: Creston | I80: =INDEX(Breakdown[],MATCH($D80,Breakdown[Dist],0),MATCH(I$4,Breakdown[#Headers],0)) -> 526742 | J80: =INDEX(Breakdown[],MATCH($D80,Breakdown[Dist],0),MATCH(J$4,Breakdown[#Headers],0)) -> 416421 | K80: =INDEX(Breakdown[],MATCH($D80,Breakdown[Dist],0),MATCH(K$4,Breakdown[#Headers],0)) -> 89190 | L80: =INDEX(Breakdown[],MATCH($D80,Breakdown[Dist],0),MATCH(L$4,Breakdown[#Headers],0)) -> 327231 | M80: =INDEX(Breakdown[],MATCH($D80,Breakdown[Dist],0),MATCH(M$4,Breakdown[#Headers],0)) -> 7198 | N80: =I80-K80+M80 -> 444750 | O80: =ROUND(N80*0.1,0) -> 44475 | Q80: =INDEX(Breakdown[],MATCH($D80,Breakdown[Dist],0),MATCH(Q$4,Breakdown[#Headers],0)) -> 110321 | R80: =INDEX(Breakdown[],MATCH($D80,Breakdown[Dist],0),MATCH(R$4,Breakdown[#Headers],0)) -> 7198 | S80: =SUM(Q80:R80) -> 117519 | T80: =L80-O80 -> 282756 | U80: =SUM(S80:T80) -> 400275 | W80: =O80/N80 -> 0.1 | X80: =U80/N80 -> 0.9
A81: 2026 | B81: 11 | C81: 11 | D81: 1576 | G81: 1576 | H81: Dallas Center-Grimes | I81: =INDEX(Breakdown[],MATCH($D81,Breakdown[Dist],0),MATCH(I$4,Breakdown[#Headers],0)) -> 1311314 | J81: =INDEX(Breakdown[],MATCH($D81,Breakdown[Dist],0),MATCH(J$4,Breakdown[#Headers],0)) -> 1061170 | K81: =INDEX(Breakdown[],MATCH($D81,Breakdown[Dist],0),MATCH(K$4,Breakdown[#Headers],0)) -> 227286 | L81: =INDEX(Breakdown[],MATCH($D81,Breakdown[Dist],0),MATCH(L$4,Breakdown[#Headers],0)) -> 833884 | M81: =INDEX(Breakdown[],MATCH($D81,Breakdown[Dist],0),MATCH(M$4,Breakdown[#Headers],0)) -> 0 | N81: =I81-K81+M81 -> 1084028 | O81: =ROUND(N81*0.1,0) -> 108403 | Q81: =INDEX(Breakdown[],MATCH($D81,Breakdown[Dist],0),MATCH(Q$4,Breakdown[#Headers],0)) -> 250144 | R81: =INDEX(Breakdown[],MATCH($D81,Breakdown[Dist],0),MATCH(R$4,Breakdown[#Headers],0)) -> 0 | S81: =SUM(Q81:R81) -> 250144 | T81: =L81-O81 -> 725481 | U81: =SUM(S81:T81) -> 975625 | W81: =O81/N81 -> 0.10000018 | X81: =U81/N81 -> 0.89999982
... A269: 2026 | B269: 11 | C269: 11 | D269: 6094 | G269: 6094 | H269: Southeast Warren | I269: =INDEX(Breakdown[],MATCH($D269,Breakdown[Dist],0),MATCH(I$4,Breakdown[#Headers],0)) -> 183732 | J269: =INDEX(Breakdown[],MATCH($D269,Breakdown[Dist],0),MATCH(J$4,Breakdown[#Headers],0)) -> 148684 | K269: =INDEX(Breakdown[],MATCH($D269,Breakdown[Dist],0),MATCH(K$4,Breakdown[#Headers],0)) -> 31846 | L269: =INDEX(Breakdown[],MATCH($D269,Breakdown[Dist],0),MATCH(L$4,Breakdown[#Headers],0)) -> 116838 | M269: =INDEX(Breakdown[],MATCH($D269,Breakdown[Dist],0),MATCH(M$4,Breakdown[#Headers],0)) -> 6824 | N269: =I269-K269+M269 -> 158710 | O269: =ROUND(N269*0.1,0) -> 15871 | Q269: =INDEX(Breakdown[],MATCH($D269,Breakdown[Dist],0),MATCH(Q$4,Breakdown[#Headers],0)) -> 35048 | R269: =INDEX(Breakdown[],MATCH($D269,Breakdown[Dist],0),MATCH(R$4,Breakdown[#Headers],0)) -> 6824 | S269: =SUM(Q269:R269) -> 41872 | T269: =L269-O269 -> 100967 | U269: =SUM(S269:T269) -> 142839 | W269: =O269/N269 -> 0.1 | X269: =U269/N269 -> 0.9
A270: 2026 | B270: 05 | C270: 05 | D270: 6096 | E270: 5323 | G270: 6096 | H270: Southeast Valley | I270: =INDEX(Breakdown[],MATCH($D270,Breakdown[Dist],0),MATCH(I$4,Breakdown[#Headers],0)) -> 441100 | J270: =INDEX(Breakdown[],MATCH($D270,Breakdown[Dist],0),MATCH(J$4,Breakdown[#Headers],0)) -> 339052 | K270: =INDEX(Breakdown[],MATCH($D270,Breakdown[Dist],0),MATCH(K$4,Breakdown[#Headers],0)) -> 72619 | L270: =INDEX(Breakdown[],MATCH($D270,Breakdown[Dist],0),MATCH(L$4,Breakdown[#Headers],0)) -> 266433 | M270: =INDEX(Breakdown[],MATCH($D270,Breakdown[Dist],0),MATCH(M$4,Breakdown[#Headers],0)) -> 0 | N270: =I270-K270+M270 -> 368481 | O270: =ROUND(N270*0.1,0) -> 36848 | Q270: =INDEX(Breakdown[],MATCH($D270,Breakdown[Dist],0),MATCH(Q$4,Breakdown[#Headers],0)) -> 102048 | R270: =INDEX(Breakdown[],MATCH($D270,Breakdown[Dist],0),MATCH(R$4,Breakdown[#Headers],0)) -> 0 | S270: =SUM(Q270:R270) -> 102048 | T270: =L270-O270 -> 229585 | U270: =SUM(S270:T270) -> 331633 | W270: =O270/N270 -> 0.099999729 | X270: =U270/N270 -> 0.90000027
A271: 2026 | B271: 05 | C271: 05 | D271: 6102 | G271: 6102 | H271: Spencer | I271: =INDEX(Breakdown[],MATCH($D271,Breakdown[Dist],0),MATCH(I$4,Breakdown[#Headers],0)) -> 818166 | J271: =INDEX(Breakdown[],MATCH($D271,Breakdown[Dist],0),MATCH(J$4,Breakdown[#Headers],0)) -> 628885 | K271: =INDEX(Breakdown[],MATCH($D271,Breakdown[Dist],0),MATCH(K$4,Breakdown[#Headers],0)) -> 134697 | L271: =INDEX(Breakdown[],MATCH($D271,Breakdown[Dist],0),MATCH(L$4,Breakdown[#Headers],0)) -> 494188 | M271: =INDEX(Breakdown[],MATCH($D271,Breakdown[Dist],0),MATCH(M$4,Breakdown[#Headers],0)) -> 20254 | N271: =I271-K271+M271 -> 703723 | O271: =ROUND(N271*0.1,0) -> 70372 | Q271: =INDEX(Breakdown[],MATCH($D271,Breakdown[Dist],0),MATCH(Q$4,Breakdown[#Headers],0)) -> 189281 | R271: =INDEX(Breakdown[],MATCH($D271,Breakdown[Dist],0),MATCH(R$4,Breakdown[#Headers],0)) -> 20254 | S271: =SUM(Q271:R271) -> 209535 | T271: =L271-O271 -> 423816 | U271: =SUM(S271:T271) -> 633351 | W271: =O271/N271 -> 0.099999574 | X271: =U271/N271 -> 0.90000043
A272: 2026 | B272: 05 | C272: 05 | D272: 6120 | G272: 6120 | H272: Spirit Lake | I272: =INDEX(Breakdown[],MATCH($D272,Breakdown[Dist],0),MATCH(I$4,Breakdown[#Headers],0)) -> 457186 | J272: =INDEX(Breakdown[],MATCH($D272,Breakdown[Dist],0),MATCH(J$4,Breakdown[#Headers],0)) -> 351417 | K272: =INDEX(Breakdown[],MATCH($D272,Breakdown[Dist],0),MATCH(K$4,Breakdown[#Headers],0)) -> 75268 | L272: =INDEX(Breakdown[],MATCH($D272,Breakdown[Dist],0),MATCH(L$4,Breakdown[#Headers],0)) -> 276149 | M272: =INDEX(Breakdown[],MATCH($D272,Breakdown[Dist],0),MATCH(M$4,Breakdown[#Headers],0)) -> 0 | N272: =I272-K272+M272 -> 381918 | O272: =ROUND(N272*0.1,0) -> 38192 | Q272: =INDEX(Breakdown[],MATCH($D272,Breakdown[Dist],0),MATCH(Q$4,Breakdown[#Headers],0)) -> 105769 | R272: =INDEX(Breakdown[],MATCH($D272,Breakdown[Dist],0),MATCH(R$4,Breakdown[#Headers],0)) -> 0 | S272: =SUM(Q272:R272) -> 105769 | T272: =L272-O272 -> 237957 | U272: =SUM(S272:T272) -> 343726 | W272: =O272/N272 -> 0.10000052 | X272: =U272/N272 -> 0.89999948
A273: 2026 | B273: 10 | C273: 10 | D273: 6138 | G273: 6138 | H273: Springville | I273: =INDEX(Breakdown[],MATCH($D273,Breakdown[Dist],0),MATCH(I$4,Breakdown[#Headers],0)) -> 152975 | J273: =INDEX(Breakdown[],MATCH($D273,Breakdown[Dist],0),MATCH(J$4,Breakdown[#Headers],0)) -> 121269 | K273: =INDEX(Breakdown[],MATCH($D273,Breakdown[Dist],0),MATCH(K$4,Breakdown[#Headers],0)) -> 25974 | L273: =INDEX(Breakdown[],MATCH($D273,Breakdown[Dist],0),MATCH(L$4,Breakdown[#Headers],0)) -> 95295 | M273: =INDEX(Breakdown[],MATCH($D273,Breakdown[Dist],0),MATCH(M$4,Breakdown[#Headers],0)) -> 0 | N273: =I273-K273+M273 -> 127001 | O273: =ROUND(N273*0.1,0) -> 12700 | Q273: =INDEX(Breakdown[],MATCH($D273,Breakdown[Dist],0),MATCH(Q$4,Breakdown[#Headers],0)) -> 31706 | R273: =INDEX(Breakdown[],MATCH($D273,Breakdown[Dist],0),MATCH(R$4,Breakdown[#Headers],0)) -> 0 | S273: =SUM(Q273:R273) -> 31706 | T273: =L273-O273 -> 82595 | U273: =SUM(S273:T273) -> 114301 | W273: =O273/N273 -> 0.099999213 | X273: =U273/N273 -> 0.90000079
A274: 2026 | B274: 07 | C274: 07 | D274: 5751 | G274: 5751 | H274: St Ansgar | I274: =INDEX(Breakdown[],MATCH($D274,Breakdown[Dist],0),MATCH(I$4,Breakdown[#Headers],0)) -> 239797 | J274: =INDEX(Breakdown[],MATCH($D274,Breakdown[Dist],0),MATCH(J$4,Breakdown[#Headers],0)) -> 187788 | K274: =INDEX(Breakdown[],MATCH($D274,Breakdown[Dist],0),MATCH(K$4,Breakdown[#Headers],0)) -> 40221 | L274: =INDEX(Breakdown[],MATCH($D274,Breakdown[Dist],0),MATCH(L$4,Breakdown[#Headers],0)) -> 147567 | M274: =INDEX(Breakdown[],MATCH($D274,Breakdown[Dist],0),MATCH(M$4,Breakdown[#Headers],0)) -> 0 | N274: =I274-K274+M274 -> 199576 | O274: =ROUND(N274*0.1,0) -> 19958 | Q274: =INDEX(Breakdown[],MATCH($D274,Breakdown[Dist],0),MATCH(Q$4,Breakdown[#Headers],0)) -> 52009 | R274: =INDEX(Breakdown[],MATCH($D274,Breakdown[Dist],0),MATCH(R$4,Breakdown[#Headers],0)) -> 0 | S274: =SUM(Q274:R274) -> 52009 | T274: =L274-O274 -> 127609 | U274: =SUM(S274:T274) -> 179618 | W274: =O274/N274 -> 0.100002 | X274: =U274/N274 -> 0.899998
A275: 2026 | B275: 13 | C275: 13 | D275: 6165 | G275: 6165 | H275: Stanton | I275: =INDEX(Breakdown[],MATCH($D275,Breakdown[Dist],0),MATCH(I$4,Breakdown[#Headers],0)) -> 78576 | J275: =INDEX(Breakdown[],MATCH($D275,Breakdown[Dist],0),MATCH(J$4,Breakdown[#Headers],0)) -> 62119 | K275: =INDEX(Breakdown[],MATCH($D275,Breakdown[Dist],0),MATCH(K$4,Breakdown[#Headers],0)) -> 13305 | L275: =INDEX(Breakdown[],MATCH($D275,Breakdown[Dist],0),MATCH(L$4,Breakdown[#Headers],0)) -> 48814 | M275: =INDEX(Breakdown[],MATCH($D275,Breakdown[Dist],0),MATCH(M$4,Breakdown[#Headers],0)) -> 0 | N275: =I275-K275+M275 -> 65271 | O275: =ROUND(N275*0.1,0) -> 6527 | Q275: =INDEX(Breakdown[],MATCH($D275,Breakdown[Dist],0),MATCH(Q$4,Breakdown[#Headers],0)) -> 16457 | R275: =INDEX(Breakdown[],MATCH($D275,Breakdown[Dist],0),MATCH(R$4,Breakdown[#Headers],0)) -> 0 | S275: =SUM(Q275:R275) -> 16457 | T275: =L275-O275 -> 42287 | U275: =SUM(S275:T275) -> 58744 | W275: =O275/N275 -> 0.099998468 | X275: =U275/N275 -> 0.90000153
A276: 2026 | B276: 01 | C276: 01 | D276: 6175 | G276: 6175 | H276: Starmont | I276: =INDEX(Breakdown[],MATCH($D276,Breakdown[Dist],0),MATCH(I$4,Breakdown[#Headers],0)) -> 234185 | J276: =INDEX(Breakdown[],MATCH($D276,Breakdown[Dist],0),MATCH(J$4,Breakdown[#Headers],0)) -> 177901 | K276: =INDEX(Breakdown[],MATCH($D276,Breakdown[Dist],0),MATCH(K$4,Breakdown[#Headers],0)) -> 38103 | L276: =INDEX(Breakdown[],MATCH($D276,Breakdown[Dist],0),MATCH(L$4,Breakdown[#Headers],0)) -> 139798 | M276: =INDEX(Breakdown[],MATCH($D276,Breakdown[Dist],0),MATCH(M$4,Breakdown[#Headers],0)) -> 7751 | N276: =I276-K276+M276 -> 203833 | O276: =ROUND(N276*0.1,0) -> 20383 | Q276: =INDEX(Breakdown[],MATCH($D276,Breakdown[Dist],0),MATCH(Q$4,Breakdown[#Headers],0)) -> 56284 | R276: =INDEX(Breakdown[],MATCH($D276,Breakdown[Dist],0),MATCH(R$4,Breakdown[#Headers],0)) -> 7751 | S276: =SUM(Q276:R276) -> 64035 | T276: =L276-O276 -> 119415 | U276: =SUM(S276:T276) -> 183450 | W276: =O276/N276 -> 0.099998528 | X276: =U276/N276 -> 0.90000147
A277: 2026 | B277: 05 | C277: 05 | D277: 6219 | G277: 6219 | H277: Storm Lake | I277: =INDEX(Breakdown[],MATCH($D277,Breakdown[Dist],0),MATCH(I$4,Breakdown[#Headers],0)) -> 1089490 | J277: =INDEX(Breakdown[],MATCH($D277,Breakdown[Dist],0),MATCH(J$4,Breakdown[#Headers],0)) -> 837439 | K277: =INDEX(Breakdown[],MATCH($D277,Breakdown[Dist],0),MATCH(K$4,Breakdown[#Headers],0)) -> 179366 | L277: =INDEX(Breakdown[],MATCH($D277,Breakdown[Dist],0),MATCH(L$4,Breakdown[#Headers],0)) -> 658073 | M277: =INDEX(Breakdown[],MATCH($D277,Breakdown[Dist],0),MATCH(M$4,Breakdown[#Headers],0)) -> 0 | N277: =I277-K277+M277 -> 910124 | O277: =ROUND(N277*0.1,0) -> 91012 | Q277: =INDEX(Breakdown[],MATCH($D277,Breakdown[Dist],0),MATCH(Q$4,Breakdown[#Headers],0)) -> 252051 | R277: =INDEX(Breakdown[],MATCH($D277,Breakdown[Dist],0),MATCH(R$4,Breakdown[#Headers],0)) -> 0 | S277: =SUM(Q277:R277) -> 252051 | T277: =L277-O277 -> 567061 | U277: =SUM(S277:T277) -> 819112 | W277: =O277/N277 -> 0.09999956 | X277: =U277/N277 -> 0.90000044
A278: 2026 | B278: 05 | C278: 05 | D278: 6246 | G278: 6246 | H278: Stratford | I278: =INDEX(Breakdown[],MATCH($D278,Breakdown[Dist],0),MATCH(I$4,Breakdown[#Headers],0)) -> 56410 | J278: =INDEX(Breakdown[],MATCH($D278,Breakdown[Dist],0),MATCH(J$4,Breakdown[#Headers],0)) -> 43360 | K278: =INDEX(Breakdown[],MATCH($D278,Breakdown[Dist],0),MATCH(K$4,Breakdown[#Headers],0)) -> 9287 | L278: =INDEX(Breakdown[],MATCH($D278,Breakdown[Dist],0),MATCH(L$4,Breakdown[#Headers],0)) -> 34073 | M278: =INDEX(Breakdown[],MATCH($D278,Breakdown[Dist],0),MATCH(M$4,Breakdown[#Headers],0)) -> 7101 | N278: =I278-K278+M278 -> 54224 | O278: =ROUND(N278*0.1,0) -> 5422 | Q278: =INDEX(Breakdown[],MATCH($D278,Breakdown[Dist],0),MATCH(Q$4,Breakdown[#Headers],0)) -> 13050 | R278: =INDEX(Breakdown[],MATCH($D278,Breakdown[Dist],0),MATCH(R$4,Breakdown[#Headers],0)) -> 7101 | S278: =SUM(Q278:R278) -> 20151 | T278: =L278-O278 -> 28651 | U278: =SUM(S278:T278) -> 48802 | W278: =O278/N278 -> 0.099992623 | X278: =U278/N278 -> 0.90000738
A279: 2026 | B279: 07 | C279: 07 | D279: 6273 | G279: 6273 | H279: Sumner-Fredericksburg | I279: =INDEX(Breakdown[],MATCH($D279,Breakdown[Dist],0),MATCH(I$4,Breakdown[#Headers],0)) -> 314087 | J279: =INDEX(Breakdown[],MATCH($D279,Breakdown[Dist],0),MATCH(J$4,Breakdown[#Headers],0)) -> 245966 | K279: =INDEX(Breakdown[],MATCH($D279,Breakdown[Dist],0),MATCH(K$4,Breakdown[#Headers],0)) -> 52682 | L279: =INDEX(Breakdown[],MATCH($D279,Breakdown[Dist],0),MATCH(L$4,Breakdown[#Headers],0)) -> 193284 | M279: =INDEX(Breakdown[],MATCH($D279,Breakdown[Dist],0),MATCH(M$4,Breakdown[#Headers],0)) -> 637 | N279: =I279-K279+M279 -> 262042 | O279: =ROUND(N279*0.1,0) -> 26204 | Q279: =INDEX(Breakdown[],MATCH($D279,Breakdown[Dist],0),MATCH(Q$4,Breakdown[#Headers],0)) -> 68121 | R279: =INDEX(Breakdown[],MATCH($D279,Breakdown[Dist],0),MATCH(R$4,Breakdown[#Headers],0)) -> 637 | S279: =SUM(Q279:R279) -> 68758 | T279: =L279-O279 -> 167080 | U279: =SUM(S279:T279) -> 235838 | W279: =O279/N279 -> 0.099999237 | X279: =U279/N279 -> 0.90000076
A280: 2026 | B280: 10 | C280: 10 | D280: 6408 | G280: 6408 | H280: Tipton | I280: =INDEX(Breakdown[],MATCH($D280,Breakdown[Dist],0),MATCH(I$4,Breakdown[#Headers],0)) -> 301527 | J280: =INDEX(Breakdown[],MATCH($D280,Breakdown[Dist],0),MATCH(J$4,Breakdown[#Headers],0)) -> 239033 | K280: =INDEX(Breakdown[],MATCH($D280,Breakdown[Dist],0),MATCH(K$4,Breakdown[#Headers],0)) -> 51197 | L280: =INDEX(Breakdown[],MATCH($D280,Breakdown[Dist],0),MATCH(L$4,Breakdown[#Headers],0)) -> 187836 | M280: =INDEX(Breakdown[],MATCH($D280,Breakdown[Dist],0),MATCH(M$4,Breakdown[#Headers],0)) -> 18507 | N280: =I280-K280+M280 -> 268837 | O280: =ROUND(N280*0.1,0) -> 26884 | Q280: =INDEX(Breakdown[],MATCH($D280,Breakdown[Dist],0),MATCH(Q$4,Breakdown[#Headers],0)) -> 62494 | R280: =INDEX(Breakdown[],MATCH($D280,Breakdown[Dist],0),MATCH(R$4,Breakdown[#Headers],0)) -> 18507 | S280: =SUM(Q280:R280) -> 81001 | T280: =L280-O280 -> 160952 | U280: =SUM(S280:T280) -> 241953 | W280: =O280/N280 -> 0.10000112 | X280: =U280/N280 -> 0.89999888
A281: 2026 | B281: 13 | C281: 13 | D281: 6453 | G281: 6453 | H281: Treynor | I281: =INDEX(Breakdown[],MATCH($D281,Breakdown[Dist],0),MATCH(I$4,Breakdown[#Headers],0)) -> 214932 | J281: =INDEX(Breakdown[],MATCH($D281,Breakdown[Dist],0),MATCH(J$4,Breakdown[#Headers],0)) -> 169917 | K281: =INDEX(Breakdown[],MATCH($D281,Breakdown[Dist],0),MATCH(K$4,Breakdown[#Headers],0)) -> 36393 | L281: =INDEX(Breakdown[],MATCH($D281,Breakdown[Dist],0),MATCH(L$4,Breakdown[#Headers],0)) -> 133524 | M281: =INDEX(Breakdown[],MATCH($D281,Breakdown[Dist],0),MATCH(M$4,Breakdown[#Headers],0)) -> 0 | N281: =I281-K281+M281 -> 178539 | O281: =ROUND(N281*0.1,0) -> 17854 | Q281: =INDEX(Breakdown[],MATCH($D281,Breakdown[Dist],0),MATCH(Q$4,Breakdown[#Headers],0)) -> 45015 | R281: =INDEX(Breakdown[],MATCH($D281,Breakdown[Dist],0),MATCH(R$4,Breakdown[#Headers],0)) -> 0 | S281: =SUM(Q281:R281) -> 45015 | T281: =L281-O281 -> 115670 | U281: =SUM(S281:T281) -> 160685 | W281: =O281/N281 -> 0.10000056 | X281: =U281/N281 -> 0.89999944
A282: 2026 | B282: 13 | C282: 13 | D282: 6460 | G282: 6460 | H282: Tri-Center | I282: =INDEX(Breakdown[],MATCH($D282,Breakdown[Dist],0),MATCH(I$4,Breakdown[#Headers],0)) -> 257801 | J282: =INDEX(Breakdown[],MATCH($D282,Breakdown[Dist],0),MATCH(J$4,Breakdown[#Headers],0)) -> 203807 | K282: =INDEX(Breakdown[],MATCH($D282,Breakdown[Dist],0),MATCH(K$4,Breakdown[#Headers],0)) -> 43653 | L282: =INDEX(Breakdown[],MATCH($D282,Breakdown[Dist],0),MATCH(L$4,Breakdown[#Headers],0)) -> 160154 | M282: =INDEX(Breakdown[],MATCH($D282,Breakdown[Dist],0),MATCH(M$4,Breakdown[#Headers],0)) -> 0 | N282: =I282-K282+M282 -> 214148 | O282: =ROUND(N282*0.1,0) -> 21415 | Q282: =INDEX(Breakdown[],MATCH($D282,Breakdown[Dist],0),MATCH(Q$4,Breakdown[#Headers],0)) -> 53994 | R282: =INDEX(Breakdown[],MATCH($D282,Breakdown[Dist],0),MATCH(R$4,Breakdown[#Headers],0)) -> 0 | S282: =SUM(Q282:R282) -> 53994 | T282: =L282-O282 -> 138739 | U282: =SUM(S282:T282) -> 192733 | W282: =O282/N282 -> 0.10000093 | X282: =U282/N282 -> 0.89999907
... A303: 2026 | B303: 15 | C303: 15 | D303: 6854 | G303: 6854 | H303: Wayne | I303: =INDEX(Breakdown[],MATCH($D303,Breakdown[Dist],0),MATCH(I$4,Breakdown[#Headers],0)) -> 219000 | J303: =INDEX(Breakdown[],MATCH($D303,Breakdown[Dist],0),MATCH(J$4,Breakdown[#Headers],0)) -> 174451 | K303: =INDEX(Breakdown[],MATCH($D303,Breakdown[Dist],0),MATCH(K$4,Breakdown[#Headers],0)) -> 37365 | L303: =INDEX(Breakdown[],MATCH($D303,Breakdown[Dist],0),MATCH(L$4,Breakdown[#Headers],0)) -> 137086 | M303: =INDEX(Breakdown[],MATCH($D303,Breakdown[Dist],0),MATCH(M$4,Breakdown[#Headers],0)) -> 6776 | N303: =I303-K303+M303 -> 188411 | O303: =ROUND(N303*0.1,0) -> 18841 | Q303: =INDEX(Breakdown[],MATCH($D303,Breakdown[Dist],0),MATCH(Q$4,Breakdown[#Headers],0)) -> 44549 | R303: =INDEX(Breakdown[],MATCH($D303,Breakdown[Dist],0),MATCH(R$4,Breakdown[#Headers],0)) -> 6776 | S303: =SUM(Q303:R303) -> 51325 | T303: =L303-O303 -> 118245 | U303: =SUM(S303:T303) -> 169570 | W303: =O303/N303 -> 0.099999469 | X303: =U303/N303 -> 0.90000053
A304: 2026 | B304: 05 | C304: 05 | D304: 6867 | E304: 4775 | G304: 6867 | H304: Webster City | I304: =INDEX(Breakdown[],MATCH($D304,Breakdown[Dist],0),MATCH(I$4,Breakdown[#Headers],0)) -> 692786 | J304: =INDEX(Breakdown[],MATCH($D304,Breakdown[Dist],0),MATCH(J$4,Breakdown[#Headers],0)) -> 532512 | K304: =INDEX(Breakdown[],MATCH($D304,Breakdown[Dist],0),MATCH(K$4,Breakdown[#Headers],0)) -> 114055 | L304: =INDEX(Breakdown[],MATCH($D304,Breakdown[Dist],0),MATCH(L$4,Breakdown[#Headers],0)) -> 418457 | M304: =INDEX(Breakdown[],MATCH($D304,Breakdown[Dist],0),MATCH(M$4,Breakdown[#Headers],0)) -> 0 | N304: =I304-K304+M304 -> 578731 | O304: =ROUND(N304*0.1,0) -> 57873 | Q304: =INDEX(Breakdown[],MATCH($D304,Breakdown[Dist],0),MATCH(Q$4,Breakdown[#Headers],0)) -> 160274 | R304: =INDEX(Breakdown[],MATCH($D304,Breakdown[Dist],0),MATCH(R$4,Breakdown[#Headers],0)) -> 0 | S304: =SUM(Q304:R304) -> 160274 | T304: =L304-O304 -> 360584 | U304: =SUM(S304:T304) -> 520858 | W304: =O304/N304 -> 0.099999827 | X304: =U304/N304 -> 0.90000017
A305: 2026 | B305: 05 | C305: 05 | D305: 6921 | G305: 6921 | H305: West Bend-Mallard | I305: =INDEX(Breakdown[],MATCH($D305,Breakdown[Dist],0),MATCH(I$4,Breakdown[#Headers],0)) -> 125402 | J305: =INDEX(Breakdown[],MATCH($D305,Breakdown[Dist],0),MATCH(J$4,Breakdown[#Headers],0)) -> 96390 | K305: =INDEX(Breakdown[],MATCH($D305,Breakdown[Dist],0),MATCH(K$4,Breakdown[#Headers],0)) -> 20645 | L305: =INDEX(Breakdown[],MATCH($D305,Breakdown[Dist],0),MATCH(L$4,Breakdown[#Headers],0)) -> 75745 | M305: =INDEX(Breakdown[],MATCH($D305,Breakdown[Dist],0),MATCH(M$4,Breakdown[#Headers],0)) -> 3986 | N305: =I305-K305+M305 -> 108743 | O305: =ROUND(N305*0.1,0) -> 10874 | Q305: =INDEX(Breakdown[],MATCH($D305,Breakdown[Dist],0),MATCH(Q$4,Breakdown[#Headers],0)) -> 29012 | R305: =INDEX(Breakdown[],MATCH($D305,Breakdown[Dist],0),MATCH(R$4,Breakdown[#Headers],0)) -> 3986 | S305: =SUM(Q305:R305) -> 32998 | T305: =L305-O305 -> 64871 | U305: =SUM(S305:T305) -> 97869 | W305: =O305/N305 -> 0.099997241 | X305: =U305/N305 -> 0.90000276
A306: 2026 | B306: 10 | C306: 10 | D306: 6930 | G306: 6930 | H306: West Branch | I306: =INDEX(Breakdown[],MATCH($D306,Breakdown[Dist],0),MATCH(I$4,Breakdown[#Headers],0)) -> 313306 | J306: =INDEX(Breakdown[],MATCH($D306,Breakdown[Dist],0),MATCH(J$4,Breakdown[#Headers],0)) -> 248370 | K306: =INDEX(Breakdown[],MATCH($D306,Breakdown[Dist],0),MATCH(K$4,Breakdown[#Headers],0)) -> 53197 | L306: =INDEX(Breakdown[],MATCH($D306,Breakdown[Dist],0),MATCH(L$4,Breakdown[#Headers],0)) -> 195173 | M306: =INDEX(Breakdown[],MATCH($D306,Breakdown[Dist],0),MATCH(M$4,Breakdown[#Headers],0)) -> 0 | N306: =I306-K306+M306 -> 260109 | O306: =ROUND(N306*0.1,0) -> 26011 | Q306: =INDEX(Breakdown[],MATCH($D306,Breakdown[Dist],0),MATCH(Q$4,Breakdown[#Headers],0)) -> 64936 | R306: =INDEX(Breakdown[],MATCH($D306,Breakdown[Dist],0),MATCH(R$4,Breakdown[#Headers],0)) -> 0 | S306: =SUM(Q306:R306) -> 64936 | T306: =L306-O306 -> 169162 | U306: =SUM(S306:T306) -> 234098 | W306: =O306/N306 -> 0.10000038 | X306: =U306/N306 -> 0.89999962
A307: 2026 | B307: 15 | C307: 15 | D307: 6937 | G307: 6937 | H307: West Burlington | I307: =INDEX(Breakdown[],MATCH($D307,Breakdown[Dist],0),MATCH(I$4,Breakdown[#Headers],0)) -> 153193 | J307: =INDEX(Breakdown[],MATCH($D307,Breakdown[Dist],0),MATCH(J$4,Breakdown[#Headers],0)) -> 122031 | K307: =INDEX(Breakdown[],MATCH($D307,Breakdown[Dist],0),MATCH(K$4,Breakdown[#Headers],0)) -> 26137 | L307: =INDEX(Breakdown[],MATCH($D307,Breakdown[Dist],0),MATCH(L$4,Breakdown[#Headers],0)) -> 95894 | M307: =INDEX(Breakdown[],MATCH($D307,Breakdown[Dist],0),MATCH(M$4,Breakdown[#Headers],0)) -> 5683 | N307: =I307-K307+M307 -> 132739 | O307: =ROUND(N307*0.1,0) -> 13274 | Q307: =INDEX(Breakdown[],MATCH($D307,Breakdown[Dist],0),MATCH(Q$4,Breakdown[#Headers],0)) -> 31162 | R307: =INDEX(Breakdown[],MATCH($D307,Breakdown[Dist],0),MATCH(R$4,Breakdown[#Headers],0)) -> 5683 | S307: =SUM(Q307:R307) -> 36845 | T307: =L307-O307 -> 82620 | U307: =SUM(S307:T307) -> 119465 | W307: =O307/N307 -> 0.10000075 | X307: =U307/N307 -> 0.89999925
A308: 2026 | B308: 01 | C308: 01 | D308: 6943 | G308: 6943 | H308: West Central | I308: =INDEX(Breakdown[],MATCH($D308,Breakdown[Dist],0),MATCH(I$4,Breakdown[#Headers],0)) -> 113447 | J308: =INDEX(Breakdown[],MATCH($D308,Breakdown[Dist],0),MATCH(J$4,Breakdown[#Headers],0)) -> 86181 | K308: =INDEX(Breakdown[],MATCH($D308,Breakdown[Dist],0),MATCH(K$4,Breakdown[#Headers],0)) -> 18459 | L308: =INDEX(Breakdown[],MATCH($D308,Breakdown[Dist],0),MATCH(L$4,Breakdown[#Headers],0)) -> 67722 | M308: =INDEX(Breakdown[],MATCH($D308,Breakdown[Dist],0),MATCH(M$4,Breakdown[#Headers],0)) -> 0 | N308: =I308-K308+M308 -> 94988 | O308: =ROUND(N308*0.1,0) -> 9499 | Q308: =INDEX(Breakdown[],MATCH($D308,Breakdown[Dist],0),MATCH(Q$4,Breakdown[#Headers],0)) -> 27266 | R308: =INDEX(Breakdown[],MATCH($D308,Breakdown[Dist],0),MATCH(R$4,Breakdown[#Headers],0)) -> 0 | S308: =SUM(Q308:R308) -> 27266 | T308: =L308-O308 -> 58223 | U308: =SUM(S308:T308) -> 85489 | W308: =O308/N308 -> 0.10000211 | X308: =U308/N308 -> 0.89999789
A309: 2026 | B309: 11 | C309: 11 | D309: 6264 | G309: 6264 | H309: West Central Valley | I309: =INDEX(Breakdown[],MATCH($D309,Breakdown[Dist],0),MATCH(I$4,Breakdown[#Headers],0)) -> 374671 | J309: =INDEX(Breakdown[],MATCH($D309,Breakdown[Dist],0),MATCH(J$4,Breakdown[#Headers],0)) -> 303200 | K309: =INDEX(Breakdown[],MATCH($D309,Breakdown[Dist],0),MATCH(K$4,Breakdown[#Headers],0)) -> 64940 | L309: =INDEX(Breakdown[],MATCH($D309,Breakdown[Dist],0),MATCH(L$4,Breakdown[#Headers],0)) -> 238260 | M309: =INDEX(Breakdown[],MATCH($D309,Breakdown[Dist],0),MATCH(M$4,Breakdown[#Headers],0)) -> 0 | N309: =I309-K309+M309 -> 309731 | O309: =ROUND(N309*0.1,0) -> 30973 | Q309: =INDEX(Breakdown[],MATCH($D309,Breakdown[Dist],0),MATCH(Q$4,Breakdown[#Headers],0)) -> 71471 | R309: =INDEX(Breakdown[],MATCH($D309,Breakdown[Dist],0),MATCH(R$4,Breakdown[#Headers],0)) -> 0 | S309: =SUM(Q309:R309) -> 71471 | T309: =L309-O309 -> 207287 | U309: =SUM(S309:T309) -> 278758 | W309: =O309/N309 -> 0.099999677 | X309: =U309/N309 -> 0.90000032
A310: 2026 | B310: 01 | C310: 01 | D310: 6950 | G310: 6950 | H310: West Delaware Co | I310: =INDEX(Breakdown[],MATCH($D310,Breakdown[Dist],0),MATCH(I$4,Breakdown[#Headers],0)) -> 543142 | J310: =INDEX(Breakdown[],MATCH($D310,Breakdown[Dist],0),MATCH(J$4,Breakdown[#Headers],0)) -> 412603 | K310: =INDEX(Breakdown[],MATCH($D310,Breakdown[Dist],0),MATCH(K$4,Breakdown[#Headers],0)) -> 88373 | L310: =INDEX(Breakdown[],MATCH($D310,Breakdown[Dist],0),MATCH(L$4,Breakdown[#Headers],0)) -> 324230 | M310: =INDEX(Breakdown[],MATCH($D310,Breakdown[Dist],0),MATCH(M$4,Breakdown[#Headers],0)) -> 0 | N310: =I310-K310+M310 -> 454769 | O310: =ROUND(N310*0.1,0) -> 45477 | Q310: =INDEX(Breakdown[],MATCH($D310,Breakdown[Dist],0),MATCH(Q$4,Breakdown[#Headers],0)) -> 130539 | R310: =INDEX(Breakdown[],MATCH($D310,Breakdown[Dist],0),MATCH(R$4,Breakdown[#Headers],0)) -> 0 | S310: =SUM(Q310:R310) -> 130539 | T310: =L310-O310 -> 278753 | U310: =SUM(S310:T310) -> 409292 | W310: =O310/N310 -> 0.10000022 | X310: =U310/N310 -> 0.89999978
A311: 2026 | B311: 11 | C311: 11 | D311: 6957 | G311: 6957 | H311: West Des Moines | I311: =INDEX(Breakdown[],MATCH($D311,Breakdown[Dist],0),MATCH(I$4,Breakdown[#Headers],0)) -> 3301955 | J311: =INDEX(Breakdown[],MATCH($D311,Breakdown[Dist],0),MATCH(J$4,Breakdown[#Headers],0)) -> 2672080 | K311: =INDEX(Breakdown[],MATCH($D311,Breakdown[Dist],0),MATCH(K$4,Breakdown[#Headers],0)) -> 572317 | L311: =INDEX(Breakdown[],MATCH($D311,Breakdown[Dist],0),MATCH(L$4,Breakdown[#Headers],0)) -> 2099763 | M311: =INDEX(Breakdown[],MATCH($D311,Breakdown[Dist],0),MATCH(M$4,Breakdown[#Headers],0)) -> 0 | N311: =I311-K311+M311 -> 2729638 | O311: =ROUND(N311*0.1,0) -> 272964 | Q311: =INDEX(Breakdown[],MATCH($D311,Breakdown[Dist],0),MATCH(Q$4,Breakdown[#Headers],0)) -> 629875 | R311: =INDEX(Breakdown[],MATCH($D311,Breakdown[Dist],0),MATCH(R$4,Breakdown[#Headers],0)) -> 0 | S311: =SUM(Q311:R311) -> 629875 | T311: =L311-O311 -> 1826799 | U311: =SUM(S311:T311) -> 2456674 | W311: =O311/N311 -> 0.10000007 | X311: =U311/N311 -> 0.89999993
A312: 2026 | B312: 07 | C312: 07 | D312: 5922 | G312: 5922 | H312: West Fork | I312: =INDEX(Breakdown[],MATCH($D312,Breakdown[Dist],0),MATCH(I$4,Breakdown[#Headers],0)) -> 298002 | J312: =INDEX(Breakdown[],MATCH($D312,Breakdown[Dist],0),MATCH(J$4,Breakdown[#Headers],0)) -> 233369 | K312: =INDEX(Breakdown[],MATCH($D312,Breakdown[Dist],0),MATCH(K$4,Breakdown[#Headers],0)) -> 49984 | L312: =INDEX(Breakdown[],MATCH($D312,Breakdown[Dist],0),MATCH(L$4,Breakdown[#Headers],0)) -> 183385 | M312: =INDEX(Breakdown[],MATCH($D312,Breakdown[Dist],0),MATCH(M$4,Breakdown[#Headers],0)) -> 0 | N312: =I312-K312+M312 -> 248018 | O312: =ROUND(N312*0.1,0) -> 24802 | Q312: =INDEX(Breakdown[],MATCH($D312,Breakdown[Dist],0),MATCH(Q$4,Breakdown[#Headers],0)) -> 64633 | R312: =INDEX(Breakdown[],MATCH($D312,Breakdown[Dist],0),MATCH(R$4,Breakdown[#Headers],0)) -> 0 | S312: =SUM(Q312:R312) -> 64633 | T312: =L312-O312 -> 158583 | U312: =SUM(S312:T312) -> 223216 | W312: =O312/N312 -> 0.10000081 | X312: =U312/N312 -> 0.89999919
A313: 2026 | B313: 07 | C313: 07 | D313: 0819 | G313: 0819 | H313: West Hancock | I313: =INDEX(Breakdown[],MATCH($D313,Breakdown[Dist],0),MATCH(I$4,Breakdown[#Headers],0)) -> 225188 | J313: =INDEX(Breakdown[],MATCH($D313,Breakdown[Dist],0),MATCH(J$4,Breakdown[#Headers],0)) -> 176347 | K313: =INDEX(Breakdown[],MATCH($D313,Breakdown[Dist],0),MATCH(K$4,Breakdown[#Headers],0)) -> 37770 | L313: =INDEX(Breakdown[],MATCH($D313,Breakdown[Dist],0),MATCH(L$4,Breakdown[#Headers],0)) -> 138577 | M313: =INDEX(Breakdown[],MATCH($D313,Breakdown[Dist],0),MATCH(M$4,Breakdown[#Headers],0)) -> 0 | N313: =I313-K313+M313 -> 187418 | O313: =ROUND(N313*0.1,0) -> 18742 | Q313: =INDEX(Breakdown[],MATCH($D313,Breakdown[Dist],0),MATCH(Q$4,Breakdown[#Headers],0)) -> 48841 | R313: =INDEX(Breakdown[],MATCH($D313,Breakdown[Dist],0),MATCH(R$4,Breakdown[#Headers],0)) -> 0 | S313: =SUM(Q313:R313) -> 48841 | T313: =L313-O313 -> 119835 | U313: =SUM(S313:T313) -> 168676 | W313: =O313/N313 -> 0.10000107 | X313: =U313/N313 -> 0.89999893
A314: 2026 | B314: 13 | C314: 13 | D314: 6969 | G314: 6969 | H314: West Harrison | I314: =INDEX(Breakdown[],MATCH($D314,Breakdown[Dist],0),MATCH(I$4,Breakdown[#Headers],0)) -> 134292 | J314: =INDEX(Breakdown[],MATCH($D314,Breakdown[Dist],0),MATCH(J$4,Breakdown[#Headers],0)) -> 106166 | K314: =INDEX(Breakdown[],MATCH($D314,Breakdown[Dist],0),MATCH(K$4,Breakdown[#Headers],0)) -> 22739 | L314: =INDEX(Breakdown[],MATCH($D314,Breakdown[Dist],0),MATCH(L$4,Breakdown[#Headers],0)) -> 83427 | M314: =INDEX(Breakdown[],MATCH($D314,Breakdown[Dist],0),MATCH(M$4,Breakdown[#Headers],0)) -> 13668 | N314: =I314-K314+M314 -> 125221 | O314: =ROUND(N314*0.1,0) -> 12522 | Q314: =INDEX(Breakdown[],MATCH($D314,Breakdown[Dist],0),MATCH(Q$4,Breakdown[#Headers],0)) -> 28126 | R314: =INDEX(Breakdown[],MATCH($D314,Breakdown[Dist],0),MATCH(R$4,Breakdown[#Headers],0)) -> 13668 | S314: =SUM(Q314:R314) -> 41794 | T314: =L314-O314 -> 70905 | U314: =SUM(S314:T314) -> 112699 | W314: =O314/N314 -> 0.099999201 | X314: =U314/N314 -> 0.9000008
A315: 2026 | B315: 09 | C315: 09 | D315: 6975 | G315: 6975 | H315: West Liberty | I315: =INDEX(Breakdown[],MATCH($D315,Breakdown[Dist],0),MATCH(I$4,Breakdown[#Headers],0)) -> 485022 | J315: =INDEX(Breakdown[],MATCH($D315,Breakdown[Dist],0),MATCH(J$4,Breakdown[#Headers],0)) -> 382387 | K315: =INDEX(Breakdown[],MATCH($D315,Breakdown[Dist],0),MATCH(K$4,Breakdown[#Headers],0)) -> 81901 | L315: =INDEX(Breakdown[],MATCH($D315,Breakdown[Dist],0),MATCH(L$4,Breakdown[#Headers],0)) -> 300486 | M315: =INDEX(Breakdown[],MATCH($D315,Breakdown[Dist],0),MATCH(M$4,Breakdown[#Headers],0)) -> 0 | N315: =I315-K315+M315 -> 403121 | O315: =ROUND(N315*0.1,0) -> 40312 | Q315: =INDEX(Breakdown[],MATCH($D315,Breakdown[Dist],0),MATCH(Q$4,Breakdown[#Headers],0)) -> 102635 | R315: =INDEX(Breakdown[],MATCH($D315,Breakdown[Dist],0),MATCH(R$4,Breakdown[#Headers],0)) -> 0 | S315: =SUM(Q315:R315) -> 102635 | T315: =L315-O315 -> 260174 | U315: =SUM(S315:T315) -> 362809 | W315: =O315/N315 -> 0.099999752 | X315: =U315/N315 -> 0.90000025
A316: 2026 | B316: 12 | C316: 12 | D316: 6983 | G316: 6983 | H316: West Lyon | I316: =INDEX(Breakdown[],MATCH($D316,Breakdown[Dist],0),MATCH(I$4,Breakdown[#Headers],0)) -> 367733 | J316: =INDEX(Breakdown[],MATCH($D316,Breakdown[Dist],0),MATCH(J$4,Breakdown[#Headers],0)) -> 285337 | K316: =INDEX(Breakdown[],MATCH($D316,Breakdown[Dist],0),MATCH(K$4,Breakdown[#Headers],0)) -> 61114 | L316: =INDEX(Breakdown[],MATCH($D316,Breakdown[Dist],0),MATCH(L$4,Breakdown[#Headers],0)) -> 224223 | M316: =INDEX(Breakdown[],MATCH($D316,Breakdown[Dist],0),MATCH(M$4,Breakdown[#Headers],0)) -> 0 | N316: =I316-K316+M316 -> 306619 | O316: =ROUND(N316*0.1,0) -> 30662 | Q316: =INDEX(Breakdown[],MATCH($D316,Breakdown[Dist],0),MATCH(Q$4,Breakdown[#Headers],0)) -> 82396 | R316: =INDEX(Breakdown[],MATCH($D316,Breakdown[Dist],0),MATCH(R$4,Breakdown[#Headers],0)) -> 0 | S316: =SUM(Q316:R316) -> 82396 | T316: =L316-O316 -> 193561 | U316: =SUM(S316:T316) -> 275957 | W316: =O316/N316 -> 0.10000033 | X316: =U316/N316 -> 0.89999967
... A329: 2026 | B329: 11 | C329: 11 | D329: 7110 | G329: 7110 | H329: Woodward-Granger | I329: =INDEX(Breakdown[],MATCH($D329,Breakdown[Dist],0),MATCH(I$4,Breakdown[#Headers],0)) -> 416632 | J329: =INDEX(Breakdown[],MATCH($D329,Breakdown[Dist],0),MATCH(J$4,Breakdown[#Headers],0)) -> 337156 | K329: =INDEX(Breakdown[],MATCH($D329,Breakdown[Dist],0),MATCH(K$4,Breakdown[#Headers],0)) -> 72214 | L329: =INDEX(Breakdown[],MATCH($D329,Breakdown[Dist],0),MATCH(L$4,Breakdown[#Headers],0)) -> 264942 | M329: =INDEX(Breakdown[],MATCH($D329,Breakdown[Dist],0),MATCH(M$4,Breakdown[#Headers],0)) -> 0 | N329: =I329-K329+M329 -> 344418 | O329: =ROUND(N329*0.1,0) -> 34442 | Q329: =INDEX(Breakdown[],MATCH($D329,Breakdown[Dist],0),MATCH(Q$4,Breakdown[#Headers],0)) -> 79476 | R329: =INDEX(Breakdown[],MATCH($D329,Breakdown[Dist],0),MATCH(R$4,Breakdown[#Headers],0)) -> 0 | S329: =SUM(Q329:R329) -> 79476 | T329: =L329-O329 -> 230500 | U329: =SUM(S329:T329) -> 309976 | W329: =O329/N329 -> 0.10000058 | X329: =U329/N329 -> 0.89999942
H330: Statewide | I330: =SUM(I5:I329) -> 191818201 | J330: =SUM(J5:J329) -> 151738653 | K330: =SUM(K5:K329) -> 32500000 | L330: =SUM(L5:L329) -> 119238653 | M330: =SUM(M5:M329) -> 1172290 | N330: =SUM(N5:N329) -> 160490491 | O330: =SUM(O5:O329) -> 16049065 | Q330: =SUM(Q5:Q329) -> 40079548 | R330: =SUM(R5:R329) -> 1172290 | S330: =SUM(S5:S329) -> 41251838 | T330: =SUM(T5:T329) -> 103189588 | U330: =SUM(U5:U329) -> 144441426

Sheet Special Education By AEA
D1: Line 4.49 A&L | E1: Calculated | F1: Line 5.16 A&L | G1: Calculated | H1: Line 4.54 A&L | I1: Calculated | J1: Calculated
D2: Column A | E2: Column B | F2: Column C | G2: Column D | H2: Column E | I2: Column F | J2: Column G
G3: B-C | I3: A-C+E | J3: A-C+E *10%
B4: AEA District Chose to Receive Services From | C4: AEA Name | D4: AEA Special Ed Support District Cost Formula Generated | E4: State Aid Portion Special Ed | F4: AEA Statewide State Aid Reduction | G4: State Aid Special Ed Minus Reduction | H4: AEA Special Ed Support Adjustment | I4: Total Special Ed Funding Removing Reduction Including Adjustment | J4: 10% Portion District Can Keep from State Aid portion
B5: 01 | C5: Keystone AEA 1 | D5: =SUMIF('Special Education Breakdown'!$C$5:$C$329,'Special Education By AEA'!$B5,'Special Education Breakdown'!I$5:I$329) -> 11576155 | E5: =SUMIF('Special Education Breakdown'!$C$5:$C$329,'Special Education By AEA'!$B5,'Special Education Breakdown'!J$5:J$329) -> 8793953 | F5: =SUMIF('Special Education Breakdown'!$C$5:$C$329,'Special Education By AEA'!$B5,'Special Education Breakdown'!K$5:K$329) -> 1883523 | G5: =SUMIF('Special Education Breakdown'!$C$5:$C$329,'Special Education By AEA'!$B5,'Special Education Breakdown'!L$5:L$329) -> 6910430 | H5: =SUMIF('Special Education Breakdown'!$C$5:$C$329,'Special Education By AEA'!$B5,'Special Education Breakdown'!M$5:M$329) -> 47018 | I5: =SUMIF('Special Education Breakdown'!$C$5:$C$329,'Special Education By AEA'!$B5,'Special Education Breakdown'!N$5:N$329) -> 9739650 | J5: =SUMIF('Special Education Breakdown'!$C$5:$C$329,'Special Education By AEA'!$B5,'Special Education Breakdown'!O$5:O$329) -> 973966
B6: 05 | C6: Prairie Lakes AEA 8 | D6: =SUMIF('Special Education Breakdown'!$C$5:$C$329,'Special Education By AEA'!$B6,'Special Education Breakdown'!I$5:I$329) -> 11961182 | E6: =SUMIF('Special Education Breakdown'!$C$5:$C$329,'Special Education By AEA'!$B6,'Special Education Breakdown'!J$5:J$329) -> 9193987 | F6: =SUMIF('Special Education Breakdown'!$C$5:$C$329,'Special Education By AEA'!$B6,'Special Education Breakdown'!K$5:K$329) -> 1969206 | G6: =SUMIF('Special Education Breakdown'!$C$5:$C$329,'Special Education By AEA'!$B6,'Special Education Breakdown'!L$5:L$329) -> 7224781 | H6: =SUMIF('Special Education Breakdown'!$C$5:$C$329,'Special Education By AEA'!$B6,'Special Education Breakdown'!M$5:M$329) -> 167396 | I6: =SUMIF('Special Education Breakdown'!$C$5:$C$329,'Special Education By AEA'!$B6,'Special Education Breakdown'!N$5:N$329) -> 10159372 | J6: =SUMIF('Special Education Breakdown'!$C$5:$C$329,'Special Education By AEA'!$B6,'Special Education Breakdown'!O$5:O$329) -> 1015937
B7: 07 | C7: Central Rivers | D7: =SUMIF('Special Education Breakdown'!$C$5:$C$329,'Special Education By AEA'!$B7,'Special Education Breakdown'!I$5:I$329) -> 24560553 | E7: =SUMIF('Special Education Breakdown'!$C$5:$C$329,'Special Education By AEA'!$B7,'Special Education Breakdown'!J$5:J$329) -> 19233662 | F7: =SUMIF('Special Education Breakdown'!$C$5:$C$329,'Special Education By AEA'!$B7,'Special Education Breakdown'!K$5:K$329) -> 4119546 | G7: =SUMIF('Special Education Breakdown'!$C$5:$C$329,'Special Education By AEA'!$B7,'Special Education Breakdown'!L$5:L$329) -> 15114116 | H7: =SUMIF('Special Education Breakdown'!$C$5:$C$329,'Special Education By AEA'!$B7,'Special Education Breakdown'!M$5:M$329) -> 206737 | I7: =SUMIF('Special Education Breakdown'!$C$5:$C$329,'Special Education By AEA'!$B7,'Special Education Breakdown'!N$5:N$329) -> 20647744 | J7: =SUMIF('Special Education Breakdown'!$C$5:$C$329,'Special Education By AEA'!$B7,'Special Education Breakdown'!O$5:O$329) -> 2064777
B8: 09 | C8: Mississippi Bend AEA 9 | D8: =SUMIF('Special Education Breakdown'!$C$5:$C$329,'Special Education By AEA'!$B8,'Special Education Breakdown'!I$5:I$329) -> 17666093 | E8: =SUMIF('Special Education Breakdown'!$C$5:$C$329,'Special Education By AEA'!$B8,'Special Education Breakdown'!J$5:J$329) -> 13927789 | F8: =SUMIF('Special Education Breakdown'!$C$5:$C$329,'Special Education By AEA'!$B8,'Special Education Breakdown'!K$5:K$329) -> 2983110 | G8: =SUMIF('Special Education Breakdown'!$C$5:$C$329,'Special Education By AEA'!$B8,'Special Education Breakdown'!L$5:L$329) -> 10944679 | H8: =SUMIF('Special Education Breakdown'!$C$5:$C$329,'Special Education By AEA'!$B8,'Special Education Breakdown'!M$5:M$329) -> 84238 | I8: =SUMIF('Special Education Breakdown'!$C$5:$C$329,'Special Education By AEA'!$B8,'Special Education Breakdown'!N$5:N$329) -> 14767221 | J8: =SUMIF('Special Education Breakdown'!$C$5:$C$329,'Special Education By AEA'!$B8,'Special Education Breakdown'!O$5:O$329) -> 1476722
B9: 10 | C9: Grant Wood AEA 10 | D9: =SUMIF('Special Education Breakdown'!$C$5:$C$329,'Special Education By AEA'!$B9,'Special Education Breakdown'!I$5:I$329) -> 26987736 | E9: =SUMIF('Special Education Breakdown'!$C$5:$C$329,'Special Education By AEA'!$B9,'Special Education Breakdown'!J$5:J$329) -> 21394233 | F9: =SUMIF('Special Education Breakdown'!$C$5:$C$329,'Special Education By AEA'!$B9,'Special Education Breakdown'!K$5:K$329) -> 4582301 | G9: =SUMIF('Special Education Breakdown'!$C$5:$C$329,'Special Education By AEA'!$B9,'Special Education Breakdown'!L$5:L$329) -> 16811932 | H9: =SUMIF('Special Education Breakdown'!$C$5:$C$329,'Special Education By AEA'!$B9,'Special Education Breakdown'!M$5:M$329) -> 140219 | I9: =SUMIF('Special Education Breakdown'!$C$5:$C$329,'Special Education By AEA'!$B9,'Special Education Breakdown'!N$5:N$329) -> 22545654 | J9: =SUMIF('Special Education Breakdown'!$C$5:$C$329,'Special Education By AEA'!$B9,'Special Education Breakdown'!O$5:O$329) -> 2254567
B10: 11 | C10: Heartland AEA 11 | D10: =SUMIF('Special Education Breakdown'!$C$5:$C$329,'Special Education By AEA'!$B10,'Special Education Breakdown'!I$5:I$329) -> 55239348 | E10: =SUMIF('Special Education Breakdown'!$C$5:$C$329,'Special Education By AEA'!$B10,'Special Education Breakdown'!J$5:J$329) -> 44701993 | F10: =SUMIF('Special Education Breakdown'!$C$5:$C$329,'Special Education By AEA'!$B10,'Special Education Breakdown'!K$5:K$329) -> 9574454 | G10: =SUMIF('Special Education Breakdown'!$C$5:$C$329,'Special Education By AEA'!$B10,'Special Education Breakdown'!L$5:L$329) -> 35127539 | H10: =SUMIF('Special Education Breakdown'!$C$5:$C$329,'Special Education By AEA'!$B10,'Special Education Breakdown'!M$5:M$329) -> 116312 | I10: =SUMIF('Special Education Breakdown'!$C$5:$C$329,'Special Education By AEA'!$B10,'Special Education Breakdown'!N$5:N$329) -> 45781206 | J10: =SUMIF('Special Education Breakdown'!$C$5:$C$329,'Special Education By AEA'!$B10,'Special Education Breakdown'!O$5:O$329) -> 4578123
B11: 12 | C11: Northwest AEA | D11: =SUMIF('Special Education Breakdown'!$C$5:$C$329,'Special Education By AEA'!$B11,'Special Education Breakdown'!I$5:I$329) -> 16002942 | E11: =SUMIF('Special Education Breakdown'!$C$5:$C$329,'Special Education By AEA'!$B11,'Special Education Breakdown'!J$5:J$329) -> 12417240 | F11: =SUMIF('Special Education Breakdown'!$C$5:$C$329,'Special Education By AEA'!$B11,'Special Education Breakdown'!K$5:K$329) -> 2659575 | G11: =SUMIF('Special Education Breakdown'!$C$5:$C$329,'Special Education By AEA'!$B11,'Special Education Breakdown'!L$5:L$329) -> 9757665 | H11: =SUMIF('Special Education Breakdown'!$C$5:$C$329,'Special Education By AEA'!$B11,'Special Education Breakdown'!M$5:M$329) -> 106969 | I11: =SUMIF('Special Education Breakdown'!$C$5:$C$329,'Special Education By AEA'!$B11,'Special Education Breakdown'!N$5:N$329) -> 13450336 | J11: =SUMIF('Special Education Breakdown'!$C$5:$C$329,'Special Education By AEA'!$B11,'Special Education Breakdown'!O$5:O$329) -> 1345036
B12: 13 | C12: Green Hills AEA 13 | D12: =SUMIF('Special Education Breakdown'!$C$5:$C$329,'Special Education By AEA'!$B12,'Special Education Breakdown'!I$5:I$329) -> 14688682 | E12: =SUMIF('Special Education Breakdown'!$C$5:$C$329,'Special Education By AEA'!$B12,'Special Education Breakdown'!J$5:J$329) -> 11612276 | F12: =SUMIF('Special Education Breakdown'!$C$5:$C$329,'Special Education By AEA'!$B12,'Special Education Breakdown'!K$5:K$329) -> 2487165 | G12: =SUMIF('Special Education Breakdown'!$C$5:$C$329,'Special Education By AEA'!$B12,'Special Education Breakdown'!L$5:L$329) -> 9125111 | H12: =SUMIF('Special Education Breakdown'!$C$5:$C$329,'Special Education By AEA'!$B12,'Special Education Breakdown'!M$5:M$329) -> 172236 | I12: =SUMIF('Special Education Breakdown'!$C$5:$C$329,'Special Education By AEA'!$B12,'Special Education Breakdown'!N$5:N$329) -> 12373753 | J12: =SUMIF('Special Education Breakdown'!$C$5:$C$329,'Special Education By AEA'!$B12,'Special Education Breakdown'!O$5:O$329) -> 1237379
B13: 15 | C13: Great Prairie AEA 15 | D13: =SUMIF('Special Education Breakdown'!$C$5:$C$329,'Special Education By AEA'!$B13,'Special Education Breakdown'!I$5:I$329) -> 13135510 | E13: =SUMIF('Special Education Breakdown'!$C$5:$C$329,'Special Education By AEA'!$B13,'Special Education Breakdown'!J$5:J$329) -> 10463520 | F13: =SUMIF('Special Education Breakdown'!$C$5:$C$329,'Special Education By AEA'!$B13,'Special Education Breakdown'!K$5:K$329) -> 2241120 | G13: =SUMIF('Special Education Breakdown'!$C$5:$C$329,'Special Education By AEA'!$B13,'Special Education Breakdown'!L$5:L$329) -> 8222400 | H13: =SUMIF('Special Education Breakdown'!$C$5:$C$329,'Special Education By AEA'!$B13,'Special Education Breakdown'!M$5:M$329) -> 131165 | I13: =SUMIF('Special Education Breakdown'!$C$5:$C$329,'Special Education By AEA'!$B13,'Special Education Breakdown'!N$5:N$329) -> 11025555 | J13: =SUMIF('Special Education Breakdown'!$C$5:$C$329,'Special Education By AEA'!$B13,'Special Education Breakdown'!O$5:O$329) -> 1102558
C14: Total | D14: =SUM(D5:D13) -> 191818201 | E14: =SUM(E5:E13) -> 151738653 | F14: =SUM(F5:F13) -> 32500000 | G14: =SUM(G5:G13) -> 119238653 | H14: =SUM(H5:H13) -> 1172290 | I14: =SUM(I5:I13) -> 160490491 | J14: =SUM(J5:J13) -> 16049065
D16: Calculated | E16: Line 4.54 A&L | F16: Calculated | G16: Calculated | H16: Calculated | I16: Calculated | J16: Calculated
D17: Column H | E17: Column I | F17: Column J | G17: Column K | H17: Column L | I17: Column M | J17: Column N
F18: H+I | G18: D-G | H18: J+K | I18: G/F | J18: L/F
B19: AEA District Chose to Receive Services From | C19: AEA Name | D19: =Breakdown[[#Headers],[Special Education Property Tax Portion]] -> Special Education Property Tax Portion | E19: =Breakdown[[#Headers],[AEA Special Ed Support Adjustment]] -> AEA Special Ed Support Adjustment | F19: Total Property Tax Portion District Pays AEA | G19: State Aid Portion District Sends to AEA | H19: Total Payment from District to AEA | I19: District Percentage ability to Retain | J19: District Percentage to Pay to AEAs
B20: 01 | C20: Keystone AEA 1 | D20: =SUMIF('Special Education Breakdown'!$C$5:$C$329,'Special Education By AEA'!$B20,'Special Education Breakdown'!Q$5:Q$329) -> 2782202 | E20: =SUMIF('Special Education Breakdown'!$C$5:$C$329,'Special Education By AEA'!$B20,'Special Education Breakdown'!R$5:R$329) -> 47018 | F20: =SUMIF('Special Education Breakdown'!$C$5:$C$329,'Special Education By AEA'!$B20,'Special Education Breakdown'!S$5:S$329) -> 2829220 | G20: =SUMIF('Special Education Breakdown'!$C$5:$C$329,'Special Education By AEA'!$B20,'Special Education Breakdown'!T$5:T$329) -> 5936464 | H20: =SUMIF('Special Education Breakdown'!$C$5:$C$329,'Special Education By AEA'!$B20,'Special Education Breakdown'!U$5:U$329) -> 8765684 | I20: =J5/I5 -> 0.1000001 | J20: =H20/I5 -> 0.8999999
B21: 05 | C21: Prairie Lakes AEA 8 | D21: =SUMIF('Special Education Breakdown'!$C$5:$C$329,'Special Education By AEA'!$B21,'Special Education Breakdown'!Q$5:Q$329) -> 2767195 | E21: =SUMIF('Special Education Breakdown'!$C$5:$C$329,'Special Education By AEA'!$B21,'Special Education Breakdown'!R$5:R$329) -> 167396 | F21: =SUMIF('Special Education Breakdown'!$C$5:$C$329,'Special Education By AEA'!$B21,'Special Education Breakdown'!S$5:S$329) -> 2934591 | G21: =SUMIF('Special Education Breakdown'!$C$5:$C$329,'Special Education By AEA'!$B21,'Special Education Breakdown'!T$5:T$329) -> 6208844 | H21: =SUMIF('Special Education Breakdown'!$C$5:$C$329,'Special Education By AEA'!$B21,'Special Education Breakdown'!U$5:U$329) -> 9143435 | I21: =J6/I6 -> 0.09999998 | J21: =H21/I6 -> 0.90000002
B22: 07 | C22: Central Rivers | D22: =SUMIF('Special Education Breakdown'!$C$5:$C$329,'Special Education By AEA'!$B22,'Special Education Breakdown'!Q$5:Q$329) -> 5326891 | E22: =SUMIF('Special Education Breakdown'!$C$5:$C$329,'Special Education By AEA'!$B22,'Special Education Breakdown'!R$5:R$329) -> 206737 | F22: =SUMIF('Special Education Breakdown'!$C$5:$C$329,'Special Education By AEA'!$B22,'Special Education Breakdown'!S$5:S$329) -> 5533628 | G22: =SUMIF('Special Education Breakdown'!$C$5:$C$329,'Special Education By AEA'!$B22,'Special Education Breakdown'!T$5:T$329) -> 13049339 | H22: =SUMIF('Special Education Breakdown'!$C$5:$C$329,'Special Education By AEA'!$B22,'Special Education Breakdown'!U$5:U$329) -> 18582967 | I22: =J7/I7 -> 0.10000013 | J22: =H22/I7 -> 0.89999987
B23: 09 | C23: Mississippi Bend AEA 9 | D23: =SUMIF('Special Education Breakdown'!$C$5:$C$329,'Special Education By AEA'!$B23,'Special Education Breakdown'!Q$5:Q$329) -> 3738304 | E23: =SUMIF('Special Education Breakdown'!$C$5:$C$329,'Special Education By AEA'!$B23,'Special Education Breakdown'!R$5:R$329) -> 84238 | F23: =SUMIF('Special Education Breakdown'!$C$5:$C$329,'Special Education By AEA'!$B23,'Special Education Breakdown'!S$5:S$329) -> 3822542 | G23: =SUMIF('Special Education Breakdown'!$C$5:$C$329,'Special Education By AEA'!$B23,'Special Education Breakdown'!T$5:T$329) -> 9467957 | H23: =SUMIF('Special Education Breakdown'!$C$5:$C$329,'Special Education By AEA'!$B23,'Special Education Breakdown'!U$5:U$329) -> 13290499 | I23: =J8/I8 -> 0.099999993 | J23: =H23/I8 -> 0.90000001
B24: 10 | C24: Grant Wood AEA 10 | D24: =SUMIF('Special Education Breakdown'!$C$5:$C$329,'Special Education By AEA'!$B24,'Special Education Breakdown'!Q$5:Q$329) -> 5593503 | E24: =SUMIF('Special Education Breakdown'!$C$5:$C$329,'Special Education By AEA'!$B24,'Special Education Breakdown'!R$5:R$329) -> 140219 | F24: =SUMIF('Special Education Breakdown'!$C$5:$C$329,'Special Education By AEA'!$B24,'Special Education Breakdown'!S$5:S$329) -> 5733722 | G24: =SUMIF('Special Education Breakdown'!$C$5:$C$329,'Special Education By AEA'!$B24,'Special Education Breakdown'!T$5:T$329) -> 14557365 | H24: =SUMIF('Special Education Breakdown'!$C$5:$C$329,'Special Education By AEA'!$B24,'Special Education Breakdown'!U$5:U$329) -> 20291087 | I24: =J9/I9 -> 0.10000007 | J24: =H24/I9 -> 0.89999993
B25: 11 | C25: Heartland AEA 11 | D25: =SUMIF('Special Education Breakdown'!$C$5:$C$329,'Special Education By AEA'!$B25,'Special Education Breakdown'!Q$5:Q$329) -> 10537355 | E25: =SUMIF('Special Education Breakdown'!$C$5:$C$329,'Special Education By AEA'!$B25,'Special Education Breakdown'!R$5:R$329) -> 116312 | F25: =SUMIF('Special Education Breakdown'!$C$5:$C$329,'Special Education By AEA'!$B25,'Special Education Breakdown'!S$5:S$329) -> 10653667 | G25: =SUMIF('Special Education Breakdown'!$C$5:$C$329,'Special Education By AEA'!$B25,'Special Education Breakdown'!T$5:T$329) -> 30549416 | H25: =SUMIF('Special Education Breakdown'!$C$5:$C$329,'Special Education By AEA'!$B25,'Special Education Breakdown'!U$5:U$329) -> 41203083 | I25: =J10/I10 -> 0.10000005 | J25: =H25/I10 -> 0.89999995
B26: 12 | C26: Northwest AEA | D26: =SUMIF('Special Education Breakdown'!$C$5:$C$329,'Special Education By AEA'!$B26,'Special Education Breakdown'!Q$5:Q$329) -> 3585702 | E26: =SUMIF('Special Education Breakdown'!$C$5:$C$329,'Special Education By AEA'!$B26,'Special Education Breakdown'!R$5:R$329) -> 106969 | F26: =SUMIF('Special Education Breakdown'!$C$5:$C$329,'Special Education By AEA'!$B26,'Special Education Breakdown'!S$5:S$329) -> 3692671 | G26: =SUMIF('Special Education Breakdown'!$C$5:$C$329,'Special Education By AEA'!$B26,'Special Education Breakdown'!T$5:T$329) -> 8412629 | H26: =SUMIF('Special Education Breakdown'!$C$5:$C$329,'Special Education By AEA'!$B26,'Special Education Breakdown'!U$5:U$329) -> 12105300 | I26: =J11/I11 -> 0.10000018 | J26: =H26/I11 -> 0.89999982
B27: 13 | C27: Green Hills AEA 13 | D27: =SUMIF('Special Education Breakdown'!$C$5:$C$329,'Special Education By AEA'!$B27,'Special Education Breakdown'!Q$5:Q$329) -> 3076406 | E27: =SUMIF('Special Education Breakdown'!$C$5:$C$329,'Special Education By AEA'!$B27,'Special Education Breakdown'!R$5:R$329) -> 172236 | F27: =SUMIF('Special Education Breakdown'!$C$5:$C$329,'Special Education By AEA'!$B27,'Special Education Breakdown'!S$5:S$329) -> 3248642 | G27: =SUMIF('Special Education Breakdown'!$C$5:$C$329,'Special Education By AEA'!$B27,'Special Education Breakdown'!T$5:T$329) -> 7887732 | H27: =SUMIF('Special Education Breakdown'!$C$5:$C$329,'Special Education By AEA'!$B27,'Special Education Breakdown'!U$5:U$329) -> 11136374 | I27: =J12/I12 -> 0.1000003 | J27: =H27/I12 -> 0.8999997
B28: 15 | C28: Great Prairie AEA 15 | D28: =SUMIF('Special Education Breakdown'!$C$5:$C$329,'Special Education By AEA'!$B28,'Special Education Breakdown'!Q$5:Q$329) -> 2671990 | E28: =SUMIF('Special Education Breakdown'!$C$5:$C$329,'Special Education By AEA'!$B28,'Special Education Breakdown'!R$5:R$329) -> 131165 | F28: =SUMIF('Special Education Breakdown'!$C$5:$C$329,'Special Education By AEA'!$B28,'Special Education Breakdown'!S$5:S$329) -> 2803155 | G28: =SUMIF('Special Education Breakdown'!$C$5:$C$329,'Special Education By AEA'!$B28,'Special Education Breakdown'!T$5:T$329) -> 7119842 | H28: =SUMIF('Special Education Breakdown'!$C$5:$C$329,'Special Education By AEA'!$B28,'Special Education Breakdown'!U$5:U$329) -> 9922997 | I28: =J13/I13 -> 0.10000023 | J28: =H28/I13 -> 0.89999977
C29: Total | D29: =SUM(D20:D28) -> 40079548 | E29: =SUM(E20:E28) -> 1172290 | F29: =SUM(F20:F28) -> 41251838 | G29: =SUM(G20:G28) -> 103189588 | H29: =SUM(H20:H28) -> 144441426

Sheet ActiveSchools
A1: FiscalYear | B1: AEA | C1: Dist | D1: DistSub1 | E1: DistSub2 | F1: DistrictNumber | G1: Label
A2: 2026 | B2: 11 | C2: 0018 | F2: 0018 | G2: Adair-Casey
A3: 2026 | B3: 11 | C3: 0027 | F3: 0027 | G3: Adel-Desoto-Minburn
A4: 2026 | B4: 07 | C4: 0009 | F4: 0009 | G4: AGWSR
A5: 2026 | B5: 13 | C5: 0441 | F5: 0441 | G5: AHSTW
A6: 2026 | B6: 12 | C6: 0063 | F6: 0063 | G6: Akron-Westfield
A7: 2026 | B7: 05 | C7: 0072 | F7: 0072 | G7: Albert City-Truesdale
A8: 2026 | B8: 15 | C8: 0081 | F8: 0081 | G8: Albia
A9: 2026 | B9: 10 | C9: 0099 | F9: 0099 | G9: Alburnett
A10: 2026 | B10: 07 | C10: 0108 | F10: 0108 | G10: Alden
A11: 2026 | B11: 05 | C11: 0126 | D11: 6417 | E11: 3897 | F11: 0126 | G11: Algona
A12: 2026 | B12: 01 | C12: 0135 | F12: 0135 | G12: Allamakee
A13: 2026 | B13: 05 | C13: 0171 | F13: 0171 | G13: Alta-Aurelia
A14: 2026 | B14: 11 | C14: 0225 | F14: 0225 | G14: Ames
A15: 2026 | B15: 10 | C15: 0234 | F15: 0234 | G15: Anamosa
A16: 2026 | B16: 09 | C16: 0243 | F16: 0243 | G16: Andrew
A17: 2026 | B17: 11 | C17: 0261 | F17: 0261 | G17: Ankeny
A18: 2026 | B18: 07 | C18: 0279 | F18: 0279 | G18: Aplington-Parkersburg
A19: 2026 | B19: 12 | C19: 0355 | F19: 0355 | G19: Ar-We-Va
A20: 2026 | B20: 13 | C20: 0387 | F20: 0387 | G20: Atlantic
A21: 2026 | B21: 11 | C21: 0414 | F21: 0414 | G21: Audubon
A22: 2026 | B22: 11 | C22: 0472 | F22: 0472 | G22: Ballard
A23: 2026 | B23: 11 | C23: 0513 | F23: 0513 | G23: Baxter
... A60: 2026 | B60: 13 | C60: 1197 | F60: 1197 | G60: Clarinda
A61: 2026 | B61: 05 | C61: 1206 | D61: 1854 | F61: 1206 | G61: Clarion-Goldfield-Dows
A62: 2026 | B62: 13 | C62: 1211 | F62: 1211 | G62: Clarke
A63: 2026 | B63: 07 | C63: 1215 | F63: 1215 | G63: Clarksville
A64: 2026 | B64: 05 | C64: 1218 | F64: 1218 | G64: Clay Central-Everly
A65: 2026 | B65: 01 | C65: 2763 | F65: 2763 | G65: Clayton Ridge
A66: 2026 | B66: 10 | C66: 1221 | D66: 0216 | F66: 1221 | G66: Clear Creek-Amana
A67: 2026 | B67: 07 | C67: 1233 | F67: 1233 | G67: Clear Lake
A68: 2026 | B68: 09 | C68: 1278 | F68: 1278 | G68: Clinton
A69: 2026 | B69: 11 | C69: 1332 | F69: 1332 | G69: Colfax-Mingo
A70: 2026 | B70: 10 | C70: 1337 | F70: 1337 | G70: College Community
A71: 2026 | B71: 11 | C71: 1350 | F71: 1350 | G71: Collins-Maxwell
A72: 2026 | B72: 11 | C72: 1359 | F72: 1359 | G72: Colo-Nesco
A73: 2026 | B73: 09 | C73: 1368 | F73: 1368 | G73: Columbus
A74: 2026 | B74: 11 | C74: 1413 | F74: 1413 | G74: Coon Rapids-Bayard
A75: 2026 | B75: 13 | C75: 1431 | F75: 1431 | G75: Corning
A76: 2026 | B76: 13 | C76: 1476 | F76: 1476 | G76: Council Bluffs
A77: 2026 | B77: 13 | C77: 1503 | F77: 1503 | G77: Creston
A78: 2026 | B78: 11 | C78: 1576 | F78: 1576 | G78: Dallas Center-Grimes
... A266: 2026 | B266: 11 | C266: 6094 | F266: 6094 | G266: Southeast Warren
A267: 2026 | B267: 05 | C267: 6096 | D267: 5323 | F267: 6096 | G267: Southeast Valley
A268: 2026 | B268: 05 | C268: 6102 | F268: 6102 | G268: Spencer
A269: 2026 | B269: 05 | C269: 6120 | F269: 6120 | G269: Spirit Lake
A270: 2026 | B270: 10 | C270: 6138 | F270: 6138 | G270: Springville
A271: 2026 | B271: 07 | C271: 5751 | F271: 5751 | G271: St Ansgar
A272: 2026 | B272: 13 | C272: 6165 | F272: 6165 | G272: Stanton
A273: 2026 | B273: 01 | C273: 6175 | F273: 6175 | G273: Starmont
A274: 2026 | B274: 05 | C274: 6219 | F274: 6219 | G274: Storm Lake
A275: 2026 | B275: 05 | C275: 6246 | F275: 6246 | G275: Stratford
A276: 2026 | B276: 07 | C276: 6273 | F276: 6273 | G276: Sumner-Fredericksburg
A277: 2026 | B277: 10 | C277: 6408 | F277: 6408 | G277: Tipton
A278: 2026 | B278: 13 | C278: 6453 | F278: 6453 | G278: Treynor
A279: 2026 | B279: 13 | C279: 6460 | F279: 6460 | G279: Tri-Center
... A300: 2026 | B300: 15 | C300: 6854 | F300: 6854 | G300: Wayne
A301: 2026 | B301: 05 | C301: 6867 | D301: 4775 | F301: 6867 | G301: Webster City
A302: 2026 | B302: 05 | C302: 6921 | F302: 6921 | G302: West Bend-Mallard
A303: 2026 | B303: 10 | C303: 6930 | F303: 6930 | G303: West Branch
A304: 2026 | B304: 15 | C304: 6937 | F304: 6937 | G304: West Burlington
A305: 2026 | B305: 01 | C305: 6943 | F305: 6943 | G305: West Central
A306: 2026 | B306: 11 | C306: 6264 | F306: 6264 | G306: West Central Valley
A307: 2026 | B307: 01 | C307: 6950 | F307: 6950 | G307: West Delaware Co
A308: 2026 | B308: 11 | C308: 6957 | F308: 6957 | G308: West Des Moines
A309: 2026 | B309: 07 | C309: 5922 | F309: 5922 | G309: West Fork
A310: 2026 | B310: 07 | C310: 0819 | F310: 0819 | G310: West Hancock
A311: 2026 | B311: 13 | C311: 6969 | F311: 6969 | G311: West Harrison
A312: 2026 | B312: 09 | C312: 6975 | F312: 6975 | G312: West Liberty
A313: 2026 | B313: 12 | C313: 6983 | F313: 6983 | G313: West Lyon
... A326: 2026 | B326: 11 | C326: 7110 | F326: 7110 | G326: Woodward-Granger

Sheet Media&EdByAEA,Dist,Nonpublic
A1: Final FY 2026 Media and Educational Services Funding by AEA, Resident School District, and Nonpublic School
A2: AEA | B2: AEA Name | C2: Nonpublic School Name | D2: Nonpublic School District Number | E2: School Number | F2: Resident School District | G2: Resident School District Number | H2: DOM Dist | I2: Enrollment | J2: Resident Accredited Nonpublic Students | K2: Portion of funding attributed to Resident Pupils | L2: AEA Media Services Nonpublic Portion | M2: AEA Educational Services Nonpublic Portion
A3: 01 | B3: Keystone AEA | C3: St Patrick School | D3: 0135 | E3: 8102 | F3: Allamakee Comm School District | G3: 0135 | H3: =_xlfn.IFNA(INDEX(ActiveSchools!$C$2:$F$326,MATCH(G3,ActiveSchools!$F$2:$F$326,0),1),"Total") -> 0135 | I3: 149 | J3: =_xlfn.IFNA(INDEX(DetailByDistrict[],MATCH($H3,DetailByDistrict[Dist],0),MATCH(J$2,DetailByDistrict[#Headers],0)),0) -> 155 | K3: =I3/J3 -> 0.96129032 | L3: =ROUND(INDEX(DetailByDistrict[],MATCH($H3,DetailByDistrict[Dist],0),MATCH(L$2,DetailByDistrict[#Headers],0))*K3,2) -> 9723.45 | M3: =ROUND(INDEX(DetailByDistrict[],MATCH($H3,DetailByDistrict[Dist],0),MATCH(M$2,DetailByDistrict[#Headers],0))*K3,2) -> 10830.86
A4: 01 | B4: Keystone AEA | C4: St Patrick School | D4: 0135 | E4: 8102 | F4: Eastern Allamakee Comm School District | G4: 1972 | H4: =_xlfn.IFNA(INDEX(ActiveSchools!$C$2:$F$326,MATCH(G4,ActiveSchools!$F$2:$F$326,0),1),"Total") -> 1972 | I4: 10 | J4: =_xlfn.IFNA(INDEX(DetailByDistrict[],MATCH($H4,DetailByDistrict[Dist],0),MATCH(J$2,DetailByDistrict[#Headers],0)),0) -> 10 | K4: =I4/J4 -> 1 | L4: =ROUND(INDEX(DetailByDistrict[],MATCH($H4,DetailByDistrict[Dist],0),MATCH(L$2,DetailByDistrict[#Headers],0))*K4,2) -> 653 | M4: =ROUND(INDEX(DetailByDistrict[],MATCH($H4,DetailByDistrict[Dist],0),MATCH(M$2,DetailByDistrict[#Headers],0))*K4,2) -> 727
A5: 01 | B5: Keystone AEA | C5: St Patrick School | D5: 0135 | E5: 8102 | F5: MFL MarMac Comm School District | G5: 4419 | H5: =_xlfn.IFNA(INDEX(ActiveSchools!$C$2:$F$326,MATCH(G5,ActiveSchools!$F$2:$F$326,0),1),"Total") -> 4419 | I5: 6 | J5: =_xlfn.IFNA(INDEX(DetailByDistrict[],MATCH($H5,DetailByDistrict[Dist],0),MATCH(J$2,DetailByDistrict[#Headers],0)),0) -> 6 | K5: =I5/J5 -> 1 | L5: =ROUND(INDEX(DetailByDistrict[],MATCH($H5,DetailByDistrict[Dist],0),MATCH(L$2,DetailByDistrict[#Headers],0))*K5,2) -> 392 | M5: =ROUND(INDEX(DetailByDistrict[],MATCH($H5,DetailByDistrict[Dist],0),MATCH(M$2,DetailByDistrict[#Headers],0))*K5,2) -> 436
A6: 01 | B6: Keystone AEA | C6: St Patrick School | D6: 0135 | E6: 8102 | F6: Postville Comm School District | G6: 5310 | H6: =_xlfn.IFNA(INDEX(ActiveSchools!$C$2:$F$326,MATCH(G6,ActiveSchools!$F$2:$F$326,0),1),"Total") -> 5310 | I6: 3 | J6: =_xlfn.IFNA(INDEX(DetailByDistrict[],MATCH($H6,DetailByDistrict[Dist],0),MATCH(J$2,DetailByDistrict[#Headers],0)),0) -> 6 | K6: =I6/J6 -> 0.5 | L6: =ROUND(INDEX(DetailByDistrict[],MATCH($H6,DetailByDistrict[Dist],0),MATCH(L$2,DetailByDistrict[#Headers],0))*K6,2) -> 196 | M6: =ROUND(INDEX(DetailByDistrict[],MATCH($H6,DetailByDistrict[Dist],0),MATCH(M$2,DetailByDistrict[#Headers],0))*K6,2) -> 218
A7: 01 | B7: Keystone AEA | C7: Marquette Catholic Elementary | D7: 0585 | E7: 8107 | F7: Dubuque Comm School District | G7: 1863 | H7: =_xlfn.IFNA(INDEX(ActiveSchools!$C$2:$F$326,MATCH(G7,ActiveSchools!$F$2:$F$326,0),1),"Total") -> 1863 | I7: 23 | J7: =_xlfn.IFNA(INDEX(DetailByDistrict[],MATCH($H7,DetailByDistrict[Dist],0),MATCH(J$2,DetailByDistrict[#Headers],0)),0) -> 1933 | K7: =I7/J7 -> 0.011898603 | L7: =ROUND(INDEX(DetailByDistrict[],MATCH($H7,DetailByDistrict[Dist],0),MATCH(L$2,DetailByDistrict[#Headers],0))*K7,2) -> 1500.98 | M7: =ROUND(INDEX(DetailByDistrict[],MATCH($H7,DetailByDistrict[Dist],0),MATCH(M$2,DetailByDistrict[#Headers],0))*K7,2) -> 1671.87
A8: 01 | B8: Keystone AEA | C8: Marquette Catholic High School | D8: 0585 | E8: 8109 | F8: Dubuque Comm School District | G8: 1863 | H8: =_xlfn.IFNA(INDEX(ActiveSchools!$C$2:$F$326,MATCH(G8,ActiveSchools!$F$2:$F$326,0),1),"Total") -> 1863 | I8: 7 | J8: =_xlfn.IFNA(INDEX(DetailByDistrict[],MATCH($H8,DetailByDistrict[Dist],0),MATCH(J$2,DetailByDistrict[#Headers],0)),0) -> 1933 | K8: =I8/J8 -> 0.003621314 | L8: =ROUND(INDEX(DetailByDistrict[],MATCH($H8,DetailByDistrict[Dist],0),MATCH(L$2,DetailByDistrict[#Headers],0))*K8,2) -> 456.82 | M8: =ROUND(INDEX(DetailByDistrict[],MATCH($H8,DetailByDistrict[Dist],0),MATCH(M$2,DetailByDistrict[#Headers],0))*K8,2) -> 508.83
A9: 01 | B9: Keystone AEA | C9: Immaculate Conception School | D9: 1116 | E9: 8102 | F9: Howard-Winneshiek Comm School District | G9: 3029 | H9: =_xlfn.IFNA(INDEX(ActiveSchools!$C$2:$F$326,MATCH(G9,ActiveSchools!$F$2:$F$326,0),1),"Total") -> 3029 | I9: 1 | J9: =_xlfn.IFNA(INDEX(DetailByDistrict[],MATCH($H9,DetailByDistrict[Dist],0),MATCH(J$2,DetailByDistrict[#Headers],0)),0) -> 120 | K9: =I9/J9 -> 0.0083333333 | L9: =ROUND(INDEX(DetailByDistrict[],MATCH($H9,DetailByDistrict[Dist],0),MATCH(L$2,DetailByDistrict[#Headers],0))*K9,2) -> 65.26 | M9: =ROUND(INDEX(DetailByDistrict[],MATCH($H9,DetailByDistrict[Dist],0),MATCH(M$2,DetailByDistrict[#Headers],0))*K9,2) -> 72.69
A10: 01 | B10: Keystone AEA | C10: Immaculate Conception School | D10: 1116 | E10: 8102 | F10: New Hampton Comm School District | G10: 4662 | H10: =_xlfn.IFNA(INDEX(ActiveSchools!$C$2:$F$326,MATCH(G10,ActiveSchools!$F$2:$F$326,0),1),"Total") -> 4662 | I10: 2 | J10: =_xlfn.IFNA(INDEX(DetailByDistrict[],MATCH($H10,DetailByDistrict[Dist],0),MATCH(J$2,DetailByDistrict[#Headers],0)),0) -> 71 | K10: =I10/J10 -> 0.028169014 | L10: =ROUND(INDEX(DetailByDistrict[],MATCH($H10,DetailByDistrict[Dist],0),MATCH(L$2,DetailByDistrict[#Headers],0))*K10,2) -> 130.51 | M10: =ROUND(INDEX(DetailByDistrict[],MATCH($H10,DetailByDistrict[Dist],0),MATCH(M$2,DetailByDistrict[#Headers],0))*K10,2) -> 145.38
A11: 01 | B11: Keystone AEA | C11: Lighthouse Christian Academy | D11: 1116 | E11: 8106 | F11: Riceville Comm School District | G11: 5508 | H11: =_xlfn.IFNA(INDEX(ActiveSchools!$C$2:$F$326,MATCH(G11,ActiveSchools!$F$2:$F$326,0),1),"Total") -> 5508 | I11: 1 | J11: =_xlfn.IFNA(INDEX(DetailByDistrict[],MATCH($H11,DetailByDistrict[Dist],0),MATCH(J$2,DetailByDistrict[#Headers],0)),0) -> 3 | K11: =I11/J11 -> 0.33333333 | L11: =ROUND(INDEX(DetailByDistrict[],MATCH($H11,DetailByDistrict[Dist],0),MATCH(L$2,DetailByDistrict[#Headers],0))*K11,2) -> 65.33 | M11: =ROUND(INDEX(DetailByDistrict[],MATCH($H11,DetailByDistrict[Dist],0),MATCH(M$2,DetailByDistrict[#Headers],0))*K11,2) -> 72.67
A12: 01 | B12: Keystone AEA | C12: St Benedict School | D12: 1638 | E12: 8102 | F12: Decorah Community School District | G12: 1638 | H12: =_xlfn.IFNA(INDEX(ActiveSchools!$C$2:$F$326,MATCH(G12,ActiveSchools!$F$2:$F$326,0),1),"Total") -> 1638 | I12: 149 | J12: =_xlfn.IFNA(INDEX(DetailByDistrict[],MATCH($H12,DetailByDistrict[Dist],0),MATCH(J$2,DetailByDistrict[#Headers],0)),0) -> 170 | K12: =I12/J12 -> 0.87647059 | L12: =ROUND(INDEX(DetailByDistrict[],MATCH($H12,DetailByDistrict[Dist],0),MATCH(L$2,DetailByDistrict[#Headers],0))*K12,2) -> 9723.56 | M12: =ROUND(INDEX(DetailByDistrict[],MATCH($H12,DetailByDistrict[Dist],0),MATCH(M$2,DetailByDistrict[#Headers],0))*K12,2) -> 10830.55
A13: 01 | B13: Keystone AEA | C13: St Benedict School | D13: 1638 | E13: 8102 | F13: Howard-Winneshiek Comm School District | G13: 3029 | H13: =_xlfn.IFNA(INDEX(ActiveSchools!$C$2:$F$326,MATCH(G13,ActiveSchools!$F$2:$F$326,0),1),"Total") -> 3029 | I13: 3 | J13: =_xlfn.IFNA(INDEX(DetailByDistrict[],MATCH($H13,DetailByDistrict[Dist],0),MATCH(J$2,DetailByDistrict[#Headers],0)),0) -> 120 | K13: =I13/J13 -> 0.025 | L13: =ROUND(INDEX(DetailByDistrict[],MATCH($H13,DetailByDistrict[Dist],0),MATCH(L$2,DetailByDistrict[#Headers],0))*K13,2) -> 195.78 | M13: =ROUND(INDEX(DetailByDistrict[],MATCH($H13,DetailByDistrict[Dist],0),MATCH(M$2,DetailByDistrict[#Headers],0))*K13,2) -> 218.08
A14: 01 | B14: Keystone AEA | C14: St Benedict School | D14: 1638 | E14: 8102 | F14: South Winneshiek Comm School District | G14: 6100 | H14: =_xlfn.IFNA(INDEX(ActiveSchools!$C$2:$F$326,MATCH(G14,ActiveSchools!$F$2:$F$326,0),1),"Total") -> 6100 | I14: 1 | J14: =_xlfn.IFNA(INDEX(DetailByDistrict[],MATCH($H14,DetailByDistrict[Dist],0),MATCH(J$2,DetailByDistrict[#Headers],0)),0) -> 160 | K14: =I14/J14 -> 0.00625 | L14: =ROUND(INDEX(DetailByDistrict[],MATCH($H14,DetailByDistrict[Dist],0),MATCH(L$2,DetailByDistrict[#Headers],0))*K14,2) -> 65.26 | M14: =ROUND(INDEX(DetailByDistrict[],MATCH($H14,DetailByDistrict[Dist],0),MATCH(M$2,DetailByDistrict[#Headers],0))*K14,2) -> 72.69
A15: 01 | B15: Keystone AEA | C15: Northeast Iowa Montessori School | D15: 1638 | E15: 8106 | F15: Allamakee Comm School District | G15: 0135 | H15: =_xlfn.IFNA(INDEX(ActiveSchools!$C$2:$F$326,MATCH(G15,ActiveSchools!$F$2:$F$326,0),1),"Total") -> 0135 | I15: 5 | J15: =_xlfn.IFNA(INDEX(DetailByDistrict[],MATCH($H15,DetailByDistrict[Dist],0),MATCH(J$2,DetailByDistrict[#Headers],0)),0) -> 155 | K15: =I15/J15 -> 0.032258065 | L15: =ROUND(INDEX(DetailByDistrict[],MATCH($H15,DetailByDistrict[Dist],0),MATCH(L$2,DetailByDistrict[#Headers],0))*K15,2) -> 326.29 | M15: =ROUND(INDEX(DetailByDistrict[],MATCH($H15,DetailByDistrict[Dist],0),MATCH(M$2,DetailByDistrict[#Headers],0))*K15,2) -> 363.45
A16: 01 | B16: Keystone AEA | C16: Northeast Iowa Montessori School | D16: 1638 | E16: 8106 | F16: Decorah Community School District | G16: 1638 | H16: =_xlfn.IFNA(INDEX(ActiveSchools!$C$2:$F$326,MATCH(G16,ActiveSchools!$F$2:$F$326,0),1),"Total") -> 1638 | I16: 20 | J16: =_xlfn.IFNA(INDEX(DetailByDistrict[],MATCH($H16,DetailByDistrict[Dist],0),MATCH(J$2,DetailByDistrict[#Headers],0)),0) -> 170 | K16: =I16/J16 -> 0.11764706 | L16: =ROUND(INDEX(DetailByDistrict[],MATCH($H16,DetailByDistrict[Dist],0),MATCH(L$2,DetailByDistrict[#Headers],0))*K16,2) -> 1305.18 | M16: =ROUND(INDEX(DetailByDistrict[],MATCH($H16,DetailByDistrict[Dist],0),MATCH(M$2,DetailByDistrict[#Headers],0))*K16,2) -> 1453.76
A17: 01 | B17: Keystone AEA | C17: St Columbkille School | D17: 1863 | E17: 8122 | F17: Dubuque Comm School District | G17: 1863 | H17: =_xlfn.IFNA(INDEX(ActiveSchools!$C$2:$F$326,MATCH(G17,ActiveSchools!$F$2:$F$326,0),1),"Total") -> 1863 | I17: 268 | J17: =_xlfn.IFNA(INDEX(DetailByDistrict[],MATCH($H17,DetailByDistrict[Dist],0),MATCH(J$2,DetailByDistrict[#Headers],0)),0) -> 1933 | K17: =I17/J17 -> 0.13864459 | L17: =ROUND(INDEX(DetailByDistrict[],MATCH($H17,DetailByDistrict[Dist],0),MATCH(L$2,DetailByDistrict[#Headers],0))*K17,2) -> 17489.74 | M17: =ROUND(INDEX(DetailByDistrict[],MATCH($H17,DetailByDistrict[Dist],0),MATCH(M$2,DetailByDistrict[#Headers],0))*K17,2) -> 19480.95
A18: 01 | B18: Keystone AEA | C18: St Columbkille School | D18: 1863 | E18: 8122 | F18: Western Dubuque Comm School District | G18: 6961 | H18: =_xlfn.IFNA(INDEX(ActiveSchools!$C$2:$F$326,MATCH(G18,ActiveSchools!$F$2:$F$326,0),1),"Total") -> 6961 | I18: 3 | J18: =_xlfn.IFNA(INDEX(DetailByDistrict[],MATCH($H18,DetailByDistrict[Dist],0),MATCH(J$2,DetailByDistrict[#Headers],0)),0) -> 1030 | K18: =I18/J18 -> 0.0029126214 | L18: =ROUND(INDEX(DetailByDistrict[],MATCH($H18,DetailByDistrict[Dist],0),MATCH(L$2,DetailByDistrict[#Headers],0))*K18,2) -> 195.78 | M18: =ROUND(INDEX(DetailByDistrict[],MATCH($H18,DetailByDistrict[Dist],0),MATCH(M$2,DetailByDistrict[#Headers],0))*K18,2) -> 218.07
A19: 01 | B19: Keystone AEA | C19: Our Lady of Guadalupe | D19: 1863 | E19: 8126 | F19: Dubuque Comm School District | G19: 1863 | H19: =_xlfn.IFNA(INDEX(ActiveSchools!$C$2:$F$326,MATCH(G19,ActiveSchools!$F$2:$F$326,0),1),"Total") -> 1863 | I19: 261 | J19: =_xlfn.IFNA(INDEX(DetailByDistrict[],MATCH($H19,DetailByDistrict[Dist],0),MATCH(J$2,DetailByDistrict[#Headers],0)),0) -> 1933 | K19: =I19/J19 -> 0.13502328 | L19: =ROUND(INDEX(DetailByDistrict[],MATCH($H19,DetailByDistrict[Dist],0),MATCH(L$2,DetailByDistrict[#Headers],0))*K19,2) -> 17032.92 | M19: =ROUND(INDEX(DetailByDistrict[],MATCH($H19,DetailByDistrict[Dist],0),MATCH(M$2,DetailByDistrict[#Headers],0))*K19,2) -> 18972.12
A20: 01 | B20: Keystone AEA | C20: Our Lady of Guadalupe | D20: 1863 | E20: 8126 | F20: Western Dubuque Comm School District | G20: 6961 | H20: =_xlfn.IFNA(INDEX(ActiveSchools!$C$2:$F$326,MATCH(G20,ActiveSchools!$F$2:$F$326,0),1),"Total") -> 6961 | I20: 3 | J20: =_xlfn.IFNA(INDEX(DetailByDistrict[],MATCH($H20,DetailByDistrict[Dist],0),MATCH(J$2,DetailByDistrict[#Headers],0)),0) -> 1030 | K20: =I20/J20 -> 0.0029126214 | L20: =ROUND(INDEX(DetailByDistrict[],MATCH($H20,DetailByDistrict[Dist],0),MATCH(L$2,DetailByDistrict[#Headers],0))*K20,2) -> 195.78 | M20: =ROUND(INDEX(DetailByDistrict[],MATCH($H20,DetailByDistrict[Dist],0),MATCH(M$2,DetailByDistrict[#Headers],0))*K20,2) -> 218.07
... A22: 01 | B22: Keystone AEA | C22: Mazzuchelli Catholic Middle School | D22: 1863 | E22: 8128 | F22: Western Dubuque Comm School District | G22: 6961 | H22: =_xlfn.IFNA(INDEX(ActiveSchools!$C$2:$F$326,MATCH(G22,ActiveSchools!$F$2:$F$326,0),1),"Total") -> 6961 | I22: 4 | J22: =_xlfn.IFNA(INDEX(DetailByDistrict[],MATCH($H22,DetailByDistrict[Dist],0),MATCH(J$2,DetailByDistrict[#Headers],0)),0) -> 1030 | K22: =I22/J22 -> 0.0038834951 | L22: =ROUND(INDEX(DetailByDistrict[],MATCH($H22,DetailByDistrict[Dist],0),MATCH(L$2,DetailByDistrict[#Headers],0))*K22,2) -> 261.04 | M22: =ROUND(INDEX(DetailByDistrict[],MATCH($H22,DetailByDistrict[Dist],0),MATCH(M$2,DetailByDistrict[#Headers],0))*K22,2) -> 290.76
A23: 01 | B23: Keystone AEA | C23: Wahlert Catholic High School | D23: 1863 | E23: 8134 | F23: Dubuque Comm School District | G23: 1863 | H23: =_xlfn.IFNA(INDEX(ActiveSchools!$C$2:$F$326,MATCH(G23,ActiveSchools!$F$2:$F$326,0),1),"Total") -> 1863 | I23: 407 | J23: =_xlfn.IFNA(INDEX(DetailByDistrict[],MATCH($H23,DetailByDistrict[Dist],0),MATCH(J$2,DetailByDistrict[#Headers],0)),0) -> 1933 | K23: =I23/J23 -> 0.21055354 | L23: =ROUND(INDEX(DetailByDistrict[],MATCH($H23,DetailByDistrict[Dist],0),MATCH(L$2,DetailByDistrict[#Headers],0))*K23,2)-0.04 -> 26560.87 | M23: =ROUND(INDEX(DetailByDistrict[],MATCH($H23,DetailByDistrict[Dist],0),MATCH(M$2,DetailByDistrict[#Headers],0))*K23,2) -> 29584.88
A24: 01 | B24: Keystone AEA | C24: Wahlert Catholic High School | D24: 1863 | E24: 8134 | F24: Western Dubuque Comm School District | G24: 6961 | H24: =_xlfn.IFNA(INDEX(ActiveSchools!$C$2:$F$326,MATCH(G24,ActiveSchools!$F$2:$F$326,0),1),"Total") -> 6961 | I24: 14 | J24: =_xlfn.IFNA(INDEX(DetailByDistrict[],MATCH($H24,DetailByDistrict[Dist],0),MATCH(J$2,DetailByDistrict[#Headers],0)),0) -> 1030 | K24: =I24/J24 -> 0.013592233 | L24: =ROUND(INDEX(DetailByDistrict[],MATCH($H24,DetailByDistrict[Dist],0),MATCH(L$2,DetailByDistrict[#Headers],0))*K24,2) -> 913.64 | M24: =ROUND(INDEX(DetailByDistrict[],MATCH($H24,DetailByDistrict[Dist],0),MATCH(M$2,DetailByDistrict[#Headers],0))*K24,2) -> 1017.66
A25: 01 | B25: Keystone AEA | C25: Resurrection Elementary | D25: 1863 | E25: 8136 | F25: Dubuque Comm School District | G25: 1863 | H25: =_xlfn.IFNA(INDEX(ActiveSchools!$C$2:$F$326,MATCH(G25,ActiveSchools!$F$2:$F$326,0),1),"Total") -> 1863 | I25: 293 | J25: =_xlfn.IFNA(INDEX(DetailByDistrict[],MATCH($H25,DetailByDistrict[Dist],0),MATCH(J$2,DetailByDistrict[#Headers],0)),0) -> 1933 | K25: =I25/J25 -> 0.15157786 | L25: =ROUND(INDEX(DetailByDistrict[],MATCH($H25,DetailByDistrict[Dist],0),MATCH(L$2,DetailByDistrict[#Headers],0))*K25,2) -> 19121.24 | M25: =ROUND(INDEX(DetailByDistrict[],MATCH($H25,DetailByDistrict[Dist],0),MATCH(M$2,DetailByDistrict[#Headers],0))*K25,2) -> 21298.2
A26: 01 | B26: Keystone AEA | C26: Resurrection Elementary | D26: 1863 | E26: 8136 | F26: Western Dubuque Comm School District | G26: 6961 | H26: =_xlfn.IFNA(INDEX(ActiveSchools!$C$2:$F$326,MATCH(G26,ActiveSchools!$F$2:$F$326,0),1),"Total") -> 6961 | I26: 6 | J26: =_xlfn.IFNA(INDEX(DetailByDistrict[],MATCH($H26,DetailByDistrict[Dist],0),MATCH(J$2,DetailByDistrict[#Headers],0)),0) -> 1030 | K26: =I26/J26 -> 0.0058252427 | L26: =ROUND(INDEX(DetailByDistrict[],MATCH($H26,DetailByDistrict[Dist],0),MATCH(L$2,DetailByDistrict[#Headers],0))*K26,2) -> 391.56 | M26: =ROUND(INDEX(DetailByDistrict[],MATCH($H26,DetailByDistrict[Dist],0),MATCH(M$2,DetailByDistrict[#Headers],0))*K26,2) -> 436.14
A27: 01 | B27: Keystone AEA | C27: Tri-State Christian School (Secondary Campus) | D27: 1863 | E27: 8163 | F27: Dubuque Comm School District | G27: 1863 | H27: =_xlfn.IFNA(INDEX(ActiveSchools!$C$2:$F$326,MATCH(G27,ActiveSchools!$F$2:$F$326,0),1),"Total") -> 1863 | I27: 70 | J27: =_xlfn.IFNA(INDEX(DetailByDistrict[],MATCH($H27,DetailByDistrict[Dist],0),MATCH(J$2,DetailByDistrict[#Headers],0)),0) -> 1933 | K27: =I27/J27 -> 0.03621314 | L27: =ROUND(INDEX(DetailByDistrict[],MATCH($H27,DetailByDistrict[Dist],0),MATCH(L$2,DetailByDistrict[#Headers],0))*K27,2) -> 4568.22 | M27: =ROUND(INDEX(DetailByDistrict[],MATCH($H27,DetailByDistrict[Dist],0),MATCH(M$2,DetailByDistrict[#Headers],0))*K27,2) -> 5088.31
A28: 01 | B28: Keystone AEA | C28: Tri-State Christian School (Secondary Campus) | D28: 1863 | E28: 8163 | F28: Western Dubuque Comm School District | G28: 6961 | H28: =_xlfn.IFNA(INDEX(ActiveSchools!$C$2:$F$326,MATCH(G28,ActiveSchools!$F$2:$F$326,0),1),"Total") -> 6961 | I28: 3 | J28: =_xlfn.IFNA(INDEX(DetailByDistrict[],MATCH($H28,DetailByDistrict[Dist],0),MATCH(J$2,DetailByDistrict[#Headers],0)),0) -> 1030 | K28: =I28/J28 -> 0.0029126214 | L28: =ROUND(INDEX(DetailByDistrict[],MATCH($H28,DetailByDistrict[Dist],0),MATCH(L$2,DetailByDistrict[#Headers],0))*K28,2) -> 195.78 | M28: =ROUND(INDEX(DetailByDistrict[],MATCH($H28,DetailByDistrict[Dist],0),MATCH(M$2,DetailByDistrict[#Headers],0))*K28,2) -> 218.07
A29: 01 | B29: Keystone AEA | C29: Tri-State Christian School (Elementary Campus) | D29: 1863 | E29: 8165 | F29: Dubuque Comm School District | G29: 1863 | H29: =_xlfn.IFNA(INDEX(ActiveSchools!$C$2:$F$326,MATCH(G29,ActiveSchools!$F$2:$F$326,0),1),"Total") -> 1863 | I29: 87 | J29: =_xlfn.IFNA(INDEX(DetailByDistrict[],MATCH($H29,DetailByDistrict[Dist],0),MATCH(J$2,DetailByDistrict[#Headers],0)),0) -> 1933 | K29: =I29/J29 -> 0.04500776 | L29: =ROUND(INDEX(DetailByDistrict[],MATCH($H29,DetailByDistrict[Dist],0),MATCH(L$2,DetailByDistrict[#Headers],0))*K29,2) -> 5677.64 | M29: =ROUND(INDEX(DetailByDistrict[],MATCH($H29,DetailByDistrict[Dist],0),MATCH(M$2,DetailByDistrict[#Headers],0))*K29,2) -> 6324.04
A30: 01 | B30: Keystone AEA | C30: Tri-State Christian School (Elementary Campus) | D30: 1863 | E30: 8165 | F30: Maquoketa Valley Comm School District | G30: 4043 | H30: =_xlfn.IFNA(INDEX(ActiveSchools!$C$2:$F$326,MATCH(G30,ActiveSchools!$F$2:$F$326,0),1),"Total") -> 4043 | I30: 1 | J30: =_xlfn.IFNA(INDEX(DetailByDistrict[],MATCH($H30,DetailByDistrict[Dist],0),MATCH(J$2,DetailByDistrict[#Headers],0)),0) -> 40 | K30: =I30/J30 -> 0.025 | L30: =ROUND(INDEX(DetailByDistrict[],MATCH($H30,DetailByDistrict[Dist],0),MATCH(L$2,DetailByDistrict[#Headers],0))*K30,2) -> 65.25 | M30: =ROUND(INDEX(DetailByDistrict[],MATCH($H30,DetailByDistrict[Dist],0),MATCH(M$2,DetailByDistrict[#Headers],0))*K30,2) -> 72.7
A31: 01 | B31: Keystone AEA | C31: Tri-State Christian School (Elementary Campus) | D31: 1863 | E31: 8165 | F31: Western Dubuque Comm School District | G31: 6961 | H31: =_xlfn.IFNA(INDEX(ActiveSchools!$C$2:$F$326,MATCH(G31,ActiveSchools!$F$2:$F$326,0),1),"Total") -> 6961 | I31: 2 | J31: =_xlfn.IFNA(INDEX(DetailByDistrict[],MATCH($H31,DetailByDistrict[Dist],0),MATCH(J$2,DetailByDistrict[#Headers],0)),0) -> 1030 | K31: =I31/J31 -> 0.0019417476 | L31: =ROUND(INDEX(DetailByDistrict[],MATCH($H31,DetailByDistrict[Dist],0),MATCH(L$2,DetailByDistrict[#Headers],0))*K31,2) -> 130.52 | M31: =ROUND(INDEX(DetailByDistrict[],MATCH($H31,DetailByDistrict[Dist],0),MATCH(M$2,DetailByDistrict[#Headers],0))*K31,2) -> 145.38
A32: 01 | B32: Keystone AEA | C32: Dubuque Dream Center Academy | D32: 1863 | E32: 8170 | F32: Dubuque Comm School District | G32: 1863 | H32: =_xlfn.IFNA(INDEX(ActiveSchools!$C$2:$F$326,MATCH(G32,ActiveSchools!$F$2:$F$326,0),1),"Total") -> 1863 | I32: 90 | J32: =_xlfn.IFNA(INDEX(DetailByDistrict[],MATCH($H32,DetailByDistrict[Dist],0),MATCH(J$2,DetailByDistrict[#Headers],0)),0) -> 1933 | K32: =I32/J32 -> 0.046559752 | L32: =ROUND(INDEX(DetailByDistrict[],MATCH($H32,DetailByDistrict[Dist],0),MATCH(L$2,DetailByDistrict[#Headers],0))*K32,2) -> 5873.42 | M32: =ROUND(INDEX(DetailByDistrict[],MATCH($H32,DetailByDistrict[Dist],0),MATCH(M$2,DetailByDistrict[#Headers],0))*K32,2) -> 6542.11
A33: 01 | B33: Keystone AEA | C33: Notre Dame Elementary School | D33: 3029 | E33: 8104 | F33: Decorah Community School District | G33: 1638 | H33: =_xlfn.IFNA(INDEX(ActiveSchools!$C$2:$F$326,MATCH(G33,ActiveSchools!$F$2:$F$326,0),1),"Total") -> 1638 | I33: 1 | J33: =_xlfn.IFNA(INDEX(DetailByDistrict[],MATCH($H33,DetailByDistrict[Dist],0),MATCH(J$2,DetailByDistrict[#Headers],0)),0) -> 170 | K33: =I33/J33 -> 0.0058823529 | L33: =ROUND(INDEX(DetailByDistrict[],MATCH($H33,DetailByDistrict[Dist],0),MATCH(L$2,DetailByDistrict[#Headers],0))*K33,2) -> 65.26 | M33: =ROUND(INDEX(DetailByDistrict[],MATCH($H33,DetailByDistrict[Dist],0),MATCH(M$2,DetailByDistrict[#Headers],0))*K33,2) -> 72.69
A34: 01 | B34: Keystone AEA | C34: Notre Dame Elementary School | D34: 3029 | E34: 8104 | F34: Howard-Winneshiek Comm School District | G34: 3029 | H34: =_xlfn.IFNA(INDEX(ActiveSchools!$C$2:$F$326,MATCH(G34,ActiveSchools!$F$2:$F$326,0),1),"Total") -> 3029 | I34: 101 | J34: =_xlfn.IFNA(INDEX(DetailByDistrict[],MATCH($H34,DetailByDistrict[Dist],0),MATCH(J$2,DetailByDistrict[#Headers],0)),0) -> 120 | K34: =I34/J34 -> 0.84166667 | L34: =ROUND(INDEX(DetailByDistrict[],MATCH($H34,DetailByDistrict[Dist],0),MATCH(L$2,DetailByDistrict[#Headers],0))*K34,2) -> 6591.09 | M34: =ROUND(INDEX(DetailByDistrict[],MATCH($H34,DetailByDistrict[Dist],0),MATCH(M$2,DetailByDistrict[#Headers],0))*K34,2) -> 7341.86
A35: 01 | B35: Keystone AEA | C35: Notre Dame Elementary School | D35: 3029 | E35: 8104 | F35: Riceville Comm School District | G35: 5508 | H35: =_xlfn.IFNA(INDEX(ActiveSchools!$C$2:$F$326,MATCH(G35,ActiveSchools!$F$2:$F$326,0),1),"Total") -> 5508 | I35: 2 | J35: =_xlfn.IFNA(INDEX(DetailByDistrict[],MATCH($H35,DetailByDistrict[Dist],0),MATCH(J$2,DetailByDistrict[#Headers],0)),0) -> 3 | K35: =I35/J35 -> 0.66666667 | L35: =ROUND(INDEX(DetailByDistrict[],MATCH($H35,DetailByDistrict[Dist],0),MATCH(L$2,DetailByDistrict[#Headers],0))*K35,2) -> 130.67 | M35: =ROUND(INDEX(DetailByDistrict[],MATCH($H35,DetailByDistrict[Dist],0),MATCH(M$2,DetailByDistrict[#Headers],0))*K35,2) -> 145.33
... A50: 01 | B50: Keystone AEA | C50: St Teresa of Calcutta School - Ossian | D50: 6100 | E50: 8105 | F50: North Fayette Valley Comm School District | G50: 4774 | H50: =_xlfn.IFNA(INDEX(ActiveSchools!$C$2:$F$326,MATCH(G50,ActiveSchools!$F$2:$F$326,0),1),"Total") -> 4774 | I50: 2 | J50: =_xlfn.IFNA(INDEX(DetailByDistrict[],MATCH($H50,DetailByDistrict[Dist],0),MATCH(J$2,DetailByDistrict[#Headers],0)),0) -> 2 | K50: =I50/J50 -> 1 | L50: =ROUND(INDEX(DetailByDistrict[],MATCH($H50,DetailByDistrict[Dist],0),MATCH(L$2,DetailByDistrict[#Headers],0))*K50,2) -> 131 | M50: =ROUND(INDEX(DetailByDistrict[],MATCH($H50,DetailByDistrict[Dist],0),MATCH(M$2,DetailByDistrict[#Headers],0))*K50,2) -> 145
A51: 01 | B51: Keystone AEA | C51: St Teresa of Calcutta School - Ossian | D51: 6100 | E51: 8105 | F51: Postville Comm School District | G51: 5310 | H51: =_xlfn.IFNA(INDEX(ActiveSchools!$C$2:$F$326,MATCH(G51,ActiveSchools!$F$2:$F$326,0),1),"Total") -> 5310 | I51: 1 | J51: =_xlfn.IFNA(INDEX(DetailByDistrict[],MATCH($H51,DetailByDistrict[Dist],0),MATCH(J$2,DetailByDistrict[#Headers],0)),0) -> 6 | K51: =I51/J51 -> 0.16666667 | L51: =ROUND(INDEX(DetailByDistrict[],MATCH($H51,DetailByDistrict[Dist],0),MATCH(L$2,DetailByDistrict[#Headers],0))*K51,2) -> 65.33 | M51: =ROUND(INDEX(DetailByDistrict[],MATCH($H51,DetailByDistrict[Dist],0),MATCH(M$2,DetailByDistrict[#Headers],0))*K51,2)+0.02 -> 72.69
A52: 01 | B52: Keystone AEA | C52: St Teresa of Calcutta School - Ossian | D52: 6100 | E52: 8105 | F52: South Winneshiek Comm School District | G52: 6100 | H52: =_xlfn.IFNA(INDEX(ActiveSchools!$C$2:$F$326,MATCH(G52,ActiveSchools!$F$2:$F$326,0),1),"Total") -> 6100 | I52: 117 | J52: =_xlfn.IFNA(INDEX(DetailByDistrict[],MATCH($H52,DetailByDistrict[Dist],0),MATCH(J$2,DetailByDistrict[#Headers],0)),0) -> 160 | K52: =I52/J52 -> 0.73125 | L52: =ROUND(INDEX(DetailByDistrict[],MATCH($H52,DetailByDistrict[Dist],0),MATCH(L$2,DetailByDistrict[#Headers],0))*K52,2) -> 7635.71 | M52: =ROUND(INDEX(DetailByDistrict[],MATCH($H52,DetailByDistrict[Dist],0),MATCH(M$2,DetailByDistrict[#Headers],0))*K52,2) -> 8504.44
A53: 01 | B53: Keystone AEA | C53: St Teresa of Calcutta School - Ossian | D53: 6100 | E53: 8105 | F53: Turkey Valley Comm School District | G53: 6509 | H53: =_xlfn.IFNA(INDEX(ActiveSchools!$C$2:$F$326,MATCH(G53,ActiveSchools!$F$2:$F$326,0),1),"Total") -> 6509 | I53: 6 | J53: =_xlfn.IFNA(INDEX(DetailByDistrict[],MATCH($H53,DetailByDistrict[Dist],0),MATCH(J$2,DetailByDistrict[#Headers],0)),0) -> 54 | K53: =I53/J53 -> 0.11111111 | L53: =ROUND(INDEX(DetailByDistrict[],MATCH($H53,DetailByDistrict[Dist],0),MATCH(L$2,DetailByDistrict[#Headers],0))*K53,2) -> 391.56 | M53: =ROUND(INDEX(DetailByDistrict[],MATCH($H53,DetailByDistrict[Dist],0),MATCH(M$2,DetailByDistrict[#Headers],0))*K53,2) -> 436.11
A54: 01 | B54: Keystone AEA | C54: Trinity Catholic School | D54: 6509 | E54: 8109 | F54: Howard-Winneshiek Comm School District | G54: 3029 | H54: =_xlfn.IFNA(INDEX(ActiveSchools!$C$2:$F$326,MATCH(G54,ActiveSchools!$F$2:$F$326,0),1),"Total") -> 3029 | I54: 5 | J54: =_xlfn.IFNA(INDEX(DetailByDistrict[],MATCH($H54,DetailByDistrict[Dist],0),MATCH(J$2,DetailByDistrict[#Headers],0)),0) -> 120 | K54: =I54/J54 -> 0.041666667 | L54: =ROUND(INDEX(DetailByDistrict[],MATCH($H54,DetailByDistrict[Dist],0),MATCH(L$2,DetailByDistrict[#Headers],0))*K54,2) -> 326.29 | M54: =ROUND(INDEX(DetailByDistrict[],MATCH($H54,DetailByDistrict[Dist],0),MATCH(M$2,DetailByDistrict[#Headers],0))*K54,2) -> 363.46
A55: 01 | B55: Keystone AEA | C55: Trinity Catholic School | D55: 6509 | E55: 8109 | F55: South Winneshiek Comm School District | G55: 6100 | H55: =_xlfn.IFNA(INDEX(ActiveSchools!$C$2:$F$326,MATCH(G55,ActiveSchools!$F$2:$F$326,0),1),"Total") -> 6100 | I55: 3 | J55: =_xlfn.IFNA(INDEX(DetailByDistrict[],MATCH($H55,DetailByDistrict[Dist],0),MATCH(J$2,DetailByDistrict[#Headers],0)),0) -> 160 | K55: =I55/J55 -> 0.01875 | L55: =ROUND(INDEX(DetailByDistrict[],MATCH($H55,DetailByDistrict[Dist],0),MATCH(L$2,DetailByDistrict[#Headers],0))*K55,2) -> 195.79 | M55: =ROUND(INDEX(DetailByDistrict[],MATCH($H55,DetailByDistrict[Dist],0),MATCH(M$2,DetailByDistrict[#Headers],0))*K55,2) -> 218.06
A56: 01 | B56: Keystone AEA | C56: Trinity Catholic School | D56: 6509 | E56: 8109 | F56: Turkey Valley Comm School District | G56: 6509 | H56: =_xlfn.IFNA(INDEX(ActiveSchools!$C$2:$F$326,MATCH(G56,ActiveSchools!$F$2:$F$326,0),1),"Total") -> 6509 | I56: 46 | J56: =_xlfn.IFNA(INDEX(DetailByDistrict[],MATCH($H56,DetailByDistrict[Dist],0),MATCH(J$2,DetailByDistrict[#Headers],0)),0) -> 54 | K56: =I56/J56 -> 0.85185185 | L56: =ROUND(INDEX(DetailByDistrict[],MATCH($H56,DetailByDistrict[Dist],0),MATCH(L$2,DetailByDistrict[#Headers],0))*K56,2) -> 3001.93 | M56: =ROUND(INDEX(DetailByDistrict[],MATCH($H56,DetailByDistrict[Dist],0),MATCH(M$2,DetailByDistrict[#Headers],0))*K56,2) -> 3343.52
A57: 01 | B57: Keystone AEA | C57: Immaculate Conception | D57: 6795 | E57: 8110 | F57: Oelwein Comm School District | G57: 4869 | H57: =_xlfn.IFNA(INDEX(ActiveSchools!$C$2:$F$326,MATCH(G57,ActiveSchools!$F$2:$F$326,0),1),"Total") -> 4869 | I57: 1 | J57: =_xlfn.IFNA(INDEX(DetailByDistrict[],MATCH($H57,DetailByDistrict[Dist],0),MATCH(J$2,DetailByDistrict[#Headers],0)),0) -> 11 | K57: =I57/J57 -> 0.090909091 | L57: =ROUND(INDEX(DetailByDistrict[],MATCH($H57,DetailByDistrict[Dist],0),MATCH(L$2,DetailByDistrict[#Headers],0))*K57,2) -> 65.27 | M57: =ROUND(INDEX(DetailByDistrict[],MATCH($H57,DetailByDistrict[Dist],0),MATCH(M$2,DetailByDistrict[#Headers],0))*K57,2) -> 72.73
A58: 01 | B58: Keystone AEA | C58: Don Bosco High School | D58: 6795 | E58: 8115 | F58: Howard-Winneshiek Comm School District | G58: 3029 | H58: =_xlfn.IFNA(INDEX(ActiveSchools!$C$2:$F$326,MATCH(G58,ActiveSchools!$F$2:$F$326,0),1),"Total") -> 3029 | I58: 1 | J58: =_xlfn.IFNA(INDEX(DetailByDistrict[],MATCH($H58,DetailByDistrict[Dist],0),MATCH(J$2,DetailByDistrict[#Headers],0)),0) -> 120 | K58: =I58/J58 -> 0.0083333333 | L58: =ROUND(INDEX(DetailByDistrict[],MATCH($H58,DetailByDistrict[Dist],0),MATCH(L$2,DetailByDistrict[#Headers],0))*K58,2) -> 65.26 | M58: =ROUND(INDEX(DetailByDistrict[],MATCH($H58,DetailByDistrict[Dist],0),MATCH(M$2,DetailByDistrict[#Headers],0))*K58,2) -> 72.69
A59: 01 | B59: Keystone AEA | C59: Don Bosco High School | D59: 6795 | E59: 8115 | F59: Oelwein Comm School District | G59: 4869 | H59: =_xlfn.IFNA(INDEX(ActiveSchools!$C$2:$F$326,MATCH(G59,ActiveSchools!$F$2:$F$326,0),1),"Total") -> 4869 | I59: 2 | J59: =_xlfn.IFNA(INDEX(DetailByDistrict[],MATCH($H59,DetailByDistrict[Dist],0),MATCH(J$2,DetailByDistrict[#Headers],0)),0) -> 11 | K59: =I59/J59 -> 0.18181818 | L59: =ROUND(INDEX(DetailByDistrict[],MATCH($H59,DetailByDistrict[Dist],0),MATCH(L$2,DetailByDistrict[#Headers],0))*K59,2) -> 130.55 | M59: =ROUND(INDEX(DetailByDistrict[],MATCH($H59,DetailByDistrict[Dist],0),MATCH(M$2,DetailByDistrict[#Headers],0))*K59,2) -> 145.45
A60: 01 | B60: Keystone AEA | C60: St Marys School | D60: 6950 | E60: 8104 | F60: Edgewood-Colesburg Comm School District | G60: 1989 | H60: =_xlfn.IFNA(INDEX(ActiveSchools!$C$2:$F$326,MATCH(G60,ActiveSchools!$F$2:$F$326,0),1),"Total") -> 1989 | I60: 2 | J60: =_xlfn.IFNA(INDEX(DetailByDistrict[],MATCH($H60,DetailByDistrict[Dist],0),MATCH(J$2,DetailByDistrict[#Headers],0)),0) -> 21 | K60: =I60/J60 -> 0.095238095 | L60: =ROUND(INDEX(DetailByDistrict[],MATCH($H60,DetailByDistrict[Dist],0),MATCH(L$2,DetailByDistrict[#Headers],0))*K60,2) -> 130.48 | M60: =ROUND(INDEX(DetailByDistrict[],MATCH($H60,DetailByDistrict[Dist],0),MATCH(M$2,DetailByDistrict[#Headers],0))*K60,2) -> 145.33
A61: 01 | B61: Keystone AEA | C61: St Marys School | D61: 6950 | E61: 8104 | F61: Maquoketa Valley Comm School District | G61: 4043 | H61: =_xlfn.IFNA(INDEX(ActiveSchools!$C$2:$F$326,MATCH(G61,ActiveSchools!$F$2:$F$326,0),1),"Total") -> 4043 | I61: 9 | J61: =_xlfn.IFNA(INDEX(DetailByDistrict[],MATCH($H61,DetailByDistrict[Dist],0),MATCH(J$2,DetailByDistrict[#Headers],0)),0) -> 40 | K61: =I61/J61 -> 0.225 | L61: =ROUND(INDEX(DetailByDistrict[],MATCH($H61,DetailByDistrict[Dist],0),MATCH(L$2,DetailByDistrict[#Headers],0))*K61,2) -> 587.25 | M61: =ROUND(INDEX(DetailByDistrict[],MATCH($H61,DetailByDistrict[Dist],0),MATCH(M$2,DetailByDistrict[#Headers],0))*K61,2) -> 654.3
A62: 01 | B62: Keystone AEA | C62: St Marys School | D62: 6950 | E62: 8104 | F62: West Delaware County Comm School District | G62: 6950 | H62: =_xlfn.IFNA(INDEX(ActiveSchools!$C$2:$F$326,MATCH(G62,ActiveSchools!$F$2:$F$326,0),1),"Total") -> 6950 | I62: 203 | J62: =_xlfn.IFNA(INDEX(DetailByDistrict[],MATCH($H62,DetailByDistrict[Dist],0),MATCH(J$2,DetailByDistrict[#Headers],0)),0) -> 209 | K62: =I62/J62 -> 0.97129187 | L62: =ROUND(INDEX(DetailByDistrict[],MATCH($H62,DetailByDistrict[Dist],0),MATCH(L$2,DetailByDistrict[#Headers],0))*K62,2) -> 13247.45 | M62: =ROUND(INDEX(DetailByDistrict[],MATCH($H62,DetailByDistrict[Dist],0),MATCH(M$2,DetailByDistrict[#Headers],0))*K62,2) -> 14755.87
A63: 01 | B63: Keystone AEA | C63: St Francis Xavier School | D63: 6961 | E63: 8103 | F63: Dubuque Comm School District | G63: 1863 | H63: =_xlfn.IFNA(INDEX(ActiveSchools!$C$2:$F$326,MATCH(G63,ActiveSchools!$F$2:$F$326,0),1),"Total") -> 1863 | I63: 1 | J63: =_xlfn.IFNA(INDEX(DetailByDistrict[],MATCH($H63,DetailByDistrict[Dist],0),MATCH(J$2,DetailByDistrict[#Headers],0)),0) -> 1933 | K63: =I63/J63 -> 0.00051733057 | L63: =ROUND(INDEX(DetailByDistrict[],MATCH($H63,DetailByDistrict[Dist],0),MATCH(L$2,DetailByDistrict[#Headers],0))*K63,2) -> 65.26 | M63: =ROUND(INDEX(DetailByDistrict[],MATCH($H63,DetailByDistrict[Dist],0),MATCH(M$2,DetailByDistrict[#Headers],0))*K63,2) -> 72.69
... A83: 01 | B83: Keystone AEA | C83: Seton Catholic Elem Sch Peosta Center | D83: 6961 | E83: 8157 | F83: Western Dubuque Comm School District | G83: 6961 | H83: =_xlfn.IFNA(INDEX(ActiveSchools!$C$2:$F$326,MATCH(G83,ActiveSchools!$F$2:$F$326,0),1),"Total") -> 6961 | I83: 136 | J83: =_xlfn.IFNA(INDEX(DetailByDistrict[],MATCH($H83,DetailByDistrict[Dist],0),MATCH(J$2,DetailByDistrict[#Headers],0)),0) -> 1030 | K83: =I83/J83 -> 0.13203883 | L83: =ROUND(INDEX(DetailByDistrict[],MATCH($H83,DetailByDistrict[Dist],0),MATCH(L$2,DetailByDistrict[#Headers],0))*K83,2) -> 8875.39 | M83: =ROUND(INDEX(DetailByDistrict[],MATCH($H83,DetailByDistrict[Dist],0),MATCH(M$2,DetailByDistrict[#Headers],0))*K83,2) -> 9885.88
F84: Keystone AEA | G84: Total | H84: =_xlfn.IFNA(INDEX(ActiveSchools!$C$2:$F$326,MATCH(G84,ActiveSchools!$F$2:$F$326,0),1),"Total") -> Total | I84: =SUM(I3:I83) -> 4016 | L84: =SUM(L3:L83) -> 262085 | M84: =SUM(M3:M83) -> 291923
A85: 05 | B85: Prairie Lakes AEA | C85: Seton Grade School | D85: 0126 | E85: 8101 | F85: Algona Comm School District | G85: 0126 | H85: =_xlfn.IFNA(INDEX(ActiveSchools!$C$2:$F$326,MATCH(G85,ActiveSchools!$F$2:$F$326,0),1),"Total") -> 0126 | I85: 83 | J85: =_xlfn.IFNA(INDEX(DetailByDistrict[],MATCH($H85,DetailByDistrict[Dist],0),MATCH(J$2,DetailByDistrict[#Headers],0)),0) -> 324 | K85: =I85/J85 -> 0.25617284 | L85: =ROUND(INDEX(DetailByDistrict[],MATCH($H85,DetailByDistrict[Dist],0),MATCH(L$2,DetailByDistrict[#Headers],0))*K85,2) -> 5423.18 | M85: =ROUND(INDEX(DetailByDistrict[],MATCH($H85,DetailByDistrict[Dist],0),MATCH(M$2,DetailByDistrict[#Headers],0))*K85,2) -> 6072.32
A86: 05 | B86: Prairie Lakes AEA | C86: Seton Grade School | D86: 0126 | E86: 8101 | F86: North Union Comm School District | G86: 0333 | H86: =_xlfn.IFNA(INDEX(ActiveSchools!$C$2:$F$326,MATCH(G86,ActiveSchools!$F$2:$F$326,0),1),"Total") -> 0333 | I86: 2 | J86: =_xlfn.IFNA(INDEX(DetailByDistrict[],MATCH($H86,DetailByDistrict[Dist],0),MATCH(J$2,DetailByDistrict[#Headers],0)),0) -> 14 | K86: =I86/J86 -> 0.14285714 | L86: =ROUND(INDEX(DetailByDistrict[],MATCH($H86,DetailByDistrict[Dist],0),MATCH(L$2,DetailByDistrict[#Headers],0))*K86,2) -> 130.71 | M86: =ROUND(INDEX(DetailByDistrict[],MATCH($H86,DetailByDistrict[Dist],0),MATCH(M$2,DetailByDistrict[#Headers],0))*K86,2) -> 146.29
A87: 05 | B87: Prairie Lakes AEA | C87: Seton Grade School | D87: 0126 | E87: 8101 | F87: Emmetsburg Comm School District | G87: 2088 | H87: =_xlfn.IFNA(INDEX(ActiveSchools!$C$2:$F$326,MATCH(G87,ActiveSchools!$F$2:$F$326,0),1),"Total") -> 2088 | I87: 1 | J87: =_xlfn.IFNA(INDEX(DetailByDistrict[],MATCH($H87,DetailByDistrict[Dist],0),MATCH(J$2,DetailByDistrict[#Headers],0)),0) -> 86 | K87: =I87/J87 -> 0.011627907 | L87: =ROUND(INDEX(DetailByDistrict[],MATCH($H87,DetailByDistrict[Dist],0),MATCH(L$2,DetailByDistrict[#Headers],0))*K87,2) -> 65.34 | M87: =ROUND(INDEX(DetailByDistrict[],MATCH($H87,DetailByDistrict[Dist],0),MATCH(M$2,DetailByDistrict[#Headers],0))*K87,2) -> 73.16
A88: 05 | B88: Prairie Lakes AEA | C88: Seton Grade School | D88: 0126 | E88: 8101 | F88: North Kossuth Comm School District | G88: 4778 | H88: =_xlfn.IFNA(INDEX(ActiveSchools!$C$2:$F$326,MATCH(G88,ActiveSchools!$F$2:$F$326,0),1),"Total") -> 4778 | I88: 3 | J88: =_xlfn.IFNA(INDEX(DetailByDistrict[],MATCH($H88,DetailByDistrict[Dist],0),MATCH(J$2,DetailByDistrict[#Headers],0)),0) -> 25 | K88: =I88/J88 -> 0.12 | L88: =ROUND(INDEX(DetailByDistrict[],MATCH($H88,DetailByDistrict[Dist],0),MATCH(L$2,DetailByDistrict[#Headers],0))*K88,2) -> 196.08 | M88: =ROUND(INDEX(DetailByDistrict[],MATCH($H88,DetailByDistrict[Dist],0),MATCH(M$2,DetailByDistrict[#Headers],0))*K88,2) -> 219.48
A89: 05 | B89: Prairie Lakes AEA | C89: Seton Grade School | D89: 0126 | E89: 8101 | F89: Twin Rivers Comm School District | G89: 6516 | H89: =_xlfn.IFNA(INDEX(ActiveSchools!$C$2:$F$326,MATCH(G89,ActiveSchools!$F$2:$F$326,0),1),"Total") -> 6516 | I89: 3 | J89: =_xlfn.IFNA(INDEX(DetailByDistrict[],MATCH($H89,DetailByDistrict[Dist],0),MATCH(J$2,DetailByDistrict[#Headers],0)),0) -> 18 | K89: =I89/J89 -> 0.16666667 | L89: =ROUND(INDEX(DetailByDistrict[],MATCH($H89,DetailByDistrict[Dist],0),MATCH(L$2,DetailByDistrict[#Headers],0))*K89,2) -> 196 | M89: =ROUND(INDEX(DetailByDistrict[],MATCH($H89,DetailByDistrict[Dist],0),MATCH(M$2,DetailByDistrict[#Headers],0))*K89,2) -> 219.5
A90: 05 | B90: Prairie Lakes AEA | C90: Seton Grade School | D90: 0126 | E90: 8101 | F90: West Bend-Mallard Comm School District | G90: 6921 | H90: =_xlfn.IFNA(INDEX(ActiveSchools!$C$2:$F$326,MATCH(G90,ActiveSchools!$F$2:$F$326,0),1),"Total") -> 6921 | I90: 9 | J90: =_xlfn.IFNA(INDEX(DetailByDistrict[],MATCH($H90,DetailByDistrict[Dist],0),MATCH(J$2,DetailByDistrict[#Headers],0)),0) -> 40 | K90: =I90/J90 -> 0.225 | L90: =ROUND(INDEX(DetailByDistrict[],MATCH($H90,DetailByDistrict[Dist],0),MATCH(L$2,DetailByDistrict[#Headers],0))*K90,2) -> 588.15 | M90: =ROUND(INDEX(DetailByDistrict[],MATCH($H90,DetailByDistrict[Dist],0),MATCH(M$2,DetailByDistrict[#Headers],0))*K90,2) -> 658.35
A91: 05 | B91: Prairie Lakes AEA | C91: Bishop Garrigan Campus | D91: 0126 | E91: 8108 | F91: Algona Comm School District | G91: 0126 | H91: =_xlfn.IFNA(INDEX(ActiveSchools!$C$2:$F$326,MATCH(G91,ActiveSchools!$F$2:$F$326,0),1),"Total") -> 0126 | I91: 239 | J91: =_xlfn.IFNA(INDEX(DetailByDistrict[],MATCH($H91,DetailByDistrict[Dist],0),MATCH(J$2,DetailByDistrict[#Headers],0)),0) -> 324 | K91: =I91/J91 -> 0.73765432 | L91: =ROUND(INDEX(DetailByDistrict[],MATCH($H91,DetailByDistrict[Dist],0),MATCH(L$2,DetailByDistrict[#Headers],0))*K91,2) -> 15616.14 | M91: =ROUND(INDEX(DetailByDistrict[],MATCH($H91,DetailByDistrict[Dist],0),MATCH(M$2,DetailByDistrict[#Headers],0))*K91,2) -> 17485.36
A92: 05 | B92: Prairie Lakes AEA | C92: Bishop Garrigan Campus | D92: 0126 | E92: 8108 | F92: North Union Comm School District | G92: 0333 | H92: =_xlfn.IFNA(INDEX(ActiveSchools!$C$2:$F$326,MATCH(G92,ActiveSchools!$F$2:$F$326,0),1),"Total") -> 0333 | I92: 10 | J92: =_xlfn.IFNA(INDEX(DetailByDistrict[],MATCH($H92,DetailByDistrict[Dist],0),MATCH(J$2,DetailByDistrict[#Headers],0)),0) -> 14 | K92: =I92/J92 -> 0.71428571 | L92: =ROUND(INDEX(DetailByDistrict[],MATCH($H92,DetailByDistrict[Dist],0),MATCH(L$2,DetailByDistrict[#Headers],0))*K92,2) -> 653.57 | M92: =ROUND(INDEX(DetailByDistrict[],MATCH($H92,DetailByDistrict[Dist],0),MATCH(M$2,DetailByDistrict[#Headers],0))*K92,2) -> 731.43
A93: 05 | B93: Prairie Lakes AEA | C93: Bishop Garrigan Campus | D93: 0126 | E93: 8108 | F93: Emmetsburg Comm School District | G93: 2088 | H93: =_xlfn.IFNA(INDEX(ActiveSchools!$C$2:$F$326,MATCH(G93,ActiveSchools!$F$2:$F$326,0),1),"Total") -> 2088 | I93: 8 | J93: =_xlfn.IFNA(INDEX(DetailByDistrict[],MATCH($H93,DetailByDistrict[Dist],0),MATCH(J$2,DetailByDistrict[#Headers],0)),0) -> 86 | K93: =I93/J93 -> 0.093023256 | L93: =ROUND(INDEX(DetailByDistrict[],MATCH($H93,DetailByDistrict[Dist],0),MATCH(L$2,DetailByDistrict[#Headers],0))*K93,2) -> 522.7 | M93: =ROUND(INDEX(DetailByDistrict[],MATCH($H93,DetailByDistrict[Dist],0),MATCH(M$2,DetailByDistrict[#Headers],0))*K93,2) -> 585.3
A94: 05 | B94: Prairie Lakes AEA | C94: Bishop Garrigan Campus | D94: 0126 | E94: 8108 | F94: Humboldt Comm School District | G94: 3060 | H94: =_xlfn.IFNA(INDEX(ActiveSchools!$C$2:$F$326,MATCH(G94,ActiveSchools!$F$2:$F$326,0),1),"Total") -> 3060 | I94: 1 | J94: =_xlfn.IFNA(INDEX(DetailByDistrict[],MATCH($H94,DetailByDistrict[Dist],0),MATCH(J$2,DetailByDistrict[#Headers],0)),0) -> 133 | K94: =I94/J94 -> 0.007518797 | L94: =ROUND(INDEX(DetailByDistrict[],MATCH($H94,DetailByDistrict[Dist],0),MATCH(L$2,DetailByDistrict[#Headers],0))*K94,2) -> 65.34 | M94: =ROUND(INDEX(DetailByDistrict[],MATCH($H94,DetailByDistrict[Dist],0),MATCH(M$2,DetailByDistrict[#Headers],0))*K94,2) -> 73.16
A95: 05 | B95: Prairie Lakes AEA | C95: Bishop Garrigan Campus | D95: 0126 | E95: 8108 | F95: North Kossuth Comm School District | G95: 4778 | H95: =_xlfn.IFNA(INDEX(ActiveSchools!$C$2:$F$326,MATCH(G95,ActiveSchools!$F$2:$F$326,0),1),"Total") -> 4778 | I95: 22 | J95: =_xlfn.IFNA(INDEX(DetailByDistrict[],MATCH($H95,DetailByDistrict[Dist],0),MATCH(J$2,DetailByDistrict[#Headers],0)),0) -> 25 | K95: =I95/J95 -> 0.88 | L95: =ROUND(INDEX(DetailByDistrict[],MATCH($H95,DetailByDistrict[Dist],0),MATCH(L$2,DetailByDistrict[#Headers],0))*K95,2) -> 1437.92 | M95: =ROUND(INDEX(DetailByDistrict[],MATCH($H95,DetailByDistrict[Dist],0),MATCH(M$2,DetailByDistrict[#Headers],0))*K95,2) -> 1609.52
A96: 05 | B96: Prairie Lakes AEA | C96: Bishop Garrigan Campus | D96: 0126 | E96: 8108 | F96: Pocahontas Area Comm School District | G96: 5283 | H96: =_xlfn.IFNA(INDEX(ActiveSchools!$C$2:$F$326,MATCH(G96,ActiveSchools!$F$2:$F$326,0),1),"Total") -> 5283 | I96: 2 | J96: =_xlfn.IFNA(INDEX(DetailByDistrict[],MATCH($H96,DetailByDistrict[Dist],0),MATCH(J$2,DetailByDistrict[#Headers],0)),0) -> 91 | K96: =I96/J96 -> 0.021978022 | L96: =ROUND(INDEX(DetailByDistrict[],MATCH($H96,DetailByDistrict[Dist],0),MATCH(L$2,DetailByDistrict[#Headers],0))*K96,2) -> 130.68 | M96: =ROUND(INDEX(DetailByDistrict[],MATCH($H96,DetailByDistrict[Dist],0),MATCH(M$2,DetailByDistrict[#Headers],0))*K96,2) -> 146.33
... A108: 05 | B108: Prairie Lakes AEA | C108: Kuemper Catholic Grade School | D108: 0999 | E108: 8104 | F108: East Sac County Comm School District | G108: 6741 | H108: =_xlfn.IFNA(INDEX(ActiveSchools!$C$2:$F$326,MATCH(G108,ActiveSchools!$F$2:$F$326,0),1),"Total") -> 6741 | I108: 36 | J108: =_xlfn.IFNA(INDEX(DetailByDistrict[],MATCH($H108,DetailByDistrict[Dist],0),MATCH(J$2,DetailByDistrict[#Headers],0)),0) -> 59 | K108: =I108/J108 -> 0.61016949 | L108: =ROUND(INDEX(DetailByDistrict[],MATCH($H108,DetailByDistrict[Dist],0),MATCH(L$2,DetailByDistrict[#Headers],0))*K108,2) -> 2352.2 | M108: =ROUND(INDEX(DetailByDistrict[],MATCH($H108,DetailByDistrict[Dist],0),MATCH(M$2,DetailByDistrict[#Headers],0))*K108,2) -> 2633.49
A109: 05 | B109: Prairie Lakes AEA | C109: Clear Lake Classical School | D109: 1233 | E109: 8102 | F109: Clarion-Goldfield-Dows Comm School District | G109: 1206 | H109: =_xlfn.IFNA(INDEX(ActiveSchools!$C$2:$F$326,MATCH(G109,ActiveSchools!$F$2:$F$326,0),1),"Total") -> 1206 | I109: 1 | J109: =_xlfn.IFNA(INDEX(DetailByDistrict[],MATCH($H109,DetailByDistrict[Dist],0),MATCH(J$2,DetailByDistrict[#Headers],0)),0) -> 5 | K109: =I109/J109 -> 0.2 | L109: =ROUND(INDEX(DetailByDistrict[],MATCH($H109,DetailByDistrict[Dist],0),MATCH(L$2,DetailByDistrict[#Headers],0))*K109,2) -> 65.4 | M109: =ROUND(INDEX(DetailByDistrict[],MATCH($H109,DetailByDistrict[Dist],0),MATCH(M$2,DetailByDistrict[#Headers],0))*K109,2) -> 73.2
A110: 05 | B110: Prairie Lakes AEA | C110: Emmetsburg Catholic School | D110: 2088 | E110: 8102 | F110: Algona Comm School District | G110: 0126 | H110: =_xlfn.IFNA(INDEX(ActiveSchools!$C$2:$F$326,MATCH(G110,ActiveSchools!$F$2:$F$326,0),1),"Total") -> 0126 | I110: 2 | J110: =_xlfn.IFNA(INDEX(DetailByDistrict[],MATCH($H110,DetailByDistrict[Dist],0),MATCH(J$2,DetailByDistrict[#Headers],0)),0) -> 324 | K110: =I110/J110 -> 0.0061728395 | L110: =ROUND(INDEX(DetailByDistrict[],MATCH($H110,DetailByDistrict[Dist],0),MATCH(L$2,DetailByDistrict[#Headers],0))*K110,2) -> 130.68 | M110: =ROUND(INDEX(DetailByDistrict[],MATCH($H110,DetailByDistrict[Dist],0),MATCH(M$2,DetailByDistrict[#Headers],0))*K110,2) -> 146.32
A111: 05 | B111: Prairie Lakes AEA | C111: Emmetsburg Catholic School | D111: 2088 | E111: 8102 | F111: North Union Comm School District | G111: 0333 | H111: =_xlfn.IFNA(INDEX(ActiveSchools!$C$2:$F$326,MATCH(G111,ActiveSchools!$F$2:$F$326,0),1),"Total") -> 0333 | I111: 2 | J111: =_xlfn.IFNA(INDEX(DetailByDistrict[],MATCH($H111,DetailByDistrict[Dist],0),MATCH(J$2,DetailByDistrict[#Headers],0)),0) -> 14 | K111: =I111/J111 -> 0.14285714 | L111: =ROUND(INDEX(DetailByDistrict[],MATCH($H111,DetailByDistrict[Dist],0),MATCH(L$2,DetailByDistrict[#Headers],0))*K111,2) -> 130.71 | M111: =ROUND(INDEX(DetailByDistrict[],MATCH($H111,DetailByDistrict[Dist],0),MATCH(M$2,DetailByDistrict[#Headers],0))*K111,2) -> 146.29
A112: 05 | B112: Prairie Lakes AEA | C112: Emmetsburg Catholic School | D112: 2088 | E112: 8102 | F112: Emmetsburg Comm School District | G112: 2088 | H112: =_xlfn.IFNA(INDEX(ActiveSchools!$C$2:$F$326,MATCH(G112,ActiveSchools!$F$2:$F$326,0),1),"Total") -> 2088 | I112: 77 | J112: =_xlfn.IFNA(INDEX(DetailByDistrict[],MATCH($H112,DetailByDistrict[Dist],0),MATCH(J$2,DetailByDistrict[#Headers],0)),0) -> 86 | K112: =I112/J112 -> 0.89534884 | L112: =ROUND(INDEX(DetailByDistrict[],MATCH($H112,DetailByDistrict[Dist],0),MATCH(L$2,DetailByDistrict[#Headers],0))*K112,2) -> 5030.97 | M112: =ROUND(INDEX(DetailByDistrict[],MATCH($H112,DetailByDistrict[Dist],0),MATCH(M$2,DetailByDistrict[#Headers],0))*K112,2) -> 5633.53
A113: 05 | B113: Prairie Lakes AEA | C113: Emmetsburg Catholic School | D113: 2088 | E113: 8102 | F113: Graettinger-Terril Comm School District | G113: 2556 | H113: =_xlfn.IFNA(INDEX(ActiveSchools!$C$2:$F$326,MATCH(G113,ActiveSchools!$F$2:$F$326,0),1),"Total") -> 2556 | I113: 3 | J113: =_xlfn.IFNA(INDEX(DetailByDistrict[],MATCH($H113,DetailByDistrict[Dist],0),MATCH(J$2,DetailByDistrict[#Headers],0)),0) -> 6 | K113: =I113/J113 -> 0.5 | L113: =ROUND(INDEX(DetailByDistrict[],MATCH($H113,DetailByDistrict[Dist],0),MATCH(L$2,DetailByDistrict[#Headers],0))*K113,2) -> 196 | M113: =ROUND(INDEX(DetailByDistrict[],MATCH($H113,DetailByDistrict[Dist],0),MATCH(M$2,DetailByDistrict[#Headers],0))*K113,2) -> 219.5
A114: 05 | B114: Prairie Lakes AEA | C114: Emmetsburg Catholic School | D114: 2088 | E114: 8102 | F114: Ruthven-Ayrshire Comm School District | G114: 5724 | H114: =_xlfn.IFNA(INDEX(ActiveSchools!$C$2:$F$326,MATCH(G114,ActiveSchools!$F$2:$F$326,0),1),"Total") -> 5724 | I114: 3 | J114: =_xlfn.IFNA(INDEX(DetailByDistrict[],MATCH($H114,DetailByDistrict[Dist],0),MATCH(J$2,DetailByDistrict[#Headers],0)),0) -> 10 | K114: =I114/J114 -> 0.3 | L114: =ROUND(INDEX(DetailByDistrict[],MATCH($H114,DetailByDistrict[Dist],0),MATCH(L$2,DetailByDistrict[#Headers],0))*K114,2) -> 195.9 | M114: =ROUND(INDEX(DetailByDistrict[],MATCH($H114,DetailByDistrict[Dist],0),MATCH(M$2,DetailByDistrict[#Headers],0))*K114,2) -> 219.6
A115: 05 | B115: Prairie Lakes AEA | C115: Emmetsburg Catholic School | D115: 2088 | E115: 8102 | F115: West Bend-Mallard Comm School District | G115: 6921 | H115: =_xlfn.IFNA(INDEX(ActiveSchools!$C$2:$F$326,MATCH(G115,ActiveSchools!$F$2:$F$326,0),1),"Total") -> 6921 | I115: 4 | J115: =_xlfn.IFNA(INDEX(DetailByDistrict[],MATCH($H115,DetailByDistrict[Dist],0),MATCH(J$2,DetailByDistrict[#Headers],0)),0) -> 40 | K115: =I115/J115 -> 0.1 | L115: =ROUND(INDEX(DetailByDistrict[],MATCH($H115,DetailByDistrict[Dist],0),MATCH(L$2,DetailByDistrict[#Headers],0))*K115,2) -> 261.4 | M115: =ROUND(INDEX(DetailByDistrict[],MATCH($H115,DetailByDistrict[Dist],0),MATCH(M$2,DetailByDistrict[#Headers],0))*K115,2) -> 292.6
A116: 05 | B116: Prairie Lakes AEA | C116: St Edmond Catholic | D116: 2313 | E116: 8104 | F116: Fort Dodge Comm School District | G116: 2313 | H116: =_xlfn.IFNA(INDEX(ActiveSchools!$C$2:$F$326,MATCH(G116,ActiveSchools!$F$2:$F$326,0),1),"Total") -> 2313 | I116: 533 | J116: =_xlfn.IFNA(INDEX(DetailByDistrict[],MATCH($H116,DetailByDistrict[Dist],0),MATCH(J$2,DetailByDistrict[#Headers],0)),0) -> 677 | K116: =I116/J116 -> 0.7872969 | L116: =ROUND(INDEX(DetailByDistrict[],MATCH($H116,DetailByDistrict[Dist],0),MATCH(L$2,DetailByDistrict[#Headers],0))*K116,2)-0.02 -> 34826.06 | M116: =ROUND(INDEX(DetailByDistrict[],MATCH($H116,DetailByDistrict[Dist],0),MATCH(M$2,DetailByDistrict[#Headers],0))*K116,2) -> 38994.03
A117: 05 | B117: Prairie Lakes AEA | C117: St Edmond Catholic | D117: 2313 | E117: 8104 | F117: Humboldt Comm School District | G117: 3060 | H117: =_xlfn.IFNA(INDEX(ActiveSchools!$C$2:$F$326,MATCH(G117,ActiveSchools!$F$2:$F$326,0),1),"Total") -> 3060 | I117: 4 | J117: =_xlfn.IFNA(INDEX(DetailByDistrict[],MATCH($H117,DetailByDistrict[Dist],0),MATCH(J$2,DetailByDistrict[#Headers],0)),0) -> 133 | K117: =I117/J117 -> 0.030075188 | L117: =ROUND(INDEX(DetailByDistrict[],MATCH($H117,DetailByDistrict[Dist],0),MATCH(L$2,DetailByDistrict[#Headers],0))*K117,2) -> 261.35 | M117: =ROUND(INDEX(DetailByDistrict[],MATCH($H117,DetailByDistrict[Dist],0),MATCH(M$2,DetailByDistrict[#Headers],0))*K117,2) -> 292.63
A118: 05 | B118: Prairie Lakes AEA | C118: St Edmond Catholic | D118: 2313 | E118: 8104 | F118: Manson Northwest Webster Comm School District | G118: 4023 | H118: =_xlfn.IFNA(INDEX(ActiveSchools!$C$2:$F$326,MATCH(G118,ActiveSchools!$F$2:$F$326,0),1),"Total") -> 4023 | I118: 52 | J118: =_xlfn.IFNA(INDEX(DetailByDistrict[],MATCH($H118,DetailByDistrict[Dist],0),MATCH(J$2,DetailByDistrict[#Headers],0)),0) -> 78 | K118: =I118/J118 -> 0.66666667 | L118: =ROUND(INDEX(DetailByDistrict[],MATCH($H118,DetailByDistrict[Dist],0),MATCH(L$2,DetailByDistrict[#Headers],0))*K118,2) -> 3398 | M118: =ROUND(INDEX(DetailByDistrict[],MATCH($H118,DetailByDistrict[Dist],0),MATCH(M$2,DetailByDistrict[#Headers],0))*K118,2) -> 3804
A119: 05 | B119: Prairie Lakes AEA | C119: St Edmond Catholic | D119: 2313 | E119: 8104 | F119: Pocahontas Area Comm School District | G119: 5283 | H119: =_xlfn.IFNA(INDEX(ActiveSchools!$C$2:$F$326,MATCH(G119,ActiveSchools!$F$2:$F$326,0),1),"Total") -> 5283 | I119: 2 | J119: =_xlfn.IFNA(INDEX(DetailByDistrict[],MATCH($H119,DetailByDistrict[Dist],0),MATCH(J$2,DetailByDistrict[#Headers],0)),0) -> 91 | K119: =I119/J119 -> 0.021978022 | L119: =ROUND(INDEX(DetailByDistrict[],MATCH($H119,DetailByDistrict[Dist],0),MATCH(L$2,DetailByDistrict[#Headers],0))*K119,2) -> 130.68 | M119: =ROUND(INDEX(DetailByDistrict[],MATCH($H119,DetailByDistrict[Dist],0),MATCH(M$2,DetailByDistrict[#Headers],0))*K119,2) -> 146.33
A120: 05 | B120: Prairie Lakes AEA | C120: St Edmond Catholic | D120: 2313 | E120: 8104 | F120: Southeast Valley Comm School District | G120: 6096 | H120: =_xlfn.IFNA(INDEX(ActiveSchools!$C$2:$F$326,MATCH(G120,ActiveSchools!$F$2:$F$326,0),1),"Total") -> 6096 | I120: 19 | J120: =_xlfn.IFNA(INDEX(DetailByDistrict[],MATCH($H120,DetailByDistrict[Dist],0),MATCH(J$2,DetailByDistrict[#Headers],0)),0) -> 25 | K120: =I120/J120 -> 0.76 | L120: =ROUND(INDEX(DetailByDistrict[],MATCH($H120,DetailByDistrict[Dist],0),MATCH(L$2,DetailByDistrict[#Headers],0))*K120,2) -> 1241.84 | M120: =ROUND(INDEX(DetailByDistrict[],MATCH($H120,DetailByDistrict[Dist],0),MATCH(M$2,DetailByDistrict[#Headers],0))*K120,2) -> 1390.04
A121: 05 | B121: Prairie Lakes AEA | C121: St Edmond Catholic | D121: 2313 | E121: 8104 | F121: Stratford Comm School District | G121: 6246 | H121: =_xlfn.IFNA(INDEX(ActiveSchools!$C$2:$F$326,MATCH(G121,ActiveSchools!$F$2:$F$326,0),1),"Total") -> 6246 | I121: 4 | J121: =_xlfn.IFNA(INDEX(DetailByDistrict[],MATCH($H121,DetailByDistrict[Dist],0),MATCH(J$2,DetailByDistrict[#Headers],0)),0) -> 6 | K121: =I121/J121 -> 0.66666667 | L121: =ROUND(INDEX(DetailByDistrict[],MATCH($H121,DetailByDistrict[Dist],0),MATCH(L$2,DetailByDistrict[#Headers],0))*K121,2) -> 261.33 | M121: =ROUND(INDEX(DetailByDistrict[],MATCH($H121,DetailByDistrict[Dist],0),MATCH(M$2,DetailByDistrict[#Headers],0))*K121,2) -> 292.67
A122: 05 | B122: Prairie Lakes AEA | C122: St Edmond Catholic | D122: 2313 | E122: 8104 | F122: Webster City Comm School District | G122: 6867 | H122: =_xlfn.IFNA(INDEX(ActiveSchools!$C$2:$F$326,MATCH(G122,ActiveSchools!$F$2:$F$326,0),1),"Total") -> 6867 | I122: 12 | J122: =_xlfn.IFNA(INDEX(DetailByDistrict[],MATCH($H122,DetailByDistrict[Dist],0),MATCH(J$2,DetailByDistrict[#Headers],0)),0) -> 90 | K122: =I122/J122 -> 0.13333333 | L122: =ROUND(INDEX(DetailByDistrict[],MATCH($H122,DetailByDistrict[Dist],0),MATCH(L$2,DetailByDistrict[#Headers],0))*K122,2) -> 784.13 | M122: =ROUND(INDEX(DetailByDistrict[],MATCH($H122,DetailByDistrict[Dist],0),MATCH(M$2,DetailByDistrict[#Headers],0))*K122,2) -> 877.87
A123: 05 | B123: Prairie Lakes AEA | C123: St Paul Lutheran School | D123: 2313 | E123: 8206 | F123: Eagle Grove Comm School District | G123: 1944 | H123: =_xlfn.IFNA(INDEX(ActiveSchools!$C$2:$F$326,MATCH(G123,ActiveSchools!$F$2:$F$326,0),1),"Total") -> 1944 | I123: 2 | J123: =_xlfn.IFNA(INDEX(DetailByDistrict[],MATCH($H123,DetailByDistrict[Dist],0),MATCH(J$2,DetailByDistrict[#Headers],0)),0) -> 6 | K123: =I123/J123 -> 0.33333333 | L123: =ROUND(INDEX(DetailByDistrict[],MATCH($H123,DetailByDistrict[Dist],0),MATCH(L$2,DetailByDistrict[#Headers],0))*K123,2) -> 130.67 | M123: =ROUND(INDEX(DetailByDistrict[],MATCH($H123,DetailByDistrict[Dist],0),MATCH(M$2,DetailByDistrict[#Headers],0))*K123,2) -> 146.33
A124: 05 | B124: Prairie Lakes AEA | C124: St Paul Lutheran School | D124: 2313 | E124: 8206 | F124: Fort Dodge Comm School District | G124: 2313 | H124: =_xlfn.IFNA(INDEX(ActiveSchools!$C$2:$F$326,MATCH(G124,ActiveSchools!$F$2:$F$326,0),1),"Total") -> 2313 | I124: 84 | J124: =_xlfn.IFNA(INDEX(DetailByDistrict[],MATCH($H124,DetailByDistrict[Dist],0),MATCH(J$2,DetailByDistrict[#Headers],0)),0) -> 677 | K124: =I124/J124 -> 0.12407681 | L124: =ROUND(INDEX(DetailByDistrict[],MATCH($H124,DetailByDistrict[Dist],0),MATCH(L$2,DetailByDistrict[#Headers],0))*K124,2) -> 5488.54 | M124: =ROUND(INDEX(DetailByDistrict[],MATCH($H124,DetailByDistrict[Dist],0),MATCH(M$2,DetailByDistrict[#Headers],0))*K124,2) -> 6145.4
A125: 05 | B125: Prairie Lakes AEA | C125: St Paul Lutheran School | D125: 2313 | E125: 8206 | F125: Manson Northwest Webster Comm School District | G125: 4023 | H125: =_xlfn.IFNA(INDEX(ActiveSchools!$C$2:$F$326,MATCH(G125,ActiveSchools!$F$2:$F$326,0),1),"Total") -> 4023 | I125: 8 | J125: =_xlfn.IFNA(INDEX(DetailByDistrict[],MATCH($H125,DetailByDistrict[Dist],0),MATCH(J$2,DetailByDistrict[#Headers],0)),0) -> 78 | K125: =I125/J125 -> 0.1025641 | L125: =ROUND(INDEX(DetailByDistrict[],MATCH($H125,DetailByDistrict[Dist],0),MATCH(L$2,DetailByDistrict[#Headers],0))*K125,2) -> 522.77 | M125: =ROUND(INDEX(DetailByDistrict[],MATCH($H125,DetailByDistrict[Dist],0),MATCH(M$2,DetailByDistrict[#Headers],0))*K125,2) -> 585.23
A126: 05 | B126: Prairie Lakes AEA | C126: St Paul Lutheran School | D126: 2313 | E126: 8206 | F126: Southeast Valley Comm School District | G126: 6096 | H126: =_xlfn.IFNA(INDEX(ActiveSchools!$C$2:$F$326,MATCH(G126,ActiveSchools!$F$2:$F$326,0),1),"Total") -> 6096 | I126: 2 | J126: =_xlfn.IFNA(INDEX(DetailByDistrict[],MATCH($H126,DetailByDistrict[Dist],0),MATCH(J$2,DetailByDistrict[#Headers],0)),0) -> 25 | K126: =I126/J126 -> 0.08 | L126: =ROUND(INDEX(DetailByDistrict[],MATCH($H126,DetailByDistrict[Dist],0),MATCH(L$2,DetailByDistrict[#Headers],0))*K126,2) -> 130.72 | M126: =ROUND(INDEX(DetailByDistrict[],MATCH($H126,DetailByDistrict[Dist],0),MATCH(M$2,DetailByDistrict[#Headers],0))*K126,2) -> 146.32
A127: 05 | B127: Prairie Lakes AEA | C127: Community Christian School | D127: 2313 | E127: 8301 | F127: Eagle Grove Comm School District | G127: 1944 | H127: =_xlfn.IFNA(INDEX(ActiveSchools!$C$2:$F$326,MATCH(G127,ActiveSchools!$F$2:$F$326,0),1),"Total") -> 1944 | I127: 2 | J127: =_xlfn.IFNA(INDEX(DetailByDistrict[],MATCH($H127,DetailByDistrict[Dist],0),MATCH(J$2,DetailByDistrict[#Headers],0)),0) -> 6 | K127: =I127/J127 -> 0.33333333 | L127: =ROUND(INDEX(DetailByDistrict[],MATCH($H127,DetailByDistrict[Dist],0),MATCH(L$2,DetailByDistrict[#Headers],0))*K127,2) -> 130.67 | M127: =ROUND(INDEX(DetailByDistrict[],MATCH($H127,DetailByDistrict[Dist],0),MATCH(M$2,DetailByDistrict[#Headers],0))*K127,2) -> 146.33
A128: 05 | B128: Prairie Lakes AEA | C128: Community Christian School | D128: 2313 | E128: 8301 | F128: Fort Dodge Comm School District | G128: 2313 | H128: =_xlfn.IFNA(INDEX(ActiveSchools!$C$2:$F$326,MATCH(G128,ActiveSchools!$F$2:$F$326,0),1),"Total") -> 2313 | I128: 59 | J128: =_xlfn.IFNA(INDEX(DetailByDistrict[],MATCH($H128,DetailByDistrict[Dist],0),MATCH(J$2,DetailByDistrict[#Headers],0)),0) -> 677 | K128: =I128/J128 -> 0.087149188 | L128: =ROUND(INDEX(DetailByDistrict[],MATCH($H128,DetailByDistrict[Dist],0),MATCH(L$2,DetailByDistrict[#Headers],0))*K128,2) -> 3855.04 | M128: =ROUND(INDEX(DetailByDistrict[],MATCH($H128,DetailByDistrict[Dist],0),MATCH(M$2,DetailByDistrict[#Headers],0))*K128,2) -> 4316.41
... A169: 05 | B169: Prairie Lakes AEA | C169: St Thomas Aquinas School | D169: 6867 | E169: 8102 | F169: Webster City Comm School District | G169: 6867 | H169: =_xlfn.IFNA(INDEX(ActiveSchools!$C$2:$F$326,MATCH(G169,ActiveSchools!$F$2:$F$326,0),1),"Total") -> 6867 | I169: 75 | J169: =_xlfn.IFNA(INDEX(DetailByDistrict[],MATCH($H169,DetailByDistrict[Dist],0),MATCH(J$2,DetailByDistrict[#Headers],0)),0) -> 90 | K169: =I169/J169 -> 0.83333333 | L169: =ROUND(INDEX(DetailByDistrict[],MATCH($H169,DetailByDistrict[Dist],0),MATCH(L$2,DetailByDistrict[#Headers],0))*K169,2) -> 4900.83 | M169: =ROUND(INDEX(DetailByDistrict[],MATCH($H169,DetailByDistrict[Dist],0),MATCH(M$2,DetailByDistrict[#Headers],0))*K169,2) -> 5486.67
F170: Prairie Lakes AEA | G170: Total | H170: =_xlfn.IFNA(INDEX(ActiveSchools!$C$2:$F$326,MATCH(G170,ActiveSchools!$F$2:$F$326,0),1),"Total") -> Total | I170: =SUM(I85:I169) -> 2303 | J170: =_xlfn.IFNA(INDEX(DetailByDistrict[],MATCH($H170,DetailByDistrict[Dist],0),MATCH(J$2,DetailByDistrict[#Headers],0)),0) -> 0 | K170: =I170/J170 -> #DIV/0! | L170: =SUM(L85:L169) -> 150479 | M170: =SUM(M85:M169) -> 168486
