Workbook
Name AEA_Name: #REF!
Name AEA_Name: #REF!
Name Slicer_AEA_Name: #N/A

Sheet Summary
C1: =Detail[[#Headers],[Total Special Ed Weighting in Addition to 1.0]] -> Total Special Ed Weighting in Addition to 1.0 | D1: =Detail[[#Headers],[Budget Enrollment]] -> Budget Enrollment | E1: =Detail[[#Headers],[AEA Weighted Enrollment]] -> AEA Weighted Enrollment | F1: =Detail[[#Headers],[Resident Accredited Nonpublic Students]] -> Resident Accredited Nonpublic Students | G1: =Detail[[#Headers],[Shared-Time Nonpublic Pupils Counted in Line 1.1]] -> Shared-Time Nonpublic Pupils Counted in Line 1.1 | H1: =Detail[[#Headers],[Total Enrollment Served - AEA Media and Ed Services]] -> Total Enrollment Served - AEA Media and Ed Services | I1: =Detail[[#Headers],[AEA Special Ed Support Cost Per Pupil]] -> AEA Special Ed Support Cost Per Pupil | J1: =Detail[[#Headers],[AEA Media Cost Per Pupil]] -> AEA Media Cost Per Pupil | K1: =Detail[[#Headers],[AEA Ed Services Cost Per Pupil]] -> AEA Ed Services Cost Per Pupil
A2: AEA | B2: AEA Name | C2: Special Ed Weights | D2: Budget Enrollment | E2: Weighted Enrollment | F2: Nonpublic | G2: Shared-Time | H2: Media/Ed Served | I2: Support Cost PP | J2: Media Cost PP | K2: Ed Cost PP
A3: {=IFERROR(INDEX(Detail[AEA], MATCH(0,COUNTIF(Summary!$A$2:'Summary'!A2, Detail[AEA]), 0)),"")} -> 01 | B3: =INDEX(Detail[],MATCH(Summary!$A3,Detail[AEA],0),2) -> Keystone AEA 1 | C3: =SUMIFS(INDEX(Detail[],0,MATCH(C$1,Detail[#Headers],0)),Detail[AEA],$A3) -> 4438.62 | D3: =SUMIFS(INDEX(Detail[],0,MATCH(D$1,Detail[#Headers],0)),Detail[AEA],$A3) -> 27757.8 | E3: =SUMIFS(INDEX(Detail[],0,MATCH(E$1,Detail[#Headers],0)),Detail[AEA],$A3) -> 32196.42 | F3: =SUMIFS(INDEX(Detail[],0,MATCH(F$1,Detail[#Headers],0)),Detail[AEA],$A3) -> 3820 | G3: =SUMIFS(INDEX(Detail[],0,MATCH(G$1,Detail[#Headers],0)),Detail[AEA],$A3) -> 20.5 | H3: =SUMIFS(INDEX(Detail[],0,MATCH(H$1,Detail[#Headers],0)),Detail[AEA],$A3) -> 31557 | I3: =INDEX(Detail[],MATCH($A3,Detail[AEA],0),MATCH(I$1,Detail[#Headers],0)) -> 356.48 | J3: =INDEX(Detail[],MATCH($A3,Detail[AEA],0),MATCH(J$1,Detail[#Headers],0)) -> 63.99 | K3: =INDEX(Detail[],MATCH($A3,Detail[AEA],0),MATCH(K$1,Detail[#Headers],0)) -> 71.28
A4: {=IFERROR(INDEX(Detail[AEA], MATCH(0,COUNTIF(Summary!$A$2:'Summary'!A3, Detail[AEA]), 0)),"")} -> 05 | B4: =INDEX(Detail[],MATCH(Summary!$A4,Detail[AEA],0),2) -> Prairie Lakes AEA 8 | C4: =SUMIFS(INDEX(Detail[],0,MATCH(C$1,Detail[#Headers],0)),Detail[AEA],$A4) -> 3841.8 | D4: =SUMIFS(INDEX(Detail[],0,MATCH(D$1,Detail[#Headers],0)),Detail[AEA],$A4) -> 29814.9 | E4: =SUMIFS(INDEX(Detail[],0,MATCH(E$1,Detail[#Headers],0)),Detail[AEA],$A4) -> 33656.7 | F4: =SUMIFS(INDEX(Detail[],0,MATCH(F$1,Detail[#Headers],0)),Detail[AEA],$A4) -> 2076 | G4: =SUMIFS(INDEX(Detail[],0,MATCH(G$1,Detail[#Headers],0)),Detail[AEA],$A4) -> 24.4 | H4: =SUMIFS(INDEX(Detail[],0,MATCH(H$1,Detail[#Headers],0)),Detail[AEA],$A4) -> 31869 | I4: =INDEX(Detail[],MATCH($A4,Detail[AEA],0),MATCH(I$1,Detail[#Headers],0)) -> 352.23 | J4: =INDEX(Detail[],MATCH($A4,Detail[AEA],0),MATCH(J$1,Detail[#Headers],0)) -> 64.07 | K4: =INDEX(Detail[],MATCH($A4,Detail[AEA],0),MATCH(K$1,Detail[#Headers],0)) -> 71.75
A5: {=IFERROR(INDEX(Detail[AEA], MATCH(0,COUNTIF(Summary!$A$2:'Summary'!A4, Detail[AEA]), 0)),"")} -> 07 | B5: =INDEX(Detail[],MATCH(Summary!$A5,Detail[AEA],0),2) -> Central Rivers | C5: =SUMIFS(INDEX(Detail[],0,MATCH(C$1,Detail[#Headers],0)),Detail[AEA],$A5) -> 9442.65 | D5: =SUMIFS(INDEX(Detail[],0,MATCH(D$1,Detail[#Headers],0)),Detail[AEA],$A5) -> 60817.1 | E5: =SUMIFS(INDEX(Detail[],0,MATCH(E$1,Detail[#Headers],0)),Detail[AEA],$A5) -> 70259.75 | F5: =SUMIFS(INDEX(Detail[],0,MATCH(F$1,Detail[#Headers],0)),Detail[AEA],$A5) -> 3508 | G5: =SUMIFS(INDEX(Detail[],0,MATCH(G$1,Detail[#Headers],0)),Detail[AEA],$A5) -> 52.4 | H5: =SUMIFS(INDEX(Detail[],0,MATCH(H$1,Detail[#Headers],0)),Detail[AEA],$A5) -> 64274 | I5: =INDEX(Detail[],MATCH($A5,Detail[AEA],0),MATCH(I$1,Detail[#Headers],0)) -> 345.6 | J5: =INDEX(Detail[],MATCH($A5,Detail[AEA],0),MATCH(J$1,Detail[#Headers],0)) -> 64.02 | K5: =INDEX(Detail[],MATCH($A5,Detail[AEA],0),MATCH(K$1,Detail[#Headers],0)) -> 71.37
A6: {=IFERROR(INDEX(Detail[AEA], MATCH(0,COUNTIF(Summary!$A$2:'Summary'!A5, Detail[AEA]), 0)),"")} -> 09 | B6: =INDEX(Detail[],MATCH(Summary!$A6,Detail[AEA],0),2) -> Mississippi Bend AEA 9 | C6: =SUMIFS(INDEX(Detail[],0,MATCH(C$1,Detail[#Headers],0)),Detail[AEA],$A6) -> 6529.02 | D6: =SUMIFS(INDEX(Detail[],0,MATCH(D$1,Detail[#Headers],0)),Detail[AEA],$A6) -> 44440.4 | E6: =SUMIFS(INDEX(Detail[],0,MATCH(E$1,Detail[#Headers],0)),Detail[AEA],$A6) -> 50969.42 | F6: =SUMIFS(INDEX(Detail[],0,MATCH(F$1,Detail[#Headers],0)),Detail[AEA],$A6) -> 3409 | G6: =SUMIFS(INDEX(Detail[],0,MATCH(G$1,Detail[#Headers],0)),Detail[AEA],$A6) -> 7.6 | H6: =SUMIFS(INDEX(Detail[],0,MATCH(H$1,Detail[#Headers],0)),Detail[AEA],$A6) -> 47841 | I6: =INDEX(Detail[],MATCH($A6,Detail[AEA],0),MATCH(I$1,Detail[#Headers],0)) -> 343.24 | J6: =INDEX(Detail[],MATCH($A6,Detail[AEA],0),MATCH(J$1,Detail[#Headers],0)) -> 63.53 | K6: =INDEX(Detail[],MATCH($A6,Detail[AEA],0),MATCH(K$1,Detail[#Headers],0)) -> 69.45
A7: {=IFERROR(INDEX(Detail[AEA], MATCH(0,COUNTIF(Summary!$A$2:'Summary'!A6, Detail[AEA]), 0)),"")} -> 10 | B7: =INDEX(Detail[],MATCH(Summary!$A7,Detail[AEA],0),2) -> Grant Wood AEA 10 | C7: =SUMIFS(INDEX(Detail[],0,MATCH(C$1,Detail[#Headers],0)),Detail[AEA],$A7) -> 8401.1 | D7: =SUMIFS(INDEX(Detail[],0,MATCH(D$1,Detail[#Headers],0)),Detail[AEA],$A7) -> 69189.5 | E7: =SUMIFS(INDEX(Detail[],0,MATCH(E$1,Detail[#Headers],0)),Detail[AEA],$A7) -> 77590.6 | F7: =SUMIFS(INDEX(Detail[],0,MATCH(F$1,Detail[#Headers],0)),Detail[AEA],$A7) -> 4830 | G7: =SUMIFS(INDEX(Detail[],0,MATCH(G$1,Detail[#Headers],0)),Detail[AEA],$A7) -> 20.9 | H7: =SUMIFS(INDEX(Detail[],0,MATCH(H$1,Detail[#Headers],0)),Detail[AEA],$A7) -> 74001 | I7: =INDEX(Detail[],MATCH($A7,Detail[AEA],0),MATCH(I$1,Detail[#Headers],0)) -> 341.32 | J7: =INDEX(Detail[],MATCH($A7,Detail[AEA],0),MATCH(J$1,Detail[#Headers],0)) -> 63.71 | K7: =INDEX(Detail[],MATCH($A7,Detail[AEA],0),MATCH(K$1,Detail[#Headers],0)) -> 70.05
A8: {=IFERROR(INDEX(Detail[AEA], MATCH(0,COUNTIF(Summary!$A$2:'Summary'!A7, Detail[AEA]), 0)),"")} -> 11 | B8: =INDEX(Detail[],MATCH(Summary!$A8,Detail[AEA],0),2) -> Heartland AEA 11 | C8: =SUMIFS(INDEX(Detail[],0,MATCH(C$1,Detail[#Headers],0)),Detail[AEA],$A8) -> 19285.99 | D8: =SUMIFS(INDEX(Detail[],0,MATCH(D$1,Detail[#Headers],0)),Detail[AEA],$A8) -> 142253.1 | E8: =SUMIFS(INDEX(Detail[],0,MATCH(E$1,Detail[#Headers],0)),Detail[AEA],$A8) -> 161539.09 | F8: =SUMIFS(INDEX(Detail[],0,MATCH(F$1,Detail[#Headers],0)),Detail[AEA],$A8) -> 10534 | G8: =SUMIFS(INDEX(Detail[],0,MATCH(G$1,Detail[#Headers],0)),Detail[AEA],$A8) -> 93.6 | H8: =SUMIFS(INDEX(Detail[],0,MATCH(H$1,Detail[#Headers],0)),Detail[AEA],$A8) -> 152700 | I8: =INDEX(Detail[],MATCH($A8,Detail[AEA],0),MATCH(I$1,Detail[#Headers],0)) -> 334.22 | J8: =INDEX(Detail[],MATCH($A8,Detail[AEA],0),MATCH(J$1,Detail[#Headers],0)) -> 63.59 | K8: =INDEX(Detail[],MATCH($A8,Detail[AEA],0),MATCH(K$1,Detail[#Headers],0)) -> 69.87
A9: {=IFERROR(INDEX(Detail[AEA], MATCH(0,COUNTIF(Summary!$A$2:'Summary'!A8, Detail[AEA]), 0)),"")} -> 12 | B9: =INDEX(Detail[],MATCH(Summary!$A9,Detail[AEA],0),2) -> Northwest AEA | C9: =SUMIFS(INDEX(Detail[],0,MATCH(C$1,Detail[#Headers],0)),Detail[AEA],$A9) -> 5795.66 | D9: =SUMIFS(INDEX(Detail[],0,MATCH(D$1,Detail[#Headers],0)),Detail[AEA],$A9) -> 39403.5 | E9: =SUMIFS(INDEX(Detail[],0,MATCH(E$1,Detail[#Headers],0)),Detail[AEA],$A9) -> 45199.16 | F9: =SUMIFS(INDEX(Detail[],0,MATCH(F$1,Detail[#Headers],0)),Detail[AEA],$A9) -> 5566 | G9: =SUMIFS(INDEX(Detail[],0,MATCH(G$1,Detail[#Headers],0)),Detail[AEA],$A9) -> 36.7 | H9: =SUMIFS(INDEX(Detail[],0,MATCH(H$1,Detail[#Headers],0)),Detail[AEA],$A9) -> 44932 | I9: =INDEX(Detail[],MATCH($A9,Detail[AEA],0),MATCH(I$1,Detail[#Headers],0)) -> 348.86 | J9: =INDEX(Detail[],MATCH($A9,Detail[AEA],0),MATCH(J$1,Detail[#Headers],0)) -> 64 | K9: =INDEX(Detail[],MATCH($A9,Detail[AEA],0),MATCH(K$1,Detail[#Headers],0)) -> 71.65
A10: {=IFERROR(INDEX(Detail[AEA], MATCH(0,COUNTIF(Summary!$A$2:'Summary'!A9, Detail[AEA]), 0)),"")} -> 13 | B10: =INDEX(Detail[],MATCH(Summary!$A10,Detail[AEA],0),2) -> Green Hills AEA 13 | C10: =SUMIFS(INDEX(Detail[],0,MATCH(C$1,Detail[#Headers],0)),Detail[AEA],$A10) -> 6032.86 | D10: =SUMIFS(INDEX(Detail[],0,MATCH(D$1,Detail[#Headers],0)),Detail[AEA],$A10) -> 36581.1 | E10: =SUMIFS(INDEX(Detail[],0,MATCH(E$1,Detail[#Headers],0)),Detail[AEA],$A10) -> 42613.96 | F10: =SUMIFS(INDEX(Detail[],0,MATCH(F$1,Detail[#Headers],0)),Detail[AEA],$A10) -> 1124 | G10: =SUMIFS(INDEX(Detail[],0,MATCH(G$1,Detail[#Headers],0)),Detail[AEA],$A10) -> 4.1 | H10: =SUMIFS(INDEX(Detail[],0,MATCH(H$1,Detail[#Headers],0)),Detail[AEA],$A10) -> 37701 | I10: =INDEX(Detail[],MATCH($A10,Detail[AEA],0),MATCH(I$1,Detail[#Headers],0)) -> 342.28 | J10: =INDEX(Detail[],MATCH($A10,Detail[AEA],0),MATCH(J$1,Detail[#Headers],0)) -> 63.72 | K10: =INDEX(Detail[],MATCH($A10,Detail[AEA],0),MATCH(K$1,Detail[#Headers],0)) -> 70.45
A11: {=IFERROR(INDEX(Detail[AEA], MATCH(0,COUNTIF(Summary!$A$2:'Summary'!A10, Detail[AEA]), 0)),"")} -> 15 | B11: =INDEX(Detail[],MATCH(Summary!$A11,Detail[AEA],0),2) -> Great Prairie AEA 15 | C11: =SUMIFS(INDEX(Detail[],0,MATCH(C$1,Detail[#Headers],0)),Detail[AEA],$A11) -> 4716.93 | D11: =SUMIFS(INDEX(Detail[],0,MATCH(D$1,Detail[#Headers],0)),Detail[AEA],$A11) -> 33441.3 | E11: =SUMIFS(INDEX(Detail[],0,MATCH(E$1,Detail[#Headers],0)),Detail[AEA],$A11) -> 38158.23 | F11: =SUMIFS(INDEX(Detail[],0,MATCH(F$1,Detail[#Headers],0)),Detail[AEA],$A11) -> 1328 | G11: =SUMIFS(INDEX(Detail[],0,MATCH(G$1,Detail[#Headers],0)),Detail[AEA],$A11) -> 9.6 | H11: =SUMIFS(INDEX(Detail[],0,MATCH(H$1,Detail[#Headers],0)),Detail[AEA],$A11) -> 34763 | I11: =INDEX(Detail[],MATCH($A11,Detail[AEA],0),MATCH(I$1,Detail[#Headers],0)) -> 339.64 | J11: =INDEX(Detail[],MATCH($A11,Detail[AEA],0),MATCH(J$1,Detail[#Headers],0)) -> 63.69 | K11: =INDEX(Detail[],MATCH($A11,Detail[AEA],0),MATCH(K$1,Detail[#Headers],0)) -> 70.02
C12: =SUM(C3:C11) -> 68484.63 | D12: =SUM(D3:D11) -> 483698.7 | E12: =SUM(E3:E11) -> 552183.33 | F12: =SUM(F3:F11) -> 36195 | G12: =SUM(G3:G11) -> 269.8 | H12: =SUM(H3:H11) -> 519638
C14: =Detail[[#Headers],[AEA Teacher Salary Supplement District Cost Per Pupil]] -> AEA Teacher Salary Supplement District Cost Per Pupil | D14: =Detail[[#Headers],[Professional Development Supplement District Cost Per Pupil]] -> Professional Development Supplement District Cost Per Pupil | E14: =Detail[[#Headers],[AEA Special Ed Support District Cost without Adjustment]] -> AEA Special Ed Support District Cost without Adjustment | F14: =Detail[[#Headers],[AEA Special Ed Support Adjustment]] -> AEA Special Ed Support Adjustment | G14: =Detail[[#Headers],[Special Education Total Cost]] -> Special Education Total Cost | H14: =Detail[[#Headers],[Media Services 40%]] -> Media Services 40% | I14: =Detail[[#Headers],[Education Services 40%]] -> Education Services 40% | J14: =Detail[[#Headers],[AEA Sharing District Cost]] -> AEA Sharing District Cost
A15: =A2 -> AEA | B15: =B2 -> AEA Name | C15: Teach Sal Cost PP | D15: Spec ED Support | E15: Spec Ed Adjust | F15: Special Ed Total Cost | G15: Media Services | H15: Education Services | I15: Sharing Operations
A16: =A3 -> 01 | B16: =B3 -> Keystone AEA 1 | C16: =INDEX(Detail[],MATCH($A16,Detail[AEA],0),MATCH(C$14,Detail[#Headers],0)) -> 35.33 | D16: =SUMIFS(INDEX(Detail[],0,MATCH(E$14,Detail[#Headers],0)),Detail[AEA],$A16) -> 11477381 | E16: =SUMIFS(INDEX(Detail[],0,MATCH(F$14,Detail[#Headers],0)),Detail[AEA],$A16) -> 14190 | F16: =SUMIFS(INDEX(Detail[],0,MATCH(G$14,Detail[#Headers],0)),Detail[AEA],$A16) -> 11491571 | G16: =SUMIFS(INDEX(Detail[],0,MATCH(H$14,Detail[#Headers],0)),Detail[AEA],$A16) -> 807734 | H16: =SUMIFS(INDEX(Detail[],0,MATCH(I$14,Detail[#Headers],0)),Detail[AEA],$A16) -> 899752 | I16: =SUMIFS(INDEX(Detail[],0,MATCH(J$14,Detail[#Headers],0)),Detail[AEA],$A16) -> 30001
A17: =A4 -> 05 | B17: =B4 -> Prairie Lakes AEA 8 | C17: =INDEX(Detail[],MATCH($A17,Detail[AEA],0),MATCH(C$14,Detail[#Headers],0)) -> 37.29 | D17: =SUMIFS(INDEX(Detail[],0,MATCH(E$14,Detail[#Headers],0)),Detail[AEA],$A17) -> 11854900 | E17: =SUMIFS(INDEX(Detail[],0,MATCH(F$14,Detail[#Headers],0)),Detail[AEA],$A17) -> 138167 | F17: =SUMIFS(INDEX(Detail[],0,MATCH(G$14,Detail[#Headers],0)),Detail[AEA],$A17) -> 11993067 | G17: =SUMIFS(INDEX(Detail[],0,MATCH(H$14,Detail[#Headers],0)),Detail[AEA],$A17) -> 816737 | H17: =SUMIFS(INDEX(Detail[],0,MATCH(I$14,Detail[#Headers],0)),Detail[AEA],$A17) -> 914643 | I17: =SUMIFS(INDEX(Detail[],0,MATCH(J$14,Detail[#Headers],0)),Detail[AEA],$A17) -> 0
A18: =A5 -> 07 | B18: =B5 -> Central Rivers | C18: =INDEX(Detail[],MATCH($A18,Detail[AEA],0),MATCH(C$14,Detail[#Headers],0)) -> 42.56 | D18: =SUMIFS(INDEX(Detail[],0,MATCH(E$14,Detail[#Headers],0)),Detail[AEA],$A18) -> 24281771 | E18: =SUMIFS(INDEX(Detail[],0,MATCH(F$14,Detail[#Headers],0)),Detail[AEA],$A18) -> 120080 | F18: =SUMIFS(INDEX(Detail[],0,MATCH(G$14,Detail[#Headers],0)),Detail[AEA],$A18) -> 24401851 | G18: =SUMIFS(INDEX(Detail[],0,MATCH(H$14,Detail[#Headers],0)),Detail[AEA],$A18) -> 1645929 | H18: =SUMIFS(INDEX(Detail[],0,MATCH(I$14,Detail[#Headers],0)),Detail[AEA],$A18) -> 1834892 | I18: =SUMIFS(INDEX(Detail[],0,MATCH(J$14,Detail[#Headers],0)),Detail[AEA],$A18) -> 30000
A19: =A6 -> 09 | B19: =B6 -> Mississippi Bend AEA 9 | C19: =INDEX(Detail[],MATCH($A19,Detail[AEA],0),MATCH(C$14,Detail[#Headers],0)) -> 31.63 | D19: =SUMIFS(INDEX(Detail[],0,MATCH(E$14,Detail[#Headers],0)),Detail[AEA],$A19) -> 17494746 | E19: =SUMIFS(INDEX(Detail[],0,MATCH(F$14,Detail[#Headers],0)),Detail[AEA],$A19) -> 105832 | F19: =SUMIFS(INDEX(Detail[],0,MATCH(G$14,Detail[#Headers],0)),Detail[AEA],$A19) -> 17600578 | G19: =SUMIFS(INDEX(Detail[],0,MATCH(H$14,Detail[#Headers],0)),Detail[AEA],$A19) -> 1215736 | H19: =SUMIFS(INDEX(Detail[],0,MATCH(I$14,Detail[#Headers],0)),Detail[AEA],$A19) -> 1329022 | I19: =SUMIFS(INDEX(Detail[],0,MATCH(J$14,Detail[#Headers],0)),Detail[AEA],$A19) -> 30001
A20: =A7 -> 10 | B20: =B7 -> Grant Wood AEA 10 | C20: =INDEX(Detail[],MATCH($A20,Detail[AEA],0),MATCH(C$14,Detail[#Headers],0)) -> 32.38 | D20: =SUMIFS(INDEX(Detail[],0,MATCH(E$14,Detail[#Headers],0)),Detail[AEA],$A20) -> 26483224 | E20: =SUMIFS(INDEX(Detail[],0,MATCH(F$14,Detail[#Headers],0)),Detail[AEA],$A20) -> 106540 | F20: =SUMIFS(INDEX(Detail[],0,MATCH(G$14,Detail[#Headers],0)),Detail[AEA],$A20) -> 26589764 | G20: =SUMIFS(INDEX(Detail[],0,MATCH(H$14,Detail[#Headers],0)),Detail[AEA],$A20) -> 1885841 | H20: =SUMIFS(INDEX(Detail[],0,MATCH(I$14,Detail[#Headers],0)),Detail[AEA],$A20) -> 2073506 | I20: =SUMIFS(INDEX(Detail[],0,MATCH(J$14,Detail[#Headers],0)),Detail[AEA],$A20) -> 30000
A21: =A8 -> 11 | B21: =B8 -> Heartland AEA 11 | C21: =INDEX(Detail[],MATCH($A21,Detail[AEA],0),MATCH(C$14,Detail[#Headers],0)) -> 28.61 | D21: =SUMIFS(INDEX(Detail[],0,MATCH(E$14,Detail[#Headers],0)),Detail[AEA],$A21) -> 53989595 | E21: =SUMIFS(INDEX(Detail[],0,MATCH(F$14,Detail[#Headers],0)),Detail[AEA],$A21) -> 46909 | F21: =SUMIFS(INDEX(Detail[],0,MATCH(G$14,Detail[#Headers],0)),Detail[AEA],$A21) -> 54036504 | G21: =SUMIFS(INDEX(Detail[],0,MATCH(H$14,Detail[#Headers],0)),Detail[AEA],$A21) -> 3884077 | H21: =SUMIFS(INDEX(Detail[],0,MATCH(I$14,Detail[#Headers],0)),Detail[AEA],$A21) -> 4267657 | I21: =SUMIFS(INDEX(Detail[],0,MATCH(J$14,Detail[#Headers],0)),Detail[AEA],$A21) -> 0
A22: =A9 -> 12 | B22: =B9 -> Northwest AEA | C22: =INDEX(Detail[],MATCH($A22,Detail[AEA],0),MATCH(C$14,Detail[#Headers],0)) -> 35.17 | D22: =SUMIFS(INDEX(Detail[],0,MATCH(E$14,Detail[#Headers],0)),Detail[AEA],$A22) -> 15768181 | E22: =SUMIFS(INDEX(Detail[],0,MATCH(F$14,Detail[#Headers],0)),Detail[AEA],$A22) -> 79672 | F22: =SUMIFS(INDEX(Detail[],0,MATCH(G$14,Detail[#Headers],0)),Detail[AEA],$A22) -> 15847853 | G22: =SUMIFS(INDEX(Detail[],0,MATCH(H$14,Detail[#Headers],0)),Detail[AEA],$A22) -> 1150261 | H22: =SUMIFS(INDEX(Detail[],0,MATCH(I$14,Detail[#Headers],0)),Detail[AEA],$A22) -> 1287750 | I22: =SUMIFS(INDEX(Detail[],0,MATCH(J$14,Detail[#Headers],0)),Detail[AEA],$A22) -> 30000
A23: =A10 -> 13 | B23: =B10 -> Green Hills AEA 13 | C23: =INDEX(Detail[],MATCH($A23,Detail[AEA],0),MATCH(C$14,Detail[#Headers],0)) -> 35.15 | D23: =SUMIFS(INDEX(Detail[],0,MATCH(E$14,Detail[#Headers],0)),Detail[AEA],$A23) -> 14585910 | E23: =SUMIFS(INDEX(Detail[],0,MATCH(F$14,Detail[#Headers],0)),Detail[AEA],$A23) -> 101921 | F23: =SUMIFS(INDEX(Detail[],0,MATCH(G$14,Detail[#Headers],0)),Detail[AEA],$A23) -> 14687831 | G23: =SUMIFS(INDEX(Detail[],0,MATCH(H$14,Detail[#Headers],0)),Detail[AEA],$A23) -> 960922 | H23: =SUMIFS(INDEX(Detail[],0,MATCH(I$14,Detail[#Headers],0)),Detail[AEA],$A23) -> 1062418 | I23: =SUMIFS(INDEX(Detail[],0,MATCH(J$14,Detail[#Headers],0)),Detail[AEA],$A23) -> 30001
A24: =A11 -> 15 | B24: =B11 -> Great Prairie AEA 15 | C24: =INDEX(Detail[],MATCH($A24,Detail[AEA],0),MATCH(C$14,Detail[#Headers],0)) -> 34.16 | D24: =SUMIFS(INDEX(Detail[],0,MATCH(E$14,Detail[#Headers],0)),Detail[AEA],$A24) -> 12960059 | E24: =SUMIFS(INDEX(Detail[],0,MATCH(F$14,Detail[#Headers],0)),Detail[AEA],$A24) -> 121335 | F24: =SUMIFS(INDEX(Detail[],0,MATCH(G$14,Detail[#Headers],0)),Detail[AEA],$A24) -> 13081394 | G24: =SUMIFS(INDEX(Detail[],0,MATCH(H$14,Detail[#Headers],0)),Detail[AEA],$A24) -> 885624 | H24: =SUMIFS(INDEX(Detail[],0,MATCH(I$14,Detail[#Headers],0)),Detail[AEA],$A24) -> 973641 | I24: =SUMIFS(INDEX(Detail[],0,MATCH(J$14,Detail[#Headers],0)),Detail[AEA],$A24) -> 30001
D25: =SUM(D16:D24) -> 188895767 | E25: =SUM(E16:E24) -> 834646 | F25: =SUM(F16:F24) -> 189730413 | G25: =SUM(G16:G24) -> 13252861 | H25: =SUM(H16:H24) -> 14643281 | I25: =SUM(I16:I24) -> 210004
C27: =Detail[[#Headers],[AEA Teacher Salary Supplement District Cost]] -> AEA Teacher Salary Supplement District Cost | D27: =Detail[[#Headers],[AEA Professional Development Supplement District Cost]] -> AEA Professional Development Supplement District Cost | E27: =Detail[[#Headers],[Subtotal Budget]] -> Subtotal Budget | F27: =Detail[[#Headers],[AEA Statewide State Aid Reduction]] -> AEA Statewide State Aid Reduction | G27: =Detail[[#Headers],[Total Budget]] -> Total Budget | H27: =Detail[[#Headers],[State Aid Portion]] -> State Aid Portion | I27: =Detail[[#Headers],[Property Tax Portion]] -> Property Tax Portion
A28: =A15 -> AEA | B28: =B15 -> AEA Name | C28: Teacher Salary Supplement | D28: Subtotal Budget | E28: Prorata Reduction | F28: Total Budget | G28: State Aid | H28: Property Tax
A29: =A16 -> 01 | B29: =B16 -> Keystone AEA 1 | C29: =SUMIFS(INDEX(Detail[],0,MATCH(C$27,Detail[#Headers],0)),Detail[AEA],$A29) -> 1138633 | D29: =SUMIFS(INDEX(Detail[],0,MATCH(E$27,Detail[#Headers],0)),Detail[AEA],$A29) -> 14367691 | E29: =SUMIFS(INDEX(Detail[],0,MATCH(F$27,Detail[#Headers],0)),Detail[AEA],$A29) -> 1894993 | F29: =SUMIFS(INDEX(Detail[],0,MATCH(G$27,Detail[#Headers],0)),Detail[AEA],$A29) -> 12472698 | G29: =SUMIFS(INDEX(Detail[],0,MATCH(H$27,Detail[#Headers],0)),Detail[AEA],$A29) -> 7959399 | H29: =SUMIFS(INDEX(Detail[],0,MATCH(I$27,Detail[#Headers],0)),Detail[AEA],$A29) -> 4513299
A30: =A17 -> 05 | B30: =B17 -> Prairie Lakes AEA 8 | C30: =SUMIFS(INDEX(Detail[],0,MATCH(C$27,Detail[#Headers],0)),Detail[AEA],$A30) -> 1264347 | D30: =SUMIFS(INDEX(Detail[],0,MATCH(E$27,Detail[#Headers],0)),Detail[AEA],$A30) -> 14988794 | E30: =SUMIFS(INDEX(Detail[],0,MATCH(F$27,Detail[#Headers],0)),Detail[AEA],$A30) -> 1980939 | F30: =SUMIFS(INDEX(Detail[],0,MATCH(G$27,Detail[#Headers],0)),Detail[AEA],$A30) -> 13007855 | G30: =SUMIFS(INDEX(Detail[],0,MATCH(H$27,Detail[#Headers],0)),Detail[AEA],$A30) -> 8370719 | H30: =SUMIFS(INDEX(Detail[],0,MATCH(I$27,Detail[#Headers],0)),Detail[AEA],$A30) -> 4637136
A31: =A18 -> 07 | B31: =B18 -> Central Rivers | C31: =SUMIFS(INDEX(Detail[],0,MATCH(C$27,Detail[#Headers],0)),Detail[AEA],$A31) -> 2996590 | D31: =SUMIFS(INDEX(Detail[],0,MATCH(E$27,Detail[#Headers],0)),Detail[AEA],$A31) -> 30909262 | E31: =SUMIFS(INDEX(Detail[],0,MATCH(F$27,Detail[#Headers],0)),Detail[AEA],$A31) -> 4135301 | F31: =SUMIFS(INDEX(Detail[],0,MATCH(G$27,Detail[#Headers],0)),Detail[AEA],$A31) -> 26773961 | G31: =SUMIFS(INDEX(Detail[],0,MATCH(H$27,Detail[#Headers],0)),Detail[AEA],$A31) -> 17854855 | H31: =SUMIFS(INDEX(Detail[],0,MATCH(I$27,Detail[#Headers],0)),Detail[AEA],$A31) -> 8919106
A32: =A19 -> 09 | B32: =B19 -> Mississippi Bend AEA 9 | C32: =SUMIFS(INDEX(Detail[],0,MATCH(C$27,Detail[#Headers],0)),Detail[AEA],$A32) -> 1615203 | D32: =SUMIFS(INDEX(Detail[],0,MATCH(E$27,Detail[#Headers],0)),Detail[AEA],$A32) -> 21790540 | E32: =SUMIFS(INDEX(Detail[],0,MATCH(F$27,Detail[#Headers],0)),Detail[AEA],$A32) -> 2999921 | F32: =SUMIFS(INDEX(Detail[],0,MATCH(G$27,Detail[#Headers],0)),Detail[AEA],$A32) -> 18790619 | G32: =SUMIFS(INDEX(Detail[],0,MATCH(H$27,Detail[#Headers],0)),Detail[AEA],$A32) -> 12400626 | H32: =SUMIFS(INDEX(Detail[],0,MATCH(I$27,Detail[#Headers],0)),Detail[AEA],$A32) -> 6389993
A33: =A20 -> 10 | B33: =B20 -> Grant Wood AEA 10 | C33: =SUMIFS(INDEX(Detail[],0,MATCH(C$27,Detail[#Headers],0)),Detail[AEA],$A33) -> 2515465 | D33: =SUMIFS(INDEX(Detail[],0,MATCH(E$27,Detail[#Headers],0)),Detail[AEA],$A33) -> 33094576 | E33: =SUMIFS(INDEX(Detail[],0,MATCH(F$27,Detail[#Headers],0)),Detail[AEA],$A33) -> 4566772 | F33: =SUMIFS(INDEX(Detail[],0,MATCH(G$27,Detail[#Headers],0)),Detail[AEA],$A33) -> 28527804 | G33: =SUMIFS(INDEX(Detail[],0,MATCH(H$27,Detail[#Headers],0)),Detail[AEA],$A33) -> 18921885 | H33: =SUMIFS(INDEX(Detail[],0,MATCH(I$27,Detail[#Headers],0)),Detail[AEA],$A33) -> 9605919
A34: =A21 -> 11 | B34: =B21 -> Heartland AEA 11 | C34: =SUMIFS(INDEX(Detail[],0,MATCH(C$27,Detail[#Headers],0)),Detail[AEA],$A34) -> 4623704 | D34: =SUMIFS(INDEX(Detail[],0,MATCH(E$27,Detail[#Headers],0)),Detail[AEA],$A34) -> 66811942 | E34: =SUMIFS(INDEX(Detail[],0,MATCH(F$27,Detail[#Headers],0)),Detail[AEA],$A34) -> 9507746 | F34: =SUMIFS(INDEX(Detail[],0,MATCH(G$27,Detail[#Headers],0)),Detail[AEA],$A34) -> 57304196 | G34: =SUMIFS(INDEX(Detail[],0,MATCH(H$27,Detail[#Headers],0)),Detail[AEA],$A34) -> 38731511 | H34: =SUMIFS(INDEX(Detail[],0,MATCH(I$27,Detail[#Headers],0)),Detail[AEA],$A34) -> 18572685
A35: =A22 -> 12 | B35: =B22 -> Northwest AEA | C35: =SUMIFS(INDEX(Detail[],0,MATCH(C$27,Detail[#Headers],0)),Detail[AEA],$A35) -> 1595606 | D35: =SUMIFS(INDEX(Detail[],0,MATCH(E$27,Detail[#Headers],0)),Detail[AEA],$A35) -> 19911470 | E35: =SUMIFS(INDEX(Detail[],0,MATCH(F$27,Detail[#Headers],0)),Detail[AEA],$A35) -> 2660304 | F35: =SUMIFS(INDEX(Detail[],0,MATCH(G$27,Detail[#Headers],0)),Detail[AEA],$A35) -> 17251166 | G35: =SUMIFS(INDEX(Detail[],0,MATCH(H$27,Detail[#Headers],0)),Detail[AEA],$A35) -> 11162299 | H35: =SUMIFS(INDEX(Detail[],0,MATCH(I$27,Detail[#Headers],0)),Detail[AEA],$A35) -> 6088867
A36: =A23 -> 13 | B36: =B23 -> Green Hills AEA 13 | C36: =SUMIFS(INDEX(Detail[],0,MATCH(C$27,Detail[#Headers],0)),Detail[AEA],$A36) -> 1506001 | D36: =SUMIFS(INDEX(Detail[],0,MATCH(E$27,Detail[#Headers],0)),Detail[AEA],$A36) -> 18247173 | E36: =SUMIFS(INDEX(Detail[],0,MATCH(F$27,Detail[#Headers],0)),Detail[AEA],$A36) -> 2508136 | F36: =SUMIFS(INDEX(Detail[],0,MATCH(G$27,Detail[#Headers],0)),Detail[AEA],$A36) -> 15739037 | G36: =SUMIFS(INDEX(Detail[],0,MATCH(H$27,Detail[#Headers],0)),Detail[AEA],$A36) -> 10527304 | H36: =SUMIFS(INDEX(Detail[],0,MATCH(I$27,Detail[#Headers],0)),Detail[AEA],$A36) -> 5211733
A37: =A24 -> 15 | B37: =B24 -> Great Prairie AEA 15 | C37: =SUMIFS(INDEX(Detail[],0,MATCH(C$27,Detail[#Headers],0)),Detail[AEA],$A37) -> 1308929 | D37: =SUMIFS(INDEX(Detail[],0,MATCH(E$27,Detail[#Headers],0)),Detail[AEA],$A37) -> 16279589 | E37: =SUMIFS(INDEX(Detail[],0,MATCH(F$27,Detail[#Headers],0)),Detail[AEA],$A37) -> 2245888 | F37: =SUMIFS(INDEX(Detail[],0,MATCH(G$27,Detail[#Headers],0)),Detail[AEA],$A37) -> 14033701 | G37: =SUMIFS(INDEX(Detail[],0,MATCH(H$27,Detail[#Headers],0)),Detail[AEA],$A37) -> 9389615 | H37: =SUMIFS(INDEX(Detail[],0,MATCH(I$27,Detail[#Headers],0)),Detail[AEA],$A37) -> 4644086
C38: =SUM(C29:C37) -> 18564478 | D38: =SUM(D29:D37) -> 236401037 | E38: =SUM(E29:E37) -> 32500000 | F38: =SUM(F29:F37) -> 203901037 | G38: =SUM(G29:G37) -> 135318213 | H38: =SUM(H29:H37) -> 68582824

Sheet Comparison to FY 2024
C3: AEA Name | D3: Total Special Ed Funding with $29.6 million Reduction FY 2024 | E3: Total Special Ed Funding with $32.5 million Reduction FY 2025 | F3: Change Compared to FY 2024
C4: Keystone AEA 1 | D4: 9131830 | E4: =StateAidVsPropertyTax!I2 -> 9596578 | F4: =E4-D4 -> 464748
C5: Prairie Lakes AEA 8 | D5: 9579835 | E5: =StateAidVsPropertyTax!I3 -> 10012128 | F5: =E5-D5 -> 432293
C6: Central Rivers | D6: 19800340 | E6: =StateAidVsPropertyTax!I4 -> 20266550 | F6: =E6-D6 -> 466210
C7: Mississippi Bend AEA 9 | D7: 14446352 | E7: =StateAidVsPropertyTax!I5 -> 14600657 | F7: =E7-D7 -> 154305
C8: Grant Wood AEA 10 | D8: 22192132 | E8: =StateAidVsPropertyTax!I6 -> 22022992 | F8: =E8-D8 -> -169140
C9: Heartland AEA 11 | D9: 45803064 | E9: =StateAidVsPropertyTax!I7 -> 44528758 | F9: =E9-D9 -> -1274306
C10: Northwest AEA | D10: 13081985 | E10: =StateAidVsPropertyTax!I8 -> 13187549 | F10: =E10-D10 -> 105564
C11: Green Hills AEA 13 | D11: 11787978 | E11: =StateAidVsPropertyTax!I9 -> 12179695 | F11: =E11-D11 -> 391717
C12: Great Prairie AEA 15 | D12: 10483319 | E12: =StateAidVsPropertyTax!I10 -> 10835506 | F12: =E12-D12 -> 352187
D13: =SUM(D4:D12) -> 156306835 | E13: =SUM(E4:E12) -> 157230413 | F13: =E13-D13 -> 923578

Sheet StateAidVsPropertyTax
A1: AEA | B1: AEA Name | C1: =Breakdown[[#Headers],[AEA Special Ed Support District Cost Formula Generated]] -> AEA Special Ed Support District Cost Formula Generated | D1: =Breakdown[[#Headers],[State Aid Portion Special Ed]] -> State Aid Portion Special Ed | E1: =Breakdown[[#Headers],[AEA Statewide State Aid Reduction]] -> AEA Statewide State Aid Reduction | F1: =Breakdown[[#Headers],[State Aid Special Ed Minus Reduction]] -> State Aid Special Ed Minus Reduction | G1: =Breakdown[[#Headers],[Special Education Property Tax Portion]] -> Special Education Property Tax Portion | H1: =Breakdown[[#Headers],[AEA Special Ed Support Adjustment]] -> AEA Special Ed Support Adjustment | I1: =Breakdown[[#Headers],[Total Special Ed Funding Removing Reduction Including Adjustment]] -> Total Special Ed Funding Removing Reduction Including Adjustment
A2: {=IFERROR(INDEX(Detail[AEA], MATCH(0,COUNTIF(StateAidVsPropertyTax!$A$1:'StateAidVsPropertyTax'!A1, Detail[AEA]), 0)),"")} -> 01 | B2: =INDEX(Detail[],MATCH(StateAidVsPropertyTax!$A2,Detail[AEA],0),2) -> Keystone AEA 1 | C2: =SUMIFS(INDEX(Breakdown[],0,MATCH(C$1,Breakdown[#Headers],0)),Breakdown[AEA],$A2) -> 11477381 | D2: =SUMIFS(INDEX(Breakdown[],0,MATCH(D$1,Breakdown[#Headers],0)),Breakdown[AEA],$A2) -> 8693035 | E2: =SUMIFS(INDEX(Breakdown[],0,MATCH(E$1,Breakdown[#Headers],0)),Breakdown[AEA],$A2) -> 1894993 | F2: =SUMIFS(INDEX(Breakdown[],0,MATCH(F$1,Breakdown[#Headers],0)),Breakdown[AEA],$A2) -> 6798042 | G2: =SUMIFS(INDEX(Breakdown[],0,MATCH(G$1,Breakdown[#Headers],0)),Breakdown[AEA],$A2) -> 2784346 | H2: =SUMIFS(INDEX(Breakdown[],0,MATCH(H$1,Breakdown[#Headers],0)),Breakdown[AEA],$A2) -> 14190 | I2: =SUMIFS(INDEX(Breakdown[],0,MATCH(I$1,Breakdown[#Headers],0)),Breakdown[AEA],$A2) -> 9596578 | P2: =G11+D23+H11+C35+D35-G35 -> 0
A3: {=IFERROR(INDEX(Detail[AEA], MATCH(0,COUNTIF(StateAidVsPropertyTax!$A$1:'StateAidVsPropertyTax'!A2, Detail[AEA]), 0)),"")} -> 05 | B3: =INDEX(Detail[],MATCH(StateAidVsPropertyTax!$A3,Detail[AEA],0),2) -> Prairie Lakes AEA 8 | C3: =SUMIFS(INDEX(Breakdown[],0,MATCH(C$1,Breakdown[#Headers],0)),Breakdown[AEA],$A3) -> 11854900 | D3: =SUMIFS(INDEX(Breakdown[],0,MATCH(D$1,Breakdown[#Headers],0)),Breakdown[AEA],$A3) -> 9087311 | E3: =SUMIFS(INDEX(Breakdown[],0,MATCH(E$1,Breakdown[#Headers],0)),Breakdown[AEA],$A3) -> 1980939 | F3: =SUMIFS(INDEX(Breakdown[],0,MATCH(F$1,Breakdown[#Headers],0)),Breakdown[AEA],$A3) -> 7106372 | G3: =SUMIFS(INDEX(Breakdown[],0,MATCH(G$1,Breakdown[#Headers],0)),Breakdown[AEA],$A3) -> 2767589 | H3: =SUMIFS(INDEX(Breakdown[],0,MATCH(H$1,Breakdown[#Headers],0)),Breakdown[AEA],$A3) -> 138167 | I3: =SUMIFS(INDEX(Breakdown[],0,MATCH(I$1,Breakdown[#Headers],0)),Breakdown[AEA],$A3) -> 10012128 | P3: =F11+C23+F23-F35 -> 0
A4: {=IFERROR(INDEX(Detail[AEA], MATCH(0,COUNTIF(StateAidVsPropertyTax!$A$1:'StateAidVsPropertyTax'!A3, Detail[AEA]), 0)),"")} -> 07 | B4: =INDEX(Detail[],MATCH(StateAidVsPropertyTax!$A4,Detail[AEA],0),2) -> Central Rivers | C4: =SUMIFS(INDEX(Breakdown[],0,MATCH(C$1,Breakdown[#Headers],0)),Breakdown[AEA],$A4) -> 24281771 | D4: =SUMIFS(INDEX(Breakdown[],0,MATCH(D$1,Breakdown[#Headers],0)),Breakdown[AEA],$A4) -> 18970133 | E4: =SUMIFS(INDEX(Breakdown[],0,MATCH(E$1,Breakdown[#Headers],0)),Breakdown[AEA],$A4) -> 4135301 | F4: =SUMIFS(INDEX(Breakdown[],0,MATCH(F$1,Breakdown[#Headers],0)),Breakdown[AEA],$A4) -> 14834832 | G4: =SUMIFS(INDEX(Breakdown[],0,MATCH(G$1,Breakdown[#Headers],0)),Breakdown[AEA],$A4) -> 5311638 | H4: =SUMIFS(INDEX(Breakdown[],0,MATCH(H$1,Breakdown[#Headers],0)),Breakdown[AEA],$A4) -> 120080 | I4: =SUMIFS(INDEX(Breakdown[],0,MATCH(I$1,Breakdown[#Headers],0)),Breakdown[AEA],$A4) -> 20266550
A5: {=IFERROR(INDEX(Detail[AEA], MATCH(0,COUNTIF(StateAidVsPropertyTax!$A$1:'StateAidVsPropertyTax'!A4, Detail[AEA]), 0)),"")} -> 09 | B5: =INDEX(Detail[],MATCH(StateAidVsPropertyTax!$A5,Detail[AEA],0),2) -> Mississippi Bend AEA 9 | C5: =SUMIFS(INDEX(Breakdown[],0,MATCH(C$1,Breakdown[#Headers],0)),Breakdown[AEA],$A5) -> 17494746 | D5: =SUMIFS(INDEX(Breakdown[],0,MATCH(D$1,Breakdown[#Headers],0)),Breakdown[AEA],$A5) -> 13761746 | E5: =SUMIFS(INDEX(Breakdown[],0,MATCH(E$1,Breakdown[#Headers],0)),Breakdown[AEA],$A5) -> 2999921 | F5: =SUMIFS(INDEX(Breakdown[],0,MATCH(F$1,Breakdown[#Headers],0)),Breakdown[AEA],$A5) -> 10761825 | G5: =SUMIFS(INDEX(Breakdown[],0,MATCH(G$1,Breakdown[#Headers],0)),Breakdown[AEA],$A5) -> 3733000 | H5: =SUMIFS(INDEX(Breakdown[],0,MATCH(H$1,Breakdown[#Headers],0)),Breakdown[AEA],$A5) -> 105832 | I5: =SUMIFS(INDEX(Breakdown[],0,MATCH(I$1,Breakdown[#Headers],0)),Breakdown[AEA],$A5) -> 14600657
A6: {=IFERROR(INDEX(Detail[AEA], MATCH(0,COUNTIF(StateAidVsPropertyTax!$A$1:'StateAidVsPropertyTax'!A5, Detail[AEA]), 0)),"")} -> 10 | B6: =INDEX(Detail[],MATCH(StateAidVsPropertyTax!$A6,Detail[AEA],0),2) -> Grant Wood AEA 10 | C6: =SUMIFS(INDEX(Breakdown[],0,MATCH(C$1,Breakdown[#Headers],0)),Breakdown[AEA],$A6) -> 26483224 | D6: =SUMIFS(INDEX(Breakdown[],0,MATCH(D$1,Breakdown[#Headers],0)),Breakdown[AEA],$A6) -> 20949463 | E6: =SUMIFS(INDEX(Breakdown[],0,MATCH(E$1,Breakdown[#Headers],0)),Breakdown[AEA],$A6) -> 4566772 | F6: =SUMIFS(INDEX(Breakdown[],0,MATCH(F$1,Breakdown[#Headers],0)),Breakdown[AEA],$A6) -> 16382691 | G6: =SUMIFS(INDEX(Breakdown[],0,MATCH(G$1,Breakdown[#Headers],0)),Breakdown[AEA],$A6) -> 5533761 | H6: =SUMIFS(INDEX(Breakdown[],0,MATCH(H$1,Breakdown[#Headers],0)),Breakdown[AEA],$A6) -> 106540 | I6: =SUMIFS(INDEX(Breakdown[],0,MATCH(I$1,Breakdown[#Headers],0)),Breakdown[AEA],$A6) -> 22022992
A7: {=IFERROR(INDEX(Detail[AEA], MATCH(0,COUNTIF(StateAidVsPropertyTax!$A$1:'StateAidVsPropertyTax'!A6, Detail[AEA]), 0)),"")} -> 11 | B7: =INDEX(Detail[],MATCH(StateAidVsPropertyTax!$A7,Detail[AEA],0),2) -> Heartland AEA 11 | C7: =SUMIFS(INDEX(Breakdown[],0,MATCH(C$1,Breakdown[#Headers],0)),Breakdown[AEA],$A7) -> 53989595 | D7: =SUMIFS(INDEX(Breakdown[],0,MATCH(D$1,Breakdown[#Headers],0)),Breakdown[AEA],$A7) -> 43615553 | E7: =SUMIFS(INDEX(Breakdown[],0,MATCH(E$1,Breakdown[#Headers],0)),Breakdown[AEA],$A7) -> 9507746 | F7: =SUMIFS(INDEX(Breakdown[],0,MATCH(F$1,Breakdown[#Headers],0)),Breakdown[AEA],$A7) -> 34107807 | G7: =SUMIFS(INDEX(Breakdown[],0,MATCH(G$1,Breakdown[#Headers],0)),Breakdown[AEA],$A7) -> 10374042 | H7: =SUMIFS(INDEX(Breakdown[],0,MATCH(H$1,Breakdown[#Headers],0)),Breakdown[AEA],$A7) -> 46909 | I7: =SUMIFS(INDEX(Breakdown[],0,MATCH(I$1,Breakdown[#Headers],0)),Breakdown[AEA],$A7) -> 44528758
A8: {=IFERROR(INDEX(Detail[AEA], MATCH(0,COUNTIF(StateAidVsPropertyTax!$A$1:'StateAidVsPropertyTax'!A7, Detail[AEA]), 0)),"")} -> 12 | B8: =INDEX(Detail[],MATCH(StateAidVsPropertyTax!$A8,Detail[AEA],0),2) -> Northwest AEA | C8: =SUMIFS(INDEX(Breakdown[],0,MATCH(C$1,Breakdown[#Headers],0)),Breakdown[AEA],$A8) -> 15768181 | D8: =SUMIFS(INDEX(Breakdown[],0,MATCH(D$1,Breakdown[#Headers],0)),Breakdown[AEA],$A8) -> 12203773 | E8: =SUMIFS(INDEX(Breakdown[],0,MATCH(E$1,Breakdown[#Headers],0)),Breakdown[AEA],$A8) -> 2660304 | F8: =SUMIFS(INDEX(Breakdown[],0,MATCH(F$1,Breakdown[#Headers],0)),Breakdown[AEA],$A8) -> 9543469 | G8: =SUMIFS(INDEX(Breakdown[],0,MATCH(G$1,Breakdown[#Headers],0)),Breakdown[AEA],$A8) -> 3564408 | H8: =SUMIFS(INDEX(Breakdown[],0,MATCH(H$1,Breakdown[#Headers],0)),Breakdown[AEA],$A8) -> 79672 | I8: =SUMIFS(INDEX(Breakdown[],0,MATCH(I$1,Breakdown[#Headers],0)),Breakdown[AEA],$A8) -> 13187549
A9: {=IFERROR(INDEX(Detail[AEA], MATCH(0,COUNTIF(StateAidVsPropertyTax!$A$1:'StateAidVsPropertyTax'!A8, Detail[AEA]), 0)),"")} -> 13 | B9: =INDEX(Detail[],MATCH(StateAidVsPropertyTax!$A9,Detail[AEA],0),2) -> Green Hills AEA 13 | C9: =SUMIFS(INDEX(Breakdown[],0,MATCH(C$1,Breakdown[#Headers],0)),Breakdown[AEA],$A9) -> 14585910 | D9: =SUMIFS(INDEX(Breakdown[],0,MATCH(D$1,Breakdown[#Headers],0)),Breakdown[AEA],$A9) -> 11505771 | E9: =SUMIFS(INDEX(Breakdown[],0,MATCH(E$1,Breakdown[#Headers],0)),Breakdown[AEA],$A9) -> 2508136 | F9: =SUMIFS(INDEX(Breakdown[],0,MATCH(F$1,Breakdown[#Headers],0)),Breakdown[AEA],$A9) -> 8997635 | G9: =SUMIFS(INDEX(Breakdown[],0,MATCH(G$1,Breakdown[#Headers],0)),Breakdown[AEA],$A9) -> 3080139 | H9: =SUMIFS(INDEX(Breakdown[],0,MATCH(H$1,Breakdown[#Headers],0)),Breakdown[AEA],$A9) -> 101921 | I9: =SUMIFS(INDEX(Breakdown[],0,MATCH(I$1,Breakdown[#Headers],0)),Breakdown[AEA],$A9) -> 12179695
A10: {=IFERROR(INDEX(Detail[AEA], MATCH(0,COUNTIF(StateAidVsPropertyTax!$A$1:'StateAidVsPropertyTax'!A9, Detail[AEA]), 0)),"")} -> 15 | B10: =INDEX(Detail[],MATCH(StateAidVsPropertyTax!$A10,Detail[AEA],0),2) -> Great Prairie AEA 15 | C10: =SUMIFS(INDEX(Breakdown[],0,MATCH(C$1,Breakdown[#Headers],0)),Breakdown[AEA],$A10) -> 12960059 | D10: =SUMIFS(INDEX(Breakdown[],0,MATCH(D$1,Breakdown[#Headers],0)),Breakdown[AEA],$A10) -> 10302723 | E10: =SUMIFS(INDEX(Breakdown[],0,MATCH(E$1,Breakdown[#Headers],0)),Breakdown[AEA],$A10) -> 2245888 | F10: =SUMIFS(INDEX(Breakdown[],0,MATCH(F$1,Breakdown[#Headers],0)),Breakdown[AEA],$A10) -> 8056835 | G10: =SUMIFS(INDEX(Breakdown[],0,MATCH(G$1,Breakdown[#Headers],0)),Breakdown[AEA],$A10) -> 2657336 | H10: =SUMIFS(INDEX(Breakdown[],0,MATCH(H$1,Breakdown[#Headers],0)),Breakdown[AEA],$A10) -> 121335 | I10: =SUMIFS(INDEX(Breakdown[],0,MATCH(I$1,Breakdown[#Headers],0)),Breakdown[AEA],$A10) -> 10835506
C11: =SUM(C2:C10) -> 188895767 | D11: =SUM(D2:D10) -> 149089508 | E11: =SUM(E2:E10) -> 32500000 | F11: =SUM(F2:F10) -> 116589508 | G11: =SUM(G2:G10) -> 39806259 | H11: =SUM(H2:H10) -> 834646 | I11: =SUM(I2:I10) -> 157230413
A13: =A1 -> AEA | B13: =B1 -> AEA Name | C13: =Breakdown[[#Headers],[State Aid Portion Sharing Operations]] -> State Aid Portion Sharing Operations | D13: =Breakdown[[#Headers],[Sharing Operations Property Tax]] -> Sharing Operations Property Tax | E13: =Breakdown[[#Headers],[Total AEA Sharing Operations]] -> Total AEA Sharing Operations | F13: =Breakdown[[#Headers],[AEA Teacher Salary Supplement District Cost]] -> AEA Teacher Salary Supplement District Cost
A14: =A2 -> 01 | B14: =B2 -> Keystone AEA 1 | C14: =SUMIFS(INDEX(Breakdown[],0,MATCH(C$13,Breakdown[#Headers],0)),Breakdown[AEA],$A14) -> 22724 | D14: =SUMIFS(INDEX(Breakdown[],0,MATCH(D$13,Breakdown[#Headers],0)),Breakdown[AEA],$A14) -> 7277 | E14: =SUMIFS(INDEX(Breakdown[],0,MATCH(E$13,Breakdown[#Headers],0)),Breakdown[AEA],$A14) -> 30001 | F14: =SUMIFS(INDEX(Breakdown[],0,MATCH(F$13,Breakdown[#Headers],0)),Breakdown[AEA],$A14) -> 1138633
A15: =A3 -> 05 | B15: =B3 -> Prairie Lakes AEA 8 | C15: =SUMIFS(INDEX(Breakdown[],0,MATCH(C$13,Breakdown[#Headers],0)),Breakdown[AEA],$A15) -> 0 | D15: =SUMIFS(INDEX(Breakdown[],0,MATCH(D$13,Breakdown[#Headers],0)),Breakdown[AEA],$A15) -> 0 | E15: =SUMIFS(INDEX(Breakdown[],0,MATCH(E$13,Breakdown[#Headers],0)),Breakdown[AEA],$A15) -> 0 | F15: =SUMIFS(INDEX(Breakdown[],0,MATCH(F$13,Breakdown[#Headers],0)),Breakdown[AEA],$A15) -> 1264347 | G15: State Aid Portion
A16: =A4 -> 07 | B16: =B4 -> Central Rivers | C16: =SUMIFS(INDEX(Breakdown[],0,MATCH(C$13,Breakdown[#Headers],0)),Breakdown[AEA],$A16) -> 23433 | D16: =SUMIFS(INDEX(Breakdown[],0,MATCH(D$13,Breakdown[#Headers],0)),Breakdown[AEA],$A16) -> 6567 | E16: =SUMIFS(INDEX(Breakdown[],0,MATCH(E$13,Breakdown[#Headers],0)),Breakdown[AEA],$A16) -> 30000 | F16: =SUMIFS(INDEX(Breakdown[],0,MATCH(F$13,Breakdown[#Headers],0)),Breakdown[AEA],$A16) -> 2996590
A17: =A5 -> 09 | B17: =B5 -> Mississippi Bend AEA 9 | C17: =SUMIFS(INDEX(Breakdown[],0,MATCH(C$13,Breakdown[#Headers],0)),Breakdown[AEA],$A17) -> 23600 | D17: =SUMIFS(INDEX(Breakdown[],0,MATCH(D$13,Breakdown[#Headers],0)),Breakdown[AEA],$A17) -> 6401 | E17: =SUMIFS(INDEX(Breakdown[],0,MATCH(E$13,Breakdown[#Headers],0)),Breakdown[AEA],$A17) -> 30001 | F17: =SUMIFS(INDEX(Breakdown[],0,MATCH(F$13,Breakdown[#Headers],0)),Breakdown[AEA],$A17) -> 1615203 | G17: Propery Tax Portion
A18: =A6 -> 10 | B18: =B6 -> Grant Wood AEA 10 | C18: =SUMIFS(INDEX(Breakdown[],0,MATCH(C$13,Breakdown[#Headers],0)),Breakdown[AEA],$A18) -> 23732 | D18: =SUMIFS(INDEX(Breakdown[],0,MATCH(D$13,Breakdown[#Headers],0)),Breakdown[AEA],$A18) -> 6268 | E18: =SUMIFS(INDEX(Breakdown[],0,MATCH(E$13,Breakdown[#Headers],0)),Breakdown[AEA],$A18) -> 30000 | F18: =SUMIFS(INDEX(Breakdown[],0,MATCH(F$13,Breakdown[#Headers],0)),Breakdown[AEA],$A18) -> 2515465
A19: =A7 -> 11 | B19: =B7 -> Heartland AEA 11 | C19: =SUMIFS(INDEX(Breakdown[],0,MATCH(C$13,Breakdown[#Headers],0)),Breakdown[AEA],$A19) -> 0 | D19: =SUMIFS(INDEX(Breakdown[],0,MATCH(D$13,Breakdown[#Headers],0)),Breakdown[AEA],$A19) -> 0 | E19: =SUMIFS(INDEX(Breakdown[],0,MATCH(E$13,Breakdown[#Headers],0)),Breakdown[AEA],$A19) -> 0 | F19: =SUMIFS(INDEX(Breakdown[],0,MATCH(F$13,Breakdown[#Headers],0)),Breakdown[AEA],$A19) -> 4623704
A20: =A8 -> 12 | B20: =B8 -> Northwest AEA | C20: =SUMIFS(INDEX(Breakdown[],0,MATCH(C$13,Breakdown[#Headers],0)),Breakdown[AEA],$A20) -> 23222 | D20: =SUMIFS(INDEX(Breakdown[],0,MATCH(D$13,Breakdown[#Headers],0)),Breakdown[AEA],$A20) -> 6778 | E20: =SUMIFS(INDEX(Breakdown[],0,MATCH(E$13,Breakdown[#Headers],0)),Breakdown[AEA],$A20) -> 30000 | F20: =SUMIFS(INDEX(Breakdown[],0,MATCH(F$13,Breakdown[#Headers],0)),Breakdown[AEA],$A20) -> 1595606
A21: =A9 -> 13 | B21: =B9 -> Green Hills AEA 13 | C21: =SUMIFS(INDEX(Breakdown[],0,MATCH(C$13,Breakdown[#Headers],0)),Breakdown[AEA],$A21) -> 23667 | D21: =SUMIFS(INDEX(Breakdown[],0,MATCH(D$13,Breakdown[#Headers],0)),Breakdown[AEA],$A21) -> 6334 | E21: =SUMIFS(INDEX(Breakdown[],0,MATCH(E$13,Breakdown[#Headers],0)),Breakdown[AEA],$A21) -> 30001 | F21: =SUMIFS(INDEX(Breakdown[],0,MATCH(F$13,Breakdown[#Headers],0)),Breakdown[AEA],$A21) -> 1506001
A22: =A10 -> 15 | B22: =B10 -> Great Prairie AEA 15 | C22: =SUMIFS(INDEX(Breakdown[],0,MATCH(C$13,Breakdown[#Headers],0)),Breakdown[AEA],$A22) -> 23849 | D22: =SUMIFS(INDEX(Breakdown[],0,MATCH(D$13,Breakdown[#Headers],0)),Breakdown[AEA],$A22) -> 6152 | E22: =SUMIFS(INDEX(Breakdown[],0,MATCH(E$13,Breakdown[#Headers],0)),Breakdown[AEA],$A22) -> 30001 | F22: =SUMIFS(INDEX(Breakdown[],0,MATCH(F$13,Breakdown[#Headers],0)),Breakdown[AEA],$A22) -> 1308929
C23: =SUM(C14:C22) -> 164227 | D23: =SUM(D14:D22) -> 45777 | E23: =SUM(E14:E22) -> 210004 | F23: =SUM(F14:F22) -> 18564478
A25: =A13 -> AEA | B25: =B13 -> AEA Name | C25: =Breakdown[[#Headers],[AEA Media Services District Cost - 40%]] -> AEA Media Services District Cost - 40% | D25: =Breakdown[[#Headers],[AEA Ed Services District Cost - 40%]] -> AEA Ed Services District Cost - 40% | E25: =Breakdown[[#Headers],[Total Budget]] -> Total Budget | F25: =Breakdown[[#Headers],[State Aid Portion]] -> State Aid Portion | G25: =Breakdown[[#Headers],[Property Tax Portion]] -> Property Tax Portion
A26: =A14 -> 01 | B26: =B14 -> Keystone AEA 1 | C26: =SUMIFS(INDEX(Breakdown[],0,MATCH(C$25,Breakdown[#Headers],0)),Breakdown[AEA],$A26) -> 807734 | D26: =SUMIFS(INDEX(Breakdown[],0,MATCH(D$25,Breakdown[#Headers],0)),Breakdown[AEA],$A26) -> 899752 | E26: =SUMIFS(INDEX(Breakdown[],0,MATCH(E$25,Breakdown[#Headers],0)),Breakdown[AEA],$A26) -> 12472698 | F26: =SUMIFS(INDEX(Breakdown[],0,MATCH(F$25,Breakdown[#Headers],0)),Breakdown[AEA],$A26) -> 7959399 | G26: =SUMIFS(INDEX(Breakdown[],0,MATCH(G$25,Breakdown[#Headers],0)),Breakdown[AEA],$A26) -> 4513299
A27: =A15 -> 05 | B27: =B15 -> Prairie Lakes AEA 8 | C27: =SUMIFS(INDEX(Breakdown[],0,MATCH(C$25,Breakdown[#Headers],0)),Breakdown[AEA],$A27) -> 816737 | D27: =SUMIFS(INDEX(Breakdown[],0,MATCH(D$25,Breakdown[#Headers],0)),Breakdown[AEA],$A27) -> 914643 | E27: =SUMIFS(INDEX(Breakdown[],0,MATCH(E$25,Breakdown[#Headers],0)),Breakdown[AEA],$A27) -> 13007855 | F27: =SUMIFS(INDEX(Breakdown[],0,MATCH(F$25,Breakdown[#Headers],0)),Breakdown[AEA],$A27) -> 8370719 | G27: =SUMIFS(INDEX(Breakdown[],0,MATCH(G$25,Breakdown[#Headers],0)),Breakdown[AEA],$A27) -> 4637136
A28: =A16 -> 07 | B28: =B16 -> Central Rivers | C28: =SUMIFS(INDEX(Breakdown[],0,MATCH(C$25,Breakdown[#Headers],0)),Breakdown[AEA],$A28) -> 1645929 | D28: =SUMIFS(INDEX(Breakdown[],0,MATCH(D$25,Breakdown[#Headers],0)),Breakdown[AEA],$A28) -> 1834892 | E28: =SUMIFS(INDEX(Breakdown[],0,MATCH(E$25,Breakdown[#Headers],0)),Breakdown[AEA],$A28) -> 26773961 | F28: =SUMIFS(INDEX(Breakdown[],0,MATCH(F$25,Breakdown[#Headers],0)),Breakdown[AEA],$A28) -> 17854855 | G28: =SUMIFS(INDEX(Breakdown[],0,MATCH(G$25,Breakdown[#Headers],0)),Breakdown[AEA],$A28) -> 8919106
A29: =A17 -> 09 | B29: =B17 -> Mississippi Bend AEA 9 | C29: =SUMIFS(INDEX(Breakdown[],0,MATCH(C$25,Breakdown[#Headers],0)),Breakdown[AEA],$A29) -> 1215736 | D29: =SUMIFS(INDEX(Breakdown[],0,MATCH(D$25,Breakdown[#Headers],0)),Breakdown[AEA],$A29) -> 1329022 | E29: =SUMIFS(INDEX(Breakdown[],0,MATCH(E$25,Breakdown[#Headers],0)),Breakdown[AEA],$A29) -> 18790619 | F29: =SUMIFS(INDEX(Breakdown[],0,MATCH(F$25,Breakdown[#Headers],0)),Breakdown[AEA],$A29) -> 12400626 | G29: =SUMIFS(INDEX(Breakdown[],0,MATCH(G$25,Breakdown[#Headers],0)),Breakdown[AEA],$A29) -> 6389993
A30: =A18 -> 10 | B30: =B18 -> Grant Wood AEA 10 | C30: =SUMIFS(INDEX(Breakdown[],0,MATCH(C$25,Breakdown[#Headers],0)),Breakdown[AEA],$A30) -> 1885841 | D30: =SUMIFS(INDEX(Breakdown[],0,MATCH(D$25,Breakdown[#Headers],0)),Breakdown[AEA],$A30) -> 2073506 | E30: =SUMIFS(INDEX(Breakdown[],0,MATCH(E$25,Breakdown[#Headers],0)),Breakdown[AEA],$A30) -> 28527804 | F30: =SUMIFS(INDEX(Breakdown[],0,MATCH(F$25,Breakdown[#Headers],0)),Breakdown[AEA],$A30) -> 18921885 | G30: =SUMIFS(INDEX(Breakdown[],0,MATCH(G$25,Breakdown[#Headers],0)),Breakdown[AEA],$A30) -> 9605919
A31: =A19 -> 11 | B31: =B19 -> Heartland AEA 11 | C31: =SUMIFS(INDEX(Breakdown[],0,MATCH(C$25,Breakdown[#Headers],0)),Breakdown[AEA],$A31) -> 3884077 | D31: =SUMIFS(INDEX(Breakdown[],0,MATCH(D$25,Breakdown[#Headers],0)),Breakdown[AEA],$A31) -> 4267657 | E31: =SUMIFS(INDEX(Breakdown[],0,MATCH(E$25,Breakdown[#Headers],0)),Breakdown[AEA],$A31) -> 57304196 | F31: =SUMIFS(INDEX(Breakdown[],0,MATCH(F$25,Breakdown[#Headers],0)),Breakdown[AEA],$A31) -> 38731511 | G31: =SUMIFS(INDEX(Breakdown[],0,MATCH(G$25,Breakdown[#Headers],0)),Breakdown[AEA],$A31) -> 18572685
A32: =A20 -> 12 | B32: =B20 -> Northwest AEA | C32: =SUMIFS(INDEX(Breakdown[],0,MATCH(C$25,Breakdown[#Headers],0)),Breakdown[AEA],$A32) -> 1150261 | D32: =SUMIFS(INDEX(Breakdown[],0,MATCH(D$25,Breakdown[#Headers],0)),Breakdown[AEA],$A32) -> 1287750 | E32: =SUMIFS(INDEX(Breakdown[],0,MATCH(E$25,Breakdown[#Headers],0)),Breakdown[AEA],$A32) -> 17251166 | F32: =SUMIFS(INDEX(Breakdown[],0,MATCH(F$25,Breakdown[#Headers],0)),Breakdown[AEA],$A32) -> 11162299 | G32: =SUMIFS(INDEX(Breakdown[],0,MATCH(G$25,Breakdown[#Headers],0)),Breakdown[AEA],$A32) -> 6088867
A33: =A21 -> 13 | B33: =B21 -> Green Hills AEA 13 | C33: =SUMIFS(INDEX(Breakdown[],0,MATCH(C$25,Breakdown[#Headers],0)),Breakdown[AEA],$A33) -> 960922 | D33: =SUMIFS(INDEX(Breakdown[],0,MATCH(D$25,Breakdown[#Headers],0)),Breakdown[AEA],$A33) -> 1062418 | E33: =SUMIFS(INDEX(Breakdown[],0,MATCH(E$25,Breakdown[#Headers],0)),Breakdown[AEA],$A33) -> 15739037 | F33: =SUMIFS(INDEX(Breakdown[],0,MATCH(F$25,Breakdown[#Headers],0)),Breakdown[AEA],$A33) -> 10527304 | G33: =SUMIFS(INDEX(Breakdown[],0,MATCH(G$25,Breakdown[#Headers],0)),Breakdown[AEA],$A33) -> 5211733
A34: =A22 -> 15 | B34: =B22 -> Great Prairie AEA 15 | C34: =SUMIFS(INDEX(Breakdown[],0,MATCH(C$25,Breakdown[#Headers],0)),Breakdown[AEA],$A34) -> 885624 | D34: =SUMIFS(INDEX(Breakdown[],0,MATCH(D$25,Breakdown[#Headers],0)),Breakdown[AEA],$A34) -> 973641 | E34: =SUMIFS(INDEX(Breakdown[],0,MATCH(E$25,Breakdown[#Headers],0)),Breakdown[AEA],$A34) -> 14033701 | F34: =SUMIFS(INDEX(Breakdown[],0,MATCH(F$25,Breakdown[#Headers],0)),Breakdown[AEA],$A34) -> 9389615 | G34: =SUMIFS(INDEX(Breakdown[],0,MATCH(G$25,Breakdown[#Headers],0)),Breakdown[AEA],$A34) -> 4644086
C35: =SUM(C26:C34) -> 13252861 | D35: =SUM(D26:D34) -> 14643281 | E35: =SUM(E26:E34) -> 203901037 | F35: =SUM(F26:F34) -> 135318213 | G35: =SUM(G26:G34) -> 68582824

Sheet Breakdown
A1: AEA | B1: AEA Name | C1: Dist | D1: District | E1: AEA Special Ed Support District Cost Formula Generated | F1: State Aid Portion Special Ed | G1: AEA Statewide State Aid Reduction | H1: State Aid Special Ed Minus Reduction | I1: Special Education Property Tax Portion | J1: AEA Special Ed Support Adjustment | K1: Total Special Ed Funding Removing Reduction Including Adjustment | L1: State Aid Portion Sharing Operations | M1: Sharing Operations Property Tax | N1: Total AEA Sharing Operations | O1: AEA Teacher Salary Supplement District Cost | P1: AEA Professional Development Supplement District Cost | Q1: AEA Media Services District Cost - 40% | R1: AEA Ed Services District Cost - 40% | S1: Total Budget | T1: State Aid Portion | U1: Property Tax Portion
A2: 01 | B2: Keystone AEA 1 | C2: 0135 | D2: Allamakee | E2: 451115 | F2: 341677 | G2: 74482 | H2: 267195 | I2: 109438 | J2: 0 | K2: 376633 | L2: 894 | M2: 286 | N2: 1180 | O2: 44709 | P2: 0 | Q2: 32174 | R2: 35840 | S2: 490536 | T2: 312798 | U2: 177738
A3: 01 | B3: Keystone AEA 1 | C3: 1080 | D3: Central Clayton | E3: 191505 | F3: 145047 | G3: 31619 | H3: 113428 | I3: 46458 | J3: 0 | K3: 159886 | L3: 381 | M3: 122 | N3: 503 | O3: 18980 | P3: 0 | Q3: 11953 | R3: 13315 | S3: 204637 | T3: 132788 | U3: 71849
A4: 01 | B4: Keystone AEA 1 | C4: 2763 | D4: Clayton Ridge | E4: 255058 | F4: 193182 | G4: 42111 | H4: 151071 | I4: 61876 | J4: 0 | K4: 212947 | L4: 505 | M4: 162 | N4: 667 | O4: 25278 | P4: 0 | Q4: 16356 | R4: 18219 | S4: 273467 | T4: 176854 | U4: 96613
A5: 01 | B5: Keystone AEA 1 | C5: 1638 | D5: Decorah | E5: 604387 | F5: 457766 | G5: 99788 | H5: 357978 | I5: 146621 | J5: 0 | K5: 504599 | L5: 1196 | M5: 383 | N5: 1579 | O5: 59900 | P5: 0 | Q5: 42336 | R5: 47159 | S5: 655573 | T5: 419074 | U5: 236499
A6: 01 | B6: Keystone AEA 1 | C6: 1863 | D6: Dubuque | E6: 4249056 | F6: 3218260 | G6: 701548 | H6: 2516712 | I6: 1030796 | J6: 0 | K6: 3547508 | L6: 8411 | M6: 2693 | N6: 11104 | O6: 421115 | P6: 0 | Q6: 301188 | R6: 335501 | S6: 4616416 | T6: 2946237 | U6: 1670179
A7: 01 | B7: Keystone AEA 1 | C7: 1972 | D7: Eastern Allamakee | E7: 119888 | F7: 90804 | G7: 19795 | H7: 71009 | I7: 29084 | J7: 11434 | K7: 111527 | L7: 238 | M7: 76 | N7: 314 | O7: 13002 | P7: 0 | Q7: 7909 | R7: 8810 | S7: 141562 | T7: 84248 | U7: 57314
A8: 01 | B8: Keystone AEA 1 | C8: 1989 | D8: Edgewood-Colesburg | E8: 148955 | F8: 112820 | G8: 24593 | H8: 88227 | I8: 36135 | J8: 0 | K8: 124362 | L8: 294 | M8: 95 | N8: 389 | O8: 14763 | P8: 0 | Q8: 10622 | R8: 11832 | S8: 161968 | T8: 103284 | U8: 58684
A9: 01 | B9: Keystone AEA 1 | C9: 3029 | D9: Howard-Winneshiek | E9: 464283 | F9: 351651 | G9: 76657 | H9: 274994 | I9: 112632 | J9: 0 | K9: 387626 | L9: 921 | M9: 295 | N9: 1216 | O9: 46014 | P9: 0 | Q9: 32200 | R9: 35868 | S9: 502924 | T9: 321928 | U9: 180996
A10: 01 | B10: Keystone AEA 1 | C10: 4419 | D10: MFL Mar Mac | E10: 325912 | F10: 246848 | G10: 53811 | H10: 193037 | I10: 79064 | J10: 0 | K10: 272101 | L10: 645 | M10: 207 | N10: 852 | O10: 32300 | P10: 0 | Q10: 20912 | R10: 23294 | S10: 349459 | T10: 225982 | U10: 123477
A11: 01 | B11: Keystone AEA 1 | C11: 4043 | D11: Maquoketa Valley | E11: 271360 | F11: 205529 | G11: 44803 | H11: 160726 | I11: 65831 | J11: 0 | K11: 226557 | L11: 537 | M11: 172 | N11: 709 | O11: 26894 | P11: 0 | Q11: 18199 | R11: 20272 | S11: 292631 | T11: 188158 | U11: 104473
A12: 01 | B12: Keystone AEA 1 | C12: 4662 | D12: New Hampton | E12: 383986 | F12: 290833 | G12: 63398 | H12: 227435 | I12: 93153 | J12: 0 | K12: 320588 | L12: 761 | M12: 244 | N12: 1005 | O12: 38056 | P12: 0 | Q12: 26518 | R12: 29538 | S12: 415705 | T12: 266253 | U12: 149452
A13: 01 | B13: Keystone AEA 1 | C13: 4774 | D13: North Fayette Valley | E13: 469249 | F13: 355412 | G13: 77476 | H13: 277936 | I13: 113837 | J13: 0 | K13: 391773 | L13: 929 | M13: 297 | N13: 1226 | O13: 46506 | P13: 0 | Q13: 28412 | R13: 31648 | S13: 499565 | T13: 325371 | U13: 174194
... A326: 15 | B326: Great Prairie AEA 15 | C326: 7047 | D326: Winfield-Mt Union | E326: 121221 | F326: 96366 | G326: 21007 | H326: 75359 | I326: 24855 | J326: 0 | K326: 100214 | L326: 224 | M326: 58 | N326: 282 | O326: 12192 | P326: 0 | Q326: 8076 | R326: 8878 | S326: 129642 | T326: 87775 | U326: 41867

Sheet Detail
A1: FY 2025 AEA Weights and Costs Detail
A2: AEA | B2: AEA Name | C2: Dist | D2: District | E2: Total Special Ed Weighting in Addition to 1.0 | F2: Budget Enrollment | G2: AEA Weighted Enrollment | H2: AEA Supplementary Weight for Sharing | I2: Resident Accredited Nonpublic Students | J2: Shared-Time Nonpublic Pupils Counted in Line 1.1 | K2: Total Enrollment Served - AEA Media and Ed Services | L2: AEA Special Ed Support Cost Per Pupil | M2: AEA Media Cost Per Pupil | N2: AEA Ed Services Cost Per Pupil | O2: AEA Teacher Salary Supplement District Cost Per Pupil | P2: Professional Development Supplement District Cost Per Pupil | Q2: AEA Special Ed Support District Cost without Adjustment | R2: AEA Special Ed Support Adjustment | S2: Special Education Total Cost | T2: Media Services 40% | U2: Education Services 40% | V2: AEA Sharing District Cost | W2: AEA Teacher Salary Supplement District Cost | X2: AEA Professional Development Supplement District Cost | Y2: Subtotal Budget | Z2: AEA Statewide State Aid Reduction | AA2: Total Budget | AB2: State Aid Portion | AC2: Property Tax Portion
A3: 01 | B3: Keystone AEA 1 | C3: 0135 | D3: Allamakee | E3: 155.67 | F3: 1109.8 | G3: 1265.47 | H3: 3.31 | I3: 148 | J3: 1.3 | K3: 1257 | L3: 356.48 | M3: 63.99 | N3: 71.28 | O3: 35.33 | P3: 3.84 | Q3: 451115 | R3: 0 | S3: 451115 | T3: 32174 | U3: 35840 | V3: 1180 | W3: 44709 | X3: 0 | Y3: 565018 | Z3: 74482 | AA3: 490536 | AB3: 312798 | AC3: 177738
A4: 01 | B4: Keystone AEA 1 | C4: 1080 | D4: Central Clayton | E4: 69.91 | F4: 467.3 | G4: 537.21 | H4: 1.41 | I4: 0 | J4: 0 | K4: 467 | L4: 356.48 | M4: 63.99 | N4: 71.28 | O4: 35.33 | P4: 3.84 | Q4: 191505 | R4: 0 | S4: 191505 | T4: 11953 | U4: 13315 | V4: 503 | W4: 18980 | X4: 0 | Y4: 236256 | Z4: 31619 | AA4: 204637 | AB4: 132788 | AC4: 71849
A5: 01 | B5: Keystone AEA 1 | C5: 2763 | D5: Clayton Ridge | E5: 87.49 | F5: 628 | G5: 715.49 | H5: 1.87 | I5: 11 | J5: 0 | K5: 639 | L5: 356.48 | M5: 63.99 | N5: 71.28 | O5: 35.33 | P5: 3.84 | Q5: 255058 | R5: 0 | S5: 255058 | T5: 16356 | U5: 18219 | V5: 667 | W5: 25278 | X5: 0 | Y5: 315578 | Z5: 42111 | AA5: 273467 | AB5: 176854 | AC5: 96613
A6: 01 | B6: Keystone AEA 1 | C6: 1638 | D6: Decorah | E6: 186.83 | F6: 1508.6 | G6: 1695.43 | H6: 4.43 | I6: 146 | J6: 0.8 | K6: 1654 | L6: 356.48 | M6: 63.99 | N6: 71.28 | O6: 35.33 | P6: 3.84 | Q6: 604387 | R6: 0 | S6: 604387 | T6: 42336 | U6: 47159 | V6: 1579 | W6: 59900 | X6: 0 | Y6: 755361 | Z6: 99788 | AA6: 655573 | AB6: 419074 | AC6: 236499
A7: 01 | B7: Keystone AEA 1 | C7: 1863 | D7: Dubuque | E7: 1923.48 | F7: 9996 | G7: 11919.48 | H7: 31.15 | I7: 1777 | J7: 6.4 | K7: 11767 | L7: 356.48 | M7: 63.99 | N7: 71.28 | O7: 35.33 | P7: 3.84 | Q7: 4249056 | R7: 0 | S7: 4249056 | T7: 301188 | U7: 335501 | V7: 11104 | W7: 421115 | X7: 0 | Y7: 5317964 | Z7: 701548 | AA7: 4616416 | AB7: 2946237 | AC7: 1670179
A8: 01 | B8: Keystone AEA 1 | C8: 1972 | D8: Eastern Allamakee | E8: 35.01 | F8: 301.3 | G8: 336.31 | H8: 0.88 | I8: 8 | J8: 0 | K8: 309 | L8: 356.48 | M8: 63.99 | N8: 71.28 | O8: 35.33 | P8: 3.84 | Q8: 119888 | R8: 11434 | S8: 131322 | T8: 7909 | U8: 8810 | V8: 314 | W8: 13002 | X8: 0 | Y8: 161357 | Z8: 19795 | AA8: 141562 | AB8: 84248 | AC8: 57314
A9: 01 | B9: Keystone AEA 1 | C9: 1989 | D9: Edgewood-Colesburg | E9: 25.85 | F9: 392 | G9: 417.85 | H9: 1.09 | I9: 23 | J9: 0 | K9: 415 | L9: 356.48 | M9: 63.99 | N9: 71.28 | O9: 35.33 | P9: 3.84 | Q9: 148955 | R9: 0 | S9: 148955 | T9: 10622 | U9: 11832 | V9: 389 | W9: 14763 | X9: 0 | Y9: 186561 | Z9: 24593 | AA9: 161968 | AB9: 103284 | AC9: 58684
A10: 01 | B10: Keystone AEA 1 | C10: 3029 | D10: Howard-Winneshiek | E10: 167.41 | F10: 1135 | G10: 1302.41 | H10: 3.41 | I10: 125 | J10: 1.6 | K10: 1258 | L10: 356.48 | M10: 63.99 | N10: 71.28 | O10: 35.33 | P10: 3.84 | Q10: 464283 | R10: 0 | S10: 464283 | T10: 32200 | U10: 35868 | V10: 1216 | W10: 46014 | X10: 0 | Y10: 579581 | Z10: 76657 | AA10: 502924 | AB10: 321928 | AC10: 180996
A11: 01 | B11: Keystone AEA 1 | C11: 4419 | D11: MFL Mar Mac | E11: 101.95 | F11: 812.3 | G11: 914.25 | H11: 2.39 | I11: 5 | J11: 0 | K11: 817 | L11: 356.48 | M11: 63.99 | N11: 71.28 | O11: 35.33 | P11: 3.84 | Q11: 325912 | R11: 0 | S11: 325912 | T11: 20912 | U11: 23294 | V11: 852 | W11: 32300 | X11: 0 | Y11: 403270 | Z11: 53811 | AA11: 349459 | AB11: 225982 | AC11: 123477
A12: 01 | B12: Keystone AEA 1 | C12: 4043 | D12: Maquoketa Valley | E12: 86.92 | F12: 674.3 | G12: 761.22 | H12: 1.99 | I12: 37 | J12: 0 | K12: 711 | L12: 356.48 | M12: 63.99 | N12: 71.28 | O12: 35.33 | P12: 3.84 | Q12: 271360 | R12: 0 | S12: 271360 | T12: 18199 | U12: 20272 | V12: 709 | W12: 26894 | X12: 0 | Y12: 337434 | Z12: 44803 | AA12: 292631 | AB12: 188158 | AC12: 104473
A13: 01 | B13: Keystone AEA 1 | C13: 4662 | D13: New Hampton | E13: 106.56 | F13: 970.6 | G13: 1077.16 | H13: 2.82 | I13: 66 | J13: 1.1 | K13: 1036 | L13: 356.48 | M13: 63.99 | N13: 71.28 | O13: 35.33 | P13: 3.84 | Q13: 383986 | R13: 0 | S13: 383986 | T13: 26518 | U13: 29538 | V13: 1005 | W13: 38056 | X13: 0 | Y13: 479103 | Z13: 63398 | AA13: 415705 | AB13: 266253 | AC13: 149452
A14: 01 | B14: Keystone AEA 1 | C14: 4774 | D14: North Fayette Valley | E14: 209.74 | F14: 1106.6 | G14: 1316.34 | H14: 3.44 | I14: 3 | J14: 0 | K14: 1110 | L14: 356.48 | M14: 63.99 | N14: 71.28 | O14: 35.33 | P14: 3.84 | Q14: 469249 | R14: 0 | S14: 469249 | T14: 28412 | U14: 31648 | V14: 1226 | W14: 46506 | X14: 0 | Y14: 577041 | Z14: 77476 | AA14: 499565 | AB14: 325371 | AC14: 174194
... A327: 15 | B327: Great Prairie AEA 15 | C327: 7047 | D327: Winfield-Mt Union | E327: 40.31 | F327: 316.6 | G327: 356.91 | H327: 0.83 | I327: 0 | J327: 0 | K327: 317 | L327: 339.64 | M327: 63.69 | N327: 70.02 | O327: 34.16 | P327: 3.75 | Q327: 121221 | R327: 0 | S327: 121221 | T327: 8076 | U327: 8878 | V327: 282 | W327: 12192 | X327: 0 | Y327: 150649 | Z327: 21007 | AA327: 129642 | AB327: 87775 | AC327: 41867

Sheet Detail By AEA
B1: =CONCATENATE(INDEX(Detail[],MATCH(A5,Detail[Dist],0),2)," Detail by School District") -> Green Hills AEA 13 Detail by School District
A4: Dist | B4: District | C4: Total Special Ed Weighting | D4: Budget Enrollment | E4: AEA Weighted Enrollment | F4: AEA Supplementary Weight for Sharing | G4: Resident Accredited Nonpublic Students | H4: Shared-Time Nonpublic Pupils | I4: Total Enrollment Served - AEA Media and Ed Services | J4: AEA Special Ed Support District Cost without Adjustment | K4: AEA Special Ed Support Adjustment | L4: Special Education Total Cost | M4: AEA Sharing District Cost | N4: AEA Teacher Salary Supplement District Cost | O4: AEA Professional Development Supplement District Cost | P4: Subtotal Budget | Q4: AEA State Aid Reduction | R4: Total Budget | S4: State Aid Portion | T4: Property Tax Portion
A5: 0387 | B5: Atlantic | C5: 246.65 | D5: 1414.2 | E5: 1660.85 | F5: 3.42 | G5: 1 | H5: 0 | I5: 1415 | J5: 568476 | K5: 0 | L5: 568476 | M5: 1171 | N5: 58379 | O5: 0 | P5: 703967 | Q5: 97753 | R5: 606214 | S5: 409979 | T5: 196235
A6: 0441 | B6: AHSTW | C6: 94.62 | D6: 780.7 | E6: 875.32 | F6: 1.8 | G6: 3 | H6: 0 | I6: 784 | J6: 299605 | K6: 0 | L6: 299605 | M6: 616 | N6: 30767 | O6: 0 | P6: 373063 | Q6: 51519 | R6: 321544 | S6: 216070 | T6: 105474
A7: 0549 | B7: Bedford | C7: 64.07 | D7: 511 | E7: 575.07 | F7: 1.18 | G7: 6 | H7: 0 | I7: 517 | J7: 196835 | K7: 0 | L7: 196835 | M7: 404 | N7: 20214 | O7: 0 | P7: 245199 | Q7: 33847 | R7: 211352 | S7: 141955 | T7: 69397
A8: 0914 | B8: CAM | C8: 57.93 | D8: 447.6 | E8: 505.53 | F8: 1.04 | G8: 2 | H8: 0 | I8: 450 | J8: 173033 | K8: 38 | L8: 173071 | M8: 356 | N8: 17771 | O8: 0 | P8: 215349 | Q8: 29754 | R8: 185595 | S8: 124791 | T8: 60804
A9: 1093 | B9: Central Decatur | C9: 120.12 | D9: 632.4 | E9: 752.52 | F9: 1.55 | G9: 0 | H9: 0 | I9: 632 | J9: 257573 | K9: 0 | L9: 257573 | M9: 531 | N9: 26451 | O9: 0 | P9: 318473 | Q9: 44291 | R9: 274182 | S9: 185759 | T9: 88423
A10: 1197 | B10: Clarinda | C10: 113.58 | D10: 958.7 | E10: 1072.28 | F10: 2.21 | G10: 64 | H10: 1.2 | I10: 1022 | J10: 367020 | K10: 5273 | L10: 372293 | M10: 756 | N10: 38228 | O10: 0 | P10: 466126 | Q10: 63111 | R10: 403015 | S10: 265229 | T10: 137786
A11: 1211 | B11: Clarke | C11: 185.18 | D11: 1429.1 | E11: 1614.28 | F11: 3.32 | G11: 6 | H11: 0 | I11: 1435 | J11: 552536 | K11: 0 | L11: 552536 | M11: 1136 | N11: 56742 | O11: 0 | P11: 687427 | Q11: 95012 | R11: 592415 | S11: 398482 | T11: 193933
A12: 1431 | B12: Corning | C12: 48 | D12: 376.2 | E12: 424.2 | F12: 0.87 | G12: 4 | H12: 0 | I12: 380 | J12: 145195 | K12: 6355 | L12: 151550 | M12: 298 | N12: 14911 | O12: 0 | P12: 187153 | Q12: 24967 | R12: 162186 | S12: 104713 | T12: 57473
A13: 1476 | B13: Council Bluffs | C13: 2225.1 | D13: 8632.4 | E13: 10857.5 | F13: 22.33 | G13: 465 | H13: 0 | I13: 9097 | J13: 3716305 | K13: 0 | L13: 3716305 | M13: 7643 | N13: 381641 | O13: 0 | P13: 4593807 | Q13: 639043 | R13: 3954764 | S13: 2680152 | T13: 1274612
A14: 1503 | B14: Creston | C14: 190.55 | D14: 1369.4 | E14: 1559.95 | F14: 3.21 | G14: 115 | H14: 1 | I14: 1483 | J14: 533940 | K14: 0 | L14: 533940 | M14: 1099 | N14: 54832 | O14: 0 | P14: 669461 | Q14: 91815 | R14: 577646 | S14: 385070 | T14: 192576
A15: 1782 | B15: Diagonal | C15: 8.53 | D15: 87 | E15: 95.53 | F15: 0.2 | G15: 0 | H15: 0 | I15: 87 | J15: 32698 | K15: 9322 | L15: 42020 | M15: 68 | N15: 4315 | O15: 0 | P15: 51073 | Q15: 5623 | R15: 45450 | S15: 24539 | T15: 20911
A16: 1917 | B16: Boyer Valley | C16: 38.48 | D16: 385.6 | E16: 424.08 | F16: 0.87 | G16: 3 | H16: 0 | I16: 389 | J16: 145154 | K16: 0 | L16: 145154 | M16: 298 | N16: 14906 | O16: 0 | P16: 181235 | Q16: 24960 | R16: 156275 | S16: 104683 | T16: 51592
... A47: 7092 | B47: Woodbine | C47: 63.6 | D47: 507 | E47: 570.6 | F47: 1.17 | G47: 3 | H47: 0 | I47: 510 | J47: 195305 | K47: 0 | L47: 195305 | M47: 400 | N47: 20057 | O47: 0 | P47: 243133 | Q47: 33584 | R47: 209549 | S47: 140851 | T47: 68698
A48: AEA Total | C48: 6032.86 | D48: 36581.1 | E48: 42613.96 | F48: 87.65 | G48: 1124 | H48: 4.1 | I48: 37701 | J48: 14585910 | K48: 101921 | L48: 14687831 | M48: 30001 | N48: 1506001 | O48: 0 | P48: 18247173 | Q48: 2508136 | R48: 15739037 | S48: 10527304 | T48: 5211733
