Workbook
Name AEA_Name: #REF!
Name Slicer_AEA_Name: #N/A

Sheet Summary
C1: =Detail[[#Headers],[Total Special Ed Weighting in Addition to 1.0]] -> Total Special Ed Weighting in Addition to 1.0 | D1: =Detail[[#Headers],[Budget Enrollment]] -> Budget Enrollment | E1: =Detail[[#Headers],[AEA Weighted Enrollment]] -> AEA Weighted Enrollment | F1: =Detail[[#Headers],[Resident Accredited Nonpublic Students]] -> Resident Accredited Nonpublic Students | G1: =Detail[[#Headers],[Shared-Time Nonpublic Pupils Counted in Line 1.1]] -> Shared-Time Nonpublic Pupils Counted in Line 1.1 | H1: =Detail[[#Headers],[Total Enrollment Served - AEA Media and Ed Services]] -> Total Enrollment Served - AEA Media and Ed Services | I1: =Detail[[#Headers],[AEA Special Ed Support Cost Per Pupil]] -> AEA Special Ed Support Cost Per Pupil | J1: =Detail[[#Headers],[AEA Media Cost Per Pupil]] -> AEA Media Cost Per Pupil | K1: =Detail[[#Headers],[AEA Ed Services Cost Per Pupil]] -> AEA Ed Services Cost Per Pupil
A2: AEA | B2: AEA Name | C2: Special Ed Weights | D2: Budget Enrollment | E2: Weighted Enrollment | F2: Nonpublic | G2: Shared-Time | H2: Media/Ed Served | I2: Support Cost PP | J2: Media Cost PP | K2: Ed Cost PP
A3: {=IFERROR(INDEX(Detail[AEA], MATCH(0,COUNTIF(Summary!$A$2:'Summary'!A2, Detail[AEA]), 0)),"")} -> 01 | B3: =INDEX(Detail[],MATCH(Summary!$A3,Detail[AEA],0),2) -> Keystone AEA 1 | C3: =SUMIFS(INDEX(Detail[],0,MATCH(C$1,Detail[#Headers],0)),Detail[AEA],$A3) -> 4386.05 | D3: =SUMIFS(INDEX(Detail[],0,MATCH(D$1,Detail[#Headers],0)),Detail[AEA],$A3) -> 27800.7 | E3: =SUMIFS(INDEX(Detail[],0,MATCH(E$1,Detail[#Headers],0)),Detail[AEA],$A3) -> 32186.75 | F3: =SUMIFS(INDEX(Detail[],0,MATCH(F$1,Detail[#Headers],0)),Detail[AEA],$A3) -> 3829 | G3: =SUMIFS(INDEX(Detail[],0,MATCH(G$1,Detail[#Headers],0)),Detail[AEA],$A3) -> 14.8 | H3: =SUMIFS(INDEX(Detail[],0,MATCH(H$1,Detail[#Headers],0)),Detail[AEA],$A3) -> 31617 | I3: =INDEX(Detail[],MATCH($A3,Detail[AEA],0),MATCH(I$1,Detail[#Headers],0)) -> 338.42 | J3: =INDEX(Detail[],MATCH($A3,Detail[AEA],0),MATCH(J$1,Detail[#Headers],0)) -> 60.63 | K3: =INDEX(Detail[],MATCH($A3,Detail[AEA],0),MATCH(K$1,Detail[#Headers],0)) -> 67.56
A4: {=IFERROR(INDEX(Detail[AEA], MATCH(0,COUNTIF(Summary!$A$2:'Summary'!A3, Detail[AEA]), 0)),"")} -> 05 | B4: =INDEX(Detail[],MATCH(Summary!$A4,Detail[AEA],0),2) -> Prairie Lakes AEA 8 | C4: =SUMIFS(INDEX(Detail[],0,MATCH(C$1,Detail[#Headers],0)),Detail[AEA],$A4) -> 4040.94 | D4: =SUMIFS(INDEX(Detail[],0,MATCH(D$1,Detail[#Headers],0)),Detail[AEA],$A4) -> 30029.6 | E4: =SUMIFS(INDEX(Detail[],0,MATCH(E$1,Detail[#Headers],0)),Detail[AEA],$A4) -> 34070.54 | F4: =SUMIFS(INDEX(Detail[],0,MATCH(F$1,Detail[#Headers],0)),Detail[AEA],$A4) -> 1995 | G4: =SUMIFS(INDEX(Detail[],0,MATCH(G$1,Detail[#Headers],0)),Detail[AEA],$A4) -> 27.8 | H4: =SUMIFS(INDEX(Detail[],0,MATCH(H$1,Detail[#Headers],0)),Detail[AEA],$A4) -> 31995 | I4: =INDEX(Detail[],MATCH($A4,Detail[AEA],0),MATCH(I$1,Detail[#Headers],0)) -> 334.17 | J4: =INDEX(Detail[],MATCH($A4,Detail[AEA],0),MATCH(J$1,Detail[#Headers],0)) -> 60.71 | K4: =INDEX(Detail[],MATCH($A4,Detail[AEA],0),MATCH(K$1,Detail[#Headers],0)) -> 68.03
A5: {=IFERROR(INDEX(Detail[AEA], MATCH(0,COUNTIF(Summary!$A$2:'Summary'!A4, Detail[AEA]), 0)),"")} -> 07 | B5: =INDEX(Detail[],MATCH(Summary!$A5,Detail[AEA],0),2) -> Central Rivers | C5: =SUMIFS(INDEX(Detail[],0,MATCH(C$1,Detail[#Headers],0)),Detail[AEA],$A5) -> 9290.28 | D5: =SUMIFS(INDEX(Detail[],0,MATCH(D$1,Detail[#Headers],0)),Detail[AEA],$A5) -> 61360 | E5: =SUMIFS(INDEX(Detail[],0,MATCH(E$1,Detail[#Headers],0)),Detail[AEA],$A5) -> 70650.28 | F5: =SUMIFS(INDEX(Detail[],0,MATCH(F$1,Detail[#Headers],0)),Detail[AEA],$A5) -> 3233 | G5: =SUMIFS(INDEX(Detail[],0,MATCH(G$1,Detail[#Headers],0)),Detail[AEA],$A5) -> 35.5 | H5: =SUMIFS(INDEX(Detail[],0,MATCH(H$1,Detail[#Headers],0)),Detail[AEA],$A5) -> 64559 | I5: =INDEX(Detail[],MATCH($A5,Detail[AEA],0),MATCH(I$1,Detail[#Headers],0)) -> 327.54 | J5: =INDEX(Detail[],MATCH($A5,Detail[AEA],0),MATCH(J$1,Detail[#Headers],0)) -> 60.66 | K5: =INDEX(Detail[],MATCH($A5,Detail[AEA],0),MATCH(K$1,Detail[#Headers],0)) -> 67.65
A6: {=IFERROR(INDEX(Detail[AEA], MATCH(0,COUNTIF(Summary!$A$2:'Summary'!A5, Detail[AEA]), 0)),"")} -> 09 | B6: =INDEX(Detail[],MATCH(Summary!$A6,Detail[AEA],0),2) -> Mississippi Bend AEA 9 | C6: =SUMIFS(INDEX(Detail[],0,MATCH(C$1,Detail[#Headers],0)),Detail[AEA],$A6) -> 6561.12 | D6: =SUMIFS(INDEX(Detail[],0,MATCH(D$1,Detail[#Headers],0)),Detail[AEA],$A6) -> 45498.3 | E6: =SUMIFS(INDEX(Detail[],0,MATCH(E$1,Detail[#Headers],0)),Detail[AEA],$A6) -> 52059.42 | F6: =SUMIFS(INDEX(Detail[],0,MATCH(F$1,Detail[#Headers],0)),Detail[AEA],$A6) -> 3060 | G6: =SUMIFS(INDEX(Detail[],0,MATCH(G$1,Detail[#Headers],0)),Detail[AEA],$A6) -> 2.7 | H6: =SUMIFS(INDEX(Detail[],0,MATCH(H$1,Detail[#Headers],0)),Detail[AEA],$A6) -> 48556 | I6: =INDEX(Detail[],MATCH($A6,Detail[AEA],0),MATCH(I$1,Detail[#Headers],0)) -> 325.18 | J6: =INDEX(Detail[],MATCH($A6,Detail[AEA],0),MATCH(J$1,Detail[#Headers],0)) -> 60.17 | K6: =INDEX(Detail[],MATCH($A6,Detail[AEA],0),MATCH(K$1,Detail[#Headers],0)) -> 65.73
A7: {=IFERROR(INDEX(Detail[AEA], MATCH(0,COUNTIF(Summary!$A$2:'Summary'!A6, Detail[AEA]), 0)),"")} -> 10 | B7: =INDEX(Detail[],MATCH(Summary!$A7,Detail[AEA],0),2) -> Grant Wood AEA 10 | C7: =SUMIFS(INDEX(Detail[],0,MATCH(C$1,Detail[#Headers],0)),Detail[AEA],$A7) -> 8310.65 | D7: =SUMIFS(INDEX(Detail[],0,MATCH(D$1,Detail[#Headers],0)),Detail[AEA],$A7) -> 69378.5 | E7: =SUMIFS(INDEX(Detail[],0,MATCH(E$1,Detail[#Headers],0)),Detail[AEA],$A7) -> 77689.15 | F7: =SUMIFS(INDEX(Detail[],0,MATCH(F$1,Detail[#Headers],0)),Detail[AEA],$A7) -> 4283 | G7: =SUMIFS(INDEX(Detail[],0,MATCH(G$1,Detail[#Headers],0)),Detail[AEA],$A7) -> 12.2 | H7: =SUMIFS(INDEX(Detail[],0,MATCH(H$1,Detail[#Headers],0)),Detail[AEA],$A7) -> 73649 | I7: =INDEX(Detail[],MATCH($A7,Detail[AEA],0),MATCH(I$1,Detail[#Headers],0)) -> 323.26 | J7: =INDEX(Detail[],MATCH($A7,Detail[AEA],0),MATCH(J$1,Detail[#Headers],0)) -> 60.35 | K7: =INDEX(Detail[],MATCH($A7,Detail[AEA],0),MATCH(K$1,Detail[#Headers],0)) -> 66.33
A8: {=IFERROR(INDEX(Detail[AEA], MATCH(0,COUNTIF(Summary!$A$2:'Summary'!A7, Detail[AEA]), 0)),"")} -> 11 | B8: =INDEX(Detail[],MATCH(Summary!$A8,Detail[AEA],0),2) -> Heartland AEA 11 | C8: =SUMIFS(INDEX(Detail[],0,MATCH(C$1,Detail[#Headers],0)),Detail[AEA],$A8) -> 18534.05 | D8: =SUMIFS(INDEX(Detail[],0,MATCH(D$1,Detail[#Headers],0)),Detail[AEA],$A8) -> 141056.7 | E8: =SUMIFS(INDEX(Detail[],0,MATCH(E$1,Detail[#Headers],0)),Detail[AEA],$A8) -> 159590.75 | F8: =SUMIFS(INDEX(Detail[],0,MATCH(F$1,Detail[#Headers],0)),Detail[AEA],$A8) -> 9710 | G8: =SUMIFS(INDEX(Detail[],0,MATCH(G$1,Detail[#Headers],0)),Detail[AEA],$A8) -> 52.4 | H8: =SUMIFS(INDEX(Detail[],0,MATCH(H$1,Detail[#Headers],0)),Detail[AEA],$A8) -> 150716 | I8: =INDEX(Detail[],MATCH($A8,Detail[AEA],0),MATCH(I$1,Detail[#Headers],0)) -> 316.16 | J8: =INDEX(Detail[],MATCH($A8,Detail[AEA],0),MATCH(J$1,Detail[#Headers],0)) -> 60.23 | K8: =INDEX(Detail[],MATCH($A8,Detail[AEA],0),MATCH(K$1,Detail[#Headers],0)) -> 66.15
A9: {=IFERROR(INDEX(Detail[AEA], MATCH(0,COUNTIF(Summary!$A$2:'Summary'!A8, Detail[AEA]), 0)),"")} -> 12 | B9: =INDEX(Detail[],MATCH(Summary!$A9,Detail[AEA],0),2) -> Northwest AEA | C9: =SUMIFS(INDEX(Detail[],0,MATCH(C$1,Detail[#Headers],0)),Detail[AEA],$A9) -> 5813.82 | D9: =SUMIFS(INDEX(Detail[],0,MATCH(D$1,Detail[#Headers],0)),Detail[AEA],$A9) -> 39999.7 | E9: =SUMIFS(INDEX(Detail[],0,MATCH(E$1,Detail[#Headers],0)),Detail[AEA],$A9) -> 45813.52 | F9: =SUMIFS(INDEX(Detail[],0,MATCH(F$1,Detail[#Headers],0)),Detail[AEA],$A9) -> 5265 | G9: =SUMIFS(INDEX(Detail[],0,MATCH(G$1,Detail[#Headers],0)),Detail[AEA],$A9) -> 37.3 | H9: =SUMIFS(INDEX(Detail[],0,MATCH(H$1,Detail[#Headers],0)),Detail[AEA],$A9) -> 45231 | I9: =INDEX(Detail[],MATCH($A9,Detail[AEA],0),MATCH(I$1,Detail[#Headers],0)) -> 330.8 | J9: =INDEX(Detail[],MATCH($A9,Detail[AEA],0),MATCH(J$1,Detail[#Headers],0)) -> 60.64 | K9: =INDEX(Detail[],MATCH($A9,Detail[AEA],0),MATCH(K$1,Detail[#Headers],0)) -> 67.93
A10: {=IFERROR(INDEX(Detail[AEA], MATCH(0,COUNTIF(Summary!$A$2:'Summary'!A9, Detail[AEA]), 0)),"")} -> 13 | B10: =INDEX(Detail[],MATCH(Summary!$A10,Detail[AEA],0),2) -> Green Hills AEA 13 | C10: =SUMIFS(INDEX(Detail[],0,MATCH(C$1,Detail[#Headers],0)),Detail[AEA],$A10) -> 5815.97 | D10: =SUMIFS(INDEX(Detail[],0,MATCH(D$1,Detail[#Headers],0)),Detail[AEA],$A10) -> 36677 | E10: =SUMIFS(INDEX(Detail[],0,MATCH(E$1,Detail[#Headers],0)),Detail[AEA],$A10) -> 42492.97 | F10: =SUMIFS(INDEX(Detail[],0,MATCH(F$1,Detail[#Headers],0)),Detail[AEA],$A10) -> 1011 | G10: =SUMIFS(INDEX(Detail[],0,MATCH(G$1,Detail[#Headers],0)),Detail[AEA],$A10) -> 3 | H10: =SUMIFS(INDEX(Detail[],0,MATCH(H$1,Detail[#Headers],0)),Detail[AEA],$A10) -> 37686 | I10: =INDEX(Detail[],MATCH($A10,Detail[AEA],0),MATCH(I$1,Detail[#Headers],0)) -> 324.22 | J10: =INDEX(Detail[],MATCH($A10,Detail[AEA],0),MATCH(J$1,Detail[#Headers],0)) -> 60.36 | K10: =INDEX(Detail[],MATCH($A10,Detail[AEA],0),MATCH(K$1,Detail[#Headers],0)) -> 66.73
A11: {=IFERROR(INDEX(Detail[AEA], MATCH(0,COUNTIF(Summary!$A$2:'Summary'!A10, Detail[AEA]), 0)),"")} -> 15 | B11: =INDEX(Detail[],MATCH(Summary!$A11,Detail[AEA],0),2) -> Great Prairie AEA 15 | C11: =SUMIFS(INDEX(Detail[],0,MATCH(C$1,Detail[#Headers],0)),Detail[AEA],$A11) -> 4726.16 | D11: =SUMIFS(INDEX(Detail[],0,MATCH(D$1,Detail[#Headers],0)),Detail[AEA],$A11) -> 33829.9 | E11: =SUMIFS(INDEX(Detail[],0,MATCH(E$1,Detail[#Headers],0)),Detail[AEA],$A11) -> 38556.06 | F11: =SUMIFS(INDEX(Detail[],0,MATCH(F$1,Detail[#Headers],0)),Detail[AEA],$A11) -> 1211 | G11: =SUMIFS(INDEX(Detail[],0,MATCH(G$1,Detail[#Headers],0)),Detail[AEA],$A11) -> 6.7 | H11: =SUMIFS(INDEX(Detail[],0,MATCH(H$1,Detail[#Headers],0)),Detail[AEA],$A11) -> 35034 | I11: =INDEX(Detail[],MATCH($A11,Detail[AEA],0),MATCH(I$1,Detail[#Headers],0)) -> 321.58 | J11: =INDEX(Detail[],MATCH($A11,Detail[AEA],0),MATCH(J$1,Detail[#Headers],0)) -> 60.33 | K11: =INDEX(Detail[],MATCH($A11,Detail[AEA],0),MATCH(K$1,Detail[#Headers],0)) -> 66.3
C12: =SUM(C3:C11) -> 67479.04 | D12: =SUM(D3:D11) -> 485630.4 | E12: =SUM(E3:E11) -> 553109.44 | F12: =SUM(F3:F11) -> 33597 | G12: =SUM(G3:G11) -> 192.4 | H12: =SUM(H3:H11) -> 519043
C14: =Detail[[#Headers],[AEA Teacher Salary Supplement District Cost Per Pupil]] -> AEA Teacher Salary Supplement District Cost Per Pupil | D14: =Detail[[#Headers],[Professional Development Supplement District Cost Per Pupil]] -> Professional Development Supplement District Cost Per Pupil | E14: =Detail[[#Headers],[AEA Special Ed Support District Cost without Adjustment]] -> AEA Special Ed Support District Cost without Adjustment | F14: =Detail[[#Headers],[AEA Special Ed Support Adjustment]] -> AEA Special Ed Support Adjustment | G14: =Detail[[#Headers],[Special Education Total Cost]] -> Special Education Total Cost | H14: =Detail[[#Headers],[AEA Media Services District Cost]] -> AEA Media Services District Cost | I14: =Detail[[#Headers],[AEA Ed Services District Cost]] -> AEA Ed Services District Cost | J14: =Detail[[#Headers],[AEA Sharing District Cost]] -> AEA Sharing District Cost
A15: =A2 -> AEA | B15: =B2 -> AEA Name | C15: Teach Sal Cost PP | D15: Prof Dev Cost PP | E15: Spec ED Support | F15: Spec Ed Adjust | G15: Special Ed Total Cost | H15: Media Services | I15: Education Services | J15: Sharing Operations
A16: =A3 -> 01 | B16: =B3 -> Keystone AEA 1 | C16: =INDEX(Detail[],MATCH($A16,Detail[AEA],0),MATCH(C$14,Detail[#Headers],0)) -> 33.47 | D16: =INDEX(Detail[],MATCH($A16,Detail[AEA],0),MATCH(D$14,Detail[#Headers],0)) -> 3.62 | E16: =SUMIFS(INDEX(Detail[],0,MATCH(E$14,Detail[#Headers],0)),Detail[AEA],$A16) -> 10892639 | F16: =SUMIFS(INDEX(Detail[],0,MATCH(F$14,Detail[#Headers],0)),Detail[AEA],$A16) -> 32188 | G16: =SUMIFS(INDEX(Detail[],0,MATCH(G$14,Detail[#Headers],0)),Detail[AEA],$A16) -> 10924827 | H16: =SUMIFS(INDEX(Detail[],0,MATCH(H$14,Detail[#Headers],0)),Detail[AEA],$A16) -> 1916940 | I16: =SUMIFS(INDEX(Detail[],0,MATCH(I$14,Detail[#Headers],0)),Detail[AEA],$A16) -> 2136044 | J16: =SUMIFS(INDEX(Detail[],0,MATCH(J$14,Detail[#Headers],0)),Detail[AEA],$A16) -> 30002
A17: =A4 -> 05 | B17: =B4 -> Prairie Lakes AEA 8 | C17: =INDEX(Detail[],MATCH($A17,Detail[AEA],0),MATCH(C$14,Detail[#Headers],0)) -> 35.43 | D17: =INDEX(Detail[],MATCH($A17,Detail[AEA],0),MATCH(D$14,Detail[#Headers],0)) -> 4.21 | E17: =SUMIFS(INDEX(Detail[],0,MATCH(E$14,Detail[#Headers],0)),Detail[AEA],$A17) -> 11385351 | F17: =SUMIFS(INDEX(Detail[],0,MATCH(F$14,Detail[#Headers],0)),Detail[AEA],$A17) -> 119140 | G17: =SUMIFS(INDEX(Detail[],0,MATCH(G$14,Detail[#Headers],0)),Detail[AEA],$A17) -> 11504491 | H17: =SUMIFS(INDEX(Detail[],0,MATCH(H$14,Detail[#Headers],0)),Detail[AEA],$A17) -> 1942415 | I17: =SUMIFS(INDEX(Detail[],0,MATCH(I$14,Detail[#Headers],0)),Detail[AEA],$A17) -> 2176620 | J17: =SUMIFS(INDEX(Detail[],0,MATCH(J$14,Detail[#Headers],0)),Detail[AEA],$A17) -> 0
A18: =A5 -> 07 | B18: =B5 -> Central Rivers | C18: =INDEX(Detail[],MATCH($A18,Detail[AEA],0),MATCH(C$14,Detail[#Headers],0)) -> 40.7 | D18: =INDEX(Detail[],MATCH($A18,Detail[AEA],0),MATCH(D$14,Detail[#Headers],0)) -> 4.68 | E18: =SUMIFS(INDEX(Detail[],0,MATCH(E$14,Detail[#Headers],0)),Detail[AEA],$A18) -> 23140792 | F18: =SUMIFS(INDEX(Detail[],0,MATCH(F$14,Detail[#Headers],0)),Detail[AEA],$A18) -> 228348 | G18: =SUMIFS(INDEX(Detail[],0,MATCH(G$14,Detail[#Headers],0)),Detail[AEA],$A18) -> 23369140 | H18: =SUMIFS(INDEX(Detail[],0,MATCH(H$14,Detail[#Headers],0)),Detail[AEA],$A18) -> 3916147 | I18: =SUMIFS(INDEX(Detail[],0,MATCH(I$14,Detail[#Headers],0)),Detail[AEA],$A18) -> 4367412 | J18: =SUMIFS(INDEX(Detail[],0,MATCH(J$14,Detail[#Headers],0)),Detail[AEA],$A18) -> 30001
A19: =A6 -> 09 | B19: =B6 -> Mississippi Bend AEA 9 | C19: =INDEX(Detail[],MATCH($A19,Detail[AEA],0),MATCH(C$14,Detail[#Headers],0)) -> 29.77 | D19: =INDEX(Detail[],MATCH($A19,Detail[AEA],0),MATCH(D$14,Detail[#Headers],0)) -> 3.49 | E19: =SUMIFS(INDEX(Detail[],0,MATCH(E$14,Detail[#Headers],0)),Detail[AEA],$A19) -> 16928684 | F19: =SUMIFS(INDEX(Detail[],0,MATCH(F$14,Detail[#Headers],0)),Detail[AEA],$A19) -> 184554 | G19: =SUMIFS(INDEX(Detail[],0,MATCH(G$14,Detail[#Headers],0)),Detail[AEA],$A19) -> 17113238 | H19: =SUMIFS(INDEX(Detail[],0,MATCH(H$14,Detail[#Headers],0)),Detail[AEA],$A19) -> 2921615 | I19: =SUMIFS(INDEX(Detail[],0,MATCH(I$14,Detail[#Headers],0)),Detail[AEA],$A19) -> 3191586 | J19: =SUMIFS(INDEX(Detail[],0,MATCH(J$14,Detail[#Headers],0)),Detail[AEA],$A19) -> 30001
A20: =A7 -> 10 | B20: =B7 -> Grant Wood AEA 10 | C20: =INDEX(Detail[],MATCH($A20,Detail[AEA],0),MATCH(C$14,Detail[#Headers],0)) -> 30.52 | D20: =INDEX(Detail[],MATCH($A20,Detail[AEA],0),MATCH(D$14,Detail[#Headers],0)) -> 3.55 | E20: =SUMIFS(INDEX(Detail[],0,MATCH(E$14,Detail[#Headers],0)),Detail[AEA],$A20) -> 25113798 | F20: =SUMIFS(INDEX(Detail[],0,MATCH(F$14,Detail[#Headers],0)),Detail[AEA],$A20) -> 100491 | G20: =SUMIFS(INDEX(Detail[],0,MATCH(G$14,Detail[#Headers],0)),Detail[AEA],$A20) -> 25214289 | H20: =SUMIFS(INDEX(Detail[],0,MATCH(H$14,Detail[#Headers],0)),Detail[AEA],$A20) -> 4444716 | I20: =SUMIFS(INDEX(Detail[],0,MATCH(I$14,Detail[#Headers],0)),Detail[AEA],$A20) -> 4885140 | J20: =SUMIFS(INDEX(Detail[],0,MATCH(J$14,Detail[#Headers],0)),Detail[AEA],$A20) -> 30000
A21: =A8 -> 11 | B21: =B8 -> Heartland AEA 11 | C21: =INDEX(Detail[],MATCH($A21,Detail[AEA],0),MATCH(C$14,Detail[#Headers],0)) -> 26.75 | D21: =INDEX(Detail[],MATCH($A21,Detail[AEA],0),MATCH(D$14,Detail[#Headers],0)) -> 3.36 | E21: =SUMIFS(INDEX(Detail[],0,MATCH(E$14,Detail[#Headers],0)),Detail[AEA],$A21) -> 50456211 | F21: =SUMIFS(INDEX(Detail[],0,MATCH(F$14,Detail[#Headers],0)),Detail[AEA],$A21) -> 67805 | G21: =SUMIFS(INDEX(Detail[],0,MATCH(G$14,Detail[#Headers],0)),Detail[AEA],$A21) -> 50524016 | H21: =SUMIFS(INDEX(Detail[],0,MATCH(H$14,Detail[#Headers],0)),Detail[AEA],$A21) -> 9077623 | I21: =SUMIFS(INDEX(Detail[],0,MATCH(I$14,Detail[#Headers],0)),Detail[AEA],$A21) -> 9969861 | J21: =SUMIFS(INDEX(Detail[],0,MATCH(J$14,Detail[#Headers],0)),Detail[AEA],$A21) -> 0
A22: =A9 -> 12 | B22: =B9 -> Northwest AEA | C22: =INDEX(Detail[],MATCH($A22,Detail[AEA],0),MATCH(C$14,Detail[#Headers],0)) -> 33.31 | D22: =INDEX(Detail[],MATCH($A22,Detail[AEA],0),MATCH(D$14,Detail[#Headers],0)) -> 3.97 | E22: =SUMIFS(INDEX(Detail[],0,MATCH(E$14,Detail[#Headers],0)),Detail[AEA],$A22) -> 15155113 | F22: =SUMIFS(INDEX(Detail[],0,MATCH(F$14,Detail[#Headers],0)),Detail[AEA],$A22) -> 59137 | G22: =SUMIFS(INDEX(Detail[],0,MATCH(G$14,Detail[#Headers],0)),Detail[AEA],$A22) -> 15214250 | H22: =SUMIFS(INDEX(Detail[],0,MATCH(H$14,Detail[#Headers],0)),Detail[AEA],$A22) -> 2742807 | I22: =SUMIFS(INDEX(Detail[],0,MATCH(I$14,Detail[#Headers],0)),Detail[AEA],$A22) -> 3072541 | J22: =SUMIFS(INDEX(Detail[],0,MATCH(J$14,Detail[#Headers],0)),Detail[AEA],$A22) -> 30001
A23: =A10 -> 13 | B23: =B10 -> Green Hills AEA 13 | C23: =INDEX(Detail[],MATCH($A23,Detail[AEA],0),MATCH(C$14,Detail[#Headers],0)) -> 33.29 | D23: =INDEX(Detail[],MATCH($A23,Detail[AEA],0),MATCH(D$14,Detail[#Headers],0)) -> 3.58 | E23: =SUMIFS(INDEX(Detail[],0,MATCH(E$14,Detail[#Headers],0)),Detail[AEA],$A23) -> 13777070 | F23: =SUMIFS(INDEX(Detail[],0,MATCH(F$14,Detail[#Headers],0)),Detail[AEA],$A23) -> 83363 | G23: =SUMIFS(INDEX(Detail[],0,MATCH(G$14,Detail[#Headers],0)),Detail[AEA],$A23) -> 13860433 | H23: =SUMIFS(INDEX(Detail[],0,MATCH(H$14,Detail[#Headers],0)),Detail[AEA],$A23) -> 2274728 | I23: =SUMIFS(INDEX(Detail[],0,MATCH(I$14,Detail[#Headers],0)),Detail[AEA],$A23) -> 2514787 | J23: =SUMIFS(INDEX(Detail[],0,MATCH(J$14,Detail[#Headers],0)),Detail[AEA],$A23) -> 30001
A24: =A11 -> 15 | B24: =B11 -> Great Prairie AEA 15 | C24: =INDEX(Detail[],MATCH($A24,Detail[AEA],0),MATCH(C$14,Detail[#Headers],0)) -> 32.3 | D24: =INDEX(Detail[],MATCH($A24,Detail[AEA],0),MATCH(D$14,Detail[#Headers],0)) -> 3.53 | E24: =SUMIFS(INDEX(Detail[],0,MATCH(E$14,Detail[#Headers],0)),Detail[AEA],$A24) -> 12398858 | F24: =SUMIFS(INDEX(Detail[],0,MATCH(F$14,Detail[#Headers],0)),Detail[AEA],$A24) -> 86612 | G24: =SUMIFS(INDEX(Detail[],0,MATCH(G$14,Detail[#Headers],0)),Detail[AEA],$A24) -> 12485470 | H24: =SUMIFS(INDEX(Detail[],0,MATCH(H$14,Detail[#Headers],0)),Detail[AEA],$A24) -> 2113603 | I24: =SUMIFS(INDEX(Detail[],0,MATCH(I$14,Detail[#Headers],0)),Detail[AEA],$A24) -> 2322760 | J24: =SUMIFS(INDEX(Detail[],0,MATCH(J$14,Detail[#Headers],0)),Detail[AEA],$A24) -> 30001
E25: =SUM(E16:E24) -> 179248516 | F25: =SUM(F16:F24) -> 961638 | G25: =SUM(G16:G24) -> 180210154 | H25: =SUM(H16:H24) -> 31350594 | I25: =SUM(I16:I24) -> 34636751 | J25: =SUM(J16:J24) -> 210007
C27: =Detail[[#Headers],[AEA Teacher Salary Supplement District Cost]] -> AEA Teacher Salary Supplement District Cost | D27: =Detail[[#Headers],[AEA Professional Development Supplement District Cost]] -> AEA Professional Development Supplement District Cost | E27: =Detail[[#Headers],[Subtotal Budget]] -> Subtotal Budget | F27: =Detail[[#Headers],[AEA Statewide State Aid Reduction]] -> AEA Statewide State Aid Reduction | G27: =Detail[[#Headers],[Total Budget]] -> Total Budget | H27: =Detail[[#Headers],[State Aid Portion]] -> State Aid Portion | I27: =Detail[[#Headers],[Property Tax Portion]] -> Property Tax Portion
A28: =A15 -> AEA | B28: =B15 -> AEA Name | C28: Teacher Salary Supplement | D28: Professional Development Supplement | E28: Subtotal Budget | F28: Prorata Reduction | G28: Total Budget | H28: State Aid | I28: Property Tax | L28: Professional Development Reduction Language HF 2589 | M28: https://www.legis.iowa.gov/legislation/BillBook?ga=89&ba=HF%202589&v=e
A29: =A16 -> 01 | B29: =B16 -> Keystone AEA 1 | C29: =SUMIFS(INDEX(Detail[],0,MATCH(C$27,Detail[#Headers],0)),Detail[AEA],$A29) -> 1078327 | D29: =SUMIFS(INDEX(Detail[],0,MATCH(D$27,Detail[#Headers],0)),Detail[AEA],$A29) -> 116624 | E29: =SUMIFS(INDEX(Detail[],0,MATCH(E$27,Detail[#Headers],0)),Detail[AEA],$A29) -> 16202764 | F29: =SUMIFS(INDEX(Detail[],0,MATCH(F$27,Detail[#Headers],0)),Detail[AEA],$A29) -> 1713114 | G29: =SUMIFS(INDEX(Detail[],0,MATCH(G$27,Detail[#Headers],0)),Detail[AEA],$A29) -> 14489650 | H29: =SUMIFS(INDEX(Detail[],0,MATCH(H$27,Detail[#Headers],0)),Detail[AEA],$A29) -> 7744340 | I29: =SUMIFS(INDEX(Detail[],0,MATCH(I$27,Detail[#Headers],0)),Detail[AEA],$A29) -> 6745310 | L29: b. Notwithstanding subsection 1, and in addition to the reductions applicable pursuant to subsection 2 and paragraph “a” of this subsection, the state aid for area education agencies and the portion of the combined district cost calculated for these agencies related to professional development expenditures for the fiscal year beginning July 1, 2022, and ending June 30, 2023, shall be reduced by the department of management by an amount equal to the sum of the area education agency professional development supplement district cost for all area education agencies determined under section 257.37A, subsection 2, for the budget year beginning July 1, 2022. The reduction for each area education agency shall be equal to the area education agency’s professional development district cost determined under section 257.37A, subsection 2, for the budget year beginning July 1, 2022. The amounts reduced under this paragraph shall be considered funds paid to school districts and area education agencies under chapter 284 for purposes of requirements for providing professional development opportunities.
A30: =A17 -> 05 | B30: =B17 -> Prairie Lakes AEA 8 | C30: =SUMIFS(INDEX(Detail[],0,MATCH(C$27,Detail[#Headers],0)),Detail[AEA],$A30) -> 1211494 | D30: =SUMIFS(INDEX(Detail[],0,MATCH(D$27,Detail[#Headers],0)),Detail[AEA],$A30) -> 143978 | E30: =SUMIFS(INDEX(Detail[],0,MATCH(E$27,Detail[#Headers],0)),Detail[AEA],$A30) -> 16978998 | F30: =SUMIFS(INDEX(Detail[],0,MATCH(F$27,Detail[#Headers],0)),Detail[AEA],$A30) -> 1841660 | G30: =SUMIFS(INDEX(Detail[],0,MATCH(G$27,Detail[#Headers],0)),Detail[AEA],$A30) -> 15137338 | H30: =SUMIFS(INDEX(Detail[],0,MATCH(H$27,Detail[#Headers],0)),Detail[AEA],$A30) -> 8235873 | I30: =SUMIFS(INDEX(Detail[],0,MATCH(I$27,Detail[#Headers],0)),Detail[AEA],$A30) -> 6901465
A31: =A18 -> 07 | B31: =B18 -> Central Rivers | C31: =SUMIFS(INDEX(Detail[],0,MATCH(C$27,Detail[#Headers],0)),Detail[AEA],$A31) -> 2880300 | D31: =SUMIFS(INDEX(Detail[],0,MATCH(D$27,Detail[#Headers],0)),Detail[AEA],$A31) -> 331234 | E31: =SUMIFS(INDEX(Detail[],0,MATCH(E$27,Detail[#Headers],0)),Detail[AEA],$A31) -> 34894234 | F31: =SUMIFS(INDEX(Detail[],0,MATCH(F$27,Detail[#Headers],0)),Detail[AEA],$A31) -> 3478978 | G31: =SUMIFS(INDEX(Detail[],0,MATCH(G$27,Detail[#Headers],0)),Detail[AEA],$A31) -> 31415256 | H31: =SUMIFS(INDEX(Detail[],0,MATCH(H$27,Detail[#Headers],0)),Detail[AEA],$A31) -> 17842475 | I31: =SUMIFS(INDEX(Detail[],0,MATCH(I$27,Detail[#Headers],0)),Detail[AEA],$A31) -> 13572781
A32: =A19 -> 09 | B32: =B19 -> Mississippi Bend AEA 9 | C32: =SUMIFS(INDEX(Detail[],0,MATCH(C$27,Detail[#Headers],0)),Detail[AEA],$A32) -> 1551088 | D32: =SUMIFS(INDEX(Detail[],0,MATCH(D$27,Detail[#Headers],0)),Detail[AEA],$A32) -> 181851 | E32: =SUMIFS(INDEX(Detail[],0,MATCH(E$27,Detail[#Headers],0)),Detail[AEA],$A32) -> 24989379 | F32: =SUMIFS(INDEX(Detail[],0,MATCH(F$27,Detail[#Headers],0)),Detail[AEA],$A32) -> 2473263 | G32: =SUMIFS(INDEX(Detail[],0,MATCH(G$27,Detail[#Headers],0)),Detail[AEA],$A32) -> 22516116 | H32: =SUMIFS(INDEX(Detail[],0,MATCH(H$27,Detail[#Headers],0)),Detail[AEA],$A32) -> 12610507 | I32: =SUMIFS(INDEX(Detail[],0,MATCH(I$27,Detail[#Headers],0)),Detail[AEA],$A32) -> 9905609
A33: =A20 -> 10 | B33: =B20 -> Grant Wood AEA 10 | C33: =SUMIFS(INDEX(Detail[],0,MATCH(C$27,Detail[#Headers],0)),Detail[AEA],$A33) -> 2373182 | D33: =SUMIFS(INDEX(Detail[],0,MATCH(D$27,Detail[#Headers],0)),Detail[AEA],$A33) -> 276066 | E33: =SUMIFS(INDEX(Detail[],0,MATCH(E$27,Detail[#Headers],0)),Detail[AEA],$A33) -> 37223393 | F33: =SUMIFS(INDEX(Detail[],0,MATCH(F$27,Detail[#Headers],0)),Detail[AEA],$A33) -> 3182392 | G33: =SUMIFS(INDEX(Detail[],0,MATCH(G$27,Detail[#Headers],0)),Detail[AEA],$A33) -> 34041001 | H33: =SUMIFS(INDEX(Detail[],0,MATCH(H$27,Detail[#Headers],0)),Detail[AEA],$A33) -> 19379037 | I33: =SUMIFS(INDEX(Detail[],0,MATCH(I$27,Detail[#Headers],0)),Detail[AEA],$A33) -> 14661964
A34: =A21 -> 11 | B34: =B21 -> Heartland AEA 11 | C34: =SUMIFS(INDEX(Detail[],0,MATCH(C$27,Detail[#Headers],0)),Detail[AEA],$A34) -> 4270230 | D34: =SUMIFS(INDEX(Detail[],0,MATCH(D$27,Detail[#Headers],0)),Detail[AEA],$A34) -> 536419 | E34: =SUMIFS(INDEX(Detail[],0,MATCH(E$27,Detail[#Headers],0)),Detail[AEA],$A34) -> 74378149 | F34: =SUMIFS(INDEX(Detail[],0,MATCH(F$27,Detail[#Headers],0)),Detail[AEA],$A34) -> 5681091 | G34: =SUMIFS(INDEX(Detail[],0,MATCH(G$27,Detail[#Headers],0)),Detail[AEA],$A34) -> 68697058 | H34: =SUMIFS(INDEX(Detail[],0,MATCH(H$27,Detail[#Headers],0)),Detail[AEA],$A34) -> 39980789 | I34: =SUMIFS(INDEX(Detail[],0,MATCH(I$27,Detail[#Headers],0)),Detail[AEA],$A34) -> 28716269
A35: =A22 -> 12 | B35: =B22 -> Northwest AEA | C35: =SUMIFS(INDEX(Detail[],0,MATCH(C$27,Detail[#Headers],0)),Detail[AEA],$A35) -> 1529140 | D35: =SUMIFS(INDEX(Detail[],0,MATCH(D$27,Detail[#Headers],0)),Detail[AEA],$A35) -> 182276 | E35: =SUMIFS(INDEX(Detail[],0,MATCH(E$27,Detail[#Headers],0)),Detail[AEA],$A35) -> 22771015 | F35: =SUMIFS(INDEX(Detail[],0,MATCH(F$27,Detail[#Headers],0)),Detail[AEA],$A35) -> 2111383 | G35: =SUMIFS(INDEX(Detail[],0,MATCH(G$27,Detail[#Headers],0)),Detail[AEA],$A35) -> 20659632 | H35: =SUMIFS(INDEX(Detail[],0,MATCH(H$27,Detail[#Headers],0)),Detail[AEA],$A35) -> 11351511 | I35: =SUMIFS(INDEX(Detail[],0,MATCH(I$27,Detail[#Headers],0)),Detail[AEA],$A35) -> 9308121
A36: =A23 -> 13 | B36: =B23 -> Green Hills AEA 13 | C36: =SUMIFS(INDEX(Detail[],0,MATCH(C$27,Detail[#Headers],0)),Detail[AEA],$A36) -> 1417195 | D36: =SUMIFS(INDEX(Detail[],0,MATCH(D$27,Detail[#Headers],0)),Detail[AEA],$A36) -> 152387 | E36: =SUMIFS(INDEX(Detail[],0,MATCH(E$27,Detail[#Headers],0)),Detail[AEA],$A36) -> 20249531 | F36: =SUMIFS(INDEX(Detail[],0,MATCH(F$27,Detail[#Headers],0)),Detail[AEA],$A36) -> 2111676 | G36: =SUMIFS(INDEX(Detail[],0,MATCH(G$27,Detail[#Headers],0)),Detail[AEA],$A36) -> 18137855 | H36: =SUMIFS(INDEX(Detail[],0,MATCH(H$27,Detail[#Headers],0)),Detail[AEA],$A36) -> 10359793 | I36: =SUMIFS(INDEX(Detail[],0,MATCH(I$27,Detail[#Headers],0)),Detail[AEA],$A36) -> 7778062
A37: =A24 -> 15 | B37: =B24 -> Great Prairie AEA 15 | C37: =SUMIFS(INDEX(Detail[],0,MATCH(C$27,Detail[#Headers],0)),Detail[AEA],$A37) -> 1247183 | D37: =SUMIFS(INDEX(Detail[],0,MATCH(D$27,Detail[#Headers],0)),Detail[AEA],$A37) -> 136296 | E37: =SUMIFS(INDEX(Detail[],0,MATCH(E$27,Detail[#Headers],0)),Detail[AEA],$A37) -> 18335313 | F37: =SUMIFS(INDEX(Detail[],0,MATCH(F$27,Detail[#Headers],0)),Detail[AEA],$A37) -> 1963574 | G37: =SUMIFS(INDEX(Detail[],0,MATCH(G$27,Detail[#Headers],0)),Detail[AEA],$A37) -> 16371739 | H37: =SUMIFS(INDEX(Detail[],0,MATCH(H$27,Detail[#Headers],0)),Detail[AEA],$A37) -> 9314137 | I37: =SUMIFS(INDEX(Detail[],0,MATCH(I$27,Detail[#Headers],0)),Detail[AEA],$A37) -> 7057602
C38: =SUM(C29:C37) -> 17558139 | D38: =SUM(D29:D37) -> 2057131 | E38: =SUM(E29:E37) -> 266022776 | F38: =SUM(F29:F37) -> 24557131 | G38: =SUM(G29:G37) -> 241465645 | H38: =SUM(H29:H37) -> 136818462 | I38: =SUM(I29:I37) -> 104647183

Sheet Detail
A1: FY 2023 AEA Weights and Costs Detail
A2: AEA | B2: AEA Name | C2: Dist | D2: District | E2: Total Special Ed Weighting in Addition to 1.0 | F2: Budget Enrollment | G2: AEA Weighted Enrollment | H2: AEA Supplementary Weight for Sharing | I2: Resident Accredited Nonpublic Students | J2: Shared-Time Nonpublic Pupils Counted in Line 1.1 | K2: Total Enrollment Served - AEA Media and Ed Services | L2: AEA Special Ed Support Cost Per Pupil | M2: AEA Media Cost Per Pupil | N2: AEA Ed Services Cost Per Pupil | O2: AEA Teacher Salary Supplement District Cost Per Pupil | P2: Professional Development Supplement District Cost Per Pupil | Q2: AEA Special Ed Support District Cost without Adjustment | R2: AEA Special Ed Support Adjustment | S2: Special Education Total Cost | T2: AEA Media Services District Cost | U2: AEA Ed Services District Cost | V2: AEA Sharing District Cost | W2: AEA Teacher Salary Supplement District Cost | X2: AEA Professional Development Supplement District Cost | Y2: Subtotal Budget | Z2: AEA Statewide State Aid Reduction | AA2: Total Budget | AB2: State Aid Portion | AC2: Property Tax Portion
A3: 01 | B3: Keystone AEA 1 | C3: 0135 | D3: Allamakee | E3: 145.88 | F3: 1048.7 | G3: 1194.58 | H3: 3.29 | I3: 164 | J3: 1.2 | K3: 1212 | L3: 338.42 | M3: 60.63 | N3: 67.56 | O3: 33.47 | P3: 3.62 | Q3: 404270 | R3: 0 | S3: 404270 | T3: 73484 | U3: 81883 | V3: 1113 | W3: 39983 | X3: 4324 | Y3: 605057 | Z3: 77856 | AA3: 527201 | AB3: 273106 | AC3: 254095
A4: 01 | B4: Keystone AEA 1 | C4: 1080 | D4: Central Clayton | E4: 53.44 | F4: 437.3 | G4: 490.74 | H4: 1.35 | I4: 1 | J4: 0 | K4: 438 | L4: 338.42 | M4: 60.63 | N4: 67.56 | O4: 33.47 | P4: 3.62 | Q4: 166076 | R4: 2920 | S4: 168996 | T4: 26556 | U4: 29591 | V4: 457 | W4: 16425 | X4: 1776 | Y4: 243801 | Z4: 31764 | AA4: 212037 | AB4: 112412 | AC4: 99625
A5: 01 | B5: Keystone AEA 1 | C5: 2763 | D5: Clayton Ridge | E5: 71.34 | F5: 601.8 | G5: 673.14 | H5: 1.85 | I5: 64 | J5: 3 | K5: 663 | L5: 338.42 | M5: 60.63 | N5: 67.56 | O5: 33.47 | P5: 3.62 | Q5: 227804 | R5: 0 | S5: 227804 | T5: 40198 | U5: 44792 | V5: 626 | W5: 22530 | X5: 2437 | Y5: 338387 | Z5: 41812 | AA5: 296575 | AB5: 155952 | AC5: 140623
A6: 01 | B6: Keystone AEA 1 | C6: 1638 | D6: Decorah | E6: 188.78 | F6: 1530.5 | G6: 1719.28 | H6: 4.73 | I6: 135 | J6: 0 | K6: 1666 | L6: 338.42 | M6: 60.63 | N6: 67.56 | O6: 33.47 | P6: 3.62 | Q6: 581839 | R6: 0 | S6: 581839 | T6: 101010 | U6: 112555 | V6: 1601 | W6: 57544 | X6: 6224 | Y6: 860773 | Z6: 99232 | AA6: 761541 | AB6: 405883 | AC6: 355658
A7: 01 | B7: Keystone AEA 1 | C7: 1863 | D7: Dubuque | E7: 1960.66 | F7: 10120.3 | G7: 12080.96 | H7: 33.27 | I7: 1662 | J7: 1.7 | K7: 11781 | L7: 338.42 | M7: 60.63 | N7: 67.56 | O7: 33.47 | P7: 3.62 | Q7: 4088438 | R7: 0 | S7: 4088438 | T7: 714282 | U7: 795924 | V7: 11259 | W7: 404350 | X7: 43733 | Y7: 6057986 | Z7: 557910 | AA7: 5500076 | AB7: 2991416 | AC7: 2508660
A8: 01 | B8: Keystone AEA 1 | C8: 1972 | D8: Eastern Allamakee | E8: 45.86 | F8: 330.3 | G8: 376.16 | H8: 1.04 | I8: 6 | J8: 0 | K8: 336 | L8: 338.42 | M8: 60.63 | N8: 67.56 | O8: 33.47 | P8: 3.62 | Q8: 127300 | R8: 927 | S8: 128227 | T8: 20372 | U8: 22700 | V8: 352 | W8: 12590 | X8: 1362 | Y8: 185603 | Z8: 25111 | AA8: 160492 | AB8: 85404 | AC8: 75088
A9: 01 | B9: Keystone AEA 1 | C9: 1989 | D9: Edgewood-Colesburg | E9: 31.35 | F9: 399 | G9: 430.35 | H9: 1.18 | I9: 30 | J9: 0 | K9: 429 | L9: 338.42 | M9: 60.63 | N9: 67.56 | O9: 33.47 | P9: 3.62 | Q9: 145639 | R9: 704 | S9: 146343 | T9: 26010 | U9: 28983 | V9: 399 | W9: 14426 | X9: 1559 | Y9: 217720 | Z9: 28666 | AA9: 189054 | AB9: 97791 | AC9: 91263
A10: 01 | B10: Keystone AEA 1 | C10: 3029 | D10: Howard-Winneshiek | E10: 169.95 | F10: 1155 | G10: 1324.95 | H10: 3.65 | I10: 165 | J10: 0.8 | K10: 1319 | L10: 338.42 | M10: 60.63 | N10: 67.56 | O10: 33.47 | P10: 3.62 | Q10: 448390 | R10: 0 | S10: 448390 | T10: 79971 | U10: 89112 | V10: 1235 | W10: 44346 | X10: 4796 | Y10: 667850 | Z10: 79761 | AA10: 588089 | AB10: 309503 | AC10: 278586
A11: 01 | B11: Keystone AEA 1 | C11: 4419 | D11: MFL Mar Mac | E11: 89.19 | F11: 802.8 | G11: 891.99 | H11: 2.46 | I11: 2 | J11: 0 | K11: 805 | L11: 338.42 | M11: 60.63 | N11: 67.56 | O11: 33.47 | P11: 3.62 | Q11: 301867 | R11: 0 | S11: 301867 | T11: 48807 | U11: 54386 | V11: 833 | W11: 29855 | X11: 3229 | Y11: 438977 | Z11: 52250 | AA11: 386727 | AB11: 209813 | AC11: 176914
A12: 01 | B12: Keystone AEA 1 | C12: 4043 | D12: Maquoketa Valley | E12: 63.18 | F12: 677.6 | G12: 740.78 | H12: 2.04 | I12: 31 | J12: 0 | K12: 709 | L12: 338.42 | M12: 60.63 | N12: 67.56 | O12: 33.47 | P12: 3.62 | Q12: 250695 | R12: 0 | S12: 250695 | T12: 42987 | U12: 47900 | V12: 690 | W12: 24794 | X12: 2682 | Y12: 369748 | Z12: 47897 | AA12: 321851 | AB12: 169741 | AC12: 152110
A13: 01 | B13: Keystone AEA 1 | C13: 4662 | D13: New Hampton | E13: 101.38 | F13: 922.2 | G13: 1023.58 | H13: 2.82 | I13: 91 | J13: 0.9 | K13: 1012 | L13: 338.42 | M13: 60.63 | N13: 67.56 | O13: 33.47 | P13: 3.62 | Q13: 346400 | R13: 0 | S13: 346400 | T13: 61358 | U13: 68371 | V13: 954 | W13: 34259 | X13: 3705 | Y13: 515047 | Z13: 61727 | AA13: 453320 | AB13: 238995 | AC13: 214325
A14: 01 | B14: Keystone AEA 1 | C14: 4774 | D14: North Fayette Valley | E14: 190.48 | F14: 1113.2 | G14: 1303.68 | H14: 3.59 | I14: 3 | J14: 0 | K14: 1116 | L14: 338.42 | M14: 60.63 | N14: 67.56 | O14: 33.47 | P14: 3.62 | Q14: 441191 | R14: 0 | S14: 441191 | T14: 67663 | U14: 75397 | V14: 1215 | W14: 43634 | X14: 4719 | Y14: 633819 | Z14: 85617 | AA14: 548202 | AB14: 297397 | AC14: 250805
... A329: 15 | B329: Great Prairie AEA 15 | C329: 7047 | D329: Winfield-Mt Union | E329: 26.1 | F329: 315.1 | G329: 341.2 | H329: 0.82 | I329: 0 | J329: 0 | K329: 315 | L329: 321.58 | M329: 60.33 | N329: 66.3 | O329: 32.3 | P329: 3.53 | Q329: 109723 | R329: 6005 | S329: 115728 | T329: 19004 | U329: 20885 | V329: 264 | W329: 11021 | X329: 1204 | Y329: 168106 | Z329: 19465 | AA329: 148641 | AB329: 80317 | AC329: 68324

Sheet Detail By AEA
B1: =CONCATENATE(INDEX(Detail[],MATCH(A5,Detail[Dist],0),2)," Detail by School District") -> Central Rivers Detail by School District
A4: Dist | B4: District | C4: Total Special Ed Weighting | D4: Budget Enrollment | E4: AEA Weighted Enrollment | F4: AEA Supplementary Weight for Sharing | G4: Resident Accredited Nonpublic Students | H4: Shared-Time Nonpublic Pupils | I4: Total Enrollment Served - AEA Media and Ed Services | J4: AEA Special Ed Support District Cost without Adjustment | K4: AEA Special Ed Support Adjustment | L4: Special Education Total Cost | M4: AEA Media Services District Cost | N4: AEA Ed Services District Cost | O4: AEA Sharing District Cost | P4: AEA Teacher Salary Supplement District Cost | Q4: AEA Professional Development Supplement District Cost | R4: Subtotal Budget | S4: AEA State Aid Reduction | T4: Total Budget | U4: State Aid Portion | V4: Property Tax Portion
A5: 0009 | B5: AGWSR | C5: 104.66 | D5: 680.1 | E5: 784.76 | F5: 1.02 | G5: 22 | H5: 0.1 | I5: 702 | J5: 257040 | K5: 0 | L5: 257040 | M5: 42583 | N5: 47490 | O5: 334 | P5: 31940 | Q5: 3673 | R5: 383060 | S5: 44962 | T5: 338098 | U5: 191811 | V5: 146287
A6: 0108 | B6: Alden | C6: 24.37 | D6: 280.8 | E6: 305.17 | F6: 0.4 | G6: 0 | H6: 0 | I6: 281 | J6: 99955 | K6: 0 | L6: 99955 | M6: 17045 | N6: 19010 | O6: 131 | P6: 12420 | Q6: 1428 | R6: 149989 | S6: 16385 | T6: 133604 | U6: 75689 | V6: 57915
A7: 0153 | B7: North Butler | C7: 70.14 | D7: 568.6 | E7: 638.74 | F7: 0.83 | G7: 2 | H7: 0 | I7: 571 | J7: 209213 | K7: 0 | L7: 209213 | M7: 34637 | N7: 38628 | O7: 272 | P7: 25997 | Q7: 2989 | R7: 311736 | S7: 35758 | T7: 275978 | U7: 156958 | V7: 119020
A8: 0279 | B8: Aplington-Parkersburg | C8: 120.04 | D8: 814.8 | E8: 934.84 | F8: 1.21 | G8: 18 | H8: 0 | I8: 833 | J8: 306197 | K8: 0 | L8: 306197 | M8: 50530 | N8: 56352 | O8: 396 | P8: 38048 | Q8: 4375 | R8: 455898 | S8: 43475 | T8: 412423 | U8: 238577 | V8: 173846
A9: 0540 | B9: BCLUW | C9: 72.46 | D9: 486.9 | E9: 559.36 | F9: 0.73 | G9: 6 | H9: 0 | I9: 493 | J9: 183213 | K9: 3299 | L9: 186512 | M9: 29905 | N9: 33351 | O9: 239 | P9: 22766 | Q9: 2618 | R9: 275391 | S9: 32401 | T9: 242990 | U9: 136366 | V9: 106624
A10: 0594 | B10: Belmond-Klemme | C10: 93.41 | D10: 756 | E10: 849.41 | F10: 1.1 | G10: 0 | H10: 0 | I10: 756 | J10: 278216 | K10: 0 | L10: 278216 | M10: 45859 | N10: 51143 | O10: 360 | P10: 34571 | Q10: 3977 | R10: 414126 | S10: 43483 | T10: 370643 | U10: 212796 | V10: 157847
A11: 0819 | B11: West Hancock | C11: 41 | D11: 563.6 | E11: 604.6 | F11: 0.78 | G11: 8 | H11: 0 | I11: 572 | J11: 198031 | K11: 0 | L11: 198031 | M11: 34698 | N11: 38696 | O11: 255 | P11: 24607 | Q11: 2830 | R11: 299117 | S11: 34886 | T11: 264231 | U11: 147528 | V11: 116703
A12: 0846 | B12: Brooklyn-Guernsey-Malcom | C12: 66.56 | D12: 531.8 | E12: 598.36 | F12: 0.78 | G12: 1 | H12: 0 | I12: 533 | J12: 195987 | K12: 0 | L12: 195987 | M12: 32332 | N12: 36057 | O12: 255 | P12: 24353 | Q12: 2800 | R12: 291784 | S12: 32169 | T12: 259615 | U12: 148364 | V12: 111251
A13: 0873 | B13: North Iowa | C13: 49.73 | D13: 443.8 | E13: 493.53 | F13: 0.64 | G13: 2 | H13: 0 | I13: 446 | J13: 161651 | K13: 0 | L13: 161651 | M13: 27054 | N13: 30172 | O13: 210 | P13: 20087 | Q13: 2310 | R13: 241484 | S13: 31881 | T13: 209603 | U13: 117024 | V13: 92579
A14: 0916 | B14: CAL | C14: 30.9 | D14: 269.6 | E14: 300.5 | F14: 0.39 | G14: 15 | H14: 0.3 | I14: 284 | J14: 98426 | K14: 0 | L14: 98426 | M14: 17227 | N14: 19213 | O14: 128 | P14: 12230 | Q14: 1406 | R14: 148630 | S14: 15546 | T14: 133084 | U14: 75118 | V14: 57966
A15: 1044 | B15: Cedar Falls | C15: 813.81 | D15: 5565.8 | E15: 6379.61 | F15: 8.27 | G15: 286 | H15: 2.5 | I15: 5849 | J15: 2089577 | K15: 0 | L15: 2089577 | M15: 354800 | N15: 395685 | O15: 2709 | P15: 259650 | Q15: 29857 | R15: 3132278 | S15: 228020 | T15: 2904258 | U15: 1696784 | V15: 1207474
A16: 1116 | B16: Charles City | C16: 283.74 | D16: 1554.5 | E16: 1838.24 | F16: 2.38 | G16: 154 | H16: 5.8 | I16: 1703 | J16: 602097 | K16: 0 | L16: 602097 | M16: 103304 | N16: 115208 | O16: 780 | P16: 74816 | Q16: 8603 | R16: 904808 | S16: 91585 | T16: 813223 | U16: 463033 | V16: 350190
... A57: 6985 | B57: West Marshall | C57: 81.6 | D57: 813.6 | E57: 895.2 | F57: 1.16 | G57: 3 | H57: 0 | I57: 817 | J57: 293214 | K57: 1549 | L57: 294763 | M57: 49559 | N57: 55270 | O57: 380 | P57: 36435 | Q57: 4190 | R57: 440597 | S57: 43122 | T57: 397475 | U57: 226971 | V57: 170504
A58: AEA Total | C58: 9290.28 | D58: 61360 | E58: 70650.28 | F58: 91.59 | G58: 3233 | H58: 35.5 | I58: 64559 | J58: 23140792 | K58: 228348 | L58: 23369140 | M58: 3916147 | N58: 4367412 | O58: 30001 | P58: 2880300 | Q58: 331234 | R58: 34894234 | S58: 3478978 | T58: 31415256 | U58: 17842475 | V58: 13572781
