Workbook
Name IDX: Final!$A$1

Sheet CashReserveLevy
G1: =_xlfn.CONCAT("SBRC FY ",A3," Final Cash Reserve Levy Limitations Source: FY ",A3-2," Certified Annual Report") -> SBRC FY 2026 Final Cash Reserve Levy Limitations Source: FY 2024 Certified Annual Report
A2: FiscalYear | B2: AEA | C2: Dist | D2: DistSub1 | E2: DistSub2 | F2: DistrictNumber | G2: Label | H2: Expenditures | I2: 20% of Expenditures | J2: Assigned and Unassigned Fund Balance | K2: Final Maximum Cash Reserve Levy | L2: Final Cash Reserve Levy | M2: Levying Maximum Cash Reserve
A3: 2026 | B3: 11 | C3: 0018 | F3: 0018 | G3: Adair-Casey | H3: =ROUND(SUMPRODUCT(SUMIF(Final!$G$4:$G$330,CashReserveLevy!D3:F3,Final!$C$4:$C$330)),0) -> 4907234 | I3: =ROUND(H3*0.2,0) -> 981447 | J3: =ROUND(SUMPRODUCT(SUMIF(Final!$G$4:$G$330,CashReserveLevy!D3:F3,Final!$E$4:$E$330)),0) -> 1437726 | K3: =IF(I3>J3,I3-J3,0) -> 0 | L3: =INDEX(ActualCRLevy_SAS!$A$2:$D$326,MATCH(CashReserveLevy!$C3,ActualCRLevy_SAS!$B$2:$B$326,0),4) -> 0 | M3: =IF(AND(L3=K3,K3>0),"Max","") | N3: =IF(AND(L3<K3,L3=0),"No Levy but have Capacity","") | O3: =IF(L3>K3,"Exceedes Maximum Limit","")
A4: 2026 | B4: 11 | C4: 0027 | F4: 0027 | G4: Adel-Desoto-Minburn | H4: =ROUND(SUMPRODUCT(SUMIF(Final!$G$4:$G$330,CashReserveLevy!D4:F4,Final!$C$4:$C$330)),0) -> 27144003 | I4: =ROUND(H4*0.2,0) -> 5428801 | J4: =ROUND(SUMPRODUCT(SUMIF(Final!$G$4:$G$330,CashReserveLevy!D4:F4,Final!$E$4:$E$330)),0) -> 4129415 | K4: =IF(I4>J4,I4-J4,0) -> 1299386 | L4: =INDEX(ActualCRLevy_SAS!$A$2:$D$326,MATCH(CashReserveLevy!$C4,ActualCRLevy_SAS!$B$2:$B$326,0),4) -> 1299386 | M4: =IF(AND(L4=K4,K4>0),"Max","") -> Max | N4: =IF(AND(L4<K4,L4=0),"No Levy but have Capacity","") | O4: =IF(L4>K4,"Exceedes Maximum Limit","")
A5: 2026 | B5: 07 | C5: 0009 | F5: 0009 | G5: AGWSR | H5: =ROUND(SUMPRODUCT(SUMIF(Final!$G$4:$G$330,CashReserveLevy!D5:F5,Final!$C$4:$C$330)),0) -> 10259078 | I5: =ROUND(H5*0.2,0) -> 2051816 | J5: =ROUND(SUMPRODUCT(SUMIF(Final!$G$4:$G$330,CashReserveLevy!D5:F5,Final!$E$4:$E$330)),0) -> -155502 | K5: =IF(I5>J5,I5-J5,0) -> 2207318 | L5: =INDEX(ActualCRLevy_SAS!$A$2:$D$326,MATCH(CashReserveLevy!$C5,ActualCRLevy_SAS!$B$2:$B$326,0),4) -> 1000000 | M5: =IF(AND(L5=K5,K5>0),"Max","") | N5: =IF(AND(L5<K5,L5=0),"No Levy but have Capacity","") | O5: =IF(L5>K5,"Exceedes Maximum Limit","")
A6: 2026 | B6: 13 | C6: 0441 | F6: 0441 | G6: AHSTW | H6: =ROUND(SUMPRODUCT(SUMIF(Final!$G$4:$G$330,CashReserveLevy!D6:F6,Final!$C$4:$C$330)),0) -> 10779050 | I6: =ROUND(H6*0.2,0) -> 2155810 | J6: =ROUND(SUMPRODUCT(SUMIF(Final!$G$4:$G$330,CashReserveLevy!D6:F6,Final!$E$4:$E$330)),0) -> 2037901 | K6: =IF(I6>J6,I6-J6,0) -> 117909 | L6: =INDEX(ActualCRLevy_SAS!$A$2:$D$326,MATCH(CashReserveLevy!$C6,ActualCRLevy_SAS!$B$2:$B$326,0),4) -> 117909 | M6: =IF(AND(L6=K6,K6>0),"Max","") -> Max | N6: =IF(AND(L6<K6,L6=0),"No Levy but have Capacity","") | O6: =IF(L6>K6,"Exceedes Maximum Limit","")
A7: 2026 | B7: 12 | C7: 0063 | F7: 0063 | G7: Akron-Westfield | H7: =ROUND(SUMPRODUCT(SUMIF(Final!$G$4:$G$330,CashReserveLevy!D7:F7,Final!$C$4:$C$330)),0) -> 8463070 | I7: =ROUND(H7*0.2,0) -> 1692614 | J7: =ROUND(SUMPRODUCT(SUMIF(Final!$G$4:$G$330,CashReserveLevy!D7:F7,Final!$E$4:$E$330)),0) -> 861251 | K7: =IF(I7>J7,I7-J7,0) -> 831363 | L7: =INDEX(ActualCRLevy_SAS!$A$2:$D$326,MATCH(CashReserveLevy!$C7,ActualCRLevy_SAS!$B$2:$B$326,0),4) -> 831363 | M7: =IF(AND(L7=K7,K7>0),"Max","") -> Max | N7: =IF(AND(L7<K7,L7=0),"No Levy but have Capacity","") | O7: =IF(L7>K7,"Exceedes Maximum Limit","")
A8: 2026 | B8: 05 | C8: 0072 | F8: 0072 | G8: Albert City-Truesdale | H8: =ROUND(SUMPRODUCT(SUMIF(Final!$G$4:$G$330,CashReserveLevy!D8:F8,Final!$C$4:$C$330)),0) -> 2967467 | I8: =ROUND(H8*0.2,0) -> 593493 | J8: =ROUND(SUMPRODUCT(SUMIF(Final!$G$4:$G$330,CashReserveLevy!D8:F8,Final!$E$4:$E$330)),0) -> 1552674 | K8: =IF(I8>J8,I8-J8,0) -> 0 | L8: =INDEX(ActualCRLevy_SAS!$A$2:$D$326,MATCH(CashReserveLevy!$C8,ActualCRLevy_SAS!$B$2:$B$326,0),4) -> 0 | M8: =IF(AND(L8=K8,K8>0),"Max","") | N8: =IF(AND(L8<K8,L8=0),"No Levy but have Capacity","") | O8: =IF(L8>K8,"Exceedes Maximum Limit","")
A9: 2026 | B9: 15 | C9: 0081 | F9: 0081 | G9: Albia | H9: =ROUND(SUMPRODUCT(SUMIF(Final!$G$4:$G$330,CashReserveLevy!D9:F9,Final!$C$4:$C$330)),0) -> 14649277 | I9: =ROUND(H9*0.2,0) -> 2929855 | J9: =ROUND(SUMPRODUCT(SUMIF(Final!$G$4:$G$330,CashReserveLevy!D9:F9,Final!$E$4:$E$330)),0) -> 4141165 | K9: =IF(I9>J9,I9-J9,0) -> 0 | L9: =INDEX(ActualCRLevy_SAS!$A$2:$D$326,MATCH(CashReserveLevy!$C9,ActualCRLevy_SAS!$B$2:$B$326,0),4) -> 0 | M9: =IF(AND(L9=K9,K9>0),"Max","") | N9: =IF(AND(L9<K9,L9=0),"No Levy but have Capacity","") | O9: =IF(L9>K9,"Exceedes Maximum Limit","")
A10: 2026 | B10: 10 | C10: 0099 | F10: 0099 | G10: Alburnett | H10: =ROUND(SUMPRODUCT(SUMIF(Final!$G$4:$G$330,CashReserveLevy!D10:F10,Final!$C$4:$C$330)),0) -> 9574247 | I10: =ROUND(H10*0.2,0) -> 1914849 | J10: =ROUND(SUMPRODUCT(SUMIF(Final!$G$4:$G$330,CashReserveLevy!D10:F10,Final!$E$4:$E$330)),0) -> 1279357 | K10: =IF(I10>J10,I10-J10,0) -> 635492 | L10: =INDEX(ActualCRLevy_SAS!$A$2:$D$326,MATCH(CashReserveLevy!$C10,ActualCRLevy_SAS!$B$2:$B$326,0),4) -> 300000 | M10: =IF(AND(L10=K10,K10>0),"Max","") | N10: =IF(AND(L10<K10,L10=0),"No Levy but have Capacity","") | O10: =IF(L10>K10,"Exceedes Maximum Limit","")
A11: 2026 | B11: 07 | C11: 0108 | F11: 0108 | G11: Alden | H11: =ROUND(SUMPRODUCT(SUMIF(Final!$G$4:$G$330,CashReserveLevy!D11:F11,Final!$C$4:$C$330)),0) -> 3882411 | I11: =ROUND(H11*0.2,0) -> 776482 | J11: =ROUND(SUMPRODUCT(SUMIF(Final!$G$4:$G$330,CashReserveLevy!D11:F11,Final!$E$4:$E$330)),0) -> 380516 | K11: =IF(I11>J11,I11-J11,0) -> 395966 | L11: =INDEX(ActualCRLevy_SAS!$A$2:$D$326,MATCH(CashReserveLevy!$C11,ActualCRLevy_SAS!$B$2:$B$326,0),4) -> 375000 | M11: =IF(AND(L11=K11,K11>0),"Max","") | N11: =IF(AND(L11<K11,L11=0),"No Levy but have Capacity","") | O11: =IF(L11>K11,"Exceedes Maximum Limit","")
A12: 2026 | B12: 05 | C12: 0126 | D12: 6417 | E12: 3897 | F12: 0126 | G12: Algona | H12: =ROUND(SUMPRODUCT(SUMIF(Final!$G$4:$G$330,CashReserveLevy!D12:F12,Final!$C$4:$C$330)),0) -> 22265557 | I12: =ROUND(H12*0.2,0) -> 4453111 | J12: =ROUND(SUMPRODUCT(SUMIF(Final!$G$4:$G$330,CashReserveLevy!D12:F12,Final!$E$4:$E$330)),0) -> 3638895 | K12: =IF(I12>J12,I12-J12,0) -> 814216 | L12: =INDEX(ActualCRLevy_SAS!$A$2:$D$326,MATCH(CashReserveLevy!$C12,ActualCRLevy_SAS!$B$2:$B$326,0),4) -> 814216 | M12: =IF(AND(L12=K12,K12>0),"Max","") -> Max | N12: =IF(AND(L12<K12,L12=0),"No Levy but have Capacity","") | O12: =IF(L12>K12,"Exceedes Maximum Limit","")
A13: 2026 | B13: 01 | C13: 0135 | F13: 0135 | G13: Allamakee | H13: =ROUND(SUMPRODUCT(SUMIF(Final!$G$4:$G$330,CashReserveLevy!D13:F13,Final!$C$4:$C$330)),0) -> 15125260 | I13: =ROUND(H13*0.2,0) -> 3025052 | J13: =ROUND(SUMPRODUCT(SUMIF(Final!$G$4:$G$330,CashReserveLevy!D13:F13,Final!$E$4:$E$330)),0) -> 1748725 | K13: =IF(I13>J13,I13-J13,0) -> 1276327 | L13: =INDEX(ActualCRLevy_SAS!$A$2:$D$326,MATCH(CashReserveLevy!$C13,ActualCRLevy_SAS!$B$2:$B$326,0),4) -> 400000 | M13: =IF(AND(L13=K13,K13>0),"Max","") | N13: =IF(AND(L13<K13,L13=0),"No Levy but have Capacity","") | O13: =IF(L13>K13,"Exceedes Maximum Limit","")
A14: 2026 | B14: 05 | C14: 0171 | F14: 0171 | G14: Alta-Aurelia | H14: =ROUND(SUMPRODUCT(SUMIF(Final!$G$4:$G$330,CashReserveLevy!D14:F14,Final!$C$4:$C$330)),0) -> 11750216 | I14: =ROUND(H14*0.2,0) -> 2350043 | J14: =ROUND(SUMPRODUCT(SUMIF(Final!$G$4:$G$330,CashReserveLevy!D14:F14,Final!$E$4:$E$330)),0) -> 1427391 | K14: =IF(I14>J14,I14-J14,0) -> 922652 | L14: =INDEX(ActualCRLevy_SAS!$A$2:$D$326,MATCH(CashReserveLevy!$C14,ActualCRLevy_SAS!$B$2:$B$326,0),4) -> 600000 | M14: =IF(AND(L14=K14,K14>0),"Max","") | N14: =IF(AND(L14<K14,L14=0),"No Levy but have Capacity","") | O14: =IF(L14>K14,"Exceedes Maximum Limit","")
A15: 2026 | B15: 11 | C15: 0225 | F15: 0225 | G15: Ames | H15: =ROUND(SUMPRODUCT(SUMIF(Final!$G$4:$G$330,CashReserveLevy!D15:F15,Final!$C$4:$C$330)),0) -> 65267651 | I15: =ROUND(H15*0.2,0) -> 13053530 | J15: =ROUND(SUMPRODUCT(SUMIF(Final!$G$4:$G$330,CashReserveLevy!D15:F15,Final!$E$4:$E$330)),0) -> 14130396 | K15: =IF(I15>J15,I15-J15,0) -> 0 | L15: =INDEX(ActualCRLevy_SAS!$A$2:$D$326,MATCH(CashReserveLevy!$C15,ActualCRLevy_SAS!$B$2:$B$326,0),4) -> 0 | M15: =IF(AND(L15=K15,K15>0),"Max","") | N15: =IF(AND(L15<K15,L15=0),"No Levy but have Capacity","") | O15: =IF(L15>K15,"Exceedes Maximum Limit","")
A16: 2026 | B16: 10 | C16: 0234 | F16: 0234 | G16: Anamosa | H16: =ROUND(SUMPRODUCT(SUMIF(Final!$G$4:$G$330,CashReserveLevy!D16:F16,Final!$C$4:$C$330)),0) -> 15431908 | I16: =ROUND(H16*0.2,0) -> 3086382 | J16: =ROUND(SUMPRODUCT(SUMIF(Final!$G$4:$G$330,CashReserveLevy!D16:F16,Final!$E$4:$E$330)),0) -> 5859509 | K16: =IF(I16>J16,I16-J16,0) -> 0 | L16: =INDEX(ActualCRLevy_SAS!$A$2:$D$326,MATCH(CashReserveLevy!$C16,ActualCRLevy_SAS!$B$2:$B$326,0),4) -> 0 | M16: =IF(AND(L16=K16,K16>0),"Max","") | N16: =IF(AND(L16<K16,L16=0),"No Levy but have Capacity","") | O16: =IF(L16>K16,"Exceedes Maximum Limit","")
A17: 2026 | B17: 09 | C17: 0243 | F17: 0243 | G17: Andrew | H17: =ROUND(SUMPRODUCT(SUMIF(Final!$G$4:$G$330,CashReserveLevy!D17:F17,Final!$C$4:$C$330)),0) -> 4658729 | I17: =ROUND(H17*0.2,0) -> 931746 | J17: =ROUND(SUMPRODUCT(SUMIF(Final!$G$4:$G$330,CashReserveLevy!D17:F17,Final!$E$4:$E$330)),0) -> 448207 | K17: =IF(I17>J17,I17-J17,0) -> 483539 | L17: =INDEX(ActualCRLevy_SAS!$A$2:$D$326,MATCH(CashReserveLevy!$C17,ActualCRLevy_SAS!$B$2:$B$326,0),4) -> 234020 | M17: =IF(AND(L17=K17,K17>0),"Max","") | N17: =IF(AND(L17<K17,L17=0),"No Levy but have Capacity","") | O17: =IF(L17>K17,"Exceedes Maximum Limit","")
A18: 2026 | B18: 11 | C18: 0261 | F18: 0261 | G18: Ankeny | H18: =ROUND(SUMPRODUCT(SUMIF(Final!$G$4:$G$330,CashReserveLevy!D18:F18,Final!$C$4:$C$330)),0) -> 164007723 | I18: =ROUND(H18*0.2,0) -> 32801545 | J18: =ROUND(SUMPRODUCT(SUMIF(Final!$G$4:$G$330,CashReserveLevy!D18:F18,Final!$E$4:$E$330)),0) -> 16833353 | K18: =IF(I18>J18,I18-J18,0) -> 15968192 | L18: =INDEX(ActualCRLevy_SAS!$A$2:$D$326,MATCH(CashReserveLevy!$C18,ActualCRLevy_SAS!$B$2:$B$326,0),4) -> 10750000 | M18: =IF(AND(L18=K18,K18>0),"Max","") | N18: =IF(AND(L18<K18,L18=0),"No Levy but have Capacity","") | O18: =IF(L18>K18,"Exceedes Maximum Limit","")
A19: 2026 | B19: 07 | C19: 0279 | F19: 0279 | G19: Aplington-Parkersburg | H19: =ROUND(SUMPRODUCT(SUMIF(Final!$G$4:$G$330,CashReserveLevy!D19:F19,Final!$C$4:$C$330)),0) -> 10493388 | I19: =ROUND(H19*0.2,0) -> 2098678 | J19: =ROUND(SUMPRODUCT(SUMIF(Final!$G$4:$G$330,CashReserveLevy!D19:F19,Final!$E$4:$E$330)),0) -> 3343883 | K19: =IF(I19>J19,I19-J19,0) -> 0 | L19: =INDEX(ActualCRLevy_SAS!$A$2:$D$326,MATCH(CashReserveLevy!$C19,ActualCRLevy_SAS!$B$2:$B$326,0),4) -> 0 | M19: =IF(AND(L19=K19,K19>0),"Max","") | N19: =IF(AND(L19<K19,L19=0),"No Levy but have Capacity","") | O19: =IF(L19>K19,"Exceedes Maximum Limit","")
A20: 2026 | B20: 12 | C20: 0355 | F20: 0355 | G20: Ar-We-Va | H20: =ROUND(SUMPRODUCT(SUMIF(Final!$G$4:$G$330,CashReserveLevy!D20:F20,Final!$C$4:$C$330)),0) -> 3771806 | I20: =ROUND(H20*0.2,0) -> 754361 | J20: =ROUND(SUMPRODUCT(SUMIF(Final!$G$4:$G$330,CashReserveLevy!D20:F20,Final!$E$4:$E$330)),0) -> 2760760 | K20: =IF(I20>J20,I20-J20,0) -> 0 | L20: =INDEX(ActualCRLevy_SAS!$A$2:$D$326,MATCH(CashReserveLevy!$C20,ActualCRLevy_SAS!$B$2:$B$326,0),4) -> 0 | M20: =IF(AND(L20=K20,K20>0),"Max","") | N20: =IF(AND(L20<K20,L20=0),"No Levy but have Capacity","") | O20: =IF(L20>K20,"Exceedes Maximum Limit","")
A21: 2026 | B21: 13 | C21: 0387 | F21: 0387 | G21: Atlantic | H21: =ROUND(SUMPRODUCT(SUMIF(Final!$G$4:$G$330,CashReserveLevy!D21:F21,Final!$C$4:$C$330)),0) -> 19748116 | I21: =ROUND(H21*0.2,0) -> 3949623 | J21: =ROUND(SUMPRODUCT(SUMIF(Final!$G$4:$G$330,CashReserveLevy!D21:F21,Final!$E$4:$E$330)),0) -> 5401605 | K21: =IF(I21>J21,I21-J21,0) -> 0 | L21: =INDEX(ActualCRLevy_SAS!$A$2:$D$326,MATCH(CashReserveLevy!$C21,ActualCRLevy_SAS!$B$2:$B$326,0),4) -> 0 | M21: =IF(AND(L21=K21,K21>0),"Max","") | N21: =IF(AND(L21<K21,L21=0),"No Levy but have Capacity","") | O21: =IF(L21>K21,"Exceedes Maximum Limit","")
A22: 2026 | B22: 11 | C22: 0414 | F22: 0414 | G22: Audubon | H22: =ROUND(SUMPRODUCT(SUMIF(Final!$G$4:$G$330,CashReserveLevy!D22:F22,Final!$C$4:$C$330)),0) -> 7771309 | I22: =ROUND(H22*0.2,0) -> 1554262 | J22: =ROUND(SUMPRODUCT(SUMIF(Final!$G$4:$G$330,CashReserveLevy!D22:F22,Final!$E$4:$E$330)),0) -> 2082294 | K22: =IF(I22>J22,I22-J22,0) -> 0 | L22: =INDEX(ActualCRLevy_SAS!$A$2:$D$326,MATCH(CashReserveLevy!$C22,ActualCRLevy_SAS!$B$2:$B$326,0),4) -> 0 | M22: =IF(AND(L22=K22,K22>0),"Max","") | N22: =IF(AND(L22<K22,L22=0),"No Levy but have Capacity","") | O22: =IF(L22>K22,"Exceedes Maximum Limit","")
A23: 2026 | B23: 11 | C23: 0472 | F23: 0472 | G23: Ballard | H23: =ROUND(SUMPRODUCT(SUMIF(Final!$G$4:$G$330,CashReserveLevy!D23:F23,Final!$C$4:$C$330)),0) -> 24250017 | I23: =ROUND(H23*0.2,0) -> 4850003 | J23: =ROUND(SUMPRODUCT(SUMIF(Final!$G$4:$G$330,CashReserveLevy!D23:F23,Final!$E$4:$E$330)),0) -> 1968321 | K23: =IF(I23>J23,I23-J23,0) -> 2881682 | L23: =INDEX(ActualCRLevy_SAS!$A$2:$D$326,MATCH(CashReserveLevy!$C23,ActualCRLevy_SAS!$B$2:$B$326,0),4) -> 2115000 | M23: =IF(AND(L23=K23,K23>0),"Max","") | N23: =IF(AND(L23<K23,L23=0),"No Levy but have Capacity","") | O23: =IF(L23>K23,"Exceedes Maximum Limit","")
A24: 2026 | B24: 11 | C24: 0513 | F24: 0513 | G24: Baxter | H24: =ROUND(SUMPRODUCT(SUMIF(Final!$G$4:$G$330,CashReserveLevy!D24:F24,Final!$C$4:$C$330)),0) -> 5835339 | I24: =ROUND(H24*0.2,0) -> 1167068 | J24: =ROUND(SUMPRODUCT(SUMIF(Final!$G$4:$G$330,CashReserveLevy!D24:F24,Final!$E$4:$E$330)),0) -> 657131 | K24: =IF(I24>J24,I24-J24,0) -> 509937 | L24: =INDEX(ActualCRLevy_SAS!$A$2:$D$326,MATCH(CashReserveLevy!$C24,ActualCRLevy_SAS!$B$2:$B$326,0),4) -> 365268 | M24: =IF(AND(L24=K24,K24>0),"Max","") | N24: =IF(AND(L24<K24,L24=0),"No Levy but have Capacity","") | O24: =IF(L24>K24,"Exceedes Maximum Limit","")
... A61: 2026 | B61: 13 | C61: 1197 | F61: 1197 | G61: Clarinda | H61: =ROUND(SUMPRODUCT(SUMIF(Final!$G$4:$G$330,CashReserveLevy!D61:F61,Final!$C$4:$C$330)),0) -> 14365730 | I61: =ROUND(H61*0.2,0) -> 2873146 | J61: =ROUND(SUMPRODUCT(SUMIF(Final!$G$4:$G$330,CashReserveLevy!D61:F61,Final!$E$4:$E$330)),0) -> 2129371 | K61: =IF(I61>J61,I61-J61,0) -> 743775 | L61: =INDEX(ActualCRLevy_SAS!$A$2:$D$326,MATCH(CashReserveLevy!$C61,ActualCRLevy_SAS!$B$2:$B$326,0),4) -> 743775 | M61: =IF(AND(L61=K61,K61>0),"Max","") -> Max | N61: =IF(AND(L61<K61,L61=0),"No Levy but have Capacity","") | O61: =IF(L61>K61,"Exceedes Maximum Limit","")
A62: 2026 | B62: 05 | C62: 1206 | D62: 1854 | F62: 1206 | G62: Clarion-Goldfield-Dows | H62: =ROUND(SUMPRODUCT(SUMIF(Final!$G$4:$G$330,CashReserveLevy!D62:F62,Final!$C$4:$C$330)),0) -> 14594100 | I62: =ROUND(H62*0.2,0) -> 2918820 | J62: =ROUND(SUMPRODUCT(SUMIF(Final!$G$4:$G$330,CashReserveLevy!D62:F62,Final!$E$4:$E$330)),0) -> 2298018 | K62: =IF(I62>J62,I62-J62,0) -> 620802 | L62: =INDEX(ActualCRLevy_SAS!$A$2:$D$326,MATCH(CashReserveLevy!$C62,ActualCRLevy_SAS!$B$2:$B$326,0),4) -> 620802 | M62: =IF(AND(L62=K62,K62>0),"Max","") -> Max | N62: =IF(AND(L62<K62,L62=0),"No Levy but have Capacity","") | O62: =IF(L62>K62,"Exceedes Maximum Limit","")
A63: 2026 | B63: 13 | C63: 1211 | F63: 1211 | G63: Clarke | H63: =ROUND(SUMPRODUCT(SUMIF(Final!$G$4:$G$330,CashReserveLevy!D63:F63,Final!$C$4:$C$330)),0) -> 20436675 | I63: =ROUND(H63*0.2,0) -> 4087335 | J63: =ROUND(SUMPRODUCT(SUMIF(Final!$G$4:$G$330,CashReserveLevy!D63:F63,Final!$E$4:$E$330)),0) -> 1855480 | K63: =IF(I63>J63,I63-J63,0) -> 2231855 | L63: =INDEX(ActualCRLevy_SAS!$A$2:$D$326,MATCH(CashReserveLevy!$C63,ActualCRLevy_SAS!$B$2:$B$326,0),4) -> 866423 | M63: =IF(AND(L63=K63,K63>0),"Max","") | N63: =IF(AND(L63<K63,L63=0),"No Levy but have Capacity","") | O63: =IF(L63>K63,"Exceedes Maximum Limit","")
A64: 2026 | B64: 07 | C64: 1215 | F64: 1215 | G64: Clarksville | H64: =ROUND(SUMPRODUCT(SUMIF(Final!$G$4:$G$330,CashReserveLevy!D64:F64,Final!$C$4:$C$330)),0) -> 4415093 | I64: =ROUND(H64*0.2,0) -> 883019 | J64: =ROUND(SUMPRODUCT(SUMIF(Final!$G$4:$G$330,CashReserveLevy!D64:F64,Final!$E$4:$E$330)),0) -> 692102 | K64: =IF(I64>J64,I64-J64,0) -> 190917 | L64: =INDEX(ActualCRLevy_SAS!$A$2:$D$326,MATCH(CashReserveLevy!$C64,ActualCRLevy_SAS!$B$2:$B$326,0),4) -> 175000 | M64: =IF(AND(L64=K64,K64>0),"Max","") | N64: =IF(AND(L64<K64,L64=0),"No Levy but have Capacity","") | O64: =IF(L64>K64,"Exceedes Maximum Limit","")
A65: 2026 | B65: 05 | C65: 1218 | F65: 1218 | G65: Clay Central-Everly | H65: =ROUND(SUMPRODUCT(SUMIF(Final!$G$4:$G$330,CashReserveLevy!D65:F65,Final!$C$4:$C$330)),0) -> 4172739 | I65: =ROUND(H65*0.2,0) -> 834548 | J65: =ROUND(SUMPRODUCT(SUMIF(Final!$G$4:$G$330,CashReserveLevy!D65:F65,Final!$E$4:$E$330)),0) -> 1626034 | K65: =IF(I65>J65,I65-J65,0) -> 0 | L65: =INDEX(ActualCRLevy_SAS!$A$2:$D$326,MATCH(CashReserveLevy!$C65,ActualCRLevy_SAS!$B$2:$B$326,0),4) -> 0 | M65: =IF(AND(L65=K65,K65>0),"Max","") | N65: =IF(AND(L65<K65,L65=0),"No Levy but have Capacity","") | O65: =IF(L65>K65,"Exceedes Maximum Limit","")
A66: 2026 | B66: 01 | C66: 2763 | F66: 2763 | G66: Clayton Ridge | H66: =ROUND(SUMPRODUCT(SUMIF(Final!$G$4:$G$330,CashReserveLevy!D66:F66,Final!$C$4:$C$330)),0) -> 17268032 | I66: =ROUND(H66*0.2,0) -> 3453606 | J66: =ROUND(SUMPRODUCT(SUMIF(Final!$G$4:$G$330,CashReserveLevy!D66:F66,Final!$E$4:$E$330)),0) -> 1125473 | K66: =IF(I66>J66,I66-J66,0) -> 2328133 | L66: =INDEX(ActualCRLevy_SAS!$A$2:$D$326,MATCH(CashReserveLevy!$C66,ActualCRLevy_SAS!$B$2:$B$326,0),4) -> 200000 | M66: =IF(AND(L66=K66,K66>0),"Max","") | N66: =IF(AND(L66<K66,L66=0),"No Levy but have Capacity","") | O66: =IF(L66>K66,"Exceedes Maximum Limit","")
A67: 2026 | B67: 10 | C67: 1221 | D67: 0216 | F67: 1221 | G67: Clear Creek-Amana | H67: =ROUND(SUMPRODUCT(SUMIF(Final!$G$4:$G$330,CashReserveLevy!D67:F67,Final!$C$4:$C$330)),0) -> 41176959 | I67: =ROUND(H67*0.2,0) -> 8235392 | J67: =ROUND(SUMPRODUCT(SUMIF(Final!$G$4:$G$330,CashReserveLevy!D67:F67,Final!$E$4:$E$330)),0) -> 2881128 | K67: =IF(I67>J67,I67-J67,0) -> 5354264 | L67: =INDEX(ActualCRLevy_SAS!$A$2:$D$326,MATCH(CashReserveLevy!$C67,ActualCRLevy_SAS!$B$2:$B$326,0),4) -> 2342248 | M67: =IF(AND(L67=K67,K67>0),"Max","") | N67: =IF(AND(L67<K67,L67=0),"No Levy but have Capacity","") | O67: =IF(L67>K67,"Exceedes Maximum Limit","")
A68: 2026 | B68: 07 | C68: 1233 | F68: 1233 | G68: Clear Lake | H68: =ROUND(SUMPRODUCT(SUMIF(Final!$G$4:$G$330,CashReserveLevy!D68:F68,Final!$C$4:$C$330)),0) -> 18176111 | I68: =ROUND(H68*0.2,0) -> 3635222 | J68: =ROUND(SUMPRODUCT(SUMIF(Final!$G$4:$G$330,CashReserveLevy!D68:F68,Final!$E$4:$E$330)),0) -> 4309564 | K68: =IF(I68>J68,I68-J68,0) -> 0 | L68: =INDEX(ActualCRLevy_SAS!$A$2:$D$326,MATCH(CashReserveLevy!$C68,ActualCRLevy_SAS!$B$2:$B$326,0),4) -> 0 | M68: =IF(AND(L68=K68,K68>0),"Max","") | N68: =IF(AND(L68<K68,L68=0),"No Levy but have Capacity","") | O68: =IF(L68>K68,"Exceedes Maximum Limit","")
A69: 2026 | B69: 09 | C69: 1278 | F69: 1278 | G69: Clinton | H69: =ROUND(SUMPRODUCT(SUMIF(Final!$G$4:$G$330,CashReserveLevy!D69:F69,Final!$C$4:$C$330)),0) -> 54456517 | I69: =ROUND(H69*0.2,0) -> 10891303 | J69: =ROUND(SUMPRODUCT(SUMIF(Final!$G$4:$G$330,CashReserveLevy!D69:F69,Final!$E$4:$E$330)),0) -> 9736878 | K69: =IF(I69>J69,I69-J69,0) -> 1154425 | L69: =INDEX(ActualCRLevy_SAS!$A$2:$D$326,MATCH(CashReserveLevy!$C69,ActualCRLevy_SAS!$B$2:$B$326,0),4) -> 800000 | M69: =IF(AND(L69=K69,K69>0),"Max","") | N69: =IF(AND(L69<K69,L69=0),"No Levy but have Capacity","") | O69: =IF(L69>K69,"Exceedes Maximum Limit","")
A70: 2026 | B70: 11 | C70: 1332 | F70: 1332 | G70: Colfax-Mingo | H70: =ROUND(SUMPRODUCT(SUMIF(Final!$G$4:$G$330,CashReserveLevy!D70:F70,Final!$C$4:$C$330)),0) -> 11494477 | I70: =ROUND(H70*0.2,0) -> 2298895 | J70: =ROUND(SUMPRODUCT(SUMIF(Final!$G$4:$G$330,CashReserveLevy!D70:F70,Final!$E$4:$E$330)),0) -> 42040 | K70: =IF(I70>J70,I70-J70,0) -> 2256855 | L70: =INDEX(ActualCRLevy_SAS!$A$2:$D$326,MATCH(CashReserveLevy!$C70,ActualCRLevy_SAS!$B$2:$B$326,0),4) -> 675000 | M70: =IF(AND(L70=K70,K70>0),"Max","") | N70: =IF(AND(L70<K70,L70=0),"No Levy but have Capacity","") | O70: =IF(L70>K70,"Exceedes Maximum Limit","")
A71: 2026 | B71: 10 | C71: 1337 | F71: 1337 | G71: College Community | H71: =ROUND(SUMPRODUCT(SUMIF(Final!$G$4:$G$330,CashReserveLevy!D71:F71,Final!$C$4:$C$330)),0) -> 75466834 | I71: =ROUND(H71*0.2,0) -> 15093367 | J71: =ROUND(SUMPRODUCT(SUMIF(Final!$G$4:$G$330,CashReserveLevy!D71:F71,Final!$E$4:$E$330)),0) -> 8872175 | K71: =IF(I71>J71,I71-J71,0) -> 6221192 | L71: =INDEX(ActualCRLevy_SAS!$A$2:$D$326,MATCH(CashReserveLevy!$C71,ActualCRLevy_SAS!$B$2:$B$326,0),4) -> 6221192 | M71: =IF(AND(L71=K71,K71>0),"Max","") -> Max | N71: =IF(AND(L71<K71,L71=0),"No Levy but have Capacity","") | O71: =IF(L71>K71,"Exceedes Maximum Limit","")
A72: 2026 | B72: 11 | C72: 1350 | F72: 1350 | G72: Collins-Maxwell | H72: =ROUND(SUMPRODUCT(SUMIF(Final!$G$4:$G$330,CashReserveLevy!D72:F72,Final!$C$4:$C$330)),0) -> 6185648 | I72: =ROUND(H72*0.2,0) -> 1237130 | J72: =ROUND(SUMPRODUCT(SUMIF(Final!$G$4:$G$330,CashReserveLevy!D72:F72,Final!$E$4:$E$330)),0) -> 2144701 | K72: =IF(I72>J72,I72-J72,0) -> 0 | L72: =INDEX(ActualCRLevy_SAS!$A$2:$D$326,MATCH(CashReserveLevy!$C72,ActualCRLevy_SAS!$B$2:$B$326,0),4) -> 0 | M72: =IF(AND(L72=K72,K72>0),"Max","") | N72: =IF(AND(L72<K72,L72=0),"No Levy but have Capacity","") | O72: =IF(L72>K72,"Exceedes Maximum Limit","")
A73: 2026 | B73: 11 | C73: 1359 | F73: 1359 | G73: Colo-Nesco | H73: =ROUND(SUMPRODUCT(SUMIF(Final!$G$4:$G$330,CashReserveLevy!D73:F73,Final!$C$4:$C$330)),0) -> 7041403 | I73: =ROUND(H73*0.2,0) -> 1408281 | J73: =ROUND(SUMPRODUCT(SUMIF(Final!$G$4:$G$330,CashReserveLevy!D73:F73,Final!$E$4:$E$330)),0) -> 540114 | K73: =IF(I73>J73,I73-J73,0) -> 868167 | L73: =INDEX(ActualCRLevy_SAS!$A$2:$D$326,MATCH(CashReserveLevy!$C73,ActualCRLevy_SAS!$B$2:$B$326,0),4) -> 500000 | M73: =IF(AND(L73=K73,K73>0),"Max","") | N73: =IF(AND(L73<K73,L73=0),"No Levy but have Capacity","") | O73: =IF(L73>K73,"Exceedes Maximum Limit","")
A74: 2026 | B74: 09 | C74: 1368 | F74: 1368 | G74: Columbus | H74: =ROUND(SUMPRODUCT(SUMIF(Final!$G$4:$G$330,CashReserveLevy!D74:F74,Final!$C$4:$C$330)),0) -> 11130300 | I74: =ROUND(H74*0.2,0) -> 2226060 | J74: =ROUND(SUMPRODUCT(SUMIF(Final!$G$4:$G$330,CashReserveLevy!D74:F74,Final!$E$4:$E$330)),0) -> 4565508 | K74: =IF(I74>J74,I74-J74,0) -> 0 | L74: =INDEX(ActualCRLevy_SAS!$A$2:$D$326,MATCH(CashReserveLevy!$C74,ActualCRLevy_SAS!$B$2:$B$326,0),4) -> 0 | M74: =IF(AND(L74=K74,K74>0),"Max","") | N74: =IF(AND(L74<K74,L74=0),"No Levy but have Capacity","") | O74: =IF(L74>K74,"Exceedes Maximum Limit","")
A75: 2026 | B75: 11 | C75: 1413 | F75: 1413 | G75: Coon Rapids-Bayard | H75: =ROUND(SUMPRODUCT(SUMIF(Final!$G$4:$G$330,CashReserveLevy!D75:F75,Final!$C$4:$C$330)),0) -> 5592018 | I75: =ROUND(H75*0.2,0) -> 1118404 | J75: =ROUND(SUMPRODUCT(SUMIF(Final!$G$4:$G$330,CashReserveLevy!D75:F75,Final!$E$4:$E$330)),0) -> 2861913 | K75: =IF(I75>J75,I75-J75,0) -> 0 | L75: =INDEX(ActualCRLevy_SAS!$A$2:$D$326,MATCH(CashReserveLevy!$C75,ActualCRLevy_SAS!$B$2:$B$326,0),4) -> 0 | M75: =IF(AND(L75=K75,K75>0),"Max","") | N75: =IF(AND(L75<K75,L75=0),"No Levy but have Capacity","") | O75: =IF(L75>K75,"Exceedes Maximum Limit","")
A76: 2026 | B76: 13 | C76: 1431 | F76: 1431 | G76: Corning | H76: =ROUND(SUMPRODUCT(SUMIF(Final!$G$4:$G$330,CashReserveLevy!D76:F76,Final!$C$4:$C$330)),0) -> 6664449 | I76: =ROUND(H76*0.2,0) -> 1332890 | J76: =ROUND(SUMPRODUCT(SUMIF(Final!$G$4:$G$330,CashReserveLevy!D76:F76,Final!$E$4:$E$330)),0) -> 1902130 | K76: =IF(I76>J76,I76-J76,0) -> 0 | L76: =INDEX(ActualCRLevy_SAS!$A$2:$D$326,MATCH(CashReserveLevy!$C76,ActualCRLevy_SAS!$B$2:$B$326,0),4) -> 0 | M76: =IF(AND(L76=K76,K76>0),"Max","") | N76: =IF(AND(L76<K76,L76=0),"No Levy but have Capacity","") | O76: =IF(L76>K76,"Exceedes Maximum Limit","")
A77: 2026 | B77: 13 | C77: 1476 | F77: 1476 | G77: Council Bluffs | H77: =ROUND(SUMPRODUCT(SUMIF(Final!$G$4:$G$330,CashReserveLevy!D77:F77,Final!$C$4:$C$330)),0) -> 137919452 | I77: =ROUND(H77*0.2,0) -> 27583890 | J77: =ROUND(SUMPRODUCT(SUMIF(Final!$G$4:$G$330,CashReserveLevy!D77:F77,Final!$E$4:$E$330)),0) -> 6462286 | K77: =IF(I77>J77,I77-J77,0) -> 21121604 | L77: =INDEX(ActualCRLevy_SAS!$A$2:$D$326,MATCH(CashReserveLevy!$C77,ActualCRLevy_SAS!$B$2:$B$326,0),4) -> 6100000 | M77: =IF(AND(L77=K77,K77>0),"Max","") | N77: =IF(AND(L77<K77,L77=0),"No Levy but have Capacity","") | O77: =IF(L77>K77,"Exceedes Maximum Limit","")
A78: 2026 | B78: 13 | C78: 1503 | F78: 1503 | G78: Creston | H78: =ROUND(SUMPRODUCT(SUMIF(Final!$G$4:$G$330,CashReserveLevy!D78:F78,Final!$C$4:$C$330)),0) -> 18528702 | I78: =ROUND(H78*0.2,0) -> 3705740 | J78: =ROUND(SUMPRODUCT(SUMIF(Final!$G$4:$G$330,CashReserveLevy!D78:F78,Final!$E$4:$E$330)),0) -> 5857453 | K78: =IF(I78>J78,I78-J78,0) -> 0 | L78: =INDEX(ActualCRLevy_SAS!$A$2:$D$326,MATCH(CashReserveLevy!$C78,ActualCRLevy_SAS!$B$2:$B$326,0),4) -> 0 | M78: =IF(AND(L78=K78,K78>0),"Max","") | N78: =IF(AND(L78<K78,L78=0),"No Levy but have Capacity","") | O78: =IF(L78>K78,"Exceedes Maximum Limit","")
A79: 2026 | B79: 11 | C79: 1576 | F79: 1576 | G79: Dallas Center-Grimes | H79: =ROUND(SUMPRODUCT(SUMIF(Final!$G$4:$G$330,CashReserveLevy!D79:F79,Final!$C$4:$C$330)),0) -> 46173866 | I79: =ROUND(H79*0.2,0) -> 9234773 | J79: =ROUND(SUMPRODUCT(SUMIF(Final!$G$4:$G$330,CashReserveLevy!D79:F79,Final!$E$4:$E$330)),0) -> 8939303 | K79: =IF(I79>J79,I79-J79,0) -> 295470 | L79: =INDEX(ActualCRLevy_SAS!$A$2:$D$326,MATCH(CashReserveLevy!$C79,ActualCRLevy_SAS!$B$2:$B$326,0),4) -> 295470 | M79: =IF(AND(L79=K79,K79>0),"Max","") -> Max | N79: =IF(AND(L79<K79,L79=0),"No Levy but have Capacity","") | O79: =IF(L79>K79,"Exceedes Maximum Limit","")
... A267: 2026 | B267: 11 | C267: 6094 | F267: 6094 | G267: Southeast Warren | H267: =ROUND(SUMPRODUCT(SUMIF(Final!$G$4:$G$330,CashReserveLevy!D267:F267,Final!$C$4:$C$330)),0) -> 7813217 | I267: =ROUND(H267*0.2,0) -> 1562643 | J267: =ROUND(SUMPRODUCT(SUMIF(Final!$G$4:$G$330,CashReserveLevy!D267:F267,Final!$E$4:$E$330)),0) -> 372022 | K267: =IF(I267>J267,I267-J267,0) -> 1190621 | L267: =INDEX(ActualCRLevy_SAS!$A$2:$D$326,MATCH(CashReserveLevy!$C267,ActualCRLevy_SAS!$B$2:$B$326,0),4) -> 601577 | M267: =IF(AND(L267=K267,K267>0),"Max","") | N267: =IF(AND(L267<K267,L267=0),"No Levy but have Capacity","") | O267: =IF(L267>K267,"Exceedes Maximum Limit","")
A268: 2026 | B268: 05 | C268: 6096 | D268: 5323 | F268: 6096 | G268: Southeast Valley | H268: =ROUND(SUMPRODUCT(SUMIF(Final!$G$4:$G$330,CashReserveLevy!D268:F268,Final!$C$4:$C$330)),0) -> 17187654 | I268: =ROUND(H268*0.2,0) -> 3437531 | J268: =ROUND(SUMPRODUCT(SUMIF(Final!$G$4:$G$330,CashReserveLevy!D268:F268,Final!$E$4:$E$330)),0) -> 6486257 | K268: =IF(I268>J268,I268-J268,0) -> 0 | L268: =INDEX(ActualCRLevy_SAS!$A$2:$D$326,MATCH(CashReserveLevy!$C268,ActualCRLevy_SAS!$B$2:$B$326,0),4) -> 0 | M268: =IF(AND(L268=K268,K268>0),"Max","") | N268: =IF(AND(L268<K268,L268=0),"No Levy but have Capacity","") | O268: =IF(L268>K268,"Exceedes Maximum Limit","")
A269: 2026 | B269: 05 | C269: 6102 | F269: 6102 | G269: Spencer | H269: =ROUND(SUMPRODUCT(SUMIF(Final!$G$4:$G$330,CashReserveLevy!D269:F269,Final!$C$4:$C$330)),0) -> 29604483 | I269: =ROUND(H269*0.2,0) -> 5920897 | J269: =ROUND(SUMPRODUCT(SUMIF(Final!$G$4:$G$330,CashReserveLevy!D269:F269,Final!$E$4:$E$330)),0) -> 5166817 | K269: =IF(I269>J269,I269-J269,0) -> 754080 | L269: =INDEX(ActualCRLevy_SAS!$A$2:$D$326,MATCH(CashReserveLevy!$C269,ActualCRLevy_SAS!$B$2:$B$326,0),4) -> 754080 | M269: =IF(AND(L269=K269,K269>0),"Max","") -> Max | N269: =IF(AND(L269<K269,L269=0),"No Levy but have Capacity","") | O269: =IF(L269>K269,"Exceedes Maximum Limit","")
A270: 2026 | B270: 05 | C270: 6120 | F270: 6120 | G270: Spirit Lake | H270: =ROUND(SUMPRODUCT(SUMIF(Final!$G$4:$G$330,CashReserveLevy!D270:F270,Final!$C$4:$C$330)),0) -> 16043864 | I270: =ROUND(H270*0.2,0) -> 3208773 | J270: =ROUND(SUMPRODUCT(SUMIF(Final!$G$4:$G$330,CashReserveLevy!D270:F270,Final!$E$4:$E$330)),0) -> 3326718 | K270: =IF(I270>J270,I270-J270,0) -> 0 | L270: =INDEX(ActualCRLevy_SAS!$A$2:$D$326,MATCH(CashReserveLevy!$C270,ActualCRLevy_SAS!$B$2:$B$326,0),4) -> 0 | M270: =IF(AND(L270=K270,K270>0),"Max","") | N270: =IF(AND(L270<K270,L270=0),"No Levy but have Capacity","") | O270: =IF(L270>K270,"Exceedes Maximum Limit","")
A271: 2026 | B271: 10 | C271: 6138 | F271: 6138 | G271: Springville | H271: =ROUND(SUMPRODUCT(SUMIF(Final!$G$4:$G$330,CashReserveLevy!D271:F271,Final!$C$4:$C$330)),0) -> 6191673 | I271: =ROUND(H271*0.2,0) -> 1238335 | J271: =ROUND(SUMPRODUCT(SUMIF(Final!$G$4:$G$330,CashReserveLevy!D271:F271,Final!$E$4:$E$330)),0) -> 1133789 | K271: =IF(I271>J271,I271-J271,0) -> 104546 | L271: =INDEX(ActualCRLevy_SAS!$A$2:$D$326,MATCH(CashReserveLevy!$C271,ActualCRLevy_SAS!$B$2:$B$326,0),4) -> 104546 | M271: =IF(AND(L271=K271,K271>0),"Max","") -> Max | N271: =IF(AND(L271<K271,L271=0),"No Levy but have Capacity","") | O271: =IF(L271>K271,"Exceedes Maximum Limit","")
A272: 2026 | B272: 07 | C272: 5751 | F272: 5751 | G272: St Ansgar | H272: =ROUND(SUMPRODUCT(SUMIF(Final!$G$4:$G$330,CashReserveLevy!D272:F272,Final!$C$4:$C$330)),0) -> 8149127 | I272: =ROUND(H272*0.2,0) -> 1629825 | J272: =ROUND(SUMPRODUCT(SUMIF(Final!$G$4:$G$330,CashReserveLevy!D272:F272,Final!$E$4:$E$330)),0) -> 1155841 | K272: =IF(I272>J272,I272-J272,0) -> 473984 | L272: =INDEX(ActualCRLevy_SAS!$A$2:$D$326,MATCH(CashReserveLevy!$C272,ActualCRLevy_SAS!$B$2:$B$326,0),4) -> 0 | M272: =IF(AND(L272=K272,K272>0),"Max","") | N272: =IF(AND(L272<K272,L272=0),"No Levy but have Capacity","") -> No Levy but have Capacity | O272: =IF(L272>K272,"Exceedes Maximum Limit","")
A273: 2026 | B273: 13 | C273: 6165 | F273: 6165 | G273: Stanton | H273: =ROUND(SUMPRODUCT(SUMIF(Final!$G$4:$G$330,CashReserveLevy!D273:F273,Final!$C$4:$C$330)),0) -> 3738054 | I273: =ROUND(H273*0.2,0) -> 747611 | J273: =ROUND(SUMPRODUCT(SUMIF(Final!$G$4:$G$330,CashReserveLevy!D273:F273,Final!$E$4:$E$330)),0) -> 1446943 | K273: =IF(I273>J273,I273-J273,0) -> 0 | L273: =INDEX(ActualCRLevy_SAS!$A$2:$D$326,MATCH(CashReserveLevy!$C273,ActualCRLevy_SAS!$B$2:$B$326,0),4) -> 0 | M273: =IF(AND(L273=K273,K273>0),"Max","") | N273: =IF(AND(L273<K273,L273=0),"No Levy but have Capacity","") | O273: =IF(L273>K273,"Exceedes Maximum Limit","")
A274: 2026 | B274: 01 | C274: 6175 | F274: 6175 | G274: Starmont | H274: =ROUND(SUMPRODUCT(SUMIF(Final!$G$4:$G$330,CashReserveLevy!D274:F274,Final!$C$4:$C$330)),0) -> 8879419 | I274: =ROUND(H274*0.2,0) -> 1775884 | J274: =ROUND(SUMPRODUCT(SUMIF(Final!$G$4:$G$330,CashReserveLevy!D274:F274,Final!$E$4:$E$330)),0) -> 3584348 | K274: =IF(I274>J274,I274-J274,0) -> 0 | L274: =INDEX(ActualCRLevy_SAS!$A$2:$D$326,MATCH(CashReserveLevy!$C274,ActualCRLevy_SAS!$B$2:$B$326,0),4) -> 0 | M274: =IF(AND(L274=K274,K274>0),"Max","") | N274: =IF(AND(L274<K274,L274=0),"No Levy but have Capacity","") | O274: =IF(L274>K274,"Exceedes Maximum Limit","")
A275: 2026 | B275: 05 | C275: 6219 | F275: 6219 | G275: Storm Lake | H275: =ROUND(SUMPRODUCT(SUMIF(Final!$G$4:$G$330,CashReserveLevy!D275:F275,Final!$C$4:$C$330)),0) -> 42442955 | I275: =ROUND(H275*0.2,0) -> 8488591 | J275: =ROUND(SUMPRODUCT(SUMIF(Final!$G$4:$G$330,CashReserveLevy!D275:F275,Final!$E$4:$E$330)),0) -> 2136399 | K275: =IF(I275>J275,I275-J275,0) -> 6352192 | L275: =INDEX(ActualCRLevy_SAS!$A$2:$D$326,MATCH(CashReserveLevy!$C275,ActualCRLevy_SAS!$B$2:$B$326,0),4) -> 1150959 | M275: =IF(AND(L275=K275,K275>0),"Max","") | N275: =IF(AND(L275<K275,L275=0),"No Levy but have Capacity","") | O275: =IF(L275>K275,"Exceedes Maximum Limit","")
A276: 2026 | B276: 05 | C276: 6246 | F276: 6246 | G276: Stratford | H276: =ROUND(SUMPRODUCT(SUMIF(Final!$G$4:$G$330,CashReserveLevy!D276:F276,Final!$C$4:$C$330)),0) -> 2487883 | I276: =ROUND(H276*0.2,0) -> 497577 | J276: =ROUND(SUMPRODUCT(SUMIF(Final!$G$4:$G$330,CashReserveLevy!D276:F276,Final!$E$4:$E$330)),0) -> 126394 | K276: =IF(I276>J276,I276-J276,0) -> 371183 | L276: =INDEX(ActualCRLevy_SAS!$A$2:$D$326,MATCH(CashReserveLevy!$C276,ActualCRLevy_SAS!$B$2:$B$326,0),4) -> 176000 | M276: =IF(AND(L276=K276,K276>0),"Max","") | N276: =IF(AND(L276<K276,L276=0),"No Levy but have Capacity","") | O276: =IF(L276>K276,"Exceedes Maximum Limit","")
A277: 2026 | B277: 07 | C277: 6273 | F277: 6273 | G277: Sumner-Fredericksburg | H277: =ROUND(SUMPRODUCT(SUMIF(Final!$G$4:$G$330,CashReserveLevy!D277:F277,Final!$C$4:$C$330)),0) -> 10954106 | I277: =ROUND(H277*0.2,0) -> 2190821 | J277: =ROUND(SUMPRODUCT(SUMIF(Final!$G$4:$G$330,CashReserveLevy!D277:F277,Final!$E$4:$E$330)),0) -> 1440949 | K277: =IF(I277>J277,I277-J277,0) -> 749872 | L277: =INDEX(ActualCRLevy_SAS!$A$2:$D$326,MATCH(CashReserveLevy!$C277,ActualCRLevy_SAS!$B$2:$B$326,0),4) -> 202000 | M277: =IF(AND(L277=K277,K277>0),"Max","") | N277: =IF(AND(L277<K277,L277=0),"No Levy but have Capacity","") | O277: =IF(L277>K277,"Exceedes Maximum Limit","")
A278: 2026 | B278: 10 | C278: 6408 | F278: 6408 | G278: Tipton | H278: =ROUND(SUMPRODUCT(SUMIF(Final!$G$4:$G$330,CashReserveLevy!D278:F278,Final!$C$4:$C$330)),0) -> 11768305 | I278: =ROUND(H278*0.2,0) -> 2353661 | J278: =ROUND(SUMPRODUCT(SUMIF(Final!$G$4:$G$330,CashReserveLevy!D278:F278,Final!$E$4:$E$330)),0) -> 2012894 | K278: =IF(I278>J278,I278-J278,0) -> 340767 | L278: =INDEX(ActualCRLevy_SAS!$A$2:$D$326,MATCH(CashReserveLevy!$C278,ActualCRLevy_SAS!$B$2:$B$326,0),4) -> 340767 | M278: =IF(AND(L278=K278,K278>0),"Max","") -> Max | N278: =IF(AND(L278<K278,L278=0),"No Levy but have Capacity","") | O278: =IF(L278>K278,"Exceedes Maximum Limit","")
A279: 2026 | B279: 13 | C279: 6453 | F279: 6453 | G279: Treynor | H279: =ROUND(SUMPRODUCT(SUMIF(Final!$G$4:$G$330,CashReserveLevy!D279:F279,Final!$C$4:$C$330)),0) -> 9144390 | I279: =ROUND(H279*0.2,0) -> 1828878 | J279: =ROUND(SUMPRODUCT(SUMIF(Final!$G$4:$G$330,CashReserveLevy!D279:F279,Final!$E$4:$E$330)),0) -> 2257154 | K279: =IF(I279>J279,I279-J279,0) -> 0 | L279: =INDEX(ActualCRLevy_SAS!$A$2:$D$326,MATCH(CashReserveLevy!$C279,ActualCRLevy_SAS!$B$2:$B$326,0),4) -> 0 | M279: =IF(AND(L279=K279,K279>0),"Max","") | N279: =IF(AND(L279<K279,L279=0),"No Levy but have Capacity","") | O279: =IF(L279>K279,"Exceedes Maximum Limit","")
A280: 2026 | B280: 13 | C280: 6460 | F280: 6460 | G280: Tri-Center | H280: =ROUND(SUMPRODUCT(SUMIF(Final!$G$4:$G$330,CashReserveLevy!D280:F280,Final!$C$4:$C$330)),0) -> 9215071 | I280: =ROUND(H280*0.2,0) -> 1843014 | J280: =ROUND(SUMPRODUCT(SUMIF(Final!$G$4:$G$330,CashReserveLevy!D280:F280,Final!$E$4:$E$330)),0) -> 3869147 | K280: =IF(I280>J280,I280-J280,0) -> 0 | L280: =INDEX(ActualCRLevy_SAS!$A$2:$D$326,MATCH(CashReserveLevy!$C280,ActualCRLevy_SAS!$B$2:$B$326,0),4) -> 0 | M280: =IF(AND(L280=K280,K280>0),"Max","") | N280: =IF(AND(L280<K280,L280=0),"No Levy but have Capacity","") | O280: =IF(L280>K280,"Exceedes Maximum Limit","")
... A301: 2026 | B301: 15 | C301: 6854 | F301: 6854 | G301: Wayne | H301: =ROUND(SUMPRODUCT(SUMIF(Final!$G$4:$G$330,CashReserveLevy!D301:F301,Final!$C$4:$C$330)),0) -> 9095062 | I301: =ROUND(H301*0.2,0) -> 1819012 | J301: =ROUND(SUMPRODUCT(SUMIF(Final!$G$4:$G$330,CashReserveLevy!D301:F301,Final!$E$4:$E$330)),0) -> 5317983 | K301: =IF(I301>J301,I301-J301,0) -> 0 | L301: =INDEX(ActualCRLevy_SAS!$A$2:$D$326,MATCH(CashReserveLevy!$C301,ActualCRLevy_SAS!$B$2:$B$326,0),4) -> 0 | M301: =IF(AND(L301=K301,K301>0),"Max","") | N301: =IF(AND(L301<K301,L301=0),"No Levy but have Capacity","") | O301: =IF(L301>K301,"Exceedes Maximum Limit","")
A302: 2026 | B302: 05 | C302: 6867 | D302: 4775 | F302: 6867 | G302: Webster City | H302: =ROUND(SUMPRODUCT(SUMIF(Final!$G$4:$G$330,CashReserveLevy!D302:F302,Final!$C$4:$C$330)),0) -> 25124880 | I302: =ROUND(H302*0.2,0) -> 5024976 | J302: =ROUND(SUMPRODUCT(SUMIF(Final!$G$4:$G$330,CashReserveLevy!D302:F302,Final!$E$4:$E$330)),0) -> 4328915 | K302: =IF(I302>J302,I302-J302,0) -> 696061 | L302: =INDEX(ActualCRLevy_SAS!$A$2:$D$326,MATCH(CashReserveLevy!$C302,ActualCRLevy_SAS!$B$2:$B$326,0),4) -> 0 | M302: =IF(AND(L302=K302,K302>0),"Max","") | N302: =IF(AND(L302<K302,L302=0),"No Levy but have Capacity","") -> No Levy but have Capacity | O302: =IF(L302>K302,"Exceedes Maximum Limit","")
A303: 2026 | B303: 05 | C303: 6921 | F303: 6921 | G303: West Bend-Mallard | H303: =ROUND(SUMPRODUCT(SUMIF(Final!$G$4:$G$330,CashReserveLevy!D303:F303,Final!$C$4:$C$330)),0) -> 4869114 | I303: =ROUND(H303*0.2,0) -> 973823 | J303: =ROUND(SUMPRODUCT(SUMIF(Final!$G$4:$G$330,CashReserveLevy!D303:F303,Final!$E$4:$E$330)),0) -> 1383540 | K303: =IF(I303>J303,I303-J303,0) -> 0 | L303: =INDEX(ActualCRLevy_SAS!$A$2:$D$326,MATCH(CashReserveLevy!$C303,ActualCRLevy_SAS!$B$2:$B$326,0),4) -> 0 | M303: =IF(AND(L303=K303,K303>0),"Max","") | N303: =IF(AND(L303<K303,L303=0),"No Levy but have Capacity","") | O303: =IF(L303>K303,"Exceedes Maximum Limit","")
A304: 2026 | B304: 10 | C304: 6930 | F304: 6930 | G304: West Branch | H304: =ROUND(SUMPRODUCT(SUMIF(Final!$G$4:$G$330,CashReserveLevy!D304:F304,Final!$C$4:$C$330)),0) -> 10967692 | I304: =ROUND(H304*0.2,0) -> 2193538 | J304: =ROUND(SUMPRODUCT(SUMIF(Final!$G$4:$G$330,CashReserveLevy!D304:F304,Final!$E$4:$E$330)),0) -> 1549676 | K304: =IF(I304>J304,I304-J304,0) -> 643862 | L304: =INDEX(ActualCRLevy_SAS!$A$2:$D$326,MATCH(CashReserveLevy!$C304,ActualCRLevy_SAS!$B$2:$B$326,0),4) -> 643862 | M304: =IF(AND(L304=K304,K304>0),"Max","") -> Max | N304: =IF(AND(L304<K304,L304=0),"No Levy but have Capacity","") | O304: =IF(L304>K304,"Exceedes Maximum Limit","")
A305: 2026 | B305: 15 | C305: 6937 | F305: 6937 | G305: West Burlington | H305: =ROUND(SUMPRODUCT(SUMIF(Final!$G$4:$G$330,CashReserveLevy!D305:F305,Final!$C$4:$C$330)),0) -> 10330805 | I305: =ROUND(H305*0.2,0) -> 2066161 | J305: =ROUND(SUMPRODUCT(SUMIF(Final!$G$4:$G$330,CashReserveLevy!D305:F305,Final!$E$4:$E$330)),0) -> 1752487 | K305: =IF(I305>J305,I305-J305,0) -> 313674 | L305: =INDEX(ActualCRLevy_SAS!$A$2:$D$326,MATCH(CashReserveLevy!$C305,ActualCRLevy_SAS!$B$2:$B$326,0),4) -> 229737 | M305: =IF(AND(L305=K305,K305>0),"Max","") | N305: =IF(AND(L305<K305,L305=0),"No Levy but have Capacity","") | O305: =IF(L305>K305,"Exceedes Maximum Limit","")
A306: 2026 | B306: 01 | C306: 6943 | F306: 6943 | G306: West Central | H306: =ROUND(SUMPRODUCT(SUMIF(Final!$G$4:$G$330,CashReserveLevy!D306:F306,Final!$C$4:$C$330)),0) -> 4778742 | I306: =ROUND(H306*0.2,0) -> 955748 | J306: =ROUND(SUMPRODUCT(SUMIF(Final!$G$4:$G$330,CashReserveLevy!D306:F306,Final!$E$4:$E$330)),0) -> 1006371 | K306: =IF(I306>J306,I306-J306,0) -> 0 | L306: =INDEX(ActualCRLevy_SAS!$A$2:$D$326,MATCH(CashReserveLevy!$C306,ActualCRLevy_SAS!$B$2:$B$326,0),4) -> 0 | M306: =IF(AND(L306=K306,K306>0),"Max","") | N306: =IF(AND(L306<K306,L306=0),"No Levy but have Capacity","") | O306: =IF(L306>K306,"Exceedes Maximum Limit","")
A307: 2026 | B307: 11 | C307: 6264 | F307: 6264 | G307: West Central Valley | H307: =ROUND(SUMPRODUCT(SUMIF(Final!$G$4:$G$330,CashReserveLevy!D307:F307,Final!$C$4:$C$330)),0) -> 13262947 | I307: =ROUND(H307*0.2,0) -> 2652589 | J307: =ROUND(SUMPRODUCT(SUMIF(Final!$G$4:$G$330,CashReserveLevy!D307:F307,Final!$E$4:$E$330)),0) -> 3070420 | K307: =IF(I307>J307,I307-J307,0) -> 0 | L307: =INDEX(ActualCRLevy_SAS!$A$2:$D$326,MATCH(CashReserveLevy!$C307,ActualCRLevy_SAS!$B$2:$B$326,0),4) -> 0 | M307: =IF(AND(L307=K307,K307>0),"Max","") | N307: =IF(AND(L307<K307,L307=0),"No Levy but have Capacity","") | O307: =IF(L307>K307,"Exceedes Maximum Limit","")
A308: 2026 | B308: 01 | C308: 6950 | F308: 6950 | G308: West Delaware Co | H308: =ROUND(SUMPRODUCT(SUMIF(Final!$G$4:$G$330,CashReserveLevy!D308:F308,Final!$C$4:$C$330)),0) -> 18208297 | I308: =ROUND(H308*0.2,0) -> 3641659 | J308: =ROUND(SUMPRODUCT(SUMIF(Final!$G$4:$G$330,CashReserveLevy!D308:F308,Final!$E$4:$E$330)),0) -> 1295487 | K308: =IF(I308>J308,I308-J308,0) -> 2346172 | L308: =INDEX(ActualCRLevy_SAS!$A$2:$D$326,MATCH(CashReserveLevy!$C308,ActualCRLevy_SAS!$B$2:$B$326,0),4) -> 1291913 | M308: =IF(AND(L308=K308,K308>0),"Max","") | N308: =IF(AND(L308<K308,L308=0),"No Levy but have Capacity","") | O308: =IF(L308>K308,"Exceedes Maximum Limit","")
A309: 2026 | B309: 11 | C309: 6957 | F309: 6957 | G309: West Des Moines | H309: =ROUND(SUMPRODUCT(SUMIF(Final!$G$4:$G$330,CashReserveLevy!D309:F309,Final!$C$4:$C$330)),0) -> 133756493 | I309: =ROUND(H309*0.2,0) -> 26751299 | J309: =ROUND(SUMPRODUCT(SUMIF(Final!$G$4:$G$330,CashReserveLevy!D309:F309,Final!$E$4:$E$330)),0) -> 19754876 | K309: =IF(I309>J309,I309-J309,0) -> 6996423 | L309: =INDEX(ActualCRLevy_SAS!$A$2:$D$326,MATCH(CashReserveLevy!$C309,ActualCRLevy_SAS!$B$2:$B$326,0),4) -> 6996423 | M309: =IF(AND(L309=K309,K309>0),"Max","") -> Max | N309: =IF(AND(L309<K309,L309=0),"No Levy but have Capacity","") | O309: =IF(L309>K309,"Exceedes Maximum Limit","")
A310: 2026 | B310: 07 | C310: 5922 | F310: 5922 | G310: West Fork | H310: =ROUND(SUMPRODUCT(SUMIF(Final!$G$4:$G$330,CashReserveLevy!D310:F310,Final!$C$4:$C$330)),0) -> 11045536 | I310: =ROUND(H310*0.2,0) -> 2209107 | J310: =ROUND(SUMPRODUCT(SUMIF(Final!$G$4:$G$330,CashReserveLevy!D310:F310,Final!$E$4:$E$330)),0) -> 1937205 | K310: =IF(I310>J310,I310-J310,0) -> 271902 | L310: =INDEX(ActualCRLevy_SAS!$A$2:$D$326,MATCH(CashReserveLevy!$C310,ActualCRLevy_SAS!$B$2:$B$326,0),4) -> 250000 | M310: =IF(AND(L310=K310,K310>0),"Max","") | N310: =IF(AND(L310<K310,L310=0),"No Levy but have Capacity","") | O310: =IF(L310>K310,"Exceedes Maximum Limit","")
A311: 2026 | B311: 07 | C311: 0819 | F311: 0819 | G311: West Hancock | H311: =ROUND(SUMPRODUCT(SUMIF(Final!$G$4:$G$330,CashReserveLevy!D311:F311,Final!$C$4:$C$330)),0) -> 7640263 | I311: =ROUND(H311*0.2,0) -> 1528053 | J311: =ROUND(SUMPRODUCT(SUMIF(Final!$G$4:$G$330,CashReserveLevy!D311:F311,Final!$E$4:$E$330)),0) -> 1906776 | K311: =IF(I311>J311,I311-J311,0) -> 0 | L311: =INDEX(ActualCRLevy_SAS!$A$2:$D$326,MATCH(CashReserveLevy!$C311,ActualCRLevy_SAS!$B$2:$B$326,0),4) -> 0 | M311: =IF(AND(L311=K311,K311>0),"Max","") | N311: =IF(AND(L311<K311,L311=0),"No Levy but have Capacity","") | O311: =IF(L311>K311,"Exceedes Maximum Limit","")
A312: 2026 | B312: 13 | C312: 6969 | F312: 6969 | G312: West Harrison | H312: =ROUND(SUMPRODUCT(SUMIF(Final!$G$4:$G$330,CashReserveLevy!D312:F312,Final!$C$4:$C$330)),0) -> 5562387 | I312: =ROUND(H312*0.2,0) -> 1112477 | J312: =ROUND(SUMPRODUCT(SUMIF(Final!$G$4:$G$330,CashReserveLevy!D312:F312,Final!$E$4:$E$330)),0) -> 684648 | K312: =IF(I312>J312,I312-J312,0) -> 427829 | L312: =INDEX(ActualCRLevy_SAS!$A$2:$D$326,MATCH(CashReserveLevy!$C312,ActualCRLevy_SAS!$B$2:$B$326,0),4) -> 300000 | M312: =IF(AND(L312=K312,K312>0),"Max","") | N312: =IF(AND(L312<K312,L312=0),"No Levy but have Capacity","") | O312: =IF(L312>K312,"Exceedes Maximum Limit","")
A313: 2026 | B313: 09 | C313: 6975 | F313: 6975 | G313: West Liberty | H313: =ROUND(SUMPRODUCT(SUMIF(Final!$G$4:$G$330,CashReserveLevy!D313:F313,Final!$C$4:$C$330)),0) -> 18118669 | I313: =ROUND(H313*0.2,0) -> 3623734 | J313: =ROUND(SUMPRODUCT(SUMIF(Final!$G$4:$G$330,CashReserveLevy!D313:F313,Final!$E$4:$E$330)),0) -> 5235848 | K313: =IF(I313>J313,I313-J313,0) -> 0 | L313: =INDEX(ActualCRLevy_SAS!$A$2:$D$326,MATCH(CashReserveLevy!$C313,ActualCRLevy_SAS!$B$2:$B$326,0),4) -> 0 | M313: =IF(AND(L313=K313,K313>0),"Max","") | N313: =IF(AND(L313<K313,L313=0),"No Levy but have Capacity","") | O313: =IF(L313>K313,"Exceedes Maximum Limit","")
A314: 2026 | B314: 12 | C314: 6983 | F314: 6983 | G314: West Lyon | H314: =ROUND(SUMPRODUCT(SUMIF(Final!$G$4:$G$330,CashReserveLevy!D314:F314,Final!$C$4:$C$330)),0) -> 11517960 | I314: =ROUND(H314*0.2,0) -> 2303592 | J314: =ROUND(SUMPRODUCT(SUMIF(Final!$G$4:$G$330,CashReserveLevy!D314:F314,Final!$E$4:$E$330)),0) -> 3577753 | K314: =IF(I314>J314,I314-J314,0) -> 0 | L314: =INDEX(ActualCRLevy_SAS!$A$2:$D$326,MATCH(CashReserveLevy!$C314,ActualCRLevy_SAS!$B$2:$B$326,0),4) -> 0 | M314: =IF(AND(L314=K314,K314>0),"Max","") | N314: =IF(AND(L314<K314,L314=0),"No Levy but have Capacity","") | O314: =IF(L314>K314,"Exceedes Maximum Limit","")
... A327: 2026 | B327: 11 | C327: 7110 | F327: 7110 | G327: Woodward-Granger | H327: =ROUND(SUMPRODUCT(SUMIF(Final!$G$4:$G$330,CashReserveLevy!D327:F327,Final!$C$4:$C$330)),0) -> 18373210 | I327: =ROUND(H327*0.2,0) -> 3674642 | J327: =ROUND(SUMPRODUCT(SUMIF(Final!$G$4:$G$330,CashReserveLevy!D327:F327,Final!$E$4:$E$330)),0) -> -1339932 | K327: =IF(I327>J327,I327-J327,0) -> 5014574 | L327: =INDEX(ActualCRLevy_SAS!$A$2:$D$326,MATCH(CashReserveLevy!$C327,ActualCRLevy_SAS!$B$2:$B$326,0),4) -> 1025000 | M327: =IF(AND(L327=K327,K327>0),"Max","") | N327: =IF(AND(L327<K327,L327=0),"No Levy but have Capacity","") | O327: =IF(L327>K327,"Exceedes Maximum Limit","")
H328: =SUM(H3:H327) -> 7102886770 | I328: =SUM(I3:I327) -> 1420577351 | J328: =SUM(J3:J327) -> 1374106096 | K328: =SUM(K3:K327) -> 344604335 | L328: =SUM(L3:L327) -> 211904981
K332: Number of Districts unable to levy for Cash Reserve: | L332: =COUNTIF($K$3:$K$327,0) -> 159
K333: Number of Districts Levying for Cash Reserve: | L333: =COUNTIF($L$3:$L$327,">0") -> 160
K334: Number of Districts Not Levying for Cash Reserve but have the Ability: | L334: =COUNTIF($N$3:$N$327,"No Levy but have Capacity") -> 6
K335: Number of Districts Levying Maximum for Cash Reserve Levy: | L335: =COUNTIF($M$3:$M$327,"Max") -> 53
I337: Fiscal Year | J337: Maximum Cash Reserve Levy | K337: Total Cash Reserve Levy | L337: Percent of Maximum Utilized | M337: Percent Change
I338: 2002 | J338: 395337064 | K338: 68317829 | L338: =K338/J338 -> 0.17280907
I339: 2003 | J339: 399692119 | K339: 92775492 | L339: =K339/J339 -> 0.23211739 | M339: =(K339-K338)/K338 -> 0.35799825
I340: 2004 | J340: 443895075 | K340: 93735656 | L340: =K340/J340 -> 0.21116624 | M340: =(K340-K339)/K339 -> 0.010349328
I341: 2005 | J341: 445825608 | K341: 96591952 | L341: =K341/J341 -> 0.2166586 | M341: =(K341-K340)/K340 -> 0.03047182
I342: 2006 | J342: 468791916 | K342: 97853720 | L342: =K342/J342 -> 0.20873594 | M342: =(K342-K341)/K341 -> 0.013062869
I343: 2007 | J343: 495492815 | K343: 119543594 | L343: =K343/J343 -> 0.24126201 | M343: =(K343-K342)/K342 -> 0.2216561
I344: 2008 | J344: 610214870 | K344: 133598310 | L344: =K344/J344 -> 0.2189365 | M344: =(K344-K343)/K343 -> 0.1175698
I345: 2009 | J345: 629299779 | K345: 154418943 | L345: =K345/J345 -> 0.24538217 | M345: =(K345-K344)/K344 -> 0.15584503
I346: 2010 | J346: 697255519 | K346: 194327650 | L346: =K346/J346 -> 0.27870364 | M346: =(K346-K345)/K345 -> 0.25844437
I347: 2011 | J347: 833404808 | K347: 298278645 | L347: =K347/J347 -> 0.35790368 | M347: =(K347-K346)/K346 -> 0.53492642
I348: 2012 | J348: 939182813 | K348: 274120078 | L348: =K348/J348 -> 0.29187084 | M348: =(K348-K347)/K347 -> -0.080993284
I349: 2013 | J349: 541159478 | K349: 231935729 | L349: =K349/J349 -> 0.42859035 | M349: =(K349-K348)/K348 -> -0.15389004
I350: 2014 | J350: 372534536 | K350: 190880844 | L350: =K350/J350 -> 0.51238429 | M350: =(K350-K349)/K349 -> -0.17700975
... I362: 2026 | J362: 344604335 | K362: 211904981 | L362: =K362/J362 -> 0.61492256 | M362: =(K362-K361)/K361 -> 0.13004187

Sheet Final
A1: FY24 Expenditures, Miscellaneous Income, Assigned/Unassigned Fund Balace, Total Fund Balance - Final
A3: Agency Number | B3: Agency Name | C3: Expenditures | D3: Miscellaneous Income | E3: Assigned & Unassigned Fund Balance | F3: Total Fund Balance
A4: 9 | B4: AGWSR Comm School District | C4: 10259078 | D4: 1013438.3 | E4: -155501.85 | F4: 487213.7 | G4: =TEXT(A4,"0000") -> 0009
A5: 18 | B5: Adair-Casey Comm School District | C5: 4907234.2 | D5: 1324784.4 | E5: 1437725.9 | F5: 1589963 | G5: =TEXT(A5,"0000") -> 0018
A6: 27 | B6: Adel DeSoto Minburn Comm School District | C6: 27144003 | D6: 3518011.7 | E6: 4129415.2 | F6: 5243672.6 | G6: =TEXT(A6,"0000") -> 0027
A7: 63 | B7: Akron Westfield Comm School District | C7: 8463069.6 | D7: 1513795.6 | E7: 861250.52 | F7: 1354462.3 | G7: =TEXT(A7,"0000") -> 0063
A8: 72 | B8: Albert City-Truesdale Comm School District | C8: 2967467 | D8: 507070.49 | E8: 1552673.8 | F8: 1648347.4 | G8: =TEXT(A8,"0000") -> 0072
A9: 81 | B9: Albia Comm School District | C9: 14649277 | D9: 2153367.1 | E9: 4141164.8 | F9: 4330667.8 | G9: =TEXT(A9,"0000") -> 0081
A10: 99 | B10: Alburnett Comm School District | C10: 9574247.4 | D10: 3366760.9 | E10: 1279357.2 | F10: 1396816.6 | G10: =TEXT(A10,"0000") -> 0099
A11: 108 | B11: Alden Comm School District | C11: 3882411.4 | D11: 508751.07 | E11: 380516.29 | F11: 641113.64 | G11: =TEXT(A11,"0000") -> 0108
A12: 126 | B12: Algona Comm School District | C12: 22265557 | D12: 3291012.8 | E12: 3638894.6 | F12: 4239198 | G12: =TEXT(A12,"0000") -> 0126
A13: 135 | B13: Allamakee Comm School District | C13: 15125260 | D13: 2444149 | E13: 1748724.6 | F13: 2440450.5 | G13: =TEXT(A13,"0000") -> 0135
A14: 153 | B14: North Butler Comm School District | C14: 7898950.8 | D14: 1359378.8 | E14: 1535841.6 | F14: 1897762.9 | G14: =TEXT(A14,"0000") -> 0153
A15: 171 | B15: Alta-Aurelia Comm School District | C15: 11750216 | D15: 1388374.9 | E15: 1427391.2 | F15: 2013651.9 | G15: =TEXT(A15,"0000") -> 0171
... A330: 8200 | B330: Charter Organization: Concept Schools | C330: 2998247.2 | D330: 4195460.8 | E330: 461371.18 | F330: 532332.51 | G330: =TEXT(A330,"0000") -> 8200
C331: =SUM(C4:C328) -> 7.1028868e+09 | D331: =SUM(D4:D328) -> 1.2060084e+09 | E331: =SUM(E4:E328) -> 1.3741061e+09 | F331: =SUM(F4:F328) -> 1.5956968e+09

Sheet ActualCRLevy_SAS
A1: FiscalYear | B1: Dist | C1: Label | D1: Final Cash Reserve Levy | E1: Final 6-25-2025
A2: 2026 | B2: 0009 | C2: AGWSR | D2: 1000000
A3: 2026 | B3: 0441 | C3: AHSTW | D3: 117909
A4: 2026 | B4: 0018 | C4: Adair-Casey | D4: 0
A5: 2026 | B5: 0027 | C5: Adel-Desoto-Minburn | D5: 1299386
A6: 2026 | B6: 0063 | C6: Akron-Westfield | D6: 831363
A7: 2026 | B7: 0072 | C7: Albert City-Truesdale | D7: 0
A8: 2026 | B8: 0081 | C8: Albia | D8: 0
A9: 2026 | B9: 0099 | C9: Alburnett | D9: 300000
A10: 2026 | B10: 0108 | C10: Alden | D10: 375000
A11: 2026 | B11: 0126 | C11: Algona | D11: 814216
A12: 2026 | B12: 0135 | C12: Allamakee | D12: 400000
A13: 2026 | B13: 0171 | C13: Alta-Aurelia | D13: 600000
... A326: 2026 | B326: 7110 | C326: Woodward-Granger | D326: 1025000
