Workbook
Name IDX: Final!$A$1

Sheet CashReserveLevy
C1: =_xlfn.CONCAT("SBRC FY ",A3," Final Cash Reserve Levy Limitations Source: FY ",A3-2," Certified Annual Report") -> SBRC FY 2024 Final Cash Reserve Levy Limitations Source: FY 2022 Certified Annual Report
A2: FiscalYear | B2: AEA | C2: Dist | D2: DistSub1 | E2: DistSub2 | F2: DistrictNumber | G2: Label | H2: Expenditures | I2: 20% of Expenditures | J2: Assigned and Unassigned Fund Balance | K2: Final Maximum Cash Reserve Levy | L2: Final Cash Reserve Levy | M2: Levying Maximum Cash Reserve | Q2: Check for Negative | U2: Preliminary Maximum Cash Reserve Levy - Initial Posting
A3: 2024 | B3: 11 | C3: 0018 | F3: 0018 | G3: Adair-Casey | H3: =ROUND(SUMPRODUCT(SUMIF(Final!$G$4:$G$330,CashReserveLevy!D3:F3,Final!$C$4:$C$330)),0) -> 4593649 | I3: =ROUND(H3*0.2,0) -> 918730 | J3: =ROUND(SUMPRODUCT(SUMIF(Final!$G$4:$G$330,CashReserveLevy!D3:F3,Final!$E$4:$E$330)),0) -> 1435067 | K3: =IF(I3>J3,I3-J3,0) -> 0 | L3: =INDEX(ActualCRLevy_SAS!$A$2:$D$326,MATCH(CashReserveLevy!$C3,ActualCRLevy_SAS!$B$2:$B$326,0),4) -> 0 | M3: =IF(AND(L3=K3,K3>0),"Max","") | N3: =IF(AND(L3<K3,L3=0),"No Levy but have Capacity","") | O3: =IF(L3>K3,"Exceedes Maximum Limit","") | Q3: =K3-L3 -> 0 | U3: 0 | V3: =K3-U3 -> 0
A4: 2024 | B4: 11 | C4: 0027 | F4: 0027 | G4: Adel-Desoto-Minburn | H4: =ROUND(SUMPRODUCT(SUMIF(Final!$G$4:$G$330,CashReserveLevy!D4:F4,Final!$C$4:$C$330)),0) -> 24295219 | I4: =ROUND(H4*0.2,0) -> 4859044 | J4: =ROUND(SUMPRODUCT(SUMIF(Final!$G$4:$G$330,CashReserveLevy!D4:F4,Final!$E$4:$E$330)),0) -> 5188022 | K4: =IF(I4>J4,I4-J4,0) -> 0 | L4: =INDEX(ActualCRLevy_SAS!$A$2:$D$326,MATCH(CashReserveLevy!$C4,ActualCRLevy_SAS!$B$2:$B$326,0),4) -> 0 | M4: =IF(AND(L4=K4,K4>0),"Max","") | N4: =IF(AND(L4<K4,L4=0),"No Levy but have Capacity","") | O4: =IF(L4>K4,"Exceedes Maximum Limit","") | Q4: =K4-L4 -> 0 | U4: 0 | V4: =K4-U4 -> 0
A5: 2024 | B5: 07 | C5: 0009 | F5: 0009 | G5: AGWSR | H5: =ROUND(SUMPRODUCT(SUMIF(Final!$G$4:$G$330,CashReserveLevy!D5:F5,Final!$C$4:$C$330)),0) -> 9940867 | I5: =ROUND(H5*0.2,0) -> 1988173 | J5: =ROUND(SUMPRODUCT(SUMIF(Final!$G$4:$G$330,CashReserveLevy!D5:F5,Final!$E$4:$E$330)),0) -> 1221374 | K5: =IF(I5>J5,I5-J5,0) -> 766799 | L5: =INDEX(ActualCRLevy_SAS!$A$2:$D$326,MATCH(CashReserveLevy!$C5,ActualCRLevy_SAS!$B$2:$B$326,0),4) -> 370000 | M5: =IF(AND(L5=K5,K5>0),"Max","") | N5: =IF(AND(L5<K5,L5=0),"No Levy but have Capacity","") | O5: =IF(L5>K5,"Exceedes Maximum Limit","") | Q5: =K5-L5 -> 396799 | U5: 766799 | V5: =K5-U5 -> 0
A6: 2024 | B6: 13 | C6: 0441 | F6: 0441 | G6: AHSTW | H6: =ROUND(SUMPRODUCT(SUMIF(Final!$G$4:$G$330,CashReserveLevy!D6:F6,Final!$C$4:$C$330)),0) -> 10025049 | I6: =ROUND(H6*0.2,0) -> 2005010 | J6: =ROUND(SUMPRODUCT(SUMIF(Final!$G$4:$G$330,CashReserveLevy!D6:F6,Final!$E$4:$E$330)),0) -> 2869593 | K6: =IF(I6>J6,I6-J6,0) -> 0 | L6: =INDEX(ActualCRLevy_SAS!$A$2:$D$326,MATCH(CashReserveLevy!$C6,ActualCRLevy_SAS!$B$2:$B$326,0),4) -> 0 | M6: =IF(AND(L6=K6,K6>0),"Max","") | N6: =IF(AND(L6<K6,L6=0),"No Levy but have Capacity","") | O6: =IF(L6>K6,"Exceedes Maximum Limit","") | Q6: =K6-L6 -> 0 | U6: 0 | V6: =K6-U6 -> 0
A7: 2024 | B7: 12 | C7: 0063 | F7: 0063 | G7: Akron-Westfield | H7: =ROUND(SUMPRODUCT(SUMIF(Final!$G$4:$G$330,CashReserveLevy!D7:F7,Final!$C$4:$C$330)),0) -> 8004281 | I7: =ROUND(H7*0.2,0) -> 1600856 | J7: =ROUND(SUMPRODUCT(SUMIF(Final!$G$4:$G$330,CashReserveLevy!D7:F7,Final!$E$4:$E$330)),0) -> 1785712 | K7: =IF(I7>J7,I7-J7,0) -> 0 | L7: =INDEX(ActualCRLevy_SAS!$A$2:$D$326,MATCH(CashReserveLevy!$C7,ActualCRLevy_SAS!$B$2:$B$326,0),4) -> 0 | M7: =IF(AND(L7=K7,K7>0),"Max","") | N7: =IF(AND(L7<K7,L7=0),"No Levy but have Capacity","") | O7: =IF(L7>K7,"Exceedes Maximum Limit","") | Q7: =K7-L7 -> 0 | U7: 0 | V7: =K7-U7 -> 0
A8: 2024 | B8: 05 | C8: 0072 | F8: 0072 | G8: Albert City-Truesdale | H8: =ROUND(SUMPRODUCT(SUMIF(Final!$G$4:$G$330,CashReserveLevy!D8:F8,Final!$C$4:$C$330)),0) -> 2809844 | I8: =ROUND(H8*0.2,0) -> 561969 | J8: =ROUND(SUMPRODUCT(SUMIF(Final!$G$4:$G$330,CashReserveLevy!D8:F8,Final!$E$4:$E$330)),0) -> 1134405 | K8: =IF(I8>J8,I8-J8,0) -> 0 | L8: =INDEX(ActualCRLevy_SAS!$A$2:$D$326,MATCH(CashReserveLevy!$C8,ActualCRLevy_SAS!$B$2:$B$326,0),4) -> 0 | M8: =IF(AND(L8=K8,K8>0),"Max","") | N8: =IF(AND(L8<K8,L8=0),"No Levy but have Capacity","") | O8: =IF(L8>K8,"Exceedes Maximum Limit","") | Q8: =K8-L8 -> 0 | U8: 0 | V8: =K8-U8 -> 0
A9: 2024 | B9: 15 | C9: 0081 | F9: 0081 | G9: Albia | H9: =ROUND(SUMPRODUCT(SUMIF(Final!$G$4:$G$330,CashReserveLevy!D9:F9,Final!$C$4:$C$330)),0) -> 14271156 | I9: =ROUND(H9*0.2,0) -> 2854231 | J9: =ROUND(SUMPRODUCT(SUMIF(Final!$G$4:$G$330,CashReserveLevy!D9:F9,Final!$E$4:$E$330)),0) -> 4071860 | K9: =IF(I9>J9,I9-J9,0) -> 0 | L9: =INDEX(ActualCRLevy_SAS!$A$2:$D$326,MATCH(CashReserveLevy!$C9,ActualCRLevy_SAS!$B$2:$B$326,0),4) -> 0 | M9: =IF(AND(L9=K9,K9>0),"Max","") | N9: =IF(AND(L9<K9,L9=0),"No Levy but have Capacity","") | O9: =IF(L9>K9,"Exceedes Maximum Limit","") | Q9: =K9-L9 -> 0 | U9: 0 | V9: =K9-U9 -> 0
A10: 2024 | B10: 10 | C10: 0099 | F10: 0099 | G10: Alburnett | H10: =ROUND(SUMPRODUCT(SUMIF(Final!$G$4:$G$330,CashReserveLevy!D10:F10,Final!$C$4:$C$330)),0) -> 8476603 | I10: =ROUND(H10*0.2,0) -> 1695321 | J10: =ROUND(SUMPRODUCT(SUMIF(Final!$G$4:$G$330,CashReserveLevy!D10:F10,Final!$E$4:$E$330)),0) -> 1952462 | K10: =IF(I10>J10,I10-J10,0) -> 0 | L10: =INDEX(ActualCRLevy_SAS!$A$2:$D$326,MATCH(CashReserveLevy!$C10,ActualCRLevy_SAS!$B$2:$B$326,0),4) -> 0 | M10: =IF(AND(L10=K10,K10>0),"Max","") | N10: =IF(AND(L10<K10,L10=0),"No Levy but have Capacity","") | O10: =IF(L10>K10,"Exceedes Maximum Limit","") | Q10: =K10-L10 -> 0 | U10: 0 | V10: =K10-U10 -> 0
A11: 2024 | B11: 07 | C11: 0108 | F11: 0108 | G11: Alden | H11: =ROUND(SUMPRODUCT(SUMIF(Final!$G$4:$G$330,CashReserveLevy!D11:F11,Final!$C$4:$C$330)),0) -> 3876814 | I11: =ROUND(H11*0.2,0) -> 775363 | J11: =ROUND(SUMPRODUCT(SUMIF(Final!$G$4:$G$330,CashReserveLevy!D11:F11,Final!$E$4:$E$330)),0) -> 127457 | K11: =IF(I11>J11,I11-J11,0) -> 647906 | L11: =INDEX(ActualCRLevy_SAS!$A$2:$D$326,MATCH(CashReserveLevy!$C11,ActualCRLevy_SAS!$B$2:$B$326,0),4) -> 400000 | M11: =IF(AND(L11=K11,K11>0),"Max","") | N11: =IF(AND(L11<K11,L11=0),"No Levy but have Capacity","") | O11: =IF(L11>K11,"Exceedes Maximum Limit","") | Q11: =K11-L11 -> 247906 | U11: 647906 | V11: =K11-U11 -> 0
A12: 2024 | B12: 05 | C12: 0126 | D12: 6417 | E12: 3897 | F12: 0126 | G12: Algona | H12: =ROUND(SUMPRODUCT(SUMIF(Final!$G$4:$G$330,CashReserveLevy!D12:F12,Final!$C$4:$C$330)),0) -> 22878245 | I12: =ROUND(H12*0.2,0) -> 4575649 | J12: =ROUND(SUMPRODUCT(SUMIF(Final!$G$4:$G$330,CashReserveLevy!D12:F12,Final!$E$4:$E$330)),0) -> 3679749 | K12: =IF(I12>J12,I12-J12,0) -> 895900 | L12: =INDEX(ActualCRLevy_SAS!$A$2:$D$326,MATCH(CashReserveLevy!$C12,ActualCRLevy_SAS!$B$2:$B$326,0),4) -> 895900 | M12: =IF(AND(L12=K12,K12>0),"Max","") -> Max | N12: =IF(AND(L12<K12,L12=0),"No Levy but have Capacity","") | O12: =IF(L12>K12,"Exceedes Maximum Limit","") | Q12: =K12-L12 -> 0 | U12: 895900 | V12: =K12-U12 -> 0
A13: 2024 | B13: 01 | C13: 0135 | F13: 0135 | G13: Allamakee | H13: =ROUND(SUMPRODUCT(SUMIF(Final!$G$4:$G$330,CashReserveLevy!D13:F13,Final!$C$4:$C$330)),0) -> 14603162 | I13: =ROUND(H13*0.2,0) -> 2920632 | J13: =ROUND(SUMPRODUCT(SUMIF(Final!$G$4:$G$330,CashReserveLevy!D13:F13,Final!$E$4:$E$330)),0) -> 3081424 | K13: =IF(I13>J13,I13-J13,0) -> 0 | L13: =INDEX(ActualCRLevy_SAS!$A$2:$D$326,MATCH(CashReserveLevy!$C13,ActualCRLevy_SAS!$B$2:$B$326,0),4) -> 0 | M13: =IF(AND(L13=K13,K13>0),"Max","") | N13: =IF(AND(L13<K13,L13=0),"No Levy but have Capacity","") | O13: =IF(L13>K13,"Exceedes Maximum Limit","") | Q13: =K13-L13 -> 0 | U13: 0 | V13: =K13-U13 -> 0
A14: 2024 | B14: 05 | C14: 0171 | F14: 0171 | G14: Alta-Aurelia | H14: =ROUND(SUMPRODUCT(SUMIF(Final!$G$4:$G$330,CashReserveLevy!D14:F14,Final!$C$4:$C$330)),0) -> 11385819 | I14: =ROUND(H14*0.2,0) -> 2277164 | J14: =ROUND(SUMPRODUCT(SUMIF(Final!$G$4:$G$330,CashReserveLevy!D14:F14,Final!$E$4:$E$330)),0) -> 1634402 | K14: =IF(I14>J14,I14-J14,0) -> 642762 | L14: =INDEX(ActualCRLevy_SAS!$A$2:$D$326,MATCH(CashReserveLevy!$C14,ActualCRLevy_SAS!$B$2:$B$326,0),4) -> 350000 | M14: =IF(AND(L14=K14,K14>0),"Max","") | N14: =IF(AND(L14<K14,L14=0),"No Levy but have Capacity","") | O14: =IF(L14>K14,"Exceedes Maximum Limit","") | Q14: =K14-L14 -> 292762 | U14: 642762 | V14: =K14-U14 -> 0
A15: 2024 | B15: 11 | C15: 0225 | F15: 0225 | G15: Ames | H15: =ROUND(SUMPRODUCT(SUMIF(Final!$G$4:$G$330,CashReserveLevy!D15:F15,Final!$C$4:$C$330)),0) -> 61294605 | I15: =ROUND(H15*0.2,0) -> 12258921 | J15: =ROUND(SUMPRODUCT(SUMIF(Final!$G$4:$G$330,CashReserveLevy!D15:F15,Final!$E$4:$E$330)),0) -> 12577895 | K15: =IF(I15>J15,I15-J15,0) -> 0 | L15: =INDEX(ActualCRLevy_SAS!$A$2:$D$326,MATCH(CashReserveLevy!$C15,ActualCRLevy_SAS!$B$2:$B$326,0),4) -> 0 | M15: =IF(AND(L15=K15,K15>0),"Max","") | N15: =IF(AND(L15<K15,L15=0),"No Levy but have Capacity","") | O15: =IF(L15>K15,"Exceedes Maximum Limit","") | Q15: =K15-L15 -> 0 | U15: 0 | V15: =K15-U15 -> 0
A16: 2024 | B16: 10 | C16: 0234 | F16: 0234 | G16: Anamosa | H16: =ROUND(SUMPRODUCT(SUMIF(Final!$G$4:$G$330,CashReserveLevy!D16:F16,Final!$C$4:$C$330)),0) -> 16741535 | I16: =ROUND(H16*0.2,0) -> 3348307 | J16: =ROUND(SUMPRODUCT(SUMIF(Final!$G$4:$G$330,CashReserveLevy!D16:F16,Final!$E$4:$E$330)),0) -> 4432442 | K16: =IF(I16>J16,I16-J16,0) -> 0 | L16: =INDEX(ActualCRLevy_SAS!$A$2:$D$326,MATCH(CashReserveLevy!$C16,ActualCRLevy_SAS!$B$2:$B$326,0),4) -> 0 | M16: =IF(AND(L16=K16,K16>0),"Max","") | N16: =IF(AND(L16<K16,L16=0),"No Levy but have Capacity","") | O16: =IF(L16>K16,"Exceedes Maximum Limit","") | Q16: =K16-L16 -> 0 | U16: 0 | V16: =K16-U16 -> 0
A17: 2024 | B17: 09 | C17: 0243 | F17: 0243 | G17: Andrew | H17: =ROUND(SUMPRODUCT(SUMIF(Final!$G$4:$G$330,CashReserveLevy!D17:F17,Final!$C$4:$C$330)),0) -> 3748758 | I17: =ROUND(H17*0.2,0) -> 749752 | J17: =ROUND(SUMPRODUCT(SUMIF(Final!$G$4:$G$330,CashReserveLevy!D17:F17,Final!$E$4:$E$330)),0) -> 538148 | K17: =IF(I17>J17,I17-J17,0) -> 211604 | L17: =INDEX(ActualCRLevy_SAS!$A$2:$D$326,MATCH(CashReserveLevy!$C17,ActualCRLevy_SAS!$B$2:$B$326,0),4) -> 170000 | M17: =IF(AND(L17=K17,K17>0),"Max","") | N17: =IF(AND(L17<K17,L17=0),"No Levy but have Capacity","") | O17: =IF(L17>K17,"Exceedes Maximum Limit","") | Q17: =K17-L17 -> 41604 | U17: 211604 | V17: =K17-U17 -> 0
A18: 2024 | B18: 11 | C18: 0261 | F18: 0261 | G18: Ankeny | H18: =ROUND(SUMPRODUCT(SUMIF(Final!$G$4:$G$330,CashReserveLevy!D18:F18,Final!$C$4:$C$330)),0) -> 148362662 | I18: =ROUND(H18*0.2,0) -> 29672532 | J18: =ROUND(SUMPRODUCT(SUMIF(Final!$G$4:$G$330,CashReserveLevy!D18:F18,Final!$E$4:$E$330)),0) -> 16727252 | K18: =IF(I18>J18,I18-J18,0) -> 12945280 | L18: =INDEX(ActualCRLevy_SAS!$A$2:$D$326,MATCH(CashReserveLevy!$C18,ActualCRLevy_SAS!$B$2:$B$326,0),4) -> 11047397 | M18: =IF(AND(L18=K18,K18>0),"Max","") | N18: =IF(AND(L18<K18,L18=0),"No Levy but have Capacity","") | O18: =IF(L18>K18,"Exceedes Maximum Limit","") | Q18: =K18-L18 -> 1897883 | U18: 12945280 | V18: =K18-U18 -> 0
A19: 2024 | B19: 07 | C19: 0279 | F19: 0279 | G19: Aplington-Parkersburg | H19: =ROUND(SUMPRODUCT(SUMIF(Final!$G$4:$G$330,CashReserveLevy!D19:F19,Final!$C$4:$C$330)),0) -> 10125203 | I19: =ROUND(H19*0.2,0) -> 2025041 | J19: =ROUND(SUMPRODUCT(SUMIF(Final!$G$4:$G$330,CashReserveLevy!D19:F19,Final!$E$4:$E$330)),0) -> 2610572 | K19: =IF(I19>J19,I19-J19,0) -> 0 | L19: =INDEX(ActualCRLevy_SAS!$A$2:$D$326,MATCH(CashReserveLevy!$C19,ActualCRLevy_SAS!$B$2:$B$326,0),4) -> 0 | M19: =IF(AND(L19=K19,K19>0),"Max","") | N19: =IF(AND(L19<K19,L19=0),"No Levy but have Capacity","") | O19: =IF(L19>K19,"Exceedes Maximum Limit","") | Q19: =K19-L19 -> 0 | U19: 0 | V19: =K19-U19 -> 0
A20: 2024 | B20: 12 | C20: 0355 | F20: 0355 | G20: Ar-We-Va | H20: =ROUND(SUMPRODUCT(SUMIF(Final!$G$4:$G$330,CashReserveLevy!D20:F20,Final!$C$4:$C$330)),0) -> 3717537 | I20: =ROUND(H20*0.2,0) -> 743507 | J20: =ROUND(SUMPRODUCT(SUMIF(Final!$G$4:$G$330,CashReserveLevy!D20:F20,Final!$E$4:$E$330)),0) -> 1925063 | K20: =IF(I20>J20,I20-J20,0) -> 0 | L20: =INDEX(ActualCRLevy_SAS!$A$2:$D$326,MATCH(CashReserveLevy!$C20,ActualCRLevy_SAS!$B$2:$B$326,0),4) -> 0 | M20: =IF(AND(L20=K20,K20>0),"Max","") | N20: =IF(AND(L20<K20,L20=0),"No Levy but have Capacity","") | O20: =IF(L20>K20,"Exceedes Maximum Limit","") | Q20: =K20-L20 -> 0 | U20: 0 | V20: =K20-U20 -> 0
A21: 2024 | B21: 13 | C21: 0387 | F21: 0387 | G21: Atlantic | H21: =ROUND(SUMPRODUCT(SUMIF(Final!$G$4:$G$330,CashReserveLevy!D21:F21,Final!$C$4:$C$330)),0) -> 18916816 | I21: =ROUND(H21*0.2,0) -> 3783363 | J21: =ROUND(SUMPRODUCT(SUMIF(Final!$G$4:$G$330,CashReserveLevy!D21:F21,Final!$E$4:$E$330)),0) -> 3124645 | K21: =IF(I21>J21,I21-J21,0) -> 658718 | L21: =INDEX(ActualCRLevy_SAS!$A$2:$D$326,MATCH(CashReserveLevy!$C21,ActualCRLevy_SAS!$B$2:$B$326,0),4) -> 658718 | M21: =IF(AND(L21=K21,K21>0),"Max","") -> Max | N21: =IF(AND(L21<K21,L21=0),"No Levy but have Capacity","") | O21: =IF(L21>K21,"Exceedes Maximum Limit","") | Q21: =K21-L21 -> 0 | U21: 658718 | V21: =K21-U21 -> 0
A22: 2024 | B22: 11 | C22: 0414 | F22: 0414 | G22: Audubon | H22: =ROUND(SUMPRODUCT(SUMIF(Final!$G$4:$G$330,CashReserveLevy!D22:F22,Final!$C$4:$C$330)),0) -> 7272865 | I22: =ROUND(H22*0.2,0) -> 1454573 | J22: =ROUND(SUMPRODUCT(SUMIF(Final!$G$4:$G$330,CashReserveLevy!D22:F22,Final!$E$4:$E$330)),0) -> 1314102 | K22: =IF(I22>J22,I22-J22,0) -> 140471 | L22: =INDEX(ActualCRLevy_SAS!$A$2:$D$326,MATCH(CashReserveLevy!$C22,ActualCRLevy_SAS!$B$2:$B$326,0),4) -> 140471 | M22: =IF(AND(L22=K22,K22>0),"Max","") -> Max | N22: =IF(AND(L22<K22,L22=0),"No Levy but have Capacity","") | O22: =IF(L22>K22,"Exceedes Maximum Limit","") | Q22: =K22-L22 -> 0 | U22: 140471 | V22: =K22-U22 -> 0
A23: 2024 | B23: 11 | C23: 0472 | F23: 0472 | G23: Ballard | H23: =ROUND(SUMPRODUCT(SUMIF(Final!$G$4:$G$330,CashReserveLevy!D23:F23,Final!$C$4:$C$330)),0) -> 21737477 | I23: =ROUND(H23*0.2,0) -> 4347495 | J23: =ROUND(SUMPRODUCT(SUMIF(Final!$G$4:$G$330,CashReserveLevy!D23:F23,Final!$E$4:$E$330)),0) -> 3088911 | K23: =IF(I23>J23,I23-J23,0) -> 1258584 | L23: =INDEX(ActualCRLevy_SAS!$A$2:$D$326,MATCH(CashReserveLevy!$C23,ActualCRLevy_SAS!$B$2:$B$326,0),4) -> 1258584 | M23: =IF(AND(L23=K23,K23>0),"Max","") -> Max | N23: =IF(AND(L23<K23,L23=0),"No Levy but have Capacity","") | O23: =IF(L23>K23,"Exceedes Maximum Limit","") | Q23: =K23-L23 -> 0 | U23: 1258584 | V23: =K23-U23 -> 0
A24: 2024 | B24: 11 | C24: 0513 | F24: 0513 | G24: Baxter | H24: =ROUND(SUMPRODUCT(SUMIF(Final!$G$4:$G$330,CashReserveLevy!D24:F24,Final!$C$4:$C$330)),0) -> 5668120 | I24: =ROUND(H24*0.2,0) -> 1133624 | J24: =ROUND(SUMPRODUCT(SUMIF(Final!$G$4:$G$330,CashReserveLevy!D24:F24,Final!$E$4:$E$330)),0) -> 92318 | K24: =IF(I24>J24,I24-J24,0) -> 1041306 | L24: =INDEX(ActualCRLevy_SAS!$A$2:$D$326,MATCH(CashReserveLevy!$C24,ActualCRLevy_SAS!$B$2:$B$326,0),4) -> 495487 | M24: =IF(AND(L24=K24,K24>0),"Max","") | N24: =IF(AND(L24<K24,L24=0),"No Levy but have Capacity","") | O24: =IF(L24>K24,"Exceedes Maximum Limit","") | Q24: =K24-L24 -> 545819 | U24: 1041306 | V24: =K24-U24 -> 0
... A61: 2024 | B61: 13 | C61: 1197 | F61: 1197 | G61: Clarinda | H61: =ROUND(SUMPRODUCT(SUMIF(Final!$G$4:$G$330,CashReserveLevy!D61:F61,Final!$C$4:$C$330)),0) -> 12694281 | I61: =ROUND(H61*0.2,0) -> 2538856 | J61: =ROUND(SUMPRODUCT(SUMIF(Final!$G$4:$G$330,CashReserveLevy!D61:F61,Final!$E$4:$E$330)),0) -> 2733409 | K61: =IF(I61>J61,I61-J61,0) -> 0 | L61: =INDEX(ActualCRLevy_SAS!$A$2:$D$326,MATCH(CashReserveLevy!$C61,ActualCRLevy_SAS!$B$2:$B$326,0),4) -> 0 | M61: =IF(AND(L61=K61,K61>0),"Max","") | N61: =IF(AND(L61<K61,L61=0),"No Levy but have Capacity","") | O61: =IF(L61>K61,"Exceedes Maximum Limit","") | Q61: =K61-L61 -> 0 | U61: 0 | V61: =K61-U61 -> 0
A62: 2024 | B62: 05 | C62: 1206 | D62: 1854 | F62: 1206 | G62: Clarion-Goldfield-Dows | H62: =ROUND(SUMPRODUCT(SUMIF(Final!$G$4:$G$330,CashReserveLevy!D62:F62,Final!$C$4:$C$330)),0) -> 14308808 | I62: =ROUND(H62*0.2,0) -> 2861762 | J62: =ROUND(SUMPRODUCT(SUMIF(Final!$G$4:$G$330,CashReserveLevy!D62:F62,Final!$E$4:$E$330)),0) -> 893256 | K62: =IF(I62>J62,I62-J62,0) -> 1968506 | L62: =INDEX(ActualCRLevy_SAS!$A$2:$D$326,MATCH(CashReserveLevy!$C62,ActualCRLevy_SAS!$B$2:$B$326,0),4) -> 1300000 | M62: =IF(AND(L62=K62,K62>0),"Max","") | N62: =IF(AND(L62<K62,L62=0),"No Levy but have Capacity","") | O62: =IF(L62>K62,"Exceedes Maximum Limit","") | Q62: =K62-L62 -> 668506 | U62: 1968506 | V62: =K62-U62 -> 0
A63: 2024 | B63: 13 | C63: 1211 | F63: 1211 | G63: Clarke | H63: =ROUND(SUMPRODUCT(SUMIF(Final!$G$4:$G$330,CashReserveLevy!D63:F63,Final!$C$4:$C$330)),0) -> 18287515 | I63: =ROUND(H63*0.2,0) -> 3657503 | J63: =ROUND(SUMPRODUCT(SUMIF(Final!$G$4:$G$330,CashReserveLevy!D63:F63,Final!$E$4:$E$330)),0) -> 504151 | K63: =IF(I63>J63,I63-J63,0) -> 3153352 | L63: =INDEX(ActualCRLevy_SAS!$A$2:$D$326,MATCH(CashReserveLevy!$C63,ActualCRLevy_SAS!$B$2:$B$326,0),4) -> 1211348 | M63: =IF(AND(L63=K63,K63>0),"Max","") | N63: =IF(AND(L63<K63,L63=0),"No Levy but have Capacity","") | O63: =IF(L63>K63,"Exceedes Maximum Limit","") | Q63: =K63-L63 -> 1942004 | U63: 3153352 | V63: =K63-U63 -> 0
A64: 2024 | B64: 07 | C64: 1215 | F64: 1215 | G64: Clarksville | H64: =ROUND(SUMPRODUCT(SUMIF(Final!$G$4:$G$330,CashReserveLevy!D64:F64,Final!$C$4:$C$330)),0) -> 4228077 | I64: =ROUND(H64*0.2,0) -> 845615 | J64: =ROUND(SUMPRODUCT(SUMIF(Final!$G$4:$G$330,CashReserveLevy!D64:F64,Final!$E$4:$E$330)),0) -> 960661 | K64: =IF(I64>J64,I64-J64,0) -> 0 | L64: =INDEX(ActualCRLevy_SAS!$A$2:$D$326,MATCH(CashReserveLevy!$C64,ActualCRLevy_SAS!$B$2:$B$326,0),4) -> 0 | M64: =IF(AND(L64=K64,K64>0),"Max","") | N64: =IF(AND(L64<K64,L64=0),"No Levy but have Capacity","") | O64: =IF(L64>K64,"Exceedes Maximum Limit","") | Q64: =K64-L64 -> 0 | U64: 0 | V64: =K64-U64 -> 0
A65: 2024 | B65: 05 | C65: 1218 | F65: 1218 | G65: Clay Central-Everly | H65: =ROUND(SUMPRODUCT(SUMIF(Final!$G$4:$G$330,CashReserveLevy!D65:F65,Final!$C$4:$C$330)),0) -> 3992568 | I65: =ROUND(H65*0.2,0) -> 798514 | J65: =ROUND(SUMPRODUCT(SUMIF(Final!$G$4:$G$330,CashReserveLevy!D65:F65,Final!$E$4:$E$330)),0) -> 1379301 | K65: =IF(I65>J65,I65-J65,0) -> 0 | L65: =INDEX(ActualCRLevy_SAS!$A$2:$D$326,MATCH(CashReserveLevy!$C65,ActualCRLevy_SAS!$B$2:$B$326,0),4) -> 0 | M65: =IF(AND(L65=K65,K65>0),"Max","") | N65: =IF(AND(L65<K65,L65=0),"No Levy but have Capacity","") | O65: =IF(L65>K65,"Exceedes Maximum Limit","") | Q65: =K65-L65 -> 0 | U65: 0 | V65: =K65-U65 -> 0
A66: 2024 | B66: 01 | C66: 2763 | F66: 2763 | G66: Clayton Ridge | H66: =ROUND(SUMPRODUCT(SUMIF(Final!$G$4:$G$330,CashReserveLevy!D66:F66,Final!$C$4:$C$330)),0) -> 13064172 | I66: =ROUND(H66*0.2,0) -> 2612834 | J66: =ROUND(SUMPRODUCT(SUMIF(Final!$G$4:$G$330,CashReserveLevy!D66:F66,Final!$E$4:$E$330)),0) -> 944483 | K66: =IF(I66>J66,I66-J66,0) -> 1668351 | L66: =INDEX(ActualCRLevy_SAS!$A$2:$D$326,MATCH(CashReserveLevy!$C66,ActualCRLevy_SAS!$B$2:$B$326,0),4) -> 100000 | M66: =IF(AND(L66=K66,K66>0),"Max","") | N66: =IF(AND(L66<K66,L66=0),"No Levy but have Capacity","") | O66: =IF(L66>K66,"Exceedes Maximum Limit","") | Q66: =K66-L66 -> 1568351 | U66: 1668351 | V66: =K66-U66 -> 0
A67: 2024 | B67: 10 | C67: 1221 | D67: 0216 | F67: 1221 | G67: Clear Creek-Amana | H67: =ROUND(SUMPRODUCT(SUMIF(Final!$G$4:$G$330,CashReserveLevy!D67:F67,Final!$C$4:$C$330)),0) -> 37470438 | I67: =ROUND(H67*0.2,0) -> 7494088 | J67: =ROUND(SUMPRODUCT(SUMIF(Final!$G$4:$G$330,CashReserveLevy!D67:F67,Final!$E$4:$E$330)),0) -> -909136 | K67: =IF(I67>J67,I67-J67,0) -> 8403224 | L67: =INDEX(ActualCRLevy_SAS!$A$2:$D$326,MATCH(CashReserveLevy!$C67,ActualCRLevy_SAS!$B$2:$B$326,0),4) -> 4007958 | M67: =IF(AND(L67=K67,K67>0),"Max","") | N67: =IF(AND(L67<K67,L67=0),"No Levy but have Capacity","") | O67: =IF(L67>K67,"Exceedes Maximum Limit","") | Q67: =K67-L67 -> 4395266 | U67: 8403224 | V67: =K67-U67 -> 0
A68: 2024 | B68: 07 | C68: 1233 | F68: 1233 | G68: Clear Lake | H68: =ROUND(SUMPRODUCT(SUMIF(Final!$G$4:$G$330,CashReserveLevy!D68:F68,Final!$C$4:$C$330)),0) -> 17352833 | I68: =ROUND(H68*0.2,0) -> 3470567 | J68: =ROUND(SUMPRODUCT(SUMIF(Final!$G$4:$G$330,CashReserveLevy!D68:F68,Final!$E$4:$E$330)),0) -> 4677478 | K68: =IF(I68>J68,I68-J68,0) -> 0 | L68: =INDEX(ActualCRLevy_SAS!$A$2:$D$326,MATCH(CashReserveLevy!$C68,ActualCRLevy_SAS!$B$2:$B$326,0),4) -> 0 | M68: =IF(AND(L68=K68,K68>0),"Max","") | N68: =IF(AND(L68<K68,L68=0),"No Levy but have Capacity","") | O68: =IF(L68>K68,"Exceedes Maximum Limit","") | Q68: =K68-L68 -> 0 | U68: 0 | V68: =K68-U68 -> 0
A69: 2024 | B69: 09 | C69: 1278 | F69: 1278 | G69: Clinton | H69: =ROUND(SUMPRODUCT(SUMIF(Final!$G$4:$G$330,CashReserveLevy!D69:F69,Final!$C$4:$C$330)),0) -> 49310052 | I69: =ROUND(H69*0.2,0) -> 9862010 | J69: =ROUND(SUMPRODUCT(SUMIF(Final!$G$4:$G$330,CashReserveLevy!D69:F69,Final!$E$4:$E$330)),0) -> 12196354 | K69: =IF(I69>J69,I69-J69,0) -> 0 | L69: =INDEX(ActualCRLevy_SAS!$A$2:$D$326,MATCH(CashReserveLevy!$C69,ActualCRLevy_SAS!$B$2:$B$326,0),4) -> 0 | M69: =IF(AND(L69=K69,K69>0),"Max","") | N69: =IF(AND(L69<K69,L69=0),"No Levy but have Capacity","") | O69: =IF(L69>K69,"Exceedes Maximum Limit","") | Q69: =K69-L69 -> 0 | U69: 0 | V69: =K69-U69 -> 0
A70: 2024 | B70: 11 | C70: 1332 | F70: 1332 | G70: Colfax-Mingo | H70: =ROUND(SUMPRODUCT(SUMIF(Final!$G$4:$G$330,CashReserveLevy!D70:F70,Final!$C$4:$C$330)),0) -> 10365807 | I70: =ROUND(H70*0.2,0) -> 2073161 | J70: =ROUND(SUMPRODUCT(SUMIF(Final!$G$4:$G$330,CashReserveLevy!D70:F70,Final!$E$4:$E$330)),0) -> 1293951 | K70: =IF(I70>J70,I70-J70,0) -> 779210 | L70: =INDEX(ActualCRLevy_SAS!$A$2:$D$326,MATCH(CashReserveLevy!$C70,ActualCRLevy_SAS!$B$2:$B$326,0),4) -> 779210 | M70: =IF(AND(L70=K70,K70>0),"Max","") -> Max | N70: =IF(AND(L70<K70,L70=0),"No Levy but have Capacity","") | O70: =IF(L70>K70,"Exceedes Maximum Limit","") | Q70: =K70-L70 -> 0 | U70: 779210 | V70: =K70-U70 -> 0
A71: 2024 | B71: 10 | C71: 1337 | F71: 1337 | G71: College Community | H71: =ROUND(SUMPRODUCT(SUMIF(Final!$G$4:$G$330,CashReserveLevy!D71:F71,Final!$C$4:$C$330)),0) -> 69631304 | I71: =ROUND(H71*0.2,0) -> 13926261 | J71: =ROUND(SUMPRODUCT(SUMIF(Final!$G$4:$G$330,CashReserveLevy!D71:F71,Final!$E$4:$E$330)),0) -> 13147650 | K71: =IF(I71>J71,I71-J71,0) -> 778611 | L71: =INDEX(ActualCRLevy_SAS!$A$2:$D$326,MATCH(CashReserveLevy!$C71,ActualCRLevy_SAS!$B$2:$B$326,0),4) -> 778611 | M71: =IF(AND(L71=K71,K71>0),"Max","") -> Max | N71: =IF(AND(L71<K71,L71=0),"No Levy but have Capacity","") | O71: =IF(L71>K71,"Exceedes Maximum Limit","") | Q71: =K71-L71 -> 0 | U71: 778611 | V71: =K71-U71 -> 0
A72: 2024 | B72: 11 | C72: 1350 | F72: 1350 | G72: Collins-Maxwell | H72: =ROUND(SUMPRODUCT(SUMIF(Final!$G$4:$G$330,CashReserveLevy!D72:F72,Final!$C$4:$C$330)),0) -> 6112293 | I72: =ROUND(H72*0.2,0) -> 1222459 | J72: =ROUND(SUMPRODUCT(SUMIF(Final!$G$4:$G$330,CashReserveLevy!D72:F72,Final!$E$4:$E$330)),0) -> 2298467 | K72: =IF(I72>J72,I72-J72,0) -> 0 | L72: =INDEX(ActualCRLevy_SAS!$A$2:$D$326,MATCH(CashReserveLevy!$C72,ActualCRLevy_SAS!$B$2:$B$326,0),4) -> 0 | M72: =IF(AND(L72=K72,K72>0),"Max","") | N72: =IF(AND(L72<K72,L72=0),"No Levy but have Capacity","") | O72: =IF(L72>K72,"Exceedes Maximum Limit","") | Q72: =K72-L72 -> 0 | U72: 0 | V72: =K72-U72 -> 0
A73: 2024 | B73: 11 | C73: 1359 | F73: 1359 | G73: Colo-Nesco | H73: =ROUND(SUMPRODUCT(SUMIF(Final!$G$4:$G$330,CashReserveLevy!D73:F73,Final!$C$4:$C$330)),0) -> 6342919 | I73: =ROUND(H73*0.2,0) -> 1268584 | J73: =ROUND(SUMPRODUCT(SUMIF(Final!$G$4:$G$330,CashReserveLevy!D73:F73,Final!$E$4:$E$330)),0) -> 578100 | K73: =IF(I73>J73,I73-J73,0) -> 690484 | L73: =INDEX(ActualCRLevy_SAS!$A$2:$D$326,MATCH(CashReserveLevy!$C73,ActualCRLevy_SAS!$B$2:$B$326,0),4) -> 460000 | M73: =IF(AND(L73=K73,K73>0),"Max","") | N73: =IF(AND(L73<K73,L73=0),"No Levy but have Capacity","") | O73: =IF(L73>K73,"Exceedes Maximum Limit","") | Q73: =K73-L73 -> 230484 | U73: 690484 | V73: =K73-U73 -> 0
A74: 2024 | B74: 09 | C74: 1368 | F74: 1368 | G74: Columbus | H74: =ROUND(SUMPRODUCT(SUMIF(Final!$G$4:$G$330,CashReserveLevy!D74:F74,Final!$C$4:$C$330)),0) -> 9396307 | I74: =ROUND(H74*0.2,0) -> 1879261 | J74: =ROUND(SUMPRODUCT(SUMIF(Final!$G$4:$G$330,CashReserveLevy!D74:F74,Final!$E$4:$E$330)),0) -> 4529087 | K74: =IF(I74>J74,I74-J74,0) -> 0 | L74: =INDEX(ActualCRLevy_SAS!$A$2:$D$326,MATCH(CashReserveLevy!$C74,ActualCRLevy_SAS!$B$2:$B$326,0),4) -> 0 | M74: =IF(AND(L74=K74,K74>0),"Max","") | N74: =IF(AND(L74<K74,L74=0),"No Levy but have Capacity","") | O74: =IF(L74>K74,"Exceedes Maximum Limit","") | Q74: =K74-L74 -> 0 | U74: 0 | V74: =K74-U74 -> 0
A75: 2024 | B75: 11 | C75: 1413 | F75: 1413 | G75: Coon Rapids-Bayard | H75: =ROUND(SUMPRODUCT(SUMIF(Final!$G$4:$G$330,CashReserveLevy!D75:F75,Final!$C$4:$C$330)),0) -> 5915096 | I75: =ROUND(H75*0.2,0) -> 1183019 | J75: =ROUND(SUMPRODUCT(SUMIF(Final!$G$4:$G$330,CashReserveLevy!D75:F75,Final!$E$4:$E$330)),0) -> 1991908 | K75: =IF(I75>J75,I75-J75,0) -> 0 | L75: =INDEX(ActualCRLevy_SAS!$A$2:$D$326,MATCH(CashReserveLevy!$C75,ActualCRLevy_SAS!$B$2:$B$326,0),4) -> 0 | M75: =IF(AND(L75=K75,K75>0),"Max","") | N75: =IF(AND(L75<K75,L75=0),"No Levy but have Capacity","") | O75: =IF(L75>K75,"Exceedes Maximum Limit","") | Q75: =K75-L75 -> 0 | U75: 0 | V75: =K75-U75 -> 0
A76: 2024 | B76: 13 | C76: 1431 | F76: 1431 | G76: Corning | H76: =ROUND(SUMPRODUCT(SUMIF(Final!$G$4:$G$330,CashReserveLevy!D76:F76,Final!$C$4:$C$330)),0) -> 6982419 | I76: =ROUND(H76*0.2,0) -> 1396484 | J76: =ROUND(SUMPRODUCT(SUMIF(Final!$G$4:$G$330,CashReserveLevy!D76:F76,Final!$E$4:$E$330)),0) -> 1929198 | K76: =IF(I76>J76,I76-J76,0) -> 0 | L76: =INDEX(ActualCRLevy_SAS!$A$2:$D$326,MATCH(CashReserveLevy!$C76,ActualCRLevy_SAS!$B$2:$B$326,0),4) -> 0 | M76: =IF(AND(L76=K76,K76>0),"Max","") | N76: =IF(AND(L76<K76,L76=0),"No Levy but have Capacity","") | O76: =IF(L76>K76,"Exceedes Maximum Limit","") | Q76: =K76-L76 -> 0 | U76: 0 | V76: =K76-U76 -> 0
A77: 2024 | B77: 13 | C77: 1476 | F77: 1476 | G77: Council Bluffs | H77: =ROUND(SUMPRODUCT(SUMIF(Final!$G$4:$G$330,CashReserveLevy!D77:F77,Final!$C$4:$C$330)),0) -> 136146160 | I77: =ROUND(H77*0.2,0) -> 27229232 | J77: =ROUND(SUMPRODUCT(SUMIF(Final!$G$4:$G$330,CashReserveLevy!D77:F77,Final!$E$4:$E$330)),0) -> 14417953 | K77: =IF(I77>J77,I77-J77,0) -> 12811279 | L77: =INDEX(ActualCRLevy_SAS!$A$2:$D$326,MATCH(CashReserveLevy!$C77,ActualCRLevy_SAS!$B$2:$B$326,0),4) -> 5299348 | M77: =IF(AND(L77=K77,K77>0),"Max","") | N77: =IF(AND(L77<K77,L77=0),"No Levy but have Capacity","") | O77: =IF(L77>K77,"Exceedes Maximum Limit","") | Q77: =K77-L77 -> 7511931 | U77: 12811279 | V77: =K77-U77 -> 0
A78: 2024 | B78: 13 | C78: 1503 | F78: 1503 | G78: Creston | H78: =ROUND(SUMPRODUCT(SUMIF(Final!$G$4:$G$330,CashReserveLevy!D78:F78,Final!$C$4:$C$330)),0) -> 19399770 | I78: =ROUND(H78*0.2,0) -> 3879954 | J78: =ROUND(SUMPRODUCT(SUMIF(Final!$G$4:$G$330,CashReserveLevy!D78:F78,Final!$E$4:$E$330)),0) -> 3719579 | K78: =IF(I78>J78,I78-J78,0) -> 160375 | L78: =INDEX(ActualCRLevy_SAS!$A$2:$D$326,MATCH(CashReserveLevy!$C78,ActualCRLevy_SAS!$B$2:$B$326,0),4) -> 160375 | M78: =IF(AND(L78=K78,K78>0),"Max","") -> Max | N78: =IF(AND(L78<K78,L78=0),"No Levy but have Capacity","") | O78: =IF(L78>K78,"Exceedes Maximum Limit","") | Q78: =K78-L78 -> 0 | U78: 160375 | V78: =K78-U78 -> 0
A79: 2024 | B79: 11 | C79: 1576 | F79: 1576 | G79: Dallas Center-Grimes | H79: =ROUND(SUMPRODUCT(SUMIF(Final!$G$4:$G$330,CashReserveLevy!D79:F79,Final!$C$4:$C$330)),0) -> 40756794 | I79: =ROUND(H79*0.2,0) -> 8151359 | J79: =ROUND(SUMPRODUCT(SUMIF(Final!$G$4:$G$330,CashReserveLevy!D79:F79,Final!$E$4:$E$330)),0) -> 5632048 | K79: =IF(I79>J79,I79-J79,0) -> 2519311 | L79: =INDEX(ActualCRLevy_SAS!$A$2:$D$326,MATCH(CashReserveLevy!$C79,ActualCRLevy_SAS!$B$2:$B$326,0),4) -> 2519311 | M79: =IF(AND(L79=K79,K79>0),"Max","") -> Max | N79: =IF(AND(L79<K79,L79=0),"No Levy but have Capacity","") | O79: =IF(L79>K79,"Exceedes Maximum Limit","") | Q79: =K79-L79 -> 0 | U79: 2519311 | V79: =K79-U79 -> 0
... A267: 2024 | B267: 11 | C267: 6094 | F267: 6094 | G267: Southeast Warren | H267: =ROUND(SUMPRODUCT(SUMIF(Final!$G$4:$G$330,CashReserveLevy!D267:F267,Final!$C$4:$C$330)),0) -> 7352560 | I267: =ROUND(H267*0.2,0) -> 1470512 | J267: =ROUND(SUMPRODUCT(SUMIF(Final!$G$4:$G$330,CashReserveLevy!D267:F267,Final!$E$4:$E$330)),0) -> 1281760 | K267: =IF(I267>J267,I267-J267,0) -> 188752 | L267: =INDEX(ActualCRLevy_SAS!$A$2:$D$326,MATCH(CashReserveLevy!$C267,ActualCRLevy_SAS!$B$2:$B$326,0),4) -> 188752 | M267: =IF(AND(L267=K267,K267>0),"Max","") -> Max | N267: =IF(AND(L267<K267,L267=0),"No Levy but have Capacity","") | O267: =IF(L267>K267,"Exceedes Maximum Limit","") | Q267: =K267-L267 -> 0 | U267: 188752 | V267: =K267-U267 -> 0
A268: 2024 | B268: 05 | C268: 6096 | D268: 5323 | F268: 6096 | G268: Southeast Valley | H268: =ROUND(SUMPRODUCT(SUMIF(Final!$G$4:$G$330,CashReserveLevy!D268:F268,Final!$C$4:$C$330)),0) -> 16781302 | I268: =ROUND(H268*0.2,0) -> 3356260 | J268: =ROUND(SUMPRODUCT(SUMIF(Final!$G$4:$G$330,CashReserveLevy!D268:F268,Final!$E$4:$E$330)),0) -> 9539358 | K268: =IF(I268>J268,I268-J268,0) -> 0 | L268: =INDEX(ActualCRLevy_SAS!$A$2:$D$326,MATCH(CashReserveLevy!$C268,ActualCRLevy_SAS!$B$2:$B$326,0),4) -> 0 | M268: =IF(AND(L268=K268,K268>0),"Max","") | N268: =IF(AND(L268<K268,L268=0),"No Levy but have Capacity","") | O268: =IF(L268>K268,"Exceedes Maximum Limit","") | Q268: =K268-L268 -> 0 | U268: 0 | V268: =K268-U268 -> 0
A269: 2024 | B269: 05 | C269: 6102 | F269: 6102 | G269: Spencer | H269: =ROUND(SUMPRODUCT(SUMIF(Final!$G$4:$G$330,CashReserveLevy!D269:F269,Final!$C$4:$C$330)),0) -> 27593789 | I269: =ROUND(H269*0.2,0) -> 5518758 | J269: =ROUND(SUMPRODUCT(SUMIF(Final!$G$4:$G$330,CashReserveLevy!D269:F269,Final!$E$4:$E$330)),0) -> 5579790 | K269: =IF(I269>J269,I269-J269,0) -> 0 | L269: =INDEX(ActualCRLevy_SAS!$A$2:$D$326,MATCH(CashReserveLevy!$C269,ActualCRLevy_SAS!$B$2:$B$326,0),4) -> 0 | M269: =IF(AND(L269=K269,K269>0),"Max","") | N269: =IF(AND(L269<K269,L269=0),"No Levy but have Capacity","") | O269: =IF(L269>K269,"Exceedes Maximum Limit","") | Q269: =K269-L269 -> 0 | U269: 0 | V269: =K269-U269 -> 0
A270: 2024 | B270: 05 | C270: 6120 | F270: 6120 | G270: Spirit Lake | H270: =ROUND(SUMPRODUCT(SUMIF(Final!$G$4:$G$330,CashReserveLevy!D270:F270,Final!$C$4:$C$330)),0) -> 14922720 | I270: =ROUND(H270*0.2,0) -> 2984544 | J270: =ROUND(SUMPRODUCT(SUMIF(Final!$G$4:$G$330,CashReserveLevy!D270:F270,Final!$E$4:$E$330)),0) -> 3760568 | K270: =IF(I270>J270,I270-J270,0) -> 0 | L270: =INDEX(ActualCRLevy_SAS!$A$2:$D$326,MATCH(CashReserveLevy!$C270,ActualCRLevy_SAS!$B$2:$B$326,0),4) -> 0 | M270: =IF(AND(L270=K270,K270>0),"Max","") | N270: =IF(AND(L270<K270,L270=0),"No Levy but have Capacity","") | O270: =IF(L270>K270,"Exceedes Maximum Limit","") | Q270: =K270-L270 -> 0 | U270: 0 | V270: =K270-U270 -> 0
A271: 2024 | B271: 10 | C271: 6138 | F271: 6138 | G271: Springville | H271: =ROUND(SUMPRODUCT(SUMIF(Final!$G$4:$G$330,CashReserveLevy!D271:F271,Final!$C$4:$C$330)),0) -> 5769100 | I271: =ROUND(H271*0.2,0) -> 1153820 | J271: =ROUND(SUMPRODUCT(SUMIF(Final!$G$4:$G$330,CashReserveLevy!D271:F271,Final!$E$4:$E$330)),0) -> 1420523 | K271: =IF(I271>J271,I271-J271,0) -> 0 | L271: =INDEX(ActualCRLevy_SAS!$A$2:$D$326,MATCH(CashReserveLevy!$C271,ActualCRLevy_SAS!$B$2:$B$326,0),4) -> 0 | M271: =IF(AND(L271=K271,K271>0),"Max","") | N271: =IF(AND(L271<K271,L271=0),"No Levy but have Capacity","") | O271: =IF(L271>K271,"Exceedes Maximum Limit","") | Q271: =K271-L271 -> 0 | U271: 0 | V271: =K271-U271 -> 0
A272: 2024 | B272: 07 | C272: 5751 | F272: 5751 | G272: St Ansgar | H272: =ROUND(SUMPRODUCT(SUMIF(Final!$G$4:$G$330,CashReserveLevy!D272:F272,Final!$C$4:$C$330)),0) -> 7754593 | I272: =ROUND(H272*0.2,0) -> 1550919 | J272: =ROUND(SUMPRODUCT(SUMIF(Final!$G$4:$G$330,CashReserveLevy!D272:F272,Final!$E$4:$E$330)),0) -> 1091300 | K272: =IF(I272>J272,I272-J272,0) -> 459619 | L272: =INDEX(ActualCRLevy_SAS!$A$2:$D$326,MATCH(CashReserveLevy!$C272,ActualCRLevy_SAS!$B$2:$B$326,0),4) -> 0 | M272: =IF(AND(L272=K272,K272>0),"Max","") | N272: =IF(AND(L272<K272,L272=0),"No Levy but have Capacity","") -> No Levy but have Capacity | O272: =IF(L272>K272,"Exceedes Maximum Limit","") | Q272: =K272-L272 -> 459619 | U272: 459619 | V272: =K272-U272 -> 0
A273: 2024 | B273: 13 | C273: 6165 | F273: 6165 | G273: Stanton | H273: =ROUND(SUMPRODUCT(SUMIF(Final!$G$4:$G$330,CashReserveLevy!D273:F273,Final!$C$4:$C$330)),0) -> 3498449 | I273: =ROUND(H273*0.2,0) -> 699690 | J273: =ROUND(SUMPRODUCT(SUMIF(Final!$G$4:$G$330,CashReserveLevy!D273:F273,Final!$E$4:$E$330)),0) -> 1258078 | K273: =IF(I273>J273,I273-J273,0) -> 0 | L273: =INDEX(ActualCRLevy_SAS!$A$2:$D$326,MATCH(CashReserveLevy!$C273,ActualCRLevy_SAS!$B$2:$B$326,0),4) -> 0 | M273: =IF(AND(L273=K273,K273>0),"Max","") | N273: =IF(AND(L273<K273,L273=0),"No Levy but have Capacity","") | O273: =IF(L273>K273,"Exceedes Maximum Limit","") | Q273: =K273-L273 -> 0 | U273: 0 | V273: =K273-U273 -> 0
A274: 2024 | B274: 01 | C274: 6175 | F274: 6175 | G274: Starmont | H274: =ROUND(SUMPRODUCT(SUMIF(Final!$G$4:$G$330,CashReserveLevy!D274:F274,Final!$C$4:$C$330)),0) -> 8673680 | I274: =ROUND(H274*0.2,0) -> 1734736 | J274: =ROUND(SUMPRODUCT(SUMIF(Final!$G$4:$G$330,CashReserveLevy!D274:F274,Final!$E$4:$E$330)),0) -> 3336393 | K274: =IF(I274>J274,I274-J274,0) -> 0 | L274: =INDEX(ActualCRLevy_SAS!$A$2:$D$326,MATCH(CashReserveLevy!$C274,ActualCRLevy_SAS!$B$2:$B$326,0),4) -> 0 | M274: =IF(AND(L274=K274,K274>0),"Max","") | N274: =IF(AND(L274<K274,L274=0),"No Levy but have Capacity","") | O274: =IF(L274>K274,"Exceedes Maximum Limit","") | Q274: =K274-L274 -> 0 | U274: 0 | V274: =K274-U274 -> 0
A275: 2024 | B275: 05 | C275: 6219 | F275: 6219 | G275: Storm Lake | H275: =ROUND(SUMPRODUCT(SUMIF(Final!$G$4:$G$330,CashReserveLevy!D275:F275,Final!$C$4:$C$330)),0) -> 35522895 | I275: =ROUND(H275*0.2,0) -> 7104579 | J275: =ROUND(SUMPRODUCT(SUMIF(Final!$G$4:$G$330,CashReserveLevy!D275:F275,Final!$E$4:$E$330)),0) -> 5719810 | K275: =IF(I275>J275,I275-J275,0) -> 1384769 | L275: =INDEX(ActualCRLevy_SAS!$A$2:$D$326,MATCH(CashReserveLevy!$C275,ActualCRLevy_SAS!$B$2:$B$326,0),4) -> 439775 | M275: =IF(AND(L275=K275,K275>0),"Max","") | N275: =IF(AND(L275<K275,L275=0),"No Levy but have Capacity","") | O275: =IF(L275>K275,"Exceedes Maximum Limit","") | Q275: =K275-L275 -> 944994 | U275: 1384769 | V275: =K275-U275 -> 0
A276: 2024 | B276: 05 | C276: 6246 | F276: 6246 | G276: Stratford | H276: =ROUND(SUMPRODUCT(SUMIF(Final!$G$4:$G$330,CashReserveLevy!D276:F276,Final!$C$4:$C$330)),0) -> 2242175 | I276: =ROUND(H276*0.2,0) -> 448435 | J276: =ROUND(SUMPRODUCT(SUMIF(Final!$G$4:$G$330,CashReserveLevy!D276:F276,Final!$E$4:$E$330)),0) -> 392868 | K276: =IF(I276>J276,I276-J276,0) -> 55567 | L276: =INDEX(ActualCRLevy_SAS!$A$2:$D$326,MATCH(CashReserveLevy!$C276,ActualCRLevy_SAS!$B$2:$B$326,0),4) -> 55567 | M276: =IF(AND(L276=K276,K276>0),"Max","") -> Max | N276: =IF(AND(L276<K276,L276=0),"No Levy but have Capacity","") | O276: =IF(L276>K276,"Exceedes Maximum Limit","") | Q276: =K276-L276 -> 0 | U276: 55567 | V276: =K276-U276 -> 0
A277: 2024 | B277: 07 | C277: 6273 | F277: 6273 | G277: Sumner-Fredericksburg | H277: =ROUND(SUMPRODUCT(SUMIF(Final!$G$4:$G$330,CashReserveLevy!D277:F277,Final!$C$4:$C$330)),0) -> 10331509 | I277: =ROUND(H277*0.2,0) -> 2066302 | J277: =ROUND(SUMPRODUCT(SUMIF(Final!$G$4:$G$330,CashReserveLevy!D277:F277,Final!$E$4:$E$330)),0) -> 1196914 | K277: =IF(I277>J277,I277-J277,0) -> 869388 | L277: =INDEX(ActualCRLevy_SAS!$A$2:$D$326,MATCH(CashReserveLevy!$C277,ActualCRLevy_SAS!$B$2:$B$326,0),4) -> 400000 | M277: =IF(AND(L277=K277,K277>0),"Max","") | N277: =IF(AND(L277<K277,L277=0),"No Levy but have Capacity","") | O277: =IF(L277>K277,"Exceedes Maximum Limit","") | Q277: =K277-L277 -> 469388 | U277: 869388 | V277: =K277-U277 -> 0
A278: 2024 | B278: 10 | C278: 6408 | F278: 6408 | G278: Tipton | H278: =ROUND(SUMPRODUCT(SUMIF(Final!$G$4:$G$330,CashReserveLevy!D278:F278,Final!$C$4:$C$330)),0) -> 11372773 | I278: =ROUND(H278*0.2,0) -> 2274555 | J278: =ROUND(SUMPRODUCT(SUMIF(Final!$G$4:$G$330,CashReserveLevy!D278:F278,Final!$E$4:$E$330)),0) -> 1962235 | K278: =IF(I278>J278,I278-J278,0) -> 312320 | L278: =INDEX(ActualCRLevy_SAS!$A$2:$D$326,MATCH(CashReserveLevy!$C278,ActualCRLevy_SAS!$B$2:$B$326,0),4) -> 312320 | M278: =IF(AND(L278=K278,K278>0),"Max","") -> Max | N278: =IF(AND(L278<K278,L278=0),"No Levy but have Capacity","") | O278: =IF(L278>K278,"Exceedes Maximum Limit","") | Q278: =K278-L278 -> 0 | U278: 312320 | V278: =K278-U278 -> 0
A279: 2024 | B279: 13 | C279: 6453 | F279: 6453 | G279: Treynor | H279: =ROUND(SUMPRODUCT(SUMIF(Final!$G$4:$G$330,CashReserveLevy!D279:F279,Final!$C$4:$C$330)),0) -> 8846525 | I279: =ROUND(H279*0.2,0) -> 1769305 | J279: =ROUND(SUMPRODUCT(SUMIF(Final!$G$4:$G$330,CashReserveLevy!D279:F279,Final!$E$4:$E$330)),0) -> 2342566 | K279: =IF(I279>J279,I279-J279,0) -> 0 | L279: =INDEX(ActualCRLevy_SAS!$A$2:$D$326,MATCH(CashReserveLevy!$C279,ActualCRLevy_SAS!$B$2:$B$326,0),4) -> 0 | M279: =IF(AND(L279=K279,K279>0),"Max","") | N279: =IF(AND(L279<K279,L279=0),"No Levy but have Capacity","") | O279: =IF(L279>K279,"Exceedes Maximum Limit","") | Q279: =K279-L279 -> 0 | U279: 0 | V279: =K279-U279 -> 0
A280: 2024 | B280: 13 | C280: 6460 | F280: 6460 | G280: Tri-Center | H280: =ROUND(SUMPRODUCT(SUMIF(Final!$G$4:$G$330,CashReserveLevy!D280:F280,Final!$C$4:$C$330)),0) -> 8449476 | I280: =ROUND(H280*0.2,0) -> 1689895 | J280: =ROUND(SUMPRODUCT(SUMIF(Final!$G$4:$G$330,CashReserveLevy!D280:F280,Final!$E$4:$E$330)),0) -> 3247417 | K280: =IF(I280>J280,I280-J280,0) -> 0 | L280: =INDEX(ActualCRLevy_SAS!$A$2:$D$326,MATCH(CashReserveLevy!$C280,ActualCRLevy_SAS!$B$2:$B$326,0),4) -> 0 | M280: =IF(AND(L280=K280,K280>0),"Max","") | N280: =IF(AND(L280<K280,L280=0),"No Levy but have Capacity","") | O280: =IF(L280>K280,"Exceedes Maximum Limit","") | Q280: =K280-L280 -> 0 | U280: 0 | V280: =K280-U280 -> 0
... A301: 2024 | B301: 15 | C301: 6854 | F301: 6854 | G301: Wayne | H301: =ROUND(SUMPRODUCT(SUMIF(Final!$G$4:$G$330,CashReserveLevy!D301:F301,Final!$C$4:$C$330)),0) -> 7743602 | I301: =ROUND(H301*0.2,0) -> 1548720 | J301: =ROUND(SUMPRODUCT(SUMIF(Final!$G$4:$G$330,CashReserveLevy!D301:F301,Final!$E$4:$E$330)),0) -> 4791477 | K301: =IF(I301>J301,I301-J301,0) -> 0 | L301: =INDEX(ActualCRLevy_SAS!$A$2:$D$326,MATCH(CashReserveLevy!$C301,ActualCRLevy_SAS!$B$2:$B$326,0),4) -> 0 | M301: =IF(AND(L301=K301,K301>0),"Max","") | N301: =IF(AND(L301<K301,L301=0),"No Levy but have Capacity","") | O301: =IF(L301>K301,"Exceedes Maximum Limit","") | Q301: =K301-L301 -> 0 | U301: 0 | V301: =K301-U301 -> 0
A302: 2024 | B302: 05 | C302: 6867 | D302: 4775 | F302: 6867 | G302: Webster City | H302: =ROUND(SUMPRODUCT(SUMIF(Final!$G$4:$G$330,CashReserveLevy!D302:F302,Final!$C$4:$C$330)),0) -> 23820681 | I302: =ROUND(H302*0.2,0) -> 4764136 | J302: =ROUND(SUMPRODUCT(SUMIF(Final!$G$4:$G$330,CashReserveLevy!D302:F302,Final!$E$4:$E$330)),0) -> 4889693 | K302: =IF(I302>J302,I302-J302,0) -> 0 | L302: =INDEX(ActualCRLevy_SAS!$A$2:$D$326,MATCH(CashReserveLevy!$C302,ActualCRLevy_SAS!$B$2:$B$326,0),4) -> 0 | M302: =IF(AND(L302=K302,K302>0),"Max","") | N302: =IF(AND(L302<K302,L302=0),"No Levy but have Capacity","") | O302: =IF(L302>K302,"Exceedes Maximum Limit","") | Q302: =K302-L302 -> 0 | U302: 116019 | V302: =K302-U302 -> -116019
A303: 2024 | B303: 05 | C303: 6921 | F303: 6921 | G303: West Bend-Mallard | H303: =ROUND(SUMPRODUCT(SUMIF(Final!$G$4:$G$330,CashReserveLevy!D303:F303,Final!$C$4:$C$330)),0) -> 4688480 | I303: =ROUND(H303*0.2,0) -> 937696 | J303: =ROUND(SUMPRODUCT(SUMIF(Final!$G$4:$G$330,CashReserveLevy!D303:F303,Final!$E$4:$E$330)),0) -> 1518898 | K303: =IF(I303>J303,I303-J303,0) -> 0 | L303: =INDEX(ActualCRLevy_SAS!$A$2:$D$326,MATCH(CashReserveLevy!$C303,ActualCRLevy_SAS!$B$2:$B$326,0),4) -> 0 | M303: =IF(AND(L303=K303,K303>0),"Max","") | N303: =IF(AND(L303<K303,L303=0),"No Levy but have Capacity","") | O303: =IF(L303>K303,"Exceedes Maximum Limit","") | Q303: =K303-L303 -> 0 | U303: 0 | V303: =K303-U303 -> 0
A304: 2024 | B304: 10 | C304: 6930 | F304: 6930 | G304: West Branch | H304: =ROUND(SUMPRODUCT(SUMIF(Final!$G$4:$G$330,CashReserveLevy!D304:F304,Final!$C$4:$C$330)),0) -> 10390562 | I304: =ROUND(H304*0.2,0) -> 2078112 | J304: =ROUND(SUMPRODUCT(SUMIF(Final!$G$4:$G$330,CashReserveLevy!D304:F304,Final!$E$4:$E$330)),0) -> 1711086 | K304: =IF(I304>J304,I304-J304,0) -> 367026 | L304: =INDEX(ActualCRLevy_SAS!$A$2:$D$326,MATCH(CashReserveLevy!$C304,ActualCRLevy_SAS!$B$2:$B$326,0),4) -> 367026 | M304: =IF(AND(L304=K304,K304>0),"Max","") -> Max | N304: =IF(AND(L304<K304,L304=0),"No Levy but have Capacity","") | O304: =IF(L304>K304,"Exceedes Maximum Limit","") | Q304: =K304-L304 -> 0 | U304: 367026 | V304: =K304-U304 -> 0
A305: 2024 | B305: 15 | C305: 6937 | F305: 6937 | G305: West Burlington | H305: =ROUND(SUMPRODUCT(SUMIF(Final!$G$4:$G$330,CashReserveLevy!D305:F305,Final!$C$4:$C$330)),0) -> 10352362 | I305: =ROUND(H305*0.2,0) -> 2070472 | J305: =ROUND(SUMPRODUCT(SUMIF(Final!$G$4:$G$330,CashReserveLevy!D305:F305,Final!$E$4:$E$330)),0) -> 2292205 | K305: =IF(I305>J305,I305-J305,0) -> 0 | L305: =INDEX(ActualCRLevy_SAS!$A$2:$D$326,MATCH(CashReserveLevy!$C305,ActualCRLevy_SAS!$B$2:$B$326,0),4) -> 0 | M305: =IF(AND(L305=K305,K305>0),"Max","") | N305: =IF(AND(L305<K305,L305=0),"No Levy but have Capacity","") | O305: =IF(L305>K305,"Exceedes Maximum Limit","") | Q305: =K305-L305 -> 0 | U305: 0 | V305: =K305-U305 -> 0
A306: 2024 | B306: 01 | C306: 6943 | F306: 6943 | G306: West Central | H306: =ROUND(SUMPRODUCT(SUMIF(Final!$G$4:$G$330,CashReserveLevy!D306:F306,Final!$C$4:$C$330)),0) -> 4353968 | I306: =ROUND(H306*0.2,0) -> 870794 | J306: =ROUND(SUMPRODUCT(SUMIF(Final!$G$4:$G$330,CashReserveLevy!D306:F306,Final!$E$4:$E$330)),0) -> 1107736 | K306: =IF(I306>J306,I306-J306,0) -> 0 | L306: =INDEX(ActualCRLevy_SAS!$A$2:$D$326,MATCH(CashReserveLevy!$C306,ActualCRLevy_SAS!$B$2:$B$326,0),4) -> 0 | M306: =IF(AND(L306=K306,K306>0),"Max","") | N306: =IF(AND(L306<K306,L306=0),"No Levy but have Capacity","") | O306: =IF(L306>K306,"Exceedes Maximum Limit","") | Q306: =K306-L306 -> 0 | U306: 0 | V306: =K306-U306 -> 0
A307: 2024 | B307: 11 | C307: 6264 | F307: 6264 | G307: West Central Valley | H307: =ROUND(SUMPRODUCT(SUMIF(Final!$G$4:$G$330,CashReserveLevy!D307:F307,Final!$C$4:$C$330)),0) -> 11211968 | I307: =ROUND(H307*0.2,0) -> 2242394 | J307: =ROUND(SUMPRODUCT(SUMIF(Final!$G$4:$G$330,CashReserveLevy!D307:F307,Final!$E$4:$E$330)),0) -> 3451312 | K307: =IF(I307>J307,I307-J307,0) -> 0 | L307: =INDEX(ActualCRLevy_SAS!$A$2:$D$326,MATCH(CashReserveLevy!$C307,ActualCRLevy_SAS!$B$2:$B$326,0),4) -> 0 | M307: =IF(AND(L307=K307,K307>0),"Max","") | N307: =IF(AND(L307<K307,L307=0),"No Levy but have Capacity","") | O307: =IF(L307>K307,"Exceedes Maximum Limit","") | Q307: =K307-L307 -> 0 | U307: 0 | V307: =K307-U307 -> 0
A308: 2024 | B308: 01 | C308: 6950 | F308: 6950 | G308: West Delaware Co | H308: =ROUND(SUMPRODUCT(SUMIF(Final!$G$4:$G$330,CashReserveLevy!D308:F308,Final!$C$4:$C$330)),0) -> 18577656 | I308: =ROUND(H308*0.2,0) -> 3715531 | J308: =ROUND(SUMPRODUCT(SUMIF(Final!$G$4:$G$330,CashReserveLevy!D308:F308,Final!$E$4:$E$330)),0) -> 906250 | K308: =IF(I308>J308,I308-J308,0) -> 2809281 | L308: =INDEX(ActualCRLevy_SAS!$A$2:$D$326,MATCH(CashReserveLevy!$C308,ActualCRLevy_SAS!$B$2:$B$326,0),4) -> 503618 | M308: =IF(AND(L308=K308,K308>0),"Max","") | N308: =IF(AND(L308<K308,L308=0),"No Levy but have Capacity","") | O308: =IF(L308>K308,"Exceedes Maximum Limit","") | Q308: =K308-L308 -> 2305663 | U308: 2809281 | V308: =K308-U308 -> 0
A309: 2024 | B309: 11 | C309: 6957 | F309: 6957 | G309: West Des Moines | H309: =ROUND(SUMPRODUCT(SUMIF(Final!$G$4:$G$330,CashReserveLevy!D309:F309,Final!$C$4:$C$330)),0) -> 122209790 | I309: =ROUND(H309*0.2,0) -> 24441958 | J309: =ROUND(SUMPRODUCT(SUMIF(Final!$G$4:$G$330,CashReserveLevy!D309:F309,Final!$E$4:$E$330)),0) -> 20326638 | K309: =IF(I309>J309,I309-J309,0) -> 4115320 | L309: =INDEX(ActualCRLevy_SAS!$A$2:$D$326,MATCH(CashReserveLevy!$C309,ActualCRLevy_SAS!$B$2:$B$326,0),4) -> 4115320 | M309: =IF(AND(L309=K309,K309>0),"Max","") -> Max | N309: =IF(AND(L309<K309,L309=0),"No Levy but have Capacity","") | O309: =IF(L309>K309,"Exceedes Maximum Limit","") | Q309: =K309-L309 -> 0 | U309: 4115320 | V309: =K309-U309 -> 0
A310: 2024 | B310: 07 | C310: 5922 | F310: 5922 | G310: West Fork | H310: =ROUND(SUMPRODUCT(SUMIF(Final!$G$4:$G$330,CashReserveLevy!D310:F310,Final!$C$4:$C$330)),0) -> 9946599 | I310: =ROUND(H310*0.2,0) -> 1989320 | J310: =ROUND(SUMPRODUCT(SUMIF(Final!$G$4:$G$330,CashReserveLevy!D310:F310,Final!$E$4:$E$330)),0) -> 1627859 | K310: =IF(I310>J310,I310-J310,0) -> 361461 | L310: =INDEX(ActualCRLevy_SAS!$A$2:$D$326,MATCH(CashReserveLevy!$C310,ActualCRLevy_SAS!$B$2:$B$326,0),4) -> 360000 | M310: =IF(AND(L310=K310,K310>0),"Max","") | N310: =IF(AND(L310<K310,L310=0),"No Levy but have Capacity","") | O310: =IF(L310>K310,"Exceedes Maximum Limit","") | Q310: =K310-L310 -> 1461 | U310: 361461 | V310: =K310-U310 -> 0
A311: 2024 | B311: 07 | C311: 0819 | F311: 0819 | G311: West Hancock | H311: =ROUND(SUMPRODUCT(SUMIF(Final!$G$4:$G$330,CashReserveLevy!D311:F311,Final!$C$4:$C$330)),0) -> 7456397 | I311: =ROUND(H311*0.2,0) -> 1491279 | J311: =ROUND(SUMPRODUCT(SUMIF(Final!$G$4:$G$330,CashReserveLevy!D311:F311,Final!$E$4:$E$330)),0) -> 1654986 | K311: =IF(I311>J311,I311-J311,0) -> 0 | L311: =INDEX(ActualCRLevy_SAS!$A$2:$D$326,MATCH(CashReserveLevy!$C311,ActualCRLevy_SAS!$B$2:$B$326,0),4) -> 0 | M311: =IF(AND(L311=K311,K311>0),"Max","") | N311: =IF(AND(L311<K311,L311=0),"No Levy but have Capacity","") | O311: =IF(L311>K311,"Exceedes Maximum Limit","") | Q311: =K311-L311 -> 0 | U311: 0 | V311: =K311-U311 -> 0
A312: 2024 | B312: 13 | C312: 6969 | F312: 6969 | G312: West Harrison | H312: =ROUND(SUMPRODUCT(SUMIF(Final!$G$4:$G$330,CashReserveLevy!D312:F312,Final!$C$4:$C$330)),0) -> 5285845 | I312: =ROUND(H312*0.2,0) -> 1057169 | J312: =ROUND(SUMPRODUCT(SUMIF(Final!$G$4:$G$330,CashReserveLevy!D312:F312,Final!$E$4:$E$330)),0) -> 893466 | K312: =IF(I312>J312,I312-J312,0) -> 163703 | L312: =INDEX(ActualCRLevy_SAS!$A$2:$D$326,MATCH(CashReserveLevy!$C312,ActualCRLevy_SAS!$B$2:$B$326,0),4) -> 163703 | M312: =IF(AND(L312=K312,K312>0),"Max","") -> Max | N312: =IF(AND(L312<K312,L312=0),"No Levy but have Capacity","") | O312: =IF(L312>K312,"Exceedes Maximum Limit","") | Q312: =K312-L312 -> 0 | U312: 163703 | V312: =K312-U312 -> 0
A313: 2024 | B313: 09 | C313: 6975 | F313: 6975 | G313: West Liberty | H313: =ROUND(SUMPRODUCT(SUMIF(Final!$G$4:$G$330,CashReserveLevy!D313:F313,Final!$C$4:$C$330)),0) -> 15082829 | I313: =ROUND(H313*0.2,0) -> 3016566 | J313: =ROUND(SUMPRODUCT(SUMIF(Final!$G$4:$G$330,CashReserveLevy!D313:F313,Final!$E$4:$E$330)),0) -> 7318665 | K313: =IF(I313>J313,I313-J313,0) -> 0 | L313: =INDEX(ActualCRLevy_SAS!$A$2:$D$326,MATCH(CashReserveLevy!$C313,ActualCRLevy_SAS!$B$2:$B$326,0),4) -> 0 | M313: =IF(AND(L313=K313,K313>0),"Max","") | N313: =IF(AND(L313<K313,L313=0),"No Levy but have Capacity","") | O313: =IF(L313>K313,"Exceedes Maximum Limit","") | Q313: =K313-L313 -> 0 | U313: 0 | V313: =K313-U313 -> 0
A314: 2024 | B314: 12 | C314: 6983 | F314: 6983 | G314: West Lyon | H314: =ROUND(SUMPRODUCT(SUMIF(Final!$G$4:$G$330,CashReserveLevy!D314:F314,Final!$C$4:$C$330)),0) -> 11214860 | I314: =ROUND(H314*0.2,0) -> 2242972 | J314: =ROUND(SUMPRODUCT(SUMIF(Final!$G$4:$G$330,CashReserveLevy!D314:F314,Final!$E$4:$E$330)),0) -> 2053713 | K314: =IF(I314>J314,I314-J314,0) -> 189259 | L314: =INDEX(ActualCRLevy_SAS!$A$2:$D$326,MATCH(CashReserveLevy!$C314,ActualCRLevy_SAS!$B$2:$B$326,0),4) -> 103920 | M314: =IF(AND(L314=K314,K314>0),"Max","") | N314: =IF(AND(L314<K314,L314=0),"No Levy but have Capacity","") | O314: =IF(L314>K314,"Exceedes Maximum Limit","") | Q314: =K314-L314 -> 85339 | U314: 189259 | V314: =K314-U314 -> 0
... A327: 2024 | B327: 11 | C327: 7110 | F327: 7110 | G327: Woodward-Granger | H327: =ROUND(SUMPRODUCT(SUMIF(Final!$G$4:$G$330,CashReserveLevy!D327:F327,Final!$C$4:$C$330)),0) -> 16694725 | I327: =ROUND(H327*0.2,0) -> 3338945 | J327: =ROUND(SUMPRODUCT(SUMIF(Final!$G$4:$G$330,CashReserveLevy!D327:F327,Final!$E$4:$E$330)),0) -> 3166775 | K327: =IF(I327>J327,I327-J327,0) -> 172170 | L327: =INDEX(ActualCRLevy_SAS!$A$2:$D$326,MATCH(CashReserveLevy!$C327,ActualCRLevy_SAS!$B$2:$B$326,0),4) -> 172170 | M327: =IF(AND(L327=K327,K327>0),"Max","") -> Max | N327: =IF(AND(L327<K327,L327=0),"No Levy but have Capacity","") | O327: =IF(L327>K327,"Exceedes Maximum Limit","") | Q327: =K327-L327 -> 0 | U327: 172170 | V327: =K327-U327 -> 0
H328: =SUM(H3:H327) -> 6676211041 | I328: =SUM(I3:I327) -> 1335242211 | J328: =SUM(J3:J327) -> 1359115787 | K328: =SUM(K3:K327) -> 248818372 | L328: =SUM(L3:L327) -> 165940551
H331: =Final!C331 -> 6.676211e+09 | J331: =Final!E331 -> 1.3591158e+09
H332: =H331-H328 -> -5.79 | J332: =J331-J328 -> -7.5099995
K334: Number of Districts unable to levy for Cash Reserve: | L334: =COUNTIF($K$3:$K$327,0) -> 180
K335: Number of Districts Levying for Cash Reserve: | L335: =COUNTIF($L$3:$L$327,">0") -> 143
K336: Number of Districts Not Levying for Cash Reserve but have the Ability: | L336: =COUNTIF($N$3:$N$327,"No Levy but have Capacity") -> 2
K337: Number of Districts Levying Maximum for Cash Reserve Levy: | L337: =COUNTIF($M$3:$M$327,"Max") -> 66
J339: Fiscal Year | K339: Total Cash Reserve Levy | L339: Percent Change
J340: 2002 | K340: 68317829
J341: 2003 | K341: 92775492 | L341: =(K341-K340)/K340 -> 0.35799825
J342: 2004 | K342: 93735656 | L342: =(K342-K341)/K341 -> 0.010349328
J343: 2005 | K343: 96591952 | L343: =(K343-K342)/K342 -> 0.03047182
J344: 2006 | K344: 97853720 | L344: =(K344-K343)/K343 -> 0.013062869
J345: 2007 | K345: 119543594 | L345: =(K345-K344)/K344 -> 0.2216561
J346: 2008 | K346: 133598310 | L346: =(K346-K345)/K345 -> 0.1175698
J347: 2009 | K347: 154418943 | L347: =(K347-K346)/K346 -> 0.15584503
J348: 2010 | K348: 194327650 | L348: =(K348-K347)/K347 -> 0.25844437
J349: 2011 | K349: 298278645 | L349: =(K349-K348)/K348 -> 0.53492642
J350: 2012 | K350: 274120078 | L350: =(K350-K349)/K349 -> -0.080993284
J351: 2013 | K351: 231935729 | L351: =(K351-K350)/K350 -> -0.15389004
J352: 2014 | K352: 190880844 | L352: =(K352-K351)/K351 -> -0.17700975
... J362: 2024 | K362: 165940551 | L362: =(K362-K361)/K361 -> -0.13440043

Sheet Final
A1: FY22 Expenditures, Miscellaneous Income, Assigned/Unassigned Fund Balace, Total Fund Balance
A3: District Number | B3: District Name | C3: Expenditures | D3: Miscellaneous Income | E3: Assigned & Unassigned Fund Balance | F3: Total Fund Balance
A4: 9 | B4: AGWSR Comm School District | C4: 9940866.8 | D4: 1692562.9 | E4: 1221374.1 | F4: 1752298.7 | G4: 0009
A5: 18 | B5: Adair-Casey Comm School District | C5: 4593649.2 | D5: 1307082.4 | E5: 1435066.7 | F5: 1586394.9 | G5: 0018
A6: 27 | B6: Adel DeSoto Minburn Comm School District | C6: 24295219 | D6: 3671226.2 | E6: 5188021.8 | F6: 5815698.4 | G6: 0027
A7: 63 | B7: Akron Westfield Comm School District | C7: 8004280.8 | D7: 1613684.4 | E7: 1785711.7 | F7: 2097711.8 | G7: 0063
A8: 72 | B8: Albert City-Truesdale Comm School District | C8: 2809844.1 | D8: 487922.24 | E8: 1134405.5 | F8: 1314319 | G8: 0072
A9: 81 | B9: Albia Comm School District | C9: 14271156 | D9: 1853512.3 | E9: 4071860 | F9: 4458548.5 | G9: 0081
A10: 99 | B10: Alburnett Comm School District | C10: 8476602.7 | D10: 2566129.1 | E10: 1952461.9 | F10: 2003283.3 | G10: 0099
A11: 108 | B11: Alden Comm School District | C11: 3876813.6 | D11: 663383.29 | E11: 127456.8 | F11: 258367.39 | G11: 0108
A12: 126 | B12: Algona Comm School District | C12: 20353072 | D12: 4375610.9 | E12: 2697748.5 | F12: 3199103.3 | G12: 0126
A13: 135 | B13: Allamakee Comm School District | C13: 14603162 | D13: 2488267.8 | E13: 3081423.9 | F13: 3830037.7 | G13: 0135
A14: 153 | B14: North Butler Comm School District | C14: 8290295.9 | D14: 1769662.3 | E14: 1385554.1 | F14: 1627013.1 | G14: 0153
A15: 171 | B15: Alta-Aurelia Comm School District | C15: 11385819 | D15: 1873321.4 | E15: 1634401.8 | F15: 2327576.6 | G15: 0171
... A330: 7110 | B330: Woodward-Granger Comm School District | C330: 16694725 | D330: 5780303.8 | E330: 3166774.6 | F330: 3524464.9 | G330: 7110
C331: =SUM(C4:C330) -> 6.676211e+09 | D331: =SUM(D4:D330) -> 1.2068638e+09 | E331: =SUM(E4:E330) -> 1.3591158e+09 | F331: =SUM(F4:F330) -> 1.5855201e+09

Sheet ActualCRLevy_SAS
A1: FiscalYear | B1: Dist | C1: Label | D1: Final Cash Reserve Levy | E1: Final 6-15-2023
A2: 2024 | B2: 0009 | C2: AGWSR | D2: 370000
A3: 2024 | B3: 0441 | C3: AHSTW | D3: 0
A4: 2024 | B4: 0018 | C4: Adair-Casey | D4: 0
A5: 2024 | B5: 0027 | C5: Adel-Desoto-Minburn | D5: 0
A6: 2024 | B6: 0063 | C6: Akron-Westfield | D6: 0
A7: 2024 | B7: 0072 | C7: Albert City-Truesdale | D7: 0
A8: 2024 | B8: 0081 | C8: Albia | D8: 0
A9: 2024 | B9: 0099 | C9: Alburnett | D9: 0
A10: 2024 | B10: 0108 | C10: Alden | D10: 400000
A11: 2024 | B11: 0126 | C11: Algona | D11: 895900
A12: 2024 | B12: 0135 | C12: Allamakee | D12: 0
A13: 2024 | B13: 0171 | C13: Alta-Aurelia | D13: 350000
... A326: 2024 | B326: 7110 | C326: Woodward-Granger | D326: 172170
