Workbook
Name C_I_Prorate: '[1]C I Est'!$I$5:$I$105
Name DistrictName: [1]SNAME!$D$3:$D$329
Name frl1819_g1to6cep: #REF!
Name lunch1920_g1to6: lunch1920_g1to6!$B$2:$H$935

Sheet Summary
A1: =CONCATENATE("FY ",Calculation!$P$1," At-Risk Supplementary Weighting Formula") -> FY 2021 At-Risk Supplementary Weighting Formula | C1: At-Risk Weighting
A2: Final | C2: Free/Red. Lunch | D2: Enrollment | E2: Subtotal Line 3.10 | G2: =CONCATENATE("FY ",Calculation!$P$1, " District Cost Per Pupil") -> FY 2021 District Cost Per Pupil | H2: Dollars Generated
A3: =StartupfileInput!A2 -> 0009 | B3: =INDEX(Calculation!$A$4:$M$330,MATCH(Summary!$A3,Calculation!$A$4:$A$330,0),3) -> AGWSR | C3: =INDEX(Calculation!$A$4:$M$330,MATCH(Summary!$A3,Calculation!$A$4:$A$330,0),6) -> 1.88 | D3: =INDEX(Calculation!$A$4:$M$330,MATCH(Summary!$A3,Calculation!$A$4:$A$330,0),7) -> 1.316 | E3: =SUM(C3:D3) -> 3.196 | G3: =INDEX(Calculation!$A$4:$M$330,MATCH(Summary!$A3,Calculation!$A$4:$A$330,0),10) -> 7138 | H3: =ROUND(E3*G3,0) -> 22813
A4: =StartupfileInput!A3 -> 0441 | B4: =INDEX(Calculation!$A$4:$M$330,MATCH(Summary!$A4,Calculation!$A$4:$A$330,0),3) -> AHSTW | C4: =INDEX(Calculation!$A$4:$M$330,MATCH(Summary!$A4,Calculation!$A$4:$A$330,0),6) -> 2.101 | D4: =INDEX(Calculation!$A$4:$M$330,MATCH(Summary!$A4,Calculation!$A$4:$A$330,0),7) -> 1.593 | E4: =SUM(C4:D4) -> 3.694 | G4: =INDEX(Calculation!$A$4:$M$330,MATCH(Summary!$A4,Calculation!$A$4:$A$330,0),10) -> 7073 | H4: =ROUND(E4*G4,0) -> 26128
A5: =StartupfileInput!A4 -> 0018 | B5: =INDEX(Calculation!$A$4:$M$330,MATCH(Summary!$A5,Calculation!$A$4:$A$330,0),3) -> Adair-Casey | C5: =INDEX(Calculation!$A$4:$M$330,MATCH(Summary!$A5,Calculation!$A$4:$A$330,0),6) -> 0.851 | D5: =INDEX(Calculation!$A$4:$M$330,MATCH(Summary!$A5,Calculation!$A$4:$A$330,0),7) -> 0.607 | E5: =SUM(C5:D5) -> 1.458 | G5: =INDEX(Calculation!$A$4:$M$330,MATCH(Summary!$A5,Calculation!$A$4:$A$330,0),10) -> 7048 | H5: =ROUND(E5*G5,0) -> 10276
A6: =StartupfileInput!A5 -> 0027 | B6: =INDEX(Calculation!$A$4:$M$330,MATCH(Summary!$A6,Calculation!$A$4:$A$330,0),3) -> Adel-Desoto-Minburn | C6: =INDEX(Calculation!$A$4:$M$330,MATCH(Summary!$A6,Calculation!$A$4:$A$330,0),6) -> 2.44 | D6: =INDEX(Calculation!$A$4:$M$330,MATCH(Summary!$A6,Calculation!$A$4:$A$330,0),7) -> 3.942 | E6: =SUM(C6:D6) -> 6.382 | G6: =INDEX(Calculation!$A$4:$M$330,MATCH(Summary!$A6,Calculation!$A$4:$A$330,0),10) -> 7048 | H6: =ROUND(E6*G6,0) -> 44980
A7: =StartupfileInput!A6 -> 0063 | B7: =INDEX(Calculation!$A$4:$M$330,MATCH(Summary!$A7,Calculation!$A$4:$A$330,0),3) -> Akron-Westfield | C7: =INDEX(Calculation!$A$4:$M$330,MATCH(Summary!$A7,Calculation!$A$4:$A$330,0),6) -> 1.326 | D7: =INDEX(Calculation!$A$4:$M$330,MATCH(Summary!$A7,Calculation!$A$4:$A$330,0),7) -> 1.178 | E7: =SUM(C7:D7) -> 2.504 | G7: =INDEX(Calculation!$A$4:$M$330,MATCH(Summary!$A7,Calculation!$A$4:$A$330,0),10) -> 7079 | H7: =ROUND(E7*G7,0) -> 17726
A8: =StartupfileInput!A7 -> 0072 | B8: =INDEX(Calculation!$A$4:$M$330,MATCH(Summary!$A8,Calculation!$A$4:$A$330,0),3) -> Albert City-Truesdale | C8: =INDEX(Calculation!$A$4:$M$330,MATCH(Summary!$A8,Calculation!$A$4:$A$330,0),6) -> 0.624 | D8: =INDEX(Calculation!$A$4:$M$330,MATCH(Summary!$A8,Calculation!$A$4:$A$330,0),7) -> 0.442 | E8: =SUM(C8:D8) -> 1.066 | G8: =INDEX(Calculation!$A$4:$M$330,MATCH(Summary!$A8,Calculation!$A$4:$A$330,0),10) -> 7109 | H8: =ROUND(E8*G8,0) -> 7578
A9: =StartupfileInput!A8 -> 0081 | B9: =INDEX(Calculation!$A$4:$M$330,MATCH(Summary!$A9,Calculation!$A$4:$A$330,0),3) -> Albia | C9: =INDEX(Calculation!$A$4:$M$330,MATCH(Summary!$A9,Calculation!$A$4:$A$330,0),6) -> 2.95 | D9: =INDEX(Calculation!$A$4:$M$330,MATCH(Summary!$A9,Calculation!$A$4:$A$330,0),7) -> 2.348 | E9: =SUM(C9:D9) -> 5.298 | G9: =INDEX(Calculation!$A$4:$M$330,MATCH(Summary!$A9,Calculation!$A$4:$A$330,0),10) -> 7048 | H9: =ROUND(E9*G9,0) -> 37340
A10: =StartupfileInput!A9 -> 0099 | B10: =INDEX(Calculation!$A$4:$M$330,MATCH(Summary!$A10,Calculation!$A$4:$A$330,0),3) -> Alburnett | C10: =INDEX(Calculation!$A$4:$M$330,MATCH(Summary!$A10,Calculation!$A$4:$A$330,0),6) -> 0.673 | D10: =INDEX(Calculation!$A$4:$M$330,MATCH(Summary!$A10,Calculation!$A$4:$A$330,0),7) -> 1.044 | E10: =SUM(C10:D10) -> 1.717 | G10: =INDEX(Calculation!$A$4:$M$330,MATCH(Summary!$A10,Calculation!$A$4:$A$330,0),10) -> 7048 | H10: =ROUND(E10*G10,0) -> 12101
A11: =StartupfileInput!A10 -> 0108 | B11: =INDEX(Calculation!$A$4:$M$330,MATCH(Summary!$A11,Calculation!$A$4:$A$330,0),3) -> Alden | C11: =INDEX(Calculation!$A$4:$M$330,MATCH(Summary!$A11,Calculation!$A$4:$A$330,0),6) -> 0.628 | D11: =INDEX(Calculation!$A$4:$M$330,MATCH(Summary!$A11,Calculation!$A$4:$A$330,0),7) -> 0.539 | E11: =SUM(C11:D11) -> 1.167 | G11: =INDEX(Calculation!$A$4:$M$330,MATCH(Summary!$A11,Calculation!$A$4:$A$330,0),10) -> 7048 | H11: =ROUND(E11*G11,0) -> 8225
A12: =StartupfileInput!A11 -> 0126 | B12: =INDEX(Calculation!$A$4:$M$330,MATCH(Summary!$A12,Calculation!$A$4:$A$330,0),3) -> Algona | C12: =INDEX(Calculation!$A$4:$M$330,MATCH(Summary!$A12,Calculation!$A$4:$A$330,0),6) -> 3.389 | D12: =INDEX(Calculation!$A$4:$M$330,MATCH(Summary!$A12,Calculation!$A$4:$A$330,0),7) -> 2.643 | E12: =SUM(C12:D12) -> 6.032 | G12: =INDEX(Calculation!$A$4:$M$330,MATCH(Summary!$A12,Calculation!$A$4:$A$330,0),10) -> 7061 | H12: =ROUND(E12*G12,0) -> 42592
A13: =StartupfileInput!A12 -> 0135 | B13: =INDEX(Calculation!$A$4:$M$330,MATCH(Summary!$A13,Calculation!$A$4:$A$330,0),3) -> Allamakee | C13: =INDEX(Calculation!$A$4:$M$330,MATCH(Summary!$A13,Calculation!$A$4:$A$330,0),6) -> 3.176 | D13: =INDEX(Calculation!$A$4:$M$330,MATCH(Summary!$A13,Calculation!$A$4:$A$330,0),7) -> 2.234 | E13: =SUM(C13:D13) -> 5.41 | G13: =INDEX(Calculation!$A$4:$M$330,MATCH(Summary!$A13,Calculation!$A$4:$A$330,0),10) -> 7110 | H13: =ROUND(E13*G13,0) -> 38465
A14: =StartupfileInput!A13 -> 0171 | B14: =INDEX(Calculation!$A$4:$M$330,MATCH(Summary!$A14,Calculation!$A$4:$A$330,0),3) -> Alta-Aurelia | C14: =INDEX(Calculation!$A$4:$M$330,MATCH(Summary!$A14,Calculation!$A$4:$A$330,0),6) -> 2.482 | D14: =INDEX(Calculation!$A$4:$M$330,MATCH(Summary!$A14,Calculation!$A$4:$A$330,0),7) -> 1.639 | E14: =SUM(C14:D14) -> 4.121 | G14: =INDEX(Calculation!$A$4:$M$330,MATCH(Summary!$A14,Calculation!$A$4:$A$330,0),10) -> 7049 | H14: =ROUND(E14*G14,0) -> 29049
... A329: =StartupfileInput!A328 -> 7110 | B329: =INDEX(Calculation!$A$4:$M$330,MATCH(Summary!$A329,Calculation!$A$4:$A$330,0),3) -> Woodward-Granger | C329: =INDEX(Calculation!$A$4:$M$330,MATCH(Summary!$A329,Calculation!$A$4:$A$330,0),6) -> 1.322 | D329: =INDEX(Calculation!$A$4:$M$330,MATCH(Summary!$A329,Calculation!$A$4:$A$330,0),7) -> 1.999 | E329: =SUM(C329:D329) -> 3.321 | G329: =INDEX(Calculation!$A$4:$M$330,MATCH(Summary!$A329,Calculation!$A$4:$A$330,0),10) -> 7120 | H329: =ROUND(E329*G329,0) -> 23646
C330: =SUM(C3:C329) -> 1418.049 | D330: =SUM(D3:D329) -> 999.789 | E330: =SUM(E3:E329) -> 2417.838 | H330: =SUM(H3:H329) -> 17079488
A332: NOTES:
A333: 1) Supplementary Weighting Free/Reduced Meals - Percent free & reduced meals in grades 1-6 multiplied by budget enrollment multiplied by 0.00642 weighting.
A335: 2) Supplementary Weighting Enrollment - Budget enrollment multiplied by 0.00204 weighting.
A336: 3) Supplementary Weighting Subtotal - Free & reduced meals weighting plus enrollment weighting.
A337: 4) District Cost Per Pupil
A338: 5) Dollars Generated total - total supplementary weighting multiplied by district cost per pupil.

Sheet Calculation
D1: Oct. 15 | E1: Percent 1-6 | F1: Suppl Wght | G1: Suppl Wght | H1: Suppl Wght | I1: =CONCATENATE("FY ",P1-1) -> FY 2020 | J1: =CONCATENATE("FY ",P1) -> FY 2021 | K1: Dollars | L1: Dollars | M1: Dollars | O1: Fiscal Year | P1: 2021 | Q1: =Constants!B1 -> SPG | R1: =Constants!C1 -> CPP | S1: =Constants!D1 -> Additional_Dollar | T1: =Constants!E1 -> SCPP
D2: Enrollment | E2: Free & Red. | F2: Free & Red. | G2: Enrollment | H2: Total | I2: DCPP | J2: DCPP | K2: Generated | L2: Generated | M2: Generated | O2: SCPP | P2: =INDEX(Constants!$A$2:$AW$100,MATCH(Calculation!$P$1,Constants!$A$2:$A$100,0),MATCH(Calculation!O$2,Constants!$A$1:$AW$1,0)) -> 7048 | Q2: =INDEX(Constants!$A$2:$AW$100,MATCH(Calculation!$P$1,Constants!$A$2:$A$100,0),MATCH(Calculation!Q$1,Constants!$A$1:$AW$1,0)) -> 0.023 | R2: =INDEX(Constants!$A$2:$AW$100,MATCH(Calculation!$P$1,Constants!$A$2:$A$100,0),MATCH(Calculation!R$1,Constants!$A$1:$AW$1,0)) -> 158 | S2: =INDEX(Constants!$A$2:$AW$100,MATCH(Calculation!$P$1,Constants!$A$2:$A$100,0),MATCH(Calculation!S$1,Constants!$A$1:$AW$1,0)) -> 10 | T2: =INDEX(Constants!$A$2:$AW$100,MATCH(Calculation!$P$1,Constants!$A$2:$A$100,0),MATCH(Calculation!T$1,Constants!$A$1:$AW$1,0)) -> 7048
A3: Dist | B3: DistrictNumber | C3: =#REF! -> #REF! | E3: Meals | F3: 0.00642 | G3: 0.00204 | H3: Line 3.10 | K3: Free & Red. | L3: Enrollment | M3: Total
A4: =StartupfileInput!A2 -> 0009 | B4: =INDEX(ActiveDistricts!$A$2:$J$328,MATCH(Calculation!$A4,ActiveDistricts!$C$2:$C$328,0),6) -> 0009 | C4: =INDEX(ActiveDistricts!$A$2:$J$328,MATCH(Calculation!$A4,ActiveDistricts!$C$2:$C$328,0),7) -> AGWSR | D4: =INDEX(StartupfileInput!$A$2:$D$328,MATCH(Calculation!$A4,StartupfileInput!$A$2:$A$328,0),3) -> 645.2 | E4: =INDEX(ActiveDistricts!$A$2:$J$328,MATCH(Calculation!$A4,ActiveDistricts!$C$2:$C$328,0),10) -> 0.45387454 | F4: =ROUND(D4*E4*$F$3,3) -> 1.88 | G4: =ROUND(D4*$G$3,3) -> 1.316 | H4: =SUM(F4:G4) -> 3.196 | I4: =INDEX(StartupfileInput!$A$2:$D$328,MATCH(Calculation!$A4,StartupfileInput!$A$2:$A$328,0),4) -> 6980 | J4: =MAX(I4+$R$2,$T$2) -> 7138 | K4: =ROUND(F4*J4,0) -> 13419 | L4: =M4-K4 -> 9394 | M4: =ROUND(H4*J4,0) -> 22813
A5: =StartupfileInput!A3 -> 0441 | B5: =INDEX(ActiveDistricts!$A$2:$J$328,MATCH(Calculation!$A5,ActiveDistricts!$C$2:$C$328,0),6) -> 0441 | C5: =INDEX(ActiveDistricts!$A$2:$J$328,MATCH(Calculation!$A5,ActiveDistricts!$C$2:$C$328,0),7) -> AHSTW | D5: =INDEX(StartupfileInput!$A$2:$D$328,MATCH(Calculation!$A5,StartupfileInput!$A$2:$A$328,0),3) -> 780.7 | E5: =INDEX(ActiveDistricts!$A$2:$J$328,MATCH(Calculation!$A5,ActiveDistricts!$C$2:$C$328,0),10) -> 0.41924399 | F5: =ROUND(D5*E5*$F$3,3) -> 2.101 | G5: =ROUND(D5*$G$3,3) -> 1.593 | H5: =SUM(F5:G5) -> 3.694 | I5: =INDEX(StartupfileInput!$A$2:$D$328,MATCH(Calculation!$A5,StartupfileInput!$A$2:$A$328,0),4) -> 6915 | J5: =MAX(I5+$R$2,$T$2) -> 7073 | K5: =ROUND(F5*J5,0) -> 14860 | L5: =M5-K5 -> 11268 | M5: =ROUND(H5*J5,0) -> 26128
A6: =StartupfileInput!A4 -> 0018 | B6: =INDEX(ActiveDistricts!$A$2:$J$328,MATCH(Calculation!$A6,ActiveDistricts!$C$2:$C$328,0),6) -> 0018 | C6: =INDEX(ActiveDistricts!$A$2:$J$328,MATCH(Calculation!$A6,ActiveDistricts!$C$2:$C$328,0),7) -> Adair-Casey | D6: =INDEX(StartupfileInput!$A$2:$D$328,MATCH(Calculation!$A6,StartupfileInput!$A$2:$A$328,0),3) -> 297.4 | E6: =INDEX(ActiveDistricts!$A$2:$J$328,MATCH(Calculation!$A6,ActiveDistricts!$C$2:$C$328,0),10) -> 0.44545455 | F6: =ROUND(D6*E6*$F$3,3) -> 0.851 | G6: =ROUND(D6*$G$3,3) -> 0.607 | H6: =SUM(F6:G6) -> 1.458 | I6: =INDEX(StartupfileInput!$A$2:$D$328,MATCH(Calculation!$A6,StartupfileInput!$A$2:$A$328,0),4) -> 6880 | J6: =MAX(I6+$R$2,$T$2) -> 7048 | K6: =ROUND(F6*J6,0) -> 5998 | L6: =M6-K6 -> 4278 | M6: =ROUND(H6*J6,0) -> 10276
A7: =StartupfileInput!A5 -> 0027 | B7: =INDEX(ActiveDistricts!$A$2:$J$328,MATCH(Calculation!$A7,ActiveDistricts!$C$2:$C$328,0),6) -> 0027 | C7: =INDEX(ActiveDistricts!$A$2:$J$328,MATCH(Calculation!$A7,ActiveDistricts!$C$2:$C$328,0),7) -> Adel-Desoto-Minburn | D7: =INDEX(StartupfileInput!$A$2:$D$328,MATCH(Calculation!$A7,StartupfileInput!$A$2:$A$328,0),3) -> 1932.2 | E7: =INDEX(ActiveDistricts!$A$2:$J$328,MATCH(Calculation!$A7,ActiveDistricts!$C$2:$C$328,0),10) -> 0.19667014 | F7: =ROUND(D7*E7*$F$3,3) -> 2.44 | G7: =ROUND(D7*$G$3,3) -> 3.942 | H7: =SUM(F7:G7) -> 6.382 | I7: =INDEX(StartupfileInput!$A$2:$D$328,MATCH(Calculation!$A7,StartupfileInput!$A$2:$A$328,0),4) -> 6890 | J7: =MAX(I7+$R$2,$T$2) -> 7048 | K7: =ROUND(F7*J7,0) -> 17197 | L7: =M7-K7 -> 27783 | M7: =ROUND(H7*J7,0) -> 44980
A8: =StartupfileInput!A6 -> 0063 | B8: =INDEX(ActiveDistricts!$A$2:$J$328,MATCH(Calculation!$A8,ActiveDistricts!$C$2:$C$328,0),6) -> 0063 | C8: =INDEX(ActiveDistricts!$A$2:$J$328,MATCH(Calculation!$A8,ActiveDistricts!$C$2:$C$328,0),7) -> Akron-Westfield | D8: =INDEX(StartupfileInput!$A$2:$D$328,MATCH(Calculation!$A8,StartupfileInput!$A$2:$A$328,0),3) -> 577.4 | E8: =INDEX(ActiveDistricts!$A$2:$J$328,MATCH(Calculation!$A8,ActiveDistricts!$C$2:$C$328,0),10) -> 0.35769231 | F8: =ROUND(D8*E8*$F$3,3) -> 1.326 | G8: =ROUND(D8*$G$3,3) -> 1.178 | H8: =SUM(F8:G8) -> 2.504 | I8: =INDEX(StartupfileInput!$A$2:$D$328,MATCH(Calculation!$A8,StartupfileInput!$A$2:$A$328,0),4) -> 6921 | J8: =MAX(I8+$R$2,$T$2) -> 7079 | K8: =ROUND(F8*J8,0) -> 9387 | L8: =M8-K8 -> 8339 | M8: =ROUND(H8*J8,0) -> 17726
A9: =StartupfileInput!A7 -> 0072 | B9: =INDEX(ActiveDistricts!$A$2:$J$328,MATCH(Calculation!$A9,ActiveDistricts!$C$2:$C$328,0),6) -> 0072 | C9: =INDEX(ActiveDistricts!$A$2:$J$328,MATCH(Calculation!$A9,ActiveDistricts!$C$2:$C$328,0),7) -> Albert City-Truesdale | D9: =INDEX(StartupfileInput!$A$2:$D$328,MATCH(Calculation!$A9,StartupfileInput!$A$2:$A$328,0),3) -> 216.9 | E9: =INDEX(ActiveDistricts!$A$2:$J$328,MATCH(Calculation!$A9,ActiveDistricts!$C$2:$C$328,0),10) -> 0.44827586 | F9: =ROUND(D9*E9*$F$3,3) -> 0.624 | G9: =ROUND(D9*$G$3,3) -> 0.442 | H9: =SUM(F9:G9) -> 1.066 | I9: =INDEX(StartupfileInput!$A$2:$D$328,MATCH(Calculation!$A9,StartupfileInput!$A$2:$A$328,0),4) -> 6951 | J9: =MAX(I9+$R$2,$T$2) -> 7109 | K9: =ROUND(F9*J9,0) -> 4436 | L9: =M9-K9 -> 3142 | M9: =ROUND(H9*J9,0) -> 7578
A10: =StartupfileInput!A8 -> 0081 | B10: =INDEX(ActiveDistricts!$A$2:$J$328,MATCH(Calculation!$A10,ActiveDistricts!$C$2:$C$328,0),6) -> 0081 | C10: =INDEX(ActiveDistricts!$A$2:$J$328,MATCH(Calculation!$A10,ActiveDistricts!$C$2:$C$328,0),7) -> Albia | D10: =INDEX(StartupfileInput!$A$2:$D$328,MATCH(Calculation!$A10,StartupfileInput!$A$2:$A$328,0),3) -> 1151.1 | E10: =INDEX(ActiveDistricts!$A$2:$J$328,MATCH(Calculation!$A10,ActiveDistricts!$C$2:$C$328,0),10) -> 0.39918534 | F10: =ROUND(D10*E10*$F$3,3) -> 2.95 | G10: =ROUND(D10*$G$3,3) -> 2.348 | H10: =SUM(F10:G10) -> 5.298 | I10: =INDEX(StartupfileInput!$A$2:$D$328,MATCH(Calculation!$A10,StartupfileInput!$A$2:$A$328,0),4) -> 6880 | J10: =MAX(I10+$R$2,$T$2) -> 7048 | K10: =ROUND(F10*J10,0) -> 20792 | L10: =M10-K10 -> 16548 | M10: =ROUND(H10*J10,0) -> 37340
A11: =StartupfileInput!A9 -> 0099 | B11: =INDEX(ActiveDistricts!$A$2:$J$328,MATCH(Calculation!$A11,ActiveDistricts!$C$2:$C$328,0),6) -> 0099 | C11: =INDEX(ActiveDistricts!$A$2:$J$328,MATCH(Calculation!$A11,ActiveDistricts!$C$2:$C$328,0),7) -> Alburnett | D11: =INDEX(StartupfileInput!$A$2:$D$328,MATCH(Calculation!$A11,StartupfileInput!$A$2:$A$328,0),3) -> 511.8 | E11: =INDEX(ActiveDistricts!$A$2:$J$328,MATCH(Calculation!$A11,ActiveDistricts!$C$2:$C$328,0),10) -> 0.204947 | F11: =ROUND(D11*E11*$F$3,3) -> 0.673 | G11: =ROUND(D11*$G$3,3) -> 1.044 | H11: =SUM(F11:G11) -> 1.717 | I11: =INDEX(StartupfileInput!$A$2:$D$328,MATCH(Calculation!$A11,StartupfileInput!$A$2:$A$328,0),4) -> 6880 | J11: =MAX(I11+$R$2,$T$2) -> 7048 | K11: =ROUND(F11*J11,0) -> 4743 | L11: =M11-K11 -> 7358 | M11: =ROUND(H11*J11,0) -> 12101
A12: =StartupfileInput!A10 -> 0108 | B12: =INDEX(ActiveDistricts!$A$2:$J$328,MATCH(Calculation!$A12,ActiveDistricts!$C$2:$C$328,0),6) -> 0108 | C12: =INDEX(ActiveDistricts!$A$2:$J$328,MATCH(Calculation!$A12,ActiveDistricts!$C$2:$C$328,0),7) -> Alden | D12: =INDEX(StartupfileInput!$A$2:$D$328,MATCH(Calculation!$A12,StartupfileInput!$A$2:$A$328,0),3) -> 264.4 | E12: =INDEX(ActiveDistricts!$A$2:$J$328,MATCH(Calculation!$A12,ActiveDistricts!$C$2:$C$328,0),10) -> 0.3697479 | F12: =ROUND(D12*E12*$F$3,3) -> 0.628 | G12: =ROUND(D12*$G$3,3) -> 0.539 | H12: =SUM(F12:G12) -> 1.167 | I12: =INDEX(StartupfileInput!$A$2:$D$328,MATCH(Calculation!$A12,StartupfileInput!$A$2:$A$328,0),4) -> 6880 | J12: =MAX(I12+$R$2,$T$2) -> 7048 | K12: =ROUND(F12*J12,0) -> 4426 | L12: =M12-K12 -> 3799 | M12: =ROUND(H12*J12,0) -> 8225
A13: =StartupfileInput!A11 -> 0126 | B13: =INDEX(ActiveDistricts!$A$2:$J$328,MATCH(Calculation!$A13,ActiveDistricts!$C$2:$C$328,0),6) -> 0126 | C13: =INDEX(ActiveDistricts!$A$2:$J$328,MATCH(Calculation!$A13,ActiveDistricts!$C$2:$C$328,0),7) -> Algona | D13: =INDEX(StartupfileInput!$A$2:$D$328,MATCH(Calculation!$A13,StartupfileInput!$A$2:$A$328,0),3) -> 1295.6 | E13: =INDEX(ActiveDistricts!$A$2:$J$328,MATCH(Calculation!$A13,ActiveDistricts!$C$2:$C$328,0),10) -> 0.40740741 | F13: =ROUND(D13*E13*$F$3,3) -> 3.389 | G13: =ROUND(D13*$G$3,3) -> 2.643 | H13: =SUM(F13:G13) -> 6.032 | I13: =INDEX(StartupfileInput!$A$2:$D$328,MATCH(Calculation!$A13,StartupfileInput!$A$2:$A$328,0),4) -> 6903 | J13: =MAX(I13+$R$2,$T$2) -> 7061 | K13: =ROUND(F13*J13,0) -> 23930 | L13: =M13-K13 -> 18662 | M13: =ROUND(H13*J13,0) -> 42592
A14: =StartupfileInput!A12 -> 0135 | B14: =INDEX(ActiveDistricts!$A$2:$J$328,MATCH(Calculation!$A14,ActiveDistricts!$C$2:$C$328,0),6) -> 0135 | C14: =INDEX(ActiveDistricts!$A$2:$J$328,MATCH(Calculation!$A14,ActiveDistricts!$C$2:$C$328,0),7) -> Allamakee | D14: =INDEX(StartupfileInput!$A$2:$D$328,MATCH(Calculation!$A14,StartupfileInput!$A$2:$A$328,0),3) -> 1095 | E14: =INDEX(ActiveDistricts!$A$2:$J$328,MATCH(Calculation!$A14,ActiveDistricts!$C$2:$C$328,0),10) -> 0.45183486 | F14: =ROUND(D14*E14*$F$3,3) -> 3.176 | G14: =ROUND(D14*$G$3,3) -> 2.234 | H14: =SUM(F14:G14) -> 5.41 | I14: =INDEX(StartupfileInput!$A$2:$D$328,MATCH(Calculation!$A14,StartupfileInput!$A$2:$A$328,0),4) -> 6952 | J14: =MAX(I14+$R$2,$T$2) -> 7110 | K14: =ROUND(F14*J14,0) -> 22581 | L14: =M14-K14 -> 15884 | M14: =ROUND(H14*J14,0) -> 38465
A15: =StartupfileInput!A13 -> 0171 | B15: =INDEX(ActiveDistricts!$A$2:$J$328,MATCH(Calculation!$A15,ActiveDistricts!$C$2:$C$328,0),6) -> 0171 | C15: =INDEX(ActiveDistricts!$A$2:$J$328,MATCH(Calculation!$A15,ActiveDistricts!$C$2:$C$328,0),7) -> Alta-Aurelia | D15: =INDEX(StartupfileInput!$A$2:$D$328,MATCH(Calculation!$A15,StartupfileInput!$A$2:$A$328,0),3) -> 803.2 | E15: =INDEX(ActiveDistricts!$A$2:$J$328,MATCH(Calculation!$A15,ActiveDistricts!$C$2:$C$328,0),10) -> 0.48126801 | F15: =ROUND(D15*E15*$F$3,3) -> 2.482 | G15: =ROUND(D15*$G$3,3) -> 1.639 | H15: =SUM(F15:G15) -> 4.121 | I15: =INDEX(StartupfileInput!$A$2:$D$328,MATCH(Calculation!$A15,StartupfileInput!$A$2:$A$328,0),4) -> 6891 | J15: =MAX(I15+$R$2,$T$2) -> 7049 | K15: =ROUND(F15*J15,0) -> 17496 | L15: =M15-K15 -> 11553 | M15: =ROUND(H15*J15,0) -> 29049
... A330: =StartupfileInput!A328 -> 7110 | B330: =INDEX(ActiveDistricts!$A$2:$J$328,MATCH(Calculation!$A330,ActiveDistricts!$C$2:$C$328,0),6) -> 7110 | C330: =INDEX(ActiveDistricts!$A$2:$J$328,MATCH(Calculation!$A330,ActiveDistricts!$C$2:$C$328,0),7) -> Woodward-Granger | D330: =INDEX(StartupfileInput!$A$2:$D$328,MATCH(Calculation!$A330,StartupfileInput!$A$2:$A$328,0),3) -> 980 | E330: =INDEX(ActiveDistricts!$A$2:$J$328,MATCH(Calculation!$A330,ActiveDistricts!$C$2:$C$328,0),10) -> 0.21017699 | F330: =ROUND(D330*E330*$F$3,3) -> 1.322 | G330: =ROUND(D330*$G$3,3) -> 1.999 | H330: =SUM(F330:G330) -> 3.321 | I330: =INDEX(StartupfileInput!$A$2:$D$328,MATCH(Calculation!$A330,StartupfileInput!$A$2:$A$328,0),4) -> 6962 | J330: =MAX(I330+$R$2,$T$2) -> 7120 | K330: =ROUND(F330*J330,0) -> 9413 | L330: =M330-K330 -> 14233 | M330: =ROUND(H330*J330,0) -> 23646
D331: =SUM(D4:D330) -> 490094.4 | F331: =SUM(F4:F330) -> 1418.049 | G331: =SUM(G4:G330) -> 999.789 | H331: =SUM(H4:H330) -> 2417.838
C332: FY 2021 - calculated | D332: =SUM(D4:D330) -> 490094.4 | E332: =SUM(ActiveDistricts!$I:$I)/SUM(ActiveDistricts!$H:$H) -> 0.44452428 | F332: =ROUND(D332*E332*$F$3,3) -> 1398.654 | G332: =ROUND(D332*$G$3,3) -> 999.793 | H332: =SUM(F332:G332) -> 2398.447 | K332: =SUM(K4:K330) -> 10018058 | L332: =SUM(L4:L330) -> 7061430 | M332: =SUM(M4:M330) -> 17079488
C334: state aid portion 87.5% | M334: =ROUND(M332*0.875,0) -> 14944552
C335: property tax portion 12.5% | M335: =ROUND(M332*0.125,0) -> 2134936

Sheet StartupfileInput
A1: Dist | B1: Name | C1: line 1.1 x249 | D1: line 1.3 x272 | F1: From StartupFile
A2: 0009 | B2: AGWSR | C2: 645.2 | D2: 6980
A3: 0441 | B3: AHSTW | C3: 780.7 | D3: 6915
A4: 0018 | B4: Adair-Casey | C4: 297.4 | D4: 6880
A5: 0027 | B5: Adel-Desoto-Minburn | C5: 1932.2 | D5: 6890
A6: 0063 | B6: Akron-Westfield | C6: 577.4 | D6: 6921
A7: 0072 | B7: Albert City-Truesdale | C7: 216.9 | D7: 6951
A8: 0081 | B8: Albia | C8: 1151.1 | D8: 6880
A9: 0099 | B9: Alburnett | C9: 511.8 | D9: 6880
A10: 0108 | B10: Alden | C10: 264.4 | D10: 6880
A11: 0126 | B11: Algona | C11: 1295.6 | D11: 6903
A12: 0135 | B12: Allamakee | C12: 1095 | D12: 6952
A13: 0171 | B13: Alta-Aurelia | C13: 803.2 | D13: 6891
... A328: 7110 | B328: Woodward-Granger | C328: 980 | D328: 6962

Sheet ActiveDistricts
A1: FiscalYear | B1: AEA | C1: Dist | D1: DistSub1 | E1: DistSub2 | F1: DistrictNumber | G1: Label | H1: Enrollment | I1: # Eligible for Free or Reduced Lunch | J1: FRL %
A2: 2021 | B2: 11 | C2: 0018 | F2: 0018 | G2: Adair-Casey | H2: =SUMIF(lunch1920_g1to6!$B$3:$B$935,ActiveDistricts!$F2,lunch1920_g1to6!$F$3:$F$935) -> 110 | I2: =SUMIF(lunch1920_g1to6!$B$3:$B$935,ActiveDistricts!$F2,lunch1920_g1to6!$G$3:$G$935) -> 49 | J2: =I2/H2 -> 0.44545455
A3: 2021 | B3: 11 | C3: 0027 | F3: 0027 | G3: Adel-Desoto-Minburn | H3: =SUMIF(lunch1920_g1to6!$B$3:$B$935,ActiveDistricts!$F3,lunch1920_g1to6!$F$3:$F$935) -> 961 | I3: =SUMIF(lunch1920_g1to6!$B$3:$B$935,ActiveDistricts!$F3,lunch1920_g1to6!$G$3:$G$935) -> 189 | J3: =I3/H3 -> 0.19667014
A4: 2021 | B4: 07 | C4: 0009 | F4: 0009 | G4: AGWSR | H4: =SUMIF(lunch1920_g1to6!$B$3:$B$935,ActiveDistricts!$F4,lunch1920_g1to6!$F$3:$F$935) -> 271 | I4: =SUMIF(lunch1920_g1to6!$B$3:$B$935,ActiveDistricts!$F4,lunch1920_g1to6!$G$3:$G$935) -> 123 | J4: =I4/H4 -> 0.45387454
A5: 2021 | B5: 13 | C5: 0441 | F5: 0441 | G5: AHSTW | H5: =SUMIF(lunch1920_g1to6!$B$3:$B$935,ActiveDistricts!$F5,lunch1920_g1to6!$F$3:$F$935) -> 291 | I5: =SUMIF(lunch1920_g1to6!$B$3:$B$935,ActiveDistricts!$F5,lunch1920_g1to6!$G$3:$G$935) -> 122 | J5: =I5/H5 -> 0.41924399
A6: 2021 | B6: 12 | C6: 0063 | F6: 0063 | G6: Akron-Westfield | H6: =SUMIF(lunch1920_g1to6!$B$3:$B$935,ActiveDistricts!$F6,lunch1920_g1to6!$F$3:$F$935) -> 260 | I6: =SUMIF(lunch1920_g1to6!$B$3:$B$935,ActiveDistricts!$F6,lunch1920_g1to6!$G$3:$G$935) -> 93 | J6: =I6/H6 -> 0.35769231
A7: 2021 | B7: 05 | C7: 0072 | F7: 0072 | G7: Albert City-Truesdale | H7: =SUMIF(lunch1920_g1to6!$B$3:$B$935,ActiveDistricts!$F7,lunch1920_g1to6!$F$3:$F$935) -> 87 | I7: =SUMIF(lunch1920_g1to6!$B$3:$B$935,ActiveDistricts!$F7,lunch1920_g1to6!$G$3:$G$935) -> 39 | J7: =I7/H7 -> 0.44827586
A8: 2021 | B8: 15 | C8: 0081 | F8: 0081 | G8: Albia | H8: =SUMIF(lunch1920_g1to6!$B$3:$B$935,ActiveDistricts!$F8,lunch1920_g1to6!$F$3:$F$935) -> 491 | I8: =SUMIF(lunch1920_g1to6!$B$3:$B$935,ActiveDistricts!$F8,lunch1920_g1to6!$G$3:$G$935) -> 196 | J8: =I8/H8 -> 0.39918534
A9: 2021 | B9: 10 | C9: 0099 | F9: 0099 | G9: Alburnett | H9: =SUMIF(lunch1920_g1to6!$B$3:$B$935,ActiveDistricts!$F9,lunch1920_g1to6!$F$3:$F$935) -> 283 | I9: =SUMIF(lunch1920_g1to6!$B$3:$B$935,ActiveDistricts!$F9,lunch1920_g1to6!$G$3:$G$935) -> 58 | J9: =I9/H9 -> 0.204947
A10: 2021 | B10: 07 | C10: 0108 | F10: 0108 | G10: Alden | H10: =SUMIF(lunch1920_g1to6!$B$3:$B$935,ActiveDistricts!$F10,lunch1920_g1to6!$F$3:$F$935) -> 119 | I10: =SUMIF(lunch1920_g1to6!$B$3:$B$935,ActiveDistricts!$F10,lunch1920_g1to6!$G$3:$G$935) -> 44 | J10: =I10/H10 -> 0.3697479
A11: 2021 | B11: 05 | C11: 0126 | D11: 6417 | F11: 0126 | G11: Algona | H11: =SUMIF(lunch1920_g1to6!$B$3:$B$935,ActiveDistricts!$F11,lunch1920_g1to6!$F$3:$F$935) -> 567 | I11: =SUMIF(lunch1920_g1to6!$B$3:$B$935,ActiveDistricts!$F11,lunch1920_g1to6!$G$3:$G$935) -> 231 | J11: =I11/H11 -> 0.40740741
A12: 2021 | B12: 01 | C12: 0135 | F12: 0135 | G12: Allamakee | H12: =SUMIF(lunch1920_g1to6!$B$3:$B$935,ActiveDistricts!$F12,lunch1920_g1to6!$F$3:$F$935) -> 436 | I12: =SUMIF(lunch1920_g1to6!$B$3:$B$935,ActiveDistricts!$F12,lunch1920_g1to6!$G$3:$G$935) -> 197 | J12: =I12/H12 -> 0.45183486
A13: 2021 | B13: 05 | C13: 0171 | D13: 0423 | F13: 0171 | G13: Alta-Aurelia | H13: =SUMIF(lunch1920_g1to6!$B$3:$B$935,ActiveDistricts!$F13,lunch1920_g1to6!$F$3:$F$935) -> 347 | I13: =SUMIF(lunch1920_g1to6!$B$3:$B$935,ActiveDistricts!$F13,lunch1920_g1to6!$G$3:$G$935) -> 167 | J13: =I13/H13 -> 0.48126801
A14: 2021 | B14: 11 | C14: 0225 | F14: 0225 | G14: Ames | H14: =SUMIF(lunch1920_g1to6!$B$3:$B$935,ActiveDistricts!$F14,lunch1920_g1to6!$F$3:$F$935) -> 2160 | I14: =SUMIF(lunch1920_g1to6!$B$3:$B$935,ActiveDistricts!$F14,lunch1920_g1to6!$G$3:$G$935) -> 685 | J14: =I14/H14 -> 0.31712963
A15: 2021 | B15: 10 | C15: 0234 | F15: 0234 | G15: Anamosa | H15: =SUMIF(lunch1920_g1to6!$B$3:$B$935,ActiveDistricts!$F15,lunch1920_g1to6!$F$3:$F$935) -> 495 | I15: =SUMIF(lunch1920_g1to6!$B$3:$B$935,ActiveDistricts!$F15,lunch1920_g1to6!$G$3:$G$935) -> 223 | J15: =I15/H15 -> 0.45050505
A16: 2021 | B16: 09 | C16: 0243 | F16: 0243 | G16: Andrew | H16: =SUMIF(lunch1920_g1to6!$B$3:$B$935,ActiveDistricts!$F16,lunch1920_g1to6!$F$3:$F$935) -> 97 | I16: =SUMIF(lunch1920_g1to6!$B$3:$B$935,ActiveDistricts!$F16,lunch1920_g1to6!$G$3:$G$935) -> 39 | J16: =I16/H16 -> 0.40206186
A17: 2021 | B17: 11 | C17: 0261 | F17: 0261 | G17: Ankeny | H17: =SUMIF(lunch1920_g1to6!$B$3:$B$935,ActiveDistricts!$F17,lunch1920_g1to6!$F$3:$F$935) -> 5694 | I17: =SUMIF(lunch1920_g1to6!$B$3:$B$935,ActiveDistricts!$F17,lunch1920_g1to6!$G$3:$G$935) -> 957 | J17: =I17/H17 -> 0.16807165
A18: 2021 | B18: 07 | C18: 0279 | F18: 0279 | G18: Aplington-Parkersburg | H18: =SUMIF(lunch1920_g1to6!$B$3:$B$935,ActiveDistricts!$F18,lunch1920_g1to6!$F$3:$F$935) -> 347 | I18: =SUMIF(lunch1920_g1to6!$B$3:$B$935,ActiveDistricts!$F18,lunch1920_g1to6!$G$3:$G$935) -> 111 | J18: =I18/H18 -> 0.31988473
A19: 2021 | B19: 12 | C19: 0355 | F19: 0355 | G19: Ar-We-Va | H19: =SUMIF(lunch1920_g1to6!$B$3:$B$935,ActiveDistricts!$F19,lunch1920_g1to6!$F$3:$F$935) -> 95 | I19: =SUMIF(lunch1920_g1to6!$B$3:$B$935,ActiveDistricts!$F19,lunch1920_g1to6!$G$3:$G$935) -> 55 | J19: =I19/H19 -> 0.57894737
A20: 2021 | B20: 13 | C20: 0387 | F20: 0387 | G20: Atlantic | H20: =SUMIF(lunch1920_g1to6!$B$3:$B$935,ActiveDistricts!$F20,lunch1920_g1to6!$F$3:$F$935) -> 625 | I20: =SUMIF(lunch1920_g1to6!$B$3:$B$935,ActiveDistricts!$F20,lunch1920_g1to6!$G$3:$G$935) -> 350 | J20: =I20/H20 -> 0.56
A21: 2021 | B21: 11 | C21: 0414 | F21: 0414 | G21: Audubon | H21: =SUMIF(lunch1920_g1to6!$B$3:$B$935,ActiveDistricts!$F21,lunch1920_g1to6!$F$3:$F$935) -> 246 | I21: =SUMIF(lunch1920_g1to6!$B$3:$B$935,ActiveDistricts!$F21,lunch1920_g1to6!$G$3:$G$935) -> 113 | J21: =I21/H21 -> 0.45934959
A22: 2021 | B22: 11 | C22: 0472 | F22: 0472 | G22: Ballard | H22: =SUMIF(lunch1920_g1to6!$B$3:$B$935,ActiveDistricts!$F22,lunch1920_g1to6!$F$3:$F$935) -> 793 | I22: =SUMIF(lunch1920_g1to6!$B$3:$B$935,ActiveDistricts!$F22,lunch1920_g1to6!$G$3:$G$935) -> 139 | J22: =I22/H22 -> 0.17528373
A23: 2021 | B23: 11 | C23: 0513 | F23: 0513 | G23: Baxter | H23: =SUMIF(lunch1920_g1to6!$B$3:$B$935,ActiveDistricts!$F23,lunch1920_g1to6!$F$3:$F$935) -> 192 | I23: =SUMIF(lunch1920_g1to6!$B$3:$B$935,ActiveDistricts!$F23,lunch1920_g1to6!$G$3:$G$935) -> 53 | J23: =I23/H23 -> 0.27604167
A24: 2021 | B24: 07 | C24: 0540 | F24: 0540 | G24: BCLUW | H24: =SUMIF(lunch1920_g1to6!$B$3:$B$935,ActiveDistricts!$F24,lunch1920_g1to6!$F$3:$F$935) -> 226 | I24: =SUMIF(lunch1920_g1to6!$B$3:$B$935,ActiveDistricts!$F24,lunch1920_g1to6!$G$3:$G$935) -> 87 | J24: =I24/H24 -> 0.38495575
A25: 2021 | B25: 13 | C25: 0549 | F25: 0549 | G25: Bedford | H25: =SUMIF(lunch1920_g1to6!$B$3:$B$935,ActiveDistricts!$F25,lunch1920_g1to6!$F$3:$F$935) -> 225 | I25: =SUMIF(lunch1920_g1to6!$B$3:$B$935,ActiveDistricts!$F25,lunch1920_g1to6!$G$3:$G$935) -> 104 | J25: =I25/H25 -> 0.46222222
... A60: 2021 | B60: 13 | C60: 1197 | F60: 1197 | G60: Clarinda | H60: =SUMIF(lunch1920_g1to6!$B$3:$B$935,ActiveDistricts!$F60,lunch1920_g1to6!$F$3:$F$935) -> 488 | I60: =SUMIF(lunch1920_g1to6!$B$3:$B$935,ActiveDistricts!$F60,lunch1920_g1to6!$G$3:$G$935) -> 224 | J60: =I60/H60 -> 0.45901639
A61: 2021 | B61: 05 | C61: 1206 | D61: 1854 | F61: 1206 | G61: Clarion-Goldfield-Dows | H61: =SUMIF(lunch1920_g1to6!$B$3:$B$935,ActiveDistricts!$F61,lunch1920_g1to6!$F$3:$F$935) -> 400 | I61: =SUMIF(lunch1920_g1to6!$B$3:$B$935,ActiveDistricts!$F61,lunch1920_g1to6!$G$3:$G$935) -> 242 | J61: =I61/H61 -> 0.605
A62: 2021 | B62: 13 | C62: 1211 | F62: 1211 | G62: Clarke | H62: =SUMIF(lunch1920_g1to6!$B$3:$B$935,ActiveDistricts!$F62,lunch1920_g1to6!$F$3:$F$935) -> 592 | I62: =SUMIF(lunch1920_g1to6!$B$3:$B$935,ActiveDistricts!$F62,lunch1920_g1to6!$G$3:$G$935) -> 380 | J62: =I62/H62 -> 0.64189189
A63: 2021 | B63: 07 | C63: 1215 | F63: 1215 | G63: Clarksville | H63: =SUMIF(lunch1920_g1to6!$B$3:$B$935,ActiveDistricts!$F63,lunch1920_g1to6!$F$3:$F$935) -> 132 | I63: =SUMIF(lunch1920_g1to6!$B$3:$B$935,ActiveDistricts!$F63,lunch1920_g1to6!$G$3:$G$935) -> 39 | J63: =I63/H63 -> 0.29545455
A64: 2021 | B64: 05 | C64: 1218 | F64: 1218 | G64: Clay Central-Everly | H64: =SUMIF(lunch1920_g1to6!$B$3:$B$935,ActiveDistricts!$F64,lunch1920_g1to6!$F$3:$F$935) -> 65 | I64: =SUMIF(lunch1920_g1to6!$B$3:$B$935,ActiveDistricts!$F64,lunch1920_g1to6!$G$3:$G$935) -> 41 | J64: =I64/H64 -> 0.63076923
A65: 2021 | B65: 01 | C65: 2763 | F65: 2763 | G65: Clayton Ridge | H65: =SUMIF(lunch1920_g1to6!$B$3:$B$935,ActiveDistricts!$F65,lunch1920_g1to6!$F$3:$F$935) -> 365 | I65: =SUMIF(lunch1920_g1to6!$B$3:$B$935,ActiveDistricts!$F65,lunch1920_g1to6!$G$3:$G$935) -> 155 | J65: =I65/H65 -> 0.42465753
A66: 2021 | B66: 10 | C66: 1221 | D66: 0216 | F66: 1221 | G66: Clear Creek-Amana | H66: =SUMIF(lunch1920_g1to6!$B$3:$B$935,ActiveDistricts!$F66,lunch1920_g1to6!$F$3:$F$935) -> 1272 | I66: =SUMIF(lunch1920_g1to6!$B$3:$B$935,ActiveDistricts!$F66,lunch1920_g1to6!$G$3:$G$935) -> 349 | J66: =I66/H66 -> 0.27437107
A67: 2021 | B67: 07 | C67: 1233 | F67: 1233 | G67: Clear Lake | H67: =SUMIF(lunch1920_g1to6!$B$3:$B$935,ActiveDistricts!$F67,lunch1920_g1to6!$F$3:$F$935) -> 625 | I67: =SUMIF(lunch1920_g1to6!$B$3:$B$935,ActiveDistricts!$F67,lunch1920_g1to6!$G$3:$G$935) -> 217 | J67: =I67/H67 -> 0.3472
A68: 2021 | B68: 09 | C68: 1278 | F68: 1278 | G68: Clinton | H68: =SUMIF(lunch1920_g1to6!$B$3:$B$935,ActiveDistricts!$F68,lunch1920_g1to6!$F$3:$F$935) -> 1553 | I68: =SUMIF(lunch1920_g1to6!$B$3:$B$935,ActiveDistricts!$F68,lunch1920_g1to6!$G$3:$G$935) -> 908 | J68: =I68/H68 -> 0.58467482
A69: 2021 | B69: 11 | C69: 1332 | F69: 1332 | G69: Colfax-Mingo | H69: =SUMIF(lunch1920_g1to6!$B$3:$B$935,ActiveDistricts!$F69,lunch1920_g1to6!$F$3:$F$935) -> 285 | I69: =SUMIF(lunch1920_g1to6!$B$3:$B$935,ActiveDistricts!$F69,lunch1920_g1to6!$G$3:$G$935) -> 134 | J69: =I69/H69 -> 0.47017544
A70: 2021 | B70: 10 | C70: 1337 | F70: 1337 | G70: College Community | H70: =SUMIF(lunch1920_g1to6!$B$3:$B$935,ActiveDistricts!$F70,lunch1920_g1to6!$F$3:$F$935) -> 2474 | I70: =SUMIF(lunch1920_g1to6!$B$3:$B$935,ActiveDistricts!$F70,lunch1920_g1to6!$G$3:$G$935) -> 849 | J70: =I70/H70 -> 0.34316896
A71: 2021 | B71: 11 | C71: 1350 | F71: 1350 | G71: Collins-Maxwell | H71: =SUMIF(lunch1920_g1to6!$B$3:$B$935,ActiveDistricts!$F71,lunch1920_g1to6!$F$3:$F$935) -> 175 | I71: =SUMIF(lunch1920_g1to6!$B$3:$B$935,ActiveDistricts!$F71,lunch1920_g1to6!$G$3:$G$935) -> 67 | J71: =I71/H71 -> 0.38285714
A72: 2021 | B72: 11 | C72: 1359 | F72: 1359 | G72: Colo-Nesco | H72: =SUMIF(lunch1920_g1to6!$B$3:$B$935,ActiveDistricts!$F72,lunch1920_g1to6!$F$3:$F$935) -> 164 | I72: =SUMIF(lunch1920_g1to6!$B$3:$B$935,ActiveDistricts!$F72,lunch1920_g1to6!$G$3:$G$935) -> 70 | J72: =I72/H72 -> 0.42682927
A73: 2021 | B73: 09 | C73: 1368 | F73: 1368 | G73: Columbus | H73: =SUMIF(lunch1920_g1to6!$B$3:$B$935,ActiveDistricts!$F73,lunch1920_g1to6!$F$3:$F$935) -> 302 | I73: =SUMIF(lunch1920_g1to6!$B$3:$B$935,ActiveDistricts!$F73,lunch1920_g1to6!$G$3:$G$935) -> 216 | J73: =I73/H73 -> 0.71523179
A74: 2021 | B74: 11 | C74: 1413 | F74: 1413 | G74: Coon Rapids-Bayard | H74: =SUMIF(lunch1920_g1to6!$B$3:$B$935,ActiveDistricts!$F74,lunch1920_g1to6!$F$3:$F$935) -> 197 | I74: =SUMIF(lunch1920_g1to6!$B$3:$B$935,ActiveDistricts!$F74,lunch1920_g1to6!$G$3:$G$935) -> 98 | J74: =I74/H74 -> 0.49746193
A75: 2021 | B75: 13 | C75: 1431 | F75: 1431 | G75: Corning | H75: =SUMIF(lunch1920_g1to6!$B$3:$B$935,ActiveDistricts!$F75,lunch1920_g1to6!$F$3:$F$935) -> 149 | I75: =SUMIF(lunch1920_g1to6!$B$3:$B$935,ActiveDistricts!$F75,lunch1920_g1to6!$G$3:$G$935) -> 77 | J75: =I75/H75 -> 0.51677852
A76: 2021 | B76: 13 | C76: 1476 | F76: 1476 | G76: Council Bluffs | H76: =SUMIF(lunch1920_g1to6!$B$3:$B$935,ActiveDistricts!$F76,lunch1920_g1to6!$F$3:$F$935) -> 4027 | I76: =SUMIF(lunch1920_g1to6!$B$3:$B$935,ActiveDistricts!$F76,lunch1920_g1to6!$G$3:$G$935) -> 2724 | J76: =I76/H76 -> 0.67643407
A77: 2021 | B77: 13 | C77: 1503 | D77: 5328 | F77: 1503 | G77: Creston | H77: =SUMIF(lunch1920_g1to6!$B$3:$B$935,ActiveDistricts!$F77,lunch1920_g1to6!$F$3:$F$935) -> 555 | I77: =SUMIF(lunch1920_g1to6!$B$3:$B$935,ActiveDistricts!$F77,lunch1920_g1to6!$G$3:$G$935) -> 372 | J77: =I77/H77 -> 0.67027027
A78: 2021 | B78: 11 | C78: 1576 | F78: 1576 | G78: Dallas Center-Grimes | H78: =SUMIF(lunch1920_g1to6!$B$3:$B$935,ActiveDistricts!$F78,lunch1920_g1to6!$F$3:$F$935) -> 1568 | I78: =SUMIF(lunch1920_g1to6!$B$3:$B$935,ActiveDistricts!$F78,lunch1920_g1to6!$G$3:$G$935) -> 248 | J78: =I78/H78 -> 0.15816327
A79: 2021 | B79: 15 | C79: 1602 | F79: 1602 | G79: Danville | H79: =SUMIF(lunch1920_g1to6!$B$3:$B$935,ActiveDistricts!$F79,lunch1920_g1to6!$F$3:$F$935) -> 300 | I79: =SUMIF(lunch1920_g1to6!$B$3:$B$935,ActiveDistricts!$F79,lunch1920_g1to6!$G$3:$G$935) -> 96 | J79: =I79/H79 -> 0.32
A80: 2021 | B80: 09 | C80: 1611 | F80: 1611 | G80: Davenport | H80: =SUMIF(lunch1920_g1to6!$B$3:$B$935,ActiveDistricts!$F80,lunch1920_g1to6!$F$3:$F$935) -> 6503 | I80: =SUMIF(lunch1920_g1to6!$B$3:$B$935,ActiveDistricts!$F80,lunch1920_g1to6!$G$3:$G$935) -> 3790 | J80: =I80/H80 -> 0.58280793
A81: 2021 | B81: 15 | C81: 1619 | F81: 1619 | G81: Davis County | H81: =SUMIF(lunch1920_g1to6!$B$3:$B$935,ActiveDistricts!$F81,lunch1920_g1to6!$F$3:$F$935) -> 557 | I81: =SUMIF(lunch1920_g1to6!$B$3:$B$935,ActiveDistricts!$F81,lunch1920_g1to6!$G$3:$G$935) -> 310 | J81: =I81/H81 -> 0.55655296
A82: 2021 | B82: 01 | C82: 1638 | D82: 4787 | F82: 1638 | G82: Decorah | H82: =SUMIF(lunch1920_g1to6!$B$3:$B$935,ActiveDistricts!$F82,lunch1920_g1to6!$F$3:$F$935) -> 678 | I82: =SUMIF(lunch1920_g1to6!$B$3:$B$935,ActiveDistricts!$F82,lunch1920_g1to6!$G$3:$G$935) -> 176 | J82: =I82/H82 -> 0.25958702
A83: 2021 | B83: 09 | C83: 1675 | F83: 1675 | G83: Delwood | H83: =SUMIF(lunch1920_g1to6!$B$3:$B$935,ActiveDistricts!$F83,lunch1920_g1to6!$F$3:$F$935) -> 111 | I83: =SUMIF(lunch1920_g1to6!$B$3:$B$935,ActiveDistricts!$F83,lunch1920_g1to6!$G$3:$G$935) -> 46 | J83: =I83/H83 -> 0.41441441
A84: 2021 | B84: 12 | C84: 1701 | F84: 1701 | G84: Denison | H84: =SUMIF(lunch1920_g1to6!$B$3:$B$935,ActiveDistricts!$F84,lunch1920_g1to6!$F$3:$F$935) -> 953 | I84: =SUMIF(lunch1920_g1to6!$B$3:$B$935,ActiveDistricts!$F84,lunch1920_g1to6!$G$3:$G$935) -> 718 | J84: =I84/H84 -> 0.75341028
A85: 2021 | B85: 07 | C85: 1719 | F85: 1719 | G85: Denver | H85: =SUMIF(lunch1920_g1to6!$B$3:$B$935,ActiveDistricts!$F85,lunch1920_g1to6!$F$3:$F$935) -> 395 | I85: =SUMIF(lunch1920_g1to6!$B$3:$B$935,ActiveDistricts!$F85,lunch1920_g1to6!$G$3:$G$935) -> 54 | J85: =I85/H85 -> 0.13670886
A86: 2021 | B86: 11 | C86: 1737 | F86: 1737 | G86: Des Moines | H86: =SUMIF(lunch1920_g1to6!$B$3:$B$935,ActiveDistricts!$F86,lunch1920_g1to6!$F$3:$F$935) -> 14450 | I86: =SUMIF(lunch1920_g1to6!$B$3:$B$935,ActiveDistricts!$F86,lunch1920_g1to6!$G$3:$G$935) -> 11521 | J86: =I86/H86 -> 0.79730104
A87: 2021 | B87: 13 | C87: 1782 | F87: 1782 | G87: Diagonal | H87: =SUMIF(lunch1920_g1to6!$B$3:$B$935,ActiveDistricts!$F87,lunch1920_g1to6!$F$3:$F$935) -> 55 | I87: =SUMIF(lunch1920_g1to6!$B$3:$B$935,ActiveDistricts!$F87,lunch1920_g1to6!$G$3:$G$935) -> 38 | J87: =I87/H87 -> 0.69090909
A88: 2021 | B88: 07 | C88: 1791 | F88: 1791 | G88: Dike-New Hartford | H88: =SUMIF(lunch1920_g1to6!$B$3:$B$935,ActiveDistricts!$F88,lunch1920_g1to6!$F$3:$F$935) -> 388 | I88: =SUMIF(lunch1920_g1to6!$B$3:$B$935,ActiveDistricts!$F88,lunch1920_g1to6!$G$3:$G$935) -> 85 | J88: =I88/H88 -> 0.21907216
A89: 2021 | B89: 01 | C89: 1863 | F89: 1863 | G89: Dubuque | H89: =SUMIF(lunch1920_g1to6!$B$3:$B$935,ActiveDistricts!$F89,lunch1920_g1to6!$F$3:$F$935) -> 4550 | I89: =SUMIF(lunch1920_g1to6!$B$3:$B$935,ActiveDistricts!$F89,lunch1920_g1to6!$G$3:$G$935) -> 1963 | J89: =I89/H89 -> 0.43142857
A90: 2021 | B90: 07 | C90: 1908 | F90: 1908 | G90: Dunkerton | H90: =SUMIF(lunch1920_g1to6!$B$3:$B$935,ActiveDistricts!$F90,lunch1920_g1to6!$F$3:$F$935) -> 157 | I90: =SUMIF(lunch1920_g1to6!$B$3:$B$935,ActiveDistricts!$F90,lunch1920_g1to6!$G$3:$G$935) -> 57 | J90: =I90/H90 -> 0.36305732
A91: 2021 | B91: 09 | C91: 1926 | F91: 1926 | G91: Durant | H91: =SUMIF(lunch1920_g1to6!$B$3:$B$935,ActiveDistricts!$F91,lunch1920_g1to6!$F$3:$F$935) -> 263 | I91: =SUMIF(lunch1920_g1to6!$B$3:$B$935,ActiveDistricts!$F91,lunch1920_g1to6!$G$3:$G$935) -> 80 | J91: =I91/H91 -> 0.30418251
A92: 2021 | B92: 05 | C92: 1944 | F92: 1944 | G92: Eagle Grove | H92: =SUMIF(lunch1920_g1to6!$B$3:$B$935,ActiveDistricts!$F92,lunch1920_g1to6!$F$3:$F$935) -> 427 | I92: =SUMIF(lunch1920_g1to6!$B$3:$B$935,ActiveDistricts!$F92,lunch1920_g1to6!$G$3:$G$935) -> 317 | J92: =I92/H92 -> 0.74238876
A93: 2021 | B93: 11 | C93: 1953 | F93: 1953 | G93: Earlham | H93: =SUMIF(lunch1920_g1to6!$B$3:$B$935,ActiveDistricts!$F93,lunch1920_g1to6!$F$3:$F$935) -> 273 | I93: =SUMIF(lunch1920_g1to6!$B$3:$B$935,ActiveDistricts!$F93,lunch1920_g1to6!$G$3:$G$935) -> 84 | J93: =I93/H93 -> 0.30769231
A94: 2021 | B94: 07 | C94: 1963 | F94: 1963 | G94: East Buchanan | H94: =SUMIF(lunch1920_g1to6!$B$3:$B$935,ActiveDistricts!$F94,lunch1920_g1to6!$F$3:$F$935) -> 246 | I94: =SUMIF(lunch1920_g1to6!$B$3:$B$935,ActiveDistricts!$F94,lunch1920_g1to6!$G$3:$G$935) -> 86 | J94: =I94/H94 -> 0.3495935
A95: 2021 | B95: 07 | C95: 3582 | F95: 1968 | G95: East Marshall | H95: =SUMIF(lunch1920_g1to6!$B$3:$B$935,ActiveDistricts!$F95,lunch1920_g1to6!$F$3:$F$935) -> 355 | I95: =SUMIF(lunch1920_g1to6!$B$3:$B$935,ActiveDistricts!$F95,lunch1920_g1to6!$G$3:$G$935) -> 163 | J95: =I95/H95 -> 0.45915493
A96: 2021 | B96: 13 | C96: 3978 | D96: 4751 | F96: 3978 | G96: East Mills | H96: =SUMIF(lunch1920_g1to6!$B$3:$B$935,ActiveDistricts!$F96,lunch1920_g1to6!$F$3:$F$935) -> 178 | I96: =SUMIF(lunch1920_g1to6!$B$3:$B$935,ActiveDistricts!$F96,lunch1920_g1to6!$G$3:$G$935) -> 91 | J96: =I96/H96 -> 0.51123596
A97: 2021 | B97: 05 | C97: 6741 | F97: 6741 | G97: East Sac County | H97: =SUMIF(lunch1920_g1to6!$B$3:$B$935,ActiveDistricts!$F97,lunch1920_g1to6!$F$3:$F$935) -> 348 | I97: =SUMIF(lunch1920_g1to6!$B$3:$B$935,ActiveDistricts!$F97,lunch1920_g1to6!$G$3:$G$935) -> 185 | J97: =I97/H97 -> 0.5316092
A98: 2021 | B98: 13 | C98: 1970 | F98: 1970 | G98: East Union | H98: =SUMIF(lunch1920_g1to6!$B$3:$B$935,ActiveDistricts!$F98,lunch1920_g1to6!$F$3:$F$935) -> 229 | I98: =SUMIF(lunch1920_g1to6!$B$3:$B$935,ActiveDistricts!$F98,lunch1920_g1to6!$G$3:$G$935) -> 160 | J98: =I98/H98 -> 0.69868996
A99: 2021 | B99: 01 | C99: 1972 | F99: 1972 | G99: Eastern Allamakee | H99: =SUMIF(lunch1920_g1to6!$B$3:$B$935,ActiveDistricts!$F99,lunch1920_g1to6!$F$3:$F$935) -> 125 | I99: =SUMIF(lunch1920_g1to6!$B$3:$B$935,ActiveDistricts!$F99,lunch1920_g1to6!$G$3:$G$935) -> 51 | J99: =I99/H99 -> 0.408
A100: 2021 | B100: 09 | C100: 1965 | F100: 1965 | G100: Easton Valley | H100: =SUMIF(lunch1920_g1to6!$B$3:$B$935,ActiveDistricts!$F100,lunch1920_g1to6!$F$3:$F$935) -> 191 | I100: =SUMIF(lunch1920_g1to6!$B$3:$B$935,ActiveDistricts!$F100,lunch1920_g1to6!$G$3:$G$935) -> 91 | J100: =I100/H100 -> 0.47643979
A101: 2021 | B101: 15 | C101: 0657 | F101: 0657 | G101: Eddyville-Blakesburg-Fremont | H101: =SUMIF(lunch1920_g1to6!$B$3:$B$935,ActiveDistricts!$F101,lunch1920_g1to6!$F$3:$F$935) -> 452 | I101: =SUMIF(lunch1920_g1to6!$B$3:$B$935,ActiveDistricts!$F101,lunch1920_g1to6!$G$3:$G$935) -> 183 | J101: =I101/H101 -> 0.40486726
A102: 2021 | B102: 01 | C102: 1989 | F102: 1989 | G102: Edgewood-Colesburg | H102: =SUMIF(lunch1920_g1to6!$B$3:$B$935,ActiveDistricts!$F102,lunch1920_g1to6!$F$3:$F$935) -> 227 | I102: =SUMIF(lunch1920_g1to6!$B$3:$B$935,ActiveDistricts!$F102,lunch1920_g1to6!$G$3:$G$935) -> 83 | J102: =I102/H102 -> 0.36563877
A103: 2021 | B103: 07 | C103: 2007 | F103: 2007 | G103: Eldora-New Providence | H103: =SUMIF(lunch1920_g1to6!$B$3:$B$935,ActiveDistricts!$F103,lunch1920_g1to6!$F$3:$F$935) -> 222 | I103: =SUMIF(lunch1920_g1to6!$B$3:$B$935,ActiveDistricts!$F103,lunch1920_g1to6!$G$3:$G$935) -> 124 | J103: =I103/H103 -> 0.55855856
A104: 2021 | B104: 05 | C104: 2088 | F104: 2088 | G104: Emmetsburg | H104: =SUMIF(lunch1920_g1to6!$B$3:$B$935,ActiveDistricts!$F104,lunch1920_g1to6!$F$3:$F$935) -> 299 | I104: =SUMIF(lunch1920_g1to6!$B$3:$B$935,ActiveDistricts!$F104,lunch1920_g1to6!$G$3:$G$935) -> 149 | J104: =I104/H104 -> 0.49832776
A105: 2021 | B105: 10 | C105: 2097 | F105: 2097 | G105: English Valleys | H105: =SUMIF(lunch1920_g1to6!$B$3:$B$935,ActiveDistricts!$F105,lunch1920_g1to6!$F$3:$F$935) -> 188 | I105: =SUMIF(lunch1920_g1to6!$B$3:$B$935,ActiveDistricts!$F105,lunch1920_g1to6!$G$3:$G$935) -> 79 | J105: =I105/H105 -> 0.42021277
A106: 2021 | B106: 13 | C106: 2113 | F106: 2113 | G106: Essex | H106: =SUMIF(lunch1920_g1to6!$B$3:$B$935,ActiveDistricts!$F106,lunch1920_g1to6!$F$3:$F$935) -> 72 | I106: =SUMIF(lunch1920_g1to6!$B$3:$B$935,ActiveDistricts!$F106,lunch1920_g1to6!$G$3:$G$935) -> 51 | J106: =I106/H106 -> 0.70833333
A107: 2021 | B107: 05 | C107: 2124 | F107: 2124 | G107: Estherville-Lincoln Central | H107: =SUMIF(lunch1920_g1to6!$B$3:$B$935,ActiveDistricts!$F107,lunch1920_g1to6!$F$3:$F$935) -> 494 | I107: =SUMIF(lunch1920_g1to6!$B$3:$B$935,ActiveDistricts!$F107,lunch1920_g1to6!$G$3:$G$935) -> 271 | J107: =I107/H107 -> 0.548583
A108: 2021 | B108: 11 | C108: 2151 | F108: 2151 | G108: Exira-Elk Horn-Kimballton | H108: =SUMIF(lunch1920_g1to6!$B$3:$B$935,ActiveDistricts!$F108,lunch1920_g1to6!$F$3:$F$935) -> 160 | I108: =SUMIF(lunch1920_g1to6!$B$3:$B$935,ActiveDistricts!$F108,lunch1920_g1to6!$G$3:$G$935) -> 77 | J108: =I108/H108 -> 0.48125
... A170: 2021 | B170: 05 | C170: 4023 | F170: 4023 | G170: Manson-Northwest Webster | H170: =SUMIF(lunch1920_g1to6!$B$3:$B$935,ActiveDistricts!$F170,lunch1920_g1to6!$F$3:$F$935) -> 320 | I170: =SUMIF(lunch1920_g1to6!$B$3:$B$935,ActiveDistricts!$F170,lunch1920_g1to6!$G$3:$G$935) -> 103 | J170: =I170/H170 -> 0.321875
A171: 2021 | B171: 12 | C171: 4033 | D171: 0270 | F171: 4033 | G171: Maple Valley-Anthon Oto | H171: =SUMIF(lunch1920_g1to6!$B$3:$B$935,ActiveDistricts!$F171,lunch1920_g1to6!$F$3:$F$935) -> 239 | I171: =SUMIF(lunch1920_g1to6!$B$3:$B$935,ActiveDistricts!$F171,lunch1920_g1to6!$G$3:$G$935) -> 141 | J171: =I171/H171 -> 0.58995816
A172: 2021 | B172: 09 | C172: 4041 | F172: 4041 | G172: Maquoketa | H172: =SUMIF(lunch1920_g1to6!$B$3:$B$935,ActiveDistricts!$F172,lunch1920_g1to6!$F$3:$F$935) -> 482 | I172: =SUMIF(lunch1920_g1to6!$B$3:$B$935,ActiveDistricts!$F172,lunch1920_g1to6!$G$3:$G$935) -> 299 | J172: =I172/H172 -> 0.62033195
A173: 2021 | B173: 01 | C173: 4043 | F173: 4043 | G173: Maquoketa Valley | H173: =SUMIF(lunch1920_g1to6!$B$3:$B$935,ActiveDistricts!$F173,lunch1920_g1to6!$F$3:$F$935) -> 314 | I173: =SUMIF(lunch1920_g1to6!$B$3:$B$935,ActiveDistricts!$F173,lunch1920_g1to6!$G$3:$G$935) -> 95 | J173: =I173/H173 -> 0.30254777
A174: 2021 | B174: 12 | C174: 4068 | F174: 4068 | G174: Marcus-Meriden Cleghorn | H174: =SUMIF(lunch1920_g1to6!$B$3:$B$935,ActiveDistricts!$F174,lunch1920_g1to6!$F$3:$F$935) -> 112 | I174: =SUMIF(lunch1920_g1to6!$B$3:$B$935,ActiveDistricts!$F174,lunch1920_g1to6!$G$3:$G$935) -> 36 | J174: =I174/H174 -> 0.32142857
A175: 2021 | B175: 10 | C175: 4086 | F175: 4086 | G175: Marion | H175: =SUMIF(lunch1920_g1to6!$B$3:$B$935,ActiveDistricts!$F175,lunch1920_g1to6!$F$3:$F$935) -> 926 | I175: =SUMIF(lunch1920_g1to6!$B$3:$B$935,ActiveDistricts!$F175,lunch1920_g1to6!$G$3:$G$935) -> 341 | J175: =I175/H175 -> 0.36825054
A176: 2021 | B176: 07 | C176: 4104 | F176: 4104 | G176: Marshalltown | H176: =SUMIF(lunch1920_g1to6!$B$3:$B$935,ActiveDistricts!$F176,lunch1920_g1to6!$F$3:$F$935) -> 2244 | I176: =SUMIF(lunch1920_g1to6!$B$3:$B$935,ActiveDistricts!$F176,lunch1920_g1to6!$G$3:$G$935) -> 1302 | J176: =I176/H176 -> 0.5802139
A177: 2021 | B177: 11 | C177: 4122 | F177: 4122 | G177: Martensdale-St Marys | H177: =SUMIF(lunch1920_g1to6!$B$3:$B$935,ActiveDistricts!$F177,lunch1920_g1to6!$F$3:$F$935) -> 231 | I177: =SUMIF(lunch1920_g1to6!$B$3:$B$935,ActiveDistricts!$F177,lunch1920_g1to6!$G$3:$G$935) -> 67 | J177: =I177/H177 -> 0.29004329
A178: 2021 | B178: 07 | C178: 4131 | F178: 4131 | G178: Mason City | H178: =SUMIF(lunch1920_g1to6!$B$3:$B$935,ActiveDistricts!$F178,lunch1920_g1to6!$F$3:$F$935) -> 1681 | I178: =SUMIF(lunch1920_g1to6!$B$3:$B$935,ActiveDistricts!$F178,lunch1920_g1to6!$G$3:$G$935) -> 954 | J178: =I178/H178 -> 0.56751933
A179: 2021 | B179: 15 | C179: 4203 | F179: 4203 | G179: Mediapolis | H179: =SUMIF(lunch1920_g1to6!$B$3:$B$935,ActiveDistricts!$F179,lunch1920_g1to6!$F$3:$F$935) -> 428 | I179: =SUMIF(lunch1920_g1to6!$B$3:$B$935,ActiveDistricts!$F179,lunch1920_g1to6!$G$3:$G$935) -> 112 | J179: =I179/H179 -> 0.26168224
A180: 2021 | B180: 11 | C180: 4212 | F180: 4212 | G180: Melcher-Dallas | H180: =SUMIF(lunch1920_g1to6!$B$3:$B$935,ActiveDistricts!$F180,lunch1920_g1to6!$F$3:$F$935) -> 145 | I180: =SUMIF(lunch1920_g1to6!$B$3:$B$935,ActiveDistricts!$F180,lunch1920_g1to6!$G$3:$G$935) -> 63 | J180: =I180/H180 -> 0.43448276
A181: 2021 | B181: 01 | C181: 4419 | F181: 4419 | G181: MFL Mar Mac | H181: =SUMIF(lunch1920_g1to6!$B$3:$B$935,ActiveDistricts!$F181,lunch1920_g1to6!$F$3:$F$935) -> 351 | I181: =SUMIF(lunch1920_g1to6!$B$3:$B$935,ActiveDistricts!$F181,lunch1920_g1to6!$G$3:$G$935) -> 134 | J181: =I181/H181 -> 0.38176638
A182: 2021 | B182: 10 | C182: 4269 | F182: 4269 | G182: Midland | H182: =SUMIF(lunch1920_g1to6!$B$3:$B$935,ActiveDistricts!$F182,lunch1920_g1to6!$F$3:$F$935) -> 187 | I182: =SUMIF(lunch1920_g1to6!$B$3:$B$935,ActiveDistricts!$F182,lunch1920_g1to6!$G$3:$G$935) -> 87 | J182: =I182/H182 -> 0.46524064
A183: 2021 | B183: 10 | C183: 4271 | F183: 4271 | G183: Mid-Prairie | H183: =SUMIF(lunch1920_g1to6!$B$3:$B$935,ActiveDistricts!$F183,lunch1920_g1to6!$F$3:$F$935) -> 648 | I183: =SUMIF(lunch1920_g1to6!$B$3:$B$935,ActiveDistricts!$F183,lunch1920_g1to6!$G$3:$G$935) -> 188 | J183: =I183/H183 -> 0.29012346
... A203: 2021 | B203: 13 | C203: 2673 | F203: 2673 | G203: Nodaway Valley | H203: =SUMIF(lunch1920_g1to6!$B$3:$B$935,ActiveDistricts!$F203,lunch1920_g1to6!$F$3:$F$935) -> 254 | I203: =SUMIF(lunch1920_g1to6!$B$3:$B$935,ActiveDistricts!$F203,lunch1920_g1to6!$G$3:$G$935) -> 117 | J203: =I203/H203 -> 0.46062992
A204: 2021 | B204: 07 | C204: 0153 | D204: 2664 | F204: 0153 | G204: North Butler | H204: =SUMIF(lunch1920_g1to6!$B$3:$B$935,ActiveDistricts!$F204,lunch1920_g1to6!$F$3:$F$935) -> 245 | I204: =SUMIF(lunch1920_g1to6!$B$3:$B$935,ActiveDistricts!$F204,lunch1920_g1to6!$G$3:$G$935) -> 83 | J204: =I204/H204 -> 0.33877551
A205: 2021 | B205: 10 | C205: 3691 | F205: 3691 | G205: North Cedar | H205: =SUMIF(lunch1920_g1to6!$B$3:$B$935,ActiveDistricts!$F205,lunch1920_g1to6!$F$3:$F$935) -> 259 | I205: =SUMIF(lunch1920_g1to6!$B$3:$B$935,ActiveDistricts!$F205,lunch1920_g1to6!$G$3:$G$935) -> 121 | J205: =I205/H205 -> 0.46718147
A206: 2021 | B206: 01 | C206: 4774 | D206: 6591 | F206: 4774 | G206: North Fayette Valley | H206: =SUMIF(lunch1920_g1to6!$B$3:$B$935,ActiveDistricts!$F206,lunch1920_g1to6!$F$3:$F$935) -> 482 | I206: =SUMIF(lunch1920_g1to6!$B$3:$B$935,ActiveDistricts!$F206,lunch1920_g1to6!$G$3:$G$935) -> 192 | J206: =I206/H206 -> 0.39834025
A207: 2021 | B207: 07 | C207: 0873 | F207: 0873 | G207: North Iowa | H207: =SUMIF(lunch1920_g1to6!$B$3:$B$935,ActiveDistricts!$F207,lunch1920_g1to6!$F$3:$F$935) -> 208 | I207: =SUMIF(lunch1920_g1to6!$B$3:$B$935,ActiveDistricts!$F207,lunch1920_g1to6!$G$3:$G$935) -> 105 | J207: =I207/H207 -> 0.50480769
A208: 2021 | B208: 05 | C208: 4778 | F208: 4778 | G208: North Kossuth | H208: =SUMIF(lunch1920_g1to6!$B$3:$B$935,ActiveDistricts!$F208,lunch1920_g1to6!$F$3:$F$935) -> 148 | I208: =SUMIF(lunch1920_g1to6!$B$3:$B$935,ActiveDistricts!$F208,lunch1920_g1to6!$G$3:$G$935) -> 94 | J208: =I208/H208 -> 0.63513514
A209: 2021 | B209: 10 | C209: 4777 | F209: 4777 | G209: North Linn | H209: =SUMIF(lunch1920_g1to6!$B$3:$B$935,ActiveDistricts!$F209,lunch1920_g1to6!$F$3:$F$935) -> 228 | I209: =SUMIF(lunch1920_g1to6!$B$3:$B$935,ActiveDistricts!$F209,lunch1920_g1to6!$G$3:$G$935) -> 68 | J209: =I209/H209 -> 0.29824561
A210: 2021 | B210: 15 | C210: 4776 | F210: 4776 | G210: North Mahaska | H210: =SUMIF(lunch1920_g1to6!$B$3:$B$935,ActiveDistricts!$F210,lunch1920_g1to6!$F$3:$F$935) -> 258 | I210: =SUMIF(lunch1920_g1to6!$B$3:$B$935,ActiveDistricts!$F210,lunch1920_g1to6!$G$3:$G$935) -> 96 | J210: =I210/H210 -> 0.37209302
A211: 2021 | B211: 11 | C211: 4779 | F211: 4779 | G211: North Polk | H211: =SUMIF(lunch1920_g1to6!$B$3:$B$935,ActiveDistricts!$F211,lunch1920_g1to6!$F$3:$F$935) -> 826 | I211: =SUMIF(lunch1920_g1to6!$B$3:$B$935,ActiveDistricts!$F211,lunch1920_g1to6!$G$3:$G$935) -> 78 | J211: =I211/H211 -> 0.094430993
A212: 2021 | B212: 09 | C212: 4784 | F212: 4784 | G212: North Scott | H212: =SUMIF(lunch1920_g1to6!$B$3:$B$935,ActiveDistricts!$F212,lunch1920_g1to6!$F$3:$F$935) -> 1386 | I212: =SUMIF(lunch1920_g1to6!$B$3:$B$935,ActiveDistricts!$F212,lunch1920_g1to6!$G$3:$G$935) -> 334 | J212: =I212/H212 -> 0.24098124
A213: 2021 | B213: 07 | C213: 4785 | F213: 4785 | G213: North Tama | H213: =SUMIF(lunch1920_g1to6!$B$3:$B$935,ActiveDistricts!$F213,lunch1920_g1to6!$F$3:$F$935) -> 181 | I213: =SUMIF(lunch1920_g1to6!$B$3:$B$935,ActiveDistricts!$F213,lunch1920_g1to6!$G$3:$G$935) -> 70 | J213: =I213/H213 -> 0.38674033
A214: 2021 | B214: 05 | C214: 0333 | F214: 0333 | G214: North Union | H214: =SUMIF(lunch1920_g1to6!$B$3:$B$935,ActiveDistricts!$F214,lunch1920_g1to6!$F$3:$F$935) -> 108 | I214: =SUMIF(lunch1920_g1to6!$B$3:$B$935,ActiveDistricts!$F214,lunch1920_g1to6!$G$3:$G$935) -> 57 | J214: =I214/H214 -> 0.52777778
...

Sheet Constants
A1: FiscalYear | B1: SPG | C1: CPP | D1: Additional_Dollar | E1: SCPP | F1: SCPP_SPED | G1: TS_SPG | H1: TS_CPP | I1: TS_SCPP | J1: PD_SPG | K1: PD_CPP | L1: PD_SCPP | M1: EI_SPG | N1: EI_CPP | O1: EI_SCPP | P1: TL_SPG | Q1: TL_CPP | R1: TL_SCPP | S1: AEA_SPED_CPP | T1: AEA_SPED_SCPP | U1: AEAMED_CPP | V1: AEAMED_SCPP | W1: AEAED_CPP | X1: AEAED_SCPP | Y1: TS_AEA_CPP | Z1: TS_AEA_SCPP | AA1: PD_AEA_CPP | AB1: PD_AEA_SCPP | AC1: RPFL | AD1: RPFL_CPP | AE1: RPSPEDFL | AF1: RPSPED_CPP | AG1: AEA_SPED_FL | AH1: AEASPED_CPP | AI1: Budg_Adj | AJ1: ULR | AK1: MIN_AID | AL1: PT_SCPP | AM1: PT_PCT | AN1: SMAAPTLR | AO1: AEA_SPED_FL_CPP | AP1: PTRP_PP | AQ1: StateTaxableValuation_PP | AR1: TAG_PP | AS1: PY_RPFL | AT1: PY_SCPP | AU1: L833 | AV1: ISL_StateAidPortion | AW1: ISL_ProrataRed
A2: 1973 | B2: 0.04928 | C2: 45 | D2: 0 | E2: 903 | AC2: 0.7 | AD2: =ROUND(AC2*E2,0) -> 632 | AE2: 0 | AF2: =ROUND(AE2*F2,0) -> 0 | AM2: =1-AC2 -> 0.3
A3: 1974 | B3: 0.05 | C3: =ROUND(E2*B3,0) -> 45 | D3: 0 | E3: =E2+C3+D3 -> 948 | AC3: 0.71 | AD3: =ROUND(AC3*E3,0) -> 673 | AE3: 0 | AF3: =ROUND(AE3*F3,0) -> 0 | AM3: =1-AC3 -> 0.29 | AS3: =INDEX($A$2:$AZ$100,MATCH($A3-1,$A$2:$A$100,0),30) -> 632 | AT3: =INDEX($A$2:$AZ$100,MATCH($A3-1,$A$2:$A$100,0),5) -> 903
A4: 1975 | B4: 0.08 | C4: =ROUND(E3*B4,0) -> 76 | D4: 0 | E4: =E3+C4+D4 -> 1024 | AC4: 0.72 | AD4: =ROUND(AC4*E4,0) -> 737 | AE4: 0 | AF4: =ROUND(AE4*F4,0) -> 0 | AM4: =1-AC4 -> 0.28 | AS4: =INDEX($A$2:$AZ$100,MATCH($A4-1,$A$2:$A$100,0),30) -> 673 | AT4: =INDEX($A$2:$AZ$100,MATCH($A4-1,$A$2:$A$100,0),5) -> 948
A5: 1976 | B5: 0.107 | C5: =ROUND(E4*B5,0) -> 110 | D5: 0 | E5: =E4+C5+D5 -> 1134 | F5: =E5 -> 1134 | T5: 40.43 | V5: 6.08 | X5: 10.16 | AC5: 0.73 | AD5: =ROUND(AC5*E5,0) -> 828 | AE5: 0.73 | AF5: =ROUND(AE5*F5,0) -> 828 | AG5: 0.73 | AH5: =ROUND(AG5*T5,0) -> 30 | AM5: =1-AC5 -> 0.27 | AO5: =ROUND(T5*AG5,0) -> 30 | AS5: =INDEX($A$2:$AZ$100,MATCH($A5-1,$A$2:$A$100,0),30) -> 737 | AT5: =INDEX($A$2:$AZ$100,MATCH($A5-1,$A$2:$A$100,0),5) -> 1024
A6: 1977 | B6: 0.09825 | C6: =ROUND(E5*B6,0) -> 111 | D6: 0 | E6: =E5+C6+D6 -> 1245 | F6: =E6 -> 1245 | T6: 48.47 | V6: 6.57 | X6: 11.3 | AC6: 0.74 | AD6: =ROUND(AC6*E6,0) -> 921 | AE6: 0.74 | AF6: =ROUND(AE6*F6,0) -> 921 | AG6: 0.74 | AH6: =ROUND(AG6*T6,0) -> 36 | AM6: =1-AC6 -> 0.26 | AO6: =ROUND(T6*AG6,0) -> 36 | AS6: =INDEX($A$2:$AZ$100,MATCH($A6-1,$A$2:$A$100,0),30) -> 828 | AT6: =INDEX($A$2:$AZ$100,MATCH($A6-1,$A$2:$A$100,0),5) -> 1134
A7: 1978 | B7: 0.0784 | C7: =ROUND(E6*B7,0) -> 98 | D7: 0 | E7: =E6+C7+D7 -> 1343 | F7: =E7 -> 1343 | T7: 55.14 | V7: 6.84 | X7: 12.14 | AC7: 0.75 | AD7: =ROUND(AC7*E7,0) -> 1007 | AE7: 0.75 | AF7: =ROUND(AE7*F7,0) -> 1007 | AG7: 0.75 | AH7: =ROUND(AG7*T7,0) -> 41 | AM7: =1-AC7 -> 0.25 | AO7: =ROUND(T7*AG7,0) -> 41 | AS7: =INDEX($A$2:$AZ$100,MATCH($A7-1,$A$2:$A$100,0),30) -> 921 | AT7: =INDEX($A$2:$AZ$100,MATCH($A7-1,$A$2:$A$100,0),5) -> 1245
A8: 1979 | B8: 0.09422 | C8: =ROUND(E7*B8,0) -> 127 | D8: 0 | E8: =E7+C8+D8 -> 1470 | F8: =E8 -> 1470 | T8: 55.18 | V8: 11.05 | X8: 13.61 | AC8: 0.76 | AD8: =ROUND(AC8*E8,0) -> 1117 | AE8: 0.76 | AF8: =ROUND(AE8*F8,0) -> 1117 | AG8: 0.76 | AH8: =ROUND(AG8*T8,0) -> 42 | AM8: =1-AC8 -> 0.24 | AO8: =ROUND(T8*AG8,0) -> 42 | AS8: =INDEX($A$2:$AZ$100,MATCH($A8-1,$A$2:$A$100,0),30) -> 1007 | AT8: =INDEX($A$2:$AZ$100,MATCH($A8-1,$A$2:$A$100,0),5) -> 1343
A9: 1980 | B9: 0.09484 | C9: =ROUND(E8*B9,0) -> 139 | D9: 0 | E9: =E8+C9+D9 -> 1609 | F9: =E9 -> 1609 | T9: 74.37 | V9: 12.76 | X9: 15.32 | AC9: 0.77 | AD9: =ROUND(AC9*E9,0) -> 1239 | AE9: 0.77 | AF9: =ROUND(AE9*F9,0) -> 1239 | AG9: 0.77 | AH9: =ROUND(AG9*T9,0) -> 57 | AM9: =1-AC9 -> 0.23 | AO9: =ROUND(T9*AG9,0) -> 57 | AS9: =INDEX($A$2:$AZ$100,MATCH($A9-1,$A$2:$A$100,0),30) -> 1117 | AT9: =INDEX($A$2:$AZ$100,MATCH($A9-1,$A$2:$A$100,0),5) -> 1470
A10: 1981 | B10: 0.13592 | C10: =ROUND(E9*B10,0) -> 219 | D10: 20 | E10: =E9+C10+D10 -> 1848 | F10: =E10 -> 1848 | T10: 88.07 | V10: 14.86 | X10: 18.03 | AC10: 0.77 | AD10: =ROUND(AC10*E10,0) -> 1423 | AE10: 0.77 | AF10: =ROUND(AE10*F10,0) -> 1423 | AG10: 0.77 | AH10: =ROUND(AG10*T10,0) -> 68 | AM10: =1-AC10 -> 0.23 | AO10: =ROUND(T10*AG10,0) -> 68 | AS10: =INDEX($A$2:$AZ$100,MATCH($A10-1,$A$2:$A$100,0),30) -> 1239 | AT10: =INDEX($A$2:$AZ$100,MATCH($A10-1,$A$2:$A$100,0),5) -> 1609
A11: 1982 | B11: 0.05 | C11: =ROUND(E10*B11,0) -> 92 | D11: 0 | E11: =E10+C11+D11 -> 1940 | F11: =E11 -> 1940 | T11: 88.07 | V11: 16 | X11: 18.5 | AC11: 0.77 | AD11: =ROUND(AC11*E11,0) -> 1494 | AE11: 0.77 | AF11: =ROUND(AE11*F11,0) -> 1494 | AG11: 0.77 | AH11: =ROUND(AG11*T11,0) -> 68 | AM11: =1-AC11 -> 0.23 | AO11: =ROUND(T11*AG11,0) -> 68 | AS11: =INDEX($A$2:$AZ$100,MATCH($A11-1,$A$2:$A$100,0),30) -> 1423 | AT11: =INDEX($A$2:$AZ$100,MATCH($A11-1,$A$2:$A$100,0),5) -> 1848
A12: 1983 | B12: 0.07 | C12: =ROUND(E11*B12,0) -> 136 | D12: 13 | E12: =E11+C12+D12 -> 2089 | F12: =E12 -> 2089 | S12: =ROUND(T11*$B12,2) -> 6.16 | T12: =S12+T11 -> 94.23 | V12: 17.12 | X12: 19.8 | AC12: 0.77 | AD12: =ROUND(AC12*E12,0) -> 1609 | AE12: 0.77 | AF12: =ROUND(AE12*F12,0) -> 1609 | AG12: 0.77 | AH12: =ROUND(AG12*T12,0) -> 73 | AM12: =1-AC12 -> 0.23 | AO12: =ROUND(T12*AG12,0) -> 73 | AS12: =INDEX($A$2:$AZ$100,MATCH($A12-1,$A$2:$A$100,0),30) -> 1494 | AT12: =INDEX($A$2:$AZ$100,MATCH($A12-1,$A$2:$A$100,0),5) -> 1940
A13: 1984 | B13: 0.06103 | C13: =ROUND(E12*B13,0) -> 127 | D13: 8 | E13: =E12+C13+D13 -> 2224 | F13: =E13 -> 2224 | S13: =ROUND(T12*$B13,2) -> 5.75 | T13: =S13+T12 -> 99.98 | V13: 18.16 | X13: 21.01 | AC13: 0.78 | AD13: =ROUND(AC13*E13,0) -> 1735 | AE13: 0.78 | AF13: =ROUND(AE13*F13,0) -> 1735 | AG13: 0.78 | AH13: =ROUND(AG13*T13,0) -> 78 | AJ13: 5.4 | AK13: 200 | AM13: =1-AC13 -> 0.22 | AO13: =ROUND(T13*AG13,0) -> 78 | AS13: =INDEX($A$2:$AZ$100,MATCH($A13-1,$A$2:$A$100,0),30) -> 1609 | AT13: =INDEX($A$2:$AZ$100,MATCH($A13-1,$A$2:$A$100,0),5) -> 2089
A14: 1985 | B14: 0.0254 | C14: =ROUND(E13*B14,0) -> 56 | D14: 8 | E14: =E13+C14+D14 -> 2288 | F14: =E14 -> 2288 | S14: =ROUND(T13*$B14,2) -> 2.54 | T14: =S14+T13 -> 102.52 | V14: 18.62 | X14: 21.54 | AC14: 0.79 | AD14: =ROUND(AC14*E14,0) -> 1808 | AE14: 0.79 | AF14: =ROUND(AE14*F14,0) -> 1808 | AG14: 0.79 | AH14: =ROUND(AG14*T14,0) -> 81 | AJ14: 5.4 | AK14: 200 | AM14: =1-AC14 -> 0.21 | AO14: =ROUND(T14*AG14,0) -> 81 | AS14: =INDEX($A$2:$AZ$100,MATCH($A14-1,$A$2:$A$100,0),30) -> 1735 | AT14: =INDEX($A$2:$AZ$100,MATCH($A14-1,$A$2:$A$100,0),5) -> 2224
A15: 1986 | B15: 0.05325 | C15: =ROUND(E14*B15,0) -> 122 | D15: 0 | E15: =E14+C15+D15 -> 2410 | F15: =E15 -> 2410 | S15: =ROUND(T14*$B15,2) -> 5.46 | T15: =S15+T14 -> 107.98 | V15: 19.61 | X15: 22.69 | AC15: 0.8 | AD15: =ROUND(AC15*E15,0) -> 1928 | AE15: 0.8 | AF15: =ROUND(AE15*F15,0) -> 1928 | AG15: 0.8 | AH15: =ROUND(AG15*T15,0) -> 86 | AJ15: 5.4 | AK15: 200 | AM15: =1-AC15 -> 0.2 | AO15: =ROUND(T15*AG15,0) -> 86 | AS15: =INDEX($A$2:$AZ$100,MATCH($A15-1,$A$2:$A$100,0),30) -> 1808 | AT15: =INDEX($A$2:$AZ$100,MATCH($A15-1,$A$2:$A$100,0),5) -> 2288
A16: 1987 | B16: 0.03843 | C16: =ROUND(E15*B16,0) -> 93 | D16: 0 | E16: =E15+C16+D16 -> 2503 | F16: =E16 -> 2503 | S16: =ROUND(T15*$B16,2) -> 4.15 | T16: =S16+T15 -> 112.13 | V16: 21.37 | X16: 23.56 | AC16: 0.8 | AD16: =ROUND(AC16*E16,0) -> 2002 | AE16: 0.8 | AF16: =ROUND(AE16*F16,0) -> 2002 | AG16: 0.8 | AH16: =ROUND(AG16*T16,0) -> 90 | AJ16: 5.4 | AK16: 200 | AM16: =1-AC16 -> 0.2 | AO16: =ROUND(T16*AG16,0) -> 90 | AS16: =INDEX($A$2:$AZ$100,MATCH($A16-1,$A$2:$A$100,0),30) -> 1928 | AT16: =INDEX($A$2:$AZ$100,MATCH($A16-1,$A$2:$A$100,0),5) -> 2410
A17: 1988 | B17: 0.03469 | C17: =ROUND(E16*B17,0) -> 87 | D17: 0 | E17: =E16+C17+D17 -> 2590 | F17: =E17 -> 2590 | S17: =ROUND(T16*$B17,2) -> 3.89 | T17: =S17+T16 -> 116.02 | V17: 22.11 | X17: 24.38 | AC17: 0.815 | AD17: =ROUND(AC17*E17,0) -> 2111 | AE17: 0.815 | AF17: =ROUND(AE17*F17,0) -> 2111 | AG17: 0.815 | AH17: =ROUND(AG17*T17,0) -> 95 | AJ17: 5.4 | AK17: 200 | AM17: =1-AC17 -> 0.185 | AO17: =ROUND(T17*AG17,0) -> 95 | AS17: =INDEX($A$2:$AZ$100,MATCH($A17-1,$A$2:$A$100,0),30) -> 2002 | AT17: =INDEX($A$2:$AZ$100,MATCH($A17-1,$A$2:$A$100,0),5) -> 2503
A18: 1989 | B18: 0.03592 | C18: =ROUND(E17*B18,0) -> 93 | D18: 0 | E18: =E17+C18+D18 -> 2683 | F18: =E18 -> 2683 | S18: =ROUND(T17*$B18,2) -> 4.17 | T18: =S18+T17 -> 120.19 | V18: 22.9 | X18: 25.26 | AC18: 0.82 | AD18: =ROUND(AC18*E18,0) -> 2200 | AE18: 0.82 | AF18: =ROUND(AE18*F18,0) -> 2200 | AG18: 0.82 | AH18: =ROUND(AG18*T18,0) -> 99 | AJ18: 5.4 | AK18: 200 | AM18: =1-AC18 -> 0.18 | AO18: =ROUND(T18*AG18,0) -> 99 | AS18: =INDEX($A$2:$AZ$100,MATCH($A18-1,$A$2:$A$100,0),30) -> 2111 | AT18: =INDEX($A$2:$AZ$100,MATCH($A18-1,$A$2:$A$100,0),5) -> 2590
A19: 1990 | B19: 0.03534 | C19: =ROUND(E18*B19,0) -> 95 | D19: 0 | E19: =E18+C19+D19 -> 2778 | F19: =E19 -> 2778 | S19: =ROUND(T18*$B19,2) -> 4.25 | T19: =S19+T18 -> 124.44 | V19: 22.9 | X19: 25.26 | AC19: 0.825 | AD19: =ROUND(AC19*E19,0) -> 2292 | AE19: 0.825 | AF19: =ROUND(AE19*F19,0) -> 2292 | AG19: 0.825 | AH19: =ROUND(AG19*T19,0) -> 103 | AJ19: 5.4 | AK19: 200 | AM19: =1-AC19 -> 0.175 | AO19: =ROUND(T19*AG19,0) -> 103 | AS19: =INDEX($A$2:$AZ$100,MATCH($A19-1,$A$2:$A$100,0),30) -> 2200 | AT19: =INDEX($A$2:$AZ$100,MATCH($A19-1,$A$2:$A$100,0),5) -> 2683
A20: 1991 | B20: 0.07182 | C20: =ROUND(E19*B20,0) -> 200 | D20: 0 | E20: =E19+C20+D20 -> 2978 | F20: =E20 -> 2978 | S20: =ROUND(T19*$B20,2) -> 8.94 | T20: =S20+T19 -> 133.38 | V20: 25.41 | X20: 28.03 | AC20: 0.83 | AD20: =ROUND(AC20*E20,0) -> 2472 | AE20: 0.83 | AF20: =ROUND(AE20*F20,0) -> 2472 | AG20: 0.83 | AH20: =ROUND(AG20*T20,0) -> 111 | AJ20: 5.4 | AK20: 200 | AM20: =1-AC20 -> 0.17 | AO20: =ROUND(T20*AG20,0) -> 111 | AS20: =INDEX($A$2:$AZ$100,MATCH($A20-1,$A$2:$A$100,0),30) -> 2292 | AT20: =INDEX($A$2:$AZ$100,MATCH($A20-1,$A$2:$A$100,0),5) -> 2778
A21: 1992 | B21: 0.0434 | C21: =ROUND(E20*B21,0) -> 129 | D21: 96 | E21: =E20+C21+D21 -> 3203 | F21: =E21 -> 3203 | S21: =ROUND(T20*$B21,2) -> 5.79 | T21: 141.97 | V21: 26.48 | X21: 29.21 | AC21: 0.83 | AD21: =ROUND(AC21*E21,0) -> 2658 | AE21: 0.83 | AF21: =ROUND(AE21*F21,0) -> 2658 | AG21: 0.83 | AH21: =ROUND(AG21*T21,0) -> 118 | AJ21: 5.4 | AK21: 300 | AM21: =1-AC21 -> 0.17 | AO21: =ROUND(T21*AG21,0) -> 118 | AS21: =INDEX($A$2:$AZ$100,MATCH($A21-1,$A$2:$A$100,0),30) -> 2472 | AT21: =INDEX($A$2:$AZ$100,MATCH($A21-1,$A$2:$A$100,0),5) -> 2978
A22: 1993 | B22: 0.04151 | C22: =ROUND(E21*B22,0) -> 133 | D22: 0 | E22: =E21+C22+D22 -> 3336 | F22: =E22 -> 3336 | S22: =ROUND(T21*$B22,2) -> 5.89 | T22: =S22+T21 -> 147.86 | U22: =ROUND(V21*$B22,2) -> 1.1 | V22: =U22+V21 -> 27.58 | W22: =ROUND(X21*$B22,2) -> 1.21 | X22: =W22+X21 -> 30.42 | AC22: 0.83 | AD22: =ROUND(AC22*E22,0) -> 2769 | AE22: 0.79 | AF22: =ROUND(AE22*F22,0) -> 2635 | AG22: 0.79 | AH22: =ROUND(AG22*T22,0) -> 117 | AJ22: 5.4 | AK22: 300 | AM22: =1-AC22 -> 0.17 | AO22: =ROUND(T22*AG22,0) -> 117 | AS22: =INDEX($A$2:$AZ$100,MATCH($A22-1,$A$2:$A$100,0),30) -> 2658 | AT22: =INDEX($A$2:$AZ$100,MATCH($A22-1,$A$2:$A$100,0),5) -> 3203
A23: 1994 | B23: 0.021 | C23: =ROUND(E22*B23,0) -> 70 | D23: 0 | E23: =E22+C23+D23 -> 3406 | F23: =E23 -> 3406 | S23: =ROUND(T22*$B23,2) -> 3.11 | T23: =S23+T22 -> 150.97 | U23: =ROUND(V22*$B23,2) -> 0.58 | V23: =U23+V22 -> 28.16 | W23: =ROUND(X22*$B23,2) -> 0.64 | X23: =W23+X22 -> 31.06 | AC23: 0.83 | AD23: =ROUND(AC23*E23,0) -> 2827 | AE23: 0.79 | AF23: =ROUND(AE23*F23,0) -> 2691 | AG23: 0.79 | AH23: =ROUND(AG23*T23,0) -> 119 | AJ23: 5.4 | AK23: 300 | AM23: =1-AC23 -> 0.17 | AO23: =ROUND(T23*AG23,0) -> 119 | AS23: =INDEX($A$2:$AZ$100,MATCH($A23-1,$A$2:$A$100,0),30) -> 2769 | AT23: =INDEX($A$2:$AZ$100,MATCH($A23-1,$A$2:$A$100,0),5) -> 3336
A24: 1995 | B24: 0.0285 | C24: =ROUND(E23*B24,0) -> 97 | D24: 0 | E24: =E23+C24+D24 -> 3503 | F24: =E24 -> 3503 | S24: =ROUND(T23*$B24,2) -> 4.3 | T24: =S24+T23 -> 155.27 | U24: =ROUND(V23*$B24,2) -> 0.8 | V24: =U24+V23 -> 28.96 | W24: =ROUND(X23*$B24,2) -> 0.89 | X24: =W24+X23 -> 31.95 | AC24: 0.83 | AD24: =ROUND(AC24*E24,0) -> 2907 | AE24: 0.79 | AF24: =ROUND(AE24*F24,0) -> 2767 | AG24: 0.79 | AH24: =ROUND(AG24*T24,0) -> 123 | AJ24: 5.4 | AK24: 300 | AM24: =1-AC24 -> 0.17 | AO24: =ROUND(T24*AG24,0) -> 123 | AS24: =INDEX($A$2:$AZ$100,MATCH($A24-1,$A$2:$A$100,0),30) -> 2827 | AT24: =INDEX($A$2:$AZ$100,MATCH($A24-1,$A$2:$A$100,0),5) -> 3406
A25: 1996 | B25: 0.035 | C25: =ROUND(E24*B25,0) -> 123 | D25: 0 | E25: =E24+C25+D25 -> 3626 | F25: =E25 -> 3626 | S25: =ROUND(T24*$B25,2) -> 5.43 | T25: =S25+T24 -> 160.7 | U25: =ROUND(V24*$B25,2) -> 1.01 | V25: =U25+V24 -> 29.97 | W25: =ROUND(X24*$B25,2) -> 1.12 | X25: =W25+X24 -> 33.07 | AC25: 0.83 | AD25: =ROUND(AC25*E25,0) -> 3010 | AE25: 0.79 | AF25: =ROUND(AE25*F25,0) -> 2865 | AG25: 0.79 | AH25: =ROUND(AG25*T25,0) -> 127 | AI25: 1 | AJ25: 5.4 | AK25: 300 | AM25: =1-AC25 -> 0.17 | AO25: =ROUND(T25*AG25,0) -> 127 | AS25: =INDEX($A$2:$AZ$100,MATCH($A25-1,$A$2:$A$100,0),30) -> 2907 | AT25: =INDEX($A$2:$AZ$100,MATCH($A25-1,$A$2:$A$100,0),5) -> 3503
A26: 1997 | B26: 0.033 | C26: =ROUND(E25*B26,0) -> 120 | D26: 0 | E26: =E25+C26+D26 -> 3746 | F26: =E26 -> 3746 | S26: =ROUND(T25*$B26,2) -> 5.3 | T26: =S26+T25 -> 166 | U26: =ROUND(V25*$B26,2) -> 0.99 | V26: =U26+V25 -> 30.96 | W26: =ROUND(X25*$B26,2) -> 1.09 | X26: =W26+X25 -> 34.16 | AC26: 0.875 | AD26: =ROUND(AC26*E26,0) -> 3278 | AE26: 0.79 | AF26: =ROUND(AE26*F26,0) -> 2959 | AG26: 0.79 | AH26: =ROUND(AG26*T26,0) -> 131 | AI26: 1 | AJ26: 5.4 | AK26: 300 | AM26: =1-AC26 -> 0.125 | AO26: =ROUND(T26*AG26,0) -> 131 | AS26: =INDEX($A$2:$AZ$100,MATCH($A26-1,$A$2:$A$100,0),30) -> 3010 | AT26: =INDEX($A$2:$AZ$100,MATCH($A26-1,$A$2:$A$100,0),5) -> 3626
A27: 1998 | B27: 0.035 | C27: =ROUND(E26*B27,0) -> 131 | D27: 0 | E27: =E26+C27+D27 -> 3877 | F27: =E27 -> 3877 | S27: =ROUND(T26*$B27,2) -> 5.81 | T27: =S27+T26 -> 171.81 | U27: =ROUND(V26*$B27,2) -> 1.08 | V27: =U27+V26 -> 32.04 | W27: =ROUND(X26*$B27,2) -> 1.2 | X27: =W27+X26 -> 35.36 | AC27: 0.875 | AD27: =ROUND(AC27*E27,0) -> 3392 | AE27: 0.79 | AF27: =ROUND(AE27*F27,0) -> 3063 | AG27: 0.79 | AH27: =ROUND(AG27*T27,0) -> 136 | AI27: 1 | AJ27: 5.4 | AK27: 300 | AM27: =1-AC27 -> 0.125 | AO27: =ROUND(T27*AG27,0) -> 136 | AS27: =INDEX($A$2:$AZ$100,MATCH($A27-1,$A$2:$A$100,0),30) -> 3278 | AT27: =INDEX($A$2:$AZ$100,MATCH($A27-1,$A$2:$A$100,0),5) -> 3746
A28: 1999 | B28: 0.035 | C28: =ROUND(E27*B28,0) -> 136 | D28: 0 | E28: =E27+C28+D28 -> 4013 | F28: =E28 -> 4013 | S28: =ROUND(T27*$B28,2) -> 6.01 | T28: =S28+T27 -> 177.82 | U28: =ROUND(V27*$B28,2) -> 1.12 | V28: =U28+V27 -> 33.16 | W28: =ROUND(X27*$B28,2) -> 1.24 | X28: =W28+X27 -> 36.6 | AC28: 0.875 | AD28: =ROUND(AC28*E28,0) -> 3511 | AE28: 0.79 | AF28: =ROUND(AE28*F28,0) -> 3170 | AG28: 0.79 | AH28: =ROUND(AG28*T28,0) -> 140 | AI28: 1 | AJ28: 5.4 | AK28: 300 | AM28: =1-AC28 -> 0.125 | AO28: =ROUND(T28*AG28,0) -> 140 | AS28: =INDEX($A$2:$AZ$100,MATCH($A28-1,$A$2:$A$100,0),30) -> 3392 | AT28: =INDEX($A$2:$AZ$100,MATCH($A28-1,$A$2:$A$100,0),5) -> 3877
A29: 2000 | B29: 0.03 | C29: =ROUND(E28*B29,0) -> 120 | D29: 38 | E29: =E28+C29+D29 -> 4171 | F29: =E29 -> 4171 | S29: =ROUND(T28*$B29,2) -> 5.33 | T29: =S29+T28 -> 183.15 | U29: =ROUND(V28*$B29,2) -> 0.99 | V29: =U29+V28 -> 34.15 | W29: =ROUND(X28*$B29,2) -> 1.1 | X29: =W29+X28 -> 37.7 | AC29: 0.875 | AD29: =ROUND(AC29*E29,0) -> 3650 | AE29: 0.875 | AF29: =ROUND(AE29*F29,0) -> 3650 | AG29: 0.79 | AH29: =ROUND(AG29*T29,0) -> 145 | AI29: 1 | AJ29: 5.4 | AK29: 300 | AM29: =1-AC29 -> 0.125 | AO29: =ROUND(T29*AG29,0) -> 145 | AR29: =D29 -> 38 | AS29: =INDEX($A$2:$AZ$100,MATCH($A29-1,$A$2:$A$100,0),30) -> 3511 | AT29: =INDEX($A$2:$AZ$100,MATCH($A29-1,$A$2:$A$100,0),5) -> 4013
A30: 2001 | B30: 0.04 | C30: =ROUND(E29*B30,0) -> 167 | D30: 0 | E30: =E29+C30+D30 -> 4338 | F30: =E30 -> 4338 | S30: =ROUND(T29*$B30,2) -> 7.33 | T30: =S30+T29 -> 190.48 | U30: =ROUND(V29*$B30,2) -> 1.37 | V30: =U30+V29 -> 35.52 | W30: =ROUND(X29*$B30,2) -> 1.51 | X30: =W30+X29 -> 39.21 | AC30: 0.875 | AD30: =ROUND(AC30*E30,0) -> 3796 | AE30: 0.875 | AF30: =ROUND(AE30*F30,0) -> 3796 | AG30: 0.79 | AH30: =ROUND(AG30*T30,0) -> 150 | AI30: 1 | AJ30: 5.4 | AK30: 300 | AM30: =1-AC30 -> 0.125 | AO30: =ROUND(T30*AG30,0) -> 150 | AR30: =ROUND(AR29*(1+B30),0) -> 40 | AS30: =INDEX($A$2:$AZ$100,MATCH($A30-1,$A$2:$A$100,0),30) -> 3650 | AT30: =INDEX($A$2:$AZ$100,MATCH($A30-1,$A$2:$A$100,0),5) -> 4171
A31: 2002 | B31: 0.04 | C31: =ROUND(E30*B31,0) -> 174 | D31: 0 | E31: =E30+C31+D31 -> 4512 | F31: =E31 -> 4512 | S31: =ROUND(T30*$B31,2) -> 7.62 | T31: =S31+T30 -> 198.1 | U31: =ROUND(V30*$B31,2) -> 1.42 | V31: =U31+V30 -> 36.94 | W31: =ROUND(X30*$B31,2) -> 1.57 | X31: =W31+X30 -> 40.78 | AC31: 0.875 | AD31: =ROUND(AC31*E31,0) -> 3948 | AE31: 0.875 | AF31: =ROUND(AE31*F31,0) -> 3948 | AG31: 0.79 | AH31: =ROUND(AG31*T31,0) -> 156 | AI31: 1 | AJ31: 5.4 | AK31: 300 | AM31: =1-AC31 -> 0.125 | AO31: =ROUND(T31*AG31,0) -> 156 | AR31: =ROUND(AR30*(1+B31),0) -> 42 | AS31: =INDEX($A$2:$AZ$100,MATCH($A31-1,$A$2:$A$100,0),30) -> 3796 | AT31: =INDEX($A$2:$AZ$100,MATCH($A31-1,$A$2:$A$100,0),5) -> 4338
A32: 2003 | B32: 0.01 | C32: =ROUND(E31*B32,0) -> 45 | D32: 0 | E32: =E31+C32+D32 -> 4557 | F32: =E32 -> 4557 | S32: =ROUND(T31*$B32,2) -> 1.98 | T32: =S32+T31 -> 200.08 | U32: =ROUND(V31*$B32,2) -> 0.37 | V32: =U32+V31 -> 37.31 | W32: =ROUND(X31*$B32,2) -> 0.41 | X32: =W32+X31 -> 41.19 | AC32: 0.875 | AD32: =ROUND(AC32*E32,0) -> 3987 | AE32: 0.875 | AF32: =ROUND(AE32*F32,0) -> 3987 | AG32: 0.79 | AH32: =ROUND(AG32*T32,0) -> 158 | AI32: 1 | AJ32: 5.4 | AK32: 300 | AM32: =1-AC32 -> 0.125 | AO32: =ROUND(T32*AG32,0) -> 158 | AR32: =ROUND(AR31*(1+B32),0) -> 42 | AS32: =INDEX($A$2:$AZ$100,MATCH($A32-1,$A$2:$A$100,0),30) -> 3948 | AT32: =INDEX($A$2:$AZ$100,MATCH($A32-1,$A$2:$A$100,0),5) -> 4512
A33: 2004 | B33: 0.02 | C33: =ROUND(E32*B33,0) -> 91 | D33: 0 | E33: =E32+C33+D33 -> 4648 | F33: =E33 -> 4648 | S33: =ROUND(T32*$B33,2) -> 4 | T33: =S33+T32 -> 204.08 | U33: =ROUND(V32*$B33,2) -> 0.75 | V33: =U33+V32 -> 38.06 | W33: =ROUND(X32*$B33,2) -> 0.82 | X33: =W33+X32 -> 42.01 | AC33: 0.875 | AD33: =ROUND(AC33*E33,0) -> 4067 | AE33: 0.875 | AF33: =ROUND(AE33*F33,0) -> 4067 | AG33: 0.79 | AH33: =ROUND(AG33*T33,0) -> 161 | AI33: 1 | AJ33: 5.4 | AK33: 300 | AM33: =1-AC33 -> 0.125 | AO33: =ROUND(T33*AG33,0) -> 161 | AR33: =ROUND(AR32*(1+B33),0) -> 43 | AS33: =INDEX($A$2:$AZ$100,MATCH($A33-1,$A$2:$A$100,0),30) -> 3987 | AT33: =INDEX($A$2:$AZ$100,MATCH($A33-1,$A$2:$A$100,0),5) -> 4557
A34: 2005 | B34: 0.02 | C34: =ROUND(E33*B34,0) -> 93 | D34: 0 | E34: =E33+C34+D34 -> 4741 | F34: =E34 -> 4741 | S34: =ROUND(T33*$B34,2) -> 4.08 | T34: =S34+T33 -> 208.16 | U34: =ROUND(V33*$B34,2) -> 0.76 | V34: =U34+V33 -> 38.82 | W34: =ROUND(X33*$B34,2) -> 0.84 | X34: =W34+X33 -> 42.85 | AC34: 0.875 | AD34: =ROUND(AC34*E34,0) -> 4148 | AE34: 0.875 | AF34: =ROUND(AE34*F34,0) -> 4148 | AG34: 0.79 | AH34: =ROUND(AG34*T34,0) -> 164 | AI34: 1.01 | AJ34: 5.4 | AK34: 300 | AM34: =1-AC34 -> 0.125 | AO34: =ROUND(T34*AG34,0) -> 164 | AR34: =ROUND(AR33*(1+B34),0) -> 44 | AS34: =INDEX($A$2:$AZ$100,MATCH($A34-1,$A$2:$A$100,0),30) -> 4067 | AT34: =INDEX($A$2:$AZ$100,MATCH($A34-1,$A$2:$A$100,0),5) -> 4648
A35: 2006 | B35: 0.04 | C35: =ROUND(E34*B35,0) -> 190 | D35: 0 | E35: =E34+C35+D35 -> 4931 | F35: =E35 -> 4931 | S35: =ROUND(T34*$B35,2) -> 8.33 | T35: =S35+T34 -> 216.49 | U35: =ROUND(V34*$B35,2) -> 1.55 | V35: =U35+V34 -> 40.37 | W35: =ROUND(X34*$B35,2) -> 1.71 | X35: =W35+X34 -> 44.56 | AC35: 0.875 | AD35: =ROUND(AC35*E35,0) -> 4315 | AE35: 0.875 | AF35: =ROUND(AE35*F35,0) -> 4315 | AG35: 0.79 | AH35: =ROUND(AG35*T35,0) -> 171 | AI35: 1.01 | AJ35: 5.4 | AK35: 300 | AM35: =1-AC35 -> 0.125 | AO35: =ROUND(T35*AG35,0) -> 171 | AR35: =ROUND(AR34*(1+B35),0) -> 46 | AS35: =INDEX($A$2:$AZ$100,MATCH($A35-1,$A$2:$A$100,0),30) -> 4148 | AT35: =INDEX($A$2:$AZ$100,MATCH($A35-1,$A$2:$A$100,0),5) -> 4741
A36: 2007 | B36: 0.04 | C36: =ROUND(E35*B36,0) -> 197 | D36: 0 | E36: =E35+C36+D36 -> 5128 | F36: =E36 -> 5128 | S36: =ROUND(T35*$B36,2) -> 8.66 | T36: =S36+T35 -> 225.15 | U36: =ROUND(V35*$B36,2) -> 1.61 | V36: =U36+V35 -> 41.98 | W36: =ROUND(X35*$B36,2) -> 1.78 | X36: =W36+X35 -> 46.34 | AC36: 0.875 | AD36: =ROUND(AC36*E36,0) -> 4487 | AE36: 0.875 | AF36: =ROUND(AE36*F36,0) -> 4487 | AG36: 0.79 | AH36: =ROUND(AG36*T36,0) -> 178 | AI36: 1.01 | AJ36: 5.4 | AK36: 300 | AM36: =1-AC36 -> 0.125 | AN36: 4.72424 | AO36: =ROUND(T36*AG36,0) -> 178 | AR36: =ROUND(AR35*(1+B36),0) -> 48 | AS36: =INDEX($A$2:$AZ$100,MATCH($A36-1,$A$2:$A$100,0),30) -> 4315 | AT36: =INDEX($A$2:$AZ$100,MATCH($A36-1,$A$2:$A$100,0),5) -> 4931
A37: 2008 | B37: 0.04 | C37: =ROUND(E36*B37,0) -> 205 | D37: 0 | E37: =E36+C37+D37 -> 5333 | F37: =E37 -> 5333 | S37: =ROUND(T36*$B37,2) -> 9.01 | T37: =S37+T36 -> 234.16 | U37: =ROUND(V36*$B37,2) -> 1.68 | V37: =U37+V36 -> 43.66 | W37: =ROUND(X36*$B37,2) -> 1.85 | X37: =W37+X36 -> 48.19 | AC37: 0.875 | AD37: =ROUND(AC37*E37,0) -> 4666 | AE37: 0.875 | AF37: =ROUND(AE37*F37,0) -> 4666 | AG37: 0.79 | AH37: =ROUND(AG37*T37,0) -> 185 | AI37: 1.01 | AJ37: 5.4 | AK37: 300 | AM37: =1-AC37 -> 0.125 | AN37: 4.44454 | AO37: =ROUND(T37*AG37,0) -> 185 | AR37: =ROUND(AR36*(1+B37),0) -> 50 | AS37: =INDEX($A$2:$AZ$100,MATCH($A37-1,$A$2:$A$100,0),30) -> 4487 | AT37: =INDEX($A$2:$AZ$100,MATCH($A37-1,$A$2:$A$100,0),5) -> 5128
A38: 2009 | B38: 0.04 | C38: =ROUND(E37*B38,0) -> 213 | D38: 0 | E38: =E37+C38+D38 -> 5546 | F38: =E38 -> 5546 | S38: =ROUND(T37*$B38,2) -> 9.37 | T38: =S38+T37 -> 243.53 | U38: =ROUND(V37*$B38,2) -> 1.75 | V38: =U38+V37 -> 45.41 | W38: =ROUND(X37*$B38,2) -> 1.93 | X38: =W38+X37 -> 50.12 | AC38: 0.875 | AD38: =ROUND(AC38*E38,0) -> 4853 | AE38: 0.875 | AF38: =ROUND(AE38*F38,0) -> 4853 | AG38: 0.79 | AH38: =ROUND(AG38*T38,0) -> 192 | AI38: 1.01 | AJ38: 5.4 | AK38: 300 | AM38: =1-AC38 -> 0.125 | AN38: 4.14488 | AO38: =ROUND(T38*AG38,0) -> 192 | AR38: =ROUND(AR37*(1+B38),0) -> 52 | AS38: =INDEX($A$2:$AZ$100,MATCH($A38-1,$A$2:$A$100,0),30) -> 4666 | AT38: =INDEX($A$2:$AZ$100,MATCH($A38-1,$A$2:$A$100,0),5) -> 5333
A39: 2010 | B39: 0.04 | C39: =ROUND(E38*B39,0) -> 222 | D39: 0 | E39: =E38+C39+D39 -> 5768 | F39: =E39 -> 5768 | I39: 497.09 | L39: 56.29 | O39: 61.32 | S39: =ROUND(T38*$B39,2) -> 9.74 | T39: =S39+T38 -> 253.27 | U39: =ROUND(V38*$B39,2) -> 1.82 | V39: =U39+V38 -> 47.23 | W39: =ROUND(X38*$B39,2) -> 2 | X39: =W39+X38 -> 52.12 | Z39: 26.02 | AB39: 3.04 | AC39: 0.875 | AD39: =ROUND(AC39*E39,0) -> 5047 | AE39: 0.875 | AF39: =ROUND(AE39*F39,0) -> 5047 | AG39: 0.79 | AH39: =ROUND(AG39*T39,0) -> 200 | AI39: 1.01 | AJ39: 5.4 | AK39: 300 | AM39: =1-AC39 -> 0.125 | AN39: 3.92924 | AO39: =ROUND(T39*AG39,0) -> 200 | AR39: =ROUND(AR38*(1+B39),0) -> 54 | AS39: =INDEX($A$2:$AZ$100,MATCH($A39-1,$A$2:$A$100,0),30) -> 4853 | AT39: =INDEX($A$2:$AZ$100,MATCH($A39-1,$A$2:$A$100,0),5) -> 5546
A40: 2011 | B40: 0.02 | C40: =ROUND(E39*B40,0) -> 115 | D40: 0 | E40: =E39+C40+D40 -> 5883 | F40: =E40 -> 5883 | G40: =$B40 -> 0.02 | H40: =ROUND(I39*$G40,2) -> 9.94 | I40: =H40+I39 -> 507.03 | J40: =$B40 -> 0.02 | K40: =ROUND(L39*$J40,2) -> 1.13 | L40: =K40+L39 -> 57.42 | M40: =$B40 -> 0.02 | N40: =ROUND(O39*$M40,2) -> 1.23 | O40: =N40+O39 -> 62.55 | S40: =ROUND(T39*$B40,2) -> 5.07 | T40: =S40+T39 -> 258.34 | U40: =ROUND(V39*$B40,2) -> 0.94 | V40: =U40+V39 -> 48.17 | W40: =ROUND(X39*$B40,2) -> 1.04 | X40: =W40+X39 -> 53.16 | Y40: =ROUND(Z39*$B40,2) -> 0.52 | Z40: =Y40+Z39 -> 26.54 | AA40: =ROUND(AB39*$B40,2) -> 0.06 | AB40: =AA40+AB39 -> 3.1 | AC40: 0.875 | AD40: =ROUND(AC40*E40,0) -> 5148 | AE40: 0.875 | AF40: =ROUND(AE40*F40,0) -> 5148 | AG40: 0.79 | AH40: =ROUND(AG40*T40,0) -> 204 | AI40: 1.01 | AJ40: 5.4 | AK40: 300 | AM40: =1-AC40 -> 0.125 | AN40: 3.2606 | AO40: =ROUND(T40*AG40,0) -> 204 | AR40: =ROUND(AR39*(1+B40),0) -> 55 | AS40: =INDEX($A$2:$AZ$100,MATCH($A40-1,$A$2:$A$100,0),30) -> 5047 | AT40: =INDEX($A$2:$AZ$100,MATCH($A40-1,$A$2:$A$100,0),5) -> 5768
A41: 2012 | B41: 0 | C41: =ROUND(E40*B41,0) -> 0 | D41: 0 | E41: =E40+C41+D41 -> 5883 | F41: =E41 -> 5883 | G41: =$B41 -> 0 | H41: =ROUND(I40*$G41,2) -> 0 | I41: =H41+I40 -> 507.03 | J41: =$B41 -> 0 | K41: =ROUND(L40*$J41,2) -> 0 | L41: =K41+L40 -> 57.42 | M41: =$B41 -> 0 | N41: =ROUND(O40*$M41,2) -> 0 | O41: =N41+O40 -> 62.55 | S41: =ROUND(T40*$B41,2) -> 0 | T41: =S41+T40 -> 258.34 | U41: =ROUND(V40*$B41,2) -> 0 | V41: =U41+V40 -> 48.17 | W41: =ROUND(X40*$B41,2) -> 0 | X41: =W41+X40 -> 53.16 | Y41: =ROUND(Z40*$B41,2) -> 0 | Z41: =Y41+Z40 -> 26.54 | AA41: =ROUND(AB40*$B41,2) -> 0 | AB41: =AA41+AB40 -> 3.1 | AC41: 0.875 | AD41: =ROUND(AC41*E41,0) -> 5148 | AE41: 0.875 | AF41: =ROUND(AE41*F41,0) -> 5148 | AG41: 0.79 | AH41: =ROUND(AG41*T41,0) -> 204 | AI41: 1.01 | AJ41: 5.4 | AK41: 300 | AM41: =1-AC41 -> 0.125 | AN41: 3.51216 | AO41: =ROUND(T41*AG41,0) -> 204 | AR41: =ROUND(AR40*(1+B41),0) -> 55 | AS41: =INDEX($A$2:$AZ$100,MATCH($A41-1,$A$2:$A$100,0),30) -> 5148 | AT41: =INDEX($A$2:$AZ$100,MATCH($A41-1,$A$2:$A$100,0),5) -> 5883
A42: 2013 | B42: 0.02 | C42: =ROUND(E41*B42,0) -> 118 | D42: 0 | E42: =E41+C42+D42 -> 6001 | F42: =E42 -> 6001 | G42: =$B42 -> 0.02 | H42: =ROUND(I41*$G42,2) -> 10.14 | I42: =H42+I41 -> 517.17 | J42: =$B42 -> 0.02 | K42: =ROUND(L41*$J42,2) -> 1.15 | L42: =K42+L41 -> 58.57 | M42: =$B42 -> 0.02 | N42: =ROUND(O41*$M42,2) -> 1.25 | O42: =N42+O41 -> 63.8 | S42: =ROUND(T41*$B42,2) -> 5.17 | T42: =S42+T41 -> 263.51 | U42: =ROUND(V41*$B42,2) -> 0.96 | V42: =U42+V41 -> 49.13 | W42: =ROUND(X41*$B42,2) -> 1.06 | X42: =W42+X41 -> 54.22 | Y42: =ROUND(Z41*$B42,2) -> 0.53 | Z42: =Y42+Z41 -> 27.07 | AA42: =ROUND(AB41*$B42,2) -> 0.06 | AB42: =AA42+AB41 -> 3.16 | AC42: 0.875 | AD42: =ROUND(AC42*E42,0) -> 5251 | AE42: 0.875 | AF42: =ROUND(AE42*F42,0) -> 5251 | AG42: 0.79 | AH42: =ROUND(AG42*T42,0) -> 208 | AI42: 1.01 | AJ42: 5.4 | AK42: 300 | AM42: =1-AC42 -> 0.125 | AN42: 3.46875 | AO42: =ROUND(T42*AG42,0) -> 208 | AR42: =ROUND(AR41*(1+B42),0) -> 56 | AS42: =INDEX($A$2:$AZ$100,MATCH($A42-1,$A$2:$A$100,0),30) -> 5148 | AT42: =INDEX($A$2:$AZ$100,MATCH($A42-1,$A$2:$A$100,0),5) -> 5883
A43: 2014 | B43: 0.02 | C43: =ROUND(E42*B43,0) -> 120 | D43: 0 | E43: =E42+C43+D43 -> 6121 | F43: =E43 -> 6121 | G43: =$B43 -> 0.02 | H43: =ROUND(I42*$G43,2) -> 10.34 | I43: =H43+I42 -> 527.51 | J43: =$B43 -> 0.02 | K43: =ROUND(L42*$J43,2) -> 1.17 | L43: =K43+L42 -> 59.74 | M43: =$B43 -> 0.02 | N43: =ROUND(O42*$M43,2) -> 1.28 | O43: =N43+O42 -> 65.08 | S43: =ROUND(T42*$B43,2) -> 5.27 | T43: =S43+T42 -> 268.78 | U43: =ROUND(V42*$B43,2) -> 0.98 | V43: =U43+V42 -> 50.11 | W43: =ROUND(X42*$B43,2) -> 1.08 | X43: =W43+X42 -> 55.3 | Y43: =ROUND(Z42*$B43,2) -> 0.54 | Z43: =Y43+Z42 -> 27.61 | AA43: =ROUND(AB42*$B43,2) -> 0.06 | AB43: =AA43+AB42 -> 3.22 | AC43: 0.875 | AD43: =ROUND(AC43*E43,0) -> 5356 | AE43: 0.875 | AF43: =ROUND(AE43*F43,0) -> 5356 | AG43: 0.79 | AH43: =ROUND(AG43*T43,0) -> 212 | AI43: 1.01 | AJ43: 5.4 | AK43: 300 | AL43: 750 | AM43: =1-AC43 -> 0.125 | AN43: 3.34158 | AO43: =ROUND(T43*AG43,0) -> 212 | AP43: =E43-AD43-AL43 -> 15 | AR43: =ROUND(AR42*(1+B43),0) -> 57 | AS43: =INDEX($A$2:$AZ$100,MATCH($A43-1,$A$2:$A$100,0),30) -> 5251 | AT43: =INDEX($A$2:$AZ$100,MATCH($A43-1,$A$2:$A$100,0),5) -> 6001
A44: 2015 | B44: 0.04 | C44: =ROUND(E43*B44,0) -> 245 | D44: 0 | E44: =E43+C44+D44 -> 6366 | F44: =E44 -> 6366 | G44: =$B44 -> 0.04 | H44: =ROUND(I43*$G44,2) -> 21.1 | I44: =H44+I43 -> 548.61 | J44: =$B44 -> 0.04 | K44: =ROUND(L43*$J44,2) -> 2.39 | L44: =K44+L43 -> 62.13 | M44: =$B44 -> 0.04 | N44: =ROUND(O43*$M44,2) -> 2.6 | O44: =N44+O43 -> 67.68 | R44: 308.82 | S44: =ROUND(T43*$B44,2) -> 10.75 | T44: =S44+T43 -> 279.53 | U44: =ROUND(V43*$B44,2) -> 2 | V44: =U44+V43 -> 52.11 | W44: =ROUND(X43*$B44,2) -> 2.21 | X44: =W44+X43 -> 57.51 | Y44: =ROUND(Z43*$B44,2) -> 1.1 | Z44: =Y44+Z43 -> 28.71 | AA44: =ROUND(AB43*$B44,2) -> 0.13 | AB44: =AA44+AB43 -> 3.35 | AC44: 0.875 | AD44: =ROUND(AC44*E44,0) -> 5570 | AE44: 0.875 | AF44: =ROUND(AE44*F44,0) -> 5570 | AG44: 0.79 | AH44: =ROUND(AG44*T44,0) -> 221 | AI44: 1.01 | AJ44: 5.4 | AK44: 300 | AL44: 750 | AM44: =1-AC44 -> 0.125 | AN44: 3.38985 | AO44: =ROUND(T44*AG44,0) -> 221 | AP44: =E44-AD44-AL44 -> 46 | AR44: =ROUND(AR43*(1+B44),0) -> 59 | AS44: =INDEX($A$2:$AZ$100,MATCH($A44-1,$A$2:$A$100,0),30) -> 5356 | AT44: =INDEX($A$2:$AZ$100,MATCH($A44-1,$A$2:$A$100,0),5) -> 6121
A45: 2016 | B45: 0.0125 | C45: =ROUND(E44*B45,0) -> 80 | D45: 0 | E45: =E44+C45+D45 -> 6446 | F45: =E45 -> 6446 | G45: =$B45 -> 0.0125 | H45: =ROUND(I44*$G45,2) -> 6.86 | I45: =H45+I44 -> 555.47 | J45: =$B45 -> 0.0125 | K45: =ROUND(L44*$J45,2) -> 0.78 | L45: =K45+L44 -> 62.91 | M45: =$B45 -> 0.0125 | N45: =ROUND(O44*$M45,2) -> 0.85 | O45: =N45+O44 -> 68.53 | P45: =$B45 -> 0.0125 | Q45: =ROUND(R44*$P45,2) -> 3.86 | R45: =Q45+R44 -> 312.68 | S45: =ROUND(T44*$B45,2) -> 3.49 | T45: =S45+T44 -> 283.02 | U45: =ROUND(V44*$B45,2) -> 0.65 | V45: =U45+V44 -> 52.76 | W45: =ROUND(X44*$B45,2) -> 0.72 | X45: =W45+X44 -> 58.23 | Y45: =ROUND(Z44*$B45,2) -> 0.36 | Z45: =Y45+Z44 -> 29.07 | AA45: =ROUND(AB44*$B45,2) -> 0.04 | AB45: =AA45+AB44 -> 3.39 | AC45: 0.875 | AD45: =ROUND(AC45*E45,0) -> 5640 | AE45: 0.875 | AF45: =ROUND(AE45*F45,0) -> 5640 | AG45: 0.79 | AH45: =ROUND(AG45*T45,0) -> 224 | AI45: 1.01 | AJ45: 5.4 | AK45: 300 | AL45: 750 | AM45: =1-AC45 -> 0.125 | AN45: 3.4121 | AO45: =ROUND(T45*AG45,0) -> 224 | AP45: =E45-AD45-AL45 -> 56 | AR45: =ROUND(AR44*(1+B45),0) -> 60 | AS45: =INDEX($A$2:$AZ$100,MATCH($A45-1,$A$2:$A$100,0),30) -> 5570 | AT45: =INDEX($A$2:$AZ$100,MATCH($A45-1,$A$2:$A$100,0),5) -> 6366
A46: 2017 | B46: 0.0225 | C46: =ROUND(E45*B46,0) -> 145 | E46: =E45+C46+D46 -> 6591 | F46: =E46 -> 6591 | G46: =$B46 -> 0.0225 | H46: =ROUND(I45*$G46,2) -> 12.5 | I46: =H46+I45 -> 567.97 | J46: =$B46 -> 0.0225 | K46: =ROUND(L45*$J46,2) -> 1.42 | L46: =K46+L45 -> 64.33 | M46: =$B46 -> 0.0225 | N46: =ROUND(O45*$M46,2) -> 1.54 | O46: =N46+O45 -> 70.07 | P46: =$B46 -> 0.0225 | Q46: =ROUND(R45*$P46,2) -> 7.04 | R46: =Q46+R45 -> 319.72 | S46: =ROUND(T45*$B46,2) -> 6.37 | T46: =S46+T45 -> 289.39 | U46: =ROUND(V45*$B46,2) -> 1.19 | V46: =U46+V45 -> 53.95 | W46: =ROUND(X45*$B46,2) -> 1.31 | X46: =W46+X45 -> 59.54 | Y46: =ROUND(Z45*$B46,2) -> 0.65 | Z46: =Y46+Z45 -> 29.72 | AA46: =ROUND(AB45*$B46,2) -> 0.08 | AB46: =AA46+AB45 -> 3.47 | AC46: 0.875 | AD46: =ROUND(AC46*E46,0) -> 5767 | AE46: 0.875 | AF46: =ROUND(AE46*F46,0) -> 5767 | AG46: 0.79 | AH46: =ROUND(AG46*T46,0) -> 229 | AI46: =AI45 -> 1.01 | AJ46: 5.4 | AK46: 300 | AL46: 750 | AM46: =1-AC46 -> 0.125 | AN46: 3.24307 | AO46: =ROUND(T46*AG46,0) -> 229 | AP46: =E46-AD46-AL46 -> 74 | AQ46: 317587 | AR46: =ROUND(AR45*(1+B46),0) -> 61 | AS46: =INDEX($A$2:$AZ$100,MATCH($A46-1,$A$2:$A$100,0),30) -> 5640 | AT46: =INDEX($A$2:$AZ$100,MATCH($A46-1,$A$2:$A$100,0),5) -> 6446 | AV46: 0.25
A47: 2018 | B47: 0.0111 | C47: =ROUND(E46*B47,0) -> 73 | E47: =E46+C47+D47 -> 6664 | F47: =E47 -> 6664 | G47: =$B47 -> 0.0111 | H47: =ROUND(I46*$G47,2) -> 6.3 | I47: =H47+I46 -> 574.27 | J47: =$B47 -> 0.0111 | K47: =ROUND(L46*$J47,2) -> 0.71 | L47: =K47+L46 -> 65.04 | M47: =$B47 -> 0.0111 | N47: =ROUND(O46*$M47,2) -> 0.78 | O47: =N47+O46 -> 70.85 | P47: =$B47 -> 0.0111 | Q47: =ROUND(R46*$P47,2) -> 3.55 | R47: =Q47+R46 -> 323.27 | S47: =ROUND(T46*$B47,2) -> 3.21 | T47: =S47+T46 -> 292.6 | U47: =ROUND(V46*$B47,2) -> 0.6 | V47: =U47+V46 -> 54.55 | W47: =ROUND(X46*$B47,2) -> 0.66 | X47: =W47+X46 -> 60.2 | Y47: =ROUND(Z46*$B47,2) -> 0.33 | Z47: =Y47+Z46 -> 30.05 | AA47: =ROUND(AB46*$B47,2) -> 0.04 | AB47: =AA47+AB46 -> 3.51 | AC47: 0.875 | AD47: =ROUND(AC47*E47,0) -> 5831 | AE47: 0.875 | AF47: =ROUND(AE47*F47,0) -> 5831 | AG47: 0.79 | AH47: =ROUND(AG47*T47,0) -> 231 | AI47: =AI46 -> 1.01 | AJ47: 5.4 | AK47: 300 | AL47: 750 | AM47: =1-AC47 -> 0.125 | AN47: 3.16389 | AO47: =ROUND(T47*AG47,0) -> 231 | AP47: =E47-AD47-AL47 -> 83 | AQ47: =ROUND(159714313837/485147.3,0) -> 329208 | AR47: =ROUND(AR46*(1+B47),0) -> 62 | AS47: =INDEX($A$2:$AZ$100,MATCH($A47-1,$A$2:$A$100,0),30) -> 5767 | AT47: =INDEX($A$2:$AZ$100,MATCH($A47-1,$A$2:$A$100,0),5) -> 6591 | AU47: 0 | AV47: 0.25 | AW47: 0
A48: 2019 | B48: 0.01 | C48: =ROUND(E47*B48,0) -> 67 | D48: 5 | E48: =E47+C48+D48 -> 6736 | F48: =E48 -> 6736 | G48: 0.01 | H48: =ROUND(I47*$G48,2) -> 5.74 | I48: =H48+I47 -> 580.01 | J48: 0.01 | K48: =ROUND(L47*$J48,2) -> 0.65 | L48: =K48+L47 -> 65.69 | M48: 0.01 | N48: =ROUND(O47*$M48,2) -> 0.71 | O48: =N48+O47 -> 71.56 | P48: 0.01 | Q48: =ROUND(R47*$P48,2) -> 3.23 | R48: =Q48+R47 -> 326.5 | S48: =ROUND(T47*$B48,2) -> 2.93 | T48: =S48+T47 -> 295.53 | U48: =ROUND(V47*$B48,2) -> 0.55 | V48: =U48+V47 -> 55.1 | W48: =ROUND(X47*$B48,2) -> 0.6 | X48: =W48+X47 -> 60.8 | Y48: =ROUND(Z47*$B48,2) -> 0.3 | Z48: =Y48+Z47 -> 30.35 | AA48: =ROUND(AB47*$B48,2) -> 0.04 | AB48: =AA48+AB47 -> 3.55 | AC48: 0.875 | AD48: =ROUND(AC48*E48,0) -> 5894 | AE48: 0.875 | AF48: =ROUND(AE48*F48,0) -> 5894 | AG48: 0.79 | AH48: =ROUND(AG48*T48,0) -> 233 | AI48: =AI47 -> 1.01 | AJ48: 5.4 | AK48: 300 | AL48: 750 | AM48: =1-AC48 -> 0.125 | AN48: 3.03936 | AO48: =ROUND(T48*AG48,0) -> 233 | AP48: =E48-AD48-AL48 -> 92 | AQ48: 345229 | AR48: =ROUND(AR47*(1+B48),0) -> 63 | AS48: =INDEX($A$2:$AZ$100,MATCH($A48-1,$A$2:$A$100,0),30) -> 5831 | AT48: =INDEX($A$2:$AZ$100,MATCH($A48-1,$A$2:$A$100,0),5) -> 6664 | AU48: 0 | AV48: 0.25 | AW48: 0
A49: 2020 | B49: 0.0206 | C49: =ROUND(E48*B49,0) -> 139 | D49: 5 | E49: =E48+C49+D49 -> 6880 | F49: =E49 -> 6880 | G49: =B49 -> 0.0206 | H49: =ROUND(I48*$G49,2) -> 11.95 | I49: =H49+I48 -> 591.96 | J49: =B49 -> 0.0206 | K49: =ROUND(L48*$J49,2) -> 1.35 | L49: =K49+L48 -> 67.04 | M49: =B49 -> 0.0206 | N49: =ROUND(O48*$M49,2) -> 1.47 | O49: =N49+O48 -> 73.03 | P49: =B49 -> 0.0206 | Q49: =ROUND(R48*$P49,2) -> 6.73 | R49: =Q49+R48 -> 333.23 | S49: =ROUND(T48*$B49,2) -> 6.09 | T49: =S49+T48 -> 301.62 | U49: =ROUND(V48*$B49,2) -> 1.14 | V49: =U49+V48 -> 56.24 | W49: =ROUND(X48*$B49,2) -> 1.25 | X49: =W49+X48 -> 62.05 | Y49: =ROUND(Z48*$B49,2) -> 0.63 | Z49: =Y49+Z48 -> 30.98 | AA49: =ROUND(AB48*$B49,2) -> 0.07 | AB49: =AA49+AB48 -> 3.62 | AC49: 0.875 | AD49: =ROUND(AC49*E49,0) -> 6020 | AE49: 0.875 | AF49: =ROUND(AE49*F49,0) -> 6020 | AG49: 0.79 | AH49: =ROUND(AG49*T49,0) -> 238 | AI49: =AI48 -> 1.01 | AJ49: 5.4 | AK49: 300 | AL49: 750 | AM49: =1-AC49 -> 0.125 | AN49: 0 | AO49: =ROUND(T49*AG49,0) -> 238 | AP49: =E49-AD49-AL49 -> 110 | AQ49: 0 | AR49: =ROUND(AR48*(1+B49),0) -> 64 | AS49: =INDEX($A$2:$AZ$100,MATCH($A49-1,$A$2:$A$100,0),30) -> 5894 | AT49: =INDEX($A$2:$AZ$100,MATCH($A49-1,$A$2:$A$100,0),5) -> 6736 | AU49: 0 | AV49: 0.25 | AW49: 0
A50: 2021 | B50: 0.023 | C50: =ROUND(E49*B50,0) -> 158 | D50: 10 | E50: =E49+C50+D50 -> 7048 | F50: =E50 -> 7048 | G50: =B50 -> 0.023 | H50: =ROUND(I49*$G50,2) -> 13.62 | I50: =H50+I49 -> 605.58 | J50: =B50 -> 0.023 | K50: =ROUND(L49*$J50,2) -> 1.54 | L50: =K50+L49 -> 68.58 | M50: =B50 -> 0.023 | N50: =ROUND(O49*$M50,2) -> 1.68 | O50: =N50+O49 -> 74.71 | P50: =B50 -> 0.023 | Q50: =ROUND(R49*$P50,2) -> 7.66 | R50: =Q50+R49 -> 340.89 | S50: =ROUND(T49*$B50,2) -> 6.94 | T50: =S50+T49 -> 308.56 | U50: =ROUND(V49*$B50,2) -> 1.29 | V50: =U50+V49 -> 57.53 | W50: =ROUND(X49*$B50,2) -> 1.43 | X50: =W50+X49 -> 63.48 | Y50: =ROUND(Z49*$B50,2) -> 0.71 | Z50: =Y50+Z49 -> 31.69 | AA50: =ROUND(AB49*$B50,2) -> 0.08 | AB50: =AA50+AB49 -> 3.7 | AC50: 0.875 | AD50: =ROUND(AC50*E50,0) -> 6167 | AE50: 0.875 | AF50: =ROUND(AE50*F50,0) -> 6167 | AG50: 0.79 | AH50: =ROUND(AG50*T50,0) -> 244 | AI50: =AI49 -> 1.01 | AJ50: 5.4 | AK50: 300 | AL50: =E50-AD50-$AP49 -> 771 | AM50: =1-AC50 -> 0.125 | AO50: =ROUND(T50*AG50,0) -> 244 | AP50: =E50-AD50-AL50 -> 110 | AR50: =ROUND(AR49*(1+B50),0) -> 65 | AS50: =INDEX($A$2:$AZ$100,MATCH($A50-1,$A$2:$A$100,0),30) -> 6020 | AT50: =INDEX($A$2:$AZ$100,MATCH($A50-1,$A$2:$A$100,0),5) -> 6880
A51: 2022 | B51: 0 | C51: =ROUND(E50*B51,0) -> 0 | E51: =E50+C51+D51 -> 7048 | F51: =E51 -> 7048 | G51: =B51 -> 0 | H51: =ROUND(I50*$G51,2) -> 0 | I51: =H51+I50 -> 605.58 | J51: =B51 -> 0 | K51: =ROUND(L50*$J51,2) -> 0 | L51: =K51+L50 -> 68.58 | M51: =B51 -> 0 | N51: =ROUND(O50*$M51,2) -> 0 | O51: =N51+O50 -> 74.71 | P51: =B51 -> 0 | Q51: =ROUND(R50*$P51,2) -> 0 | R51: =Q51+R50 -> 340.89 | S51: =ROUND(T50*$B51,2) -> 0 | T51: =S51+T50 -> 308.56 | U51: =ROUND(V50*$B51,2) -> 0 | V51: =U51+V50 -> 57.53 | W51: =ROUND(X50*$B51,2) -> 0 | X51: =W51+X50 -> 63.48 | Y51: =ROUND(Z50*$B51,2) -> 0 | Z51: =Y51+Z50 -> 31.69 | AA51: =ROUND(AB50*$B51,2) -> 0 | AB51: =AA51+AB50 -> 3.7 | AC51: 0.875 | AD51: =ROUND(AC51*E51,0) -> 6167 | AE51: 0.875 | AF51: =ROUND(AE51*F51,0) -> 6167 | AG51: 0.79 | AH51: =ROUND(AG51*T51,0) -> 244 | AI51: =AI50 -> 1.01 | AJ51: 5.4 | AK51: 300 | AL51: =E51-AD51-$AP50 -> 771 | AM51: =1-AC51 -> 0.125 | AO51: =ROUND(T51*AG51,0) -> 244 | AP51: =E51-AD51-AL51 -> 110 | AR51: =ROUND(AR50*(1+B51),0) -> 65 | AS51: =INDEX($A$2:$AZ$100,MATCH($A51-1,$A$2:$A$100,0),30) -> 6167 | AT51: =INDEX($A$2:$AZ$100,MATCH($A51-1,$A$2:$A$100,0),5) -> 7048

Sheet lunch1920_g1to6
A1: 2019-20 - FRL Grades 1 to 6 - December 20, 2019
A2: AEA | B2: District # | C2: District Name | D2: School | E2: School Name | F2: Enrollment | G2: # Eligible for Free or Reduced Lunch | H2: FRL %
A3: 07 | B3: 0009 | C3: AGWSR | D3: 0172 | E3: AGWSR Middle School | F3: 45 | G3: 23 | H3: 0.51111111
A4: 07 | B4: 0009 | C4: AGWSR | D4: 0409 | E4: AGWSR Elementary School | F4: 193 | G4: 83 | H4: 0.43005181
A5: 07 | B5: 0009 | C5: AGWSR | D5: 0436 | E5: AGWSR Elementary at Wellsburg | F5: 33 | G5: 17 | H5: 0.51515152
A6: 11 | B6: 0018 | C6: Adair-Casey | D6: 0409 | E6: Adair-Casey Elementary School | F6: 110 | G6: 49 | H6: 0.44545455
A7: 11 | B7: 0027 | C7: Adel DeSoto Minburn | D7: 0409 | E7: Adel Elementary School | F7: 297 | G7: 55 | H7: 0.18518519
A8: 11 | B8: 0027 | C8: Adel DeSoto Minburn | D8: 0412 | E8: ADM Middle School | F8: 165 | G8: 36 | H8: 0.21818182
A9: 11 | B9: 0027 | C9: Adel DeSoto Minburn | D9: 0418 | E9: DeSoto Intermediate School | F9: 499 | G9: 98 | H9: 0.19639279
A10: 12 | B10: 0063 | C10: Akron Westfield | D10: 0409 | E10: Akron Westfield Elementary School | F10: 216 | G10: 80 | H10: 0.37037037
A11: 12 | B11: 0063 | C11: Akron Westfield | D11: 0418 | E11: Akron Westfield Middle School | F11: 44 | G11: 13 | H11: 0.29545455
A12: 05 | B12: 0072 | C12: Albert City-Truesdale | D12: 0409 | E12: Albert City-Truesdale Elementary School | F12: 87 | G12: 39 | H12: 0.44827586
A13: 15 | B13: 0081 | C13: Albia | D13: 0409 | E13: Grant Center | F13: 148 | G13: 59 | H13: 0.39864865
A14: 15 | B14: 0081 | C14: Albia | D14: 0427 | E14: Lincoln Center | F14: 343 | G14: 137 | H14: 0.39941691
... A935: 11 | B935: 7110 | C935: Woodward-Granger | D935: 0427 | E935: Woodward-Granger Early Learning Center | F935: 100 | G935: 18 | H935: 0.18
F936: =SUM(F3:F935) -> 218501 | G936: =SUM(G3:G935) -> 97129 | H936: =G936/F936 -> 0.44452428
