Workbook
Name C_I_Prorate: #REF!
Name DistrictName: #REF!
Name fr2021g1to6dst_cep: #REF!
Name fr2122kto6dst_cep2: fr2223g1to6dst_cep!$E$1:$I$328
Name frl1819_g1to6cep: #REF!
Name lunch1920_g1to6: #REF!

Sheet Summary
A1: =CONCATENATE("FY ",Calculation!$P$1," At-Risk Supplementary Weighting Formula") -> FY 2024 At-Risk Supplementary Weighting Formula | C1: At-Risk Weighting
A2: Final | C2: Free/Red. Lunch | D2: Enrollment | E2: Subtotal Line 3.10 | G2: =CONCATENATE("FY ",Calculation!$P$1, " District Cost Per Pupil") -> FY 2024 District Cost Per Pupil | H2: Dollars Generated
A3: =StartupfileInput!C2 -> 0009 | B3: =INDEX(Calculation!$A$4:$M$328,MATCH(Summary!$A3,Calculation!$A$4:$A$328,0),3) -> AGWSR | C3: =INDEX(Calculation!$A$4:$M$328,MATCH(Summary!$A3,Calculation!$A$4:$A$328,0),6) -> 1.759 | D3: =INDEX(Calculation!$A$4:$M$328,MATCH(Summary!$A3,Calculation!$A$4:$A$328,0),7) -> 1.4 | E3: =SUM(C3:D3) -> 3.159 | G3: =INDEX(Calculation!$A$4:$M$328,MATCH(Summary!$A3,Calculation!$A$4:$A$328,0),10) -> 7710 | H3: =ROUND(E3*G3,0) -> 24356
A4: =StartupfileInput!C3 -> 0441 | B4: =INDEX(Calculation!$A$4:$M$328,MATCH(Summary!$A4,Calculation!$A$4:$A$328,0),3) -> AHSTW | C4: =INDEX(Calculation!$A$4:$M$328,MATCH(Summary!$A4,Calculation!$A$4:$A$328,0),6) -> 2.156 | D4: =INDEX(Calculation!$A$4:$M$328,MATCH(Summary!$A4,Calculation!$A$4:$A$328,0),7) -> 1.617 | E4: =SUM(C4:D4) -> 3.773 | G4: =INDEX(Calculation!$A$4:$M$328,MATCH(Summary!$A4,Calculation!$A$4:$A$328,0),10) -> 7645 | H4: =ROUND(E4*G4,0) -> 28845
A5: =StartupfileInput!C4 -> 0018 | B5: =INDEX(Calculation!$A$4:$M$328,MATCH(Summary!$A5,Calculation!$A$4:$A$328,0),3) -> Adair-Casey | C5: =INDEX(Calculation!$A$4:$M$328,MATCH(Summary!$A5,Calculation!$A$4:$A$328,0),6) -> 1.013 | D5: =INDEX(Calculation!$A$4:$M$328,MATCH(Summary!$A5,Calculation!$A$4:$A$328,0),7) -> 0.625 | E5: =SUM(C5:D5) -> 1.638 | G5: =INDEX(Calculation!$A$4:$M$328,MATCH(Summary!$A5,Calculation!$A$4:$A$328,0),10) -> 7635 | H5: =ROUND(E5*G5,0) -> 12506
A6: =StartupfileInput!C5 -> 0027 | B6: =INDEX(Calculation!$A$4:$M$328,MATCH(Summary!$A6,Calculation!$A$4:$A$328,0),3) -> Adel-Desoto-Minburn | C6: =INDEX(Calculation!$A$4:$M$328,MATCH(Summary!$A6,Calculation!$A$4:$A$328,0),6) -> 2.517 | D6: =INDEX(Calculation!$A$4:$M$328,MATCH(Summary!$A6,Calculation!$A$4:$A$328,0),7) -> 4.347 | E6: =SUM(C6:D6) -> 6.864 | G6: =INDEX(Calculation!$A$4:$M$328,MATCH(Summary!$A6,Calculation!$A$4:$A$328,0),10) -> 7635 | H6: =ROUND(E6*G6,0) -> 52407
A7: =StartupfileInput!C6 -> 0063 | B7: =INDEX(Calculation!$A$4:$M$328,MATCH(Summary!$A7,Calculation!$A$4:$A$328,0),3) -> Akron-Westfield | C7: =INDEX(Calculation!$A$4:$M$328,MATCH(Summary!$A7,Calculation!$A$4:$A$328,0),6) -> 1.414 | D7: =INDEX(Calculation!$A$4:$M$328,MATCH(Summary!$A7,Calculation!$A$4:$A$328,0),7) -> 1.133 | E7: =SUM(C7:D7) -> 2.547 | G7: =INDEX(Calculation!$A$4:$M$328,MATCH(Summary!$A7,Calculation!$A$4:$A$328,0),10) -> 7651 | H7: =ROUND(E7*G7,0) -> 19487
A8: =StartupfileInput!C7 -> 0072 | B8: =INDEX(Calculation!$A$4:$M$328,MATCH(Summary!$A8,Calculation!$A$4:$A$328,0),3) -> Albert City-Truesdale | C8: =INDEX(Calculation!$A$4:$M$328,MATCH(Summary!$A8,Calculation!$A$4:$A$328,0),6) -> 0.714 | D8: =INDEX(Calculation!$A$4:$M$328,MATCH(Summary!$A8,Calculation!$A$4:$A$328,0),7) -> 0.428 | E8: =SUM(C8:D8) -> 1.142 | G8: =INDEX(Calculation!$A$4:$M$328,MATCH(Summary!$A8,Calculation!$A$4:$A$328,0),10) -> 7681 | H8: =ROUND(E8*G8,0) -> 8772
A9: =StartupfileInput!C8 -> 0081 | B9: =INDEX(Calculation!$A$4:$M$328,MATCH(Summary!$A9,Calculation!$A$4:$A$328,0),3) -> Albia | C9: =INDEX(Calculation!$A$4:$M$328,MATCH(Summary!$A9,Calculation!$A$4:$A$328,0),6) -> 3.029 | D9: =INDEX(Calculation!$A$4:$M$328,MATCH(Summary!$A9,Calculation!$A$4:$A$328,0),7) -> 2.243 | E9: =SUM(C9:D9) -> 5.272 | G9: =INDEX(Calculation!$A$4:$M$328,MATCH(Summary!$A9,Calculation!$A$4:$A$328,0),10) -> 7635 | H9: =ROUND(E9*G9,0) -> 40252
A10: =StartupfileInput!C9 -> 0099 | B10: =INDEX(Calculation!$A$4:$M$328,MATCH(Summary!$A10,Calculation!$A$4:$A$328,0),3) -> Alburnett | C10: =INDEX(Calculation!$A$4:$M$328,MATCH(Summary!$A10,Calculation!$A$4:$A$328,0),6) -> 0.782 | D10: =INDEX(Calculation!$A$4:$M$328,MATCH(Summary!$A10,Calculation!$A$4:$A$328,0),7) -> 1.074 | E10: =SUM(C10:D10) -> 1.856 | G10: =INDEX(Calculation!$A$4:$M$328,MATCH(Summary!$A10,Calculation!$A$4:$A$328,0),10) -> 7635 | H10: =ROUND(E10*G10,0) -> 14171
A11: =StartupfileInput!C10 -> 0108 | B11: =INDEX(Calculation!$A$4:$M$328,MATCH(Summary!$A11,Calculation!$A$4:$A$328,0),3) -> Alden | C11: =INDEX(Calculation!$A$4:$M$328,MATCH(Summary!$A11,Calculation!$A$4:$A$328,0),6) -> 0.728 | D11: =INDEX(Calculation!$A$4:$M$328,MATCH(Summary!$A11,Calculation!$A$4:$A$328,0),7) -> 0.558 | E11: =SUM(C11:D11) -> 1.286 | G11: =INDEX(Calculation!$A$4:$M$328,MATCH(Summary!$A11,Calculation!$A$4:$A$328,0),10) -> 7635 | H11: =ROUND(E11*G11,0) -> 9819
A12: =StartupfileInput!C11 -> 0126 | B12: =INDEX(Calculation!$A$4:$M$328,MATCH(Summary!$A12,Calculation!$A$4:$A$328,0),3) -> Algona | C12: =INDEX(Calculation!$A$4:$M$328,MATCH(Summary!$A12,Calculation!$A$4:$A$328,0),6) -> 3.503 | D12: =INDEX(Calculation!$A$4:$M$328,MATCH(Summary!$A12,Calculation!$A$4:$A$328,0),7) -> 2.951 | E12: =SUM(C12:D12) -> 6.454 | G12: =INDEX(Calculation!$A$4:$M$328,MATCH(Summary!$A12,Calculation!$A$4:$A$328,0),10) -> 7649 | H12: =ROUND(E12*G12,0) -> 49367
A13: =StartupfileInput!C12 -> 0135 | B13: =INDEX(Calculation!$A$4:$M$328,MATCH(Summary!$A13,Calculation!$A$4:$A$328,0),3) -> Allamakee | C13: =INDEX(Calculation!$A$4:$M$328,MATCH(Summary!$A13,Calculation!$A$4:$A$328,0),6) -> 2.963 | D13: =INDEX(Calculation!$A$4:$M$328,MATCH(Summary!$A13,Calculation!$A$4:$A$328,0),7) -> 2.218 | E13: =SUM(C13:D13) -> 5.181 | G13: =INDEX(Calculation!$A$4:$M$328,MATCH(Summary!$A13,Calculation!$A$4:$A$328,0),10) -> 7682 | H13: =ROUND(E13*G13,0) -> 39800
A14: =StartupfileInput!C13 -> 0171 | B14: =INDEX(Calculation!$A$4:$M$328,MATCH(Summary!$A14,Calculation!$A$4:$A$328,0),3) -> Alta-Aurelia | C14: =INDEX(Calculation!$A$4:$M$328,MATCH(Summary!$A14,Calculation!$A$4:$A$328,0),6) -> 2.484 | D14: =INDEX(Calculation!$A$4:$M$328,MATCH(Summary!$A14,Calculation!$A$4:$A$328,0),7) -> 1.781 | E14: =SUM(C14:D14) -> 4.265 | G14: =INDEX(Calculation!$A$4:$M$328,MATCH(Summary!$A14,Calculation!$A$4:$A$328,0),10) -> 7635 | H14: =ROUND(E14*G14,0) -> 32563
... A327: =StartupfileInput!C326 -> 7110 | B327: =INDEX(Calculation!$A$4:$M$328,MATCH(Summary!$A327,Calculation!$A$4:$A$328,0),3) -> Woodward-Granger | C327: =INDEX(Calculation!$A$4:$M$328,MATCH(Summary!$A327,Calculation!$A$4:$A$328,0),6) -> 1.525 | D327: =INDEX(Calculation!$A$4:$M$328,MATCH(Summary!$A327,Calculation!$A$4:$A$328,0),7) -> 2.168 | E327: =SUM(C327:D327) -> 3.693 | G327: =INDEX(Calculation!$A$4:$M$328,MATCH(Summary!$A327,Calculation!$A$4:$A$328,0),10) -> 7692 | H327: =ROUND(E327*G327,0) -> 28407
C328: =SUM(C3:C327) -> 1422.691 | D328: =SUM(D3:D327) -> 992.412 | E328: =SUM(E3:E327) -> 2415.103 | H328: =SUM(H3:H327) -> 18465688
A330: NOTES:
A331: 1) Supplementary Weighting Free/Reduced Meals - Percent free & reduced meals in grades 1-6 multiplied by budget enrollment multiplied by 0.00642 weighting.
A333: 2) Supplementary Weighting Enrollment - Budget enrollment multiplied by 0.00204 weighting.
A334: 3) Supplementary Weighting Subtotal - Free & reduced meals weighting plus enrollment weighting.
A335: 4) District Cost Per Pupil
A336: 5) Dollars Generated total - total supplementary weighting multiplied by district cost per pupil.

Sheet Calculation
D1: Oct. 15 | E1: Percent 1-6 | F1: Suppl Wght | G1: Suppl Wght | H1: Suppl Wght | I1: =CONCATENATE("FY ",P1-1) -> FY 2023 | J1: =CONCATENATE("FY ",P1) -> FY 2024 | K1: Dollars | L1: Dollars | M1: Dollars | O1: Fiscal Year | P1: 2024 | Q1: =Constants!B1 -> SPG | R1: =Constants!C1 -> CPP | S1: =Constants!D1 -> Additional_Dollar | T1: =Constants!E1 -> SCPP
D2: Enrollment | E2: Free & Red. | F2: Free & Red. | G2: Enrollment | H2: Total | I2: DCPP | J2: DCPP | K2: Generated | L2: Generated | M2: Generated | O2: SCPP | P2: =INDEX(Constants!$A$2:$AW$100,MATCH(Calculation!$P$1,Constants!$A$2:$A$100,0),MATCH(Calculation!O$2,Constants!$A$1:$AW$1,0)) -> 7635 | Q2: =INDEX(Constants!$A$2:$AW$100,MATCH(Calculation!$P$1,Constants!$A$2:$A$100,0),MATCH(Calculation!Q$1,Constants!$A$1:$AW$1,0)) -> 0.03 | R2: =INDEX(Constants!$A$2:$AW$100,MATCH(Calculation!$P$1,Constants!$A$2:$A$100,0),MATCH(Calculation!R$1,Constants!$A$1:$AW$1,0)) -> 222 | S2: =INDEX(Constants!$A$2:$AW$100,MATCH(Calculation!$P$1,Constants!$A$2:$A$100,0),MATCH(Calculation!S$1,Constants!$A$1:$AW$1,0)) -> 0 | T2: =INDEX(Constants!$A$2:$AW$100,MATCH(Calculation!$P$1,Constants!$A$2:$A$100,0),MATCH(Calculation!T$1,Constants!$A$1:$AW$1,0)) -> 7635
A3: Dist | B3: DistrictNumber | C3: =ActiveDistricts!G1 -> Label | E3: Meals | F3: 0.00642 | G3: 0.00204 | H3: Line 3.10 | K3: Free & Red. | L3: Enrollment | M3: Total
A4: =StartupfileInput!C2 -> 0009 | B4: =INDEX(ActiveDistricts!$A$2:$J$326,MATCH(Calculation!$A4,ActiveDistricts!$C$2:$C$326,0),6) -> 0009 | C4: =INDEX(ActiveDistricts!$A$2:$J$326,MATCH(Calculation!$A4,ActiveDistricts!$C$2:$C$326,0),7) -> AGWSR | D4: =INDEX(StartupfileInput!$A$2:$I$326,MATCH(Calculation!$A4,StartupfileInput!$C$2:$C$326,0),8) -> 686.4 | E4: =INDEX(ActiveDistricts!$A$2:$J$326,MATCH(Calculation!$A4,ActiveDistricts!$C$2:$C$326,0),10) -> 0.39920949 | F4: =ROUND(D4*E4*$F$3,3) -> 1.759 | G4: =ROUND(D4*$G$3,3) -> 1.4 | H4: =SUM(F4:G4) -> 3.159 | I4: =INDEX(StartupfileInput!$A$2:$I$326,MATCH(Calculation!$A4,StartupfileInput!$C$2:$C$326,0),9) -> 7488 | J4: =MAX(I4+$R$2,$T$2) -> 7710 | K4: =ROUND(F4*J4,0) -> 13562 | L4: =M4-K4 -> 10794 | M4: =ROUND(H4*J4,0) -> 24356
A5: =StartupfileInput!C3 -> 0441 | B5: =INDEX(ActiveDistricts!$A$2:$J$326,MATCH(Calculation!$A5,ActiveDistricts!$C$2:$C$326,0),6) -> 0441 | C5: =INDEX(ActiveDistricts!$A$2:$J$326,MATCH(Calculation!$A5,ActiveDistricts!$C$2:$C$326,0),7) -> AHSTW | D5: =INDEX(StartupfileInput!$A$2:$I$326,MATCH(Calculation!$A5,StartupfileInput!$C$2:$C$326,0),8) -> 792.6 | E5: =INDEX(ActiveDistricts!$A$2:$J$326,MATCH(Calculation!$A5,ActiveDistricts!$C$2:$C$326,0),10) -> 0.42378049 | F5: =ROUND(D5*E5*$F$3,3) -> 2.156 | G5: =ROUND(D5*$G$3,3) -> 1.617 | H5: =SUM(F5:G5) -> 3.773 | I5: =INDEX(StartupfileInput!$A$2:$I$326,MATCH(Calculation!$A5,StartupfileInput!$C$2:$C$326,0),9) -> 7423 | J5: =MAX(I5+$R$2,$T$2) -> 7645 | K5: =ROUND(F5*J5,0) -> 16483 | L5: =M5-K5 -> 12362 | M5: =ROUND(H5*J5,0) -> 28845
A6: =StartupfileInput!C4 -> 0018 | B6: =INDEX(ActiveDistricts!$A$2:$J$326,MATCH(Calculation!$A6,ActiveDistricts!$C$2:$C$326,0),6) -> 0018 | C6: =INDEX(ActiveDistricts!$A$2:$J$326,MATCH(Calculation!$A6,ActiveDistricts!$C$2:$C$326,0),7) -> Adair-Casey | D6: =INDEX(StartupfileInput!$A$2:$I$326,MATCH(Calculation!$A6,StartupfileInput!$C$2:$C$326,0),8) -> 306.3 | E6: =INDEX(ActiveDistricts!$A$2:$J$326,MATCH(Calculation!$A6,ActiveDistricts!$C$2:$C$326,0),10) -> 0.51515152 | F6: =ROUND(D6*E6*$F$3,3) -> 1.013 | G6: =ROUND(D6*$G$3,3) -> 0.625 | H6: =SUM(F6:G6) -> 1.638 | I6: =INDEX(StartupfileInput!$A$2:$I$326,MATCH(Calculation!$A6,StartupfileInput!$C$2:$C$326,0),9) -> 7413 | J6: =MAX(I6+$R$2,$T$2) -> 7635 | K6: =ROUND(F6*J6,0) -> 7734 | L6: =M6-K6 -> 4772 | M6: =ROUND(H6*J6,0) -> 12506
A7: =StartupfileInput!C5 -> 0027 | B7: =INDEX(ActiveDistricts!$A$2:$J$326,MATCH(Calculation!$A7,ActiveDistricts!$C$2:$C$326,0),6) -> 0027 | C7: =INDEX(ActiveDistricts!$A$2:$J$326,MATCH(Calculation!$A7,ActiveDistricts!$C$2:$C$326,0),7) -> Adel-Desoto-Minburn | D7: =INDEX(StartupfileInput!$A$2:$I$326,MATCH(Calculation!$A7,StartupfileInput!$C$2:$C$326,0),8) -> 2130.9 | E7: =INDEX(ActiveDistricts!$A$2:$J$326,MATCH(Calculation!$A7,ActiveDistricts!$C$2:$C$326,0),10) -> 0.18395303 | F7: =ROUND(D7*E7*$F$3,3) -> 2.517 | G7: =ROUND(D7*$G$3,3) -> 4.347 | H7: =SUM(F7:G7) -> 6.864 | I7: =INDEX(StartupfileInput!$A$2:$I$326,MATCH(Calculation!$A7,StartupfileInput!$C$2:$C$326,0),9) -> 7413 | J7: =MAX(I7+$R$2,$T$2) -> 7635 | K7: =ROUND(F7*J7,0) -> 19217 | L7: =M7-K7 -> 33190 | M7: =ROUND(H7*J7,0) -> 52407
A8: =StartupfileInput!C6 -> 0063 | B8: =INDEX(ActiveDistricts!$A$2:$J$326,MATCH(Calculation!$A8,ActiveDistricts!$C$2:$C$326,0),6) -> 0063 | C8: =INDEX(ActiveDistricts!$A$2:$J$326,MATCH(Calculation!$A8,ActiveDistricts!$C$2:$C$326,0),7) -> Akron-Westfield | D8: =INDEX(StartupfileInput!$A$2:$I$326,MATCH(Calculation!$A8,StartupfileInput!$C$2:$C$326,0),8) -> 555.2 | E8: =INDEX(ActiveDistricts!$A$2:$J$326,MATCH(Calculation!$A8,ActiveDistricts!$C$2:$C$326,0),10) -> 0.39676113 | F8: =ROUND(D8*E8*$F$3,3) -> 1.414 | G8: =ROUND(D8*$G$3,3) -> 1.133 | H8: =SUM(F8:G8) -> 2.547 | I8: =INDEX(StartupfileInput!$A$2:$I$326,MATCH(Calculation!$A8,StartupfileInput!$C$2:$C$326,0),9) -> 7429 | J8: =MAX(I8+$R$2,$T$2) -> 7651 | K8: =ROUND(F8*J8,0) -> 10819 | L8: =M8-K8 -> 8668 | M8: =ROUND(H8*J8,0) -> 19487
A9: =StartupfileInput!C7 -> 0072 | B9: =INDEX(ActiveDistricts!$A$2:$J$326,MATCH(Calculation!$A9,ActiveDistricts!$C$2:$C$326,0),6) -> 0072 | C9: =INDEX(ActiveDistricts!$A$2:$J$326,MATCH(Calculation!$A9,ActiveDistricts!$C$2:$C$326,0),7) -> Albert City-Truesdale | D9: =INDEX(StartupfileInput!$A$2:$I$326,MATCH(Calculation!$A9,StartupfileInput!$C$2:$C$326,0),8) -> 209.6 | E9: =INDEX(ActiveDistricts!$A$2:$J$326,MATCH(Calculation!$A9,ActiveDistricts!$C$2:$C$326,0),10) -> 0.5308642 | F9: =ROUND(D9*E9*$F$3,3) -> 0.714 | G9: =ROUND(D9*$G$3,3) -> 0.428 | H9: =SUM(F9:G9) -> 1.142 | I9: =INDEX(StartupfileInput!$A$2:$I$326,MATCH(Calculation!$A9,StartupfileInput!$C$2:$C$326,0),9) -> 7459 | J9: =MAX(I9+$R$2,$T$2) -> 7681 | K9: =ROUND(F9*J9,0) -> 5484 | L9: =M9-K9 -> 3288 | M9: =ROUND(H9*J9,0) -> 8772
A10: =StartupfileInput!C8 -> 0081 | B10: =INDEX(ActiveDistricts!$A$2:$J$326,MATCH(Calculation!$A10,ActiveDistricts!$C$2:$C$326,0),6) -> 0081 | C10: =INDEX(ActiveDistricts!$A$2:$J$326,MATCH(Calculation!$A10,ActiveDistricts!$C$2:$C$326,0),7) -> Albia | D10: =INDEX(StartupfileInput!$A$2:$I$326,MATCH(Calculation!$A10,StartupfileInput!$C$2:$C$326,0),8) -> 1099.4 | E10: =INDEX(ActiveDistricts!$A$2:$J$326,MATCH(Calculation!$A10,ActiveDistricts!$C$2:$C$326,0),10) -> 0.42921348 | F10: =ROUND(D10*E10*$F$3,3) -> 3.029 | G10: =ROUND(D10*$G$3,3) -> 2.243 | H10: =SUM(F10:G10) -> 5.272 | I10: =INDEX(StartupfileInput!$A$2:$I$326,MATCH(Calculation!$A10,StartupfileInput!$C$2:$C$326,0),9) -> 7413 | J10: =MAX(I10+$R$2,$T$2) -> 7635 | K10: =ROUND(F10*J10,0) -> 23126 | L10: =M10-K10 -> 17126 | M10: =ROUND(H10*J10,0) -> 40252
A11: =StartupfileInput!C9 -> 0099 | B11: =INDEX(ActiveDistricts!$A$2:$J$326,MATCH(Calculation!$A11,ActiveDistricts!$C$2:$C$326,0),6) -> 0099 | C11: =INDEX(ActiveDistricts!$A$2:$J$326,MATCH(Calculation!$A11,ActiveDistricts!$C$2:$C$326,0),7) -> Alburnett | D11: =INDEX(StartupfileInput!$A$2:$I$326,MATCH(Calculation!$A11,StartupfileInput!$C$2:$C$326,0),8) -> 526.5 | E11: =INDEX(ActiveDistricts!$A$2:$J$326,MATCH(Calculation!$A11,ActiveDistricts!$C$2:$C$326,0),10) -> 0.23148148 | F11: =ROUND(D11*E11*$F$3,3) -> 0.782 | G11: =ROUND(D11*$G$3,3) -> 1.074 | H11: =SUM(F11:G11) -> 1.856 | I11: =INDEX(StartupfileInput!$A$2:$I$326,MATCH(Calculation!$A11,StartupfileInput!$C$2:$C$326,0),9) -> 7413 | J11: =MAX(I11+$R$2,$T$2) -> 7635 | K11: =ROUND(F11*J11,0) -> 5971 | L11: =M11-K11 -> 8200 | M11: =ROUND(H11*J11,0) -> 14171
A12: =StartupfileInput!C10 -> 0108 | B12: =INDEX(ActiveDistricts!$A$2:$J$326,MATCH(Calculation!$A12,ActiveDistricts!$C$2:$C$326,0),6) -> 0108 | C12: =INDEX(ActiveDistricts!$A$2:$J$326,MATCH(Calculation!$A12,ActiveDistricts!$C$2:$C$326,0),7) -> Alden | D12: =INDEX(StartupfileInput!$A$2:$I$326,MATCH(Calculation!$A12,StartupfileInput!$C$2:$C$326,0),8) -> 273.7 | E12: =INDEX(ActiveDistricts!$A$2:$J$326,MATCH(Calculation!$A12,ActiveDistricts!$C$2:$C$326,0),10) -> 0.41441441 | F12: =ROUND(D12*E12*$F$3,3) -> 0.728 | G12: =ROUND(D12*$G$3,3) -> 0.558 | H12: =SUM(F12:G12) -> 1.286 | I12: =INDEX(StartupfileInput!$A$2:$I$326,MATCH(Calculation!$A12,StartupfileInput!$C$2:$C$326,0),9) -> 7413 | J12: =MAX(I12+$R$2,$T$2) -> 7635 | K12: =ROUND(F12*J12,0) -> 5558 | L12: =M12-K12 -> 4261 | M12: =ROUND(H12*J12,0) -> 9819
A13: =StartupfileInput!C11 -> 0126 | B13: =INDEX(ActiveDistricts!$A$2:$J$326,MATCH(Calculation!$A13,ActiveDistricts!$C$2:$C$326,0),6) -> 0126 | C13: =INDEX(ActiveDistricts!$A$2:$J$326,MATCH(Calculation!$A13,ActiveDistricts!$C$2:$C$326,0),7) -> Algona | D13: =INDEX(StartupfileInput!$A$2:$I$326,MATCH(Calculation!$A13,StartupfileInput!$C$2:$C$326,0),8) -> 1446.4 | E13: =INDEX(ActiveDistricts!$A$2:$J$326,MATCH(Calculation!$A13,ActiveDistricts!$C$2:$C$326,0),10) -> 0.37720706 | F13: =ROUND(D13*E13*$F$3,3) -> 3.503 | G13: =ROUND(D13*$G$3,3) -> 2.951 | H13: =SUM(F13:G13) -> 6.454 | I13: =INDEX(StartupfileInput!$A$2:$I$326,MATCH(Calculation!$A13,StartupfileInput!$C$2:$C$326,0),9) -> 7427 | J13: =MAX(I13+$R$2,$T$2) -> 7649 | K13: =ROUND(F13*J13,0) -> 26794 | L13: =M13-K13 -> 22573 | M13: =ROUND(H13*J13,0) -> 49367
A14: =StartupfileInput!C12 -> 0135 | B14: =INDEX(ActiveDistricts!$A$2:$J$326,MATCH(Calculation!$A14,ActiveDistricts!$C$2:$C$326,0),6) -> 0135 | C14: =INDEX(ActiveDistricts!$A$2:$J$326,MATCH(Calculation!$A14,ActiveDistricts!$C$2:$C$326,0),7) -> Allamakee | D14: =INDEX(StartupfileInput!$A$2:$I$326,MATCH(Calculation!$A14,StartupfileInput!$C$2:$C$326,0),8) -> 1087.4 | E14: =INDEX(ActiveDistricts!$A$2:$J$326,MATCH(Calculation!$A14,ActiveDistricts!$C$2:$C$326,0),10) -> 0.42439024 | F14: =ROUND(D14*E14*$F$3,3) -> 2.963 | G14: =ROUND(D14*$G$3,3) -> 2.218 | H14: =SUM(F14:G14) -> 5.181 | I14: =INDEX(StartupfileInput!$A$2:$I$326,MATCH(Calculation!$A14,StartupfileInput!$C$2:$C$326,0),9) -> 7460 | J14: =MAX(I14+$R$2,$T$2) -> 7682 | K14: =ROUND(F14*J14,0) -> 22762 | L14: =M14-K14 -> 17038 | M14: =ROUND(H14*J14,0) -> 39800
A15: =StartupfileInput!C13 -> 0171 | B15: =INDEX(ActiveDistricts!$A$2:$J$326,MATCH(Calculation!$A15,ActiveDistricts!$C$2:$C$326,0),6) -> 0171 | C15: =INDEX(ActiveDistricts!$A$2:$J$326,MATCH(Calculation!$A15,ActiveDistricts!$C$2:$C$326,0),7) -> Alta-Aurelia | D15: =INDEX(StartupfileInput!$A$2:$I$326,MATCH(Calculation!$A15,StartupfileInput!$C$2:$C$326,0),8) -> 872.8 | E15: =INDEX(ActiveDistricts!$A$2:$J$326,MATCH(Calculation!$A15,ActiveDistricts!$C$2:$C$326,0),10) -> 0.44324324 | F15: =ROUND(D15*E15*$F$3,3) -> 2.484 | G15: =ROUND(D15*$G$3,3) -> 1.781 | H15: =SUM(F15:G15) -> 4.265 | I15: =INDEX(StartupfileInput!$A$2:$I$326,MATCH(Calculation!$A15,StartupfileInput!$C$2:$C$326,0),9) -> 7413 | J15: =MAX(I15+$R$2,$T$2) -> 7635 | K15: =ROUND(F15*J15,0) -> 18965 | L15: =M15-K15 -> 13598 | M15: =ROUND(H15*J15,0) -> 32563
... A328: =StartupfileInput!C326 -> 7110 | B328: =INDEX(ActiveDistricts!$A$2:$J$326,MATCH(Calculation!$A328,ActiveDistricts!$C$2:$C$326,0),6) -> 7110 | C328: =INDEX(ActiveDistricts!$A$2:$J$326,MATCH(Calculation!$A328,ActiveDistricts!$C$2:$C$326,0),7) -> Woodward-Granger | D328: =INDEX(StartupfileInput!$A$2:$I$326,MATCH(Calculation!$A328,StartupfileInput!$C$2:$C$326,0),8) -> 1062.9 | E328: =INDEX(ActiveDistricts!$A$2:$J$326,MATCH(Calculation!$A328,ActiveDistricts!$C$2:$C$326,0),10) -> 0.22352941 | F328: =ROUND(D328*E328*$F$3,3) -> 1.525 | G328: =ROUND(D328*$G$3,3) -> 2.168 | H328: =SUM(F328:G328) -> 3.693 | I328: =INDEX(StartupfileInput!$A$2:$I$326,MATCH(Calculation!$A328,StartupfileInput!$C$2:$C$326,0),9) -> 7470 | J328: =MAX(I328+$R$2,$T$2) -> 7692 | K328: =ROUND(F328*J328,0) -> 11730 | L328: =M328-K328 -> 16677 | M328: =ROUND(H328*J328,0) -> 28407
D329: =SUM(D4:D328) -> 486475.5 | F329: =SUM(F4:F328) -> 1422.691 | G329: =SUM(G4:G328) -> 992.412 | H329: =SUM(H4:H328) -> 2415.103
C330: FY 2024 - calculated | D330: =SUM(D4:D328) -> 486475.5 | E330: =SUM(ActiveDistricts!$I:$I)/SUM(ActiveDistricts!$H:$H) -> 0.4469317 | F330: =ROUND(D330*E330*$F$3,3) -> 1395.845 | G330: =ROUND(D330*$G$3,3) -> 992.41 | H330: =SUM(F330:G330) -> 2388.255 | K330: =SUM(K4:K328) -> 10878196 | L330: =SUM(L4:L328) -> 7587492 | M330: =SUM(M4:M328) -> 18465688
C332: state aid portion 88.4% | M332: =ROUND(M330*0.884,0) -> 16323668
C333: property tax portion 11.6% | M333: =ROUND(M330*0.116,0) -> 2142020
F337: The calculated for the Fee and Reduced lunch is always off by 20-30 students due to using the statewide number and comparing it to district by district.

Sheet StartupfileInput
A1: FiscalYear | B1: AEA | C1: Dist | D1: DistSub1 | E1: DistSub2 | F1: DistrictNumber | G1: NAME | H1: x249 | I1: x272 | K1: Double Check Reorgs Did prelim but check against SAS Calculation for them | P1: 12/19 - Only pasted in Enrollment - Did not account for mergers
A2: 2024 | B2: 11 | C2: 0009 | F2: 0018 | G2: AGWSR | H2: 686.4 | I2: 7488
A3: 2024 | B3: 11 | C3: 0441 | F3: 0027 | G3: AHSTW | H3: 792.6 | I3: 7423
A4: 2024 | B4: 07 | C4: 0018 | F4: 0009 | G4: Adair-Casey | H4: 306.3 | I4: 7413
A5: 2024 | B5: 13 | C5: 0027 | F5: 0441 | G5: Adel-Desoto-Minburn | H5: 2130.9 | I5: 7413
A6: 2024 | B6: 12 | C6: 0063 | F6: 0063 | G6: Akron-Westfield | H6: 555.2 | I6: 7429
A7: 2024 | B7: 05 | C7: 0072 | F7: 0072 | G7: Albert City-Truesdale | H7: 209.6 | I7: 7459
A8: 2024 | B8: 15 | C8: 0081 | F8: 0081 | G8: Albia | H8: 1099.4 | I8: 7413
A9: 2024 | B9: 10 | C9: 0099 | F9: 0099 | G9: Alburnett | H9: 526.5 | I9: 7413
A10: 2024 | B10: 07 | C10: 0108 | F10: 0108 | G10: Alden | H10: 273.7 | I10: 7413
A11: 2024 | B11: 05 | C11: 0126 | D11: 6417 | E11: 3897 | F11: 0126 | G11: Algona | H11: 1446.4 | I11: 7427
A12: 2024 | B12: 01 | C12: 0135 | F12: 0135 | G12: Allamakee | H12: 1087.4 | I12: 7460
A13: 2024 | B13: 05 | C13: 0171 | F13: 0171 | G13: Alta-Aurelia | H13: 872.8 | I13: 7413
A14: 2024 | B14: 11 | C14: 0225 | F14: 0225 | G14: Ames | H14: 4439.6 | I14: 7468
A15: 2024 | B15: 10 | C15: 0234 | F15: 0234 | G15: Anamosa | H15: 1256.1 | I15: 7413
A16: 2024 | B16: 09 | C16: 0243 | F16: 0243 | G16: Andrew | H16: 233 | I16: 7443
A17: 2024 | B17: 11 | C17: 0261 | F17: 0261 | G17: Ankeny | H17: 12671.4 | I17: 7413
A18: 2024 | B18: 07 | C18: 0279 | F18: 0279 | G18: Aplington-Parkersburg | H18: 813.2 | I18: 7413
A19: 2024 | B19: 12 | C19: 0355 | F19: 0355 | G19: Ar-We-Va | H19: 276.2 | I19: 7413
A20: 2024 | B20: 13 | C20: 0387 | F20: 0387 | G20: Atlantic | H20: 1401.9 | I20: 7413
A21: 2024 | B21: 11 | C21: 0414 | F21: 0414 | G21: Audubon | H21: 510.6 | I21: 7457
A22: 2024 | B22: 11 | C22: 0540 | F22: 0472 | G22: BCLUW | H22: 461.6 | I22: 7459
A23: 2024 | B23: 11 | C23: 0472 | F23: 0513 | G23: Ballard | H23: 1759.2 | I23: 7413
... A60: 2024 | B60: 13 | C60: 1197 | F60: 1197 | G60: Clarinda | H60: 989.1 | I60: 7413
A61: 2024 | B61: 05 | C61: 1206 | D61: 1854 | F61: 1206 | G61: Clarion-Goldfield-Dows | H61: 1011.1 | I61: 7413
A62: 2024 | B62: 13 | C62: 1211 | F62: 1211 | G62: Clarke | H62: 1442.5 | I62: 7413
A63: 2024 | B63: 07 | C63: 1215 | F63: 1215 | G63: Clarksville | H63: 289.4 | I63: 7413
A64: 2024 | B64: 05 | C64: 1218 | F64: 1218 | G64: Clay Central-Everly | H64: 290.1 | I64: 7506
A65: 2024 | B65: 01 | C65: 2763 | F65: 2763 | G65: Clayton Ridge | H65: 641.9 | I65: 7470
A66: 2024 | B66: 10 | C66: 1221 | D66: 0216 | F66: 1221 | G66: Clear Creek-Amana | H66: 2937.9 | I66: 7414
A67: 2024 | B67: 07 | C67: 1233 | F67: 1233 | G67: Clear Lake | H67: 1173.1 | I67: 7413
A68: 2024 | B68: 09 | C68: 1278 | F68: 1278 | G68: Clinton | H68: 3604.2 | I68: 7424
A69: 2024 | B69: 11 | C69: 1332 | F69: 1332 | G69: Colfax-Mingo | H69: 707.2 | I69: 7413
A70: 2024 | B70: 10 | C70: 1337 | F70: 1337 | G70: College Community | H70: 5147.9 | I70: 7413
A71: 2024 | B71: 11 | C71: 1350 | F71: 1350 | G71: Collins-Maxwell | H71: 463.9 | I71: 7413
A72: 2024 | B72: 11 | C72: 1359 | F72: 1359 | G72: Colo-Nesco | H72: 452.9 | I72: 7413
A73: 2024 | B73: 09 | C73: 1368 | F73: 1368 | G73: Columbus | H73: 741.9 | I73: 7413
A74: 2024 | B74: 11 | C74: 1413 | F74: 1413 | G74: Coon Rapids-Bayard | H74: 425 | I74: 7525
A75: 2024 | B75: 13 | C75: 1431 | F75: 1431 | G75: Corning | H75: 382.1 | I75: 7425
A76: 2024 | B76: 13 | C76: 1476 | F76: 1476 | G76: Council Bluffs | H76: 8707.7 | I76: 7447
A77: 2024 | B77: 13 | C77: 1503 | F77: 1503 | G77: Creston | H77: 1397 | I77: 7413
A78: 2024 | B78: 11 | C78: 1576 | F78: 1576 | G78: Dallas Center-Grimes | H78: 3478 | I78: 7413
... A266: 2024 | B266: 11 | C266: 6096 | F266: 6094 | G266: Southeast Valley | H266: 1093.7 | I266: 7502
A267: 2024 | B267: 05 | C267: 6094 | D267: 5323 | F267: 6096 | G267: Southeast Warren | H267: 505.7 | I267: 7413
A268: 2024 | B268: 05 | C268: 6102 | F268: 6102 | G268: Spencer | H268: 2025.3 | I268: 7413
A269: 2024 | B269: 05 | C269: 6120 | F269: 6120 | G269: Spirit Lake | H269: 1167.9 | I269: 7413
A270: 2024 | B270: 10 | C270: 6138 | F270: 6138 | G270: Springville | H270: 406.7 | I270: 7420
A271: 2024 | B271: 07 | C271: 5751 | F271: 5751 | G271: St Ansgar | H271: 570.7 | I271: 7413
A272: 2024 | B272: 13 | C272: 6165 | F272: 6165 | G272: Stanton | H272: 197 | I272: 7413
A273: 2024 | B273: 01 | C273: 6175 | F273: 6175 | G273: Starmont | H273: 584.6 | I273: 7413
A274: 2024 | B274: 05 | C274: 6219 | F274: 6219 | G274: Storm Lake | H274: 2531.7 | I274: 7413
A275: 2024 | B275: 05 | C275: 6246 | F275: 6246 | G275: Stratford | H275: 132.8 | I275: 7553
A276: 2024 | B276: 07 | C276: 6273 | F276: 6273 | G276: Sumner-Fredericksburg | H276: 769.6 | I276: 7413
A277: 2024 | B277: 10 | C277: 6408 | F277: 6408 | G277: Tipton | H277: 828.7 | I277: 7429
A278: 2024 | B278: 13 | C278: 6453 | F278: 6453 | G278: Treynor | H278: 575.2 | I278: 7413
A279: 2024 | B279: 13 | C279: 6460 | F279: 6460 | G279: Tri-Center | H279: 656.1 | I279: 7413
... A300: 2024 | B300: 15 | C300: 6854 | F300: 6854 | G300: Wayne | H300: 574.5 | I300: 7413
A301: 2024 | B301: 05 | C301: 6867 | D301: 4775 | F301: 6867 | G301: Webster City | H301: 1729.2 | I301: 7413
A302: 2024 | B302: 05 | C302: 6921 | F302: 6921 | G302: West Bend-Mallard | H302: 328.1 | I302: 7430
A303: 2024 | B303: 10 | C303: 6930 | F303: 6930 | G303: West Branch | H303: 785.9 | I303: 7413
A304: 2024 | B304: 15 | C304: 6937 | F304: 6937 | G304: West Burlington | H304: 405 | I304: 7413
A305: 2024 | B305: 01 | C305: 6943 | F305: 6943 | G305: West Central | H305: 268.2 | I305: 7413
A306: 2024 | B306: 11 | C306: 6264 | F306: 6264 | G306: West Central Valley | H306: 947.2 | I306: 7444
A307: 2024 | B307: 01 | C307: 6950 | F307: 6950 | G307: West Delaware Co | H307: 1363.5 | I307: 7413
A308: 2024 | B308: 11 | C308: 6957 | F308: 6957 | G308: West Des Moines | H308: 8678.6 | I308: 7413
A309: 2024 | B309: 07 | C309: 5922 | F309: 5922 | G309: West Fork | H309: 763.8 | I309: 7434
A310: 2024 | B310: 07 | C310: 0819 | F310: 0819 | G310: West Hancock | H310: 559.3 | I310: 7413
A311: 2024 | B311: 13 | C311: 6969 | F311: 6969 | G311: West Harrison | H311: 356.3 | I311: 7548
A312: 2024 | B312: 09 | C312: 6975 | F312: 6975 | G312: West Liberty | H312: 1235.1 | I312: 7413
A313: 2024 | B313: 12 | C313: 6983 | F313: 6983 | G313: West Lyon | H313: 938.4 | I313: 7413
... A326: 2024 | B326: 11 | C326: 7110 | F326: 7110 | G326: Woodward-Granger | H326: 1062.9 | I326: 7470

Sheet ActiveDistricts
A1: FiscalYear | B1: AEA | C1: Dist | D1: DistSub1 | E1: DistSub2 | F1: DistrictNumber | G1: Label | H1: Enrollment | I1: # Eligible for Free or Reduced Lunch | J1: FRL %
A2: 2024 | B2: 11 | C2: 0018 | F2: 0018 | G2: Adair-Casey | H2: =SUMPRODUCT(SUMIF(fr2223g1to6dst_cep!$E$2:$E$328,ActiveDistricts!$D2:$F2,fr2223g1to6dst_cep!$G$2:$G$328)) -> 132 | I2: =SUMPRODUCT(SUMIF(fr2223g1to6dst_cep!$E$2:$E$328,ActiveDistricts!$D2:$F2,fr2223g1to6dst_cep!$H$2:$H$328)) -> 68 | J2: =I2/H2 -> 0.51515152 | M2: 306.3
A3: 2024 | B3: 11 | C3: 0027 | F3: 0027 | G3: Adel-Desoto-Minburn | H3: =SUMPRODUCT(SUMIF(fr2223g1to6dst_cep!$E$2:$E$328,ActiveDistricts!$D3:$F3,fr2223g1to6dst_cep!$G$2:$G$328)) -> 1022 | I3: =SUMPRODUCT(SUMIF(fr2223g1to6dst_cep!$E$2:$E$328,ActiveDistricts!$D3:$F3,fr2223g1to6dst_cep!$H$2:$H$328)) -> 188 | J3: =I3/H3 -> 0.18395303 | M3: 2130.9
A4: 2024 | B4: 07 | C4: 0009 | F4: 0009 | G4: AGWSR | H4: =SUMPRODUCT(SUMIF(fr2223g1to6dst_cep!$E$2:$E$328,ActiveDistricts!$D4:$F4,fr2223g1to6dst_cep!$G$2:$G$328)) -> 253 | I4: =SUMPRODUCT(SUMIF(fr2223g1to6dst_cep!$E$2:$E$328,ActiveDistricts!$D4:$F4,fr2223g1to6dst_cep!$H$2:$H$328)) -> 101 | J4: =I4/H4 -> 0.39920949 | M4: 686.4
A5: 2024 | B5: 13 | C5: 0441 | F5: 0441 | G5: AHSTW | H5: =SUMPRODUCT(SUMIF(fr2223g1to6dst_cep!$E$2:$E$328,ActiveDistricts!$D5:$F5,fr2223g1to6dst_cep!$G$2:$G$328)) -> 328 | I5: =SUMPRODUCT(SUMIF(fr2223g1to6dst_cep!$E$2:$E$328,ActiveDistricts!$D5:$F5,fr2223g1to6dst_cep!$H$2:$H$328)) -> 139 | J5: =I5/H5 -> 0.42378049 | M5: 792.6
A6: 2024 | B6: 12 | C6: 0063 | F6: 0063 | G6: Akron-Westfield | H6: =SUMPRODUCT(SUMIF(fr2223g1to6dst_cep!$E$2:$E$328,ActiveDistricts!$D6:$F6,fr2223g1to6dst_cep!$G$2:$G$328)) -> 247 | I6: =SUMPRODUCT(SUMIF(fr2223g1to6dst_cep!$E$2:$E$328,ActiveDistricts!$D6:$F6,fr2223g1to6dst_cep!$H$2:$H$328)) -> 98 | J6: =I6/H6 -> 0.39676113 | M6: 555.2
A7: 2024 | B7: 05 | C7: 0072 | F7: 0072 | G7: Albert City-Truesdale | H7: =SUMPRODUCT(SUMIF(fr2223g1to6dst_cep!$E$2:$E$328,ActiveDistricts!$D7:$F7,fr2223g1to6dst_cep!$G$2:$G$328)) -> 81 | I7: =SUMPRODUCT(SUMIF(fr2223g1to6dst_cep!$E$2:$E$328,ActiveDistricts!$D7:$F7,fr2223g1to6dst_cep!$H$2:$H$328)) -> 43 | J7: =I7/H7 -> 0.5308642 | M7: 209.6
A8: 2024 | B8: 15 | C8: 0081 | F8: 0081 | G8: Albia | H8: =SUMPRODUCT(SUMIF(fr2223g1to6dst_cep!$E$2:$E$328,ActiveDistricts!$D8:$F8,fr2223g1to6dst_cep!$G$2:$G$328)) -> 445 | I8: =SUMPRODUCT(SUMIF(fr2223g1to6dst_cep!$E$2:$E$328,ActiveDistricts!$D8:$F8,fr2223g1to6dst_cep!$H$2:$H$328)) -> 191 | J8: =I8/H8 -> 0.42921348 | M8: 1099.4
A9: 2024 | B9: 10 | C9: 0099 | F9: 0099 | G9: Alburnett | H9: =SUMPRODUCT(SUMIF(fr2223g1to6dst_cep!$E$2:$E$328,ActiveDistricts!$D9:$F9,fr2223g1to6dst_cep!$G$2:$G$328)) -> 324 | I9: =SUMPRODUCT(SUMIF(fr2223g1to6dst_cep!$E$2:$E$328,ActiveDistricts!$D9:$F9,fr2223g1to6dst_cep!$H$2:$H$328)) -> 75 | J9: =I9/H9 -> 0.23148148 | M9: 526.5
A10: 2024 | B10: 07 | C10: 0108 | F10: 0108 | G10: Alden | H10: =SUMPRODUCT(SUMIF(fr2223g1to6dst_cep!$E$2:$E$328,ActiveDistricts!$D10:$F10,fr2223g1to6dst_cep!$G$2:$G$328)) -> 111 | I10: =SUMPRODUCT(SUMIF(fr2223g1to6dst_cep!$E$2:$E$328,ActiveDistricts!$D10:$F10,fr2223g1to6dst_cep!$H$2:$H$328)) -> 46 | J10: =I10/H10 -> 0.41441441 | M10: 273.7
A11: 2024 | B11: 05 | C11: 0126 | D11: 6417 | E11: 3897 | F11: 0126 | G11: Algona | H11: =SUMPRODUCT(SUMIF(fr2223g1to6dst_cep!$E$2:$E$328,ActiveDistricts!$D11:$F11,fr2223g1to6dst_cep!$G$2:$G$328)) -> 623 | I11: =SUMPRODUCT(SUMIF(fr2223g1to6dst_cep!$E$2:$E$328,ActiveDistricts!$D11:$F11,fr2223g1to6dst_cep!$H$2:$H$328)) -> 235 | J11: =I11/H11 -> 0.37720706 | M11: 1307.3
A12: 2024 | B12: 01 | C12: 0135 | F12: 0135 | G12: Allamakee | H12: =SUMPRODUCT(SUMIF(fr2223g1to6dst_cep!$E$2:$E$328,ActiveDistricts!$D12:$F12,fr2223g1to6dst_cep!$G$2:$G$328)) -> 410 | I12: =SUMPRODUCT(SUMIF(fr2223g1to6dst_cep!$E$2:$E$328,ActiveDistricts!$D12:$F12,fr2223g1to6dst_cep!$H$2:$H$328)) -> 174 | J12: =I12/H12 -> 0.42439024 | M12: 1087.4
A13: 2024 | B13: 05 | C13: 0171 | F13: 0171 | G13: Alta-Aurelia | H13: =SUMPRODUCT(SUMIF(fr2223g1to6dst_cep!$E$2:$E$328,ActiveDistricts!$D13:$F13,fr2223g1to6dst_cep!$G$2:$G$328)) -> 370 | I13: =SUMPRODUCT(SUMIF(fr2223g1to6dst_cep!$E$2:$E$328,ActiveDistricts!$D13:$F13,fr2223g1to6dst_cep!$H$2:$H$328)) -> 164 | J13: =I13/H13 -> 0.44324324 | M13: 872.8
A14: 2024 | B14: 11 | C14: 0225 | F14: 0225 | G14: Ames | H14: =SUMPRODUCT(SUMIF(fr2223g1to6dst_cep!$E$2:$E$328,ActiveDistricts!$D14:$F14,fr2223g1to6dst_cep!$G$2:$G$328)) -> 1959 | I14: =SUMPRODUCT(SUMIF(fr2223g1to6dst_cep!$E$2:$E$328,ActiveDistricts!$D14:$F14,fr2223g1to6dst_cep!$H$2:$H$328)) -> 665 | J14: =I14/H14 -> 0.33945891 | M14: 4439.6
A15: 2024 | B15: 10 | C15: 0234 | F15: 0234 | G15: Anamosa | H15: =SUMPRODUCT(SUMIF(fr2223g1to6dst_cep!$E$2:$E$328,ActiveDistricts!$D15:$F15,fr2223g1to6dst_cep!$G$2:$G$328)) -> 441 | I15: =SUMPRODUCT(SUMIF(fr2223g1to6dst_cep!$E$2:$E$328,ActiveDistricts!$D15:$F15,fr2223g1to6dst_cep!$H$2:$H$328)) -> 184 | J15: =I15/H15 -> 0.41723356 | M15: 1256.1
A16: 2024 | B16: 09 | C16: 0243 | F16: 0243 | G16: Andrew | H16: =SUMPRODUCT(SUMIF(fr2223g1to6dst_cep!$E$2:$E$328,ActiveDistricts!$D16:$F16,fr2223g1to6dst_cep!$G$2:$G$328)) -> 106 | I16: =SUMPRODUCT(SUMIF(fr2223g1to6dst_cep!$E$2:$E$328,ActiveDistricts!$D16:$F16,fr2223g1to6dst_cep!$H$2:$H$328)) -> 35 | J16: =I16/H16 -> 0.33018868 | M16: 233
A17: 2024 | B17: 11 | C17: 0261 | F17: 0261 | G17: Ankeny | H17: =SUMPRODUCT(SUMIF(fr2223g1to6dst_cep!$E$2:$E$328,ActiveDistricts!$D17:$F17,fr2223g1to6dst_cep!$G$2:$G$328)) -> 5782 | I17: =SUMPRODUCT(SUMIF(fr2223g1to6dst_cep!$E$2:$E$328,ActiveDistricts!$D17:$F17,fr2223g1to6dst_cep!$H$2:$H$328)) -> 1144 | J17: =I17/H17 -> 0.19785541 | M17: 12671.4
A18: 2024 | B18: 07 | C18: 0279 | F18: 0279 | G18: Aplington-Parkersburg | H18: =SUMPRODUCT(SUMIF(fr2223g1to6dst_cep!$E$2:$E$328,ActiveDistricts!$D18:$F18,fr2223g1to6dst_cep!$G$2:$G$328)) -> 371 | I18: =SUMPRODUCT(SUMIF(fr2223g1to6dst_cep!$E$2:$E$328,ActiveDistricts!$D18:$F18,fr2223g1to6dst_cep!$H$2:$H$328)) -> 110 | J18: =I18/H18 -> 0.29649596 | M18: 813.2
A19: 2024 | B19: 12 | C19: 0355 | F19: 0355 | G19: Ar-We-Va | H19: =SUMPRODUCT(SUMIF(fr2223g1to6dst_cep!$E$2:$E$328,ActiveDistricts!$D19:$F19,fr2223g1to6dst_cep!$G$2:$G$328)) -> 109 | I19: =SUMPRODUCT(SUMIF(fr2223g1to6dst_cep!$E$2:$E$328,ActiveDistricts!$D19:$F19,fr2223g1to6dst_cep!$H$2:$H$328)) -> 51 | J19: =I19/H19 -> 0.46788991 | M19: 276.2
A20: 2024 | B20: 13 | C20: 0387 | F20: 0387 | G20: Atlantic | H20: =SUMPRODUCT(SUMIF(fr2223g1to6dst_cep!$E$2:$E$328,ActiveDistricts!$D20:$F20,fr2223g1to6dst_cep!$G$2:$G$328)) -> 654 | I20: =SUMPRODUCT(SUMIF(fr2223g1to6dst_cep!$E$2:$E$328,ActiveDistricts!$D20:$F20,fr2223g1to6dst_cep!$H$2:$H$328)) -> 268 | J20: =I20/H20 -> 0.40978593 | M20: 1401.9
A21: 2024 | B21: 11 | C21: 0414 | F21: 0414 | G21: Audubon | H21: =SUMPRODUCT(SUMIF(fr2223g1to6dst_cep!$E$2:$E$328,ActiveDistricts!$D21:$F21,fr2223g1to6dst_cep!$G$2:$G$328)) -> 226 | I21: =SUMPRODUCT(SUMIF(fr2223g1to6dst_cep!$E$2:$E$328,ActiveDistricts!$D21:$F21,fr2223g1to6dst_cep!$H$2:$H$328)) -> 94 | J21: =I21/H21 -> 0.4159292 | M21: 510.6
A22: 2024 | B22: 11 | C22: 0472 | F22: 0472 | G22: Ballard | H22: =SUMPRODUCT(SUMIF(fr2223g1to6dst_cep!$E$2:$E$328,ActiveDistricts!$D22:$F22,fr2223g1to6dst_cep!$G$2:$G$328)) -> 825 | I22: =SUMPRODUCT(SUMIF(fr2223g1to6dst_cep!$E$2:$E$328,ActiveDistricts!$D22:$F22,fr2223g1to6dst_cep!$H$2:$H$328)) -> 141 | J22: =I22/H22 -> 0.17090909 | M22: 1759.2
A23: 2024 | B23: 11 | C23: 0513 | F23: 0513 | G23: Baxter | H23: =SUMPRODUCT(SUMIF(fr2223g1to6dst_cep!$E$2:$E$328,ActiveDistricts!$D23:$F23,fr2223g1to6dst_cep!$G$2:$G$328)) -> 209 | I23: =SUMPRODUCT(SUMIF(fr2223g1to6dst_cep!$E$2:$E$328,ActiveDistricts!$D23:$F23,fr2223g1to6dst_cep!$H$2:$H$328)) -> 58 | J23: =I23/H23 -> 0.27751196 | M23: 360.7
... A60: 2024 | B60: 13 | C60: 1197 | F60: 1197 | G60: Clarinda | H60: =SUMPRODUCT(SUMIF(fr2223g1to6dst_cep!$E$2:$E$328,ActiveDistricts!$D60:$F60,fr2223g1to6dst_cep!$G$2:$G$328)) -> 451 | I60: =SUMPRODUCT(SUMIF(fr2223g1to6dst_cep!$E$2:$E$328,ActiveDistricts!$D60:$F60,fr2223g1to6dst_cep!$H$2:$H$328)) -> 199 | J60: =I60/H60 -> 0.44124169 | M60: 989.1
A61: 2024 | B61: 05 | C61: 1206 | D61: 1854 | F61: 1206 | G61: Clarion-Goldfield-Dows | H61: =SUMPRODUCT(SUMIF(fr2223g1to6dst_cep!$E$2:$E$328,ActiveDistricts!$D61:$F61,fr2223g1to6dst_cep!$G$2:$G$328)) -> 399 | I61: =SUMPRODUCT(SUMIF(fr2223g1to6dst_cep!$E$2:$E$328,ActiveDistricts!$D61:$F61,fr2223g1to6dst_cep!$H$2:$H$328)) -> 230 | J61: =I61/H61 -> 0.5764411 | M61: 1011.1
A62: 2024 | B62: 13 | C62: 1211 | F62: 1211 | G62: Clarke | H62: =SUMPRODUCT(SUMIF(fr2223g1to6dst_cep!$E$2:$E$328,ActiveDistricts!$D62:$F62,fr2223g1to6dst_cep!$G$2:$G$328)) -> 525 | I62: =SUMPRODUCT(SUMIF(fr2223g1to6dst_cep!$E$2:$E$328,ActiveDistricts!$D62:$F62,fr2223g1to6dst_cep!$H$2:$H$328)) -> 317 | J62: =I62/H62 -> 0.60380952 | M62: 1442.5
A63: 2024 | B63: 07 | C63: 1215 | F63: 1215 | G63: Clarksville | H63: =SUMPRODUCT(SUMIF(fr2223g1to6dst_cep!$E$2:$E$328,ActiveDistricts!$D63:$F63,fr2223g1to6dst_cep!$G$2:$G$328)) -> 126 | I63: =SUMPRODUCT(SUMIF(fr2223g1to6dst_cep!$E$2:$E$328,ActiveDistricts!$D63:$F63,fr2223g1to6dst_cep!$H$2:$H$328)) -> 42 | J63: =I63/H63 -> 0.33333333 | M63: 289.4
A64: 2024 | B64: 05 | C64: 1218 | F64: 1218 | G64: Clay Central-Everly | H64: =SUMPRODUCT(SUMIF(fr2223g1to6dst_cep!$E$2:$E$328,ActiveDistricts!$D64:$F64,fr2223g1to6dst_cep!$G$2:$G$328)) -> 51 | I64: =SUMPRODUCT(SUMIF(fr2223g1to6dst_cep!$E$2:$E$328,ActiveDistricts!$D64:$F64,fr2223g1to6dst_cep!$H$2:$H$328)) -> 38 | J64: =I64/H64 -> 0.74509804 | M64: 290.1
A65: 2024 | B65: 01 | C65: 2763 | F65: 2763 | G65: Clayton Ridge | H65: =SUMPRODUCT(SUMIF(fr2223g1to6dst_cep!$E$2:$E$328,ActiveDistricts!$D65:$F65,fr2223g1to6dst_cep!$G$2:$G$328)) -> 510 | I65: =SUMPRODUCT(SUMIF(fr2223g1to6dst_cep!$E$2:$E$328,ActiveDistricts!$D65:$F65,fr2223g1to6dst_cep!$H$2:$H$328)) -> 231 | J65: =I65/H65 -> 0.45294118 | M65: 641.9
A66: 2024 | B66: 10 | C66: 1221 | D66: 0216 | F66: 1221 | G66: Clear Creek-Amana | H66: =SUMPRODUCT(SUMIF(fr2223g1to6dst_cep!$E$2:$E$328,ActiveDistricts!$D66:$F66,fr2223g1to6dst_cep!$G$2:$G$328)) -> 1479 | I66: =SUMPRODUCT(SUMIF(fr2223g1to6dst_cep!$E$2:$E$328,ActiveDistricts!$D66:$F66,fr2223g1to6dst_cep!$H$2:$H$328)) -> 402 | J66: =I66/H66 -> 0.27180527 | M66: 2937.9
A67: 2024 | B67: 07 | C67: 1233 | F67: 1233 | G67: Clear Lake | H67: =SUMPRODUCT(SUMIF(fr2223g1to6dst_cep!$E$2:$E$328,ActiveDistricts!$D67:$F67,fr2223g1to6dst_cep!$G$2:$G$328)) -> 615 | I67: =SUMPRODUCT(SUMIF(fr2223g1to6dst_cep!$E$2:$E$328,ActiveDistricts!$D67:$F67,fr2223g1to6dst_cep!$H$2:$H$328)) -> 190 | J67: =I67/H67 -> 0.30894309 | M67: 1173.1
A68: 2024 | B68: 09 | C68: 1278 | F68: 1278 | G68: Clinton | H68: =SUMPRODUCT(SUMIF(fr2223g1to6dst_cep!$E$2:$E$328,ActiveDistricts!$D68:$F68,fr2223g1to6dst_cep!$G$2:$G$328)) -> 1439 | I68: =SUMPRODUCT(SUMIF(fr2223g1to6dst_cep!$E$2:$E$328,ActiveDistricts!$D68:$F68,fr2223g1to6dst_cep!$H$2:$H$328)) -> 888 | J68: =I68/H68 -> 0.61709521 | M68: 3604.2
A69: 2024 | B69: 11 | C69: 1332 | F69: 1332 | G69: Colfax-Mingo | H69: =SUMPRODUCT(SUMIF(fr2223g1to6dst_cep!$E$2:$E$328,ActiveDistricts!$D69:$F69,fr2223g1to6dst_cep!$G$2:$G$328)) -> 274 | I69: =SUMPRODUCT(SUMIF(fr2223g1to6dst_cep!$E$2:$E$328,ActiveDistricts!$D69:$F69,fr2223g1to6dst_cep!$H$2:$H$328)) -> 119 | J69: =I69/H69 -> 0.43430657 | M69: 707.2
A70: 2024 | B70: 10 | C70: 1337 | F70: 1337 | G70: College Community | H70: =SUMPRODUCT(SUMIF(fr2223g1to6dst_cep!$E$2:$E$328,ActiveDistricts!$D70:$F70,fr2223g1to6dst_cep!$G$2:$G$328)) -> 2399 | I70: =SUMPRODUCT(SUMIF(fr2223g1to6dst_cep!$E$2:$E$328,ActiveDistricts!$D70:$F70,fr2223g1to6dst_cep!$H$2:$H$328)) -> 907 | J70: =I70/H70 -> 0.3780742 | M70: 5147.9
A71: 2024 | B71: 11 | C71: 1350 | F71: 1350 | G71: Collins-Maxwell | H71: =SUMPRODUCT(SUMIF(fr2223g1to6dst_cep!$E$2:$E$328,ActiveDistricts!$D71:$F71,fr2223g1to6dst_cep!$G$2:$G$328)) -> 188 | I71: =SUMPRODUCT(SUMIF(fr2223g1to6dst_cep!$E$2:$E$328,ActiveDistricts!$D71:$F71,fr2223g1to6dst_cep!$H$2:$H$328)) -> 83 | J71: =I71/H71 -> 0.44148936 | M71: 463.9
A72: 2024 | B72: 11 | C72: 1359 | F72: 1359 | G72: Colo-Nesco | H72: =SUMPRODUCT(SUMIF(fr2223g1to6dst_cep!$E$2:$E$328,ActiveDistricts!$D72:$F72,fr2223g1to6dst_cep!$G$2:$G$328)) -> 153 | I72: =SUMPRODUCT(SUMIF(fr2223g1to6dst_cep!$E$2:$E$328,ActiveDistricts!$D72:$F72,fr2223g1to6dst_cep!$H$2:$H$328)) -> 68 | J72: =I72/H72 -> 0.44444444 | M72: 452.9
A73: 2024 | B73: 09 | C73: 1368 | F73: 1368 | G73: Columbus | H73: =SUMPRODUCT(SUMIF(fr2223g1to6dst_cep!$E$2:$E$328,ActiveDistricts!$D73:$F73,fr2223g1to6dst_cep!$G$2:$G$328)) -> 278 | I73: =SUMPRODUCT(SUMIF(fr2223g1to6dst_cep!$E$2:$E$328,ActiveDistricts!$D73:$F73,fr2223g1to6dst_cep!$H$2:$H$328)) -> 186 | J73: =I73/H73 -> 0.66906475 | M73: 741.9
A74: 2024 | B74: 11 | C74: 1413 | F74: 1413 | G74: Coon Rapids-Bayard | H74: =SUMPRODUCT(SUMIF(fr2223g1to6dst_cep!$E$2:$E$328,ActiveDistricts!$D74:$F74,fr2223g1to6dst_cep!$G$2:$G$328)) -> 189 | I74: =SUMPRODUCT(SUMIF(fr2223g1to6dst_cep!$E$2:$E$328,ActiveDistricts!$D74:$F74,fr2223g1to6dst_cep!$H$2:$H$328)) -> 91 | J74: =I74/H74 -> 0.48148148 | M74: 425
A75: 2024 | B75: 13 | C75: 1431 | F75: 1431 | G75: Corning | H75: =SUMPRODUCT(SUMIF(fr2223g1to6dst_cep!$E$2:$E$328,ActiveDistricts!$D75:$F75,fr2223g1to6dst_cep!$G$2:$G$328)) -> 143 | I75: =SUMPRODUCT(SUMIF(fr2223g1to6dst_cep!$E$2:$E$328,ActiveDistricts!$D75:$F75,fr2223g1to6dst_cep!$H$2:$H$328)) -> 61 | J75: =I75/H75 -> 0.42657343 | M75: 382.1
A76: 2024 | B76: 13 | C76: 1476 | F76: 1476 | G76: Council Bluffs | H76: =SUMPRODUCT(SUMIF(fr2223g1to6dst_cep!$E$2:$E$328,ActiveDistricts!$D76:$F76,fr2223g1to6dst_cep!$G$2:$G$328)) -> 3727 | I76: =SUMPRODUCT(SUMIF(fr2223g1to6dst_cep!$E$2:$E$328,ActiveDistricts!$D76:$F76,fr2223g1to6dst_cep!$H$2:$H$328)) -> 2420 | J76: =I76/H76 -> 0.6493158 | M76: 8707.7
A77: 2024 | B77: 13 | C77: 1503 | F77: 1503 | G77: Creston | H77: =SUMPRODUCT(SUMIF(fr2223g1to6dst_cep!$E$2:$E$328,ActiveDistricts!$D77:$F77,fr2223g1to6dst_cep!$G$2:$G$328)) -> 502 | I77: =SUMPRODUCT(SUMIF(fr2223g1to6dst_cep!$E$2:$E$328,ActiveDistricts!$D77:$F77,fr2223g1to6dst_cep!$H$2:$H$328)) -> 284 | J77: =I77/H77 -> 0.56573705 | M77: 1397
A78: 2024 | B78: 11 | C78: 1576 | F78: 1576 | G78: Dallas Center-Grimes | H78: =SUMPRODUCT(SUMIF(fr2223g1to6dst_cep!$E$2:$E$328,ActiveDistricts!$D78:$F78,fr2223g1to6dst_cep!$G$2:$G$328)) -> 1697 | I78: =SUMPRODUCT(SUMIF(fr2223g1to6dst_cep!$E$2:$E$328,ActiveDistricts!$D78:$F78,fr2223g1to6dst_cep!$H$2:$H$328)) -> 299 | J78: =I78/H78 -> 0.17619328 | M78: 3478
... A266: 2024 | B266: 11 | C266: 6094 | F266: 6094 | G266: Southeast Warren | H266: =SUMPRODUCT(SUMIF(fr2223g1to6dst_cep!$E$2:$E$328,ActiveDistricts!$D266:$F266,fr2223g1to6dst_cep!$G$2:$G$328)) -> 179 | I266: =SUMPRODUCT(SUMIF(fr2223g1to6dst_cep!$E$2:$E$328,ActiveDistricts!$D266:$F266,fr2223g1to6dst_cep!$H$2:$H$328)) -> 63 | J266: =I266/H266 -> 0.35195531 | M266: 516.7
A267: 2024 | B267: 05 | C267: 6096 | D267: 5323 | F267: 6096 | G267: Southeast Valley | H267: =SUMPRODUCT(SUMIF(fr2223g1to6dst_cep!$E$2:$E$328,ActiveDistricts!$D267:$F267,fr2223g1to6dst_cep!$G$2:$G$328)) -> 451 | I267: =SUMPRODUCT(SUMIF(fr2223g1to6dst_cep!$E$2:$E$328,ActiveDistricts!$D267:$F267,fr2223g1to6dst_cep!$H$2:$H$328)) -> 202 | J267: =I267/H267 -> 0.44789357 | M267: 7211
A268: 2024 | B268: 05 | C268: 6102 | F268: 6102 | G268: Spencer | H268: =SUMPRODUCT(SUMIF(fr2223g1to6dst_cep!$E$2:$E$328,ActiveDistricts!$D268:$F268,fr2223g1to6dst_cep!$G$2:$G$328)) -> 921 | I268: =SUMPRODUCT(SUMIF(fr2223g1to6dst_cep!$E$2:$E$328,ActiveDistricts!$D268:$F268,fr2223g1to6dst_cep!$H$2:$H$328)) -> 455 | J268: =I268/H268 -> 0.49402823 | M268: 505.7
A269: 2024 | B269: 05 | C269: 6120 | F269: 6120 | G269: Spirit Lake | H269: =SUMPRODUCT(SUMIF(fr2223g1to6dst_cep!$E$2:$E$328,ActiveDistricts!$D269:$F269,fr2223g1to6dst_cep!$G$2:$G$328)) -> 533 | I269: =SUMPRODUCT(SUMIF(fr2223g1to6dst_cep!$E$2:$E$328,ActiveDistricts!$D269:$F269,fr2223g1to6dst_cep!$H$2:$H$328)) -> 156 | J269: =I269/H269 -> 0.29268293 | M269: 524.3
A270: 2024 | B270: 10 | C270: 6138 | F270: 6138 | G270: Springville | H270: =SUMPRODUCT(SUMIF(fr2223g1to6dst_cep!$E$2:$E$328,ActiveDistricts!$D270:$F270,fr2223g1to6dst_cep!$G$2:$G$328)) -> 188 | I270: =SUMPRODUCT(SUMIF(fr2223g1to6dst_cep!$E$2:$E$328,ActiveDistricts!$D270:$F270,fr2223g1to6dst_cep!$H$2:$H$328)) -> 48 | J270: =I270/H270 -> 0.25531915 | M270: 2025.3
A271: 2024 | B271: 07 | C271: 5751 | F271: 5751 | G271: St Ansgar | H271: =SUMPRODUCT(SUMIF(fr2223g1to6dst_cep!$E$2:$E$328,ActiveDistricts!$D271:$F271,fr2223g1to6dst_cep!$G$2:$G$328)) -> 262 | I271: =SUMPRODUCT(SUMIF(fr2223g1to6dst_cep!$E$2:$E$328,ActiveDistricts!$D271:$F271,fr2223g1to6dst_cep!$H$2:$H$328)) -> 66 | J271: =I271/H271 -> 0.2519084 | M271: 1167.9
A272: 2024 | B272: 13 | C272: 6165 | F272: 6165 | G272: Stanton | H272: =SUMPRODUCT(SUMIF(fr2223g1to6dst_cep!$E$2:$E$328,ActiveDistricts!$D272:$F272,fr2223g1to6dst_cep!$G$2:$G$328)) -> 129 | I272: =SUMPRODUCT(SUMIF(fr2223g1to6dst_cep!$E$2:$E$328,ActiveDistricts!$D272:$F272,fr2223g1to6dst_cep!$H$2:$H$328)) -> 61 | J272: =I272/H272 -> 0.47286822 | M272: 406.7
A273: 2024 | B273: 01 | C273: 6175 | F273: 6175 | G273: Starmont | H273: =SUMPRODUCT(SUMIF(fr2223g1to6dst_cep!$E$2:$E$328,ActiveDistricts!$D273:$F273,fr2223g1to6dst_cep!$G$2:$G$328)) -> 224 | I273: =SUMPRODUCT(SUMIF(fr2223g1to6dst_cep!$E$2:$E$328,ActiveDistricts!$D273:$F273,fr2223g1to6dst_cep!$H$2:$H$328)) -> 90 | J273: =I273/H273 -> 0.40178571 | M273: 570.7
A274: 2024 | B274: 05 | C274: 6219 | F274: 6219 | G274: Storm Lake | H274: =SUMPRODUCT(SUMIF(fr2223g1to6dst_cep!$E$2:$E$328,ActiveDistricts!$D274:$F274,fr2223g1to6dst_cep!$G$2:$G$328)) -> 1208 | I274: =SUMPRODUCT(SUMIF(fr2223g1to6dst_cep!$E$2:$E$328,ActiveDistricts!$D274:$F274,fr2223g1to6dst_cep!$H$2:$H$328)) -> 884 | J274: =I274/H274 -> 0.73178808 | M274: 197
A275: 2024 | B275: 05 | C275: 6246 | F275: 6246 | G275: Stratford | H275: =SUMPRODUCT(SUMIF(fr2223g1to6dst_cep!$E$2:$E$328,ActiveDistricts!$D275:$F275,fr2223g1to6dst_cep!$G$2:$G$328)) -> 47 | I275: =SUMPRODUCT(SUMIF(fr2223g1to6dst_cep!$E$2:$E$328,ActiveDistricts!$D275:$F275,fr2223g1to6dst_cep!$H$2:$H$328)) -> 25 | J275: =I275/H275 -> 0.53191489 | M275: 584.6
A276: 2024 | B276: 07 | C276: 6273 | F276: 6273 | G276: Sumner-Fredericksburg | H276: =SUMPRODUCT(SUMIF(fr2223g1to6dst_cep!$E$2:$E$328,ActiveDistricts!$D276:$F276,fr2223g1to6dst_cep!$G$2:$G$328)) -> 335 | I276: =SUMPRODUCT(SUMIF(fr2223g1to6dst_cep!$E$2:$E$328,ActiveDistricts!$D276:$F276,fr2223g1to6dst_cep!$H$2:$H$328)) -> 145 | J276: =I276/H276 -> 0.43283582 | M276: 2531.7
A277: 2024 | B277: 10 | C277: 6408 | F277: 6408 | G277: Tipton | H277: =SUMPRODUCT(SUMIF(fr2223g1to6dst_cep!$E$2:$E$328,ActiveDistricts!$D277:$F277,fr2223g1to6dst_cep!$G$2:$G$328)) -> 387 | I277: =SUMPRODUCT(SUMIF(fr2223g1to6dst_cep!$E$2:$E$328,ActiveDistricts!$D277:$F277,fr2223g1to6dst_cep!$H$2:$H$328)) -> 146 | J277: =I277/H277 -> 0.37726098 | M277: 132.8
A278: 2024 | B278: 13 | C278: 6453 | F278: 6453 | G278: Treynor | H278: =SUMPRODUCT(SUMIF(fr2223g1to6dst_cep!$E$2:$E$328,ActiveDistricts!$D278:$F278,fr2223g1to6dst_cep!$G$2:$G$328)) -> 362 | I278: =SUMPRODUCT(SUMIF(fr2223g1to6dst_cep!$E$2:$E$328,ActiveDistricts!$D278:$F278,fr2223g1to6dst_cep!$H$2:$H$328)) -> 52 | J278: =I278/H278 -> 0.14364641 | M278: 769.6
A279: 2024 | B279: 13 | C279: 6460 | F279: 6460 | G279: Tri-Center | H279: =SUMPRODUCT(SUMIF(fr2223g1to6dst_cep!$E$2:$E$328,ActiveDistricts!$D279:$F279,fr2223g1to6dst_cep!$G$2:$G$328)) -> 306 | I279: =SUMPRODUCT(SUMIF(fr2223g1to6dst_cep!$E$2:$E$328,ActiveDistricts!$D279:$F279,fr2223g1to6dst_cep!$H$2:$H$328)) -> 104 | J279: =I279/H279 -> 0.33986928 | M279: 828.7
... A300: 2024 | B300: 15 | C300: 6854 | F300: 6854 | G300: Wayne | H300: =SUMPRODUCT(SUMIF(fr2223g1to6dst_cep!$E$2:$E$328,ActiveDistricts!$D300:$F300,fr2223g1to6dst_cep!$G$2:$G$328)) -> 285 | I300: =SUMPRODUCT(SUMIF(fr2223g1to6dst_cep!$E$2:$E$328,ActiveDistricts!$D300:$F300,fr2223g1to6dst_cep!$H$2:$H$328)) -> 162 | J300: =I300/H300 -> 0.56842105 | M300: 13153.9
A301: 2024 | B301: 05 | C301: 6867 | D301: 4775 | F301: 6867 | G301: Webster City | H301: =SUMPRODUCT(SUMIF(fr2223g1to6dst_cep!$E$2:$E$328,ActiveDistricts!$D301:$F301,fr2223g1to6dst_cep!$G$2:$G$328)) -> 746 | I301: =SUMPRODUCT(SUMIF(fr2223g1to6dst_cep!$E$2:$E$328,ActiveDistricts!$D301:$F301,fr2223g1to6dst_cep!$H$2:$H$328)) -> 399 | J301: =I301/H301 -> 0.53485255 | M301: 2197.8
A302: 2024 | B302: 05 | C302: 6921 | F302: 6921 | G302: West Bend-Mallard | H302: =SUMPRODUCT(SUMIF(fr2223g1to6dst_cep!$E$2:$E$328,ActiveDistricts!$D302:$F302,fr2223g1to6dst_cep!$G$2:$G$328)) -> 146 | I302: =SUMPRODUCT(SUMIF(fr2223g1to6dst_cep!$E$2:$E$328,ActiveDistricts!$D302:$F302,fr2223g1to6dst_cep!$H$2:$H$328)) -> 68 | J302: =I302/H302 -> 0.46575342 | M302: 574.5
A303: 2024 | B303: 10 | C303: 6930 | F303: 6930 | G303: West Branch | H303: =SUMPRODUCT(SUMIF(fr2223g1to6dst_cep!$E$2:$E$328,ActiveDistricts!$D303:$F303,fr2223g1to6dst_cep!$G$2:$G$328)) -> 361 | I303: =SUMPRODUCT(SUMIF(fr2223g1to6dst_cep!$E$2:$E$328,ActiveDistricts!$D303:$F303,fr2223g1to6dst_cep!$H$2:$H$328)) -> 99 | J303: =I303/H303 -> 0.27423823 | M303: 1729.2
A304: 2024 | B304: 15 | C304: 6937 | F304: 6937 | G304: West Burlington | H304: =SUMPRODUCT(SUMIF(fr2223g1to6dst_cep!$E$2:$E$328,ActiveDistricts!$D304:$F304,fr2223g1to6dst_cep!$G$2:$G$328)) -> 403 | I304: =SUMPRODUCT(SUMIF(fr2223g1to6dst_cep!$E$2:$E$328,ActiveDistricts!$D304:$F304,fr2223g1to6dst_cep!$H$2:$H$328)) -> 165 | J304: =I304/H304 -> 0.40942928 | M304: 328.1
A305: 2024 | B305: 01 | C305: 6943 | F305: 6943 | G305: West Central | H305: =SUMPRODUCT(SUMIF(fr2223g1to6dst_cep!$E$2:$E$328,ActiveDistricts!$D305:$F305,fr2223g1to6dst_cep!$G$2:$G$328)) -> 124 | I305: =SUMPRODUCT(SUMIF(fr2223g1to6dst_cep!$E$2:$E$328,ActiveDistricts!$D305:$F305,fr2223g1to6dst_cep!$H$2:$H$328)) -> 58 | J305: =I305/H305 -> 0.46774194 | M305: 785.9
A306: 2024 | B306: 11 | C306: 6264 | F306: 6264 | G306: West Central Valley | H306: =SUMPRODUCT(SUMIF(fr2223g1to6dst_cep!$E$2:$E$328,ActiveDistricts!$D306:$F306,fr2223g1to6dst_cep!$G$2:$G$328)) -> 368 | I306: =SUMPRODUCT(SUMIF(fr2223g1to6dst_cep!$E$2:$E$328,ActiveDistricts!$D306:$F306,fr2223g1to6dst_cep!$H$2:$H$328)) -> 171 | J306: =I306/H306 -> 0.46467391 | M306: 405
A307: 2024 | B307: 01 | C307: 6950 | F307: 6950 | G307: West Delaware Co | H307: =SUMPRODUCT(SUMIF(fr2223g1to6dst_cep!$E$2:$E$328,ActiveDistricts!$D307:$F307,fr2223g1to6dst_cep!$G$2:$G$328)) -> 514 | I307: =SUMPRODUCT(SUMIF(fr2223g1to6dst_cep!$E$2:$E$328,ActiveDistricts!$D307:$F307,fr2223g1to6dst_cep!$H$2:$H$328)) -> 244 | J307: =I307/H307 -> 0.47470817 | M307: 268.2
A308: 2024 | B308: 11 | C308: 6957 | F308: 6957 | G308: West Des Moines | H308: =SUMPRODUCT(SUMIF(fr2223g1to6dst_cep!$E$2:$E$328,ActiveDistricts!$D308:$F308,fr2223g1to6dst_cep!$G$2:$G$328)) -> 3814 | I308: =SUMPRODUCT(SUMIF(fr2223g1to6dst_cep!$E$2:$E$328,ActiveDistricts!$D308:$F308,fr2223g1to6dst_cep!$H$2:$H$328)) -> 1510 | J308: =I308/H308 -> 0.39590981 | M308: 947.2
A309: 2024 | B309: 07 | C309: 5922 | F309: 5922 | G309: West Fork | H309: =SUMPRODUCT(SUMIF(fr2223g1to6dst_cep!$E$2:$E$328,ActiveDistricts!$D309:$F309,fr2223g1to6dst_cep!$G$2:$G$328)) -> 333 | I309: =SUMPRODUCT(SUMIF(fr2223g1to6dst_cep!$E$2:$E$328,ActiveDistricts!$D309:$F309,fr2223g1to6dst_cep!$H$2:$H$328)) -> 134 | J309: =I309/H309 -> 0.4024024 | M309: 1363.5
A310: 2024 | B310: 07 | C310: 0819 | F310: 0819 | G310: West Hancock | H310: =SUMPRODUCT(SUMIF(fr2223g1to6dst_cep!$E$2:$E$328,ActiveDistricts!$D310:$F310,fr2223g1to6dst_cep!$G$2:$G$328)) -> 240 | I310: =SUMPRODUCT(SUMIF(fr2223g1to6dst_cep!$E$2:$E$328,ActiveDistricts!$D310:$F310,fr2223g1to6dst_cep!$H$2:$H$328)) -> 98 | J310: =I310/H310 -> 0.40833333 | M310: 8678.6
A311: 2024 | B311: 13 | C311: 6969 | F311: 6969 | G311: West Harrison | H311: =SUMPRODUCT(SUMIF(fr2223g1to6dst_cep!$E$2:$E$328,ActiveDistricts!$D311:$F311,fr2223g1to6dst_cep!$G$2:$G$328)) -> 140 | I311: =SUMPRODUCT(SUMIF(fr2223g1to6dst_cep!$E$2:$E$328,ActiveDistricts!$D311:$F311,fr2223g1to6dst_cep!$H$2:$H$328)) -> 82 | J311: =I311/H311 -> 0.58571429 | M311: 763.8
A312: 2024 | B312: 09 | C312: 6975 | F312: 6975 | G312: West Liberty | H312: =SUMPRODUCT(SUMIF(fr2223g1to6dst_cep!$E$2:$E$328,ActiveDistricts!$D312:$F312,fr2223g1to6dst_cep!$G$2:$G$328)) -> 537 | I312: =SUMPRODUCT(SUMIF(fr2223g1to6dst_cep!$E$2:$E$328,ActiveDistricts!$D312:$F312,fr2223g1to6dst_cep!$H$2:$H$328)) -> 298 | J312: =I312/H312 -> 0.55493482 | M312: 559.3
A313: 2024 | B313: 12 | C313: 6983 | F313: 6983 | G313: West Lyon | H313: =SUMPRODUCT(SUMIF(fr2223g1to6dst_cep!$E$2:$E$328,ActiveDistricts!$D313:$F313,fr2223g1to6dst_cep!$G$2:$G$328)) -> 392 | I313: =SUMPRODUCT(SUMIF(fr2223g1to6dst_cep!$E$2:$E$328,ActiveDistricts!$D313:$F313,fr2223g1to6dst_cep!$H$2:$H$328)) -> 114 | J313: =I313/H313 -> 0.29081633 | M313: 356.3
... A326: 2024 | B326: 11 | C326: 7110 | F326: 7110 | G326: Woodward-Granger | H326: =SUMPRODUCT(SUMIF(fr2223g1to6dst_cep!$E$2:$E$328,ActiveDistricts!$D326:$F326,fr2223g1to6dst_cep!$G$2:$G$328)) -> 510 | I326: =SUMPRODUCT(SUMIF(fr2223g1to6dst_cep!$E$2:$E$328,ActiveDistricts!$D326:$F326,fr2223g1to6dst_cep!$H$2:$H$328)) -> 114 | J326: =I326/H326 -> 0.22352941 | M326: 466

Sheet Constants
A1: FiscalYear | B1: SPG | C1: CPP | D1: Additional_Dollar | E1: SCPP | F1: SCPP_SPED | G1: TS_SPG | H1: TS_CPP | I1: TS_SCPP | J1: PD_SPG | K1: PD_CPP | L1: PD_SCPP | M1: EI_SPG | N1: EI_CPP | O1: EI_SCPP | P1: TL_SPG | Q1: TL_CPP | R1: TL_SCPP | S1: AEA_SPED_CPP | T1: AEA_SPED_SCPP | U1: AEAMED_CPP | V1: AEAMED_SCPP | W1: AEAED_CPP | X1: AEAED_SCPP | Y1: TS_AEA_CPP | Z1: TS_AEA_SCPP | AA1: PD_AEA_CPP | AB1: PD_AEA_SCPP | AC1: RPFL | AD1: RPFL_CPP | AE1: RPSPEDFL | AF1: RPSPED_CPP | AG1: AEA_SPED_FL | AH1: AEASPED_CPP | AI1: Budg_Adj | AJ1: ULR | AK1: MIN_AID | AL1: PT_SCPP | AM1: PT_PCT | AN1: SMAAPTLR | AO1: AEA_SPED_FL_CPP | AP1: PTRP_PP | AQ1: StateTaxableValuation_PP | AR1: TAG_PP | AS1: PY_RPFL | AT1: PY_SCPP | AU1: L833 | AV1: ISL_StateAidPortion | AW1: ISL_ProrataRed
A2: 1973 | B2: 0.04928 | C2: 45 | D2: 0 | E2: 903 | AC2: 0.7 | AD2: =ROUND(AC2*E2,0) -> 632 | AE2: 0 | AF2: =ROUND(AE2*F2,0) -> 0 | AM2: =1-AC2 -> 0.3
A3: 1974 | B3: 0.05 | C3: =ROUND(E2*B3,0) -> 45 | D3: 0 | E3: =E2+C3+D3 -> 948 | AC3: 0.71 | AD3: =ROUND(AC3*E3,0) -> 673 | AE3: 0 | AF3: =ROUND(AE3*F3,0) -> 0 | AM3: =1-AC3 -> 0.29 | AS3: =INDEX($A$2:$AZ$100,MATCH($A3-1,$A$2:$A$100,0),30) -> 632 | AT3: =INDEX($A$2:$AZ$100,MATCH($A3-1,$A$2:$A$100,0),5) -> 903
A4: 1975 | B4: 0.08 | C4: =ROUND(E3*B4,0) -> 76 | D4: 0 | E4: =E3+C4+D4 -> 1024 | AC4: 0.72 | AD4: =ROUND(AC4*E4,0) -> 737 | AE4: 0 | AF4: =ROUND(AE4*F4,0) -> 0 | AM4: =1-AC4 -> 0.28 | AS4: =INDEX($A$2:$AZ$100,MATCH($A4-1,$A$2:$A$100,0),30) -> 673 | AT4: =INDEX($A$2:$AZ$100,MATCH($A4-1,$A$2:$A$100,0),5) -> 948
A5: 1976 | B5: 0.107 | C5: =ROUND(E4*B5,0) -> 110 | D5: 0 | E5: =E4+C5+D5 -> 1134 | F5: =E5 -> 1134 | T5: 40.43 | V5: 6.08 | X5: 10.16 | AC5: 0.73 | AD5: =ROUND(AC5*E5,0) -> 828 | AE5: 0.73 | AF5: =ROUND(AE5*F5,0) -> 828 | AG5: 0.73 | AH5: =ROUND(AG5*T5,0) -> 30 | AM5: =1-AC5 -> 0.27 | AO5: =ROUND(T5*AG5,0) -> 30 | AS5: =INDEX($A$2:$AZ$100,MATCH($A5-1,$A$2:$A$100,0),30) -> 737 | AT5: =INDEX($A$2:$AZ$100,MATCH($A5-1,$A$2:$A$100,0),5) -> 1024
A6: 1977 | B6: 0.09825 | C6: =ROUND(E5*B6,0) -> 111 | D6: 0 | E6: =E5+C6+D6 -> 1245 | F6: =E6 -> 1245 | T6: 48.47 | V6: 6.57 | X6: 11.3 | AC6: 0.74 | AD6: =ROUND(AC6*E6,0) -> 921 | AE6: 0.74 | AF6: =ROUND(AE6*F6,0) -> 921 | AG6: 0.74 | AH6: =ROUND(AG6*T6,0) -> 36 | AM6: =1-AC6 -> 0.26 | AO6: =ROUND(T6*AG6,0) -> 36 | AS6: =INDEX($A$2:$AZ$100,MATCH($A6-1,$A$2:$A$100,0),30) -> 828 | AT6: =INDEX($A$2:$AZ$100,MATCH($A6-1,$A$2:$A$100,0),5) -> 1134
A7: 1978 | B7: 0.0784 | C7: =ROUND(E6*B7,0) -> 98 | D7: 0 | E7: =E6+C7+D7 -> 1343 | F7: =E7 -> 1343 | T7: 55.14 | V7: 6.84 | X7: 12.14 | AC7: 0.75 | AD7: =ROUND(AC7*E7,0) -> 1007 | AE7: 0.75 | AF7: =ROUND(AE7*F7,0) -> 1007 | AG7: 0.75 | AH7: =ROUND(AG7*T7,0) -> 41 | AM7: =1-AC7 -> 0.25 | AO7: =ROUND(T7*AG7,0) -> 41 | AS7: =INDEX($A$2:$AZ$100,MATCH($A7-1,$A$2:$A$100,0),30) -> 921 | AT7: =INDEX($A$2:$AZ$100,MATCH($A7-1,$A$2:$A$100,0),5) -> 1245
A8: 1979 | B8: 0.09422 | C8: =ROUND(E7*B8,0) -> 127 | D8: 0 | E8: =E7+C8+D8 -> 1470 | F8: =E8 -> 1470 | T8: 55.18 | V8: 11.05 | X8: 13.61 | AC8: 0.76 | AD8: =ROUND(AC8*E8,0) -> 1117 | AE8: 0.76 | AF8: =ROUND(AE8*F8,0) -> 1117 | AG8: 0.76 | AH8: =ROUND(AG8*T8,0) -> 42 | AM8: =1-AC8 -> 0.24 | AO8: =ROUND(T8*AG8,0) -> 42 | AS8: =INDEX($A$2:$AZ$100,MATCH($A8-1,$A$2:$A$100,0),30) -> 1007 | AT8: =INDEX($A$2:$AZ$100,MATCH($A8-1,$A$2:$A$100,0),5) -> 1343
A9: 1980 | B9: 0.09484 | C9: =ROUND(E8*B9,0) -> 139 | D9: 0 | E9: =E8+C9+D9 -> 1609 | F9: =E9 -> 1609 | T9: 74.37 | V9: 12.76 | X9: 15.32 | AC9: 0.77 | AD9: =ROUND(AC9*E9,0) -> 1239 | AE9: 0.77 | AF9: =ROUND(AE9*F9,0) -> 1239 | AG9: 0.77 | AH9: =ROUND(AG9*T9,0) -> 57 | AM9: =1-AC9 -> 0.23 | AO9: =ROUND(T9*AG9,0) -> 57 | AS9: =INDEX($A$2:$AZ$100,MATCH($A9-1,$A$2:$A$100,0),30) -> 1117 | AT9: =INDEX($A$2:$AZ$100,MATCH($A9-1,$A$2:$A$100,0),5) -> 1470
A10: 1981 | B10: 0.13592 | C10: =ROUND(E9*B10,0) -> 219 | D10: 20 | E10: =E9+C10+D10 -> 1848 | F10: =E10 -> 1848 | T10: 88.07 | V10: 14.86 | X10: 18.03 | AC10: 0.77 | AD10: =ROUND(AC10*E10,0) -> 1423 | AE10: 0.77 | AF10: =ROUND(AE10*F10,0) -> 1423 | AG10: 0.77 | AH10: =ROUND(AG10*T10,0) -> 68 | AM10: =1-AC10 -> 0.23 | AO10: =ROUND(T10*AG10,0) -> 68 | AS10: =INDEX($A$2:$AZ$100,MATCH($A10-1,$A$2:$A$100,0),30) -> 1239 | AT10: =INDEX($A$2:$AZ$100,MATCH($A10-1,$A$2:$A$100,0),5) -> 1609
A11: 1982 | B11: 0.05 | C11: =ROUND(E10*B11,0) -> 92 | D11: 0 | E11: =E10+C11+D11 -> 1940 | F11: =E11 -> 1940 | T11: 88.07 | V11: 16 | X11: 18.5 | AC11: 0.77 | AD11: =ROUND(AC11*E11,0) -> 1494 | AE11: 0.77 | AF11: =ROUND(AE11*F11,0) -> 1494 | AG11: 0.77 | AH11: =ROUND(AG11*T11,0) -> 68 | AM11: =1-AC11 -> 0.23 | AO11: =ROUND(T11*AG11,0) -> 68 | AS11: =INDEX($A$2:$AZ$100,MATCH($A11-1,$A$2:$A$100,0),30) -> 1423 | AT11: =INDEX($A$2:$AZ$100,MATCH($A11-1,$A$2:$A$100,0),5) -> 1848
A12: 1983 | B12: 0.07 | C12: =ROUND(E11*B12,0) -> 136 | D12: 13 | E12: =E11+C12+D12 -> 2089 | F12: =E12 -> 2089 | S12: =ROUND(T11*$B12,2) -> 6.16 | T12: =S12+T11 -> 94.23 | V12: 17.12 | X12: 19.8 | AC12: 0.77 | AD12: =ROUND(AC12*E12,0) -> 1609 | AE12: 0.77 | AF12: =ROUND(AE12*F12,0) -> 1609 | AG12: 0.77 | AH12: =ROUND(AG12*T12,0) -> 73 | AM12: =1-AC12 -> 0.23 | AO12: =ROUND(T12*AG12,0) -> 73 | AS12: =INDEX($A$2:$AZ$100,MATCH($A12-1,$A$2:$A$100,0),30) -> 1494 | AT12: =INDEX($A$2:$AZ$100,MATCH($A12-1,$A$2:$A$100,0),5) -> 1940
A13: 1984 | B13: 0.06103 | C13: =ROUND(E12*B13,0) -> 127 | D13: 8 | E13: =E12+C13+D13 -> 2224 | F13: =E13 -> 2224 | S13: =ROUND(T12*$B13,2) -> 5.75 | T13: =S13+T12 -> 99.98 | V13: 18.16 | X13: 21.01 | AC13: 0.78 | AD13: =ROUND(AC13*E13,0) -> 1735 | AE13: 0.78 | AF13: =ROUND(AE13*F13,0) -> 1735 | AG13: 0.78 | AH13: =ROUND(AG13*T13,0) -> 78 | AJ13: 5.4 | AK13: 200 | AM13: =1-AC13 -> 0.22 | AO13: =ROUND(T13*AG13,0) -> 78 | AS13: =INDEX($A$2:$AZ$100,MATCH($A13-1,$A$2:$A$100,0),30) -> 1609 | AT13: =INDEX($A$2:$AZ$100,MATCH($A13-1,$A$2:$A$100,0),5) -> 2089
A14: 1985 | B14: 0.0254 | C14: =ROUND(E13*B14,0) -> 56 | D14: 8 | E14: =E13+C14+D14 -> 2288 | F14: =E14 -> 2288 | S14: =ROUND(T13*$B14,2) -> 2.54 | T14: =S14+T13 -> 102.52 | V14: 18.62 | X14: 21.54 | AC14: 0.79 | AD14: =ROUND(AC14*E14,0) -> 1808 | AE14: 0.79 | AF14: =ROUND(AE14*F14,0) -> 1808 | AG14: 0.79 | AH14: =ROUND(AG14*T14,0) -> 81 | AJ14: 5.4 | AK14: 200 | AM14: =1-AC14 -> 0.21 | AO14: =ROUND(T14*AG14,0) -> 81 | AS14: =INDEX($A$2:$AZ$100,MATCH($A14-1,$A$2:$A$100,0),30) -> 1735 | AT14: =INDEX($A$2:$AZ$100,MATCH($A14-1,$A$2:$A$100,0),5) -> 2224
A15: 1986 | B15: 0.05325 | C15: =ROUND(E14*B15,0) -> 122 | D15: 0 | E15: =E14+C15+D15 -> 2410 | F15: =E15 -> 2410 | S15: =ROUND(T14*$B15,2) -> 5.46 | T15: =S15+T14 -> 107.98 | V15: 19.61 | X15: 22.69 | AC15: 0.8 | AD15: =ROUND(AC15*E15,0) -> 1928 | AE15: 0.8 | AF15: =ROUND(AE15*F15,0) -> 1928 | AG15: 0.8 | AH15: =ROUND(AG15*T15,0) -> 86 | AJ15: 5.4 | AK15: 200 | AM15: =1-AC15 -> 0.2 | AO15: =ROUND(T15*AG15,0) -> 86 | AS15: =INDEX($A$2:$AZ$100,MATCH($A15-1,$A$2:$A$100,0),30) -> 1808 | AT15: =INDEX($A$2:$AZ$100,MATCH($A15-1,$A$2:$A$100,0),5) -> 2288
A16: 1987 | B16: 0.03843 | C16: =ROUND(E15*B16,0) -> 93 | D16: 0 | E16: =E15+C16+D16 -> 2503 | F16: =E16 -> 2503 | S16: =ROUND(T15*$B16,2) -> 4.15 | T16: =S16+T15 -> 112.13 | V16: 21.37 | X16: 23.56 | AC16: 0.8 | AD16: =ROUND(AC16*E16,0) -> 2002 | AE16: 0.8 | AF16: =ROUND(AE16*F16,0) -> 2002 | AG16: 0.8 | AH16: =ROUND(AG16*T16,0) -> 90 | AJ16: 5.4 | AK16: 200 | AM16: =1-AC16 -> 0.2 | AO16: =ROUND(T16*AG16,0) -> 90 | AS16: =INDEX($A$2:$AZ$100,MATCH($A16-1,$A$2:$A$100,0),30) -> 1928 | AT16: =INDEX($A$2:$AZ$100,MATCH($A16-1,$A$2:$A$100,0),5) -> 2410
A17: 1988 | B17: 0.03469 | C17: =ROUND(E16*B17,0) -> 87 | D17: 0 | E17: =E16+C17+D17 -> 2590 | F17: =E17 -> 2590 | S17: =ROUND(T16*$B17,2) -> 3.89 | T17: =S17+T16 -> 116.02 | V17: 22.11 | X17: 24.38 | AC17: 0.815 | AD17: =ROUND(AC17*E17,0) -> 2111 | AE17: 0.815 | AF17: =ROUND(AE17*F17,0) -> 2111 | AG17: 0.815 | AH17: =ROUND(AG17*T17,0) -> 95 | AJ17: 5.4 | AK17: 200 | AM17: =1-AC17 -> 0.185 | AO17: =ROUND(T17*AG17,0) -> 95 | AS17: =INDEX($A$2:$AZ$100,MATCH($A17-1,$A$2:$A$100,0),30) -> 2002 | AT17: =INDEX($A$2:$AZ$100,MATCH($A17-1,$A$2:$A$100,0),5) -> 2503
A18: 1989 | B18: 0.03592 | C18: =ROUND(E17*B18,0) -> 93 | D18: 0 | E18: =E17+C18+D18 -> 2683 | F18: =E18 -> 2683 | S18: =ROUND(T17*$B18,2) -> 4.17 | T18: =S18+T17 -> 120.19 | V18: 22.9 | X18: 25.26 | AC18: 0.82 | AD18: =ROUND(AC18*E18,0) -> 2200 | AE18: 0.82 | AF18: =ROUND(AE18*F18,0) -> 2200 | AG18: 0.82 | AH18: =ROUND(AG18*T18,0) -> 99 | AJ18: 5.4 | AK18: 200 | AM18: =1-AC18 -> 0.18 | AO18: =ROUND(T18*AG18,0) -> 99 | AS18: =INDEX($A$2:$AZ$100,MATCH($A18-1,$A$2:$A$100,0),30) -> 2111 | AT18: =INDEX($A$2:$AZ$100,MATCH($A18-1,$A$2:$A$100,0),5) -> 2590
A19: 1990 | B19: 0.03534 | C19: =ROUND(E18*B19,0) -> 95 | D19: 0 | E19: =E18+C19+D19 -> 2778 | F19: =E19 -> 2778 | S19: =ROUND(T18*$B19,2) -> 4.25 | T19: =S19+T18 -> 124.44 | V19: 22.9 | X19: 25.26 | AC19: 0.825 | AD19: =ROUND(AC19*E19,0) -> 2292 | AE19: 0.825 | AF19: =ROUND(AE19*F19,0) -> 2292 | AG19: 0.825 | AH19: =ROUND(AG19*T19,0) -> 103 | AJ19: 5.4 | AK19: 200 | AM19: =1-AC19 -> 0.175 | AO19: =ROUND(T19*AG19,0) -> 103 | AS19: =INDEX($A$2:$AZ$100,MATCH($A19-1,$A$2:$A$100,0),30) -> 2200 | AT19: =INDEX($A$2:$AZ$100,MATCH($A19-1,$A$2:$A$100,0),5) -> 2683
A20: 1991 | B20: 0.07182 | C20: =ROUND(E19*B20,0) -> 200 | D20: 0 | E20: =E19+C20+D20 -> 2978 | F20: =E20 -> 2978 | S20: =ROUND(T19*$B20,2) -> 8.94 | T20: =S20+T19 -> 133.38 | V20: 25.41 | X20: 28.03 | AC20: 0.83 | AD20: =ROUND(AC20*E20,0) -> 2472 | AE20: 0.83 | AF20: =ROUND(AE20*F20,0) -> 2472 | AG20: 0.83 | AH20: =ROUND(AG20*T20,0) -> 111 | AJ20: 5.4 | AK20: 200 | AM20: =1-AC20 -> 0.17 | AO20: =ROUND(T20*AG20,0) -> 111 | AS20: =INDEX($A$2:$AZ$100,MATCH($A20-1,$A$2:$A$100,0),30) -> 2292 | AT20: =INDEX($A$2:$AZ$100,MATCH($A20-1,$A$2:$A$100,0),5) -> 2778
A21: 1992 | B21: 0.0434 | C21: =ROUND(E20*B21,0) -> 129 | D21: 96 | E21: =E20+C21+D21 -> 3203 | F21: =E21 -> 3203 | S21: =ROUND(T20*$B21,2) -> 5.79 | T21: 141.97 | V21: 26.48 | X21: 29.21 | AC21: 0.83 | AD21: =ROUND(AC21*E21,0) -> 2658 | AE21: 0.83 | AF21: =ROUND(AE21*F21,0) -> 2658 | AG21: 0.83 | AH21: =ROUND(AG21*T21,0) -> 118 | AJ21: 5.4 | AK21: 300 | AM21: =1-AC21 -> 0.17 | AO21: =ROUND(T21*AG21,0) -> 118 | AS21: =INDEX($A$2:$AZ$100,MATCH($A21-1,$A$2:$A$100,0),30) -> 2472 | AT21: =INDEX($A$2:$AZ$100,MATCH($A21-1,$A$2:$A$100,0),5) -> 2978
A22: 1993 | B22: 0.04151 | C22: =ROUND(E21*B22,0) -> 133 | D22: 0 | E22: =E21+C22+D22 -> 3336 | F22: =E22 -> 3336 | S22: =ROUND(T21*$B22,2) -> 5.89 | T22: =S22+T21 -> 147.86 | U22: =ROUND(V21*$B22,2) -> 1.1 | V22: =U22+V21 -> 27.58 | W22: =ROUND(X21*$B22,2) -> 1.21 | X22: =W22+X21 -> 30.42 | AC22: 0.83 | AD22: =ROUND(AC22*E22,0) -> 2769 | AE22: 0.79 | AF22: =ROUND(AE22*F22,0) -> 2635 | AG22: 0.79 | AH22: =ROUND(AG22*T22,0) -> 117 | AJ22: 5.4 | AK22: 300 | AM22: =1-AC22 -> 0.17 | AO22: =ROUND(T22*AG22,0) -> 117 | AS22: =INDEX($A$2:$AZ$100,MATCH($A22-1,$A$2:$A$100,0),30) -> 2658 | AT22: =INDEX($A$2:$AZ$100,MATCH($A22-1,$A$2:$A$100,0),5) -> 3203
A23: 1994 | B23: 0.021 | C23: =ROUND(E22*B23,0) -> 70 | D23: 0 | E23: =E22+C23+D23 -> 3406 | F23: =E23 -> 3406 | S23: =ROUND(T22*$B23,2) -> 3.11 | T23: =S23+T22 -> 150.97 | U23: =ROUND(V22*$B23,2) -> 0.58 | V23: =U23+V22 -> 28.16 | W23: =ROUND(X22*$B23,2) -> 0.64 | X23: =W23+X22 -> 31.06 | AC23: 0.83 | AD23: =ROUND(AC23*E23,0) -> 2827 | AE23: 0.79 | AF23: =ROUND(AE23*F23,0) -> 2691 | AG23: 0.79 | AH23: =ROUND(AG23*T23,0) -> 119 | AJ23: 5.4 | AK23: 300 | AM23: =1-AC23 -> 0.17 | AO23: =ROUND(T23*AG23,0) -> 119 | AS23: =INDEX($A$2:$AZ$100,MATCH($A23-1,$A$2:$A$100,0),30) -> 2769 | AT23: =INDEX($A$2:$AZ$100,MATCH($A23-1,$A$2:$A$100,0),5) -> 3336
A24: 1995 | B24: 0.0285 | C24: =ROUND(E23*B24,0) -> 97 | D24: 0 | E24: =E23+C24+D24 -> 3503 | F24: =E24 -> 3503 | S24: =ROUND(T23*$B24,2) -> 4.3 | T24: =S24+T23 -> 155.27 | U24: =ROUND(V23*$B24,2) -> 0.8 | V24: =U24+V23 -> 28.96 | W24: =ROUND(X23*$B24,2) -> 0.89 | X24: =W24+X23 -> 31.95 | AC24: 0.83 | AD24: =ROUND(AC24*E24,0) -> 2907 | AE24: 0.79 | AF24: =ROUND(AE24*F24,0) -> 2767 | AG24: 0.79 | AH24: =ROUND(AG24*T24,0) -> 123 | AJ24: 5.4 | AK24: 300 | AM24: =1-AC24 -> 0.17 | AO24: =ROUND(T24*AG24,0) -> 123 | AS24: =INDEX($A$2:$AZ$100,MATCH($A24-1,$A$2:$A$100,0),30) -> 2827 | AT24: =INDEX($A$2:$AZ$100,MATCH($A24-1,$A$2:$A$100,0),5) -> 3406
A25: 1996 | B25: 0.035 | C25: =ROUND(E24*B25,0) -> 123 | D25: 0 | E25: =E24+C25+D25 -> 3626 | F25: =E25 -> 3626 | S25: =ROUND(T24*$B25,2) -> 5.43 | T25: =S25+T24 -> 160.7 | U25: =ROUND(V24*$B25,2) -> 1.01 | V25: =U25+V24 -> 29.97 | W25: =ROUND(X24*$B25,2) -> 1.12 | X25: =W25+X24 -> 33.07 | AC25: 0.83 | AD25: =ROUND(AC25*E25,0) -> 3010 | AE25: 0.79 | AF25: =ROUND(AE25*F25,0) -> 2865 | AG25: 0.79 | AH25: =ROUND(AG25*T25,0) -> 127 | AI25: 1 | AJ25: 5.4 | AK25: 300 | AM25: =1-AC25 -> 0.17 | AO25: =ROUND(T25*AG25,0) -> 127 | AS25: =INDEX($A$2:$AZ$100,MATCH($A25-1,$A$2:$A$100,0),30) -> 2907 | AT25: =INDEX($A$2:$AZ$100,MATCH($A25-1,$A$2:$A$100,0),5) -> 3503
A26: 1997 | B26: 0.033 | C26: =ROUND(E25*B26,0) -> 120 | D26: 0 | E26: =E25+C26+D26 -> 3746 | F26: =E26 -> 3746 | S26: =ROUND(T25*$B26,2) -> 5.3 | T26: =S26+T25 -> 166 | U26: =ROUND(V25*$B26,2) -> 0.99 | V26: =U26+V25 -> 30.96 | W26: =ROUND(X25*$B26,2) -> 1.09 | X26: =W26+X25 -> 34.16 | AC26: 0.875 | AD26: =ROUND(AC26*E26,0) -> 3278 | AE26: 0.79 | AF26: =ROUND(AE26*F26,0) -> 2959 | AG26: 0.79 | AH26: =ROUND(AG26*T26,0) -> 131 | AI26: 1 | AJ26: 5.4 | AK26: 300 | AM26: =1-AC26 -> 0.125 | AO26: =ROUND(T26*AG26,0) -> 131 | AS26: =INDEX($A$2:$AZ$100,MATCH($A26-1,$A$2:$A$100,0),30) -> 3010 | AT26: =INDEX($A$2:$AZ$100,MATCH($A26-1,$A$2:$A$100,0),5) -> 3626
A27: 1998 | B27: 0.035 | C27: =ROUND(E26*B27,0) -> 131 | D27: 0 | E27: =E26+C27+D27 -> 3877 | F27: =E27 -> 3877 | S27: =ROUND(T26*$B27,2) -> 5.81 | T27: =S27+T26 -> 171.81 | U27: =ROUND(V26*$B27,2) -> 1.08 | V27: =U27+V26 -> 32.04 | W27: =ROUND(X26*$B27,2) -> 1.2 | X27: =W27+X26 -> 35.36 | AC27: 0.875 | AD27: =ROUND(AC27*E27,0) -> 3392 | AE27: 0.79 | AF27: =ROUND(AE27*F27,0) -> 3063 | AG27: 0.79 | AH27: =ROUND(AG27*T27,0) -> 136 | AI27: 1 | AJ27: 5.4 | AK27: 300 | AM27: =1-AC27 -> 0.125 | AO27: =ROUND(T27*AG27,0) -> 136 | AS27: =INDEX($A$2:$AZ$100,MATCH($A27-1,$A$2:$A$100,0),30) -> 3278 | AT27: =INDEX($A$2:$AZ$100,MATCH($A27-1,$A$2:$A$100,0),5) -> 3746
A28: 1999 | B28: 0.035 | C28: =ROUND(E27*B28,0) -> 136 | D28: 0 | E28: =E27+C28+D28 -> 4013 | F28: =E28 -> 4013 | S28: =ROUND(T27*$B28,2) -> 6.01 | T28: =S28+T27 -> 177.82 | U28: =ROUND(V27*$B28,2) -> 1.12 | V28: =U28+V27 -> 33.16 | W28: =ROUND(X27*$B28,2) -> 1.24 | X28: =W28+X27 -> 36.6 | AC28: 0.875 | AD28: =ROUND(AC28*E28,0) -> 3511 | AE28: 0.79 | AF28: =ROUND(AE28*F28,0) -> 3170 | AG28: 0.79 | AH28: =ROUND(AG28*T28,0) -> 140 | AI28: 1 | AJ28: 5.4 | AK28: 300 | AM28: =1-AC28 -> 0.125 | AO28: =ROUND(T28*AG28,0) -> 140 | AS28: =INDEX($A$2:$AZ$100,MATCH($A28-1,$A$2:$A$100,0),30) -> 3392 | AT28: =INDEX($A$2:$AZ$100,MATCH($A28-1,$A$2:$A$100,0),5) -> 3877
A29: 2000 | B29: 0.03 | C29: =ROUND(E28*B29,0) -> 120 | D29: 38 | E29: =E28+C29+D29 -> 4171 | F29: =E29 -> 4171 | S29: =ROUND(T28*$B29,2) -> 5.33 | T29: =S29+T28 -> 183.15 | U29: =ROUND(V28*$B29,2) -> 0.99 | V29: =U29+V28 -> 34.15 | W29: =ROUND(X28*$B29,2) -> 1.1 | X29: =W29+X28 -> 37.7 | AC29: 0.875 | AD29: =ROUND(AC29*E29,0) -> 3650 | AE29: 0.875 | AF29: =ROUND(AE29*F29,0) -> 3650 | AG29: 0.79 | AH29: =ROUND(AG29*T29,0) -> 145 | AI29: 1 | AJ29: 5.4 | AK29: 300 | AM29: =1-AC29 -> 0.125 | AO29: =ROUND(T29*AG29,0) -> 145 | AR29: =D29 -> 38 | AS29: =INDEX($A$2:$AZ$100,MATCH($A29-1,$A$2:$A$100,0),30) -> 3511 | AT29: =INDEX($A$2:$AZ$100,MATCH($A29-1,$A$2:$A$100,0),5) -> 4013
A30: 2001 | B30: 0.04 | C30: =ROUND(E29*B30,0) -> 167 | D30: 0 | E30: =E29+C30+D30 -> 4338 | F30: =E30 -> 4338 | S30: =ROUND(T29*$B30,2) -> 7.33 | T30: =S30+T29 -> 190.48 | U30: =ROUND(V29*$B30,2) -> 1.37 | V30: =U30+V29 -> 35.52 | W30: =ROUND(X29*$B30,2) -> 1.51 | X30: =W30+X29 -> 39.21 | AC30: 0.875 | AD30: =ROUND(AC30*E30,0) -> 3796 | AE30: 0.875 | AF30: =ROUND(AE30*F30,0) -> 3796 | AG30: 0.79 | AH30: =ROUND(AG30*T30,0) -> 150 | AI30: 1 | AJ30: 5.4 | AK30: 300 | AM30: =1-AC30 -> 0.125 | AO30: =ROUND(T30*AG30,0) -> 150 | AR30: =ROUND(AR29*(1+B30),0) -> 40 | AS30: =INDEX($A$2:$AZ$100,MATCH($A30-1,$A$2:$A$100,0),30) -> 3650 | AT30: =INDEX($A$2:$AZ$100,MATCH($A30-1,$A$2:$A$100,0),5) -> 4171
A31: 2002 | B31: 0.04 | C31: =ROUND(E30*B31,0) -> 174 | D31: 0 | E31: =E30+C31+D31 -> 4512 | F31: =E31 -> 4512 | S31: =ROUND(T30*$B31,2) -> 7.62 | T31: =S31+T30 -> 198.1 | U31: =ROUND(V30*$B31,2) -> 1.42 | V31: =U31+V30 -> 36.94 | W31: =ROUND(X30*$B31,2) -> 1.57 | X31: =W31+X30 -> 40.78 | AC31: 0.875 | AD31: =ROUND(AC31*E31,0) -> 3948 | AE31: 0.875 | AF31: =ROUND(AE31*F31,0) -> 3948 | AG31: 0.79 | AH31: =ROUND(AG31*T31,0) -> 156 | AI31: 1 | AJ31: 5.4 | AK31: 300 | AM31: =1-AC31 -> 0.125 | AO31: =ROUND(T31*AG31,0) -> 156 | AR31: =ROUND(AR30*(1+B31),0) -> 42 | AS31: =INDEX($A$2:$AZ$100,MATCH($A31-1,$A$2:$A$100,0),30) -> 3796 | AT31: =INDEX($A$2:$AZ$100,MATCH($A31-1,$A$2:$A$100,0),5) -> 4338
A32: 2003 | B32: 0.01 | C32: =ROUND(E31*B32,0) -> 45 | D32: 0 | E32: =E31+C32+D32 -> 4557 | F32: =E32 -> 4557 | S32: =ROUND(T31*$B32,2) -> 1.98 | T32: =S32+T31 -> 200.08 | U32: =ROUND(V31*$B32,2) -> 0.37 | V32: =U32+V31 -> 37.31 | W32: =ROUND(X31*$B32,2) -> 0.41 | X32: =W32+X31 -> 41.19 | AC32: 0.875 | AD32: =ROUND(AC32*E32,0) -> 3987 | AE32: 0.875 | AF32: =ROUND(AE32*F32,0) -> 3987 | AG32: 0.79 | AH32: =ROUND(AG32*T32,0) -> 158 | AI32: 1 | AJ32: 5.4 | AK32: 300 | AM32: =1-AC32 -> 0.125 | AO32: =ROUND(T32*AG32,0) -> 158 | AR32: =ROUND(AR31*(1+B32),0) -> 42 | AS32: =INDEX($A$2:$AZ$100,MATCH($A32-1,$A$2:$A$100,0),30) -> 3948 | AT32: =INDEX($A$2:$AZ$100,MATCH($A32-1,$A$2:$A$100,0),5) -> 4512
A33: 2004 | B33: 0.02 | C33: =ROUND(E32*B33,0) -> 91 | D33: 0 | E33: =E32+C33+D33 -> 4648 | F33: =E33 -> 4648 | S33: =ROUND(T32*$B33,2) -> 4 | T33: =S33+T32 -> 204.08 | U33: =ROUND(V32*$B33,2) -> 0.75 | V33: =U33+V32 -> 38.06 | W33: =ROUND(X32*$B33,2) -> 0.82 | X33: =W33+X32 -> 42.01 | AC33: 0.875 | AD33: =ROUND(AC33*E33,0) -> 4067 | AE33: 0.875 | AF33: =ROUND(AE33*F33,0) -> 4067 | AG33: 0.79 | AH33: =ROUND(AG33*T33,0) -> 161 | AI33: 1 | AJ33: 5.4 | AK33: 300 | AM33: =1-AC33 -> 0.125 | AO33: =ROUND(T33*AG33,0) -> 161 | AR33: =ROUND(AR32*(1+B33),0) -> 43 | AS33: =INDEX($A$2:$AZ$100,MATCH($A33-1,$A$2:$A$100,0),30) -> 3987 | AT33: =INDEX($A$2:$AZ$100,MATCH($A33-1,$A$2:$A$100,0),5) -> 4557
A34: 2005 | B34: 0.02 | C34: =ROUND(E33*B34,0) -> 93 | D34: 0 | E34: =E33+C34+D34 -> 4741 | F34: =E34 -> 4741 | S34: =ROUND(T33*$B34,2) -> 4.08 | T34: =S34+T33 -> 208.16 | U34: =ROUND(V33*$B34,2) -> 0.76 | V34: =U34+V33 -> 38.82 | W34: =ROUND(X33*$B34,2) -> 0.84 | X34: =W34+X33 -> 42.85 | AC34: 0.875 | AD34: =ROUND(AC34*E34,0) -> 4148 | AE34: 0.875 | AF34: =ROUND(AE34*F34,0) -> 4148 | AG34: 0.79 | AH34: =ROUND(AG34*T34,0) -> 164 | AI34: 1.01 | AJ34: 5.4 | AK34: 300 | AM34: =1-AC34 -> 0.125 | AO34: =ROUND(T34*AG34,0) -> 164 | AR34: =ROUND(AR33*(1+B34),0) -> 44 | AS34: =INDEX($A$2:$AZ$100,MATCH($A34-1,$A$2:$A$100,0),30) -> 4067 | AT34: =INDEX($A$2:$AZ$100,MATCH($A34-1,$A$2:$A$100,0),5) -> 4648
A35: 2006 | B35: 0.04 | C35: =ROUND(E34*B35,0) -> 190 | D35: 0 | E35: =E34+C35+D35 -> 4931 | F35: =E35 -> 4931 | S35: =ROUND(T34*$B35,2) -> 8.33 | T35: =S35+T34 -> 216.49 | U35: =ROUND(V34*$B35,2) -> 1.55 | V35: =U35+V34 -> 40.37 | W35: =ROUND(X34*$B35,2) -> 1.71 | X35: =W35+X34 -> 44.56 | AC35: 0.875 | AD35: =ROUND(AC35*E35,0) -> 4315 | AE35: 0.875 | AF35: =ROUND(AE35*F35,0) -> 4315 | AG35: 0.79 | AH35: =ROUND(AG35*T35,0) -> 171 | AI35: 1.01 | AJ35: 5.4 | AK35: 300 | AM35: =1-AC35 -> 0.125 | AO35: =ROUND(T35*AG35,0) -> 171 | AR35: =ROUND(AR34*(1+B35),0) -> 46 | AS35: =INDEX($A$2:$AZ$100,MATCH($A35-1,$A$2:$A$100,0),30) -> 4148 | AT35: =INDEX($A$2:$AZ$100,MATCH($A35-1,$A$2:$A$100,0),5) -> 4741
A36: 2007 | B36: 0.04 | C36: =ROUND(E35*B36,0) -> 197 | D36: 0 | E36: =E35+C36+D36 -> 5128 | F36: =E36 -> 5128 | S36: =ROUND(T35*$B36,2) -> 8.66 | T36: =S36+T35 -> 225.15 | U36: =ROUND(V35*$B36,2) -> 1.61 | V36: =U36+V35 -> 41.98 | W36: =ROUND(X35*$B36,2) -> 1.78 | X36: =W36+X35 -> 46.34 | AC36: 0.875 | AD36: =ROUND(AC36*E36,0) -> 4487 | AE36: 0.875 | AF36: =ROUND(AE36*F36,0) -> 4487 | AG36: 0.79 | AH36: =ROUND(AG36*T36,0) -> 178 | AI36: 1.01 | AJ36: 5.4 | AK36: 300 | AM36: =1-AC36 -> 0.125 | AN36: 4.72424 | AO36: =ROUND(T36*AG36,0) -> 178 | AR36: =ROUND(AR35*(1+B36),0) -> 48 | AS36: =INDEX($A$2:$AZ$100,MATCH($A36-1,$A$2:$A$100,0),30) -> 4315 | AT36: =INDEX($A$2:$AZ$100,MATCH($A36-1,$A$2:$A$100,0),5) -> 4931
A37: 2008 | B37: 0.04 | C37: =ROUND(E36*B37,0) -> 205 | D37: 0 | E37: =E36+C37+D37 -> 5333 | F37: =E37 -> 5333 | S37: =ROUND(T36*$B37,2) -> 9.01 | T37: =S37+T36 -> 234.16 | U37: =ROUND(V36*$B37,2) -> 1.68 | V37: =U37+V36 -> 43.66 | W37: =ROUND(X36*$B37,2) -> 1.85 | X37: =W37+X36 -> 48.19 | AC37: 0.875 | AD37: =ROUND(AC37*E37,0) -> 4666 | AE37: 0.875 | AF37: =ROUND(AE37*F37,0) -> 4666 | AG37: 0.79 | AH37: =ROUND(AG37*T37,0) -> 185 | AI37: 1.01 | AJ37: 5.4 | AK37: 300 | AM37: =1-AC37 -> 0.125 | AN37: 4.44454 | AO37: =ROUND(T37*AG37,0) -> 185 | AR37: =ROUND(AR36*(1+B37),0) -> 50 | AS37: =INDEX($A$2:$AZ$100,MATCH($A37-1,$A$2:$A$100,0),30) -> 4487 | AT37: =INDEX($A$2:$AZ$100,MATCH($A37-1,$A$2:$A$100,0),5) -> 5128
A38: 2009 | B38: 0.04 | C38: =ROUND(E37*B38,0) -> 213 | D38: 0 | E38: =E37+C38+D38 -> 5546 | F38: =E38 -> 5546 | S38: =ROUND(T37*$B38,2) -> 9.37 | T38: =S38+T37 -> 243.53 | U38: =ROUND(V37*$B38,2) -> 1.75 | V38: =U38+V37 -> 45.41 | W38: =ROUND(X37*$B38,2) -> 1.93 | X38: =W38+X37 -> 50.12 | AC38: 0.875 | AD38: =ROUND(AC38*E38,0) -> 4853 | AE38: 0.875 | AF38: =ROUND(AE38*F38,0) -> 4853 | AG38: 0.79 | AH38: =ROUND(AG38*T38,0) -> 192 | AI38: 1.01 | AJ38: 5.4 | AK38: 300 | AM38: =1-AC38 -> 0.125 | AN38: 4.14488 | AO38: =ROUND(T38*AG38,0) -> 192 | AR38: =ROUND(AR37*(1+B38),0) -> 52 | AS38: =INDEX($A$2:$AZ$100,MATCH($A38-1,$A$2:$A$100,0),30) -> 4666 | AT38: =INDEX($A$2:$AZ$100,MATCH($A38-1,$A$2:$A$100,0),5) -> 5333
A39: 2010 | B39: 0.04 | C39: =ROUND(E38*B39,0) -> 222 | D39: 0 | E39: =E38+C39+D39 -> 5768 | F39: =E39 -> 5768 | I39: 497.09 | L39: 56.29 | O39: 61.32 | S39: =ROUND(T38*$B39,2) -> 9.74 | T39: =S39+T38 -> 253.27 | U39: =ROUND(V38*$B39,2) -> 1.82 | V39: =U39+V38 -> 47.23 | W39: =ROUND(X38*$B39,2) -> 2 | X39: =W39+X38 -> 52.12 | Z39: 26.02 | AB39: 3.04 | AC39: 0.875 | AD39: =ROUND(AC39*E39,0) -> 5047 | AE39: 0.875 | AF39: =ROUND(AE39*F39,0) -> 5047 | AG39: 0.79 | AH39: =ROUND(AG39*T39,0) -> 200 | AI39: 1.01 | AJ39: 5.4 | AK39: 300 | AM39: =1-AC39 -> 0.125 | AN39: 3.92924 | AO39: =ROUND(T39*AG39,0) -> 200 | AR39: =ROUND(AR38*(1+B39),0) -> 54 | AS39: =INDEX($A$2:$AZ$100,MATCH($A39-1,$A$2:$A$100,0),30) -> 4853 | AT39: =INDEX($A$2:$AZ$100,MATCH($A39-1,$A$2:$A$100,0),5) -> 5546
A40: 2011 | B40: 0.02 | C40: =ROUND(E39*B40,0) -> 115 | D40: 0 | E40: =E39+C40+D40 -> 5883 | F40: =E40 -> 5883 | G40: =$B40 -> 0.02 | H40: =ROUND(I39*$G40,2) -> 9.94 | I40: =H40+I39 -> 507.03 | J40: =$B40 -> 0.02 | K40: =ROUND(L39*$J40,2) -> 1.13 | L40: =K40+L39 -> 57.42 | M40: =$B40 -> 0.02 | N40: =ROUND(O39*$M40,2) -> 1.23 | O40: =N40+O39 -> 62.55 | S40: =ROUND(T39*$B40,2) -> 5.07 | T40: =S40+T39 -> 258.34 | U40: =ROUND(V39*$B40,2) -> 0.94 | V40: =U40+V39 -> 48.17 | W40: =ROUND(X39*$B40,2) -> 1.04 | X40: =W40+X39 -> 53.16 | Y40: =ROUND(Z39*$B40,2) -> 0.52 | Z40: =Y40+Z39 -> 26.54 | AA40: =ROUND(AB39*$B40,2) -> 0.06 | AB40: =AA40+AB39 -> 3.1 | AC40: 0.875 | AD40: =ROUND(AC40*E40,0) -> 5148 | AE40: 0.875 | AF40: =ROUND(AE40*F40,0) -> 5148 | AG40: 0.79 | AH40: =ROUND(AG40*T40,0) -> 204 | AI40: 1.01 | AJ40: 5.4 | AK40: 300 | AM40: =1-AC40 -> 0.125 | AN40: 3.2606 | AO40: =ROUND(T40*AG40,0) -> 204 | AR40: =ROUND(AR39*(1+B40),0) -> 55 | AS40: =INDEX($A$2:$AZ$100,MATCH($A40-1,$A$2:$A$100,0),30) -> 5047 | AT40: =INDEX($A$2:$AZ$100,MATCH($A40-1,$A$2:$A$100,0),5) -> 5768
A41: 2012 | B41: 0 | C41: =ROUND(E40*B41,0) -> 0 | D41: 0 | E41: =E40+C41+D41 -> 5883 | F41: =E41 -> 5883 | G41: =$B41 -> 0 | H41: =ROUND(I40*$G41,2) -> 0 | I41: =H41+I40 -> 507.03 | J41: =$B41 -> 0 | K41: =ROUND(L40*$J41,2) -> 0 | L41: =K41+L40 -> 57.42 | M41: =$B41 -> 0 | N41: =ROUND(O40*$M41,2) -> 0 | O41: =N41+O40 -> 62.55 | S41: =ROUND(T40*$B41,2) -> 0 | T41: =S41+T40 -> 258.34 | U41: =ROUND(V40*$B41,2) -> 0 | V41: =U41+V40 -> 48.17 | W41: =ROUND(X40*$B41,2) -> 0 | X41: =W41+X40 -> 53.16 | Y41: =ROUND(Z40*$B41,2) -> 0 | Z41: =Y41+Z40 -> 26.54 | AA41: =ROUND(AB40*$B41,2) -> 0 | AB41: =AA41+AB40 -> 3.1 | AC41: 0.875 | AD41: =ROUND(AC41*E41,0) -> 5148 | AE41: 0.875 | AF41: =ROUND(AE41*F41,0) -> 5148 | AG41: 0.79 | AH41: =ROUND(AG41*T41,0) -> 204 | AI41: 1.01 | AJ41: 5.4 | AK41: 300 | AM41: =1-AC41 -> 0.125 | AN41: 3.51216 | AO41: =ROUND(T41*AG41,0) -> 204 | AR41: =ROUND(AR40*(1+B41),0) -> 55 | AS41: =INDEX($A$2:$AZ$100,MATCH($A41-1,$A$2:$A$100,0),30) -> 5148 | AT41: =INDEX($A$2:$AZ$100,MATCH($A41-1,$A$2:$A$100,0),5) -> 5883
A42: 2013 | B42: 0.02 | C42: =ROUND(E41*B42,0) -> 118 | D42: 0 | E42: =E41+C42+D42 -> 6001 | F42: =E42 -> 6001 | G42: =$B42 -> 0.02 | H42: =ROUND(I41*$G42,2) -> 10.14 | I42: =H42+I41 -> 517.17 | J42: =$B42 -> 0.02 | K42: =ROUND(L41*$J42,2) -> 1.15 | L42: =K42+L41 -> 58.57 | M42: =$B42 -> 0.02 | N42: =ROUND(O41*$M42,2) -> 1.25 | O42: =N42+O41 -> 63.8 | S42: =ROUND(T41*$B42,2) -> 5.17 | T42: =S42+T41 -> 263.51 | U42: =ROUND(V41*$B42,2) -> 0.96 | V42: =U42+V41 -> 49.13 | W42: =ROUND(X41*$B42,2) -> 1.06 | X42: =W42+X41 -> 54.22 | Y42: =ROUND(Z41*$B42,2) -> 0.53 | Z42: =Y42+Z41 -> 27.07 | AA42: =ROUND(AB41*$B42,2) -> 0.06 | AB42: =AA42+AB41 -> 3.16 | AC42: 0.875 | AD42: =ROUND(AC42*E42,0) -> 5251 | AE42: 0.875 | AF42: =ROUND(AE42*F42,0) -> 5251 | AG42: 0.79 | AH42: =ROUND(AG42*T42,0) -> 208 | AI42: 1.01 | AJ42: 5.4 | AK42: 300 | AM42: =1-AC42 -> 0.125 | AN42: 3.46875 | AO42: =ROUND(T42*AG42,0) -> 208 | AR42: =ROUND(AR41*(1+B42),0) -> 56 | AS42: =INDEX($A$2:$AZ$100,MATCH($A42-1,$A$2:$A$100,0),30) -> 5148 | AT42: =INDEX($A$2:$AZ$100,MATCH($A42-1,$A$2:$A$100,0),5) -> 5883
A43: 2014 | B43: 0.02 | C43: =ROUND(E42*B43,0) -> 120 | D43: 0 | E43: =E42+C43+D43 -> 6121 | F43: =E43 -> 6121 | G43: =$B43 -> 0.02 | H43: =ROUND(I42*$G43,2) -> 10.34 | I43: =H43+I42 -> 527.51 | J43: =$B43 -> 0.02 | K43: =ROUND(L42*$J43,2) -> 1.17 | L43: =K43+L42 -> 59.74 | M43: =$B43 -> 0.02 | N43: =ROUND(O42*$M43,2) -> 1.28 | O43: =N43+O42 -> 65.08 | S43: =ROUND(T42*$B43,2) -> 5.27 | T43: =S43+T42 -> 268.78 | U43: =ROUND(V42*$B43,2) -> 0.98 | V43: =U43+V42 -> 50.11 | W43: =ROUND(X42*$B43,2) -> 1.08 | X43: =W43+X42 -> 55.3 | Y43: =ROUND(Z42*$B43,2) -> 0.54 | Z43: =Y43+Z42 -> 27.61 | AA43: =ROUND(AB42*$B43,2) -> 0.06 | AB43: =AA43+AB42 -> 3.22 | AC43: 0.875 | AD43: =ROUND(AC43*E43,0) -> 5356 | AE43: 0.875 | AF43: =ROUND(AE43*F43,0) -> 5356 | AG43: 0.79 | AH43: =ROUND(AG43*T43,0) -> 212 | AI43: 1.01 | AJ43: 5.4 | AK43: 300 | AL43: 750 | AM43: =1-AC43 -> 0.125 | AN43: 3.34158 | AO43: =ROUND(T43*AG43,0) -> 212 | AP43: =E43-AD43-AL43 -> 15 | AR43: =ROUND(AR42*(1+B43),0) -> 57 | AS43: =INDEX($A$2:$AZ$100,MATCH($A43-1,$A$2:$A$100,0),30) -> 5251 | AT43: =INDEX($A$2:$AZ$100,MATCH($A43-1,$A$2:$A$100,0),5) -> 6001
A44: 2015 | B44: 0.04 | C44: =ROUND(E43*B44,0) -> 245 | D44: 0 | E44: =E43+C44+D44 -> 6366 | F44: =E44 -> 6366 | G44: =$B44 -> 0.04 | H44: =ROUND(I43*$G44,2) -> 21.1 | I44: =H44+I43 -> 548.61 | J44: =$B44 -> 0.04 | K44: =ROUND(L43*$J44,2) -> 2.39 | L44: =K44+L43 -> 62.13 | M44: =$B44 -> 0.04 | N44: =ROUND(O43*$M44,2) -> 2.6 | O44: =N44+O43 -> 67.68 | R44: 308.82 | S44: =ROUND(T43*$B44,2) -> 10.75 | T44: =S44+T43 -> 279.53 | U44: =ROUND(V43*$B44,2) -> 2 | V44: =U44+V43 -> 52.11 | W44: =ROUND(X43*$B44,2) -> 2.21 | X44: =W44+X43 -> 57.51 | Y44: =ROUND(Z43*$B44,2) -> 1.1 | Z44: =Y44+Z43 -> 28.71 | AA44: =ROUND(AB43*$B44,2) -> 0.13 | AB44: =AA44+AB43 -> 3.35 | AC44: 0.875 | AD44: =ROUND(AC44*E44,0) -> 5570 | AE44: 0.875 | AF44: =ROUND(AE44*F44,0) -> 5570 | AG44: 0.79 | AH44: =ROUND(AG44*T44,0) -> 221 | AI44: 1.01 | AJ44: 5.4 | AK44: 300 | AL44: 750 | AM44: =1-AC44 -> 0.125 | AN44: 3.38985 | AO44: =ROUND(T44*AG44,0) -> 221 | AP44: =E44-AD44-AL44 -> 46 | AR44: =ROUND(AR43*(1+B44),0) -> 59 | AS44: =INDEX($A$2:$AZ$100,MATCH($A44-1,$A$2:$A$100,0),30) -> 5356 | AT44: =INDEX($A$2:$AZ$100,MATCH($A44-1,$A$2:$A$100,0),5) -> 6121
A45: 2016 | B45: 0.0125 | C45: =ROUND(E44*B45,0) -> 80 | D45: 0 | E45: =E44+C45+D45 -> 6446 | F45: =E45 -> 6446 | G45: =$B45 -> 0.0125 | H45: =ROUND(I44*$G45,2) -> 6.86 | I45: =H45+I44 -> 555.47 | J45: =$B45 -> 0.0125 | K45: =ROUND(L44*$J45,2) -> 0.78 | L45: =K45+L44 -> 62.91 | M45: =$B45 -> 0.0125 | N45: =ROUND(O44*$M45,2) -> 0.85 | O45: =N45+O44 -> 68.53 | P45: =$B45 -> 0.0125 | Q45: =ROUND(R44*$P45,2) -> 3.86 | R45: =Q45+R44 -> 312.68 | S45: =ROUND(T44*$B45,2) -> 3.49 | T45: =S45+T44 -> 283.02 | U45: =ROUND(V44*$B45,2) -> 0.65 | V45: =U45+V44 -> 52.76 | W45: =ROUND(X44*$B45,2) -> 0.72 | X45: =W45+X44 -> 58.23 | Y45: =ROUND(Z44*$B45,2) -> 0.36 | Z45: =Y45+Z44 -> 29.07 | AA45: =ROUND(AB44*$B45,2) -> 0.04 | AB45: =AA45+AB44 -> 3.39 | AC45: 0.875 | AD45: =ROUND(AC45*E45,0) -> 5640 | AE45: 0.875 | AF45: =ROUND(AE45*F45,0) -> 5640 | AG45: 0.79 | AH45: =ROUND(AG45*T45,0) -> 224 | AI45: 1.01 | AJ45: 5.4 | AK45: 300 | AL45: 750 | AM45: =1-AC45 -> 0.125 | AN45: 3.4121 | AO45: =ROUND(T45*AG45,0) -> 224 | AP45: =E45-AD45-AL45 -> 56 | AR45: =ROUND(AR44*(1+B45),0) -> 60 | AS45: =INDEX($A$2:$AZ$100,MATCH($A45-1,$A$2:$A$100,0),30) -> 5570 | AT45: =INDEX($A$2:$AZ$100,MATCH($A45-1,$A$2:$A$100,0),5) -> 6366
A46: 2017 | B46: 0.0225 | C46: =ROUND(E45*B46,0) -> 145 | E46: =E45+C46+D46 -> 6591 | F46: =E46 -> 6591 | G46: =$B46 -> 0.0225 | H46: =ROUND(I45*$G46,2) -> 12.5 | I46: =H46+I45 -> 567.97 | J46: =$B46 -> 0.0225 | K46: =ROUND(L45*$J46,2) -> 1.42 | L46: =K46+L45 -> 64.33 | M46: =$B46 -> 0.0225 | N46: =ROUND(O45*$M46,2) -> 1.54 | O46: =N46+O45 -> 70.07 | P46: =$B46 -> 0.0225 | Q46: =ROUND(R45*$P46,2) -> 7.04 | R46: =Q46+R45 -> 319.72 | S46: =ROUND(T45*$B46,2) -> 6.37 | T46: =S46+T45 -> 289.39 | U46: =ROUND(V45*$B46,2) -> 1.19 | V46: =U46+V45 -> 53.95 | W46: =ROUND(X45*$B46,2) -> 1.31 | X46: =W46+X45 -> 59.54 | Y46: =ROUND(Z45*$B46,2) -> 0.65 | Z46: =Y46+Z45 -> 29.72 | AA46: =ROUND(AB45*$B46,2) -> 0.08 | AB46: =AA46+AB45 -> 3.47 | AC46: 0.875 | AD46: =ROUND(AC46*E46,0) -> 5767 | AE46: 0.875 | AF46: =ROUND(AE46*F46,0) -> 5767 | AG46: 0.79 | AH46: =ROUND(AG46*T46,0) -> 229 | AI46: =AI45 -> 1.01 | AJ46: 5.4 | AK46: 300 | AL46: 750 | AM46: =1-AC46 -> 0.125 | AN46: 3.24307 | AO46: =ROUND(T46*AG46,0) -> 229 | AP46: =E46-AD46-AL46 -> 74 | AQ46: 317587 | AR46: =ROUND(AR45*(1+B46),0) -> 61 | AS46: =INDEX($A$2:$AZ$100,MATCH($A46-1,$A$2:$A$100,0),30) -> 5640 | AT46: =INDEX($A$2:$AZ$100,MATCH($A46-1,$A$2:$A$100,0),5) -> 6446 | AV46: 0.25
A47: 2018 | B47: 0.0111 | C47: =ROUND(E46*B47,0) -> 73 | E47: =E46+C47+D47 -> 6664 | F47: =E47 -> 6664 | G47: =$B47 -> 0.0111 | H47: =ROUND(I46*$G47,2) -> 6.3 | I47: =H47+I46 -> 574.27 | J47: =$B47 -> 0.0111 | K47: =ROUND(L46*$J47,2) -> 0.71 | L47: =K47+L46 -> 65.04 | M47: =$B47 -> 0.0111 | N47: =ROUND(O46*$M47,2) -> 0.78 | O47: =N47+O46 -> 70.85 | P47: =$B47 -> 0.0111 | Q47: =ROUND(R46*$P47,2) -> 3.55 | R47: =Q47+R46 -> 323.27 | S47: =ROUND(T46*$B47,2) -> 3.21 | T47: =S47+T46 -> 292.6 | U47: =ROUND(V46*$B47,2) -> 0.6 | V47: =U47+V46 -> 54.55 | W47: =ROUND(X46*$B47,2) -> 0.66 | X47: =W47+X46 -> 60.2 | Y47: =ROUND(Z46*$B47,2) -> 0.33 | Z47: =Y47+Z46 -> 30.05 | AA47: =ROUND(AB46*$B47,2) -> 0.04 | AB47: =AA47+AB46 -> 3.51 | AC47: 0.875 | AD47: =ROUND(AC47*E47,0) -> 5831 | AE47: 0.875 | AF47: =ROUND(AE47*F47,0) -> 5831 | AG47: 0.79 | AH47: =ROUND(AG47*T47,0) -> 231 | AI47: =AI46 -> 1.01 | AJ47: 5.4 | AK47: 300 | AL47: 750 | AM47: =1-AC47 -> 0.125 | AN47: 3.16389 | AO47: =ROUND(T47*AG47,0) -> 231 | AP47: =E47-AD47-AL47 -> 83 | AQ47: =ROUND(159714313837/485147.3,0) -> 329208 | AR47: =ROUND(AR46*(1+B47),0) -> 62 | AS47: =INDEX($A$2:$AZ$100,MATCH($A47-1,$A$2:$A$100,0),30) -> 5767 | AT47: =INDEX($A$2:$AZ$100,MATCH($A47-1,$A$2:$A$100,0),5) -> 6591 | AU47: 0 | AV47: 0.25 | AW47: 0
A48: 2019 | B48: 0.01 | C48: =ROUND(E47*B48,0) -> 67 | D48: 5 | E48: =E47+C48+D48 -> 6736 | F48: =E48 -> 6736 | G48: 0.01 | H48: =ROUND(I47*$G48,2) -> 5.74 | I48: =H48+I47 -> 580.01 | J48: 0.01 | K48: =ROUND(L47*$J48,2) -> 0.65 | L48: =K48+L47 -> 65.69 | M48: 0.01 | N48: =ROUND(O47*$M48,2) -> 0.71 | O48: =N48+O47 -> 71.56 | P48: 0.01 | Q48: =ROUND(R47*$P48,2) -> 3.23 | R48: =Q48+R47 -> 326.5 | S48: =ROUND(T47*$B48,2) -> 2.93 | T48: =S48+T47 -> 295.53 | U48: =ROUND(V47*$B48,2) -> 0.55 | V48: =U48+V47 -> 55.1 | W48: =ROUND(X47*$B48,2) -> 0.6 | X48: =W48+X47 -> 60.8 | Y48: =ROUND(Z47*$B48,2) -> 0.3 | Z48: =Y48+Z47 -> 30.35 | AA48: =ROUND(AB47*$B48,2) -> 0.04 | AB48: =AA48+AB47 -> 3.55 | AC48: 0.875 | AD48: =ROUND(AC48*E48,0) -> 5894 | AE48: 0.875 | AF48: =ROUND(AE48*F48,0) -> 5894 | AG48: 0.79 | AH48: =ROUND(AG48*T48,0) -> 233 | AI48: =AI47 -> 1.01 | AJ48: 5.4 | AK48: 300 | AL48: 750 | AM48: =1-AC48 -> 0.125 | AN48: 3.03936 | AO48: =ROUND(T48*AG48,0) -> 233 | AP48: =E48-AD48-AL48 -> 92 | AQ48: 345229 | AR48: =ROUND(AR47*(1+B48),0) -> 63 | AS48: =INDEX($A$2:$AZ$100,MATCH($A48-1,$A$2:$A$100,0),30) -> 5831 | AT48: =INDEX($A$2:$AZ$100,MATCH($A48-1,$A$2:$A$100,0),5) -> 6664 | AU48: 0 | AV48: 0.25 | AW48: 0
A49: 2020 | B49: 0.0206 | C49: =ROUND(E48*B49,0) -> 139 | D49: 5 | E49: =E48+C49+D49 -> 6880 | F49: =E49 -> 6880 | G49: =B49 -> 0.0206 | H49: =ROUND(I48*$G49,2) -> 11.95 | I49: =H49+I48 -> 591.96 | J49: =B49 -> 0.0206 | K49: =ROUND(L48*$J49,2) -> 1.35 | L49: =K49+L48 -> 67.04 | M49: =B49 -> 0.0206 | N49: =ROUND(O48*$M49,2) -> 1.47 | O49: =N49+O48 -> 73.03 | P49: =B49 -> 0.0206 | Q49: =ROUND(R48*$P49,2) -> 6.73 | R49: =Q49+R48 -> 333.23 | S49: =ROUND(T48*$B49,2) -> 6.09 | T49: =S49+T48 -> 301.62 | U49: =ROUND(V48*$B49,2) -> 1.14 | V49: =U49+V48 -> 56.24 | W49: =ROUND(X48*$B49,2) -> 1.25 | X49: =W49+X48 -> 62.05 | Y49: =ROUND(Z48*$B49,2) -> 0.63 | Z49: =Y49+Z48 -> 30.98 | AA49: =ROUND(AB48*$B49,2) -> 0.07 | AB49: =AA49+AB48 -> 3.62 | AC49: 0.875 | AD49: =ROUND(AC49*E49,0) -> 6020 | AE49: 0.875 | AF49: =ROUND(AE49*F49,0) -> 6020 | AG49: 0.79 | AH49: =ROUND(AG49*T49,0) -> 238 | AI49: =AI48 -> 1.01 | AJ49: 5.4 | AK49: 300 | AL49: 750 | AM49: =1-AC49 -> 0.125 | AN49: 0 | AO49: =ROUND(T49*AG49,0) -> 238 | AP49: =E49-AD49-AL49 -> 110 | AQ49: 0 | AR49: =ROUND(AR48*(1+B49),0) -> 64 | AS49: =INDEX($A$2:$AZ$100,MATCH($A49-1,$A$2:$A$100,0),30) -> 5894 | AT49: =INDEX($A$2:$AZ$100,MATCH($A49-1,$A$2:$A$100,0),5) -> 6736 | AU49: 0 | AV49: 0.25 | AW49: 0
A50: 2021 | B50: 0.023 | C50: =ROUND(E49*B50,0) -> 158 | D50: 10 | E50: =E49+C50+D50 -> 7048 | F50: =E50 -> 7048 | G50: =B50 -> 0.023 | H50: =ROUND(I49*$G50,2) -> 13.62 | I50: =H50+I49 -> 605.58 | J50: =B50 -> 0.023 | K50: =ROUND(L49*$J50,2) -> 1.54 | L50: =K50+L49 -> 68.58 | M50: =B50 -> 0.023 | N50: =ROUND(O49*$M50,2) -> 1.68 | O50: =N50+O49 -> 74.71 | P50: =B50 -> 0.023 | Q50: =ROUND(R49*$P50,2) -> 7.66 | R50: =Q50+R49 -> 340.89 | S50: =ROUND(T49*$B50,2) -> 6.94 | T50: =S50+T49 -> 308.56 | U50: =ROUND(V49*$B50,2) -> 1.29 | V50: =U50+V49 -> 57.53 | W50: =ROUND(X49*$B50,2) -> 1.43 | X50: =W50+X49 -> 63.48 | Y50: =ROUND(Z49*$B50,2) -> 0.71 | Z50: =Y50+Z49 -> 31.69 | AA50: =ROUND(AB49*$B50,2) -> 0.08 | AB50: =AA50+AB49 -> 3.7 | AC50: 0.875 | AD50: =ROUND(AC50*E50,0) -> 6167 | AE50: 0.875 | AF50: =ROUND(AE50*F50,0) -> 6167 | AG50: 0.79 | AH50: =ROUND(AG50*T50,0) -> 244 | AI50: =AI49 -> 1.01 | AJ50: 5.4 | AK50: 300 | AL50: 750 | AM50: =1-AC50 -> 0.125 | AO50: =ROUND(T50*AG50,0) -> 244 | AP50: =E50-AD50-AL50 -> 131 | AR50: =ROUND(AR49*(1+B50),0) -> 65 | AS50: =INDEX($A$2:$AZ$100,MATCH($A50-1,$A$2:$A$100,0),30) -> 6020 | AT50: =INDEX($A$2:$AZ$100,MATCH($A50-1,$A$2:$A$100,0),5) -> 6880
A51: 2022 | B51: 0.024 | C51: =ROUND(E50*B51,0) -> 169 | D51: 10 | E51: =E50+C51+D51 -> 7227 | F51: =E51 -> 7227 | G51: =B51 -> 0.024 | H51: =ROUND(I50*$G51,2) -> 14.53 | I51: =H51+I50 -> 620.11 | J51: =B51 -> 0.024 | K51: =ROUND(L50*$J51,2) -> 1.65 | L51: =K51+L50 -> 70.23 | M51: =B51 -> 0.024 | N51: =ROUND(O50*$M51,2) -> 1.79 | O51: =N51+O50 -> 76.5 | P51: =B51 -> 0.024 | Q51: =ROUND(R50*$P51,2) -> 8.18 | R51: =Q51+R50 -> 349.07 | S51: =ROUND(T50*$B51,2) -> 7.41 | T51: =S51+T50 -> 315.97 | U51: =ROUND(V50*$B51,2) -> 1.38 | V51: =U51+V50 -> 58.91 | W51: =ROUND(X50*$B51,2) -> 1.52 | X51: =W51+X50 -> 65 | Y51: =ROUND(Z50*$B51,2) -> 0.76 | Z51: =Y51+Z50 -> 32.45 | AA51: =ROUND(AB50*$B51,2) -> 0.09 | AB51: =AA51+AB50 -> 3.79 | AC51: 0.875 | AD51: =ROUND(AC51*E51,0) -> 6324 | AE51: 0.875 | AF51: =ROUND(AE51*F51,0) -> 6324 | AG51: 0.79 | AH51: =ROUND(AG51*T51,0) -> 250 | AI51: =AI50 -> 1.01 | AJ51: 5.4 | AK51: 300 | AL51: 750 | AM51: =1-AC51 -> 0.125 | AO51: =ROUND(T51*AG51,0) -> 250 | AP51: =E51-AD51-AL51 -> 153 | AR51: =ROUND(AR50*(1+B51),0) -> 67 | AS51: =INDEX($A$2:$AZ$100,MATCH($A51-1,$A$2:$A$100,0),30) -> 6167 | AT51: =INDEX($A$2:$AZ$100,MATCH($A51-1,$A$2:$A$100,0),5) -> 7048
A52: 2023 | B52: 0.025 | C52: =ROUND(E51*B52,0) -> 181 | D52: 5 | E52: =E51+C52+D52 -> 7413 | F52: =E52 -> 7413 | G52: =B52 -> 0.025 | H52: =ROUND(I51*$G52,2) -> 15.5 | I52: =H52+I51 -> 635.61 | J52: =B52 -> 0.025 | K52: =ROUND(L51*$J52,2) -> 1.76 | L52: =K52+L51 -> 71.99 | M52: =B52 -> 0.025 | N52: =ROUND(O51*$M52,2) -> 1.91 | O52: =N52+O51 -> 78.41 | P52: =B52 -> 0.025 | Q52: =ROUND(R51*$P52,2) -> 8.73 | R52: =Q52+R51 -> 357.8 | S52: =ROUND(T51*$B52,2) -> 7.9 | T52: =S52+T51 -> 323.87 | U52: =ROUND(V51*$B52,2) -> 1.47 | V52: =U52+V51 -> 60.38 | W52: =ROUND(X51*$B52,2) -> 1.63 | X52: =W52+X51 -> 66.63 | Y52: =ROUND(Z51*$B52,2) -> 0.81 | Z52: =Y52+Z51 -> 33.26 | AA52: =ROUND(AB51*$B52,2) -> 0.09 | AB52: =AA52+AB51 -> 3.88 | AC52: 0.884 | AD52: =ROUND(AC52*E52,0) -> 6553 | AE52: =AC52 -> 0.884 | AF52: =ROUND(AE52*F52,0) -> 6553 | AG52: 0.79 | AH52: =ROUND(AG52*T52,0) -> 256 | AI52: =AI51 -> 1.01 | AJ52: 5.4 | AK52: 300 | AL52: =E52-AD52-$AP51 -> 707 | AM52: =1-AC52 -> 0.116 | AO52: =ROUND(T52*AG52,0) -> 256 | AP52: =E52-AD52-AL52 -> 153 | AR52: =ROUND(AR51*(1+B52),0) -> 69 | AS52: =INDEX($A$2:$AZ$100,MATCH($A52-1,$A$2:$A$100,0),30) -> 6324 | AT52: =INDEX($A$2:$AZ$100,MATCH($A52-1,$A$2:$A$100,0),5) -> 7227
A53: 2024 | B53: 0.03 | C53: =ROUND(E52*B53,0) -> 222 | E53: =E52+C53+D53 -> 7635 | F53: =E53 -> 7635 | G53: =B53 -> 0.03 | H53: =ROUND(I52*$G53,2) -> 19.07 | I53: =H53+I52 -> 654.68 | J53: =B53 -> 0.03 | K53: =ROUND(L52*$J53,2) -> 2.16 | L53: =K53+L52 -> 74.15 | M53: =B53 -> 0.03 | N53: =ROUND(O52*$M53,2) -> 2.35 | O53: =N53+O52 -> 80.76 | P53: =B53 -> 0.03 | Q53: =ROUND(R52*$P53,2) -> 10.73 | R53: =Q53+R52 -> 368.53 | S53: =ROUND(T52*$B53,2) -> 9.72 | T53: =S53+T52 -> 333.59 | U53: =ROUND(V52*$B53,2) -> 1.81 | V53: =U53+V52 -> 62.19 | W53: =ROUND(X52*$B53,2) -> 2 | X53: =W53+X52 -> 68.63 | Y53: =ROUND(Z52*$B53,2) -> 1 | Z53: =Y53+Z52 -> 34.26 | AA53: =ROUND(AB52*$B53,2) -> 0.12 | AB53: =AA53+AB52 -> 4 | AC53: 0.884 | AD53: =ROUND(AC53*E53,0) -> 6749 | AE53: =AC53 -> 0.884 | AF53: =ROUND(AE53*F53,0) -> 6749 | AG53: 0.79 | AH53: =ROUND(AG53*T53,0) -> 264 | AI53: =AI52 -> 1.01 | AJ53: 5.4 | AK53: 300 | AL53: =E53-AD53-$AP52 -> 733 | AM53: =1-AC53 -> 0.116 | AO53: =ROUND(T53*AG53,0) -> 264 | AP53: =E53-AD53-AL53 -> 153 | AR53: =ROUND(AR52*(1+B53),0) -> 71 | AS53: =INDEX($A$2:$AZ$100,MATCH($A53-1,$A$2:$A$100,0),30) -> 6553 | AT53: =INDEX($A$2:$AZ$100,MATCH($A53-1,$A$2:$A$100,0),5) -> 7413
A54: 2025 | B54: 0 | C54: =ROUND(E53*B54,0) -> 0 | E54: =E53+C54+D54 -> 7635 | F54: =E54 -> 7635 | G54: =B54 -> 0 | H54: =ROUND(I53*$G54,2) -> 0 | I54: =H54+I53 -> 654.68 | J54: =B54 -> 0 | K54: =ROUND(L53*$J54,2) -> 0 | L54: =K54+L53 -> 74.15 | M54: =B54 -> 0 | N54: =ROUND(O53*$M54,2) -> 0 | O54: =N54+O53 -> 80.76 | P54: =B54 -> 0 | Q54: =ROUND(R53*$P54,2) -> 0 | R54: =Q54+R53 -> 368.53 | S54: =ROUND(T53*$B54,2) -> 0 | T54: =S54+T53 -> 333.59 | U54: =ROUND(V53*$B54,2) -> 0 | V54: =U54+V53 -> 62.19 | W54: =ROUND(X53*$B54,2) -> 0 | X54: =W54+X53 -> 68.63 | Y54: =ROUND(Z53*$B54,2) -> 0 | Z54: =Y54+Z53 -> 34.26 | AA54: =ROUND(AB53*$B54,2) -> 0 | AB54: =AA54+AB53 -> 4 | AC54: 0.884 | AD54: =ROUND(AC54*E54,0) -> 6749 | AE54: =AC54 -> 0.884 | AF54: =ROUND(AE54*F54,0) -> 6749 | AG54: 0.79 | AH54: =ROUND(AG54*T54,0) -> 264 | AI54: =AI53 -> 1.01 | AJ54: 5.4 | AK54: 300 | AL54: =E54-AD54-$AP53 -> 733 | AM54: =1-AC54 -> 0.116 | AO54: =ROUND(T54*AG54,0) -> 264 | AP54: =E54-AD54-AL54 -> 153 | AR54: =ROUND(AR53*(1+B54),0) -> 71 | AS54: =INDEX($A$2:$AZ$100,MATCH($A54-1,$A$2:$A$100,0),30) -> 6749 | AT54: =INDEX($A$2:$AZ$100,MATCH($A54-1,$A$2:$A$100,0),5) -> 7635
A55: 2026 | B55: 0 | C55: =ROUND(E54*B55,0) -> 0 | E55: =E54+C55+D55 -> 7635 | F55: =E55 -> 7635 | G55: =B55 -> 0 | H55: =ROUND(I54*$G55,2) -> 0 | I55: =H55+I54 -> 654.68 | J55: =B55 -> 0 | K55: =ROUND(L54*$J55,2) -> 0 | L55: =K55+L54 -> 74.15 | M55: =B55 -> 0 | N55: =ROUND(O54*$M55,2) -> 0 | O55: =N55+O54 -> 80.76 | P55: =B55 -> 0 | Q55: =ROUND(R54*$P55,2) -> 0 | R55: =Q55+R54 -> 368.53 | S55: =ROUND(T54*$B55,2) -> 0 | T55: =S55+T54 -> 333.59 | U55: =ROUND(V54*$B55,2) -> 0 | V55: =U55+V54 -> 62.19 | W55: =ROUND(X54*$B55,2) -> 0 | X55: =W55+X54 -> 68.63 | Y55: =ROUND(Z54*$B55,2) -> 0 | Z55: =Y55+Z54 -> 34.26 | AA55: =ROUND(AB54*$B55,2) -> 0 | AB55: =AA55+AB54 -> 4 | AC55: 0.884 | AD55: =ROUND(AC55*E55,0) -> 6749 | AE55: =AC55 -> 0.884 | AF55: =ROUND(AE55*F55,0) -> 6749 | AG55: 0.79 | AH55: =ROUND(AG55*T55,0) -> 264 | AI55: =AI54 -> 1.01 | AJ55: 5.4 | AK55: 300 | AL55: =E55-AD55-$AP54 -> 733 | AM55: =1-AC55 -> 0.116 | AO55: =ROUND(T55*AG55,0) -> 264 | AP55: =E55-AD55-AL55 -> 153 | AR55: =ROUND(AR54*(1+B55),0) -> 71 | AS55: =INDEX($A$2:$AZ$100,MATCH($A55-1,$A$2:$A$100,0),30) -> 6749 | AT55: =INDEX($A$2:$AZ$100,MATCH($A55-1,$A$2:$A$100,0),5) -> 7635
A56: 2027 | B56: 0 | C56: =ROUND(E55*B56,0) -> 0 | E56: =E55+C56+D56 -> 7635 | F56: =E56 -> 7635 | G56: =B56 -> 0 | H56: =ROUND(I55*$G56,2) -> 0 | I56: =H56+I55 -> 654.68 | J56: =B56 -> 0 | K56: =ROUND(L55*$J56,2) -> 0 | L56: =K56+L55 -> 74.15 | M56: =B56 -> 0 | N56: =ROUND(O55*$M56,2) -> 0 | O56: =N56+O55 -> 80.76 | P56: =B56 -> 0 | Q56: =ROUND(R55*$P56,2) -> 0 | R56: =Q56+R55 -> 368.53 | S56: =ROUND(T55*$B56,2) -> 0 | T56: =S56+T55 -> 333.59 | U56: =ROUND(V55*$B56,2) -> 0 | V56: =U56+V55 -> 62.19 | W56: =ROUND(X55*$B56,2) -> 0 | X56: =W56+X55 -> 68.63 | Y56: =ROUND(Z55*$B56,2) -> 0 | Z56: =Y56+Z55 -> 34.26 | AA56: =ROUND(AB55*$B56,2) -> 0 | AB56: =AA56+AB55 -> 4 | AC56: 0.884 | AD56: =ROUND(AC56*E56,0) -> 6749 | AE56: =AC56 -> 0.884 | AF56: =ROUND(AE56*F56,0) -> 6749 | AG56: 0.79 | AH56: =ROUND(AG56*T56,0) -> 264 | AI56: =AI55 -> 1.01 | AJ56: 5.4 | AK56: 300 | AL56: =E56-AD56-$AP55 -> 733 | AM56: =1-AC56 -> 0.116 | AO56: =ROUND(T56*AG56,0) -> 264 | AP56: =E56-AD56-AL56 -> 153 | AR56: =ROUND(AR55*(1+B56),0) -> 71 | AS56: =INDEX($A$2:$AZ$100,MATCH($A56-1,$A$2:$A$100,0),30) -> 6749 | AT56: =INDEX($A$2:$AZ$100,MATCH($A56-1,$A$2:$A$100,0),5) -> 7635
A57: 2028 | B57: 0 | C57: =ROUND(E56*B57,0) -> 0 | E57: =E56+C57+D57 -> 7635 | F57: =E57 -> 7635 | G57: =B57 -> 0 | H57: =ROUND(I56*$G57,2) -> 0 | I57: =H57+I56 -> 654.68 | J57: =B57 -> 0 | K57: =ROUND(L56*$J57,2) -> 0 | L57: =K57+L56 -> 74.15 | M57: =B57 -> 0 | N57: =ROUND(O56*$M57,2) -> 0 | O57: =N57+O56 -> 80.76 | P57: =B57 -> 0 | Q57: =ROUND(R56*$P57,2) -> 0 | R57: =Q57+R56 -> 368.53 | S57: =ROUND(T56*$B57,2) -> 0 | T57: =S57+T56 -> 333.59 | U57: =ROUND(V56*$B57,2) -> 0 | V57: =U57+V56 -> 62.19 | W57: =ROUND(X56*$B57,2) -> 0 | X57: =W57+X56 -> 68.63 | Y57: =ROUND(Z56*$B57,2) -> 0 | Z57: =Y57+Z56 -> 34.26 | AA57: =ROUND(AB56*$B57,2) -> 0 | AB57: =AA57+AB56 -> 4 | AC57: 0.884 | AD57: =ROUND(AC57*E57,0) -> 6749 | AE57: =AC57 -> 0.884 | AF57: =ROUND(AE57*F57,0) -> 6749 | AG57: 0.79 | AH57: =ROUND(AG57*T57,0) -> 264 | AI57: =AI56 -> 1.01 | AJ57: 5.4 | AK57: 300 | AL57: =E57-AD57-$AP56 -> 733 | AM57: =1-AC57 -> 0.116 | AO57: =ROUND(T57*AG57,0) -> 264 | AP57: =E57-AD57-AL57 -> 153 | AR57: =ROUND(AR56*(1+B57),0) -> 71 | AS57: =INDEX($A$2:$AZ$100,MATCH($A57-1,$A$2:$A$100,0),30) -> 6749 | AT57: =INDEX($A$2:$AZ$100,MATCH($A57-1,$A$2:$A$100,0),5) -> 7635
A58: 2029 | B58: 0 | C58: =ROUND(E57*B58,0) -> 0 | E58: =E57+C58+D58 -> 7635 | F58: =E58 -> 7635 | G58: =B58 -> 0 | H58: =ROUND(I57*$G58,2) -> 0 | I58: =H58+I57 -> 654.68 | J58: =B58 -> 0 | K58: =ROUND(L57*$J58,2) -> 0 | L58: =K58+L57 -> 74.15 | M58: =B58 -> 0 | N58: =ROUND(O57*$M58,2) -> 0 | O58: =N58+O57 -> 80.76 | P58: =B58 -> 0 | Q58: =ROUND(R57*$P58,2) -> 0 | R58: =Q58+R57 -> 368.53 | S58: =ROUND(T57*$B58,2) -> 0 | T58: =S58+T57 -> 333.59 | U58: =ROUND(V57*$B58,2) -> 0 | V58: =U58+V57 -> 62.19 | W58: =ROUND(X57*$B58,2) -> 0 | X58: =W58+X57 -> 68.63 | Y58: =ROUND(Z57*$B58,2) -> 0 | Z58: =Y58+Z57 -> 34.26 | AA58: =ROUND(AB57*$B58,2) -> 0 | AB58: =AA58+AB57 -> 4 | AC58: 0.884 | AD58: =ROUND(AC58*E58,0) -> 6749 | AE58: =AC58 -> 0.884 | AF58: =ROUND(AE58*F58,0) -> 6749 | AG58: 0.79 | AH58: =ROUND(AG58*T58,0) -> 264 | AI58: =AI57 -> 1.01 | AJ58: 5.4 | AK58: 300 | AL58: =E58-AD58-$AP57 -> 733 | AM58: =1-AC58 -> 0.116 | AO58: =ROUND(T58*AG58,0) -> 264 | AP58: =E58-AD58-AL58 -> 153 | AR58: =ROUND(AR57*(1+B58),0) -> 71 | AS58: =INDEX($A$2:$AZ$100,MATCH($A58-1,$A$2:$A$100,0),30) -> 6749 | AT58: =INDEX($A$2:$AZ$100,MATCH($A58-1,$A$2:$A$100,0),5) -> 7635
A59: 2030 | B59: 0 | C59: =ROUND(E58*B59,0) -> 0 | E59: =E58+C59+D59 -> 7635 | F59: =E59 -> 7635 | G59: =B59 -> 0 | H59: =ROUND(I58*$G59,2) -> 0 | I59: =H59+I58 -> 654.68 | J59: =B59 -> 0 | K59: =ROUND(L58*$J59,2) -> 0 | L59: =K59+L58 -> 74.15 | M59: =B59 -> 0 | N59: =ROUND(O58*$M59,2) -> 0 | O59: =N59+O58 -> 80.76 | P59: =B59 -> 0 | Q59: =ROUND(R58*$P59,2) -> 0 | R59: =Q59+R58 -> 368.53 | S59: =ROUND(T58*$B59,2) -> 0 | T59: =S59+T58 -> 333.59 | U59: =ROUND(V58*$B59,2) -> 0 | V59: =U59+V58 -> 62.19 | W59: =ROUND(X58*$B59,2) -> 0 | X59: =W59+X58 -> 68.63 | Y59: =ROUND(Z58*$B59,2) -> 0 | Z59: =Y59+Z58 -> 34.26 | AA59: =ROUND(AB58*$B59,2) -> 0 | AB59: =AA59+AB58 -> 4 | AC59: 0.884 | AD59: =ROUND(AC59*E59,0) -> 6749 | AE59: =AC59 -> 0.884 | AF59: =ROUND(AE59*F59,0) -> 6749 | AG59: 0.79 | AH59: =ROUND(AG59*T59,0) -> 264 | AI59: =AI58 -> 1.01 | AJ59: 5.4 | AK59: 300 | AL59: =E59-AD59-$AP58 -> 733 | AM59: =1-AC59 -> 0.116 | AO59: =ROUND(T59*AG59,0) -> 264 | AP59: =E59-AD59-AL59 -> 153 | AR59: =ROUND(AR58*(1+B59),0) -> 71 | AS59: =INDEX($A$2:$AZ$100,MATCH($A59-1,$A$2:$A$100,0),30) -> 6749 | AT59: =INDEX($A$2:$AZ$100,MATCH($A59-1,$A$2:$A$100,0),5) -> 7635

Sheet fr2223g1to6dst_cep
A1: aea | B1: aea_name | C1: county | D1: Co_Name | E1: district | F1: dstName | G1: Enroll_g1to6 | H1: FRL_g1to6 | I1: %FRL | M1: STILL PRELIMINARY - Jay daid on 12/16/2022 There are still rounding issues.
A2: 07 | B2: Central Rivers AEA | C2: 42 | D2: Hardin | E2: 0009 | F2: AGWSR Comm School District | G2: 253 | H2: 101 | I2: =H2/G2*100 -> 39.920949
A3: 11 | B3: Heartland AEA | C3: 39 | D3: Guthrie | E3: 0018 | F3: Adair-Casey Comm School District | G3: 132 | H3: 68 | I3: =H3/G3*100 -> 51.515152
A4: 11 | B4: Heartland AEA | C4: 25 | D4: Dallas | E4: 0027 | F4: Adel DeSoto Minburn Comm School District | G4: 1022 | H4: 188 | I4: =H4/G4*100 -> 18.395303
A5: 12 | B5: Northwest AEA | C5: 75 | D5: Plymouth | E5: 0063 | F5: Akron Westfield Comm School District | G5: 247 | H5: 98 | I5: =H5/G5*100 -> 39.676113
A6: 05 | B6: Prairie Lakes AEA | C6: 11 | D6: Buena Vista | E6: 0072 | F6: Albert City-Truesdale Comm School District | G6: 81 | H6: 43 | I6: =H6/G6*100 -> 53.08642
A7: 15 | B7: Great Prairie AEA | C7: 68 | D7: Monroe | E7: 0081 | F7: Albia Comm School District | G7: 445 | H7: 191 | I7: =H7/G7*100 -> 42.921348
A8: 10 | B8: Grant Wood AEA | C8: 57 | D8: Linn | E8: 0099 | F8: Alburnett Comm School District | G8: 324 | H8: 75 | I8: =H8/G8*100 -> 23.148148
A9: 07 | B9: Central Rivers AEA | C9: 42 | D9: Hardin | E9: 0108 | F9: Alden Comm School District | G9: 111 | H9: 46 | I9: =H9/G9*100 -> 41.441441
A10: 05 | B10: Prairie Lakes AEA | C10: 55 | D10: Kossuth | E10: 0126 | F10: Algona Comm School District | G10: 597 | H10: 218 | I10: =H10/G10*100 -> 36.515913
A11: 01 | B11: Keystone AEA | C11: 03 | D11: Allamakee | E11: 0135 | F11: Allamakee Comm School District | G11: 410 | H11: 174 | I11: =H11/G11*100 -> 42.439024
A12: 07 | B12: Central Rivers AEA | C12: 12 | D12: Butler | E12: 0153 | F12: North Butler Comm School District | G12: 211 | H12: 63 | I12: =H12/G12*100 -> 29.85782
A13: 05 | B13: Prairie Lakes AEA | C13: 11 | D13: Buena Vista | E13: 0171 | F13: Alta-Aurelia Comm School District | G13: 370 | H13: 164 | I13: =H13/G13*100 -> 44.324324
... A328: 11 | B328: Heartland AEA | C328: 25 | D328: Dallas | E328: 7110 | F328: Woodward-Granger Comm School District | G328: 510 | H328: 114 | I328: =H328/G328*100 -> 22.352941
F329: Total | G329: =SUM(G2:G328) -> 213310 | H329: =SUM(H2:H328) -> 95335 | I329: =H329/G329*100 -> 44.69317
