Workbook

Sheet Sheet1
A1: JE
A2: 10 421 000 0000 000 | B2: Cor from Payable to Due to 61 | C2: 11594.02
A3: 10 402 000 0000 000 | B3: Cor from Payable to Due to 61 | D3: 11594.02 | E3: 1 | I3: Summary JE by GL
A4: 21 401 011 0000 000 | B4: Void Fundraiser Due to tran - No supporting doc | D4: 814717.44 | E4: 2 | I4: Fund | J4: Ledger Cat. | K4: Acct. Des | L4: GL # | M4: DR | N4: CR | O4: DR/(CR)
A5: 21 0000 1791 920 6601 | B5: Void Fundraiser Due to tran - No supporting doc | C5: 814717.44 | I5: {=LEFT(_xlfn.ANCHORARRAY(L5),2)} -> 10 | J5: EXP | K5: =VLOOKUP(L5,Sheet2!A:B,2,FALSE) -> MISC EXPENDITURES | L5: {=_xlfn._xlws.SORT(_xlfn.UNIQUE(A2:A123))} -> 10 0000 1100 100 0000 892 | M5: {=SUMIF($A:$A,_xlfn.ANCHORARRAY($L$5),C:C)} -> 1604 | N5: {=SUMIF($A:$A,_xlfn.ANCHORARRAY($L$5),D:D)} -> 0 | O5: =M5-N5 -> 1604
A6: 10 131 000 0000 000 | B6: Void CAR Corr 3 | C6: 357.86 | E6: 3 | I6: 10 | J6: REV | K6: =VLOOKUP(L6,Sheet2!A:B,2,FALSE) -> MISC REVENUE | L6: 10 0000 1991 000 0000 | M6: 738.76 | N6: 0 | O6: =M6-N6 -> 738.76
A7: 10 0000 2327 000 0000 611 | B7: Void CAR Corr 3 | D7: 357.86 | I7: 10 | J7: EXP | K7: =VLOOKUP(L7,Sheet2!A:B,2,FALSE) -> CENTRAL OFFICE OFFICE SUPPLIES | L7: 10 0000 2327 000 0000 611 | M7: 0 | N7: 357.86 | O7: =M7-N7 -> -357.86
A8: 10 421 000 0000 000 | B8: Cor from Payable to Due to 61 | C8: 13049.51 | I8: 10 | J8: EXP | K8: =VLOOKUP(L8,Sheet2!A:B,2,FALSE) -> SUPPLIES/OFFICE | L8: 10 0000 2610 000 0000 611 | M8: 0 | N8: 80239.68 | O8: =M8-N8 -> -80239.68
A9: 10 402 000 0000 000 | B9: Cor from Payable to Due to 61 | D9: =C8 -> 13049.51 | E9: 5 | I9: 10 | J9: EXP | K9: =VLOOKUP(L9,Sheet2!A:B,2,FALSE) -> CITY FURNITURE/EQUIPMENT | L9: 10 0109 1100 100 0000 739 | M9: 0 | N9: 24088 | O9: =M9-N9 -> -24088
A10: 10 131 000 0000 000 | B10: Correct December Mastercard | C10: 75337.65 | E10: 6 | I10: 10 | J10: Interfund | K10: =VLOOKUP(L10,Sheet2!A:B,2,FALSE) -> INTERFUND LOANS RECEIVABLE | L10: 10 131 000 0000 000 | M10: 189943.6 | N10: 1604 | O10: =M10-N10 -> 188339.6
A11: 10 421 000 0000 000 | B11: Correct December Mastercard | D11: 75337.65 | I11: 10 | J11: Interfund | K11: =VLOOKUP(L11,Sheet2!A:B,2,FALSE) -> INTERFUND ACCOUNTS RECEIVABLE | L11: 10 132 000 0000 000 | M11: 104327.68 | N11: 0 | O11: =M11-N11 -> 104327.68
A12: 10 421 000 0000 000 | B12: Correct January 2024 Nutrition | C12: 7347.56 | I12: 10 | J12: Receivable | K12: =VLOOKUP(L12,Sheet2!A:B,2,FALSE) -> OTHER ACCTS RECV | L12: 10 153 000 0000 000 | M12: 0 | N12: 206.03 | O12: =M12-N12 -> -206.03
A13: 10 402 000 0000 000 | B13: Correct January 2024 Nutrition | D13: =C12 -> 7347.56 | E13: 8 | I13: 10 | J13: Interfund | K13: =VLOOKUP(L13,Sheet2!A:B,2,FALSE) -> INTERFUND ACCOUNTS PAYABLE | L13: 10 402 000 0000 000 | M13: 0 | N13: 32729.85 | O13: =M13-N13 -> -32729.85
A14: 61 401 011 0000 000 | B14: Void 1/20 Food for speech contest | I14: 10 | J14: Payable | K14: =VLOOKUP(L14,Sheet2!A:B,2,FALSE) -> ACCOUNTS PAYABLE | L14: 10 421 000 0000 000 | M14: 31991.09 | N14: 189379.71 | O14: =M14-N14 -> -157388.62
A15: 61 0000 3110 000 0000 631 | B15: Void 1/20 Food for speech contest | I15: 21 | J15: REV | K15: =VLOOKUP(L15,Sheet2!A:B,2,FALSE) -> DISTRICTWIDE ATHLETICS ALL SPORTS FUND RAISERS | L15: 21 0000 1791 920 6601 | M15: 814717.44 | N15: 0 | O15: =M15-N15 -> 814717.44
A16: 61 401 011 0000 000 | B16: Correct Food for Speech Contest | I16: 21 | J16: EXP | K16: =VLOOKUP(L16,Sheet2!A:B,2,FALSE) -> WHS ATHLETICS-ALL SPORTS SUPPLIES/OFFICE | L16: 21 0118 1900 923 6601 611 | M16: 0 | N16: 1040 | O16: =M16-N16 -> -1040
A17: 61 0000 3110 000 0000 631 | B17: Correct Food for Speech Contest | I17: 21 | J17: Interfund | K17: =VLOOKUP(L17,Sheet2!A:B,2,FALSE) -> INTERFUND LOANS RECEIVABLE | L17: 21 132 000 0000 000 | M17: 1040 | N17: 0 | O17: =M17-N17 -> 1040
A18: 61 401 011 0000 000 | B18: Void:Box Lunches - ESC | C18: 217.6 | D18: 0 | E18: 12 | I18: 21 | J18: Interfund | K18: =VLOOKUP(L18,Sheet2!A:B,2,FALSE) -> INTERFUND PAYABLE 11 | L18: 21 401 011 0000 000 | M18: 0 | N18: 814717.44 | O18: =M18-N18 -> -814717.44
A19: 61 0000 3110 000 0000 631 | B19: Void:Box Lunches - ESC | C19: 0 | D19: 217.6 | I19: 33 | J19: Interfund | K19: =VLOOKUP(L19,Sheet2!A:B,2,FALSE) -> INTERFUND LOANS PAYABLE | L19: 33 401 000 0000 000 | M19: 946.1 | N19: 0 | O19: =M19-N19 -> 946.1
A20: 61 401 011 0000 000 | B20: Void:CLP Lunches | C20: 154.55 | D20: 0 | E20: 12 | I20: 33 | J20: Payable | K20: =VLOOKUP(L20,Sheet2!A:B,2,FALSE) -> ACCOUNTS PAYABLE | L20: 33 421 000 0000 000 | M20: 0 | N20: 946.1 | O20: =M20-N20 -> -946.1
A21: 61 0000 3110 000 0000 631 | B21: Void:CLP Lunches | C21: 0 | D21: 154.55 | I21: 61 | J21: EXP | K21: =VLOOKUP(L21,Sheet2!A:B,2,FALSE) -> FOOD | L21: 61 0000 3110 000 0000 631 | M21: 0 | N21: 3554.38 | O21: =M21-N21 -> -3554.38
A22: 61 401 011 0000 000 | B22: Void:Coffee Supplies - ESC | C22: 191.05 | D22: 0 | E22: 12 | I22: 61 | J22: Interfund | K22: =VLOOKUP(L22,Sheet2!A:B,2,FALSE) -> INTERFUND LOANS RECEIVABLE | L22: 61 131 000 0000 000 | M22: 79.9 | N22: 0 | O22: =M22-N22 -> 79.9
A23: 61 0000 3110 000 0000 631 | B23: Void:Coffee Supplies - ESC | C23: 0 | D23: 191.05 | I23: 61 | J23: Receivable | K23: =VLOOKUP(L23,Sheet2!A:B,2,FALSE) -> STATE AID RECEIVABLE | L23: 61 141 000 0000 000 | M23: 0 | N23: 79.9 | O23: =M23-N23 -> -79.9
A24: 61 401 011 0000 000 | B24: Void:Cookies | C24: 97.5 | D24: 0 | E24: 12 | I24: 61 | J24: Deferred Outflow | K24: =VLOOKUP(L24,Sheet2!A:B,2,FALSE) -> DEFERRED OUTFLOWS-ASSUMPTIONS | L24: 61 322 000 0000 000 | M24: 0 | N24: 241711 | O24: =M24-N24 -> -241711
A25: 61 0000 3110 000 0000 631 | B25: Void:Cookies | C25: 0 | D25: 97.5 | I25: 61 | J25: Interfund | K25: =VLOOKUP(L25,Sheet2!A:B,2,FALSE) -> INTERFUND LOANS PAYABLE | L25: 61 401 000 0000 000 | M25: 0 | N25: 2139.09 | O25: =M25-N25 -> -2139.09
A26: 61 401 011 0000 000 | B26: Void:Cookies - Teacher Meeting | C26: 53.95 | D26: 0 | E26: 12 | I26: 61 | J26: Interfund | K26: =VLOOKUP(L26,Sheet2!A:B,2,FALSE) -> PAYABLE: FUND 11 | L26: 61 401 011 0000 000 | M26: 245265.38 | N26: 0 | O26: =M26-N26 -> 245265.38
A27: 61 401 011 0000 000 | B27: Void:Cookies - Teacher Meeting | C27: 159.9 | D27: 0 | E27: 12 | I27: 61 | J27: Payable | K27: =VLOOKUP(L27,Sheet2!A:B,2,FALSE) -> PAYROLL DED & WITHHOLDINGS | L27: 61 471 013 0000 000 | M27: 2139.09 | N27: 0 | O27: =M27-N27 -> 2139.09
A28: 61 0000 3110 000 0000 631 | B28: Void:Cookies - Teacher Meeting | C28: 0 | D28: 159.9 | I28: 71 | J28: REV | K28: =VLOOKUP(L28,Sheet2!A:B,2,FALSE) -> Added by Prev Year Adjustments | L28: 71 0000 1970 000 0000 | M28: 0 | N28: 2105471.2 | O28: =M28-N28 -> -2105471.2
A29: 61 0000 3110 000 0000 631 | B29: Void:Cookies - Teacher Meeting | C29: 0 | D29: 53.95 | I29: 71 | J29: REV | K29: =VLOOKUP(L29,Sheet2!A:B,2,FALSE) -> EMPLOYER CONTRIBUT'N | L29: 71 0000 1997 000 0000 | M29: 0 | N29: 6273988.1 | O29: =M29-N29 -> -6273988.1
A30: 61 401 011 0000 000 | B30: Void:Crackers - Health Services | C30: 50.02 | D30: 0 | E30: 12 | I30: 71 | J30: Interfund | K30: =VLOOKUP(L30,Sheet2!A:B,2,FALSE) -> Premiums Receivable | L30: 71 132 000 0000 000 | M30: 8379459.4 | N30: 0 | O30: =M30-N30 -> 8379459.4
A31: 61 401 011 0000 000 | B31: Void:Crackers - Health Services | C31: 50.04 | D31: 0 | E31: 12 | I31: 74 | J31: REV | K31: =VLOOKUP(L31,Sheet2!A:B,2,FALSE) -> EMPLOYEE CONTRIBUT'N | L31: 74 0000 1970 000 0000 | M31: 0 | N31: 257357.23 | O31: =M31-N31 -> -257357.23
A32: 61 401 011 0000 000 | B32: Void:Crackers - Health Services | C32: 50.04 | D32: 0 | E32: 12 | I32: 74 | J32: REV | K32: =VLOOKUP(L32,Sheet2!A:B,2,FALSE) -> EMPLOYER CONTRIBUT'N | L32: 74 0000 1997 000 0000 | M32: 0 | N32: 237683.56 | O32: =M32-N32 -> -237683.56
A33: 61 0000 3110 000 0000 631 | B33: Void:Crackers - Health Services | C33: 0 | D33: 50.04 | I33: 74 | J33: Interfund | K33: =VLOOKUP(L33,Sheet2!A:B,2,FALSE) -> Premiums Receivable | L33: 74 132 000 0000 000 | M33: 495040.79 | N33: 0 | O33: =M33-N33 -> 495040.79
A34: 61 0000 3110 000 0000 631 | B34: Void:Crackers - Health Services | C34: 0 | D34: 50.04
A35: 61 0000 3110 000 0000 631 | B35: Void:Crackers - Health Services | C35: 0 | D35: 50.02 | I35: Net DR/(CR) by fund and account type.
A36: 61 401 011 0000 000 | B36: Void:Kindergarten Camp Snack - Lemme | C36: 87.5 | D36: 0 | E36: 12 | J36: {=TRANSPOSE(_xlfn._xlws.SORT(_xlfn.UNIQUE(_xlfn.ANCHORARRAY(I5))))} -> 10 | K36: 21 | L36: 33 | M36: 61 | N36: 71 | O36: 74
A37: 61 0000 3110 000 0000 631 | B37: Void:Kindergarten Camp Snack - Lemme | C37: 0 | D37: 87.5 | I37: {=_xlfn.UNIQUE(J5:J33)} -> EXP | J37: {=SUMIFS(O5:O33,_xlfn.ANCHORARRAY(I5),_xlfn.ANCHORARRAY(J36),J5:J33,_xlfn.ANCHORARRAY(I37))} -> -103081.54 | K37: -1040 | L37: 0 | M37: -3554.38 | N37: 0 | O37: 0
A38: 61 401 011 0000 000 | B38: Void:Legislative Forum - ESC | C38: 31.52 | D38: 0 | E38: 12 | I38: REV | J38: 738.76 | K38: 814717.44 | L38: 0 | M38: 0 | N38: -8379459.4 | O38: -495040.79
A39: 61 0000 3110 000 0000 631 | B39: Void:Legislative Forum - ESC | C39: 0 | D39: 31.52 | I39: Interfund | J39: 259937.43 | K39: -813677.44 | L39: 946.1 | M39: 243206.19 | N39: 8379459.4 | O39: 495040.79
A40: 61 401 011 0000 000 | B40: Void:Plates/ Spoons - ESC | C40: 107.82 | D40: 0 | E40: 12 | I40: Receivable | J40: -206.03 | K40: 0 | L40: 0 | M40: -79.9 | N40: 0 | O40: 0
A41: 61 0000 3110 000 0000 631 | B41: Void:Plates/ Spoons - ESC | C41: 0 | D41: 107.82 | I41: Payable | J41: -157388.62 | K41: 0 | L41: -946.1 | M41: 2139.09 | N41: 0 | O41: 0
A42: 61 401 011 0000 000 | B42: Void:Uncrustables - Special Ed | C42: 122.2 | D42: 0 | E42: 12 | I42: Deferred Outflow | J42: 0 | K42: 0 | L42: 0 | M42: -241711 | N42: 0 | O42: 0
A43: 61 0000 3110 000 0000 631 | B43: Void:Uncrustables - Special Ed | C43: 0 | D43: 122.2
A44: 61 401 011 0000 000 | B44: Cor:Box Lunches - ESC | C44: 217.6 | D44: 0 | E44: 12
A45: 61 0000 3110 000 0000 631 | B45: Cor:Box Lunches - ESC | C45: 0 | D45: 217.6
A46: 61 401 011 0000 000 | B46: Cor:CLP Lunches | C46: 154.55 | D46: 0 | E46: 12
A47: 61 0000 3110 000 0000 631 | B47: Cor:CLP Lunches | C47: 0 | D47: 154.55
A48: 61 401 011 0000 000 | B48: Cor:Coffee Supplies - ESC | C48: 191.05 | D48: 0 | E48: 12
A49: 61 0000 3110 000 0000 631 | B49: Cor:Coffee Supplies - ESC | C49: 0 | D49: 191.05
A50: 61 401 011 0000 000 | B50: Cor:Cookies | C50: 97.5 | D50: 0 | E50: 12
A51: 61 0000 3110 000 0000 631 | B51: Cor:Cookies | C51: 0 | D51: 97.5
A52: 61 401 011 0000 000 | B52: Cor:Cookies - Teacher Meeting | C52: 53.95 | D52: 0 | E52: 12
A53: 61 401 011 0000 000 | B53: Cor:Cookies - Teacher Meeting | C53: 159.9 | D53: 0 | E53: 12
A54: 61 0000 3110 000 0000 631 | B54: Cor:Cookies - Teacher Meeting | C54: 0 | D54: 159.9
A55: 61 0000 3110 000 0000 631 | B55: Cor:Cookies - Teacher Meeting | C55: 0 | D55: 53.95
A56: 61 401 011 0000 000 | B56: Cor:Crackers - Health Services | C56: 50.02 | D56: 0 | E56: 12
A57: 61 401 011 0000 000 | B57: Cor:Crackers - Health Services | C57: 50.04 | D57: 0 | E57: 12
A58: 61 401 011 0000 000 | B58: Cor:Crackers - Health Services | C58: 50.04 | D58: 0 | E58: 12
A59: 61 0000 3110 000 0000 631 | B59: Cor:Crackers - Health Services | C59: 0 | D59: 50.04
A60: 61 0000 3110 000 0000 631 | B60: Cor:Crackers - Health Services | C60: 0 | D60: 50.04
A61: 61 0000 3110 000 0000 631 | B61: Cor:Crackers - Health Services | C61: 0 | D61: 50.02
A62: 61 401 011 0000 000 | B62: Cor:Kindergarten Camp Snack - Lemme | C62: 87.5 | D62: 0 | E62: 12
A63: 61 0000 3110 000 0000 631 | B63: Cor:Kindergarten Camp Snack - Lemme | C63: 0 | D63: 87.5
A64: 61 401 011 0000 000 | B64: Cor:Legislative Forum - ESC | C64: 31.52 | D64: 0 | E64: 12
A65: 61 0000 3110 000 0000 631 | B65: Cor:Legislative Forum - ESC | C65: 0 | D65: 31.52
A66: 61 401 011 0000 000 | B66: Cor:Plates/ Spoons - ESC | C66: 107.82 | D66: 0 | E66: 12
A67: 61 0000 3110 000 0000 631 | B67: Cor:Plates/ Spoons - ESC | C67: 0 | D67: 107.82
A68: 61 401 011 0000 000 | B68: Cor:Uncrustables - Special Ed | C68: 122.2 | D68: 0 | E68: 12
A69: 61 0000 3110 000 0000 631 | B69: Cor:Uncrustables - Special Ed | C69: 0 | D69: 122.2
A70: 10 421 000 0000 000 | B70: Correct Mastercard - May 24 | D70: 32.53
A71: 10 131 000 0000 000 | B71: Correct Mastercard - May 24 | C71: 32.53 | E71: 14
A72: 33 421 000 0000 000 | B72: Reclass Apple (10/18) | D72: 165.38
A73: 33 421 000 0000 000 | B73: Reclass Apple (10/18) | D73: 49.99
A74: 33 421 000 0000 000 | B74: Reclass Apple (10/20) | D74: 49.99
A75: 33 421 000 0000 000 | B75: Reclass Apple (10/25) | D75: 49.99
A76: 33 421 000 0000 000 | B76: Reclass Apple-Prentke Romich Co (10/30) | D76: 299.99
A77: 33 421 000 0000 000 | B77: Reclass Apple (10/20) | D77: 165.38
A78: 33 421 000 0000 000 | B78: Reclass Apple (10/25) | D78: 165.38
A79: 33 401 000 0000 000 | B79: Reclass Apple (10/18) | C79: 165.38 | E79: 17
A80: 33 401 000 0000 000 | B80: Reclass Apple (10/18) | C80: 49.99 | E80: 17
A81: 33 401 000 0000 000 | B81: Reclass Apple (10/20) | C81: 49.99 | E81: 17
A82: 33 401 000 0000 000 | B82: Reclass Apple (10/25) | C82: 49.99 | E82: 17
A83: 33 401 000 0000 000 | B83: Reclass Apple-Prentke Romich Co (10/30) | C83: 299.99 | E83: 17
A84: 33 401 000 0000 000 | B84: Reclass Apple (10/20) | C84: 165.38 | E84: 17
A85: 33 401 000 0000 000 | B85: Reclass Apple (10/25) | C85: 165.38 | E85: 17
A86: 10 153 000 0000 000 | B86: Correct Sept Mastercard | D86: 206.03
A87: 10 131 000 0000 000 | B87: Correct Sept Mastercard | C87: =D86 -> 206.03 | E87: 18
A88: 61 141 000 0000 000 | B88: Void Processing Fee Correction FS | D88: 39.95
A89: 61 141 000 0000 000 | B89: Processing Fee fs | D89: 39.95
A90: 61 131 000 0000 000 | B90: Void Processing Fee Correction FS | C90: 39.95 | E90: 7
A91: 61 131 000 0000 000 | B91: Processing Fee fs | C91: 39.95 | E91: 7
A92: 10 131 000 0000 000 | B92: Correct BMO - June | C92: 49639.88 | E92: 10
A93: 10 421 000 0000 000 | B93: Correct BMO - June | D93: =C92 -> 49639.88
A94: 10 131 000 0000 000 | B94: Correct Jan BMO | C94: 64369.65 | E94: 9
A95: 10 421 000 0000 000 | B95: Correct Jan BMO | D95: 64369.65
A96: 61 401 011 0000 000 | B96: void: 1/20 Food for speech contest | C96: 403.5 | E96: 11
A97: 61 0000 3110 000 0000 631 | B97: void: 1/20 Food for speech contest | D97: =C96 -> 403.5
A98: 61 401 011 0000 000 | B98: COR:1/20 Food for speech contest | C98: =D97 -> 403.5 | E98: 11
A99: 61 0000 3110 000 0000 631 | B99: COR:1/20 Food for speech contest | D99: =C98 -> 403.5
A100: 61 322 000 0000 000 | B100: Cor Nutrition Payroll | D100: =C101 -> 241711
...

Sheet Sheet2
A1: IOWA CITY COMMUNITY SCHOOL DISTRICT | B1: Chart of Accounts Listing | C1: Page: 1
A2: 46093.339 | C2: User ID: 16824
A3: Fund: | B3: 1 | C3: GOVERNMENTAL ACTIVITIES FUND
A4: Chart of Account Number | B4: Chart of Account Description | C4: Active | D4: Account Type ID | E4: Yearly Post Account
A5: 01 101 000 0000 000 | B5: CASH IN BANK | C5: X | D5: 1
A6: 01 282 000 0000 000 | B6: ACCUM DEPR INTANGIBLE ASSETS | C6: X | D6: 1
A7: 01 301 000 0000 000 | B7: ESTIMATED REVENUES | C7: X | D7: 3
A8: 01 302 000 0000 000 | B8: LESS:REVENUE RECEIVED | C8: X | D8: 3
A9: 01 421 000 0000 000 | B9: ACCOUNTS PAYABLE | C9: X | D9: 4
A10: 01 601 000 0000 000 | B10: BUDGETED EXPENDITURES | C10: X | D10: 6
A11: 01 602 000 0000 000 | B11: LESS: EXPENDITURES TO DATE | C11: X | D11: 6
A12: 01 759 000 0000 000 | B12: UNRESERVED FUND BALANCE | C12: X | D12: 7
A13: 01 771 000 0000 000 | B13: BUDGETED FUND BALANCE | C13: X | D13: 7
A14: 01 0000 2581 000 0000 790 | B14: DEPRECIATION | C14: X | D14: 9 | E14: 01 759 000 0000 000
A15: Fund: | B15: 8 | C15: GOVERNMENTAL LONG-TERM ASSETS
A16: Chart of Account Number | B16: Chart of Account Description | C16: Active | D16: Account Type ID | E16: Yearly Post Account
A17: 08 101 000 0000 000 | B17: CASH IN BANK UNUSED | D17: 1
A18: 08 211 000 0000 000 | B18: LAND AND LAND IMPROVEMENTS UNUSED | C18: X | D18: 2
A19: 08 221 000 0000 000 | B19: SITE IMPROVEMENTS | C19: X | D19: 2
A20: 08 222 000 0000 000 | B20: ACC DEPRECIATION ON SITE IMP | C20: X | D20: 2
A21: 08 231 000 0000 000 | B21: BUILDINGS & IMPROVEMENTS | C21: X | D21: 2
A22: 08 232 000 0000 000 | B22: ACC DEPR ON BLDGS & IMPROVE | C22: X | D22: 2
A23: 08 241 000 0000 000 | B23: MACHINERY & EQUIPMENT | C23: X | D23: 2
A24: 08 242 000 0000 000 | B24: ACC DEPR ON MACHINERY & EQUIP | C24: X | D24: 2
A25: 08 271 000 0000 000 | B25: CONSTRUCTION IN PROGRESS | C25: X | D25: 2
A26: 08 291 000 0000 000 | B26: SUBSCRIPTION ASSET | C26: X | D26: 2
A27: 08 301 000 0000 000 | B27: ESTIMATED REVENUES UNUSED | D27: 3
A28: 08 302 000 0000 000 | B28: LESS:REVENUE RECEIVED UNUSED | D28: 3
A29: 08 421 000 0000 000 | B29: ACCOUNTS PAYABLE UNUSED | D29: 4
A30: 08 605 000 0000 000 | B30: LESS:OUTSTANDING A/P UNUSED | D30: 4
A31: 08 601 000 0000 000 | B31: BUDGETED EXPENDITURES UNUSED | D31: 6
A32: 08 602 000 0000 000 | B32: LESS: EXPENDITURES TO DATE UNUSED | D32: 6
A33: 08 603 000 0000 000 | B33: ENCUMBRANCES UNUSED | D33: 6
A34: 08 604 000 0000 000 | B34: LESS: ENCUMBRANCE COMMITMENTS UNUSED | D34: 6
A35: 08 610 000 0000 000 | B35: INVESTMENT IN FIXED ASSETS (PRE DEPR) U | C35: X | D35: 6
A36: 08 740 000 0000 000 | B36: UNRESERVED-RETAINED EARNINGS | C36: X | D36: 7
A37: 08 770 000 0000 000 | B37: UNRESERVED-FUND BALANCE UNUSED | D37: 7
A38: 08 771 000 0000 000 | B38: BUDGETED FUND BALANCE UNUSED | D38: 7
A39: 08 0000 4700 000 0000 790 | B39: DEPRECIATION | C39: X | D39: 9 | E39: 08 740 000 0000 000
A40: 08 0000 4700 000 4045 450 | B40: ARP ESSER CONSTRUCTION SERVICES | C40: X | D40: 9 | E40: 08 610 000 0000 000
A41: Fund: | B41: 9 | C41: LONG-TERM LIABILITIES
A42: Chart of Account Number | B42: Chart of Account Description | C42: Active | D42: Account Type ID | E42: Yearly Post Account
A43: 09 101 000 0000 000 | B43: CASH IN BANK UNUSED | D43: 1
A44: 09 301 000 0000 000 | B44: ESTIMATED REVENUES UNUSED | D44: 3
A45: 09 302 000 0000 000 | B45: LESS:REVENUE RECEIVED UNUSED | D45: 3
A46: 09 303 000 0000 000 | B46: AMOUNT AVAIL IN DEBT SERV FUND | C46: X | D46: 3
A47: 09 304 000 0000 000 | B47: AMT PROVIDED FOR LONG-TERM DBT | C47: X | D47: 3.5
A48: 09 421 000 0000 000 | B48: ACCOUNTS PAYABLE UNUSED | D48: 4
A49: IOWA CITY COMMUNITY SCHOOL DISTRICT | B49: Chart of Accounts Listing | C49: Page: 2
A50: 46093.339 | C50: User ID: 16824
A51: Fund: | B51: 9 | C51: LONG-TERM LIABILITIES
A52: Chart of Account Number | B52: Chart of Account Description | C52: Active | D52: Account Type ID | E52: Yearly Post Account
A53: 09 605 000 0000 000 | B53: LESS:OUTSTANDING A/P UNUSED | D53: 4
A54: 09 511 000 0000 000 | B54: BONDS PAYABLE | C54: X | D54: 5
A55: 09 531 000 0000 000 | B55: CAPITAL LEASE OBLIGATIONS | C55: X | D55: 5
A56: 09 551 000 0000 000 | B56: COMPENSATED ABSENCES | C56: X | D56: 5
A57: 09 593 000 0000 000 | B57: NET PENSION LIABILITY | C57: X | D57: 5
A58: 09 601 000 0000 000 | B58: BUDGETED EXPENDITURES UNUSED | D58: 6
A59: 09 602 000 0000 000 | B59: LESS: EXPENDITURES TO DATE UNUSED | D59: 6
A60: 09 603 000 0000 000 | B60: ENCUMBRANCES UNUSED | D60: 6
A61: 09 604 000 0000 000 | B61: LESS: ENCUMBRANCE COMMITMENTS UNUSED | D61: 6
A62: 09 770 000 0000 000 | B62: UNRESERVED-FUND BALANCE UNUSED | D62: 7
A63: 09 771 000 0000 000 | B63: BUDGETED FUND BALANCE UNUSED | D63: 7
A64: Fund: | B64: 10 | C64: OPERATING FUND
A65: Chart of Account Number | B65: Chart of Account Description | C65: Active | D65: Account Type ID | E65: Yearly Post Account
A66: 10 101 000 0000 000 | B66: CASH IN BANK | C66: X | D66: 1
A67: 10 101 001 0000 000 | B67: CASH IN BANK-PAYROLL | C67: X | D67: 1
A68: 10 103 000 0000 000 | B68: PETTY CASH | C68: X | D68: 1
A69: 10 111 000 0000 000 | B69: INVESTMENTS | C69: X | D69: 1
A70: 10 121 000 0000 000 | B70: TAXES RECEIVABLE | C70: X | D70: 1
A71: 10 123 000 0000 000 | B71: SUCCEEDING YEAR TAX RECEIVABLE | C71: X | D71: 1
A72: 10 131 000 0000 000 | B72: INTERFUND LOANS RECEIVABLE | C72: X | D72: 1
A73: 10 131 012 0000 000 | B73: RECEIVABLE FUND 12 | C73: X | D73: 1
A74: 10 131 032 0000 000 | B74: RECEIVABLE:FUND 32 | D74: 1
A75: 10 131 033 0000 000 | B75: RECEIVABLE:FUND 33 | D75: 1
A76: 10 131 041 0000 000 | B76: RECEIVABLE:FUND 41 | D76: 1
A77: 10 131 042 0000 000 | B77: RECEIVABLE:FUND 42 | D77: 1
A78: 10 131 043 0000 000 | B78: RECEIVABLE:FUND 43 | D78: 1
A79: 10 131 048 0000 000 | B79: RECEIVABLE:FUND 48 | D79: 1
A80: 10 132 000 0000 000 | B80: INTERFUND ACCOUNTS RECEIVABLE | C80: X | D80: 1
A81: 10 141 000 0000 000 | B81: INTERGOV'T ACCOUNTS RECEIVABLE | C81: X | D81: 1
A82: 10 141 000 3261 300 | B82: Intergov't Accounts receivable | C82: X | D82: 1
A83: 10 141 000 3321 218 | B83: INTERGOV'T ACCOUNTS RECEIVABLE | C83: X | D83: 1
A84: 10 141 000 4034 000 | B84: INTERGOV'T ACCOUNTS RECEIVABLE | C84: X | D84: 1
A85: 10 141 000 4043 000 | B85: INTERGOV'T ACCOUNTS RECEIVABLE | C85: X | D85: 1
A86: 10 141 000 4045 000 | B86: INTERGOV'T ACCOUNTS RECEIVABLE | C86: X | D86: 1
A87: 10 141 000 4054 000 | B87: INTERGOV'T ACCOUNTS RECEIVABLE | C87: X | D87: 1
A88: 10 141 000 4598 000 | B88: INTERGOV'T ACCOUNTS RECEIVABLE | C88: X | D88: 1
A89: 10 141 000 4634 218 | B89: INTERGOV'T ACCOUNTS RECEIVABLE | C89: X | D89: 1
A90: 10 141 000 4644 412 | B90: INTERGOV'T ACCOUNTS RECEIVABLE | C90: X | D90: 1
A91: 10 141 000 4669 000 | B91: INTERGOV'T ACCOUNTS RECEIVABLE | C91: X | D91: 1
A92: 10 142 000 0000 000 | B92: STATE AID RECEIVABLE | D92: 1
A93: 10 143 000 0000 000 | B93: MOBILE HOME TAX RECEIVABLE | C93: X | D93: 1
A94: 10 144 000 0000 000 | B94: INCOME SURTAX RECEIVABLE | C94: X | D94: 1
A95: 10 153 000 0000 000 | B95: OTHER ACCTS RECV | C95: X | D95: 1
A96: 10 153 000 9992 000 | B96: CIRCLE SCHOOL ACCT RECEIVABLE | D96: 1
A97: 10 153 000 9994 000 | B97: MUSIC AUX ACCT REC | D97: 1
A98: 10 153 000 9995 000 | B98: ICCSD FOUNDATION - ACCT RECEIVABLE | D98: 1
A99: 10 171 000 0000 000 | B99: INVENTORIES | C99: X | D99: 1
A100: 10 181 000 0000 000 | B100: PREPAID EXPENSES | C100: X | D100: 1
...
